Workbook
Name \0: #REF!
Name \0: #REF!
Name \a: #REF!
Name \a: #REF!
Name \b: #REF!
Name \c: #REF!
Name \d: #REF!
Name \e: #REF!
Name \f: #REF!
Name \g: #REF!
Name \h: #REF!
Name \i: #REF!
Name \j: #REF!
Name \k: #REF!
Name \l: #REF!
Name \m: #REF!
Name \s: #REF!
Name \u: #REF!
Name \z: #REF!
Name ____ABS93: #REF!
Name ____ABS94: #REF!
Name ____ABS95: #REF!
Name ____ABS96: #REF!
Name ____ABS97: #REF!
Name ____DEP93: #REF!
Name ____DEP94: #REF!
Name ____DEP95: #REF!
Name ____DEP96: #REF!
Name ____DEP97: #REF!
Name ____DPS93: #REF!
Name ____DPS94: #REF!
Name ____DPS95: #REF!
Name ____DPS96: #REF!
Name ____DPS97: #REF!
Name ___ABS93: #REF!
Name ___ABS94: #REF!
Name ___ABS95: #REF!
Name ___ABS96: #REF!
Name ___ABS97: #REF!
Name ___DEP93: #REF!
Name ___DEP94: #REF!
Name ___DEP95: #REF!
Name ___DEP96: #REF!
Name ___DEP97: #REF!
Name ___DPS93: #REF!
Name ___DPS94: #REF!
Name ___DPS95: #REF!
Name ___DPS96: #REF!
Name ___DPS97: #REF!
Name __ABS93: #REF!
Name __ABS94: #REF!
Name __ABS95: #REF!
Name __ABS96: #REF!
Name __ABS97: #REF!
Name __DBS50: #REF!
Name __DBS50: #REF!
Name __DEP93: #REF!
Name __DEP93: #REF!
Name __DEP94: #REF!
Name __DEP94: #REF!

Sheet Coversheet
C2: GOLDMAN SACHS
C3: GLOBAL INVESTMENT RESEARCH
C4: Consumers Team
B6: 605499.SS
B7: Eastroc Beverage
C8: Rating | H8: Buy | K8: RATING | L8: Buy
C9: Target price | H9: 350 | K9: TARGET_PRICE | L9: 350
C10: M&A probability | H10: 3 | K10: MA_PROB | L10: 3
C11: Market Cap (US$ mn), price as of | F11: 45979 | H11: 18775.432 | K11: CAPI | L11: 18775.432
C12: Current shares outstanding (mn) | H12: 520.013 | K12: NUM_SH1 | L12: 520.013
C13: Currency | H13: CNY | K13: PRICE_CURRENCY_ISO | L13: CNY
C14: Valuation Methodology | H14: P/E
C15: Current Publication Date | H15: 45979 | K15: TARGET_PRICE_CHANGE_DATE | L15: 8-Oct-2025
C16: Previous Publication Date | H16: 16-Oct-2025
B17: Team Contacts
B18: Primary analyst
B19: Leaf Liu, Leaf.Liu@gs.com, +852-3966-4169, Goldman Sachs (Asia) L.L.C.
B20: Associated analyst
B21: Christina Liu, Christina.Liu@gs.com, +852-2978-6983, Goldman Sachs (Asia) L.L.C.

Sheet Summary financial
A1: Eastroc Beverage (605499.SS)
A2: Rmb millions
A3: Divisional P/L | B3: FY17 | C3: FY18 | D3: FY19 | E3: FY20 | F3: FY21 | G3: FY22 | H3: FY23 | I3: FY24 | J3: FY25E | K3: FY26E | L3: FY27E | M3: FY28E | O3: 18-23 5yr CAGR | P3: 23-28 5yr CAGR | Q3: 21-23 2yr CAGR | R3: 24-26E 2yr CAGR | S3: 23-26E 3yr CAGR | U3: 1H20 | V3: 2H20 | W3: 1H21 | X3: 2H21 | Y3: 1H22 | Z3: 2H22 | AA3: 1H23 | AB3: 2H23 | AD3: 1Q20 | AE3: 2Q20 | AF3: 3Q20 | AG3: 4Q20 | AH3: 1Q21 | AI3: 2Q21 | AJ3: 3Q21 | AK3: 4Q21 | AL3: 1Q22 | AM3: 2Q22 | AN3: 3Q22 | AO3: 4Q22 | AP3: 1Q23 | AQ3: 2Q23 | AR3: 3Q23 | AS3: 4Q23 | AT3: 1Q24 | AU3: 2Q24 | AV3: 3Q24 | AW3: 4Q24 | AX3: 1Q25 | AY3: 2Q25E | AZ3: 3Q25E | BA3: 4Q25E | BB3: 1Q26E | BC3: 2Q26E | BD3: 3Q26E | BE3: 4Q26E
A4: Revenue
A5: =+Segment!B11 -> Energy drinks | B5: =+Segment!F11 -> 0 | C5: =+Segment!G11 -> 2885.4971 | D5: =+Segment!H11 -> 4003.0305 | E5: =+Segment!I11 -> 4655.1538 | F5: =+Segment!J11 -> 6591.8979 | G5: =+Segment!K11 -> 8172.3068 | H5: =+Segment!L11 -> 10336.009 | I5: =+Segment!M11 -> 13303.584 | ... L5: =+Segment!P11 -> 21255.922 | M5: =+Segment!#REF! -> #REF! | O5: =(H5/C5)^(1/5)-1 -> 0.29070338 | P5: =(M5/H5)^(1/5)-1 -> #REF! | Q5: =(H5/F5)^(1/2)-1 -> 0.25219281 | R5: =(K5/I5)^(1/2)-1 -> 0.18386781 | S5: =(K5/H5)^(1/3)-1 -> 0.21732742 | U5: =+Segment!V11 -> 2272.3273 | V5: =+Segment!W11 -> 2382.8265 | W5: =+Segment!X11 -> 3547.2256 | X5: =+Segment!Y11 -> 3044.6723 | Y5: =+Segment!Z11 -> 4118.3335 | Z5: =+Segment!AA11 -> 4053.9733 | AA5: =+Segment!AB11 -> 5134.9885 | AB5: =+Segment!AC11 -> 5201.0205 | AD5: =+Segment!BB11 -> 0 | AE5: =+Segment!BC11 -> 0 | AF5: =+Segment!BD11 -> 1493.9188 | AG5: =+Segment!BE11 -> 888.9077 | AH5: =+Segment!BF11 -> 1645.0964 | AI5: =+Segment!BG11 -> 1902.1292 | AJ5: =+Segment!BH11 -> 1791.118 | AK5: =+Segment!BI11 -> 1253.5543 | ... BE5: =+Segment!CC11 -> 3572.7799
A6: =+Segment!B12 -> Other beverage | B6: =+Segment!F12 -> 0 | C6: =+Segment!G12 -> 135.6807 | D6: =+Segment!H12 -> 188.7768 | E6: =+Segment!I12 -> 280.5093 | F6: =+Segment!J12 -> 371.94956 | G6: =+Segment!K12 -> 319.02572 | H6: =+Segment!L12 -> 914.47521 | I6: =+Segment!M12 -> 2518.1799 | ... L6: =+Segment!P12 -> 8490.3589 | M6: =+Segment!#REF! -> #REF! | O6: =(H6/C6)^(1/5)-1 -> 0.4646396 | P6: =(M6/H6)^(1/5)-1 -> #REF! | Q6: =(H6/F6)^(1/2)-1 -> 0.56799236 | R6: =(K6/I6)^(1/2)-1 -> 0.63419531 | S6: =(K6/H6)^(1/3)-1 -> 0.94464759 | U6: =+Segment!V12 -> 186.8873 | V6: =+Segment!W12 -> 134.2044 | W6: =+Segment!X12 -> 125.26 | X6: =+Segment!Y12 -> 246.68956 | Y6: =+Segment!Z12 -> 165.92805 | Z6: =+Segment!AA12 -> 153.09767 | AA6: =+Segment!AB12 -> 319.9848 | AB6: =+Segment!AC12 -> 594.49041 | AD6: =+Segment!BB12 -> 0 | AE6: =+Segment!BC12 -> 0 | AF6: =+Segment!BD12 -> 73.6436 | AG6: =+Segment!BE12 -> 60.5608 | AH6: =+Segment!BF12 -> 61.5905 | AI6: =+Segment!BG12 -> 63.6695 | AJ6: =+Segment!BH12 -> 85.615 | AK6: =+Segment!BI12 -> 161.07456 | ... BE6: =+Segment!CC12 -> 1138.6074
A7: Bushuila | B7: =+Segment!F14 -> 0 | H7: =+Segment!L188 -> 393.04206 | I7: =+Segment!M188 -> 1495.0141 | J7: =+Segment!N188 -> 3303.9811 | K7: =+Segment!O188 -> 4493.4143 | L7: =+Segment!P188 -> 5684.1691 | M7: =+Segment!#REF! -> #REF! | R7: =(K7/I7)^(1/2)-1 -> 0.73366663 | S7: =(K7/H7)^(1/3)-1 -> 1.2527473 | U7: =+Segment!V14 -> 0 | V7: =+Segment!W14 -> 0 | W7: =+Segment!X14 -> 0 | X7: =+Segment!Y14 -> 0 | Y7: =+Segment!Z14 -> 0 | Z7: =+Segment!AA14 -> 0 | AA7: =+Segment!AB14 -> 0 | AB7: =+Segment!AC14 -> 0 | AD7: =+Segment!BB14 -> 0 | AE7: =+Segment!BC14 -> 0 | AF7: =+Segment!BD14 -> 0 | AG7: =+Segment!BE14 -> 0 | AH7: =+Segment!BF14 -> 0 | AI7: =+Segment!BG14 -> 0 | AJ7: =+Segment!BH14 -> 0 | AK7: =+Segment!BI14 -> 0 | AT7: =Segment!BR13 -> 157.65 | AU7: =Segment!BS13 -> 318.1878 | AV7: =Segment!BT13 -> 736.6667 | AW7: =Segment!BU13 -> 282.50957 | AX7: =Segment!BV13 -> 569.8415 | AY7: =Segment!BW13 -> 922.89694 | AZ7: =Segment!BX13 -> 1354.0319 | BA7: =Segment!BY13 -> 457.21079 | ... BE7: =Segment!CC13 -> 700.12431
A8: =+Segment!B16 -> Others | B8: =+Segment!F16 -> 0 | H8: =Segment!L190 -> 521.43315 | I8: =I6-I7 -> 1023.1658 | J8: =J6-J7 -> 1727.8459 | K8: =K6-K7 -> 2231.6225 | L8: =L6-L7 -> 2806.1898 | M8: =M6-M7 -> #REF! | R8: =(K8/I8)^(1/2)-1 -> 0.47685331 | S8: =(K8/H8)^(1/3)-1 -> 0.62358126 | U8: =+Segment!V16 -> 10.248172 | V8: =+Segment!W16 -> 12.591228 | W8: =+Segment!X16 -> 9.7761564 | X8: =+Segment!Y16 -> 4.1988779 | Y8: =+Segment!Z16 -> 7.0124213 | Z8: =+Segment!AA16 -> 7.0447582 | AA8: =+Segment!AB16 -> 5.2116289 | AB8: =+Segment!AC16 -> 7.0982465 | AD8: =+Segment!BB16 -> 0 | AE8: =+Segment!BC16 -> 0 | AF8: =+Segment!BD16 -> 6.5718274 | AG8: =+Segment!BE16 -> 6.0194004 | AH8: =+Segment!BF16 -> 4.5748272 | AI8: =+Segment!BG16 -> 5.2013272 | AJ8: =+Segment!BH16 -> 1.2177031 | AK8: =+Segment!BI16 -> 2.9811769 | AT8: =+Segment!BR15 -> 217.1284 | AU8: =+Segment!BS15 -> 310.6186 | AV8: =+Segment!BT15 -> 279.6263 | AW8: =+Segment!BU15 -> 215.79248 | AX8: =+Segment!BV15 -> 374.7969 | AY8: =+Segment!BW15 -> 502.50692 | AZ8: =+Segment!BX15 -> 547.02008 | BA8: =+Segment!BY15 -> 303.52199 | ... BE8: =+Segment!CC15 -> 438.48307
A9: Total | B9: =+Segment!F9 -> 2843.8076 | C9: =+Segment!G9 -> 3037.536 | D9: =+Segment!H9 -> 4208.7285 | E9: =+Segment!I9 -> 4958.5026 | F9: =+Segment!J9 -> 6977.8225 | G9: =+Segment!K9 -> 8505.3897 | H9: =+Segment!L9 -> 11262.794 | I9: =+Segment!M9 -> 15838.852 | ... L9: =+Segment!P9 -> 29791.987 | M9: =+Segment!#REF! -> #REF! | O9: =(H9/C9)^(1/5)-1 -> 0.2996456 | P9: =(M9/H9)^(1/5)-1 -> #REF! | Q9: =(H9/F9)^(1/2)-1 -> 0.2704662 | R9: =(K9/I9)^(1/2)-1 -> 0.26644112 | S9: =(K9/H9)^(1/3)-1 -> 0.31144229 | U9: =+Segment!V9 -> 2469.4627 | V9: =+Segment!W9 -> 2489.0399 | W9: =+Segment!X9 -> 3682.2618 | X9: =+Segment!Y9 -> 3295.5607 | Y9: =+Segment!Z9 -> 4291.274 | Z9: =+Segment!AA9 -> 4214.1157 | AA9: =+Segment!AB9 -> 5460.1849 | AB9: =+Segment!AC9 -> 5802.6092 | AD9: =+Segment!BB9 -> 933.21619 | AE9: =+Segment!BC9 -> 1536.2465 | AF9: =+Segment!BD9 -> 1574.1342 | AG9: =+Segment!BE9 -> 914.90569 | AH9: =+Segment!BF9 -> 1711.2617 | AI9: =+Segment!BG9 -> 1971 | AJ9: =+Segment!BH9 -> 1877.9507 | AK9: =+Segment!BI9 -> 1417.61 | ... BE9: =+Segment!CC9 -> 4744.3135
A11: Gross Profit | BA11: =SUM(AZ9:BA9)/SUM(AV9:AW9)-1 -> 0.28745217
A12: =+A5 -> Energy drinks | B12: =+Segment!F30 -> 0 | C12: =+Segment!G30 -> 1387.4148 | D12: =+Segment!H30 -> 1961.9362 | E12: =+Segment!I30 -> 2265.5034 | F12: =+Segment!J30 -> 3038.1215 | G12: =+Segment!K30 -> 3535.6389 | H12: =+Segment!L30 -> 4684.7677 | I12: =+Segment!M30 -> 6413.2648 | ... L12: =+Segment!P30 -> 11072.91 | M12: =+Segment!#REF! -> #REF! | O12: =(H12/C12)^(1/5)-1 -> 0.27554665 | P12: =(M12/H12)^(1/5)-1 -> #REF! | Q12: =(H12/F12)^(1/2)-1 -> 0.24177085 | R12: =(K12/I12)^(1/2)-1 -> 0.23066221 | S12: =(K12/H12)^(1/3)-1 -> 0.27513533
A13: =+A6 -> Other beverage | B13: =+Segment!F31 -> 0 | C13: =+Segment!G31 -> -3.481 | D13: =+Segment!H31 -> -8.97 | E13: =+Segment!I31 -> 22.271 | F13: =+Segment!J31 -> 48.353632 | G13: =+Segment!K31 -> 54.449432 | H13: =+Segment!L31 -> 157.75569 | I13: =+Segment!M31 -> 672.06462 | ... L13: =+Segment!P31 -> 2664.3521 | M13: =+Segment!#REF! -> #REF! | O13: =(H13/C13)^(1/5)-1 -> -3.1441551 | P13: =(M13/H13)^(1/5)-1 -> #REF! | Q13: =(H13/F13)^(1/2)-1 -> 0.80625044 | R13: =(K13/I13)^(1/2)-1 -> 0.69026364 | S13: =(K13/H13)^(1/3)-1 -> 1.3002673
A14: Bushuila | H14: =Segment!L232 -> 104.03547 | I14: =Segment!M232 -> 444.24392 | J14: =Segment!N232 -> 1063.8819 | K14: =Segment!O232 -> 1545.7345 | L14: =Segment!P232 -> 2069.0375 | M14: =Segment!#REF! -> #REF!
A15: =+A7 -> Bushuila | B15: =+Segment!F32 -> 0 | C15: =+Segment!G32 -> -0.9663 | D15: =+Segment!H32 -> 2.9421 | E15: =+Segment!I32 -> 6.5172 | F15: =+Segment!J32 -> 0 | G15: =+Segment!K32 -> 0 | H15: =+Segment!L32 -> 0 | I15: =+Segment!M32 -> 0 | ... L15: =+Segment!P32 -> 0 | M15: =+Segment!#REF! -> #REF! | S15: n.m.
A16: Others | H16: =Segment!L235 -> 63.047421 | I16: =Segment!M235 -> 227.8207 | J16: =Segment!N235 -> 241.00764 | K16: =Segment!O235 -> 374.34817 | L16: =Segment!P235 -> 595.31455 | M16: =Segment!#REF! -> #REF!
A17: Others | B17: =+Segment!F33 -> 0 | C17: =+Segment!G33 -> 12.360143 | D17: =+Segment!H33 -> 14.04294 | E17: =+Segment!I33 -> 22.880594 | F17: =+Segment!J33 -> 9.782524 | G17: =+Segment!K33 -> 9.8400256 | H17: =+Segment!L33 -> 8.6169128 | I17: =+Segment!M33 -> 11.961381 | ... L17: =+Segment!P33 -> 31.994119 | M17: =+Segment!#REF! -> #REF! | S17: =(K17/H17)^(1/3)-1 -> 0.38812832
A18: Total | B18: =+Segment!F29 -> 1362.8128 | C18: =+Segment!G29 -> 1396.2939 | D18: =+Segment!H29 -> 1967.0092 | E18: =+Segment!I29 -> 2310.6551 | F18: =+Segment!J29 -> 3096.2577 | G18: =+Segment!K29 -> 3599.9284 | H18: =+Segment!L29 -> 4851.1403 | I18: =+Segment!M29 -> 7097.2908 | ... L18: =+Segment!P29 -> 13769.256 | M18: =+Segment!#REF! -> #REF! | O18: =(H18/C18)^(1/5)-1 -> 0.28284267 | P18: =(M18/H18)^(1/5)-1 -> #REF! | Q18: =(H18/F18)^(1/2)-1 -> 0.25170899 | R18: =(K18/I18)^(1/2)-1 -> 0.28154062 | S18: =(K18/H18)^(1/3)-1 -> 0.33938214
A20: Group OP | B20: =B70 -> 380.8296 | C20: =C70 -> 243.64619 | D20: =D70 -> 709.8522 | E20: =E70 -> 1000.5113 | F20: =F70 -> 1356.6212 | G20: =G70 -> 1758.7333 | H20: =H70 -> 2351.473 | I20: =I70 -> 3768.0932 | ... M20: =M70 -> #REF! | O20: =(H20/C20)^(1/5)-1 -> 0.57367873 | P20: =(M20/H20)^(1/5)-1 -> #REF! | Q20: =(H20/F20)^(1/2)-1 -> 0.3165601 | R20: =(K20/I20)^(1/2)-1 -> 0.33523701 | S20: =(K20/H20)^(1/3)-1 -> 0.41894683
A22: Breakdown
A23: Revenues
A24: =+A5 -> Energy drinks | B24: =B5/B$9 -> 0 | C24: =C5/C$9 -> 0.94994663 | D24: =D5/D$9 -> 0.95112586 | E24: =E5/E$9 -> 0.9388225 | F24: =F5/F$9 -> 0.94469269 | G24: =G5/G$9 -> 0.96083861 | H24: =H5/H$9 -> 0.91771269 | I24: =I5/I$9 -> 0.83993363 | ... M24: =M5/M$9 -> #REF!
A25: =+A6 -> Other beverage | B25: =B6/B$9 -> 0 | C25: =C6/C$9 -> 0.044668014 | D25: =D6/D$9 -> 0.044853642 | E25: =E6/E$9 -> 0.056571373 | F25: =F6/F$9 -> 0.053304532 | G25: =G6/G$9 -> 0.037508654 | H25: =H6/H$9 -> 0.081194347 | I25: =I6/I$9 -> 0.15898753 | ... M25: =M6/M$9 -> #REF!
A26: Bushuila | H26: =H7/H5 -> 0.038026482 | I26: =I7/I5 -> 0.11237679 | J26: =J7/J5 -> 0.2073234 | K26: =K7/K5 -> 0.2409913 | L26: =L7/L5 -> 0.26741579 | M26: =M7/M5 -> #REF!
A27: =+A7 -> Bushuila | B27: =B7/B$9 -> 0 | C27: =C7/C$9 -> 0 | D27: =D7/D$9 -> 0 | E27: =E7/E$9 -> 0 | F27: =F7/F$9 -> 0 | G27: =G7/G$9 -> 0 | H27: =H7/H$9 -> 0.034897385 | I27: =I7/I$9 -> 0.094389043 | ... M27: =M7/M$9 -> #REF!
A28: Others | B28: =B8/B$9 -> 0 | C28: =C8/C$9 -> 0 | D28: =D8/D$9 -> 0 | E28: =E8/E$9 -> 0 | F28: =F8/F$9 -> 0 | G28: =G8/G$9 -> 0 | H28: =H8/H$9 -> 0.046296962 | I28: =I8/I$9 -> 0.064598482 | ... M28: =M8/M$9 -> #REF!
A29: Others | H29: =H8/H9 -> 0.046296962 | I29: =I8/I9 -> 0.064598482 | J29: =J8/J9 -> 0.082310083 | K29: =K8/K9 -> 0.087847018 | L29: =L8/L9 -> 0.094192773 | M29: =M8/M9 -> #REF!
A30: Total | B30: =+SUM(B24:B28) -> 0 | C30: =+SUM(C24:C28) -> 0.99461465 | D30: =+SUM(D24:D28) -> 0.9959795 | E30: =+SUM(E24:E28) -> 0.99539387 | F30: =+SUM(F24:F28) -> 0.99799722 | G30: =+SUM(G24:G28) -> 0.99834726 | H30: =+SUM(H24:H25) -> 0.99890703 | I30: =+SUM(I24:I25) -> 0.99892115 | J30: =+SUM(J24:J25) -> 0.99887005 | K30: =+SUM(K24:K25) -> 0.99870387 | L30: =+SUM(L24:L25) -> 0.99846583 | M30: =+SUM(M24:M25) -> #REF!
A32: Gross Profit
A33: =+A24 -> Energy drinks | B33: =B12/B$18 -> 0 | C33: =C12/C$18 -> 0.99364092 | D33: =D12/D$18 -> 0.99742095 | E33: =E12/E$18 -> 0.98045935 | F33: =F12/F$18 -> 0.98122373 | G33: =G12/G$18 -> 0.98214146 | H33: =H12/H$18 -> 0.96570443 | I33: =I12/I$18 -> 0.90362153 | ... M33: =M12/M$18 -> #REF!
A34: =+A25 -> Other beverage | B34: =B13/B$18 -> 0 | C34: =C13/C$18 -> -0.0024930281 | D34: =D13/D$18 -> -0.0045602227 | E34: =E13/E$18 -> 0.0096383921 | F34: =F13/F$18 -> 0.015616798 | G34: =G13/G$18 -> 0.015125143 | H34: =H13/H$18 -> 0.0325193 | I34: =I13/I$18 -> 0.094693121 | ... M34: =M13/M$18 -> #REF!
A35: =+A27 -> Bushuila | B35: =B15/B$18 -> 0 | C35: =C15/C$18 -> -0.00069204626 | D35: =D15/D$18 -> 0.0014957225 | E35: =E15/E$18 -> 0.0028204988 | F35: =F15/F$18 -> 0 | G35: =G15/G$18 -> 0 | H35: =H15/H$18 -> 0 | I35: =I15/I$18 -> 0 | ... M35: =M15/M$18 -> #REF!
A36: Others | B36: =B17/B$18 -> 0 | C36: =C17/C$18 -> 0.0088521065 | D36: =D17/D$18 -> 0.0071392347 | E36: =E17/E$18 -> 0.0099022108 | F36: =F17/F$18 -> 0.003159467 | G36: =G17/G$18 -> 0.0027333948 | H36: =H17/H$18 -> 0.0017762654 | I36: =I17/I$18 -> 0.0016853446 | ... M36: =M17/M$18 -> #REF!
A37: Total | B37: =+SUM(B33:B36) -> 0 | C37: =+SUM(C33:C36) -> 0.99930795 | D37: =+SUM(D33:D36) -> 1.0014957 | E37: =+SUM(E33:E36) -> 1.0028204 | F37: =+SUM(F33:F36) -> 1 | G37: =+SUM(G33:G36) -> 1 | H37: =+SUM(H33:H36) -> 1 | I37: =+SUM(I33:I36) -> 1 | ... M37: =+SUM(M33:M36) -> #REF!
A39: YoY Growth (%) | B39: FY17 | C39: =+C3 -> FY18 | D39: =+D3 -> FY19 | E39: =+E3 -> FY20 | F39: =+F3 -> FY21 | G39: =+G3 -> FY22 | H39: =+H3 -> FY23 | I39: =+I3 -> FY24 | J39: =+J3 -> FY25E | ... M39: =+M3 -> FY28E | U39: =+U3 -> 1H20 | V39: =+V3 -> 2H20 | W39: =+W3 -> 1H21 | X39: =+X3 -> 2H21 | Y39: =+Y3 -> 1H22 | Z39: =+Z3 -> 2H22 | AA39: =+AA3 -> 1H23 | AB39: =+AB3 -> 2H23 | AD39: =+AD3 -> 1Q20 | AE39: =+AE3 -> 2Q20 | AF39: =+AF3 -> 3Q20 | AG39: =+AG3 -> 4Q20 | AH39: =+AH3 -> 1Q21 | AI39: =+AI3 -> 2Q21 | AJ39: =+AJ3 -> 3Q21 | AK39: =+AK3 -> 4Q21 | ... BE39: =+BE3 -> 4Q26E
A40: By segment
A41: =+A33 -> Energy drinks | D41: =D5/C5-1 -> 0.3872932 | E41: =E5/D5-1 -> 0.1629074 | F41: =F5/E5-1 -> 0.41604298 | G41: =G5/F5-1 -> 0.23975022 | H41: =H5/G5-1 -> 0.26476027 | I41: =I5/H5-1 -> 0.28711036 | J41: =J5/I5-1 -> 0.1979 | K41: =K5/J5-1 -> 0.17 | ... M41: =M5/L5-1 -> #REF! | AX41: =AX5/AT5-1 -> 0.25795408 | AY41: =AY5/AU5-1 -> 0.18766627 | AZ41: =AZ5/AV5-1 -> 0.1459288 | BA41: =BA5/AW5-1 -> 0.21422676 | BB41: =BB5/AX5-1 -> 0.21 | BC41: =BC5/AY5-1 -> 0.2 | BD41: =BD5/AZ5-1 -> 0.19 | BE41: =BE5/BA5-1 -> 0.059163814
A42: =+A34 -> Other beverage | D42: =D6/C6-1 -> 0.39133127 | E42: =E6/D6-1 -> 0.485931 | F42: =F6/E6-1 -> 0.32597943 | G42: =G6/F6-1 -> -0.14228767 | H42: =H6/G6-1 -> 1.8664623 | I42: =I6/H6-1 -> 1.7536885 | J42: =J6/I6-1 -> 0.9982 | K42: =K6/J6-1 -> 0.3365 | ... M42: =M6/L6-1 -> #REF! | AX42: =AX6/AT6-1 -> 1.5063795 | AY42: =AY6/AU6-1 -> 1.2668406 | AZ42: =AZ6/AV6-1 -> 0.87057466 | BA42: =BA6/AW6-1 -> 0.52664991 | BB42: =BB6/AX6-1 -> 0.31636426 | BC42: =BC6/AY6-1 -> 0.28529187 | BD42: =BD6/AZ6-1 -> 0.32078515 | BE42: =BE6/BA6-1 -> 0.49672448
A43: =+A35 -> Bushuila | I43: =I7/H7-1 -> 2.8037 | J43: =J7/I7-1 -> 1.21 | K43: =K7/J7-1 -> 0.36 | L43: =L7/K7-1 -> 0.265 | M43: =M7/L7-1 -> #REF! | AX43: =AX7/AT7-1 -> 2.6145988 | AY43: =AY7/AU7-1 -> 1.9004787 | AZ43: =AZ7/AV7-1 -> 0.83805221 | BA43: =BA7/AW7-1 -> 0.61839046 | BB43: =BB7/AX7-1 -> 0.35 | BC43: =BC7/AY7-1 -> 0.34 | BD43: =BD7/AZ7-1 -> 0.32 | BE43: =BE7/BA7-1 -> 0.53129436
A44: Others | I44: =I8/H8-1 -> 0.96221851 | J44: =J8/I8-1 -> 0.68872525 | K44: =K8/J8-1 -> 0.29156338 | L44: =L8/K8-1 -> 0.2574662 | M44: =M8/L8-1 -> #REF! | AX44: =AX8/AT8-1 -> 0.72615328 | AY44: =AY8/AU8-1 -> 0.61776185 | AZ44: =AZ8/AV8-1 -> 0.95625404 | BA44: =BA8/AW8-1 -> 0.4065457 | BB44: =BB8/AX8-1 -> 0.26522445 | BC44: =BC8/AY8-1 -> 0.1848157 | BD44: =BD8/AZ8-1 -> 0.32272862 | BE44: =BE8/BA8-1 -> 0.44465009
A45: Total | C45: =C9/B9-1 -> 0.068122893 | D45: =D9/C9-1 -> 0.3855732 | E45: =E9/D9-1 -> 0.17814742 | F45: =F9/E9-1 -> 0.40724388 | G45: =G9/F9-1 -> 0.21891747 | H45: =H9/G9-1 -> 0.32419494 | I45: =I9/H9-1 -> 0.40629862 | J45: =J9/I9-1 -> 0.32534294 | ... M45: =M9/L9-1 -> #REF! | AX45: =AX9/AT9-1 -> 0.39225679 | AY45: =AY9/AU9-1 -> 0.3410146 | AZ45: =AZ9/AV9-1 -> 0.30359623 | BA45: =BA9/AW9-1 -> 0.2643968 | BB45: =BB9/AX9-1 -> 0.23 | BC45: =BC9/AY9-1 -> 0.22 | BD45: =BD9/AZ9-1 -> 0.23 | BE45: =BE9/BA9-1 -> 0.14377511
A47: Gross Profit
A48: =+A41 -> Energy drinks | D48: =D12/C12-1 -> 0.41409491 | E48: =E12/D12-1 -> 0.15472837 | F48: =F12/E12-1 -> 0.34103596 | G48: =G12/F12-1 -> 0.16375823 | H48: =H12/G12-1 -> 0.32501304 | I48: =I12/H12-1 -> 0.36896111 | J48: =J12/I12-1 -> 0.26394562 | K48: =K12/J12-1 -> 0.19825526 | ... M48: =M12/L12-1 -> #REF!
A49: =+A42 -> Other beverage | D49: =D13/C13-1 -> 1.5768457 | E49: =E13/D13-1 -> -3.4828317 | F49: =F13/E13-1 -> 1.1711478 | G49: =G13/F13-1 -> 0.12606706 | H49: =H13/G13-1 -> 1.8972881 | I49: =I13/H13-1 -> 3.2601609 | J49: =J13/I13-1 -> 0.94161322 | K49: =K13/J13-1 -> 0.47145226 | ... M49: =M13/L13-1 -> #REF!
A50: =+A43 -> Bushuila | D50: =D15/C15-1 -> -4.0447066 | E50: =E15/D15-1 -> 1.2151524 | F50: =F15/E15-1 -> -1 | G50: =G15/F15-1 -> #DIV/0! | H50: =H15/G15-1 -> #DIV/0! | I50: =I15/H15-1 -> #DIV/0! | J50: =J15/I15-1 -> #DIV/0! | K50: =K15/J15-1 -> #DIV/0! | ... M50: =M15/L15-1 -> #REF!
A51: Others | D51: =D17/C17-1 -> 0.13614711 | E51: =E17/D17-1 -> 0.6293307 | F51: =F17/E17-1 -> -0.57245323 | G51: =G17/F17-1 -> 0.0058779963 | H51: =H17/G17-1 -> -0.12429976 | I51: =I17/H17-1 -> 0.38812832 | J51: =J17/I17-1 -> 0.38812832 | K51: =K17/J17-1 -> 0.38812832 | ... M51: =M17/L17-1 -> #REF!
A52: Total | C52: =C18/B18-1 -> 0.024567675 | D52: =D18/C18-1 -> 0.40873577 | E52: =E18/D18-1 -> 0.17470477 | F52: =F18/E18-1 -> 0.33999127 | G52: =G18/F18-1 -> 0.1626708 | H52: =H18/G18-1 -> 0.34756578 | I52: =I18/H18-1 -> 0.46301495 | J52: =J18/I18-1 -> 0.32832537 | ... M52: =M18/L18-1 -> #REF!
A54: Gross Profit Margin | B54: FY17 | C54: =+C39 -> FY18 | D54: =+D39 -> FY19 | E54: =+E39 -> FY20 | F54: =+F39 -> FY21 | G54: =+G39 -> FY22 | H54: =+H39 -> FY23 | I54: =+I39 -> FY24 | J54: =+J39 -> FY25E | ... M54: =+M39 -> FY28E | U54: =U39 -> 1H20 | V54: =V39 -> 2H20 | W54: =W39 -> 1H21 | X54: =X39 -> 2H21 | Y54: =Y39 -> 1H22 | Z54: =Z39 -> 2H22 | AA54: =AA39 -> 1H23 | AB54: =AB39 -> 2H23 | AD54: =+AD39 -> 1Q20 | AE54: =+AE39 -> 2Q20 | AF54: =+AF39 -> 3Q20 | AG54: =+AG39 -> 4Q20 | AH54: =+AH39 -> 1Q21 | AI54: =+AI39 -> 2Q21 | AJ54: =+AJ39 -> 3Q21 | AK54: =+AK39 -> 4Q21 | ... BE54: =+BE39 -> 4Q26E
A55: By segment
A56: =+A48 -> Energy drinks | C56: =C12/C5 -> 0.48082349 | D56: =D12/D5 -> 0.49011273 | E56: =E12/E5 -> 0.48666564 | F56: =F12/F5 -> 0.46088723 | G56: =G12/G5 -> 0.43263659 | H56: =H12/H5 -> 0.45324726 | I56: =I12/I5 -> 0.48207045 | J56: =J12/J5 -> 0.50864916 | ... M56: =M12/M5 -> #REF!
A57: =+A49 -> Other beverage | C57: =C13/C6 -> -0.025655823 | D57: =D13/D6 -> -0.047516432 | E57: =E13/E6 -> 0.079394872 | F57: =F13/F6 -> 0.13000051 | G57: =G13/G6 -> 0.17067411 | H57: =H13/H6 -> 0.17250953 | I57: =I13/I6 -> 0.26688508 | J57: =J13/J6 -> 0.25932719 | ... M57: =M13/M6 -> #REF!
A58: =+A50 -> Bushuila | H58: =H14/H7 -> 0.26469297 | I58: =I14/I7 -> 0.29715033 | J58: =J14/J7 -> 0.322 | K58: =K14/K7 -> 0.344 | L58: =L14/L7 -> 0.364 | M58: =M14/M7 -> #REF!
A59: Others | H59: =H16/H8 -> 0.1209118 | I59: =I16/I8 -> 0.22266255 | J59: =J16/J8 -> 0.13948445 | K59: =K16/K8 -> 0.16774709 | L59: =L16/L8 -> 0.21214336 | M59: =M16/M8 -> #REF!
A60: Total | B60: =B18/B9 -> 0.47922117 | C60: =C18/C9 -> 0.4596798 | D60: =D18/D9 -> 0.46736425 | E60: =E18/E9 -> 0.46599857 | F60: =F18/F9 -> 0.44372835 | G60: =G18/G9 -> 0.42325261 | H60: =H18/H9 -> 0.43072263 | I60: =I18/I9 -> 0.44809377 | ... M60: =M18/M9 -> #REF!
A62: Consolidated P/L (Rmb mn) | B62: =B54 -> FY17 | C62: =C54 -> FY18 | D62: =D54 -> FY19 | E62: =E54 -> FY20 | F62: =F54 -> FY21 | G62: =G54 -> FY22 | H62: =H54 -> FY23 | I62: =I54 -> FY24 | ... M62: =M54 -> FY28E | O62: 18-23 5yr CAGR | P62: 23-28 5yr CAGR | Q62: 21-23 2yr CAGR | R62: 24-26E 2yr CAGR | S62: 23-26E 3yr CAGR | U62: =U54 -> 1H20 | V62: =V54 -> 2H20 | W62: =W54 -> 1H21 | X62: =X54 -> 2H21 | Y62: =Y54 -> 1H22 | Z62: =Z54 -> 2H22 | AA62: =AA54 -> 1H23 | AB62: =AB54 -> 2H23 | AD62: =+AD54 -> 1Q20 | AE62: =+AE54 -> 2Q20 | AF62: =+AF54 -> 3Q20 | AG62: =+AG54 -> 4Q20 | AH62: =+AH54 -> 1Q21 | AI62: =+AI54 -> 2Q21 | AJ62: =+AJ54 -> 3Q21 | AK62: =+AK54 -> 4Q21 | ... BE62: =+BE54 -> 4Q26E
A64: Revenue | B64: =+Model!C13 -> 2843.8076 | C64: =+Model!D13 -> 3037.536 | D64: =+Model!E13 -> 4208.7285 | E64: =+Model!F13 -> 4958.5026 | F64: =+Model!G13 -> 6977.8225 | G64: =+Model!H13 -> 8505.3897 | H64: =+Model!I13 -> 11262.794 | I64: =+Model!J13 -> 15838.852 | ... L64: =+Model!M13 -> 29791.987 | M64: =+Model!#REF! -> #REF! | O64: =(H64/C64)^(1/5)-1 -> 0.2996456 | P64: =(M64/H64)^(1/5)-1 -> #REF! | Q64: =(H64/F64)^(1/2)-1 -> 0.2704662 | R64: =(K64/I64)^(1/2)-1 -> 0.26644112 | S64: =(K64/H64)^(1/3)-1 -> 0.31144229 | U64: =+Segment!V9 -> 2469.4627 | V64: =+Segment!W9 -> 2489.0399 | W64: =+Segment!X9 -> 3682.2618 | X64: =+Segment!Y9 -> 3295.5607 | Y64: =+Segment!Z9 -> 4291.274 | Z64: =+Segment!AA9 -> 4214.1157 | AA64: =+Segment!AB9 -> 5460.1849 | AB64: =+Segment!AC9 -> 5802.6092 | AD64: =+Segment!BB9 -> 933.21619 | AE64: =+Segment!BC9 -> 1536.2465 | AF64: =+Segment!BD9 -> 1574.1342 | AG64: =+Segment!BE9 -> 914.90569 | AH64: =+Segment!BF9 -> 1711.2617 | AI64: =+Segment!BG9 -> 1971 | AJ64: =+Segment!BH9 -> 1877.9507 | AK64: =+Segment!BI9 -> 1417.61 | ... BE64: =+Segment!CC9 -> 4744.3135
A65: COGS | B65: =+Model!C18 -> -1480.9948 | C65: =+Model!D18 -> -1641.2421 | D65: =+Model!E18 -> -2241.7193 | E65: =+Model!F18 -> -2647.8475 | F65: =+Model!G18 -> -3881.5648 | G65: =+Model!H18 -> -4905.4613 | H65: =+Model!I18 -> -6411.6538 | I65: =+Model!J18 -> -8741.561 | ... L65: =+Model!M18 -> -16022.731 | M65: =+Model!#REF! -> #REF! | O65: =(H65/C65)^(1/5)-1 -> 0.31328651 | P65: =(M65/H65)^(1/5)-1 -> #REF! | Q65: =(H65/F65)^(1/2)-1 -> 0.28523224 | R65: =(K65/I65)^(1/2)-1 -> 0.25404809 | S65: =(K65/H65)^(1/3)-1 -> 0.28948344 | U65: =-Segment!V23 -> -1322.65 | V65: =-Segment!W23 -> -1325.1975 | W65: =-Segment!X23 -> -1852.9146 | X65: =-Segment!Y23 -> -2028.6502 | Y65: =-Segment!Z23 -> -2459.7423 | Z65: =-Segment!AA23 -> -2445.719 | AA65: =-Segment!AB23 -> -3106.6108 | AB65: =-Segment!AC23 -> -3305.0429 | AD65: =-Segment!BB23 -> -474.49274 | AE65: =-Segment!BC23 -> -848.15726 | AF65: =-Segment!BD23 -> -828.35415 | AG65: =-Segment!BE23 -> -496.84336 | AH65: =-Segment!BF23 -> -863.46211 | AI65: =-Segment!BG23 -> -989.4525 | AJ65: =-Segment!BH23 -> -1011.1236 | AK65: =-Segment!BI23 -> -1017.5266 | ... BE65: =-Segment!CC23 -> -2664.8138
A66: GP | B66: =SUM(B64:B65) -> 1362.8128 | C66: =SUM(C64:C65) -> 1396.2939 | D66: =SUM(D64:D65) -> 1967.0092 | E66: =SUM(E64:E65) -> 2310.6551 | F66: =SUM(F64:F65) -> 3096.2577 | G66: =SUM(G64:G65) -> 3599.9284 | H66: =SUM(H64:H65) -> 4851.1403 | I66: =SUM(I64:I65) -> 7097.2908 | ... M66: =SUM(M64:M65) -> #REF! | O66: =(H66/C66)^(1/5)-1 -> 0.28284267 | P66: =(M66/H66)^(1/5)-1 -> #REF! | Q66: =(H66/F66)^(1/2)-1 -> 0.25170899 | R66: =(K66/I66)^(1/2)-1 -> 0.28154062 | S66: =(K66/H66)^(1/3)-1 -> 0.33938214 | U66: =SUM(U64:U65) -> 1146.8127 | V66: =SUM(V64:V65) -> 1163.8424 | W66: =SUM(W64:W65) -> 1829.3471 | X66: =SUM(X64:X65) -> 1266.9105 | Y66: =SUM(Y64:Y65) -> 1831.5317 | Z66: =SUM(Z64:Z65) -> 1768.3967 | AA66: =SUM(AA64:AA65) -> 2353.5741 | AB66: =SUM(AB64:AB65) -> 2497.5662 | AD66: =AD64+AD65 -> 458.72345 | AE66: =AE64+AE65 -> 688.08925 | AF66: =AF64+AF65 -> 745.78008 | AG66: =AG64+AG65 -> 418.06233 | AH66: =AH64+AH65 -> 847.79962 | AI66: =AI64+AI65 -> 981.54753 | AJ66: =AJ64+AJ65 -> 866.82714 | AK66: =AK64+AK65 -> 400.0834 | ... BE66: =BE64+BE65 -> 2079.4997
A67: SG&A (excl. other rev/exp) | B67: =+Model!C23 -> -981.9832 | C67: =+Model!D23 -> -1152.6478 | D67: =+Model!E23 -> -1257.157 | E67: =+Model!F23 -> -1310.1438 | F67: =+Model!G23 -> -1739.6364 | G67: =+Model!H23 -> -1841.1951 | H67: =+Model!I23 -> -2499.6673 | I67: =+Model!J23 -> -3329.1976 | ... L67: =+Model!M23 -> -5684.0683 | M67: =+Model!#REF! -> #REF! | O67: =(H67/C67)^(1/5)-1 -> 0.16744686 | P67: =(M67/H67)^(1/5)-1 -> #REF! | Q67: =(H67/F67)^(1/2)-1 -> 0.19870374 | R67: =(K67/I67)^(1/2)-1 -> 0.21791251 | S67: =(K67/H67)^(1/3)-1 -> 0.25476727 | U67: =-Segment!V45-Segment!V47-Segment!V49 -> -579.2962 | V67: =-Segment!W45-Segment!W47-Segment!W49 -> -730.84764 | W67: =-Segment!X45-Segment!X47-Segment!X49 -> -992.75571 | X67: =-Segment!Y45-Segment!Y47-Segment!Y49 -> -746.88072 | Y67: =-Segment!Z45-Segment!Z47-Segment!Z49 -> -901.70576 | Z67: =-Segment!AA45-Segment!AA47-Segment!AA49 -> -939.4893 | AA67: =-Segment!AB45-Segment!AB47-Segment!AB49 -> -1111.8714 | AB67: =-Segment!AC45-Segment!AC47-Segment!AC49 -> -1387.7959 | AD67: =-Segment!BB45-Segment!BB47-Segment!BB49 -> -253.7839 | AE67: =-Segment!BC45-Segment!BC47-Segment!BC49 -> -325.5123 | AF67: =-Segment!BD45-Segment!BD47-Segment!BD49 -> -429.64733 | AG67: =-Segment!BE45-Segment!BE47-Segment!BE49 -> -301.20032 | AH67: =-Segment!BF45-Segment!BF47-Segment!BF49 -> -417.98096 | AI67: =-Segment!BG45-Segment!BG47-Segment!BG49 -> -574.77476 | AJ67: =-Segment!BH45-Segment!BH47-Segment!BH49 -> -489.31194 | AK67: =-Segment!BI45-Segment!BI47-Segment!BI49 -> -257.56879 | ... BE67: =-Segment!CC45-Segment!CC47-Segment!CC49 -> -778.42172
A68: Selling Exp. | B68: =+Model!C25 -> -825.2498 | C68: =+Model!D25 -> -969.45034 | D68: =+Model!E25 -> -983.59316 | E68: =+Model!F25 -> -1040.3473 | F68: =+Model!G25 -> -1368.3844 | G68: =+Model!H25 -> -1449.2761 | H68: =+Model!I25 -> -1955.6714 | I68: =+Model!J25 -> -2681.0798 | ... L68: =+Model!M25 -> -4584.1632 | M68: =+Model!#REF! -> #REF! | O68: =(H68/C68)^(1/5)-1 -> 0.15067867 | P68: =(M68/H68)^(1/5)-1 -> #REF! | Q68: =(H68/F68)^(1/2)-1 -> 0.19548433 | R68: =(K68/I68)^(1/2)-1 -> 0.21722811 | S68: =(K68/H68)^(1/3)-1 -> 0.26644384 | U68: =-Segment!V47 -> -452.208 | V68: =-Segment!W47 -> -588.13929 | W68: =-Segment!X47 -> -798.65826 | X68: =-Segment!Y47 -> -569.72611 | Y68: =-Segment!Z47 -> -702.69818 | Z68: =-Segment!AA47 -> -746.5779 | AA68: =-Segment!AB47 -> -863.23476 | AB68: =-Segment!AC47 -> -1092.4366 | AD68: =-Segment!BB47 -> -201.55927 | AE68: =-Segment!BC47 -> -250.64873 | AF68: =-Segment!BD47 -> -360.37018 | AG68: =-Segment!BE47 -> -227.76911 | AH68: =-Segment!BF47 -> -336.21724 | AI68: =-Segment!BG47 -> -462.44102 | AJ68: =-Segment!BH47 -> -399.24318 | AK68: =-Segment!BI47 -> -170.48293 | ... BE68: =-Segment!CC47 -> -557.40306
A69: Admin Exp. | B69: =+Model!C26 -> -110.7888 | C69: =+Model!D26 -> -143.62836 | D69: =+Model!E26 -> -229.25756 | E69: =+Model!F26 -> -219.43897 | F69: =+Model!G26 -> -294.44155 | G69: =+Model!H26 -> -299.27981 | H69: =+Model!I26 -> -422.98511 | I69: =+Model!J26 -> -488.32508 | ... L69: =+Model!M26 -> -799.34397 | M69: =+Model!#REF! -> #REF! | O69: =(H69/C69)^(1/5)-1 -> 0.24112915 | P69: =(M69/H69)^(1/5)-1 -> #REF! | Q69: =(H69/F69)^(1/2)-1 -> 0.19856887 | R69: =(K69/I69)^(1/2)-1 -> 0.2054087 | S69: =(K69/H69)^(1/3)-1 -> 0.18818536 | U69: =-Segment!V49 -> -103.3502 | V69: =-Segment!W49 -> -116.08877 | W69: =-Segment!X49 -> -152.51556 | X69: =-Segment!Y49 -> -141.92599 | Y69: =-Segment!Z49 -> -151.35686 | Z69: =-Segment!AA49 -> -147.92294 | AA69: =-Segment!AB49 -> -189.16727 | AB69: =-Segment!AC49 -> -233.81784 | AD69: =-Segment!BB49 -> -45.432064 | AE69: =-Segment!BC49 -> -57.918136 | AF69: =-Segment!BD49 -> -53.414128 | AG69: =-Segment!BE49 -> -62.674645 | AH69: =-Segment!BF49 -> -63.642069 | AI69: =-Segment!BG49 -> -88.873486 | AJ69: =-Segment!BH49 -> -71.529616 | AK69: =-Segment!BI49 -> -70.396378 | ... BE69: =-Segment!CC49 -> -176.06494
A70: OP | B70: =SUM(B66+B67) -> 380.8296 | C70: =SUM(C66+C67) -> 243.64619 | D70: =SUM(D66+D67) -> 709.8522 | E70: =SUM(E66+E67) -> 1000.5113 | F70: =SUM(F66+F67) -> 1356.6212 | G70: =SUM(G66+G67) -> 1758.7333 | H70: =SUM(H66+H67) -> 2351.473 | I70: =SUM(I66+I67) -> 3768.0932 | ... M70: =SUM(M66+M67) -> #REF! | O70: =(H70/C70)^(1/5)-1 -> 0.57367873 | P70: =(M70/H70)^(1/5)-1 -> #REF! | Q70: =(H70/F70)^(1/2)-1 -> 0.3165601 | R70: =(K70/I70)^(1/2)-1 -> 0.33523701 | S70: =(K70/H70)^(1/3)-1 -> 0.41894683 | U70: =SUM(U66,U67) -> 567.5165 | V70: =SUM(V66,V67) -> 432.99477 | W70: =SUM(W66,W67) -> 836.59143 | X70: =SUM(X66,X67) -> 520.02981 | Y70: =SUM(Y66,Y67) -> 929.82593 | Z70: =SUM(Z66,Z67) -> 828.90741 | AA70: =SUM(AA66,AA67) -> 1241.7027 | AB70: =SUM(AB66,AB67) -> 1109.7703 | AD70: =SUM(AD66,AD67) -> 204.93955 | AE70: =SUM(AE66,AE67) -> 362.57695 | AF70: =SUM(AF66,AF67) -> 316.13275 | AG70: =SUM(AG66,AG67) -> 116.86201 | AH70: =SUM(AH66,AH67) -> 429.81866 | AI70: =SUM(AI66,AI67) -> 406.77277 | AJ70: =SUM(AJ66,AJ67) -> 377.5152 | AK70: =SUM(AK66,AK67) -> 142.51461 | ... BE70: =SUM(BE66,BE67) -> 1301.078
A71: Other income/expenses | B71: =+Model!C27 -> -0.5354 | C71: =+Model!D27 -> -2.2846109 | D71: =+Model!E27 -> -6.5609849 | E71: =+Model!F27 -> 0.6175207 | F71: =+Model!G27 -> 115.88506 | G71: =+Model!H27 -> 12.42969 | H71: =+Model!I27 -> 27.680013 | I71: =+Model!J27 -> 31.990655 | ... L71: =+Model!M27 -> 54.042073 | M71: =+Model!#REF! -> #REF! | U71: =-Segment!V54+Segment!V55 -> 0.9929 | V71: =-Segment!W54+Segment!W55 -> -1.6104207 | W71: =-Segment!X54+Segment!X55 -> 6.9803632 | X71: =-Segment!Y54+Segment!Y55 -> 110.47476 | Y71: =-Segment!Z54+Segment!Z55 -> 33.737949 | Z71: =-Segment!AA54+Segment!AA55 -> -20.591977 | AA71: =-Segment!AB54+Segment!AB55 -> 73.566109 | AB71: =-Segment!AC54+Segment!AC55 -> -42.501257 | AD71: =+Segment!BB54+Segment!BB55 -> 0.13945006 | AE71: =+Segment!BC54+Segment!BC55 -> -1.1323501 | AF71: =+Segment!BD54+Segment!BD55 -> 0.50023402 | AG71: =+Segment!BE54+Segment!BE55 -> 1.1101867 | AH71: =+Segment!BF54+Segment!BF55 -> -0.54270748 | AI71: =+Segment!BG54+Segment!BG55 -> 5.9831034 | AJ71: =+Segment!BH54+Segment!BH55 -> 12.302802 | AK71: =+Segment!BI54+Segment!BI55 -> 98.141858 | ... BE71: =+Segment!CC54+Segment!CC55 -> -149.0172
A72: EBIT (reported) | B72: =B70+B71 -> 380.2942 | C72: =C70+C71 -> 241.36158 | D72: =D70+D71 -> 703.29121 | E72: =E70+E71 -> 1001.1288 | F72: =F70+F71 -> 1472.5063 | G72: =G70+G71 -> 1771.163 | H72: =H70+H71 -> 2379.153 | I72: =I70+I71 -> 3800.0839 | ... M72: =M70+M71 -> #REF! | O72: =(H72/C72)^(1/5)-1 -> 0.58034115 | P72: =(M72/H72)^(1/5)-1 -> #REF! | Q72: =(H72/F72)^(1/2)-1 -> 0.27110845 | R72: =(K72/I72)^(1/2)-1 -> 0.33444916 | S72: =(K72/H72)^(1/3)-1 -> 0.41685353 | U72: =U70+U71 -> 568.5094 | V72: =V70+V71 -> 431.38435 | W72: =W70+W71 -> 843.5718 | X72: =X70+X71 -> 630.50457 | Y72: =Y70+Y71 -> 963.56388 | Z72: =Z70+Z71 -> 808.31543 | AA72: =AA70+AA71 -> 1315.2688 | AB72: =AB70+AB71 -> 1067.269 | AD72: =AD70+AD71 -> 205.079 | AE72: =AE70+AE71 -> 361.4446 | AF72: =AF70+AF71 -> 316.63299 | AG72: =AG70+AG71 -> 117.9722 | AH72: =AH70+AH71 -> 429.27595 | AI72: =AI70+AI71 -> 412.75588 | AJ72: =AJ70+AJ71 -> 389.818 | AK72: =AK70+AK71 -> 240.65647 | ... BE72: =BE70+BE71 -> 1152.0608
A73: D&A | B73: =+Model!C33+Model!C34 -> 0 | C73: =+Model!D33+Model!D34 -> -84.971488 | D73: =+Model!E33+Model!E34 -> -109.72447 | E73: =+Model!F33+Model!F34 -> -134.44275 | F73: =+Model!G33+Model!G34 -> -185.1128 | G73: =+Model!H33+Model!H34 -> -223.94137 | H73: =+Model!I33+Model!I34 -> -254.03913 | I73: =+Model!J33+Model!J34 -> -343.05169 | ... L73: =+Model!M33+Model!M34 -> -734.1128 | M73: =+Model!#REF!+Model!#REF! -> #REF! | O73: =(H73/C73)^(1/5)-1 -> 0.24487423 | P73: =(M73/H73)^(1/5)-1 -> #REF! | Q73: =(H73/F73)^(1/2)-1 -> 0.17147244 | R73: =(K73/I73)^(1/2)-1 -> 0.21446549 | S73: =(K73/H73)^(1/3)-1 -> 0.25818094 | W73: =-SUM(Wind!CG237:CG240) -> -89.61564 | X73: =+F73-W73 -> -95.497164 | Y73: =+G73-X73 -> -128.44421 | Z73: =+H73-Y73 -> -125.59492 | AA73: =+I73-Z73 -> -217.45677 | AB73: =+J73-AA73 -> -198.75909 | AD73: =-SUM(Wind!CB237:CB240) -> -30.587446 | AH73: =-SUM(Wind!CF237:CF240) -> -42.015491 | AI73: =+W73-AH73 -> -47.600149
A74: EBITDA | B74: =B72-B73 -> 380.2942 | C74: =C72-C73 -> 326.33306 | D74: =D72-D73 -> 813.01568 | E74: =E72-E73 -> 1135.5715 | F74: =F72-F73 -> 1657.6191 | G74: =G72-G73 -> 1995.1044 | H74: =H72-H73 -> 2633.1921 | I74: =I72-I73 -> 4143.1356 | ... M74: =M72-M73 -> #REF! | O74: =(H74/C74)^(1/5)-1 -> 0.51832343 | P74: =(M74/H74)^(1/5)-1 -> #REF! | Q74: =(H74/F74)^(1/2)-1 -> 0.26037245 | R74: =(K74/I74)^(1/2)-1 -> 0.32492716 | S74: =(K74/H74)^(1/3)-1 -> 0.40306201 | U74: =U72-U73 -> 568.5094 | V74: =V72-V73 -> 431.38435 | W74: =W72-W73 -> 933.18744 | X74: =X72-X73 -> 726.00174 | Y74: =Y72-Y73 -> 1092.0081 | Z74: =Z72-Z73 -> 933.91035 | AA74: =AA72-AA73 -> 1532.7256 | AB74: =AB72-AB73 -> 1266.0281 | AD74: =AD72-AD73 -> 235.66644 | AE74: =AE72-AE73 -> 361.4446 | AF74: =AF72-AF73 -> 316.63299 | AG74: =AG72-AG73 -> 117.9722 | AH74: =AH72-AH73 -> 471.29144 | AI74: =AI72-AI73 -> 460.35603 | AJ74: =AJ72-AJ73 -> 389.818 | AK74: =AK72-AK73 -> 240.65647 | ... BE74: =BE72-BE73 -> 1152.0608
A76: Net Finance Exp. | B76: =+Model!C38 -> -10.454 | C76: =+Model!D38 -> -5.0820752 | D76: =+Model!E38 -> 13.965657 | E76: =+Model!F38 -> 15.93094 | F76: =+Model!G38 -> 11.393957 | G76: =+Model!H38 -> -41.039484 | H76: =+Model!I38 -> -2.2856168 | I76: =+Model!J38 -> 190.53573 | ... L76: =+Model!M38 -> 208.22262 | M76: =+Model!#REF! -> #REF! | U76: =-Segment!V53 -> 6.822 | V76: =-Segment!W53 -> -22.75294 | W76: =-Segment!X53 -> 4.2964605 | X76: =-Segment!Y53 -> -15.690418 | Y76: =-Segment!Z53 -> -20.767388 | Z76: =-Segment!AA53 -> 61.806872 | AA76: =-Segment!AB53 -> 5.2930758 | AB76: =-Segment!AC53 -> -3.007459 | AD76: =-Segment!BB53 -> 3.7269526 | AE76: =-Segment!BC53 -> 3.0950474 | AF76: =-Segment!BD53 -> 4.6195695 | AG76: =-Segment!BE53 -> -27.372509 | AH76: =-Segment!BF53 -> 2.3103464 | AI76: =-Segment!BG53 -> 1.9861142 | AJ76: =-Segment!BH53 -> 6.3750549 | AK76: =-Segment!BI53 -> -22.065473 | ... BE76: =-Segment!CC53 -> 117.76187
A77: Other Non-Op Income | B77: =B78-(B72+B76) -> 19.9649 | C77: =C78-(C72+C76) -> 37.048354 | D77: =D78-(D72+D76) -> 19.246076 | E77: =E78-(E72+E76) -> 12.489926 | F77: =F78-(F72+F76) -> 29.616555 | G77: =G78-(G72+G76) -> 105.8862 | H77: =H78-(H72+H76) -> 202.40354 | I77: =I78-(I72+I76) -> 116.6927 | ... M77: =M78-(M72+M76) -> #REF! | U77: =U78-(U72+U76) -> -24.0335 | V77: =V78-(V72+V76) -> 69.620347 | W77: =W78-(W72+W76) -> 3.4050005 | X77: =X78-(X72+X76) -> 47.4294 | Y77: =Y78-(Y72+Y76) -> 18.214887 | Z77: =Z78-(Z72+Z76) -> 4.876064 | AA77: =AA78-(AA72+AA76) -> 142.91268 | AB77: =AB78-(AB72+AB76) -> 101.74667 | AD77: =AD78-(AD72+AD76) -> -18.134598 | AE77: =AE78-(AE72+AE76) -> -3.913102 | AF77: =AF78-(AF72+AF76) -> 2.2820588 | AG77: =AG78-(AG72+AG76) -> 64.117447 | AH77: =AH78-(AH72+AH76) -> 2.0909105 | AI77: =AI78-(AI72+AI76) -> 2.8540573 | AJ77: =AJ78-(AJ72+AJ76) -> -5.529841 | AK77: =AK78-(AK72+AK76) -> 52.989343 | ... BE77: =BE78-(BE72+BE76) -> 6.849667
A78: Profit Before Tax | B78: =+Model!C50 -> 389.8051 | C78: =+Model!D50 -> 273.32785 | D78: =+Model!E50 -> 736.50294 | E78: =+Model!F50 -> 1029.5497 | F78: =+Model!G50 -> 1513.5168 | G78: =+Model!H50 -> 1836.0097 | H78: =+Model!I50 -> 2579.2709 | I78: =+Model!J50 -> 4107.3123 | ... L78: =+Model!M50 -> 8495.2442 | M78: =+Model!#REF! -> #REF! | O78: =(H78/C78)^(1/5)-1 -> 0.5666162 | P78: =(M78/H78)^(1/5)-1 -> #REF! | Q78: =(H78/F78)^(1/2)-1 -> 0.30543381 | R78: =(K78/I78)^(1/2)-1 -> 0.31605437 | S78: =(K78/H78)^(1/3)-1 -> 0.40239216 | U78: =+Segment!V61 -> 551.2979 | V78: =+Segment!W61 -> 478.25175 | W78: =+Segment!X61 -> 851.27326 | X78: =+Segment!Y61 -> 662.24356 | Y78: =+Segment!Z61 -> 961.01138 | Z78: =+Segment!AA61 -> 874.99837 | AA78: =+Segment!AB61 -> 1463.4746 | AB78: =+Segment!AC61 -> 1166.0083 | AD78: =+Segment!BB61 -> 190.67135 | AE78: =+Segment!BC61 -> 360.62655 | AF78: =+Segment!BD61 -> 323.53462 | AG78: =+Segment!BE61 -> 154.71714 | AH78: =+Segment!BF61 -> 433.67721 | AI78: =+Segment!BG61 -> 417.59605 | AJ78: =+Segment!BH61 -> 390.66322 | AK78: =+Segment!BI61 -> 271.58034 | ... BE78: =+Segment!CC61 -> 1276.6723
A79: Tax | B79: =+Model!C53 -> -93.6393 | C79: =+Model!D53 -> -57.496914 | D79: =+Model!E53 -> -165.92903 | E79: =+Model!F53 -> -217.48614 | F79: =+Model!G53 -> -320.55641 | G79: =+Model!H53 -> -395.48918 | H79: =+Model!I53 -> -539.49813 | I79: =+Model!J53 -> -780.88329 | ... L79: =+Model!M53 -> -1741.5251 | M79: =+Model!#REF! -> #REF! | U79: =-Segment!V62 -> -123.6327 | V79: =-Segment!W62 -> -93.853439 | W79: =-Segment!X62 -> -184.04005 | X79: =-Segment!Y62 -> -136.51636 | Y79: =-Segment!Z62 -> -206.3816 | Z79: =-Segment!AA62 -> -189.10757 | AA79: =-Segment!AB62 -> -294.04553 | AB79: =-Segment!AC62 -> -245.4526 | AD79: =-Segment!BB62 -> -44.475694 | AE79: =-Segment!BC62 -> -79.157006 | AF79: =-Segment!BD62 -> -70.040576 | AG79: =-Segment!BE62 -> -23.812862 | AH79: =-Segment!BF62 -> -96.408437 | AI79: =-Segment!BG62 -> -87.631611 | AJ79: =-Segment!BH62 -> -83.205508 | AK79: =-Segment!BI62 -> -53.310851 | ... BE79: =-Segment!CC62 -> -215.58718
A80: Minority Interest | B80: =+Model!C54 -> 0 | C80: =+Model!D54 -> 0 | D80: =+Model!E54 -> 0 | E80: =+Model!F54 -> 0 | F80: =+Model!G54 -> 0 | G80: =+Model!H54 -> 0 | H80: =+Model!I54 -> 0 | I80: =+Model!J54 -> 0.27984775 | ... L80: =+Model!M54 -> 0.27984775 | M80: =+Model!#REF! -> #REF! | U80: =+U81-U78-U79 -> 0 | V80: =+V81-V78-V79 -> 0 | W80: =+W81-W78-W79 -> 0 | X80: =+X81-X78-X79 -> 0 | Y80: =+Y81-Y78-Y79 -> 0 | Z80: =+Z81-Z78-Z79 -> 0 | AA80: =+AA81-AA78-AA79 -> 0 | AB80: =+AB81-AB78-AB79 -> -50.211884 | AD80: =-Segment!BB64 -> 0 | AE80: =-Segment!BC64 -> 0 | AF80: =-Segment!BD64 -> 0 | AG80: =-Segment!BE64 -> 0 | AH80: =-Segment!BF64 -> 0 | AI80: =-Segment!BG64 -> 0 | AJ80: =-Segment!BH64 -> 0 | AK80: =-Segment!BI64 -> 0 | ... BE80: =-Segment!CC64 -> 0.27984775
A81: NPAT to shareholders | B81: =SUM(B78:B80) -> 296.1658 | C81: =SUM(C78:C80) -> 215.83094 | D81: =SUM(D78:D80) -> 570.57391 | E81: =SUM(E78:E80) -> 812.06352 | F81: =SUM(F78:F80) -> 1192.9604 | G81: =SUM(G78:G80) -> 1440.5206 | H81: =SUM(H78:H80) -> 2039.7728 | I81: =SUM(I78:I80) -> 3326.7089 | ... M81: =SUM(M78:M80) -> #REF! | O81: =(H81/C81)^(1/5)-1 -> 0.56708884 | P81: =(M81/H81)^(1/5)-1 -> #REF! | Q81: =(H81/F81)^(1/2)-1 -> 0.30760895 | R81: =(K81/I81)^(1/2)-1 -> 0.30388595 | S81: =(K81/H81)^(1/3)-1 -> 0.40487409 | U81: =+Segment!V65 -> 427.6652 | V81: =+Segment!W65 -> 384.39832 | W81: =+Segment!X65 -> 667.23321 | X81: =+Segment!Y65 -> 525.7272 | Y81: =+Segment!Z65 -> 754.62978 | Z81: =+Segment!AA65 -> 685.89079 | AA81: =+Segment!AB65 -> 1169.429 | AB81: =+Segment!AC65 -> 870.34376 | AD81: =SUM(AD78:AD80) -> 146.19566 | AE81: =SUM(AE78:AE80) -> 281.46954 | AF81: =SUM(AF78:AF80) -> 253.49404 | AG81: =SUM(AG78:AG80) -> 130.90428 | AH81: =SUM(AH78:AH80) -> 337.26877 | AI81: =SUM(AI78:AI80) -> 329.96444 | AJ81: =SUM(AJ78:AJ80) -> 307.45771 | AK81: =SUM(AK78:AK80) -> 218.26949 | ... BE81: =SUM(BE78:BE80) -> 1061.365
A82: One-off's after tax | C82: =+C83-C81 -> -28.20334 | D82: =+D83-D81 -> 24.68219 | E82: =+E83-E81 -> -7.1518158 | U82: 0 | V82: 0 | W82: 0 | X82: 0 | Y82: 0 | Z82: 0 | AA82: 0 | AB82: 0 | AD82: 0 | AE82: 0 | AF82: 0 | AG82: 0 | AH82: 0 | AI82: 0 | AJ82: 0 | AK82: 0 | AL82: 0 | AM82: 0 | AN82: 0 | AO82: 0 | AP82: 0 | AQ82: 0 | AR82: 0 | AS82: 0 | AT82: 0 | AU82: 0 | AV82: 0 | AW82: 0 | AX82: 0 | AY82: 0 | AZ82: 0 | BA82: 0 | BB82: 0 | BC82: 0 | BD82: 0 | BE82: 0
A83: Recurring NPAT | B83: =B81+B82 -> 296.1658 | C83: =18762.76/100 -> 187.6276 | D83: =59525.61/100 -> 595.2561 | E83: =80491.17/100 -> 804.9117 | F83: =F81+F82 -> 1192.9604 | G83: =G81+G82 -> 1440.5206 | H83: =H81+H82 -> 2039.7728 | I83: =I81+I82 -> 3326.7089 | J83: =J81+J82 -> 4562.8478 | K83: =K81+K82 -> 5655.7995 | L83: =L81+L82 -> 6753.999 | M83: =M81+M82 -> #REF! | O83: =(H83/C83)^(1/5)-1 -> 0.61159909 | P83: =(M83/H83)^(1/5)-1 -> #REF! | Q83: =(H83/F83)^(1/2)-1 -> 0.30760895 | R83: =(K83/I83)^(1/2)-1 -> 0.30388595 | S83: =(K83/H83)^(1/3)-1 -> 0.40487409 | U83: =U81+U82 -> 427.6652 | V83: =V81+V82 -> 384.39832 | W83: =W81+W82 -> 667.23321 | X83: =X81+X82 -> 525.7272 | Y83: =Y81+Y82 -> 754.62978 | Z83: =Z81+Z82 -> 685.89079 | AA83: =AA81+AA82 -> 1169.429 | AB83: =AB81+AB82 -> 870.34376 | AD83: =SUM(AD81:AD82) -> 146.19566 | AE83: =SUM(AE81:AE82) -> 281.46954 | AF83: =SUM(AF81:AF82) -> 253.49404 | AG83: =SUM(AG81:AG82) -> 130.90428 | AH83: =SUM(AH81:AH82) -> 337.26877 | AI83: =SUM(AI81:AI82) -> 329.96444 | AJ83: =SUM(AJ81:AJ82) -> 307.45771 | AK83: =SUM(AK81:AK82) -> 218.26949 | ... BE83: =SUM(BE81:BE82) -> 1061.365
A84: Cross check | B84: =+Wind!U49-'Summary financial'!B81 -> 0.0031 | C84: =+Wind!V49-'Summary financial'!C81 -> 3.823e-05 | D84: =+Wind!W49-'Summary financial'!D81 -> -1.423e-05 | E84: =+Wind!X49-'Summary financial'!E81 -> -4.8400003e-06 | AD84: =+Quarterly!D70-'Summary financial'!AD81 -> 7.4493888 | AE84: =+Quarterly!E70-'Summary financial'!AE81 -> 6.1925112 | AF84: =+Quarterly!F70-'Summary financial'!AF81 -> 9.241589 | AG84: =+Quarterly!G70-'Summary financial'!AG81 -> -22.883494 | AH84: =+Quarterly!H70-'Summary financial'!AH81 -> 4.6206927 | AI84: =+Quarterly!I70-'Summary financial'!AI81 -> 3.9722284 | AJ84: =+Quarterly!J70-'Summary financial'!AJ81 -> 12.75011
A85: WA Shares - Basic | B85: =+Model!C70 -> 150.8197 | C85: =+Model!D70 -> 455 | D85: =+Model!E70 -> 468 | E85: =+Model!F70 -> 468 | F85: =+Model!G70 -> 520.013 | G85: =+Model!H70 -> 520.013 | H85: =+Model!I70 -> 520.013 | I85: =+Model!J70 -> 520.013 | ... L85: =+Model!M70 -> 520.013 | M85: =+Model!#REF! -> #REF! | U85: =+G85 -> 520.013 | V85: =+H85 -> 520.013 | W85: =+I85 -> 520.013 | X85: =+J85 -> 520.013 | Y85: =+N85 -> 0 | Z85: =+S85 -> 0 | AA85: =+T85 -> 0 | AB85: =+U85 -> 520.013 | AD85: =+E85 -> 468 | AE85: =+AD85 -> 468 | AF85: =+AE85 -> 468 | AG85: =+AF85 -> 468 | AH85: =+F85 -> 520.013 | AI85: =+AH85 -> 520.013 | AJ85: =+AI85 -> 520.013 | AK85: =+AJ85 -> 520.013 | AL85: =+AK85 -> 520.013 | AM85: =+AL85 -> 520.013 | AN85: =+AM85 -> 520.013 | AO85: =+AN85 -> 520.013 | AP85: =+AO85 -> 520.013 | ... BE85: =+BD85 -> 520.013
A86: WA Shares - Diluted | B86: =+Model!C71 -> 150.8197 | C86: =+Model!D71 -> 455 | D86: =+Model!E71 -> 468 | E86: =+Model!F71 -> 468 | F86: =+Model!G71 -> 520.013 | G86: =+Model!H71 -> 520.013 | H86: =+Model!I71 -> 520.013 | I86: =+Model!J71 -> 520.013 | ... L86: =+Model!M71 -> 520.013 | M86: =+Model!#REF! -> #REF! | U86: =+G86 -> 520.013 | V86: =+H86 -> 520.013 | W86: =+I86 -> 520.013 | X86: =+J86 -> 520.013 | Y86: =+N86 -> 0 | Z86: =+S86 -> 0 | AA86: =+T86 -> 0 | AB86: =+U86 -> 520.013 | AD86: =+E86 -> 468 | AE86: =+AD86 -> 468 | AF86: =+AE86 -> 468 | AG86: =+AF86 -> 468 | AH86: =+F86 -> 520.013 | AI86: =+AH86 -> 520.013 | AJ86: =+AI86 -> 520.013 | AK86: =+AJ86 -> 520.013 | AL86: =+AK86 -> 520.013 | AM86: =+AL86 -> 520.013 | AN86: =+AM86 -> 520.013 | AO86: =+AN86 -> 520.013 | AP86: =+AO86 -> 520.013 | ... BE86: =+BD86 -> 520.013
A88: EPS - Basic (Rmb/Sh) | B88: =B81/B85 -> 1.9637077 | C88: =C81/C85 -> 0.47435372 | D88: =D81/D85 -> 1.219175 | E88: =E81/E85 -> 1.7351785 | F88: =F81/F85 -> 2.2940973 | G88: =G81/G85 -> 2.7701626 | H88: =H81/H85 -> 3.9225419 | I88: =I81/I85 -> 6.3973571 | ... M88: =M81/M85 -> #REF! | O88: =(H88/C88)^(1/5)-1 -> 0.52578401 | P88: =(M88/H88)^(1/5)-1 -> #REF! | Q88: =(H88/F88)^(1/2)-1 -> 0.30760895 | R88: =(K88/I88)^(1/2)-1 -> 0.30388595 | S88: =(K88/H88)^(1/3)-1 -> 0.40487409 | U88: =U81/U85 -> 0.82241252 | V88: =V81/V85 -> 0.73920905 | W88: =W81/W85 -> 1.2831087 | X88: =X81/X85 -> 1.0109886 | Y88: =Y81/Y85 -> #DIV/0! | Z88: =Z81/Z85 -> #DIV/0! | AA88: =AA81/AA85 -> #DIV/0! | AB88: =AB81/AB85 -> 1.6736962 | AD88: =AD81/AD85 -> 0.31238389 | AE88: =AE81/AE85 -> 0.60143064 | AF88: =AF81/AF85 -> 0.54165393 | AG88: =AG81/AG85 -> 0.27970999 | AH88: =AH81/AH85 -> 0.64857758 | AI88: =AI81/AI85 -> 0.63453113 | AJ88: =AJ81/AJ85 -> 0.59125004 | AK88: =AK81/AK85 -> 0.41973852 | ... BE88: =BE81/BE85 -> 2.0410355
A89: EPS - Diluted (Rmb/Sh) | B89: =B81/B86 -> 1.9637077 | C89: =C81/C86 -> 0.47435372 | D89: =D81/D86 -> 1.219175 | E89: =E81/E86 -> 1.7351785 | F89: =F81/F86 -> 2.2940973 | G89: =G81/G86 -> 2.7701626 | H89: =H81/H86 -> 3.9225419 | I89: =I81/I86 -> 6.3973571 | ... M89: =M81/M86 -> #REF! | O89: =(H89/C89)^(1/5)-1 -> 0.52578401 | P89: =(M89/H89)^(1/5)-1 -> #REF! | Q89: =(H89/F89)^(1/2)-1 -> 0.30760895 | R89: =(K89/I89)^(1/2)-1 -> 0.30388595 | S89: =(K89/H89)^(1/3)-1 -> 0.40487409 | U89: =U81/U86 -> 0.82241252 | V89: =V81/V86 -> 0.73920905 | W89: =W81/W86 -> 1.2831087 | X89: =X81/X86 -> 1.0109886 | Y89: =Y81/Y86 -> #DIV/0! | Z89: =Z81/Z86 -> #DIV/0! | AA89: =AA81/AA86 -> #DIV/0! | AB89: =AB81/AB86 -> 1.6736962 | AD89: =AD81/AD86 -> 0.31238389 | AE89: =AE81/AE86 -> 0.60143064 | AF89: =AF81/AF86 -> 0.54165393 | AG89: =AG81/AG86 -> 0.27970999 | AH89: =AH81/AH86 -> 0.64857758 | AI89: =AI81/AI86 -> 0.63453113 | AJ89: =AJ81/AJ86 -> 0.59125004 | AK89: =AK81/AK86 -> 0.41973852 | ... BE89: =BE81/BE86 -> 2.0410355
AZ90: =SUM(AZ83:BA83)/SUM(AV83:AW83)-1 -> 0.37140774
A91: Growth
A92: Sales | C92: =C64/B64-1 -> 0.068122893 | D92: =D64/C64-1 -> 0.3855732 | E92: =E64/D64-1 -> 0.17814742 | F92: =F64/E64-1 -> 0.40724388 | G92: =G64/F64-1 -> 0.21891747 | H92: =H64/G64-1 -> 0.32419494 | I92: =I64/H64-1 -> 0.40629862 | J92: =J64/I64-1 -> 0.32534294 | ... M92: =M64/L64-1 -> #REF! | W92: =W64/U64-1 -> 0.4911186 | X92: =X64/V64-1 -> 0.32402887 | Y92: =Y64/W64-1 -> 0.16539081 | Z92: =Z64/X64-1 -> 0.27872495 | AA92: =AA64/Y64-1 -> 0.27239252 | AB92: =AB64/Z64-1 -> 0.37694585 | AH92: =AH64/AD64-1 -> 0.83372486 | AI92: =AI64/AE64-1 -> 0.28299724 | AJ92: =AJ64/AF64-1 -> 0.19300544 | AK92: =AK64/AG64-1 -> 0.54946027 | AL92: =AL64/AH64-1 -> 0.17255171 | AM92: =AM64/AI64-1 -> 0.15917357 | AN92: =AN64/AJ64-1 -> 0.25300085 | AO92: =AO64/AK64-1 -> 0.31280246 | ... BE92: =BE64/BA64-1 -> 0.14377511
A93: GP | C93: =C66/B66-1 -> 0.024567675 | D93: =D66/C66-1 -> 0.40873577 | E93: =E66/D66-1 -> 0.17470477 | F93: =F66/E66-1 -> 0.33999127 | G93: =G66/F66-1 -> 0.1626708 | H93: =H66/G66-1 -> 0.34756578 | I93: =I66/H66-1 -> 0.46301495 | J93: =J66/I66-1 -> 0.32832537 | ... M93: =M66/L66-1 -> #REF! | W93: =W66/U66-1 -> 0.59515773 | X93: =X66/V66-1 -> 0.088558487 | Y93: =Y66/W66-1 -> 0.0011941659 | Z93: =Z66/X66-1 -> 0.39583393 | AA93: =AA66/Y66-1 -> 0.2850305 | AB93: =AB66/Z66-1 -> 0.41233368 | AH93: =AH66/AD66-1 -> 0.84817153 | AI93: =AI66/AE66-1 -> 0.42648287 | AJ93: =AJ66/AF66-1 -> 0.16230932 | AK93: =AK66/AG66-1 -> -0.043005391 | AL93: =AL66/AH66-1 -> 0.022132968 | AM93: =AM66/AI66-1 -> -0.016891467 | AN93: =AN66/AJ66-1 -> 0.087230441 | AO93: =AO66/AK66-1 -> 1.0644592 | ... BE93: =BE66/BA66-1 -> 0.14302634
A94: SG&A | C94: =C67/B67-1 -> 0.1737958 | D94: =D67/C67-1 -> 0.090668868 | E94: =E67/D67-1 -> 0.042148133 | F94: =F67/E67-1 -> 0.32782094 | G94: =G67/F67-1 -> 0.058379223 | H94: =H67/G67-1 -> 0.35763308 | I94: =I67/H67-1 -> 0.33185627 | J94: =J67/I67-1 -> 0.25913628 | ... M94: =M67/L67-1 -> #REF! | W94: =W67/U67-1 -> 0.7137273 | X94: =X67/V67-1 -> 0.021937647 | Y94: =Y67/W67-1 -> -0.091714361 | Z94: =Z67/X67-1 -> 0.25788399 | AA94: =AA67/Y67-1 -> 0.23307562 | AB94: =AB67/Z67-1 -> 0.4771812 | AH94: =AH67/AD67-1 -> 0.64699556 | AI94: =AI67/AE67-1 -> 0.76575434 | AJ94: =AJ67/AF67-1 -> 0.1388688 | AK94: =AK67/AG67-1 -> -0.14485885 | AL94: =AL67/AH67-1 -> 0.047110407 | AM94: =AM67/AI67-1 -> -0.19266888 | AN94: =AN67/AJ67-1 -> -0.0016719523 | AO94: =AO67/AK67-1 -> 0.75097099 | ... BE94: =BE67/BA67-1 -> -0.17293012
A95: Selling Exp. | C95: =C68/B68-1 -> 0.17473562 | D95: =D68/C68-1 -> 0.014588499 | E95: =E68/D68-1 -> 0.057700821 | F95: =F68/E68-1 -> 0.31531497 | G95: =G68/F68-1 -> 0.059114763 | H95: =H68/G68-1 -> 0.34941258 | I95: =I68/H68-1 -> 0.37092552 | J95: =J68/I68-1 -> 0.25722501 | ... M95: =M68/L68-1 -> #REF! | AH95: =AH68/AD68-1 -> 0.66808124 | AI95: =AI68/AE68-1 -> 0.84497653 | AJ95: =AJ68/AF68-1 -> 0.10786962 | AK95: =AK68/AG68-1 -> -0.25150988 | AL95: =AL68/AH68-1 -> 0.0051983495 | AM95: =AM68/AI68-1 -> -0.21128716 | AN95: =AN68/AJ68-1 -> -0.04091995 | AO95: =AO68/AK68-1 -> 1.1331856 | ... BE95: =BE68/BA68-1 -> -0.26403381
A96: Admin Exp. | C96: =C69/B69-1 -> 0.29641586 | D96: =D69/C69-1 -> 0.59618593 | E96: =E69/D69-1 -> -0.042827771 | F96: =F69/E69-1 -> 0.34179242 | G96: =G69/F69-1 -> 0.016431979 | H96: =H69/G69-1 -> 0.4133433 | I96: =I69/H69-1 -> 0.15447344 | J96: =J69/I69-1 -> 0.24796531 | ... M96: =M69/L69-1 -> #REF! | AH96: =AH69/AD69-1 -> 0.40081834 | AI96: =AI69/AE69-1 -> 0.53446732 | AJ96: =AJ69/AF69-1 -> 0.33915163 | AK96: =AK69/AG69-1 -> 0.12320347 | AL96: =AL69/AH69-1 -> 0.24008101 | AM96: =AM69/AI69-1 -> -0.18495891 | AN96: =AN69/AJ69-1 -> 0.17691782 | AO96: =AO69/AK69-1 -> -0.094577529 | ... BE96: =BE69/BA69-1 -> 0.21972044
A97: Operating profit (GP less SG&A) | C97: =(C66+C67)/(B66+B67)-1 -> -0.36022256 | D97: =(D66+D67)/(C66+C67)-1 -> 1.913455 | E97: =(E66+E67)/(D66+D67)-1 -> 0.40946421 | F97: =(F66+F67)/(E66+E67)-1 -> 0.355928 | G97: =(G66+G67)/(F66+F67)-1 -> 0.29640705 | H97: =(H66+H67)/(G66+G67)-1 -> 0.33702645 | I97: =(I66+I67)/(H66+H67)-1 -> 0.6024395 | J97: =(J66+J67)/(I66+I67)-1 -> 0.38945553 | ... M97: =(M66+M67)/(L66+L67)-1 -> #REF! | W97: =(W66+W67)/(U66+U67)-1 -> 0.47412707 | X97: =(X66+X67)/(V66+V67)-1 -> 0.20100715 | Y97: =(Y66+Y67)/(W66+W67)-1 -> 0.11144568 | Z97: =(Z66+Z67)/(X66+X67)-1 -> 0.59396132 | AA97: =(AA66+AA67)/(Y66+Y67)-1 -> 0.33541414 | AB97: =(AB66+AB67)/(Z66+Z67)-1 -> 0.33883505 | AH97: =AH70/AD70-1 -> 1.0972949 | AI97: =AI70/AE70-1 -> 0.12189363 | AJ97: =AJ70/AF70-1 -> 0.19416668 | AK97: =AK70/AG70-1 -> 0.21951185 | AL97: =AL70/AH70-1 -> -0.0021565641 | AM97: =AM70/AI70-1 -> 0.2314841 | AN97: =AN70/AJ70-1 -> 0.20246024 | AO97: =AO70/AK70-1 -> 1.6310312 | ... BE97: =BE70/BA70-1 -> 0.48167525
A98: EBIT | C98: =C72/B72-1 -> -0.36532933 | D98: =D72/C72-1 -> 1.9138491 | E98: =E72/D72-1 -> 0.42349111 | F98: =F72/E72-1 -> 0.47084603 | G98: =G72/F72-1 -> 0.20282204 | H98: =H72/G72-1 -> 0.34327161 | I98: =I72/H72-1 -> 0.59724232 | J98: =J72/I72-1 -> 0.43040001 | ... M98: =M72/L72-1 -> #REF! | W98: =W72/U72-1 -> 0.48383087 | X98: =X72/V72-1 -> 0.46158427 | Y98: =Y72/W72-1 -> 0.14224288 | Z98: =Z72/X72-1 -> 0.28201359 | AA98: =AA72/Y72-1 -> 0.36500427 | AB98: =AB72/Z72-1 -> 0.32036207 | AH98: =AH72/AD72-1 -> 1.0932224 | AI98: =AI72/AE72-1 -> 0.14196166 | AJ98: =AJ72/AF72-1 -> 0.23113516 | AK98: =AK72/AG72-1 -> 1.0399422 | AL98: =AL72/AH72-1 -> 0.019661345 | AM98: =AM72/AI72-1 -> 0.26983024 | AN98: =AN72/AJ72-1 -> 0.19688989 | AO98: =AO72/AK72-1 -> 0.42422025 | ... BE98: =BE72/BA72-1 -> 0.30901779
A99: Reported NPAT | C99: =+C81/B81-1 -> -0.27124962 | D99: =+D81/C81-1 -> 1.643615 | E99: =+E81/D81-1 -> 0.42323983 | F99: =+F81/E81-1 -> 0.46904815 | G99: =+G81/F81-1 -> 0.2075175 | H99: =+H81/G81-1 -> 0.415997 | I99: =+I81/H81-1 -> 0.63092127 | J99: =+J81/I81-1 -> 0.37158013 | ... M99: =+M81/L81-1 -> #REF! | W99: =+W81/U81-1 -> 0.56017653 | X99: =+X81/V81-1 -> 0.3676626 | Y99: =+Y81/W81-1 -> 0.13098354 | Z99: =+Z81/X81-1 -> 0.30465153 | AA99: =+AA81/Y81-1 -> 0.54967254 | AB99: =+AB81/Z81-1 -> 0.26892469 | AH99: =AH83/AD83-1 -> 1.3069685 | AI99: =AI83/AE83-1 -> 0.17229181 | AJ99: =AJ83/AF83-1 -> 0.21287944 | AK99: =AK83/AG83-1 -> 0.66739769 | AL99: =AL83/AH83-1 -> 0.021882094 | AM99: =AM83/AI83-1 -> 0.24250014 | AN99: =AN83/AJ83-1 -> 0.33636679 | AO99: =AO83/AK83-1 -> 0.25997693 | ... BE99: =BE83/BA83-1 -> 0.32215273
A100: Recurring NPAT | C100: =C83/B83-1 -> -0.36647783 | D100: =D83/C83-1 -> 2.1725402 | E100: =E83/D83-1 -> 0.35221075 | F100: =F83/E83-1 -> 0.48210097 | G100: =G83/F83-1 -> 0.2075175 | H100: =H83/G83-1 -> 0.415997 | I100: =I83/H83-1 -> 0.63092127 | J100: =J83/I83-1 -> 0.37158013 | ... M100: =M83/L83-1 -> #REF!
A102: Margins
A103: GP margin | B103: =B66/B64 -> 0.47922117 | C103: =C66/C64 -> 0.4596798 | D103: =D66/D64 -> 0.46736425 | E103: =E66/E64 -> 0.46599857 | F103: =F66/F64 -> 0.44372835 | G103: =G66/G64 -> 0.42325261 | H103: =H66/H64 -> 0.43072263 | I103: =I66/I64 -> 0.44809377 | ... M103: =M66/M64 -> #REF! | U103: =U66/U64 -> 0.46439766 | V103: =V66/V64 -> 0.46758688 | W103: =W66/W64 -> 0.49679987 | X103: =X66/X64 -> 0.38442943 | Y103: =Y66/Y64 -> 0.42680372 | Z103: =Z66/Z64 -> 0.41963648 | AA103: =AA66/AA64 -> 0.43104293 | AB103: =AB66/AB64 -> 0.43042124 | AD103: =AD66/AD64 -> 0.49155111 | AE103: =AE66/AE64 -> 0.44790289 | AF103: =AF66/AF64 -> 0.47377159 | AG103: =AG66/AG64 -> 0.45694582 | AH103: =AH66/AH64 -> 0.4954237 | AI103: =AI66/AI64 -> 0.49799468 | AJ103: =AJ66/AJ64 -> 0.46158141 | AK103: =AK66/AK64 -> 0.28222388 | ... BE103: =BE66/BE64 -> 0.43831414
A104: Operating profit (GP less SG&A) | B104: =SUM(B66,B67)/B64 -> 0.13391539 | C104: =SUM(C66,C67)/C64 -> 0.080211786 | D104: =SUM(D66,D67)/D64 -> 0.16866191 | E104: =SUM(E66,E67)/E64 -> 0.2017769 | F104: =SUM(F66,F67)/F64 -> 0.194419 | G104: =SUM(G66,G67)/G64 -> 0.20677869 | H104: =SUM(H66,H67)/H64 -> 0.20878238 | I104: =SUM(I66,I67)/I64 -> 0.23790192 | ... M104: =SUM(M66,M67)/M64 -> #REF! | U104: =SUM(U66,U67)/U64 -> 0.22981376 | V104: =SUM(V66,V67)/V64 -> 0.17396056 | W104: =SUM(W66,W67)/W64 -> 0.22719499 | X104: =SUM(X66,X67)/X64 -> 0.15779707 | Y104: =SUM(Y66,Y67)/Y64 -> 0.21667829 | Z104: =SUM(Z66,Z67)/Z64 -> 0.19669783 | AA104: =SUM(AA66,AA67)/AA64 -> 0.22741037 | AB104: =SUM(AB66,AB67)/AB64 -> 0.19125367 | AD104: =SUM(AD66,AD67)/AD64 -> 0.21960565 | AE104: =SUM(AE66,AE67)/AE64 -> 0.23601483 | AF104: =SUM(AF66,AF67)/AF64 -> 0.2008296 | AG104: =SUM(AG66,AG67)/AG64 -> 0.12773121 | AH104: =SUM(AH66,AH67)/AH64 -> 0.25117061 | AI104: =SUM(AI66,AI67)/AI64 -> 0.20637888 | AJ104: =SUM(AJ66,AJ67)/AJ64 -> 0.20102509 | AK104: =SUM(AK66,AK67)/AK64 -> 0.10053161 | ... BE104: =SUM(BE66,BE67)/BE64 -> 0.27423946
A105: EBIT margin | B105: =B72/B64 -> 0.13372712 | C105: =C72/C64 -> 0.079459659 | D105: =D72/D64 -> 0.16710301 | E105: =E72/E64 -> 0.20190143 | F105: =F72/F64 -> 0.21102662 | G105: =G72/G64 -> 0.20824008 | H105: =H72/H64 -> 0.21124003 | I105: =I72/I64 -> 0.23992168 | ... M105: =M72/M64 -> #REF! | U105: =U72/U64 -> 0.23021583 | V105: =V72/V64 -> 0.17331355 | W105: =W72/W64 -> 0.22909067 | X105: =X72/X64 -> 0.19131936 | Y105: =Y72/Y64 -> 0.22454028 | Z105: =Z72/Z64 -> 0.1918114 | AA105: =AA72/AA64 -> 0.24088356 | AB105: =AB72/AB64 -> 0.18392916 | AD105: =AD72/AD64 -> 0.21975508 | AE105: =AE72/AE64 -> 0.23527774 | AF105: =AF72/AF64 -> 0.20114739 | AG105: =AG72/AG64 -> 0.12894466 | AH105: =AH72/AH64 -> 0.25085348 | AI105: =AI72/AI64 -> 0.20941444 | AJ105: =AJ72/AJ64 -> 0.20757627 | AK105: =AK72/AK64 -> 0.16976211 | ... BE105: =BE72/BE64 -> 0.24282981
A106: Reported NPAT margin | B106: =B81/B64 -> 0.10414411 | C106: =C81/C64 -> 0.071054612 | D106: =D81/D64 -> 0.13556919 | E106: =E81/E64 -> 0.16377192 | F106: =F81/F64 -> 0.17096457 | G106: =G81/G64 -> 0.16936562 | H106: =H81/H64 -> 0.18110717 | I106: =I81/I64 -> 0.21003472 | ... M106: =M81/M64 -> #REF! | U106: =U81/U64 -> 0.17318148 | V106: =V81/V64 -> 0.15443638 | W106: =W81/W64 -> 0.181202 | X106: =X81/X64 -> 0.15952587 | Y106: =Y81/Y64 -> 0.17585215 | Z106: =Z81/Z64 -> 0.16276031 | AA106: =AA81/AA64 -> 0.21417389 | AB106: =AB81/AB64 -> 0.1499918 | AD106: =AD81/AD64 -> 0.15665787 | AE106: =AE81/AE64 -> 0.18321899 | AF106: =AF81/AF64 -> 0.16103712 | AG106: =AG81/AG64 -> 0.14307953 | AH106: =AH81/AH64 -> 0.19708778 | AI106: =AI81/AI64 -> 0.16740966 | AJ106: =AJ81/AJ64 -> 0.1637198 | AK106: =AK81/AK64 -> 0.15397005 | ... BE106: =BE81/BE64 -> 0.22371308
A108: Selling expense/Sales | B108: =B68/B$64 -> -0.29019185 | C108: =C68/C$64 -> -0.31915682 | D108: =D68/D$64 -> -0.23370316 | E108: =E68/E$64 -> -0.20981078 | F108: =F68/F$64 -> -0.19610478 | G108: =G68/G$64 -> -0.17039502 | H108: =H68/H$64 -> -0.17363998 | I108: =I68/I$64 -> -0.16927236 | ... M108: =M68/M$64 -> #REF! | U108: =U68/U$64 -> -0.18312 | V108: =V68/V$64 -> -0.23629163 | W108: =W68/W$64 -> -0.2168934 | X108: =X68/X$64 -> -0.17287683 | Y108: =Y68/Y$64 -> -0.16375048 | Z108: =Z68/Z$64 -> -0.17716122 | AA108: =AA68/AA$64 -> -0.15809625 | AB108: =AB68/AB$64 -> -0.18826645 | AD108: =AD68/AD$64 -> -0.21598347 | AE108: =AE68/AE$64 -> -0.16315658 | AF108: =AF68/AF$64 -> -0.22893231 | AG108: =AG68/AG$64 -> -0.24895365 | AH108: =AH68/AH$64 -> -0.1964733 | AI108: =AI68/AI$64 -> -0.23462253 | AJ108: =AJ68/AJ$64 -> -0.21259513 | AK108: =AK68/AK$64 -> -0.12026081 | ... BE108: =BE68/BE$64 -> -0.11748867
A109: Admin expense/Sales | B109: =B69/B$64 -> -0.03895791 | C109: =C69/C$64 -> -0.047284495 | D109: =D69/D$64 -> -0.05447193 | E109: =E69/E$64 -> -0.044255089 | F109: =F69/F$64 -> -0.042196767 | G109: =G69/G$64 -> -0.035187077 | H109: =H69/H$64 -> -0.037555966 | I109: =I69/I$64 -> -0.030830838 | ... M109: =M69/M$64 -> #REF! | U109: =U69/U$64 -> -0.04185129 | V109: =V69/V$64 -> -0.04663998 | W109: =W69/W$64 -> -0.041418988 | X109: =X69/X$64 -> -0.043065811 | Y109: =Y69/Y$64 -> -0.035270846 | Z109: =Z69/Z$64 -> -0.035101775 | AA109: =AA69/AA$64 -> -0.034644847 | AB109: =AB69/AB$64 -> -0.040295293 | AD109: =AD69/AD$64 -> -0.048683322 | AE109: =AE69/AE$64 -> -0.037701069 | AF109: =AF69/AF$64 -> -0.033932384 | AG109: =AG69/AG$64 -> -0.06850394 | AH109: =AH69/AH$64 -> -0.037190143 | AI109: =AI69/AI$64 -> -0.045090556 | AJ109: =AJ69/AJ$64 -> -0.038089188 | AK109: =AK69/AK$64 -> -0.049658494 | ... BE109: =BE69/BE$64 -> -0.037110731
A110: SG&A/Sales | B110: =SUM(B67)/B64 -> -0.34530578 | C110: =SUM(C67)/C64 -> -0.37946801 | D110: =SUM(D67)/D64 -> -0.29870233 | E110: =SUM(E67)/E64 -> -0.26422167 | F110: =SUM(F67)/F64 -> -0.24930936 | G110: =SUM(G67)/G64 -> -0.21647392 | H110: =SUM(H67)/H64 -> -0.22194025 | I110: =SUM(I67)/I64 -> -0.21019185 | ... M110: =SUM(M67)/M64 -> #REF! | U110: =SUM(U67)/U64 -> -0.2345839 | V110: =SUM(V67)/V64 -> -0.29362633 | W110: =SUM(W67)/W64 -> -0.26960487 | X110: =SUM(X67)/X64 -> -0.22663237 | Y110: =SUM(Y67)/Y64 -> -0.21012542 | Z110: =SUM(Z67)/Z64 -> -0.22293866 | AA110: =SUM(AA67)/AA64 -> -0.20363255 | AB110: =SUM(AB67)/AB64 -> -0.23916757 | AD110: =SUM(AD67)/AD64 -> -0.27194545 | AE110: =SUM(AE67)/AE64 -> -0.21188806 | AF110: =SUM(AF67)/AF64 -> -0.27294199 | AG110: =SUM(AG67)/AG64 -> -0.32921461 | AH110: =SUM(AH67)/AH64 -> -0.24425309 | AI110: =SUM(AI67)/AI64 -> -0.2916158 | AJ110: =SUM(AJ67)/AJ64 -> -0.26055633 | AK110: =SUM(AK67)/AK64 -> -0.18169227 | ... BE110: =SUM(BE67)/BE64 -> -0.16407468
A111: Effective Tax Rate | B111: =B79/B78 -> -0.24022082 | C111: =C79/C78 -> -0.21035878 | D111: =D79/D78 -> -0.2252931 | E111: =E79/E78 -> -0.21124395 | F111: =F79/F78 -> -0.21179574 | G111: =G79/G78 -> -0.21540691 | H111: =H79/H78 -> -0.20916691 | I111: =I79/I78 -> -0.19012026 | ... M111: =M79/M78 -> #REF! | U111: =U79/U78 -> -0.22425752 | V111: =V79/V78 -> -0.19624275 | W111: =W79/W78 -> -0.21619386 | X111: =X79/X78 -> -0.20614222 | Y111: =Y79/Y78 -> -0.21475459 | Z111: =Z79/Z78 -> -0.21612335 | AA111: =AA79/AA78 -> -0.20092288 | AB111: =AB79/AB78 -> -0.21050675 | AD111: =AD79/AD78 -> -0.2332584 | AE111: =AE79/AE78 -> -0.21949855 | AF111: =AF79/AF78 -> -0.21648557 | AG111: =AG79/AG78 -> -0.15391225 | AH111: =AH79/AH78 -> -0.2223046 | AI111: =AI79/AI78 -> -0.2098478 | AJ111: =AJ79/AJ78 -> -0.21298526 | AK111: =AK79/AK78 -> -0.19629864 | ... BE111: =BE79/BE78 -> -0.1688665
A114: OCF | C114: =Model!D204 -> 194.93968 | D114: =Model!E204 -> 1210.9814 | E114: =Model!F204 -> 1340.3632 | F114: =Model!G204 -> 2076.844 | G114: =Model!H204 -> 2026.1051 | H114: =Model!I204 -> 3281.2697 | I114: =Model!J204 -> 5789.4085 | J114: =Model!K204 -> 5614.9213 | ... L114: =Model!M204 -> 7998.9832 | M114: =Model!#REF! -> #REF!
A115: As % of sales | C115: =C114/C$64 -> 0.06417691 | D115: =D114/D$64 -> 0.28773095 | E115: =E114/E$64 -> 0.27031611 | F115: =F114/F$64 -> 0.29763498 | G115: =G114/G$64 -> 0.23821426 | H115: =H114/H$64 -> 0.29133709 | I115: =I114/I$64 -> 0.36551946 | J115: =J114/J$64 -> 0.26748024 | ... M115: =M114/M$64 -> #REF!
...

Sheet Act Vs Est
A2: Do not delete Column A & B | C2: =Coversheet!B6 -> 605499.SS
C3: =Coversheet!B7 -> Eastroc Beverage
D5: 2017 | E5: 2018 | F5: 2019 | G5: 2020 | H5: 2021 | I5: 2022 | J5: 2023 | K5: 2024 | L5: 2024 | Q5: 1Q20 | R5: 2Q20 | S5: 3Q20 | T5: 4Q20 | U5: 1Q21 | V5: 2Q21 | W5: 3Q21 | X5: 4Q21 | Y5: 1Q22 | Z5: 2Q22 | AA5: 3Q22 | AB5: 4Q22 | AC5: 1Q23 | AD5: 2Q23 | AE5: 3Q23 | AF5: 4Q23 | AG5: 1Q24 | AH5: 2Q24 | AI5: 3Q24 | AJ5: 4Q24 | AK5: 1Q25 | AL5: 2Q25 | AM5: 3Q25 | AN5: 3Q25
C6: Summary P&L (Rmb mn) | D6: Actual | E6: Actual | F6: Actual | G6: Actual | H6: Actual | I6: Actual | J6: Actual | K6: Actual | L6: GSe | N6: Diff | O6: yoy | Q6: Actual | R6: Actual | S6: Actual | T6: Actual | U6: Actual | V6: Actual | W6: Actual | X6: Actual | Y6: Actual | Z6: Actual | AA6: Actual | AB6: Actual | AC6: Actual | AD6: Actual | AE6: Actual | AF6: Actual | AG6: Actual | AH6: Actual | AI6: Actual | AJ6: Actual | AK6: Actual | AL6: Actual | AM6: Actual | AN6: GSe | AP6: Diff | AQ6: yoy
A7: Linked to Model | B7: Linked to Raw Data | AS7: Check actual | AT7: Check Gse
A8: =Model!B13 -> Total sales/revenues | B8: ='Raw Data'!B8 -> Turnover | C8: Total revenues | D8: =Segment!F9 -> 2843.8076 | E8: =Segment!G9 -> 3037.536 | F8: =Segment!H9 -> 4208.7285 | G8: =Segment!I9 -> 4958.5026 | H8: =Segment!J9 -> 6977.8225 | I8: =Segment!K9 -> 8505.3897 | J8: =Segment!L9 -> 11262.794 | K8: =Segment!M9 -> 15838.852 | L8: 16329.345 | N8: =K8/L8-1 -> -0.030037541 | O8: =+K8/J8-1 -> 0.40629862 | Q8: =Segment!BB9 -> 933.21619 | R8: =Segment!BC9 -> 1536.2465 | S8: =Segment!BD9 -> 1574.1342 | T8: =Segment!BE9 -> 914.90569 | U8: =Segment!BF9 -> 1711.2617 | V8: =Segment!BG9 -> 1971 | W8: =Segment!BH9 -> 1877.9507 | X8: =Segment!BI9 -> 1417.61 | ... AM8: =Segment!BX9 -> 6107.34 | AN8: 6137.3417 | AP8: =AM8/AN8-1 -> -0.0048883778 | AQ8: =AM8/AI8-1 -> 0.30359623 | AR8: =SUM(AG8:AJ8) -> 15838.852 | AS8: =AR8=K8 -> TRUE | AT8: =SUM(AG8:AI8,#REF!)=L8 -> #REF!
AR9: =SUM(AF9:AI9) -> 0
A10: =Model!B16 -> COGS | B10: ='Raw Data'!B15 -> COGS | C10: COGS | D10: =-Segment!F23 -> -1480.9948 | E10: =-Segment!G23 -> -1641.2421 | F10: =-Segment!H23 -> -2241.7193 | G10: =-Segment!I23 -> -2647.8475 | H10: =-Segment!J23 -> -3881.5648 | I10: =-Segment!K23 -> -4905.4613 | J10: =-Segment!L23 -> -6411.6538 | K10: =-Segment!M23 -> -8741.561 | L10: -8969.8905 | N10: =K10/L10-1 -> -0.0254551 | O10: =+K10/J10-1 -> 0.36338632 | Q10: =-Segment!BB23 -> -474.49274 | R10: =-Segment!BC23 -> -848.15726 | S10: =-Segment!BD23 -> -828.35415 | T10: =-Segment!BE23 -> -496.84336 | U10: =-Segment!BF23 -> -863.46211 | V10: =-Segment!BG23 -> -989.4525 | W10: =-Segment!BH23 -> -1011.1236 | X10: =-Segment!BI23 -> -1017.5266 | ... AM10: =-Segment!BX23 -> -3346.3351 | AN10: -3326.4392 | AP10: =AM10/AN10-1 -> 0.0059811435 | AQ10: =AM10/AI10-1 -> 0.31796203 | AR10: =SUM(AG10:AJ10) -> -8741.561 | AS10: =AR10=K10 -> TRUE | AT10: =SUM(AG10:AI10,#REF!)=L10 -> #REF!
C11: Gross profit | D11: =D10+D8 -> 1362.8128 | E11: =E10+E8 -> 1396.2939 | F11: =F10+F8 -> 1967.0092 | G11: =G10+G8 -> 2310.6551 | H11: =H10+H8 -> 3096.2577 | I11: =I10+I8 -> 3599.9284 | J11: =J10+J8 -> 4851.1403 | K11: =K10+K8 -> 7097.2908 | L11: 7359.4547 | N11: =K11/L11-1 -> -0.035622736 | O11: =+K11/J11-1 -> 0.46301495 | Q11: =Q10+Q8 -> 458.72345 | R11: =R10+R8 -> 688.08925 | S11: =S10+S8 -> 745.78008 | T11: =T10+T8 -> 418.06233 | U11: =U10+U8 -> 847.79962 | V11: =V10+V8 -> 981.54753 | W11: =W10+W8 -> 866.82714 | X11: =X10+X8 -> 400.0834 | ... AM11: =AM10+AM8 -> 2761.0049 | AN11: 2810.9025 | AP11: =AM11/AN11-1 -> -0.017751436 | AQ11: =AM11/AI11-1 -> 0.28659921 | AR11: =SUM(AG11:AJ11) -> 7097.2908 | AS11: =AR11=K11 -> TRUE | AT11: =SUM(AG11:AI11,#REF!)=L11 -> #REF!
A12: =Model!B23 -> SG&A | B12: ='Raw Data'!B23 -> SG&A | C12: SG&A | D12: =-(Segment!F47+Segment!F49) -> -936.0386 | E12: =-(Segment!G47+Segment!G49) -> -1113.0787 | F12: =-(Segment!H47+Segment!H49) -> -1212.8507 | G12: =-(Segment!I47+Segment!I49) -> -1259.7863 | H12: =-(Segment!J47+Segment!J49) -> -1662.8259 | I12: =-(Segment!K47+Segment!K49) -> -1748.5559 | J12: =-(Segment!L47+Segment!L49) -> -2378.6565 | K12: =-(Segment!M47+Segment!M49) -> -3169.4049 | L12: -3338.5171 | N12: =K12/L12-1 -> -0.050654903 | O12: =+K12/J12-1 -> 0.33243488 | Q12: =-(Segment!BB47+Segment!BB49) -> -246.99134 | R12: =-(Segment!BC47+Segment!BC49) -> -308.56686 | S12: =-(Segment!BD47+Segment!BD49) -> -413.78431 | T12: =-(Segment!BE47+Segment!BE49) -> -290.44376 | U12: =-(Segment!BF47+Segment!BF49) -> -399.85931 | V12: =-(Segment!BG47+Segment!BG49) -> -551.3145 | W12: =-(Segment!BH47+Segment!BH49) -> -470.77279 | X12: =-(Segment!BI47+Segment!BI49) -> -240.87931 | ... AM12: =-(Segment!BX47+Segment!BX49) -> -1105.4547 | AN12: -1172.2323 | AP12: =(AM12/AN12-1) -> -0.056966139 | AQ12: =AM12/AI12-1 -> 0.1390994 | AR12: =SUM(AG12:AJ12) -> -3169.4049 | AS12: =AR12=K12 -> TRUE | AT12: =SUM(AG12:AI12,#REF!)=L12 -> #REF!
C13: Selling expense | D13: =-(Segment!F47) -> -825.2498 | E13: =-(Segment!G47) -> -969.45034 | F13: =-(Segment!H47) -> -983.59316 | G13: =-(Segment!I47) -> -1040.3473 | H13: =-(Segment!J47) -> -1368.3844 | I13: =-(Segment!K47) -> -1449.2761 | J13: =-(Segment!L47) -> -1955.6714 | K13: =-(Segment!M47) -> -2681.0798 | L13: -2830.5284 | Q13: =-(Segment!BB47) -> -201.55927 | R13: =-(Segment!BC47) -> -250.64873 | S13: =-(Segment!BD47) -> -360.37018 | T13: =-(Segment!BE47) -> -227.76911 | U13: =-(Segment!BF47) -> -336.21724 | V13: =-(Segment!BG47) -> -462.44102 | W13: =-(Segment!BH47) -> -399.24318 | X13: =-(Segment!BI47) -> -170.48293 | ... AM13: =-(Segment!BX47) -> -931.82559 | AN13: -1000.3867 | AP13: =(AM13/AN13-1) -> -0.068534604 | AQ13: =AM13/AI13-1 -> 0.11339806 | AR13: =SUM(AG13:AJ13) -> -2681.0798 | AS13: =AR13=K13 -> TRUE | AT13: =SUM(AG13:AI13,#REF!)=L13 -> #REF!
C14: Admin expense | D14: =-(Segment!F49) -> -110.7888 | E14: =-(Segment!G49) -> -143.62836 | F14: =-(Segment!H49) -> -229.25756 | G14: =-(Segment!I49) -> -219.43897 | H14: =-(Segment!J49) -> -294.44155 | I14: =-(Segment!K49) -> -299.27981 | J14: =-(Segment!L49) -> -422.98511 | K14: =-(Segment!M49) -> -488.32508 | L14: -507.9887 | Q14: =-(Segment!BB49) -> -45.432064 | R14: =-(Segment!BC49) -> -57.918136 | S14: =-(Segment!BD49) -> -53.414128 | T14: =-(Segment!BE49) -> -62.674645 | U14: =-(Segment!BF49) -> -63.642069 | V14: =-(Segment!BG49) -> -88.873486 | W14: =-(Segment!BH49) -> -71.529616 | X14: =-(Segment!BI49) -> -70.396378 | ... AM14: =-(Segment!BX49) -> -173.62913 | AN14: -171.84557 | AP14: =(AM14/AN14-1) -> 0.010378856 | AQ14: =AM14/AI14-1 -> 0.30017053 | AR14: =SUM(AG14:AJ14) -> -488.32508 | AS14: =AR14=K14 -> TRUE | AT14: =SUM(AG14:AI14,#REF!)=L14 -> #REF!
A15: =Model!B27 -> Other operating expense | B15: ='Raw Data'!B27 -> Other operating gains/expenses | C15: Other operating expenses, net | D15: =-Segment!F45+Model!C27 -> -46.48 | E15: =-Segment!G45+Model!D27 -> -41.853673 | F15: =-Segment!H45+Model!E27 -> -50.867283 | G15: =-Segment!I45+Model!F27 -> -49.740057 | H15: =-Segment!J45+Model!G27 -> 39.074537 | I15: =-Segment!K45+Model!H27 -> -80.209477 | J15: =-Segment!L45+Model!I27 -> -93.330828 | K15: =-Segment!M45+Model!J27 -> -127.80209 | L15: -144.83013 | N15: =K15/L15-1 -> -0.11757249 | O15: =+K15/J15-1 -> 0.36934488 | Q15: =-Segment!BB45+Segment!BB54+Segment!BB55 -> -6.6531128 | R15: =-Segment!BC45+Segment!BC54+Segment!BC55 -> -18.077787 | S15: =-Segment!BD45+Segment!BD54+Segment!BD55 -> -15.362783 | T15: =-Segment!BE45+Segment!BE54+Segment!BE55 -> -9.6463742 | U15: =-Segment!BF45+Segment!BF54+Segment!BF55 -> -18.664352 | V15: =-Segment!BG45+Segment!BG54+Segment!BG55 -> -17.477149 | W15: =-Segment!BH45+Segment!BH54+Segment!BH55 -> -6.2363417 | X15: =-Segment!BI45+Segment!BI54+Segment!BI55 -> 81.45238 | ... AM15: =-Segment!BX45+Segment!BX54+Segment!BX55 -> 57.695611 | AN15: -56.096248 | AP15: =-(AM15/AN15-1) -> 2.028511 | AQ15: =-(AM15/AI15-1) -> 3.2574353 | AR15: =SUM(AG15:AJ15) -> -127.80209 | AS15: =AR15=K15 -> TRUE | AT15: =SUM(AG15:AI15,#REF!)=L15 -> #REF!
C16: EBIT | D16: =D8+SUM(D10,D12,D15) -> 380.2942 | E16: =E8+SUM(E10,E12,E15) -> 241.36158 | F16: =F8+SUM(F10,F12,F15) -> 703.29121 | G16: =G8+SUM(G10,G12,G15) -> 1001.1288 | H16: =H8+SUM(H10,H12,H15) -> 1472.5063 | I16: =I8+SUM(I10,I12,I15) -> 1771.163 | J16: =J8+SUM(J10,J12,J15) -> 2379.153 | K16: =K8+SUM(K10,K12,K15) -> 3800.0839 | L16: 3876.1075 | N16: =K16/L16-1 -> -0.019613391 | O16: =+K16/J16-1 -> 0.59724232 | Q16: =Q8+SUM(Q10,Q12,Q15) -> 205.079 | R16: =R8+SUM(R10,R12,R15) -> 361.4446 | S16: =S8+SUM(S10,S12,S15) -> 316.63299 | T16: =T8+SUM(T10,T12,T15) -> 117.9722 | U16: =U8+SUM(U10,U12,U15) -> 429.27595 | V16: =V8+SUM(V10,V12,V15) -> 412.75588 | W16: =W8+SUM(W10,W12,W15) -> 389.818 | X16: =X8+SUM(X10,X12,X15) -> 240.65647 | ... AM16: =AM8+SUM(AM10,AM12,AM15) -> 1713.2458 | AN16: 1582.574 | AP16: =AM16/AN16-1 -> 0.082569189 | AQ16: =AM16/AI16-1 -> 0.48984447 | AR16: =SUM(AG16:AJ16) -> 3800.0839 | AS16: =AR16=K16 -> TRUE | AT16: =SUM(AG16:AI16,#REF!)=L16 -> #REF!
AR17: =SUM(AG17:AJ17) -> 0 | AS17: =AR17=K17 -> TRUE | AT17: =SUM(AG17:AI17,#REF!)=L17 -> #REF!
A18: =Model!B33 -> Depreciation | B18: ='Raw Data'!B31 -> Depreciation | C18: Depreciation | D18: =Model!C$33 -> 0 | E18: =Model!D$33 -> -77.859575 | F18: =Model!E$33 -> -102.17591 | G18: =Model!F$33 -> -124.5853 | H18: =Model!G$33 -> -173.1049 | I18: =Model!H$33 -> -211.99102 | J18: =Model!I$33 -> -241.69914 | K18: =Model!J$33 -> -325.93172 | L18: -337.90731 | N18: =K18/L18-1 -> -0.035440471 | O18: =+K18/J18-1 -> 0.34850179 | Q18: =Model!$F$33/4 -> -31.146326 | R18: =Model!$F$33/4 -> -31.146326 | S18: =Model!$F$33/4 -> -31.146326 | T18: =Model!$F$33/4 -> -31.146326 | U18: =Model!$G$33/4 -> -43.276224 | V18: =Model!$G$33/4 -> -43.276224 | W18: =Model!$G$33/4 -> -43.276224 | X18: =Model!$G$33/4 -> -43.276224 | Y18: =Model!$G$33/4 -> -43.276224 | Z18: =Model!$G$33/4 -> -43.276224 | AA18: =Model!$G$33/4 -> -43.276224 | AB18: =Model!$G$33/4 -> -43.276224 | ... AF18: =Model!$G$33/4 -> -43.276224 | AG18: =Model!$J$33/4 -> -81.482929 | AH18: =Model!$J$33/4 -> -81.482929 | AI18: =Model!$J$33/4 -> -81.482929 | AJ18: =Model!$J$33/4 -> -81.482929 | AK18: =Model!$J$33/4 -> -81.482929 | AL18: =Model!$J$33/4 -> -81.482929 | AM18: =Model!$J$33/4 -> -81.482929 | AN18: -81.482929 | AP18: =AM18/AN18-1 -> 0 | AQ18: =AM18/AI18-1 -> 0 | AR18: =SUM(AG18:AJ18) -> -325.93172 | AS18: =AR18=K18 -> TRUE | AT18: =SUM(AG18:AI18,#REF!)=L18 -> #REF!
A19: =Model!B34 -> Amortization | B19: ='Raw Data'!B32 -> Amortization | C19: Amortization | D19: =Model!C$34 -> 0 | E19: =Model!D$34 -> -7.1119131 | F19: =Model!E$34 -> -7.5485512 | G19: =Model!F$34 -> -9.8574461 | H19: =Model!G$34 -> -12.007907 | I19: =Model!H$34 -> -11.95035 | J19: =Model!I$34 -> -12.33999 | K19: =Model!J$34 -> -17.11997 | L19: -18.608242 | N19: =K19/L19-1 -> -0.079979169 | O19: =+K19/J19-1 -> 0.38735683 | Q19: =Model!$F$34/4 -> -2.4643615 | R19: =Model!$F$34/4 -> -2.4643615 | S19: =Model!$F$34/4 -> -2.4643615 | T19: =Model!$F$34/4 -> -2.4643615 | U19: =Model!$G$34/4 -> -3.0019768 | V19: =Model!$G$34/4 -> -3.0019768 | W19: =Model!$G$34/4 -> -3.0019768 | X19: =Model!$G$34/4 -> -3.0019768 | Y19: =Model!$G$34/4 -> -3.0019768 | Z19: =Model!$G$34/4 -> -3.0019768 | AA19: =Model!$G$34/4 -> -3.0019768 | AB19: =Model!$G$34/4 -> -3.0019768 | ... AF19: =Model!$G$34/4 -> -3.0019768 | AG19: =Model!$J$34/4 -> -4.2799925 | AH19: =Model!$J$34/4 -> -4.2799925 | AI19: =Model!$J$34/4 -> -4.2799925 | AJ19: =Model!$J$34/4 -> -4.2799925 | AK19: =Model!$J$34/4 -> -4.2799925 | AL19: =Model!$J$34/4 -> -4.2799925 | AM19: =Model!$J$34/4 -> -4.2799925 | AN19: -4.2799925 | AP19: =AM19/AN19-1 -> 0 | AQ19: =AM19/AI19-1 -> 0 | AR19: =SUM(AG19:AJ19) -> -17.11997 | AS19: =AR19=K19 -> TRUE | AT19: =SUM(AG19:AI19,#REF!)=L19 -> #REF!
C20: EBITDA | D20: =D16-SUM(D18:D19) -> 380.2942 | E20: =E16-SUM(E18:E19) -> 326.33306 | F20: =F16-SUM(F18:F19) -> 813.01568 | G20: =G16-SUM(G18:G19) -> 1135.5715 | H20: =H16-SUM(H18:H19) -> 1657.6191 | I20: =I16-SUM(I18:I19) -> 1995.1044 | J20: =J16-SUM(J18:J19) -> 2633.1921 | K20: =K16-SUM(K18:K19) -> 4143.1356 | L20: 4232.623 | N20: =K20/L20-1 -> -0.021142322 | O20: =+K20/J20-1 -> 0.57342698 | Q20: =Q16-SUM(Q18:Q19) -> 238.68969 | R20: =R16-SUM(R18:R19) -> 395.05529 | S20: =S16-SUM(S18:S19) -> 350.24367 | T20: =T16-SUM(T18:T19) -> 151.58289 | U20: =U16-SUM(U18:U19) -> 475.55415 | V20: =V16-SUM(V18:V19) -> 459.03408 | W20: =W16-SUM(W18:W19) -> 436.0962 | X20: =X16-SUM(X18:X19) -> 286.93467 | ... AM20: =AM16-SUM(AM18:AM19) -> 1799.0088 | AN20: 1668.3369 | AP20: =AM20/AN20-1 -> 0.078324617 | AQ20: =AM20/AI20-1 -> 0.45584749 | AR20: =SUM(AG20:AJ20) -> 4143.1356 | AS20: =AR20=K20 -> TRUE | AT20: =SUM(AG20:AI20,#REF!)=L20 -> #REF!
C21: Core op | AG21: =AG11+AG13+AG14 -> 779.65011 | AH21: =AH11+AH13+AH14 -> 1284.0511 | AI21: =AI11+AI13+AI14 -> 1175.5075 | AJ21: =AJ11+AJ13+AJ14 -> 688.67723 | AK21: =AK11+AK13+AK14 -> 1210.1845 | AL21: =AL11+AL13+AL14 -> 1664.0751 | AM21: =AM11+AM13+AM14 -> 1655.5502 | AN21: =AN11+AN13+AN14 -> 1638.6702 | AP21: =(AM21/AN21-1) -> 0.01030103 | AQ21: =(AM21/AI21-1) -> 0.40837063 | AR21: =SUM(AG21:AJ21) -> 3927.886 | AS21: =AR21=K21 -> FALSE | AT21: =SUM(AG21:AI21,#REF!)=L21 -> #REF!
A22: =Model!B39 -> Interest income | B22: ='Raw Data'!B38 -> Interest income | C22: Interest income | O22: =IF(ISERROR(#REF!/K22-1)," ",(#REF!/K22-1)) | AR22: =SUM(AG22:AJ22) -> 0 | AS22: =AR22=K22 -> TRUE | AT22: =SUM(AG22:AI22,#REF!)=L22 -> #REF!
A23: =Model!B40 -> Interest expense | B23: ='Raw Data'!B93 -> Total finance costs | C23: Interest expense | O23: =IF(ISERROR(#REF!/K23-1)," ",(#REF!/K23-1)) | AR23: =SUM(AG23:AJ23) -> 0 | AS23: =AR23=K23 -> TRUE | AT23: =SUM(AG23:AI23,#REF!)=L23 -> #REF!
C24: Net interest income/(expense) | D24: =Segment!F53 -> -10.454 | E24: =Segment!G53 -> -5.0820752 | F24: =Segment!H53 -> 13.965657 | G24: =Segment!I53 -> 15.93094 | H24: =Segment!J53 -> 11.393957 | I24: =Segment!K53 -> -41.039484 | J24: =Segment!L53 -> -2.2856168 | K24: =Segment!M53 -> 190.53573 | L24: 91.666162 | N24: =K24/L24-1 -> 1.0785831 | O24: n.m. | Q24: =-Segment!BB53 -> 3.7269526 | R24: =-Segment!BC53 -> 3.0950474 | S24: =-Segment!BD53 -> 4.6195695 | T24: =-Segment!BE53 -> -27.372509 | U24: =-Segment!BF53 -> 2.3103464 | V24: =-Segment!BG53 -> 1.9861142 | W24: =-Segment!BH53 -> 6.3750549 | X24: =-Segment!BI53 -> -22.065473 | ... AM24: =-Segment!BX53 -> 9.4679811 | AN24: 25.469264 | AP24: =AM24/AN24-1 -> -0.62825855 | AQ24: =AM24/AI24-1 -> -0.68926125 | AR24: =SUM(AG24:AJ24) -> 190.53573 | AS24: =AR24=K24 -> TRUE | AT24: =SUM(AG24:AI24,#REF!)=L24 -> #REF!
A25: =Model!B47 -> Other non-operating income/expense | B25: ='Raw Data'!B49 -> Other non operating income/expense | C25: Non-operating income/(loss) | D25: =Segment!F56++Segment!F58+Segment!F59-Segment!F60 -> 19.9649 | E25: =Segment!G56++Segment!G58+Segment!G59-Segment!G60 -> 37.048354 | F25: =Segment!H56++Segment!H58+Segment!H59-Segment!H60 -> 19.246076 | G25: =Segment!I56++Segment!I58+Segment!I59-Segment!I60 -> 12.489926 | H25: =Segment!J56++Segment!J58+Segment!J59-Segment!J60 -> 29.616555 | I25: =Segment!K56++Segment!K58+Segment!K59-Segment!K60 -> 105.8862 | J25: =Segment!L56++Segment!L58+Segment!L59-Segment!L60 -> 202.40354 | K25: =Segment!M56++Segment!M58+Segment!M59-Segment!M60 -> 116.6927 | L25: 160.998 | N25: =K25/L25-1 -> -0.27519165 | O25: =+K25/J25-1 -> -0.42346514 | Q25: =Segment!BB56++Segment!BB58+Segment!BB59-Segment!BB60 -> -10.680693 | R25: =Segment!BC56++Segment!BC58+Segment!BC59-Segment!BC60 -> 2.2769927 | S25: =Segment!BD56++Segment!BD58+Segment!BD59-Segment!BD60 -> 11.521198 | T25: =Segment!BE56++Segment!BE58+Segment!BE59-Segment!BE60 -> 9.3724281 | U25: =Segment!BF56++Segment!BF58+Segment!BF59-Segment!BF60 -> 6.7116032 | V25: =Segment!BG56++Segment!BG58+Segment!BG59-Segment!BG60 -> 6.8262857 | W25: =Segment!BH56++Segment!BH58+Segment!BH59-Segment!BH60 -> 7.2202687 | X25: =Segment!BI56++Segment!BI58+Segment!BI59-Segment!BI60 -> 8.8583974 | ... AM25: =Segment!BX56++Segment!BX58+Segment!BX59-Segment!BX60 -> 53.4941 | AN25: 34.613452 | AP25: =AM25/AN25-1 -> 0.54547137 | AQ25: =AM25/AI25-1 -> 0.6921309 | AR25: =SUM(AG25:AJ25) -> 116.6927 | AS25: =AR25=K25 -> TRUE | AT25: =SUM(AG25:AI25,#REF!)=L25 -> #REF!
B26: ='Raw Data'!B51 -> Pre-tax profits | C26: Pre-tax profit | D26: =D16+D24+D25 -> 389.8051 | E26: =E16+E24+E25 -> 273.32785 | F26: =F16+F24+F25 -> 736.50294 | G26: =G16+G24+G25 -> 1029.5497 | H26: =H16+H24+H25 -> 1513.5168 | I26: =I16+I24+I25 -> 1836.0097 | J26: =J16+J24+J25 -> 2579.2709 | K26: =K16+K24+K25 -> 4107.3123 | L26: 4128.7716 | N26: =K26/L26-1 -> -0.0051975142 | O26: =+K26/J26-1 -> 0.59243151 | Q26: =Q16+Q24+Q25 -> 198.12526 | R26: =R16+R24+R25 -> 366.81664 | S26: =S16+S24+S25 -> 332.77375 | T26: =T16+T24+T25 -> 99.97212 | U26: =U16+U24+U25 -> 438.2979 | V26: =V16+V24+V25 -> 421.56828 | W26: =W16+W24+W25 -> 403.41333 | X26: =X16+X24+X25 -> 227.44939 | ... AM26: =AM16+AM24+AM25 -> 1776.2079 | AN26: 1642.6567 | AP26: =AM26/AN26-1 -> 0.081301963 | AQ26: =AM26/AI26-1 -> 0.46547918 | AR26: =SUM(AG26:AJ26) -> 4107.3123 | AS26: =AR26=K26 -> TRUE | AT26: =SUM(AG26:AI26,#REF!)=L26 -> #REF!
B27: ='Raw Data'!B49 -> Other non operating income/expense | AR27: =SUM(AG27:AJ27) -> 0 | AS27: =AR27=K27 -> TRUE | AT27: =SUM(AG27:AI27,#REF!)=L27 -> #REF!
A28: =Model!B53 -> Income taxes | B28: ='Raw Data'!B54 -> Taxation | C28: Provision for taxes | D28: =-Segment!F62 -> -93.6393 | E28: =-Segment!G62 -> -57.496914 | F28: =-Segment!H62 -> -165.92903 | G28: =-Segment!I62 -> -217.48614 | H28: =-Segment!J62 -> -320.55641 | I28: =-Segment!K62 -> -395.48918 | J28: =-Segment!L62 -> -539.49813 | K28: =-Segment!M62 -> -780.88329 | L28: -822.31469 | N28: =K28/L28-1 -> -0.050383871 | O28: =+K28/J28-1 -> 0.44742539 | Q28: =-Segment!BB62 -> -44.475694 | R28: =-Segment!BC62 -> -79.157006 | S28: =-Segment!BD62 -> -70.040576 | T28: =-Segment!BE62 -> -23.812862 | U28: =-Segment!BF62 -> -96.408437 | V28: =-Segment!BG62 -> -87.631611 | W28: =-Segment!BH62 -> -83.205508 | X28: =-Segment!BI62 -> -53.310851 | ... AM28: =-Segment!BX62 -> -390.90976 | AN28: -321.96071 | AP28: =AM28/AN28-1 -> 0.21415359 | AQ28: =AM28/AI28-1 -> 0.66181041 | AR28: =SUM(AG28:AJ28) -> -780.88329 | AS28: =AR28=K28 -> TRUE | AT28: =SUM(AG28:AI28,#REF!)=L28 -> #REF!
AR29: =SUM(AG29:AJ29) -> 0 | AS29: =AR29=K29 -> TRUE | AT29: =SUM(AG29:AI29,#REF!)=L29 -> #REF!
A30: =Model!B54 -> Minority interest | B30: ='Raw Data'!B55 -> Minority interest | C30: Minority interest | D30: =-Segment!F64 -> 0 | E30: =-Segment!G64 -> 0 | F30: =-Segment!H64 -> 0 | G30: =-Segment!I64 -> 0 | H30: =-Segment!J64 -> 0 | I30: =-Segment!K64 -> 0 | J30: =-Segment!L64 -> 0 | K30: =-Segment!M64 -> 0.27984775 | L30: 0 | Q30: =-Segment!BB64 -> 0 | R30: =-Segment!BC64 -> 0 | S30: =-Segment!BD64 -> 0 | T30: =-Segment!BE64 -> 0 | U30: =-Segment!BF64 -> 0 | V30: =-Segment!BG64 -> 0 | W30: =-Segment!BH64 -> 0 | X30: =-Segment!BI64 -> 0 | ... AM30: =-Segment!BX64 -> 0.87434546 | AN30: 0 | AR30: =SUM(AG30:AJ30) -> 0.27984775 | AS30: =AR30=K30 -> TRUE | AT30: =SUM(AG30:AI30,#REF!)=L30 -> #REF!
A31: =+Model!B55 -> Preferred dividends | B31: =+'Raw Data'!B56 -> Preferred dividend | C31: Exceptionals (including preference dividend) | AR31: =SUM(AG31:AJ31) -> 0 | AS31: =AR31=K31 -> TRUE | AT31: =SUM(AG31:AI31,#REF!)=L31 -> #REF!
A32: =+Model!B56 -> Extraordinary gain/(loss) | B32: =+'Raw Data'!B60 -> Extraordinary gain/(loss) | C32: Net income | D32: =D26+D28+D30 -> 296.1658 | E32: =E26+E28+E30 -> 215.83094 | F32: =F26+F28+F30 -> 570.57391 | G32: =G26+G28+G30 -> 812.06352 | H32: =H26+H28+H30 -> 1192.9604 | I32: =I26+I28+I30 -> 1440.5206 | J32: =J26+J28+J30 -> 2039.7728 | K32: =K26+K28+K30 -> 3326.7089 | L32: 3306.457 | N32: =K32/L32-1 -> 0.0061249537 | O32: =+K32/J32-1 -> 0.63092127 | Q32: =Q26+Q28+Q30 -> 153.64956 | R32: =R26+R28+R30 -> 287.65964 | S32: =S26+S28+S30 -> 262.73318 | T32: =T26+T28+T30 -> 76.159258 | U32: =U26+U28+U30 -> 341.88947 | V32: =V26+V28+V30 -> 333.93666 | W32: =W26+W28+W30 -> 320.20782 | X32: =X26+X28+X30 -> 174.13854 | ... AM32: =AM26+AM28+AM30 -> 1386.1725 | AN32: 1320.696 | AP32: =AM32/AN32-1 -> 0.049577281 | AQ32: =AM32/AI32-1 -> 0.4190942 | AR32: =SUM(AG32:AJ32) -> 3326.7089 | AS32: =AR32=K32 -> TRUE | AT32: =SUM(AG32:AI32,#REF!)=L32 -> #REF!
C33: Recurring net income | AG33: =Quarterly!T74 -> 624.42605 | AH33: =Quarterly!U74 -> 1082.4856 | AI33: =Quarterly!V74 -> 956.31947 | AJ33: =Quarterly!W74 -> 599.01777 | AK33: =Quarterly!X74 -> 958.79253 | AL33: =Quarterly!Y74 -> 1311.6708 | AM33: =Quarterly!Z74 -> 1269.3895 | AN33: 1320.696 | AP33: =AM33/AN33-1 -> -0.038848077 | AQ33: =AM33/AI33-1 -> 0.3273697
A36: =Model!B60 -> EPS - basic | B36: ='Raw Data'!B66 -> Basic | C36: YoY Growth %
C37: Sales | E37: =E8/D8-1 -> 0.068122893 | F37: =F8/E8-1 -> 0.3855732 | G37: =G8/F8-1 -> 0.17814742 | H37: =H8/G8-1 -> 0.40724388 | I37: =I8/H8-1 -> 0.21891747 | J37: =J8/I8-1 -> 0.32419494 | K37: =K8/J8-1 -> 0.40629862 | L37: 0.44984851 | Y37: =Y8/U8-1 -> 0.17255171 | Z37: =Z8/V8-1 -> 0.15917357 | AA37: =AA8/W8-1 -> 0.25300085 | AB37: =AB8/X8-1 -> 0.31280246 | AC37: =AC8/Y8-1 -> 0.24137196 | AD37: =AD8/Z8-1 -> 0.29963602 | AE37: =AE8/AA8-1 -> 0.35173296 | AF37: =AF8/AB8-1 -> 0.40882464 | ... AM37: =AM8/AI8-1 -> 0.30359623 | AN37: 0.31
C38: Gross profit | E38: =E11/D11-1 -> 0.024567675 | F38: =F11/E11-1 -> 0.40873577 | G38: =G11/F11-1 -> 0.17470477 | H38: =H11/G11-1 -> 0.33999127 | I38: =I11/H11-1 -> 0.1626708 | J38: =J11/I11-1 -> 0.34756578 | K38: =K11/J11-1 -> 0.46301495 | L38: 0.51705666 | Y38: =Y11/U11-1 -> 0.022132968 | Z38: =Z11/V11-1 -> -0.016891467 | AA38: =AA11/W11-1 -> 0.087230441 | AB38: =AB11/X11-1 -> 1.0644592 | AC38: =AC11/Y11-1 -> 0.25117109 | AD38: =AD11/Z11-1 -> 0.31543707 | AE38: =AE11/AA11-1 -> 0.40096809 | AF38: =AF11/AB11-1 -> 0.42530216 | ... AM38: =AM11/AI11-1 -> 0.28659921 | AN38: 0.30985094 | AS38: 980.00953
C39: EBIT | E39: =E16/D16-1 -> -0.36532933 | F39: =F16/E16-1 -> 1.9138491 | G39: =G16/F16-1 -> 0.42349111 | H39: =H16/G16-1 -> 0.47084603 | I39: =I16/H16-1 -> 0.20282204 | J39: =J16/I16-1 -> 0.34327161 | K39: =K16/J16-1 -> 0.59724232 | L39: 0.62919638 | Y39: =Y16/U16-1 -> 0.019661345 | Z39: =Z16/V16-1 -> 0.26983024 | AA39: =AA16/W16-1 -> 0.19688989 | AB39: =AB16/X16-1 -> 0.42422025 | AC39: =AC16/Y16-1 -> 0.38720002 | AD39: =AD16/Z16-1 -> 0.34617903 | AE39: =AE16/AA16-1 -> 0.30022036 | AF39: =AF16/AB16-1 -> 0.34132948 | ... AM39: =AM16/AI16-1 -> 0.48984447 | AN39: 0.37621178
C40: EBITDA | E40: =E20/D20-1 -> -0.14189314 | F40: =F20/E20-1 -> 1.4913678 | G40: =G20/F20-1 -> 0.39674003 | H40: =H20/G20-1 -> 0.45972231 | I40: =I20/H20-1 -> 0.20359641 | J40: =J20/I20-1 -> 0.31982674 | K40: =K20/J20-1 -> 0.57342698 | L40: 0.60741139 | Y40: =Y20/U20-1 -> 0.017748016 | Z40: =Z20/V20-1 -> 0.2426269 | AA40: =AA20/W20-1 -> 0.17599608 | AB40: =AB20/X20-1 -> 0.35579997 | AC40: =AC20/Y20-1 -> 0.35017702 | AD40: =AD20/Z20-1 -> 0.31809293 | AE40: =AE20/AA20-1 -> 0.27312915 | AF40: =AF20/AB20-1 -> 0.30072522 | ... AM40: =AM20/AI20-1 -> 0.45584749 | AN40: 0.35010132
C41: NPAT | E41: =E32/D32-1 -> -0.27124962 | F41: =F32/E32-1 -> 1.643615 | G41: =G32/F32-1 -> 0.42323983 | H41: =H32/G32-1 -> 0.46904815 | I41: =I32/H32-1 -> 0.2075175 | J41: =J32/I32-1 -> 0.415997 | K41: =K32/J32-1 -> 0.63092127 | L41: 0.62099276 | Y41: =Y32/U32-1 -> 0.0080711882 | Z41: =Z32/V32-1 -> 0.2277204 | AA41: =AA32/W32-1 -> 0.28315503 | AB41: =AB32/X32-1 -> 0.57928575 | AC41: =AC32/Y32-1 -> 0.44277757 | AD41: =AD32/Z32-1 -> 0.48999278 | AE41: =AE32/AA32-1 -> 0.33247072 | AF41: =AF32/AB32-1 -> 0.39691515 | ... AM41: =AM32/AI32-1 -> 0.4190942 | AN41: 0.35206261
C43: Margin analysis
C44: Gross margin | D44: =(D8+D10)/D8 -> 0.47922117 | E44: =(E8+E10)/E8 -> 0.4596798 | F44: =(F8+F10)/F8 -> 0.46736425 | G44: =(G8+G10)/G8 -> 0.46599857 | H44: =(H8+H10)/H8 -> 0.44372835 | I44: =(I8+I10)/I8 -> 0.42325261 | J44: =(J8+J10)/J8 -> 0.43072263 | K44: =(K8+K10)/K8 -> 0.44809377 | L44: 0.45068891 | N44: =(K44-L44)*100 -> -0.25951371 | O44: =(+K44-J44)*100 -> 1.7371137 | Q44: =(Q8+Q10)/Q8 -> 0.49155111 | R44: =(R8+R10)/R8 -> 0.44790289 | S44: =(S8+S10)/S8 -> 0.47377159 | T44: =(T8+T10)/T8 -> 0.45694582 | U44: =(U8+U10)/U8 -> 0.4954237 | V44: =(V8+V10)/V8 -> 0.49799468 | W44: =(W8+W10)/W8 -> 0.46158141 | X44: =(X8+X10)/X8 -> 0.28222388 | ... AM44: =(AM8+AM10)/AM8 -> 0.45207978 | AN44: 0.458 | AP44: =(AM44-AN44)*100 -> -0.59202208 | AQ44: =(+AM44-AI44)*100 -> -0.597234
C45: EBITDA margin | D45: =D20/D8 -> 0.13372712 | E45: =E20/E8 -> 0.10743348 | F45: =F20/F8 -> 0.19317371 | G45: =G20/G8 -> 0.22901501 | H45: =H20/H8 -> 0.23755536 | I45: =I20/I8 -> 0.23456943 | J45: =J20/J8 -> 0.23379564 | K45: =K20/K8 -> 0.26158055 | L45: 0.25920348 | N45: =(K45-L45)*100 -> 0.23770731 | O45: =(+K45-J45)*100 -> 2.778491 | Q45: =Q20/Q8 -> 0.25577105 | R45: =R20/R8 -> 0.25715618 | S45: =S20/S8 -> 0.22249924 | T45: =T20/T8 -> 0.16568144 | U45: =U20/U8 -> 0.2778968 | V45: =V20/V8 -> 0.232894 | W45: =W20/W8 -> 0.2322192 | X45: =X20/X8 -> 0.20240734 | ... AM45: =AM20/AM8 -> 0.29456502 | AN45: 0.2718338 | AP45: =(AM45-AN45)*100 -> 2.2731223 | AQ45: =(+AM45-AI45)*100 -> 3.0805353
C46: EBIT margin | D46: =D16/D8 -> 0.13372712 | E46: =E16/E8 -> 0.079459659 | F46: =F16/F8 -> 0.16710301 | G46: =G16/G8 -> 0.20190143 | H46: =H16/H8 -> 0.21102662 | I46: =I16/I8 -> 0.20824008 | J46: =J16/J8 -> 0.21124003 | K46: =K16/K8 -> 0.23992168 | L46: 0.23737066 | N46: =(K46-L46)*100 -> 0.25510135 | O46: =(+K46-J46)*100 -> 2.8681641 | Q46: =Q16/Q8 -> 0.21975508 | R46: =R16/R8 -> 0.23527774 | S46: =S16/S8 -> 0.20114739 | T46: =T16/T8 -> 0.12894466 | U46: =U16/U8 -> 0.25085348 | V46: =V16/V8 -> 0.20941444 | W46: =W16/W8 -> 0.20757627 | X46: =X16/X8 -> 0.16976211 | ... AM46: =AM16/AM8 -> 0.28052242 | AN46: 0.25785985 | AP46: =(AM46-AN46)*100 -> 2.2662578 | AQ46: =(+AM46-AI46)*100 -> 3.5068633
C47: Pre-tax profit margin | D47: =D26/D8 -> 0.13707154 | E47: =E26/E8 -> 0.089983412 | F47: =F26/F8 -> 0.17499417 | G47: =G26/G8 -> 0.20763318 | H47: =H26/H8 -> 0.21690389 | I47: =I26/I8 -> 0.21586427 | J47: =J26/J8 -> 0.22900809 | K47: =K26/K8 -> 0.25931882 | L47: 0.25284367 | N47: =(K47-L47)*100 -> 0.64751409 | O47: =(+K47-J47)*100 -> 3.0310728 | Q47: =Q26/Q8 -> 0.21230371 | R47: =R26/R8 -> 0.2387746 | S47: =S26/S8 -> 0.21140113 | T47: =T26/T8 -> 0.10927041 | U47: =U26/U8 -> 0.25612558 | V47: =V26/V8 -> 0.21388547 | W47: =W26/W8 -> 0.21481572 | X47: =X26/X8 -> 0.16044567 | ... AM47: =AM26/AM8 -> 0.29083167 | AN47: 0.26764954 | AP47: =(AM47-AN47)*100 -> 2.3182128 | AQ47: =(+AM47-AI47)*100 -> 3.2126482
C48: Net profit margin | D48: =D32/D8 -> 0.10414411 | E48: =E32/E8 -> 0.071054612 | F48: =F32/F8 -> 0.13556919 | G48: =G32/G8 -> 0.16377192 | H48: =H32/H8 -> 0.17096457 | I48: =I32/I8 -> 0.16936562 | J48: =J32/J8 -> 0.18110717 | K48: =K32/K8 -> 0.21003472 | L48: 0.20248558 | N48: =(K48-L48)*100 -> 0.75491413 | O48: =(+K48-J48)*100 -> 2.8927549 | Q48: =Q32/Q8 -> 0.1646452 | R48: =R32/R8 -> 0.18724836 | S48: =S32/S8 -> 0.16690646 | T48: =T32/T8 -> 0.083242741 | U48: =U32/U8 -> 0.19978795 | V48: =V32/V8 -> 0.16942499 | W48: =W32/W8 -> 0.17050917 | X48: =X32/X8 -> 0.12283953 | ... AM48: =AM32/AM8 -> 0.22696829 | AN48: 0.21519023 | AP48: =(AM48-AN48)*100 -> 1.1778053 | AQ48: =(+AM48-AI48)*100 -> 1.8472612
C49: SG&A | D49: =-D12/D8 -> 0.32914976 | E49: =-E12/E8 -> 0.36644132 | F49: =-F12/F8 -> 0.28817509 | G49: =-G12/G8 -> 0.25406587 | H49: =-H12/H8 -> 0.23830155 | I49: =-I12/I8 -> 0.2055821 | J49: =-J12/J8 -> 0.21119595 | K49: =-K12/K8 -> 0.2001032 | L49: 0.20444893 | N49: =(K49-L49)*100 -> -0.43457328 | O49: =(+K49-J49)*100 -> -1.1092754 | Q49: =-Q12/Q8 -> 0.2646668 | R49: =-R12/R8 -> 0.20085765 | S49: =-S12/S8 -> 0.26286469 | T49: =-T12/T8 -> 0.31745759 | U49: =-U12/U8 -> 0.23366345 | V49: =-V12/V8 -> 0.27971309 | W49: =-W12/W8 -> 0.25068432 | X49: =-X12/X8 -> 0.16991931 | ... AM49: =-AM12/AM8 -> 0.18100428 | AN49: 0.191 | AP49: =(AM49-AN49)*100 -> -0.99957152 | AQ49: =(+AM49-AI49)*100 -> -2.6138746
C50: Selling expense ratio | D50: =-D13/D$8 -> 0.29019185 | E50: =-E13/E$8 -> 0.31915682 | F50: =-F13/F$8 -> 0.23370316 | G50: =-G13/G$8 -> 0.20981078 | H50: =-H13/H$8 -> 0.19610478 | I50: =-I13/I$8 -> 0.17039502 | J50: =-J13/J$8 -> 0.17363998 | K50: =-K13/K$8 -> 0.16927236 | L50: 0.17333998 | N50: =(K50-L50)*100 -> -0.40676258 | O50: =(+K50-J50)*100 -> -0.43676258 | Y50: =-Y13/Y$8 -> 0.1684315 | Z50: =-Z13/Z$8 -> 0.15963943 | AA50: =-AA13/AA$8 -> 0.16272595 | AB50: =-AB13/AB$8 -> 0.19541297 | AC50: =-AC13/AC$8 -> 0.15685623 | AD50: =-AD13/AD$8 -> 0.15913646 | AE50: =-AE13/AE$8 -> 0.17532819 | AF50: =-AF13/AF$8 -> 0.20396245 | ... AM50: =-AM13/AM$8 -> 0.1525747 | AN50: 0.163 | AP50: =(AM50-AN50)*100 -> -1.0425298 | AQ50: =(+AM50-AI50)*100 -> -2.6063839
C51: Admin expense ratio | D51: =-D14/D$8 -> 0.03895791 | E51: =-E14/E$8 -> 0.047284495 | F51: =-F14/F$8 -> 0.05447193 | G51: =-G14/G$8 -> 0.044255089 | H51: =-H14/H$8 -> 0.042196767 | I51: =-I14/I$8 -> 0.035187077 | J51: =-J14/J$8 -> 0.037555966 | K51: =-K14/K$8 -> 0.030830838 | L51: 0.031108945 | N51: =(K51-L51)*100 -> -0.027810703 | O51: =(+K51-J51)*100 -> -0.67251278 | Y51: =-Y14/Y$8 -> 0.039331988 | Z51: =-Z14/Z$8 -> 0.031704187 | AA51: =-AA14/AA$8 -> 0.035776387 | AB51: =-AB14/AB$8 -> 0.034248806 | AC51: =-AC14/AC$8 -> 0.036638117 | AD51: =-AD14/AD$8 -> 0.032972758 | AE51: =-AE14/AE$8 -> 0.035309663 | AF51: =-AF14/AF$8 -> 0.046343594 | ... AM51: =-AM14/AM$8 -> 0.028429582 | AN51: 0.028 | AP51: =(AM51-AN51)*100 -> 0.04295825 | AQ51: =(+AM51-AI51)*100 -> -0.0074906382
C52: Effective tax rate | D52: =+D28/D26 -> -0.24022082 | E52: =+E28/E26 -> -0.21035878 | F52: =+F28/F26 -> -0.2252931 | G52: =+G28/G26 -> -0.21124395 | H52: =+H28/H26 -> -0.21179574 | I52: =+I28/I26 -> -0.21540691 | J52: =+J28/J26 -> -0.20916691 | K52: =+K28/K26 -> -0.19012026 | L52: -0.19916691 | N52: =(K52-L52)*100 -> 0.90466471 | O52: =(+K52-J52)*100 -> 1.9046647 | Q52: =+Q28/Q26 -> -0.22448271 | R52: =+R28/R26 -> -0.21579448 | S52: =+S28/S26 -> -0.21047506 | T52: =+T28/T26 -> -0.23819503 | U52: =+U28/U26 -> -0.21996098 | V52: =+V28/V26 -> -0.20787051 | W52: =+W28/W26 -> -0.20625374 | X52: =+X28/X26 -> -0.23438555 | ... AM52: =+AM28/AM26 -> -0.22008108 | AN52: -0.196 | AP52: =-(AM52-AN52)*100 -> 2.408108 | AQ52: =-(+AM52-AI52)*100 -> 2.6001034
C55: Customer advance | Y55: =Wind!CJ118 -> 1202.0115 | Z55: =Wind!CK118 -> 1268.9439 | AA55: =Wind!CL118 -> 1343.9931 | AB55: =Wind!CM118 -> 1627.1676 | AC55: =Wind!CN118 -> 1685.8244 | AD55: =Wind!CO118 -> 1851.4306 | AE55: =Wind!CP118 -> 1916.4812 | AF55: =Wind!CQ118 -> 2607.2214 | ... AM55: =Wind!CX118 -> 3562.9942
C56: yoy | AC56: =AC55/Y55-1 -> 0.4025027 | AD56: =AD55/Z55-1 -> 0.45903263 | AE56: =AE55/AA55-1 -> 0.42596065 | AF56: =AF55/AB55-1 -> 0.60230665 | AG56: =AG55/AC55-1 -> 0.59420019 | AH56: =AH55/AD55-1 -> 0.35091315 | AI56: =AI55/AE55-1 -> 0.24175698 | AJ56: =AJ55/AF55-1 -> 0.82590985 | ... AM56: =AM55/AI55-1 -> 0.49717972
C57: Cash received from sales | Y57: =Wind!CJ176 -> 2314.9116 | Z57: =Wind!CK176-Wind!CJ176 -> 2643.7601 | AA57: =Wind!CL176-Wind!CK176 -> 2737.6421 | AB57: =Wind!CM176-Wind!CL176 -> 2444.5685 | AC57: =Wind!CN176 -> 2943.7671 | AD57: =Wind!CO176-Wind!CN176 -> 3553.3209 | AE57: =Wind!CP176-Wind!CO176 -> 3711.1528 | AF57: =Wind!CQ176-Wind!CP176 -> 3691.8035 | AG57: =Wind!CR176 -> 4095.5743 | AH57: =Wind!CS176-Wind!CR176 -> 4788.7387 | AI57: =Wind!CT176-Wind!CS176 -> 5107.1586 | AJ57: =Wind!CU176-Wind!CT176 -> 6438.672 | AK57: =Wind!CV176 -> 4863.4824 | AL57: =Wind!CW176-Wind!CV176 -> 6208.89 | AM57: =Wind!CX176-Wind!CW176 -> 6784.9668
C58: yoy | AC58: =AC57/Y57-1 -> 0.27165422 | AD58: =AD57/Z57-1 -> 0.34404062 | AE58: =AE57/AA57-1 -> 0.35560189 | AF58: =AF57/AB57-1 -> 0.51020663 | AG58: =AG57/AC57-1 -> 0.39126984 | AH58: =AH57/AD57-1 -> 0.34767976 | AI58: =AI57/AE57-1 -> 0.37616502 | AJ58: =AJ57/AF57-1 -> 0.74404513 | ... AM58: =AM57/AI57-1 -> 0.32852086
C59: OCF | Y59: =Wind!CJ190 -> 291.35359 | Z59: =Wind!CK190-Wind!CJ190 -> 421.80229 | AA59: =Wind!CL190-Wind!CK190 -> 708.7273 | AB59: =Wind!CM190-Wind!CL190 -> 604.22196 | AC59: =Wind!CN190 -> 723.99698 | AD59: =Wind!CO190-Wind!CN190 -> 573.95611 | AE59: =Wind!CP190-Wind!CO190 -> 715.49371 | AF59: =Wind!CQ190-Wind!CP190 -> 1267.8229 | AG59: =Wind!CR190 -> 859.5444 | AH59: =Wind!CS190-Wind!CR190 -> 1407.7482 | AI59: =Wind!CT190-Wind!CS190 -> 768.12649 | AJ59: =Wind!CU190-Wind!CT190 -> 2753.9894 | AK59: =Wind!CV190 -> 631.49311 | AL59: =Wind!CW190-Wind!CV190 -> 1108.9675 | AM59: =Wind!CX190-Wind!CW190 -> 1392.1731
C60: yoy | AC60: =AC59/Y59-1 -> 1.4849427 | AD60: =AD59/Z59-1 -> 0.36072308 | AE60: =AE59/AA59-1 -> 0.0095472578 | AF60: =AF59/AB59-1 -> 1.0982734 | AG60: =AG59/AC59-1 -> 0.18722097 | AH60: =AH59/AD59-1 -> 1.4527106 | AI60: =AI59/AE59-1 -> 0.073561485 | AJ60: =AJ59/AF59-1 -> 1.1722194 | ... AM60: =AM59/AI59-1 -> 0.81242692
C62: Source: Company data, Goldman Sachs Research estimates.
C67: Eastroc | Y67: Pre-results | AD67: Diff. vs GSe
C68: 2024 (Rmb mn) | Y68: Low-end | Z68: Mid-point | AA68: High-end | AB68: GSe | AD68: Low-end | AE68: Mid-point | AF68: High-end
C69: Sales | Y69: 15720 | Z69: =AVERAGE(Y69,AA69) -> 15910 | AA69: 16100 | AB69: =Quarterly!W6 -> 15838.852 | AD69: =Y69/$AB69-1 -> -0.0075038159 | AE69: =Z69/$AB69-1 -> 0.0044920031 | AF69: =AA69/$AB69-1 -> 0.016487822
C70: yoy | Y70: 0.4 | Z70: =AVERAGE(Y70,AA70) -> 0.415 | AA70: 0.43 | AB70: =Quarterly!W7 -> 0.40629862
C71: Net profits | Y71: 3150 | Z71: =AVERAGE(Y71,AA71) -> 3300 | AA71: 3450 | AB71: =Quarterly!W34 -> 3326.7089 | AD71: =Y71/$AB71-1 -> -0.05311822 | AE71: =Z71/$AB71-1 -> -0.0080286113 | AF71: =AA71/$AB71-1 -> 0.037060997
C72: yoy | Y72: 0.54 | Z72: =Z71/Quarterly!S34-1 -> 0.61782724 | AA72: 0.69 | AB72: =Quarterly!W35 -> 0.63092127
C73: NPM | Y73: =Y71/Y69 -> 0.20038168 | Z73: =Z71/Z69 -> 0.20741672 | AA73: =AA71/AA69 -> 0.21428571 | AB73: =AB71/AB69 -> 0.21003472 | AD73: =(Y73-$AB73)*100 -> -0.96530434 | AE73: =(Z73-$AB73)*100 -> -0.26180037 | AF73: =(AA73-$AB73)*100 -> 0.42509915
C74: yoy change | Y74: =(Y73-Quarterly!$S$34/Quarterly!$S$6)*100 -> 1.9274506 | Z74: =(Z73-Quarterly!$S$34/Quarterly!$S$6)*100 -> 2.6309545 | AA74: =(AA73-Quarterly!$S$34/Quarterly!$S$6)*100 -> 3.3178541 | AB74: =(AB73-Quarterly!$S$34/Quarterly!$S$6)*100 -> 2.8927549
C75: Recurring net profits | Y75: 3070 | Z75: =AVERAGE(Y75,AA75) -> 3220 | AA75: 3370
C76: yoy | Y76: 0.64 | Z76: =Z75/(Y75/(1+Y76))-1 -> 0.72013029 | AA76: 0.8
C78: Implied 4Q24 (Rmb mn) | Y78: Low-end | Z78: Mid-point | AA78: High-end | AB78: GSe | AD78: Low-end | AE78: Mid-point | AF78: High-end
C79: Sales | Y79: =Y69-Quarterly!$V$6 -> 3161.7185 | Z79: =AVERAGE(Y79,AA79) -> 3351.7185 | AA79: =AA69-Quarterly!$V$6 -> 3541.7185 | AB79: =Quarterly!W43 -> 3280.5703 | AD79: =Y79/$AB79-1 -> -0.036229014 | AE79: =Z79/$AB79-1 -> 0.021687745 | AF79: =AA79/$AB79-1 -> 0.079604503
C80: yoy | Y80: =Y79/Quarterly!$S$43-1 -> 0.2058967 | Z80: =Z79/Quarterly!$S$43-1 -> 0.27836373 | AA80: =AA79/Quarterly!$S$43-1 -> 0.35083077 | AB80: =AB79/Quarterly!$S$43-1 -> 0.25122743
C81: Net profits | Y81: =Y71-Quarterly!$V$34 -> 442.60759 | Z81: =AVERAGE(Y81,AA81) -> 592.60759 | AA81: =AA71-Quarterly!$V$34 -> 742.60759 | AB81: =Quarterly!W70 -> 619.31645 | AD81: =Y81/$AB81-1 -> -0.28532886 | AE81: =Z81/$AB81-1 -> -0.043126341 | AF81: =AA81/$AB81-1 -> 0.19907617
C82: yoy | Y82: =Y81/Quarterly!$S$70-1 -> 0.15210804 | Z82: =Z81/Quarterly!$S$70-1 -> 0.5425582 | AA82: =AA81/Quarterly!$S$70-1 -> 0.93300837 | AB82: =AB81/Quarterly!$S$70-1 -> 0.61208138
C83: NPM | Y83: =Y81/Y79 -> 0.13998956 | Z83: =Z81/Z79 -> 0.17680709 | AA83: =AA81/AA79 -> 0.20967437 | AB83: =AB81/AB79 -> 0.18878316 | AD83: =(Y83-$AB83)*100 -> -4.87936 | AE83: =(Z83-$AB83)*100 -> -1.1976074 | AF83: =(AA83-$AB83)*100 -> 2.0891206
C84: yoy change | Y84: =(Y83-Quarterly!$S$67/Quarterly!$S$43)*100 -> -0.65357154 | Z84: =(Z83-Quarterly!$S$67/Quarterly!$S$43)*100 -> 3.0281811 | AA84: =(AA83-Quarterly!$S$67/Quarterly!$S$43)*100 -> 6.314909 | AB84: =(AB83-Quarterly!$S$67/Quarterly!$S$43)*100 -> 4.2257885
C85: Recurring net profits | Y85: =Y75-2663.231 -> 406.769 | Z85: =Z75-2663.231 -> 556.769 | AA85: =AA75-2663.231 -> 706.769
C86: yoy | Y86: =Y85/368-1 -> 0.10535054 | Z86: =Z85/368-1 -> 0.51295924 | AA86: =AA85/368-1 -> 0.92056793

Sheet Model
A2: =#REF! -> #REF! | B2: Eastroc Beverage (605499.SS)
A3: =#REF! -> #REF!
C4: 2017 | D4: 2018 | E4: 2019 | F4: 2020 | G4: 2021 | H4: 2022 | I4: 2023 | J4: 2024 | K4: 2025E | L4: 2026E | M4: 2027E | O4: 1H20 | P4: 2H20 | Q4: 1H21 | R4: 2H21 | S4: 1H22 | T4: 2H22 | U4: 1H23 | V4: 2H23 | W4: 1H24 | X4: 2H24 | Y4: 1H25
B5: EPS - basic | C5: =IF(ISERROR(C60)," ",(C60)) -> 1.9637077 | D5: =IF(ISERROR(D60)," ",(D60)) -> 0.47435372 | E5: =IF(ISERROR(E60)," ",(E60)) -> 1.219175 | F5: =IF(ISERROR(F60)," ",(F60)) -> 1.7351785 | G5: =IF(ISERROR(G60)," ",(G60)) -> 2.2940973 | H5: =IF(ISERROR(H60)," ",(H60)) -> 2.7701626 | I5: =IF(ISERROR(I60)," ",(I60)) -> 3.9225419 | J5: =IF(ISERROR(J60)," ",(J60)) -> 6.3973571 | ... M5: =IF(ISERROR(M60)," ",(M60)) -> 12.988135
B6: EPS - fully diluted
B7: yoy % | C7: =IF(ISERROR(C5/#REF!-1)," ",(C5/#REF!-1)) | D7: =IF(ISERROR(D5/C5-1)," ",(D5/C5-1)) -> -0.75843975 | E7: =IF(ISERROR(E5/D5-1)," ",(E5/D5-1)) -> 1.5701812 | F7: =IF(ISERROR(F5/E5-1)," ",(F5/E5-1)) -> 0.42323983 | G7: =IF(ISERROR(G5/F5-1)," ",(G5/F5-1)) -> 0.32211028 | H7: =IF(ISERROR(H5/G5-1)," ",(H5/G5-1)) -> 0.2075175 | I7: =IF(ISERROR(I5/H5-1)," ",(I5/H5-1)) -> 0.415997 | J7: =IF(ISERROR(J5/I5-1)," ",(J5/I5-1)) -> 0.63092127 | K7: =IF(ISERROR(K5/J5-1)," ",(K5/J5-1)) -> 0.37158013 | ... M7: =IF(ISERROR(M5/L5-1)," ",(M5/L5-1)) -> 0.19417229
B8: Consensus estimates
B9: Variance from consensus (%) | I9: =(I13/G13)^(1/2)-1 -> 0.2704662 | J9: =(J13/H13)^(1/2)-1 -> 0.36462945 | L9: =(L13/J13)^(1/2)-1 -> 0.26644112
I10: =(I57/G57)^(1/2)-1 -> 0.30760895 | J10: =(J57/H57)^(1/2)-1 -> 0.51966431 | L10: =(L57/J57)^(1/2)-1 -> 0.30388595
B11: Income statements | C11: =C4 -> 2017 | D11: =D4 -> 2018 | E11: =E4 -> 2019 | F11: =F4 -> 2020 | G11: =G4 -> 2021 | H11: =H4 -> 2022 | I11: =I4 -> 2023 | J11: =J4 -> 2024 | ... M11: =M4 -> 2027E | O11: =O4 -> 1H20 | P11: =P4 -> 2H20 | Q11: =Q4 -> 1H21 | R11: =R4 -> 2H21 | S11: =S4 -> 1H22 | T11: =T4 -> 2H22 | U11: =U4 -> 1H23 | V11: =V4 -> 2H23 | ... X11: =X4 -> 2H24
B13: Total sales/revenues | C13: =+'Raw Data'!C8 -> 2843.8076 | D13: =+'Raw Data'!D8 -> 3037.536 | E13: =+'Raw Data'!E8 -> 4208.7285 | F13: =+'Raw Data'!F8 -> 4958.5026 | G13: =+'Raw Data'!G8 -> 6977.8225 | H13: =+'Raw Data'!H8 -> 8505.3897 | I13: =+'Raw Data'!I8 -> 11262.794 | J13: =+'Raw Data'!J8 -> 15838.852 | K13: =Segment!N9 -> 20991.911 | L13: =Segment!O9 -> 25403.508 | M13: =Segment!P9 -> 29791.987 | O13: =+Segment!V9 -> 2469.4627 | P13: =+Segment!W9 -> 2489.0399 | Q13: =+Segment!X9 -> 3682.2618 | R13: =+Segment!Y9 -> 3295.5607 | S13: =+Segment!Z9 -> 4291.274 | T13: =+Segment!AA9 -> 4214.1157 | U13: =+Segment!AB9 -> 5460.1849 | V13: =+Segment!AC9 -> 5802.6092 | ... Y13: =+Segment!AF9 -> 10736.628
B14: yoy % | C14: =IF(ISERROR(C13/#REF!-1)," ",(C13/#REF!-1)) | D14: =IF(ISERROR(D13/C13-1)," ",(D13/C13-1)) -> 0.068122893 | E14: =IF(ISERROR(E13/D13-1)," ",(E13/D13-1)) -> 0.3855732 | F14: =IF(ISERROR(F13/E13-1)," ",(F13/E13-1)) -> 0.17814742 | G14: =IF(ISERROR(G13/F13-1)," ",(G13/F13-1)) -> 0.40724388 | H14: =IF(ISERROR(H13/G13-1)," ",(H13/G13-1)) -> 0.21891747 | I14: =IF(ISERROR(I13/H13-1)," ",(I13/H13-1)) -> 0.32419494 | J14: =IF(ISERROR(J13/I13-1)," ",(J13/I13-1)) -> 0.40629862 | K14: =IF(ISERROR(K13/J13-1)," ",(K13/J13-1)) -> 0.32534294 | ... M14: =IF(ISERROR(M13/L13-1)," ",(M13/L13-1)) -> 0.17275087 | Q14: =Q13/O13-1 -> 0.4911186 | R14: =R13/P13-1 -> 0.32402887 | S14: =S13/Q13-1 -> 0.16539081 | T14: =T13/R13-1 -> 0.27872495 | U14: =U13/S13-1 -> 0.27239252 | V14: =V13/T13-1 -> 0.37694585 | W14: =W13/U13-1 -> 0.44194527 | X14: =X13/V13-1 -> 0.37275556 | Y14: =Y13/W13-1 -> 0.3636778
B16: COGS | C16: =+'Raw Data'!C15 -> -1480.9948 | D16: =+'Raw Data'!D15 -> -1641.2421 | E16: =+'Raw Data'!E15 -> -2241.7193 | F16: =+'Raw Data'!F15 -> -2647.8475 | G16: =+'Raw Data'!G15 -> -3881.5648 | H16: =+'Raw Data'!H15 -> -4905.4613 | I16: =+'Raw Data'!I15 -> -6411.6538 | J16: =+'Raw Data'!J15 -> -8741.561 | K16: =-Segment!N23 -> -11564.399 | L16: =-Segment!O23 -> -13747.299 | M16: =-Segment!P23 -> -16022.731 | O16: =-Segment!V23 -> -1322.65 | P16: =-Segment!W23 -> -1325.1975 | Q16: =-Segment!X23 -> -1852.9146 | R16: =-Segment!Y23 -> -2028.6502 | S16: =-Segment!Z23 -> -2459.7423 | T16: =-Segment!AA23 -> -2445.719 | U16: =-Segment!AB23 -> -3106.6108 | V16: =-Segment!AC23 -> -3305.0429 | ... Y16: =-Segment!AF23 -> -5889.4142
B17: Others | C17: =+'Raw Data'!C16 -> 0 | D17: =+'Raw Data'!D16 -> 0 | E17: =+'Raw Data'!E16 -> 0 | F17: =+'Raw Data'!F16 -> 0 | G17: =+'Raw Data'!G16 -> 0 | H17: =+'Raw Data'!H16 -> 0 | I17: =+'Raw Data'!I16 -> 0 | J17: =+'Raw Data'!J16 -> 0 | K17: =-K$13*K79 -> 0 | L17: =-L$13*L79 -> 0 | M17: =-M$13*M79 -> 0
B18: Total COGS | C18: =C16+C17 -> -1480.9948 | D18: =D16+D17 -> -1641.2421 | E18: =E16+E17 -> -2241.7193 | F18: =F16+F17 -> -2647.8475 | G18: =G16+G17 -> -3881.5648 | H18: =H16+H17 -> -4905.4613 | I18: =I16+I17 -> -6411.6538 | J18: =J16+J17 -> -8741.561 | ... M18: =M16+M17 -> -16022.731 | O18: =O16+O17 -> -1322.65 | P18: =P16+P17 -> -1325.1975 | Q18: =Q16+Q17 -> -1852.9146 | R18: =R16+R17 -> -2028.6502 | S18: =S16+S17 -> -2459.7423 | T18: =T16+T17 -> -2445.719 | U18: =U16+U17 -> -3106.6108 | V18: =V16+V17 -> -3305.0429 | ... Y18: =Y16+Y17 -> -5889.4142
B20: Gross profit | C20: =C13+C18 -> 1362.8128 | D20: =D13+D18 -> 1396.2939 | E20: =E13+E18 -> 1967.0092 | F20: =F13+F18 -> 2310.6551 | G20: =G13+G18 -> 3096.2577 | H20: =H13+H18 -> 3599.9284 | I20: =I13+I18 -> 4851.1403 | J20: =J13+J18 -> 7097.2908 | ... M20: =M13+M18 -> 13769.256 | O20: =O13+O18 -> 1146.8127 | P20: =P13+P18 -> 1163.8424 | Q20: =Q13+Q18 -> 1829.3471 | R20: =R13+R18 -> 1266.9105 | S20: =S13+S18 -> 1831.5317 | T20: =T13+T18 -> 1768.3967 | U20: =U13+U18 -> 2353.5741 | V20: =V13+V18 -> 2497.5662 | ... Y20: =Y13+Y18 -> 4847.2136
B21: yoy % | C21: =IF(ISERROR(C20/#REF!-1)," ",(C20/#REF!-1)) | D21: =IF(ISERROR(D20/C20-1)," ",(D20/C20-1)) -> 0.024567675 | E21: =IF(ISERROR(E20/D20-1)," ",(E20/D20-1)) -> 0.40873577 | F21: =IF(ISERROR(F20/E20-1)," ",(F20/E20-1)) -> 0.17470477 | G21: =IF(ISERROR(G20/F20-1)," ",(G20/F20-1)) -> 0.33999127 | H21: =IF(ISERROR(H20/G20-1)," ",(H20/G20-1)) -> 0.1626708 | I21: =IF(ISERROR(I20/H20-1)," ",(I20/H20-1)) -> 0.34756578 | J21: =IF(ISERROR(J20/I20-1)," ",(J20/I20-1)) -> 0.46301495 | K21: =IF(ISERROR(K20/J20-1)," ",(K20/J20-1)) -> 0.32832537 | ... M21: =IF(ISERROR(M20/L20-1)," ",(M20/L20-1)) -> 0.18128073
B23: SG&A | C23: =+'Raw Data'!C23 -> -981.9832 | D23: =+'Raw Data'!D23 -> -1152.6478 | E23: =+'Raw Data'!E23 -> -1257.157 | F23: =+'Raw Data'!F23 -> -1310.1438 | G23: =+'Raw Data'!G23 -> -1739.6364 | H23: =+'Raw Data'!H23 -> -1841.1951 | I23: =+'Raw Data'!I23 -> -2499.6673 | J23: =+'Raw Data'!J23 -> -3329.1976 | K23: =K24+K25+K26 -> -4191.9135 | L23: =L24+L25+L26 -> -4938.2351 | M23: =M24+M25+M26 -> -5684.0683 | O23: =O24+O25+O26 -> -579.2962 | P23: =P24+P25+P26 -> -730.84764 | Q23: =Q24+Q25+Q26 -> -992.75571 | R23: =R24+R25+R26 -> -746.88072 | S23: =S24+S25+S26 -> -901.70576 | T23: =T24+T25+T26 -> -939.4893 | U23: =U24+U25+U26 -> -1111.8714 | V23: =V24+V25+V26 -> -1387.7959 | ... Y23: =Y24+Y25+Y26 -> -2082.2833
B24: Sales tax and add-on | C24: ='Raw Data'!C20 -> -45.9446 | D24: ='Raw Data'!D20 -> -39.569062 | E24: ='Raw Data'!E20 -> -44.306298 | F24: ='Raw Data'!F20 -> -50.357577 | G24: ='Raw Data'!G20 -> -76.810518 | H24: ='Raw Data'!H20 -> -92.639167 | I24: ='Raw Data'!I20 -> -121.01084 | J24: ='Raw Data'!J20 -> -159.79275 | K24: =-Segment!N45 -> -211.78019 | L24: =-Segment!O45 -> -256.28729 | M24: =-Segment!P45 -> -300.56114 | O24: =-Segment!V45 -> -23.738 | P24: =-Segment!W45 -> -26.619577 | Q24: =-Segment!X45 -> -41.581897 | R24: =-Segment!Y45 -> -35.228621 | S24: =-Segment!Z45 -> -47.650708 | T24: =-Segment!AA45 -> -44.988459 | U24: =-Segment!AB45 -> -59.469351 | V24: =-Segment!AC45 -> -61.541491 | ... Y24: =-Segment!AF45 -> -109.32921
B25: Sales expense | C25: ='Raw Data'!C21 -> -825.2498 | D25: ='Raw Data'!D21 -> -969.45034 | E25: ='Raw Data'!E21 -> -983.59316 | F25: ='Raw Data'!F21 -> -1040.3473 | G25: ='Raw Data'!G21 -> -1368.3844 | H25: ='Raw Data'!H21 -> -1449.2761 | I25: ='Raw Data'!I21 -> -1955.6714 | J25: ='Raw Data'!J21 -> -2681.0798 | K25: =-Segment!N47 -> -3370.7206 | L25: =-Segment!O47 -> -3972.4065 | M25: =-Segment!P47 -> -4584.1632 | O25: =-Segment!V47 -> -452.208 | P25: =-Segment!W47 -> -588.13929 | Q25: =-Segment!X47 -> -798.65826 | R25: =-Segment!Y47 -> -569.72611 | S25: =-Segment!Z47 -> -702.69818 | T25: =-Segment!AA47 -> -746.5779 | U25: =-Segment!AB47 -> -863.23476 | V25: =-Segment!AC47 -> -1092.4366 | ... Y25: =-Segment!AF47 -> -1681.5191
B26: Administrative expense | C26: ='Raw Data'!C22 -> -110.7888 | D26: ='Raw Data'!D22 -> -143.62836 | E26: ='Raw Data'!E22 -> -229.25756 | F26: ='Raw Data'!F22 -> -219.43897 | G26: ='Raw Data'!G22 -> -294.44155 | H26: ='Raw Data'!H22 -> -299.27981 | I26: ='Raw Data'!I22 -> -422.98511 | J26: ='Raw Data'!J22 -> -488.32508 | K26: =-Segment!N49 -> -609.41275 | L26: =-Segment!O49 -> -709.54128 | M26: =-Segment!P49 -> -799.34397 | O26: =-Segment!V49 -> -103.3502 | P26: =-Segment!W49 -> -116.08877 | Q26: =-Segment!X49 -> -152.51556 | R26: =-Segment!Y49 -> -141.92599 | S26: =-Segment!Z49 -> -151.35686 | T26: =-Segment!AA49 -> -147.92294 | U26: =-Segment!AB49 -> -189.16727 | V26: =-Segment!AC49 -> -233.81784 | ... Y26: =-Segment!AF49 -> -291.43502
B27: Other operating expense | C27: =SUM(C28:C29) -> -0.5354 | D27: =SUM(D28:D29) -> -2.2846109 | E27: =SUM(E28:E29) -> -6.5609849 | F27: =SUM(F28:F29) -> 0.6175207 | G27: =SUM(G28:G29) -> 115.88506 | H27: =SUM(H28:H29) -> 12.42969 | I27: =SUM(I28:I29) -> 27.680013 | J27: =SUM(J28:J29) -> 31.990655 | ... M27: =SUM(M28:M29) -> 54.042073 | O27: =+O28+O29 -> -0.9929 | P27: =+P28+P29 -> 1.6104207 | Q27: =+Q28+Q29 -> 5.4403959 | R27: =+R28+R29 -> 110.44466 | S27: =+S28+S29 -> 32.020056 | T27: =+T28+T29 -> -19.590366 | U27: =+U28+U29 -> 71.069749 | V27: =+V28+V29 -> -43.389736 | ... Y27: =+Y28+Y29 -> 77.368274
B28: Impairment losses on property, plant and equipment | C28: ='Raw Data'!C25 -> -0.5354 | D28: ='Raw Data'!D25 -> -2.2846109 | E28: ='Raw Data'!E25 -> -6.5609849 | F28: ='Raw Data'!F25 -> 0.6175207 | G28: ='Raw Data'!G25 -> -0.78503444 | H28: ='Raw Data'!H25 -> -0.35814105 | I28: ='Raw Data'!I25 -> -1.6924196 | J28: ='Raw Data'!J25 -> -0.95792708 | K28: =+J28 -> -0.95792708 | L28: =+K28 -> -0.95792708 | M28: =+L28 -> -0.95792708 | O28: =Segment!V54 -> -0.9929 | P28: =Segment!W54 -> 1.6104207 | Q28: =Segment!X54 -> -0.76998364 | R28: =Segment!Y54 -> -0.0150508 | S28: =Segment!Z54 -> -0.8589465 | T28: =Segment!AA54 -> 0.50080545 | U28: =Segment!AB54 -> -1.24818 | V28: =Segment!AC54 -> -0.44423958 | ... Y28: =Segment!AF54 -> -1.9277012
B29: net gains/loss of fair value | C29: ='Raw Data'!C26 -> 0 | D29: ='Raw Data'!D26 -> 0 | E29: ='Raw Data'!E26 -> 0 | F29: ='Raw Data'!F26 -> 0 | G29: ='Raw Data'!G26 -> 116.67009 | H29: ='Raw Data'!H26 -> 12.787831 | I29: ='Raw Data'!I26 -> 29.372433 | J29: ='Raw Data'!J26 -> 32.948582 | K29: 201 | L29: 50 | M29: =+L29*1.1 -> 55 | O29: =Segment!V55 -> 0 | P29: =Segment!W55 -> 0 | Q29: =Segment!X55 -> 6.2103795 | R29: =Segment!Y55 -> 110.45971 | S29: =Segment!Z55 -> 32.879002 | T29: =Segment!AA55 -> -20.091171 | U29: =Segment!AB55 -> 72.317929 | V29: =Segment!AC55 -> -42.945496 | ... Y29: =Segment!AF55 -> 79.295975
B30: EBITDA | C30: =C20+C27+C23-C33-C34 -> 380.2942 | D30: =D20+D27+D23-D33-D34 -> 326.33306 | E30: =E20+E27+E23-E33-E34 -> 813.01568 | F30: =F20+F27+F23-F33-F34 -> 1135.5715 | G30: =G20+G27+G23-G33-G34 -> 1657.6191 | H30: =H20+H27+H23-H33-H34 -> 1995.1044 | I30: =I20+I27+I23-I33-I34 -> 2633.1921 | J30: =J20+J27+J23-J33-J34 -> 4143.1356 | ... M30: =M20+M27+M23-M33-M34 -> 8873.3424 | O30: =O20+O27+O23-O33-O34 -> 566.5236 | P30: =P20+P27+P23-P33-P34 -> 434.60519 | Q30: =Q20+Q27+Q23-Q33-Q34 -> 931.64747 | R30: =R20+R27+R23-R33-R34 -> 725.97164 | S30: =S20+S27+S23-S33-S34 -> 1078.2342 | T30: =T20+T27+T23-T33-T34 -> 916.87019 | U30: =U20+U27+U23-U33-U34 -> 1442.3025 | V30: =V20+V27+V23-V33-V34 -> 1190.8897 | ... Y30: =Y20+Y27+Y23-Y33-Y34 -> 3087.0991
B31: yoy % | C31: =IF(ISERROR(C30/#REF!-1)," ",(C30/#REF!-1)) | D31: =IF(ISERROR(D30/C30-1)," ",(D30/C30-1)) -> -0.14189314 | E31: =IF(ISERROR(E30/D30-1)," ",(E30/D30-1)) -> 1.4913678 | F31: =IF(ISERROR(F30/E30-1)," ",(F30/E30-1)) -> 0.39674003 | G31: =IF(ISERROR(G30/F30-1)," ",(G30/F30-1)) -> 0.45972231 | H31: =IF(ISERROR(H30/G30-1)," ",(H30/G30-1)) -> 0.20359641 | I31: =IF(ISERROR(I30/H30-1)," ",(I30/H30-1)) -> 0.31982674 | J31: =IF(ISERROR(J30/I30-1)," ",(J30/I30-1)) -> 0.57342698 | K31: =IF(ISERROR(K30/J30-1)," ",(K30/J30-1)) -> 0.41242202 | ... M31: =IF(ISERROR(M30/L30-1)," ",(M30/L30-1)) -> 0.22004005
B33: Depreciation | C33: =+'Raw Data'!C31 -> 0 | D33: =+'Raw Data'!D31 -> -77.859575 | E33: =+'Raw Data'!E31 -> -102.17591 | F33: =+'Raw Data'!F31 -> -124.5853 | G33: =+'Raw Data'!G31 -> -173.1049 | H33: =+'Raw Data'!H31 -> -211.99102 | I33: =+'Raw Data'!I31 -> -241.69914 | J33: =+'Raw Data'!J31 -> -325.93172 | K33: =-Capex!L21 -> -392.57668 | L33: =-Capex!M21 -> -473.34602 | M33: =-Capex!N21 -> -691.37348 | Q33: =-Wind!CG237 -> -79.766064 | R33: =+G33-Q33 -> -93.338832 | S33: =-Wind!CK237 -> -99.823009 | T33: =+H33-S33 -> -112.16801 | U33: =-Wind!CO237 -> -114.75822 | V33: =+I33-U33 -> -126.94092 | W33: =-Wind!CS237 -> -154.38297 | X33: =+J33-W33 -> -171.54875 | Y33: =+K33-X33 -> -221.02793
B34: Amortization | C34: =+'Raw Data'!C32 -> 0 | D34: =+'Raw Data'!D32 -> -7.1119131 | E34: =+'Raw Data'!E32 -> -7.5485512 | F34: =+'Raw Data'!F32 -> -9.8574461 | G34: =+'Raw Data'!G32 -> -12.007907 | H34: =+'Raw Data'!H32 -> -11.95035 | I34: =+'Raw Data'!I32 -> -12.33999 | J34: =+'Raw Data'!J32 -> -17.11997 | K34: =-(Capex!L30+Capex!L38) -> -23.639184 | L34: =-(Capex!M30+Capex!M38) -> -32.629976 | M34: =-(Capex!N30+Capex!N38) -> -42.739316 | Q34: =-SUM(Wind!CG238:CG240) -> -9.8495758 | R34: =+G34-Q34 -> -2.1583314 | S34: =-SUM(Wind!CK238:CK240) -> -16.565221 | T34: =+H34-S34 -> 4.6148708 | U34: =-SUM(Wind!CO238:CO240) -> -14.771789 | V34: =+I34-U34 -> 2.4317986 | W34: =-SUM(Wind!CS238:CS240) -> -17.253343 | X34: =+J34-W34 -> 0.13337303 | Y34: =+K34-X34 -> -23.772557
B35: EBIT (operating profit) | C35: =C30+C33+C34 -> 380.2942 | D35: =D30+D33+D34 -> 241.36158 | E35: =E30+E33+E34 -> 703.29121 | F35: =F30+F33+F34 -> 1001.1288 | G35: =G30+G33+G34 -> 1472.5063 | H35: =H30+H33+H34 -> 1771.163 | I35: =I30+I33+I34 -> 2379.153 | J35: =J30+J33+J34 -> 3800.0839 | ... M35: =M30+M33+M34 -> 8139.2296 | O35: =O30+O33+O34 -> 566.5236 | P35: =P30+P33+P34 -> 434.60519 | Q35: =Q30+Q33+Q34 -> 842.03183 | R35: =R30+R33+R34 -> 630.47447 | S35: =S30+S33+S34 -> 961.84599 | T35: =T30+T33+T34 -> 809.31704 | U35: =U30+U33+U34 -> 1312.7725 | V35: =V30+V33+V34 -> 1066.3806 | ... Y35: =Y30+Y33+Y34 -> 2842.2986
B36: yoy % | C36: =IF(ISERROR(C35/#REF!-1)," ",(C35/#REF!-1)) | D36: =IF(ISERROR(D35/C35-1)," ",(D35/C35-1)) -> -0.36532933 | E36: =IF(ISERROR(E35/D35-1)," ",(E35/D35-1)) -> 1.9138491 | F36: =IF(ISERROR(F35/E35-1)," ",(F35/E35-1)) -> 0.42349111 | G36: =IF(ISERROR(G35/F35-1)," ",(G35/F35-1)) -> 0.47084603 | H36: =IF(ISERROR(H35/G35-1)," ",(H35/G35-1)) -> 0.20282204 | I36: =IF(ISERROR(I35/H35-1)," ",(I35/H35-1)) -> 0.34327161 | J36: =IF(ISERROR(J35/I35-1)," ",(J35/I35-1)) -> 0.59724232 | K36: =IF(ISERROR(K35/J35-1)," ",(K35/J35-1)) -> 0.43040001 | ... M36: =IF(ISERROR(M35/L35-1)," ",(M35/L35-1)) -> 0.2027796
B37: EBIT margin | C37: =C35/C13 -> 0.13372712 | D37: =D35/D13 -> 0.079459659 | E37: =E35/E13 -> 0.16710301 | F37: =F35/F13 -> 0.20190143 | G37: =G35/G13 -> 0.21102662 | H37: =H35/H13 -> 0.20824008 | I37: =I35/I13 -> 0.21124003 | J37: =J35/J13 -> 0.23992168 | ... M37: =M35/M13 -> 0.27320198
B38: Net financial expenses | C38: ='Raw Data'!C42 -> -10.454 | D38: ='Raw Data'!D42 -> -5.0820752 | E38: ='Raw Data'!E42 -> 13.965657 | F38: ='Raw Data'!F42 -> 15.93094 | G38: ='Raw Data'!G42 -> 11.393957 | H38: ='Raw Data'!H42 -> -41.039484 | I38: ='Raw Data'!I42 -> -2.2856168 | J38: ='Raw Data'!J42 -> 190.53573 | K38: =SUM(K39:K42) -> 139.04711 | L38: =SUM(L39:L42) -> 191.45248 | M38: =SUM(M39:M42) -> 208.22262 | O38: =Segment!V53 -> -6.822 | P38: =Segment!W53 -> 22.75294 | Q38: =Segment!X53 -> -4.2964605 | R38: =Segment!Y53 -> 15.690418 | S38: =Segment!Z53 -> 20.767388 | T38: =Segment!AA53 -> -61.806872 | U38: =Segment!AB53 -> -5.2930758 | V38: =Segment!AC53 -> 3.007459 | ... Y38: =Segment!AF53 -> 64.222622
B39: Interest income | C39: ='Raw Data'!C38 -> 0 | D39: ='Raw Data'!D38 -> 2.7387298 | E39: ='Raw Data'!E38 -> 20.080901 | F39: ='Raw Data'!F38 -> 26.040389 | G39: ='Raw Data'!G38 -> 29.262542 | H39: ='Raw Data'!H38 -> 19.820948 | I39: ='Raw Data'!I38 -> 122.48631 | J39: ='Raw Data'!J38 -> 260.35607 | K39: =K96 -> 270.40038 | L39: =L96 -> 322.80575 | M39: =M96 -> 339.57589 | U39: -39.203 | V39: =I39-U39 -> 161.68931 | W39: -137.1066 | X39: =J39-W39 -> 397.46267 | Y39: =K39-X39 -> -127.06229
B40: Interest expense | C40: ='Raw Data'!C39 -> 0 | D40: ='Raw Data'!D39 -> -6.9068465 | E40: ='Raw Data'!E39 -> -5.4021294 | F40: ='Raw Data'!F39 -> -9.7758555 | G40: ='Raw Data'!G39 -> -13.6159 | H40: ='Raw Data'!H39 -> -52.681528 | I40: ='Raw Data'!I39 -> -80.086468 | J40: ='Raw Data'!J39 -> -97.913831 | K40: =K101 -> -131.35327 | L40: =L101 -> -131.35327 | M40: =M101 -> -131.35327 | U40: 35.908 | V40: =I40-U40 -> -115.99447 | W40: 39.70533 | X40: =J40-W40 -> -137.61916 | Y40: =K40-X40 -> 6.2658887
B41: Foreign exchange gain/(loss) | C41: ='Raw Data'!C40 -> 0 | D41: ='Raw Data'!D40 -> 0 | E41: ='Raw Data'!E40 -> 0 | F41: ='Raw Data'!F40 -> 0 | G41: ='Raw Data'!G40 -> -1.1902858 | H41: ='Raw Data'!H40 -> -0.78293142 | I41: ='Raw Data'!I40 -> -40.865641 | J41: ='Raw Data'!J40 -> 44.716061 | K41: 0 | L41: 0 | M41: 0 | U41: -5.787 | V41: =I41-U41 -> -35.078641 | W41: -16.3875 | X41: =J41-W41 -> 61.103561 | Y41: =K41-X41 -> -61.103561
B42: Other finanical costs | C42: ='Raw Data'!C41 -> 0 | D42: ='Raw Data'!D41 -> -0.91395851 | E42: ='Raw Data'!E41 -> -0.71311416 | F42: ='Raw Data'!F41 -> -0.33359337 | G42: ='Raw Data'!G41 -> -3.0623987 | H42: ='Raw Data'!H41 -> -7.3959719 | I42: ='Raw Data'!I41 -> -3.8198143 | J42: ='Raw Data'!J41 -> -16.622567 | K42: 0 | L42: 0 | M42: 0 | U42: =1.423+2.366 -> 3.789 | V42: =I42-U42 -> -7.6088143 | W42: =6.756+2.588 -> 9.344 | X42: =J42-W42 -> -25.966567 | Y42: =K42-X42 -> 25.966567
B43: Investment gains/loss | C43: ='Raw Data'!C44 -> 19.021 | D43: ='Raw Data'!D44 -> 13.060716 | E43: ='Raw Data'!E44 -> 7.1893001 | F43: ='Raw Data'!F44 -> 9.8371246 | G43: ='Raw Data'!G44 -> 22.526716 | H43: ='Raw Data'!H44 -> 70.018458 | I43: ='Raw Data'!I44 -> 141.5636 | J43: ='Raw Data'!J44 -> 95.315854 | K43: =K44+K45 -> 110 | L43: =L44+L45 -> 110 | M43: =M44+M45 -> 110 | O43: =Segment!V56 -> 3.9174 | P43: =Segment!W56 -> 5.9197246 | Q43: =Segment!X56 -> 9.5305684 | R43: =Segment!Y56 -> 12.996147 | S43: =Segment!Z56 -> 15.019116 | T43: =Segment!AA56 -> 54.999342 | U43: =Segment!AB56 -> 72.838273 | V43: =Segment!AC56 -> 68.725327 | ... Y43: =Segment!AF56 -> 56.70621
B44: Net income from associates or jointly controlled entities | C44: ='Raw Data'!C45 -> 0 | D44: ='Raw Data'!D45 -> 0 | E44: ='Raw Data'!E45 -> 0 | F44: ='Raw Data'!F45 -> 0 | G44: ='Raw Data'!G45 -> 0 | H44: ='Raw Data'!H45 -> 0 | I44: ='Raw Data'!I45 -> 0 | J44: ='Raw Data'!J45 -> 0 | K44: =K108*K109 -> 0 | L44: =L108*L109 -> 0 | M44: =M108*M109 -> 0
B45: Other investment gains/loss | C45: ='Raw Data'!C46 -> 19.021 | D45: ='Raw Data'!D46 -> 13.060716 | E45: ='Raw Data'!E46 -> 7.1893001 | F45: ='Raw Data'!F46 -> 9.8371246 | G45: ='Raw Data'!G46 -> 22.526716 | H45: ='Raw Data'!H46 -> 70.018458 | I45: ='Raw Data'!I46 -> 141.5636 | J45: ='Raw Data'!J46 -> 95.315854 | K45: 110 | L45: =K45 -> 110 | M45: =L45 -> 110
B46: Other income/loss | C46: =+Wind!U35 -> 10.3 | D46: =+Wind!V35 -> 25.5671 | E46: =+Wind!W35 -> 16.1863 | F46: =+Wind!X35 -> 23.4037 | G46: =+Wind!Y35 -> 22.13033 | H46: =+Wind!Z35 -> 54.124659 | I46: =+Wind!AA35 -> 69.936747 | J46: =+Wind!AB35 -> 58.83458 | K46: 85 | L46: =+Segment!O58 -> 76 | M46: =+Segment!P58 -> 68.4 | O46: =Segment!V58 -> 6.93 | P46: =Segment!W58 -> 16.4737 | Q46: =Segment!X58 -> 11.25573 | R46: =Segment!Y58 -> 10.8746 | S46: =Segment!Z58 -> 9.1197664 | T46: =Segment!AA58 -> 45.004893 | U46: =Segment!AB58 -> 10.470394 | V46: =Segment!AC58 -> 59.466353 | ... Y46: =Segment!AF58 -> 43.539441
B47: Other non-operating income/expense | C47: =+'Raw Data'!C49 -> -9.3561 | D47: =+'Raw Data'!D49 -> -1.5794621 | E47: =+'Raw Data'!E49 -> -4.1295241 | F47: =+'Raw Data'!F49 -> -20.750899 | G47: =+'Raw Data'!G49 -> -15.04049 | H47: =+'Raw Data'!H49 -> -18.256918 | I47: =+'Raw Data'!I49 -> -9.0968043 | J47: =+'Raw Data'!J49 -> -37.457737 | K47: =K48+K49 -> -30.607988 | L47: =L48+L49 -> -30.607988 | M47: =M48+M49 -> -30.607988 | O47: =+O48+O49 -> -19.2511 | P47: =+P48+P49 -> -1.4997988 | Q47: =+Q48+Q49 -> -7.2484096 | R47: =+R48+R49 -> -7.7920806 | S47: =+S48+S49 -> -4.2061026 | T47: =+T48+T49 -> -14.050815 | U47: =+U48+U49 -> 0.79416812 | V47: =+V48+V49 -> -9.8909724 | ... Y47: =+Y48+Y49 -> -5.1974055
B48: Other non-operating income | C48: ='Raw Data'!C47 -> 0.7278 | D48: ='Raw Data'!D47 -> 1.4104558 | E48: ='Raw Data'!E47 -> 1.7989782 | F48: ='Raw Data'!F47 -> 1.9748555 | G48: ='Raw Data'!G47 -> 2.1570989 | H48: ='Raw Data'!H47 -> 2.3318255 | I48: ='Raw Data'!I47 -> 2.1691309 | J48: ='Raw Data'!J47 -> 2.1502505 | K48: 9 | L48: =+K48 -> 9 | M48: =+L48 -> 9 | O48: =Segment!V59 -> 0.6355 | P48: =Segment!W59 -> 1.3393555 | Q48: =Segment!X59 -> 1.1791738 | R48: =Segment!Y59 -> 0.97792507 | S48: =Segment!Z59 -> 1.1675729 | T48: =Segment!AA59 -> 1.1642526 | U48: =Segment!AB59 -> 1.2054725 | V48: =Segment!AC59 -> 0.96365846 | ... Y48: =Segment!AF59 -> 4.3003498
B49: Other non-operating expense | C49: ='Raw Data'!C48 -> -10.0839 | D49: ='Raw Data'!D48 -> -2.9899179 | E49: ='Raw Data'!E48 -> -5.9285023 | F49: ='Raw Data'!F48 -> -22.725754 | G49: ='Raw Data'!G48 -> -17.197589 | H49: ='Raw Data'!H48 -> -20.588743 | I49: ='Raw Data'!I48 -> -11.265935 | J49: ='Raw Data'!J48 -> -39.607988 | K49: =J49 -> -39.607988 | L49: =K49 -> -39.607988 | M49: =L49 -> -39.607988 | O49: =-Segment!V60 -> -19.8866 | P49: =-Segment!W60 -> -2.8391543 | Q49: =-Segment!X60 -> -8.4275834 | R49: =-Segment!Y60 -> -8.7700056 | S49: =-Segment!Z60 -> -5.3736755 | T49: =-Segment!AA60 -> -15.215068 | U49: =-Segment!AB60 -> -0.41130436 | V49: =-Segment!AC60 -> -10.854631 | ... Y49: =-Segment!AF60 -> -9.4977554
B50: Pre-tax profit (income before tax) | C50: =C35+C47+C38+C43+C46 -> 389.8051 | D50: =D35+D47+D38+D43+D46 -> 273.32785 | E50: =E35+E47+E38+E43+E46 -> 736.50294 | F50: =F35+F47+F38+F43+F46 -> 1029.5497 | G50: =G35+G47+G38+G43+G46 -> 1513.5168 | H50: =H35+H47+H38+H43+H46 -> 1836.0097 | I50: =I35+I47+I38+I43+I46 -> 2579.2709 | J50: =J35+J47+J38+J43+J46 -> 4107.3123 | ... M50: =M35+M47+M38+M43+M46 -> 8495.2442 | O50: =O35+O47+O38+O43+O46 -> 551.2979 | P50: =P35+P47+P38+P43+P46 -> 478.25175 | Q50: =Q35+Q47+Q38+Q43+Q46 -> 851.27326 | R50: =R35+R47+R38+R43+R46 -> 662.24356 | S50: =S35+S47+S38+S43+S46 -> 1002.5462 | T50: =T35+T47+T38+T43+T46 -> 833.46359 | U50: =U35+U47+U38+U43+U46 -> 1391.5822 | V50: =V35+V47+V38+V43+V46 -> 1187.6887 | ... Y50: =Y35+Y47+Y38+Y43+Y46 -> 3001.5695
B51: yoy % | C51: =IF(ISERROR(C50/#REF!-1)," ",(C50/#REF!-1)) | D51: =IF(ISERROR(D50/C50-1)," ",(D50/C50-1)) -> -0.29880893 | E51: =IF(ISERROR(E50/D50-1)," ",(E50/D50-1)) -> 1.694577 | F51: =IF(ISERROR(F50/E50-1)," ",(F50/E50-1)) -> 0.39788939 | G51: =IF(ISERROR(G50/F50-1)," ",(G50/F50-1)) -> 0.47007656 | H51: =IF(ISERROR(H50/G50-1)," ",(H50/G50-1)) -> 0.21307522 | I51: =IF(ISERROR(I50/H50-1)," ",(I50/H50-1)) -> 0.4048242 | J51: =IF(ISERROR(J50/I50-1)," ",(J50/I50-1)) -> 0.59243151 | K51: =IF(ISERROR(K50/J50-1)," ",(K50/J50-1)) -> 0.39728336 | ... M51: =IF(ISERROR(M50/L50-1)," ",(M50/L50-1)) -> 0.1941819
B53: Income taxes | C53: =+'Raw Data'!C54 -> -93.6393 | D53: =+'Raw Data'!D54 -> -57.496914 | E53: =+'Raw Data'!E54 -> -165.92903 | F53: =+'Raw Data'!F54 -> -217.48614 | G53: =+'Raw Data'!G54 -> -320.55641 | H53: =+'Raw Data'!H54 -> -395.48918 | I53: =+'Raw Data'!I54 -> -539.49813 | J53: =+'Raw Data'!J54 -> -780.88329 | K53: =-(K50-K44)*K89 -> -1176.5112 | L53: =-(L50-L44)*L89 -> -1458.3415 | M53: =-(M50-M44)*M89 -> -1741.5251 | O53: =-Segment!V62 -> -123.6327 | P53: =-Segment!W62 -> -93.853439 | Q53: =-Segment!X62 -> -184.04005 | R53: =-Segment!Y62 -> -136.51636 | S53: =-Segment!Z62 -> -206.3816 | T53: =-Segment!AA62 -> -189.10757 | U53: =-Segment!AB62 -> -294.04553 | V53: =-Segment!AC62 -> -245.4526 | ... Y53: =-Segment!AF62 -> -627.05491
B54: Minority interest | C54: =-'Raw Data'!C55 -> 0 | D54: =-'Raw Data'!D55 -> 0 | E54: =-'Raw Data'!E55 -> 0 | F54: =-'Raw Data'!F55 -> 0 | G54: =-'Raw Data'!G55 -> 0 | H54: =-'Raw Data'!H55 -> 0 | I54: =-'Raw Data'!I55 -> 0 | J54: =-'Raw Data'!J55 -> 0.27984775 | K54: =J54 -> 0.27984775 | L54: =K54 -> 0.27984775 | M54: =L54 -> 0.27984775 | O54: =-Segment!V64 -> 0 | P54: =-Segment!W64 -> 0 | Q54: =-Segment!X64 -> 0 | R54: =-Segment!Y64 -> 0 | S54: =-Segment!Z64 -> 0 | T54: =-Segment!AA64 -> 0 | U54: =-Segment!AB64 -> 0 | V54: =-Segment!AC64 -> 0 | ... Y54: =-Segment!AF64 -> 0
B55: Preferred dividends | C55: =-'Raw Data'!C56 -> 0 | D55: =-'Raw Data'!D56 -> 0 | E55: =-'Raw Data'!E56 -> 0 | F55: =-'Raw Data'!F56 -> 0 | G55: =-'Raw Data'!G56 -> 0 | H55: =-'Raw Data'!H56 -> 0 | I55: =-'Raw Data'!I56 -> 0 | J55: =-'Raw Data'!J56 -> 0 | K55: 0 | L55: 0 | M55: 0
B56: Extraordinary gain/(loss) | C56: =-'Raw Data'!C60 -> 0 | D56: =-'Raw Data'!D60 -> 0 | E56: =-'Raw Data'!E60 -> 0 | F56: =-'Raw Data'!F60 -> 0 | G56: =-'Raw Data'!G60 -> 0 | H56: =-'Raw Data'!H60 -> 0 | I56: =-'Raw Data'!I60 -> 0 | J56: =-'Raw Data'!J60 -> 0 | K56: 0 | L56: 0 | M56: 0
B57: Net income | C57: =IF(ISERROR(C50+C53+C54+C55+C56)," ",C50+C53+C54+C55+C56) -> 296.1658 | D57: =IF(ISERROR(D50+D53+D54+D55+D56)," ",D50+D53+D54+D55+D56) -> 215.83094 | E57: =IF(ISERROR(E50+E53+E54+E55+E56)," ",E50+E53+E54+E55+E56) -> 570.57391 | F57: =IF(ISERROR(F50+F53+F54+F55+F56)," ",F50+F53+F54+F55+F56) -> 812.06352 | G57: =IF(ISERROR(G50+G53+G54+G55+G56)," ",G50+G53+G54+G55+G56) -> 1192.9604 | H57: =IF(ISERROR(H50+H53+H54+H55+H56)," ",H50+H53+H54+H55+H56) -> 1440.5206 | I57: =IF(ISERROR(I50+I53+I54+I55+I56)," ",I50+I53+I54+I55+I56) -> 2039.7728 | J57: =IF(ISERROR(J50+J53+J54+J55+J56)," ",J50+J53+J54+J55+J56) -> 3326.7089 | K57: =+K50+K53+K54+K55+K56 -> 4562.8478 | L57: =+L50+L53+L54+L55+L56 -> 5655.7995 | M57: =+M50+M53+M54+M55+M56 -> 6753.999 | N57: =(M57/J57)^(1/3)-1 -> 0.26623817 | O57: =IF(ISERROR(O50+O53+O54+O55+O56)," ",O50+O53+O54+O55+O56) -> 427.6652 | P57: =IF(ISERROR(P50+P53+P54+P55+P56)," ",P50+P53+P54+P55+P56) -> 384.39832 | Q57: =IF(ISERROR(Q50+Q53+Q54+Q55+Q56)," ",Q50+Q53+Q54+Q55+Q56) -> 667.23321 | R57: =IF(ISERROR(R50+R53+R54+R55+R56)," ",R50+R53+R54+R55+R56) -> 525.7272 | S57: =IF(ISERROR(S50+S53+S54+S55+S56)," ",S50+S53+S54+S55+S56) -> 796.16455 | T57: =IF(ISERROR(T50+T53+T54+T55+T56)," ",T50+T53+T54+T55+T56) -> 644.35602 | U57: =IF(ISERROR(U50+U53+U54+U55+U56)," ",U50+U53+U54+U55+U56) -> 1097.5367 | V57: =IF(ISERROR(V50+V53+V54+V55+V56)," ",V50+V53+V54+V55+V56) -> 942.23612 | ... Y57: =IF(ISERROR(Y50+Y53+Y54+Y55+Y56)," ",Y50+Y53+Y54+Y55+Y56) -> 2374.5146
B58: yoy % | C58: =IF(ISERROR(C57/#REF!-1)," ",(C57/#REF!-1)) | D58: =IF(ISERROR(D57/C57-1)," ",(D57/C57-1)) -> -0.27124962 | E58: =IF(ISERROR(E57/D57-1)," ",(E57/D57-1)) -> 1.643615 | F58: =IF(ISERROR(F57/E57-1)," ",(F57/E57-1)) -> 0.42323983 | G58: =IF(ISERROR(G57/F57-1)," ",(G57/F57-1)) -> 0.46904815 | H58: =IF(ISERROR(H57/G57-1)," ",(H57/G57-1)) -> 0.2075175 | I58: =IF(ISERROR(I57/H57-1)," ",(I57/H57-1)) -> 0.415997 | J58: =IF(ISERROR(J57/I57-1)," ",(J57/I57-1)) -> 0.63092127 | K58: =IF(ISERROR(K57/J57-1)," ",(K57/J57-1)) -> 0.37158013 | ... M58: =IF(ISERROR(M57/L57-1)," ",(M57/L57-1)) -> 0.19417229
K59: =K57/4227.8-1 -> 0.079248725 | L59: =L57/5301.6-1 -> 0.066809922
B60: EPS - basic | C60: =IF(ISERROR(C57/C70)," ",C57/C70) -> 1.9637077 | D60: =IF(ISERROR(D57/D70)," ",D57/D70) -> 0.47435372 | E60: =IF(ISERROR(E57/E70)," ",E57/E70) -> 1.219175 | F60: =IF(ISERROR(F57/F70)," ",F57/F70) -> 1.7351785 | G60: =IF(ISERROR(G57/G70)," ",G57/G70) -> 2.2940973 | H60: =IF(ISERROR(H57/H70)," ",H57/H70) -> 2.7701626 | I60: =IF(ISERROR(I57/I70)," ",I57/I70) -> 3.9225419 | J60: =IF(ISERROR(J57/J70)," ",J57/J70) -> 6.3973571 | K60: =IF(ISERROR(K57/K72)," ",K57/K72) -> 8.7744879 | L60: =IF(ISERROR(L57/L72)," ",L57/L72) -> 10.876266 | M60: =IF(ISERROR(M57/M72)," ",M57/M72) -> 12.988135
B61: EPS - fully diluted | C61: =IF(ISERROR(C57/C71)," ",C57/C71) -> 1.9637077 | D61: =IF(ISERROR(D57/D71)," ",D57/D71) -> 0.47435372 | E61: =IF(ISERROR(E57/E71)," ",E57/E71) -> 1.219175 | F61: =IF(ISERROR(F57/F71)," ",F57/F71) -> 1.7351785 | G61: =IF(ISERROR(G57/G71)," ",G57/G71) -> 2.2940973 | H61: =IF(ISERROR(H57/H71)," ",H57/H71) -> 2.7701626 | I61: =IF(ISERROR(I57/I71)," ",I57/I71) -> 3.9225419 | J61: =IF(ISERROR(J57/J71)," ",J57/J71) -> 6.3973571 | K61: =IF(ISERROR(K57/K72)," ",K57/K72) -> 8.7744879 | L61: =IF(ISERROR(L57/L72)," ",L57/L72) -> 10.876266 | M61: =IF(ISERROR(M57/M72)," ",M57/M72) -> 12.988135
B64: Dividend declared, last year final | H64: =G67 -> -600.015 | I64: =H67 -> -800.02 | J64: =I67 -> -1000.025 | K64: =J67 -> -1300.0325 | L64: =K67 -> -3154.7132 | M64: =L67 -> -3910.3705
B65: Dividend declared, current year interim | G65: -600.015 | H65: 0 | I65: 0 | J65: -1000.025 | K65: 0 | L65: 0 | M65: 0
B66: Impact on current year cash flow statement | G66: =SUM(G64:G65) -> -600.015 | H66: =SUM(H64:H65) -> -600.015 | I66: =SUM(I64:I65) -> -800.02 | J66: =SUM(J64:J65) -> -2000.05 | K66: =SUM(K64:K65) -> -1300.0325 | L66: =SUM(L64:L65) -> -3154.7132 | M66: =SUM(M64:M65) -> -3910.3705
B67: Dividend proposed, current year final | G67: =-'Raw Data'!G71 -> -600.015 | H67: =-'Raw Data'!H71 -> -800.02 | I67: =-'Raw Data'!I71 -> -1000.025 | J67: =-'Raw Data'!J71 -> -1300.0325 | K67: =K68 -> -3154.7132 | L67: =L68 -> -3910.3705 | M67: =M68 -> -4669.656
B68: Total common dividends declared, current year | D68: =-'Raw Data'!D71 -> 0 | E68: =-'Raw Data'!E71 -> 0 | F68: =-'Raw Data'!F71 -> 0 | G68: =G67+G65 -> -1200.03 | H68: =H67+H65 -> -800.02 | I68: =I67+I65 -> -1000.025 | J68: =J67+J65 -> -2300.0575 | K68: =IF(ISERROR(-K57*K184)," ",(-K57*K184)) -> -3154.7132 | L68: =IF(ISERROR(-L57*L184)," ",(-L57*L184)) -> -3910.3705 | M68: =IF(ISERROR(-M57*M184)," ",(-M57*M184)) -> -4669.656
B69: Dividends per share | C69: =IF(ISERROR(-C68/C70)," ",-C68/C70) -> 0 | D69: =IF(ISERROR(-D68/D70)," ",-D68/D70) -> 0 | E69: =IF(ISERROR(-E68/E70)," ",-E68/E70) -> 0 | F69: =IF(ISERROR(-F68/F70)," ",-F68/F70) -> 0 | G69: =IF(ISERROR(-G68/G70)," ",-G68/G70) -> 2.3076923 | H69: =IF(ISERROR(-H68/H70)," ",-H68/H70) -> 1.5384615 | I69: =IF(ISERROR(-I68/I70)," ",-I68/I70) -> 1.9230769 | J69: =-J65/W70+-J67/J70 -> 4.4230769 | K69: =MAX(0,K184*K60) -> 6.0666044 | L69: =MAX(0,L184*L60) -> 7.5197552 | M69: =MAX(0,M184*M60) -> 8.9798833
B70: Weighted avg. adj. shares outstanding (mn) | C70: =+'Raw Data'!C74 -> 150.8197 | D70: =+'Raw Data'!D74*1.3 -> 455 | E70: =+'Raw Data'!E74*1.3 -> 468 | F70: =+'Raw Data'!F74*1.3 -> 468 | G70: =+'Raw Data'!G74*1.3 -> 520.013 | H70: =+'Raw Data'!H74*1.3 -> 520.013 | I70: =+'Raw Data'!I74*1.3 -> 520.013 | J70: =I72*(1+J185) -> 520.013 | K70: =J72*(1+K185) -> 520.013 | L70: =K72*(1+L185) -> 520.013 | M70: =L72*(1+M185) -> 520.013 | Q70: =G70 -> 520.013 | W70: =I70 -> 520.013 | Y70: =K70 -> 520.013
B71: Fully diluted shares outstanding (mn) | C71: =+'Raw Data'!C75 -> 150.8197 | D71: =+'Raw Data'!D75*1.3 -> 455 | E71: =+'Raw Data'!E75*1.3 -> 468 | F71: =+'Raw Data'!F75*1.3 -> 468 | G71: =+'Raw Data'!G75*1.3 -> 520.013 | H71: =+'Raw Data'!H75*1.3 -> 520.013 | I71: =+'Raw Data'!I75*1.3 -> 520.013 | J71: =J72 -> 520.013 | K71: =+J71 -> 520.013 | L71: =+K71 -> 520.013 | M71: =+L71 -> 520.013 | Q71: =G71 -> 520.013 | W71: =W72 -> 520.013 | Y71: =Y72 -> 520.013
B72: Period end shares outstanding (mn) | C72: =+'Raw Data'!C76 -> 150.8197 | D72: =+'Raw Data'!D76*1.3 -> 455 | E72: =+'Raw Data'!E76*1.3 -> 468 | F72: =+'Raw Data'!F76*1.3 -> 468 | G72: =+'Raw Data'!G76*1.3 -> 520.013 | H72: =+'Raw Data'!H76*1.3 -> 520.013 | I72: =+'Raw Data'!I76*1.3 -> 520.013 | J72: =I72 -> 520.013 | K72: =+J72 -> 520.013 | L72: =+K72 -> 520.013 | M72: =+L72 -> 520.013 | Q72: =G72 -> 520.013 | W72: =I72 -> 520.013 | Y72: =K72 -> 520.013
I73: 400.01 | J73: 400.01
B75: Margin and growth analysis | C75: =C4 -> 2017 | D75: =D4 -> 2018 | E75: =E4 -> 2019 | F75: =F4 -> 2020 | G75: =G4 -> 2021 | H75: =H4 -> 2022 | I75: =I4 -> 2023 | J75: =J4 -> 2024 | ... M75: =M4 -> 2027E | O75: =O4 -> 1H20 | P75: =P4 -> 2H20 | Q75: =Q4 -> 1H21 | R75: =R4 -> 2H21 | S75: =S4 -> 1H22 | T75: =T4 -> 2H22 | U75: =U4 -> 1H23 | V75: =V4 -> 2H23 | ... Y75: =Y4 -> 1H25
B77: % of sales
B78: COGS (wages and staff welfare) | C78: =IF(ISERROR(-C16/C$13)," ",-C16/C$13) -> 0.52077883 | D78: =IF(ISERROR(-D16/D$13)," ",-D16/D$13) -> 0.5403202 | E78: =IF(ISERROR(-E16/E$13)," ",-E16/E$13) -> 0.53263575 | F78: =IF(ISERROR(-F16/F$13)," ",-F16/F$13) -> 0.53400143 | G78: =IF(ISERROR(-G16/G$13)," ",-G16/G$13) -> 0.55627165 | H78: =IF(ISERROR(-H16/H$13)," ",-H16/H$13) -> 0.57674739 | I78: =IF(ISERROR(-I16/I$13)," ",-I16/I$13) -> 0.56927737 | J78: =IF(ISERROR(-J16/J$13)," ",-J16/J$13) -> 0.55190623 | ... M78: =IF(ISERROR(-M16/M$13)," ",-M16/M$13) -> 0.53782015 | O78: =IF(ISERROR(-O16/O$13)," ",-O16/O$13) -> 0.53560234 | P78: =IF(ISERROR(-P16/P$13)," ",-P16/P$13) -> 0.53241312 | Q78: =IF(ISERROR(-Q16/Q$13)," ",-Q16/Q$13) -> 0.50320013 | R78: =IF(ISERROR(-R16/R$13)," ",-R16/R$13) -> 0.61557057 | S78: =IF(ISERROR(-S16/S$13)," ",-S16/S$13) -> 0.57319628 | T78: =IF(ISERROR(-T16/T$13)," ",-T16/T$13) -> 0.58036352 | U78: =IF(ISERROR(-U16/U$13)," ",-U16/U$13) -> 0.56895707 | V78: =IF(ISERROR(-V16/V$13)," ",-V16/V$13) -> 0.56957876 | ... Y78: =IF(ISERROR(-Y16/Y$13)," ",-Y16/Y$13) -> 0.54853482
B79: Others | C79: =IF(ISERROR(-C17/C$13)," ",-C17/C$13) -> 0 | D79: =IF(ISERROR(-D17/D$13)," ",-D17/D$13) -> 0 | E79: =IF(ISERROR(-E17/E$13)," ",-E17/E$13) -> 0 | F79: =IF(ISERROR(-F17/F$13)," ",-F17/F$13) -> 0 | G79: =IF(ISERROR(-G17/G$13)," ",-G17/G$13) -> 0 | H79: =G79 -> 0 | I79: =H79 -> 0 | J79: =I79 -> 0 | K79: =J79 -> 0 | L79: =K79 -> 0 | M79: =L79 -> 0 | O79: =N79 -> 0 | P79: =O79 -> 0 | Q79: =P79 -> 0 | R79: =Q79 -> 0 | S79: =R79 -> 0 | T79: =S79 -> 0 | U79: =T79 -> 0 | V79: =U79 -> 0 | ... Y79: =X79 -> 0
B80: Gross margins | C80: =IF(ISERROR(-C20/C$13)," ",C20/C$13) -> 0.47922117 | D80: =IF(ISERROR(-D20/D$13)," ",D20/D$13) -> 0.4596798 | E80: =IF(ISERROR(-E20/E$13)," ",E20/E$13) -> 0.46736425 | F80: =IF(ISERROR(-F20/F$13)," ",F20/F$13) -> 0.46599857 | G80: =IF(ISERROR(-G20/G$13)," ",G20/G$13) -> 0.44372835 | H80: =IF(ISERROR(-H20/H$13)," ",H20/H$13) -> 0.42325261 | I80: =IF(ISERROR(-I20/I$13)," ",I20/I$13) -> 0.43072263 | J80: =IF(ISERROR(-J20/J$13)," ",J20/J$13) -> 0.44809377 | ... M80: =IF(ISERROR(-M20/M$13)," ",M20/M$13) -> 0.46217985 | N80: =M80-J80 -> 0.014086078 | O80: =IF(ISERROR(-O20/O$13)," ",O20/O$13) -> 0.46439766 | P80: =IF(ISERROR(-P20/P$13)," ",P20/P$13) -> 0.46758688 | Q80: =IF(ISERROR(-Q20/Q$13)," ",Q20/Q$13) -> 0.49679987 | R80: =IF(ISERROR(-R20/R$13)," ",R20/R$13) -> 0.38442943 | S80: =IF(ISERROR(-S20/S$13)," ",S20/S$13) -> 0.42680372 | T80: =IF(ISERROR(-T20/T$13)," ",T20/T$13) -> 0.41963648 | U80: =IF(ISERROR(-U20/U$13)," ",U20/U$13) -> 0.43104293 | V80: =IF(ISERROR(-V20/V$13)," ",V20/V$13) -> 0.43042124 | ... Y80: =IF(ISERROR(-Y20/Y$13)," ",Y20/Y$13) -> 0.45146518
B81: SG&A | C81: =IF(ISERROR(-C23/C$13)," ",-C23/C$13) -> 0.34530578 | D81: =IF(ISERROR(-D23/D$13)," ",-D23/D$13) -> 0.37946801 | E81: =IF(ISERROR(-E23/E$13)," ",-E23/E$13) -> 0.29870233 | F81: =IF(ISERROR(-F23/F$13)," ",-F23/F$13) -> 0.26422167 | G81: =IF(ISERROR(-G23/G$13)," ",-G23/G$13) -> 0.24930936 | H81: =IF(ISERROR(-H23/H$13)," ",-H23/H$13) -> 0.21647392 | I81: =IF(ISERROR(-I23/I$13)," ",-I23/I$13) -> 0.22194025 | J81: =IF(ISERROR(-J23/J$13)," ",-J23/J$13) -> 0.21019185 | ... M81: =IF(ISERROR(-M23/M$13)," ",-M23/M$13) -> 0.19079185 | O81: =IF(ISERROR(-O23/O$13)," ",-O23/O$13) -> 0.2345839 | P81: =IF(ISERROR(-P23/P$13)," ",-P23/P$13) -> 0.29362633 | Q81: =IF(ISERROR(-Q23/Q$13)," ",-Q23/Q$13) -> 0.26960487 | R81: =IF(ISERROR(-R23/R$13)," ",-R23/R$13) -> 0.22663237 | S81: =IF(ISERROR(-S23/S$13)," ",-S23/S$13) -> 0.21012542 | T81: =IF(ISERROR(-T23/T$13)," ",-T23/T$13) -> 0.22293866 | U81: =IF(ISERROR(-U23/U$13)," ",-U23/U$13) -> 0.20363255 | V81: =IF(ISERROR(-V23/V$13)," ",-V23/V$13) -> 0.23916757 | ... Y81: =IF(ISERROR(-Y23/Y$13)," ",-Y23/Y$13) -> 0.19394202
B82: Sales tax and add-on | C82: =IF(ISERROR(-C24/C$13)," ",-C24/C$13) -> 0.016156016 | D82: =IF(ISERROR(-D24/D$13)," ",-D24/D$13) -> 0.013026697 | E82: =IF(ISERROR(-E24/E$13)," ",-E24/E$13) -> 0.010527241 | F82: =IF(ISERROR(-F24/F$13)," ",-F24/F$13) -> 0.010155803 | G82: =IF(ISERROR(-G24/G$13)," ",-G24/G$13) -> 0.011007806 | H82: =IF(ISERROR(-H24/H$13)," ",-H24/H$13) -> 0.010891819 | I82: =IF(ISERROR(-I24/I$13)," ",-I24/I$13) -> 0.0107443 | J82: =IF(ISERROR(-J24/J$13)," ",-J24/J$13) -> 0.010088657 | ... M82: =IF(ISERROR(-M24/M$13)," ",-M24/M$13) -> 0.010088657 | O82: =IF(ISERROR(-O24/O$13)," ",-O24/O$13) -> 0.0096126174 | P82: =IF(ISERROR(-P24/P$13)," ",-P24/P$13) -> 0.010694717 | Q82: =IF(ISERROR(-Q24/Q$13)," ",-Q24/Q$13) -> 0.011292488 | R82: =IF(ISERROR(-R24/R$13)," ",-R24/R$13) -> 0.01068972 | S82: =IF(ISERROR(-S24/S$13)," ",-S24/S$13) -> 0.011104094 | T82: =IF(ISERROR(-T24/T$13)," ",-T24/T$13) -> 0.010675658 | U82: =IF(ISERROR(-U24/U$13)," ",-U24/U$13) -> 0.010891454 | V82: =IF(ISERROR(-V24/V$13)," ",-V24/V$13) -> 0.010605831 | ... Y82: =IF(ISERROR(-Y24/Y$13)," ",-Y24/Y$13) -> 0.010182826
B83: Sales expense | C83: =IF(ISERROR(-C25/C$13)," ",-C25/C$13) -> 0.29019185 | D83: =IF(ISERROR(-D25/D$13)," ",-D25/D$13) -> 0.31915682 | E83: =IF(ISERROR(-E25/E$13)," ",-E25/E$13) -> 0.23370316 | F83: =IF(ISERROR(-F25/F$13)," ",-F25/F$13) -> 0.20981078 | G83: =IF(ISERROR(-G25/G$13)," ",-G25/G$13) -> 0.19610478 | H83: =IF(ISERROR(-H25/H$13)," ",-H25/H$13) -> 0.17039502 | I83: =IF(ISERROR(-I25/I$13)," ",-I25/I$13) -> 0.17363998 | J83: =IF(ISERROR(-J25/J$13)," ",-J25/J$13) -> 0.16927236 | ... M83: =IF(ISERROR(-M25/M$13)," ",-M25/M$13) -> 0.15387236 | N83: =M83-J83 -> -0.0154 | O83: =IF(ISERROR(-O25/O$13)," ",-O25/O$13) -> 0.18312 | P83: =IF(ISERROR(-P25/P$13)," ",-P25/P$13) -> 0.23629163 | Q83: =IF(ISERROR(-Q25/Q$13)," ",-Q25/Q$13) -> 0.2168934 | R83: =IF(ISERROR(-R25/R$13)," ",-R25/R$13) -> 0.17287683 | S83: =IF(ISERROR(-S25/S$13)," ",-S25/S$13) -> 0.16375048 | T83: =IF(ISERROR(-T25/T$13)," ",-T25/T$13) -> 0.17716122 | U83: =IF(ISERROR(-U25/U$13)," ",-U25/U$13) -> 0.15809625 | V83: =IF(ISERROR(-V25/V$13)," ",-V25/V$13) -> 0.18826645 | ... Y83: =IF(ISERROR(-Y25/Y$13)," ",-Y25/Y$13) -> 0.15661519
B84: Administrative expense | C84: =IF(ISERROR(-C26/C$13)," ",-C26/C$13) -> 0.03895791 | D84: =IF(ISERROR(-D26/D$13)," ",-D26/D$13) -> 0.047284495 | E84: =IF(ISERROR(-E26/E$13)," ",-E26/E$13) -> 0.05447193 | F84: =IF(ISERROR(-F26/F$13)," ",-F26/F$13) -> 0.044255089 | G84: =IF(ISERROR(-G26/G$13)," ",-G26/G$13) -> 0.042196767 | H84: =IF(ISERROR(-H26/H$13)," ",-H26/H$13) -> 0.035187077 | I84: =IF(ISERROR(-I26/I$13)," ",-I26/I$13) -> 0.037555966 | J84: =IF(ISERROR(-J26/J$13)," ",-J26/J$13) -> 0.030830838 | ... M84: =IF(ISERROR(-M26/M$13)," ",-M26/M$13) -> 0.026830838 | O84: =IF(ISERROR(-O26/O$13)," ",-O26/O$13) -> 0.04185129 | P84: =IF(ISERROR(-P26/P$13)," ",-P26/P$13) -> 0.04663998 | Q84: =IF(ISERROR(-Q26/Q$13)," ",-Q26/Q$13) -> 0.041418988 | R84: =IF(ISERROR(-R26/R$13)," ",-R26/R$13) -> 0.043065811 | S84: =IF(ISERROR(-S26/S$13)," ",-S26/S$13) -> 0.035270846 | T84: =IF(ISERROR(-T26/T$13)," ",-T26/T$13) -> 0.035101775 | U84: =IF(ISERROR(-U26/U$13)," ",-U26/U$13) -> 0.034644847 | V84: =IF(ISERROR(-V26/V$13)," ",-V26/V$13) -> 0.040295293 | ... Y84: =IF(ISERROR(-Y26/Y$13)," ",-Y26/Y$13) -> 0.027144
B85: Gross margins | C85: =IF(ISERROR(C20/C$13)," ",C20/C$13) -> 0.47922117 | D85: =IF(ISERROR(D20/D$13)," ",D20/D$13) -> 0.4596798 | E85: =IF(ISERROR(E20/E$13)," ",E20/E$13) -> 0.46736425 | F85: =IF(ISERROR(F20/F$13)," ",F20/F$13) -> 0.46599857 | G85: =IF(ISERROR(G20/G$13)," ",G20/G$13) -> 0.44372835 | H85: =IF(ISERROR(H20/H$13)," ",H20/H$13) -> 0.42325261 | I85: =IF(ISERROR(I20/I$13)," ",I20/I$13) -> 0.43072263 | J85: =IF(ISERROR(J20/J$13)," ",J20/J$13) -> 0.44809377 | ... M85: =IF(ISERROR(M20/M$13)," ",M20/M$13) -> 0.46217985 | O85: =IF(ISERROR(O20/O$13)," ",O20/O$13) -> 0.46439766 | P85: =IF(ISERROR(P20/P$13)," ",P20/P$13) -> 0.46758688 | Q85: =IF(ISERROR(Q20/Q$13)," ",Q20/Q$13) -> 0.49679987 | R85: =IF(ISERROR(R20/R$13)," ",R20/R$13) -> 0.38442943 | S85: =IF(ISERROR(S20/S$13)," ",S20/S$13) -> 0.42680372 | T85: =IF(ISERROR(T20/T$13)," ",T20/T$13) -> 0.41963648 | U85: =IF(ISERROR(U20/U$13)," ",U20/U$13) -> 0.43104293 | V85: =IF(ISERROR(V20/V$13)," ",V20/V$13) -> 0.43042124 | ... Y85: =IF(ISERROR(Y20/Y$13)," ",Y20/Y$13) -> 0.45146518
B86: EBITDA margin | C86: =IF(ISERROR(C30/C$13)," ",C30/C$13) -> 0.13372712 | D86: =IF(ISERROR(D30/D$13)," ",D30/D$13) -> 0.10743348 | E86: =IF(ISERROR(E30/E$13)," ",E30/E$13) -> 0.19317371 | F86: =IF(ISERROR(F30/F$13)," ",F30/F$13) -> 0.22901501 | G86: =IF(ISERROR(G30/G$13)," ",G30/G$13) -> 0.23755536 | H86: =IF(ISERROR(H30/H$13)," ",H30/H$13) -> 0.23456943 | I86: =IF(ISERROR(I30/I$13)," ",I30/I$13) -> 0.23379564 | J86: =IF(ISERROR(J30/J$13)," ",J30/J$13) -> 0.26158055 | ... M86: =IF(ISERROR(M30/M$13)," ",M30/M$13) -> 0.29784326 | O86: =IF(ISERROR(O30/O$13)," ",O30/O$13) -> 0.22941169 | P86: =IF(ISERROR(P30/P$13)," ",P30/P$13) -> 0.17460756 | Q86: =IF(ISERROR(Q30/Q$13)," ",Q30/Q$13) -> 0.25300957 | R86: =IF(ISERROR(R30/R$13)," ",R30/R$13) -> 0.22028774 | S86: =IF(ISERROR(S30/S$13)," ",S30/S$13) -> 0.25126203 | T86: =IF(ISERROR(T30/T$13)," ",T30/T$13) -> 0.21757119 | U86: =IF(ISERROR(U30/U$13)," ",U30/U$13) -> 0.26414901 | V86: =IF(ISERROR(V30/V$13)," ",V30/V$13) -> 0.20523348 | ... Y86: =IF(ISERROR(Y30/Y$13)," ",Y30/Y$13) -> 0.28752967
B87: EBIT margin | C87: =IF(ISERROR(C35/C$13)," ",C35/C$13) -> 0.13372712 | D87: =IF(ISERROR(D35/D$13)," ",D35/D$13) -> 0.079459659 | E87: =IF(ISERROR(E35/E$13)," ",E35/E$13) -> 0.16710301 | F87: =IF(ISERROR(F35/F$13)," ",F35/F$13) -> 0.20190143 | G87: =IF(ISERROR(G35/G$13)," ",G35/G$13) -> 0.21102662 | H87: =IF(ISERROR(H35/H$13)," ",H35/H$13) -> 0.20824008 | I87: =IF(ISERROR(I35/I$13)," ",I35/I$13) -> 0.21124003 | J87: =IF(ISERROR(J35/J$13)," ",J35/J$13) -> 0.23992168 | ... M87: =IF(ISERROR(M35/M$13)," ",M35/M$13) -> 0.27320198 | O87: =IF(ISERROR(O35/O$13)," ",O35/O$13) -> 0.22941169 | P87: =IF(ISERROR(P35/P$13)," ",P35/P$13) -> 0.17460756 | Q87: =IF(ISERROR(Q35/Q$13)," ",Q35/Q$13) -> 0.22867245 | R87: =IF(ISERROR(R35/R$13)," ",R35/R$13) -> 0.19131023 | S87: =IF(ISERROR(S35/S$13)," ",S35/S$13) -> 0.22413996 | T87: =IF(ISERROR(T35/T$13)," ",T35/T$13) -> 0.19204908 | U87: =IF(ISERROR(U35/U$13)," ",U35/U$13) -> 0.24042637 | V87: =IF(ISERROR(V35/V$13)," ",V35/V$13) -> 0.18377604 | ... Y87: =IF(ISERROR(Y35/Y$13)," ",Y35/Y$13) -> 0.26472917
B88: Pre-tax margin | C88: =IF(ISERROR(C50/C$13)," ",C50/C$13) -> 0.13707154 | D88: =IF(ISERROR(D50/D$13)," ",D50/D$13) -> 0.089983412 | E88: =IF(ISERROR(E50/E$13)," ",E50/E$13) -> 0.17499417 | F88: =IF(ISERROR(F50/F$13)," ",F50/F$13) -> 0.20763318 | G88: =IF(ISERROR(G50/G$13)," ",G50/G$13) -> 0.21690389 | H88: =IF(ISERROR(H50/H$13)," ",H50/H$13) -> 0.21586427 | I88: =IF(ISERROR(I50/I$13)," ",I50/I$13) -> 0.22900809 | J88: =IF(ISERROR(J50/J$13)," ",J50/J$13) -> 0.25931882 | ... M88: =IF(ISERROR(M50/M$13)," ",M50/M$13) -> 0.28515199 | O88: =IF(ISERROR(O50/O$13)," ",O50/O$13) -> 0.22324609 | P88: =IF(ISERROR(P50/P$13)," ",P50/P$13) -> 0.19214306 | Q88: =IF(ISERROR(Q50/Q$13)," ",Q50/Q$13) -> 0.23118217 | R88: =IF(ISERROR(R50/R$13)," ",R50/R$13) -> 0.20095019 | S88: =IF(ISERROR(S50/S$13)," ",S50/S$13) -> 0.23362436 | T88: =IF(ISERROR(T50/T$13)," ",T50/T$13) -> 0.197779 | U88: =IF(ISERROR(U50/U$13)," ",U50/U$13) -> 0.2548599 | V88: =IF(ISERROR(V50/V$13)," ",V50/V$13) -> 0.20468184 | ... Y88: =IF(ISERROR(Y50/Y$13)," ",Y50/Y$13) -> 0.27956352
B89: Tax rate (as a % of EBT excluding associates) | C89: =IF(ISERROR(-C53/(C50-C44))," ",-C53/(C50-C44)) -> 0.24022082 | D89: =IF(ISERROR(-D53/(D50-D44))," ",-D53/(D50-D44)) -> 0.21035878 | E89: =IF(ISERROR(-E53/(E50-E44))," ",-E53/(E50-E44)) -> 0.2252931 | F89: =IF(ISERROR(-F53/(F50-F44))," ",-F53/(F50-F44)) -> 0.21124395 | G89: =IF(ISERROR(-G53/(G50-G44))," ",-G53/(G50-G44)) -> 0.21179574 | H89: =IF(ISERROR(-H53/(H50-H44))," ",-H53/(H50-H44)) -> 0.21540691 | I89: =IF(ISERROR(-I53/(I50-I44))," ",-I53/(I50-I44)) -> 0.20916691 | J89: =IF(ISERROR(-J53/(J50-J44))," ",-J53/(J50-J44)) -> 0.19012026 | K89: 0.205 | L89: =+K89 -> 0.205 | M89: =+L89 -> 0.205 | O89: =IF(ISERROR(-O53/(O50-O44))," ",-O53/(O50-O44)) -> 0.22425752 | P89: =IF(ISERROR(-P53/(P50-P44))," ",-P53/(P50-P44)) -> 0.19624275 | Q89: =IF(ISERROR(-Q53/(Q50-Q44))," ",-Q53/(Q50-Q44)) -> 0.21619386 | R89: =IF(ISERROR(-R53/(R50-R44))," ",-R53/(R50-R44)) -> 0.20614222 | S89: =IF(ISERROR(-S53/(S50-S44))," ",-S53/(S50-S44)) -> 0.20585746 | T89: =IF(ISERROR(-T53/(T50-T44))," ",-T53/(T50-T44)) -> 0.22689362 | U89: =IF(ISERROR(-U53/(U50-U44))," ",-U53/(U50-U44)) -> 0.21130302 | V89: =IF(ISERROR(-V53/(V50-V44))," ",-V53/(V50-V44)) -> 0.20666409 | ... Y89: =IF(ISERROR(-Y53/(Y50-Y44))," ",-Y53/(Y50-Y44)) -> 0.20890901
B90: Net margins | C90: =IF(ISERROR(C57/C$13)," ",C57/C$13) -> 0.10414411 | D90: =IF(ISERROR(D57/D$13)," ",D57/D$13) -> 0.071054612 | E90: =IF(ISERROR(E57/E$13)," ",E57/E$13) -> 0.13556919 | F90: =IF(ISERROR(F57/F$13)," ",F57/F$13) -> 0.16377192 | G90: =IF(ISERROR(G57/G$13)," ",G57/G$13) -> 0.17096457 | H90: =IF(ISERROR(H57/H$13)," ",H57/H$13) -> 0.16936562 | I90: =IF(ISERROR(I57/I$13)," ",I57/I$13) -> 0.18110717 | J90: =IF(ISERROR(J57/J$13)," ",J57/J$13) -> 0.21003472 | ... M90: =IF(ISERROR(M57/M$13)," ",M57/M$13) -> 0.22670522 | N90: =M90-J90 -> 0.016670502 | O90: =IF(ISERROR(O57/O$13)," ",O57/O$13) -> 0.17318148 | P90: =IF(ISERROR(P57/P$13)," ",P57/P$13) -> 0.15443638 | Q90: =IF(ISERROR(Q57/Q$13)," ",Q57/Q$13) -> 0.181202 | R90: =IF(ISERROR(R57/R$13)," ",R57/R$13) -> 0.15952587 | S90: =IF(ISERROR(S57/S$13)," ",S57/S$13) -> 0.18553105 | T90: =IF(ISERROR(T57/T$13)," ",T57/T$13) -> 0.15290421 | U90: =IF(ISERROR(U57/U$13)," ",U57/U$13) -> 0.20100724 | V90: =IF(ISERROR(V57/V$13)," ",V57/V$13) -> 0.16238146 | ... Y90: =IF(ISERROR(Y57/Y$13)," ",Y57/Y$13) -> 0.22116018
B92: Other income statement assumptions
B94: Interest income calculation:
B95: Period end cash balance+ 债权投资 | C95: =+C130+Wind!U76 -> 464.1483 | D95: =+D130 -> 339.29503 | E95: =+E130+Wind!W82 -> 1075.0957 | F95: =+F130+Wind!X82 -> 1324.8537 | G95: =+G130+Wind!Y82 -> 1169.104 | H95: =+H130+Wind!Z82 -> 2540.5393 | I95: =+I130+Wind!AA82 -> 7277.7698 | J95: =+J130+Wind!AB82 -> 9324.151 | K95: =+K130++Wind!$AB$82 -> 11054.991 | L95: =+L130++Wind!$AB$82 -> 11472.158 | M95: =+M130++Wind!$AB$82 -> 11999.154
B96: Interest income | D96: =D39 -> 2.7387298 | E96: =E39 -> 20.080901 | F96: =F39 -> 26.040389 | G96: =G39 -> 29.262542 | H96: =H39 -> 19.820948 | I96: =I39 -> 122.48631 | J96: =J39 -> 260.35607 | K96: =K97*J95 -> 270.40038 | L96: =L97*K95 -> 322.80575 | M96: =M97*L95 -> 339.57589
B97: Interest income as a % of average cash | D97: =IF(ISERROR(D96/D95)," ",D96/AVERAGE(C95,D95)) -> 0.0068174809 | E97: =IF(ISERROR(E96/E95)," ",E96/AVERAGE(D95,E95)) -> 0.028395125 | F97: =IF(ISERROR(F96/F95)," ",F96/AVERAGE(E95,F95)) -> 0.021700782 | G97: =IF(ISERROR(G96/G95)," ",G96/AVERAGE(F95,G95)) -> 0.023466751 | H97: =IF(ISERROR(H96/H95)," ",H96/AVERAGE(G95,H95)) -> 0.010686174 | I97: =IF(ISERROR(I96/I95)," ",I96/AVERAGE(H95,I95)) -> 0.024950591 | J97: =IF(ISERROR(J96/J95)," ",J96/AVERAGE(I95,J95)) -> 0.031364572 | K97: 0.029 | L97: =K97+0.02% -> 0.0292 | M97: =L97+0.04% -> 0.0296
B98: Interest income as a % of period end cash | D98: =D96/D95 -> 0.008071824 | E98: =E96/E95 -> 0.018678245 | F98: =F96/F95 -> 0.019655294 | G98: =G96/G95 -> 0.025029887 | H98: =H96/H95 -> 0.0078018662 | I98: =I96/I95 -> 0.016830198 | J98: =J96/J95 -> 0.027922764
B99: Interest expense calculation:
B100: Average debt | C100: =+(C148+C153)/2 -> 80 | D100: =((C148+C153)+(D148+D153))/2 -> 182.39892 | E100: =((D148+D153)+(E148+E153))/2 -> 225.83642 | F100: =((E148+E153)+(F148+F153))/2 -> 329.30082 | G100: =((F148+F153)+(G148+G153))/2 -> 530.52582 | H100: =((G148+G153)+(H148+H153))/2 -> 1915.4623 | I100: =((H148+H153)+(I148+I153))/2 -> 3198.6526 | J100: =((I148+I153)+(J148+J153))/2 -> 4883.5212 | K100: =((J148+J153)+(K148+K153))/2 -> 6551.3369 | ... M100: =((L148+L153)+(M148+M153))/2 -> 6551.3369
B101: Interest charges | C101: =C40+C104 -> 0 | D101: =D40+D104 -> -6.9068465 | E101: =E40+E104 -> -5.4021294 | F101: =F40+F104 -> -9.7758555 | G101: =G40+G104 -> -13.6159 | H101: =H40+H104 -> -52.681528 | I101: =I40+I104 -> -80.086468 | J101: =J40+J104 -> -97.913831 | K101: =-K100*K102 -> -131.35327 | L101: =-L100*L102 -> -131.35327 | M101: =-M100*M102 -> -131.35327
B102: Total interest charges (as a % of avg. debt) | C102: =IF(ISERROR(-C101/C100)," ",-C101/C100) -> 0 | D102: =-D101/D100 -> 0.037866707 | E102: =-E101/E100 -> 0.023920541 | F102: =-F101/F100 -> 0.029686702 | G102: =-G101/G100 -> 0.025664916 | H102: =-H101/H100 -> 0.027503296 | I102: =-I101/I100 -> 0.025037564 | J102: =-J101/J100 -> 0.020049842 | K102: =+J102 -> 0.020049842 | L102: =+K102 -> 0.020049842 | M102: =+L102 -> 0.020049842
B104: Capitalized interest | C104: =-'Raw Data'!C92 -> 0 | D104: =-'Raw Data'!D92 -> 0 | E104: =-'Raw Data'!E92 -> 0 | F104: =-'Raw Data'!F92 -> 0 | G104: =-'Raw Data'!G92 -> 0 | H104: =-'Raw Data'!H92 -> 0 | I104: =-'Raw Data'!I92 -> 0 | J104: =-'Raw Data'!J92 -> 0 | K104: =K105*AVERAGE(J207,K207) -> 0 | L104: =L105*AVERAGE(K207,L207) -> 0 | M104: =M105*AVERAGE(L207,M207) -> 0
B105: As a % of average capital expenditure | C105: =IF(ISERROR(C104/AVERAGE(#REF!,C207))," ",C104/AVERAGE(#REF!,C207)) | D105: =C105 | E105: =D105 | F105: =E105 | G105: =F105 | H105: =G105 | I105: =H105 | J105: =I105 | K105: 0 | L105: 0 | M105: 0
B107: Income from associates:
B108: Interests in an associate | C108: ='Raw Data'!C114 -> 0 | D108: ='Raw Data'!D114 -> 0 | E108: ='Raw Data'!E114 -> 0 | F108: ='Raw Data'!F114 -> 0 | G108: ='Raw Data'!G114 -> 0 | H108: ='Raw Data'!H114 -> 0 | I108: ='Raw Data'!I114 -> 0 | J108: ='Raw Data'!J114 -> 0 | K108: =J108 -> 0 | L108: =K108 -> 0 | M108: =L108 -> 0
B109: As a % of interest in associates | C109: =IF(ISERROR(C44/C108)," ",C44/C108) | D109: =IF(ISERROR(D44/D108)," ",D44/D108) | E109: =IF(ISERROR(E44/E108)," ",E44/E108) | F109: =IF(ISERROR(F44/F108)," ",F44/F108) | G109: =IF(ISERROR(G44/G108)," ",G44/G108) | H109: =IF(ISERROR(H44/H108)," ",H44/H108) | I109: =IF(ISERROR(I44/I108)," ",I44/I108) | J109: =IF(ISERROR(J44/J108)," ",J44/J108)
B111: Income from jointly controlled entities:
B112: Interest in a jointly controlled entity | C112: ='Raw Data'!C116 -> 0 | D112: =C112 -> 0 | E112: =D112 -> 0 | F112: =E112 -> 0 | G112: =F112 -> 0 | H112: =G112 -> 0 | I112: =H112 -> 0 | J112: =I112 -> 0 | K112: =J112 -> 0 | ... M112: =L112 -> 0
B113: As a % of interest in jointly controlled entities | C113: =IF(ISERROR(#REF!/C112)," ",#REF!/C112) | D113: 0 | E113: 0 | F113: 0 | G113: 0 | K113: 0 | L113: 0 | M113: 0
B115: Fully diluted shares calculation:
B116: CB 1 - Amount outstanding (Rmb) | C116: 0 | D116: 0 | E116: 0 | F116: 0 | G116: 0 | H116: 0 | I116: 0 | J116: 0 | K116: 0 | L116: 0 | M116: 0
B117: Fx rate | C117: 0 | D117: 0 | E117: 0 | F117: 0 | G117: 0 | H117: 0 | I117: 0 | J117: 0 | K117: 0 | L117: 0 | M117: 0
...

Sheet New vs. Old
B1: Eastroc Beverage (605499.SS)
B2: Summary P&L (Rmb mn) | C2: 损益表（单位：百万元人民币） | O2: New | S2: Old estimates | X2: Old | AB2: YoY Growth | AF2: Absolute difference | AJ2: Relative difference | AO2: %
D3: 2015 | E3: 2016 | F3: 2017 | G3: 2018 | H3: 2019 | J3: 2019E | K3: 2021 | L3: 2022 | M3: 2023 | N3: 2024 | O3: 2025E | P3: 2026E | Q3: 2027E | S3: 2019E | T3: 2021E | U3: 2022E | V3: 2023E | W3: 2024 | X3: 2025E | Y3: 2026E | Z3: 2027E | AB3: 2019E | AC3: 2020E | AD3: 2021E | AF3: 2019E | AG3: 2020E | AH3: 2021E | AJ3: 2019E | AK3: 2021E | AL3: 2022E | AM3: 2023E | AN3: 2024 | AO3: 2025E | AP3: 2026E | AQ3: 2027E
B4: Total revenues | C4: 营业收入 | D4: =Model!#REF! -> #REF! | E4: =Model!#REF! -> #REF! | F4: =Model!C13 -> 2843.8076 | G4: =Model!D13 -> 3037.536 | H4: =Model!E13 -> 4208.7285 | J4: =Model!E13 -> 4208.7285 | K4: =Model!G13 -> 6977.8225 | L4: =Model!H13 -> 8505.3897 | M4: =Model!I13 -> 11262.794 | N4: =Model!J13 -> 15838.852 | O4: =Model!K13 -> 20991.911 | P4: =Model!L13 -> 25403.508 | Q4: =Model!M13 -> 29791.987 | S4: 19854.625 | T4: 2772.8977 | U4: 3479.9965 | V4: 4291.026 | W4: 16329.345 | X4: 21084.337 | Y4: 25986.185 | Z4: 30624.725 | AB4: =+J4/G4-1 -> 0.3855732 | AC4: =+#REF!/J4-1 -> #REF! | AD4: =+K4/#REF!-1 -> #REF! | AF4: =J4-S4 -> -15645.896 | AG4: =#REF!-#REF! -> #REF! | AH4: =K4-T4 -> 4204.9248 | AJ4: =IF(ISNUMBER(J4/S4-1),J4/S4-1,"n.a.") -> -0.78802276 | AK4: =IF(ISNUMBER(K4/T4-1),K4/T4-1,"n.a.") -> 1.5164371 | AL4: =IF(ISNUMBER(L4/U4-1),L4/U4-1,"n.a.") -> 1.4440799 | AM4: =IF(ISNUMBER(M4/V4-1),M4/V4-1,"n.a.") -> 1.6247322 | AN4: =IF(ISNUMBER(N4/W4-1),N4/W4-1,"n.a.") -> -0.030037541 | AO4: =IF(ISNUMBER(O4/X4-1),O4/X4-1,"n.a.") -> -0.0043836596 | AP4: =IF(ISNUMBER(P4/Y4-1),P4/Y4-1,"n.a.") -> -0.022422543 | AQ4: =IF(ISNUMBER(Q4/Z4-1),Q4/Z4-1,"n.a.") -> -0.02719171 | AS4: =(Q4/O4)^0.5-1 -> 0.19130715
B5: Energy drinks | K5: =Segment!J11 -> 6591.8979 | L5: =Segment!K11 -> 8172.3068 | M5: =Segment!L11 -> 10336.009 | N5: =Segment!M11 -> 13303.584 | O5: =Segment!N11 -> 15936.364 | P5: =Segment!O11 -> 18645.545 | Q5: =Segment!P11 -> 21255.922 | W5: 13540.689 | X5: 16199.775 | Y5: 19439.73 | Z5: 22355.689 | AN5: =IF(ISNUMBER(N5/W5-1),N5/W5-1,"n.a.") -> -0.017510506 | AO5: =IF(ISNUMBER(O5/X5-1),O5/X5-1,"n.a.") -> -0.016260163 | AP5: =IF(ISNUMBER(P5/Y5-1),P5/Y5-1,"n.a.") -> -0.040853659 | AQ5: =IF(ISNUMBER(Q5/Z5-1),Q5/Z5-1,"n.a.") -> -0.049194062
B6: Other beverage | K6: =Segment!J12 -> 371.94956 | L6: =Segment!K12 -> 319.02572 | M6: =Segment!L12 -> 914.47521 | N6: =Segment!M12 -> 2518.1799 | O6: =Segment!N12 -> 5031.827 | P6: =Segment!O12 -> 6725.0368 | Q6: =Segment!P12 -> 8490.3589 | W6: 2776.3467 | X6: 4860.8426 | Y6: 6513.529 | Z6: 8223.3304 | AN6: =IF(ISNUMBER(N6/W6-1),N6/W6-1,"n.a.") -> -0.092987981 | AO6: =IF(ISNUMBER(O6/X6-1),O6/X6-1,"n.a.") -> 0.035175879 | AP6: =IF(ISNUMBER(P6/Y6-1),P6/Y6-1,"n.a.") -> 0.032472062 | AQ6: =IF(ISNUMBER(Q6/Z6-1),Q6/Z6-1,"n.a.") -> 0.032472062
B7: Bushuila | N7: =Segment!M13 -> 1495.0141 | O7: =Segment!N13 -> 3303.9811 | P7: =Segment!O13 -> 4493.4143 | Q7: =Segment!P13 -> 5684.1691 | W7: 1550 | X7: 3139.5295 | Y7: 4238.3649 | Z7: 5361.5316 | AN7: =IF(ISNUMBER(N7/W7-1),N7/W7-1,"n.a.") -> -0.035474794 | AO7: =IF(ISNUMBER(O7/X7-1),O7/X7-1,"n.a.") -> 0.052380952 | AP7: =IF(ISNUMBER(P7/Y7-1),P7/Y7-1,"n.a.") -> 0.060176367 | AQ7: =IF(ISNUMBER(Q7/Z7-1),Q7/Z7-1,"n.a.") -> 0.060176367
B8: Other beverages | N8: =Segment!M15 -> 1023.1658 | O8: =Segment!N15 -> 1727.8459 | P8: =Segment!O15 -> 2231.6225 | Q8: =Segment!P15 -> 2806.1898 | W8: =W6-W7 -> 1226.3467 | X8: 1721.313 | Y8: 2275.1642 | Z8: 2861.7988 | AN8: =IF(ISNUMBER(N8/W8-1),N8/W8-1,"n.a.") -> -0.16567985 | AO8: =IF(ISNUMBER(O8/X8-1),O8/X8-1,"n.a.") -> 0.0037952797 | AP8: =IF(ISNUMBER(P8/Y8-1),P8/Y8-1,"n.a.") -> -0.01913782 | AQ8: =IF(ISNUMBER(Q8/Z8-1),Q8/Z8-1,"n.a.") -> -0.019431484
B10: COGS | C10: 营业成本 | D10: =-Model!#REF! -> #REF! | E10: =-Model!#REF! -> #REF! | F10: =-Model!C16 -> 1480.9948 | G10: =-Model!D16 -> 1641.2421 | H10: =-Model!E16 -> 2241.7193 | J10: =-Model!E16 -> 2241.7193 | K10: =-Model!G16 -> 3881.5648 | L10: =-Model!H16 -> 4905.4613 | M10: =-Model!I16 -> 6411.6538 | N10: =-Model!J16 -> 8741.561 | O10: =-Model!K16 -> 11564.399 | P10: =-Model!L16 -> 13747.299 | Q10: =-Model!M16 -> 16022.731 | S10: 10987.372 | T10: 2154.5373 | U10: 2662.7579 | V10: 3225.9895 | W10: 8969.8905 | X10: 11553.921 | Y10: 14057.966 | Z10: 16468.114 | AB10: =+J10/G10-1 -> 0.36586754 | AC10: =+#REF!/J10-1 -> #REF! | AD10: =+K10/#REF!-1 -> #REF! | AF10: =J10-S10 -> -8745.6529 | AG10: =#REF!-#REF! -> #REF! | AH10: =K10-T10 -> 1727.0275 | AJ10: =IF(ISNUMBER(J10/S10-1),J10/S10-1,"n.a.") -> -0.79597312 | AK10: =IF(ISNUMBER(K10/T10-1),K10/T10-1,"n.a.") -> 0.80157697 | AL10: =IF(ISNUMBER(L10/U10-1),L10/U10-1,"n.a.") -> 0.84224836 | AM10: =IF(ISNUMBER(M10/V10-1),M10/V10-1,"n.a.") -> 0.98749987 | AN10: =IF(ISNUMBER(N10/W10-1),N10/W10-1,"n.a.") -> -0.0254551 | AO10: =IF(ISNUMBER(O10/X10-1),O10/X10-1,"n.a.") -> 0.00090689746 | AP10: =IF(ISNUMBER(P10/Y10-1),P10/Y10-1,"n.a.") -> -0.02209901 | AQ10: =IF(ISNUMBER(Q10/Z10-1),Q10/Z10-1,"n.a.") -> -0.027045208
B11: GP | K11: =Model!G20 -> 3096.2577 | L11: =Model!H20 -> 3599.9284 | M11: =Model!I20 -> 4851.1403 | N11: =Model!J20 -> 7097.2908 | O11: =Model!K20 -> 9427.5114 | P11: =Model!L20 -> 11656.21 | Q11: =Model!M20 -> 13769.256 | W11: 7359.4547 | X11: 9530.4162 | Y11: 11928.219 | Z11: 14156.611 | AN11: =IF(ISNUMBER(N11/W11-1),N11/W11-1,"n.a.") -> -0.035622736 | AO11: =IF(ISNUMBER(O11/X11-1),O11/X11-1,"n.a.") -> -0.010797511 | AP11: =IF(ISNUMBER(P11/Y11-1),P11/Y11-1,"n.a.") -> -0.022803842 | AQ11: =IF(ISNUMBER(Q11/Z11-1),Q11/Z11-1,"n.a.") -> -0.027362132
B12: Energy drinks | K12: =Segment!J30 -> 3038.1215 | L12: =Segment!K30 -> 3535.6389 | M12: =Segment!L30 -> 4684.7677 | N12: =Segment!M30 -> 6413.2648 | O12: =Segment!N30 -> 8106.018 | P12: =Segment!O30 -> 9713.0786 | Q12: =Segment!P30 -> 11072.91 | R12: =Segment!P30 -> 11072.91 | W12: 6516.8388 | X12: 8256.9374 | Y12: 10003.639 | Z12: 11493.333 | AN12: =IF(ISNUMBER(N12/W12-1),N12/W12-1,"n.a.") -> -0.015893278 | AO12: =IF(ISNUMBER(O12/X12-1),O12/X12-1,"n.a.") -> -0.018277897 | AP12: =IF(ISNUMBER(P12/Y12-1),P12/Y12-1,"n.a.") -> -0.029045463 | AQ12: =IF(ISNUMBER(Q12/Z12-1),Q12/Z12-1,"n.a.") -> -0.036579784
B13: Other beverage | K13: =Segment!J31 -> 48.353632 | L13: =Segment!K31 -> 54.449432 | M13: =Segment!L31 -> 157.75569 | N13: =Segment!M31 -> 672.06462 | O13: =Segment!N31 -> 1304.8896 | P13: =Segment!O31 -> 1920.0827 | Q13: =Segment!P31 -> 2664.3521 | R13: =Segment!P31 -> 2664.3521 | W13: 833.99907 | X13: 1256.8749 | Y13: 1901.5316 | Z13: 2631.2835 | AN13: =IF(ISNUMBER(N13/W13-1),N13/W13-1,"n.a.") -> -0.19416622 | AO13: =IF(ISNUMBER(O13/X13-1),O13/X13-1,"n.a.") -> 0.038201636 | AP13: =IF(ISNUMBER(P13/Y13-1),P13/Y13-1,"n.a.") -> 0.0097558698 | AQ13: =IF(ISNUMBER(Q13/Z13-1),Q13/Z13-1,"n.a.") -> 0.012567474
B15: SG&A | C15: 营业税金、销售及管理费用 | D15: =-Model!#REF! -> #REF! | E15: =-Model!#REF! -> #REF! | F15: =-Model!C23 -> 981.9832 | G15: =-Model!D23 -> 1152.6478 | H15: =-Model!E23 -> 1257.157 | J15: =-Model!E23 -> 1257.157 | K15: =-Model!G23 -> 1739.6364 | L15: =-Model!H23 -> 1841.1951 | M15: =-Model!I23 -> 2499.6673 | N15: =-Model!J23 -> 3329.1976 | O15: =-Model!K23 -> 4191.9135 | P15: =-Model!L23 -> 4938.2351 | Q15: =-Model!M23 -> 5684.0683 | S15: 3147.8155 | T15: 366.7001 | U15: 476.13636 | V15: 613.36718 | W15: 3513.9645 | X15: 4260.9727 | Y15: 5121.6653 | Z15: 5928.6973 | AB15: =+J15/G15-1 -> 0.090668868 | AC15: =+#REF!/J15-1 -> #REF! | AD15: =+K15/#REF!-1 -> #REF! | AF15: =J15-S15 -> -1890.6584 | AG15: =#REF!-#REF! -> #REF! | AH15: =K15-T15 -> 1372.9363 | AJ15: =IF(ISNUMBER(J15/S15-1),J15/S15-1,"n.a.") -> -0.60062556 | AK15: =IF(ISNUMBER(K15/T15-1),K15/T15-1,"n.a.") -> 3.7440305 | AL15: =IF(ISNUMBER(L15/U15-1),L15/U15-1,"n.a.") -> 2.866949 | AM15: =IF(ISNUMBER(M15/V15-1),M15/V15-1,"n.a.") -> 3.0753197 | AN15: =IF(ISNUMBER(N15/W15-1),N15/W15-1,"n.a.") -> -0.052580754 | AO15: =IF(ISNUMBER(O15/X15-1),O15/X15-1,"n.a.") -> -0.016207388 | AP15: =IF(ISNUMBER(P15/Y15-1),P15/Y15-1,"n.a.") -> -0.035814569 | AQ15: =IF(ISNUMBER(Q15/Z15-1),Q15/Z15-1,"n.a.") -> -0.041261843
B16: Other operating expenses, net | C16: 其他费用 | D16: =-Model!#REF! -> #REF! | E16: =-Model!#REF! -> #REF! | F16: =-Model!C27 -> 0.5354 | G16: =-Model!D27 -> 2.2846109 | H16: =-Model!E27 -> 6.5609849 | J16: =-Model!E27 -> 6.5609849 | K16: =-Model!G27 -> -115.88506 | L16: =-Model!H27 -> -12.42969 | M16: =-Model!I27 -> -27.680013 | N16: =-Model!J27 -> -31.990655 | O16: =-Model!K27 -> -200.04207 | P16: =-Model!L27 -> -49.042073 | Q16: =-Model!M27 -> -54.042073 | S16: -157.82 | T16: 9.9976239 | U16: 9.9973863 | V16: 9.997125 | W16: -30.617257 | X16: -55.054662 | Y16: -38.580371 | Z16: -42.534201 | AF16: =J16-S16 -> 164.38098 | AG16: =#REF!-#REF! -> #REF! | AH16: =K16-T16 -> -125.88268 | AJ16: =IF(ISNUMBER(J16/S16-1),J16/S16-1,"n.a.") -> -1.0415726 | AK16: =IF(ISNUMBER(K16/T16-1),K16/T16-1,"n.a.") -> -12.59126 | AL16: =IF(ISNUMBER(L16/U16-1),L16/U16-1,"n.a.") -> -2.243294 | AM16: =IF(ISNUMBER(M16/V16-1),M16/V16-1,"n.a.") -> -3.7687974 | AN16: =IF(ISNUMBER(N16/W16-1),N16/W16-1,"n.a.") -> 0.04485699 | AO16: =IF(ISNUMBER(O16/X16-1),O16/X16-1,"n.a.") -> 2.6335174 | AP16: =IF(ISNUMBER(P16/Y16-1),P16/Y16-1,"n.a.") -> 0.27116644 | AQ16: =IF(ISNUMBER(Q16/Z16-1),Q16/Z16-1,"n.a.") -> 0.27055574
B17: EBITDA | C17: EBITDA | D17: =Model!#REF! -> #REF! | E17: =Model!#REF! -> #REF! | F17: =Model!C30 -> 380.2942 | G17: =Model!D30 -> 326.33306 | H17: =Model!E30 -> 813.01568 | J17: =Model!E30 -> 813.01568 | K17: =Model!G30 -> 1657.6191 | L17: =Model!H30 -> 1995.1044 | M17: =Model!I30 -> 2633.1921 | N17: =Model!J30 -> 4143.1356 | O17: =Model!K30 -> 5851.8559 | P17: =Model!L30 -> 7272.9927 | Q17: =Model!M30 -> 8873.3424 | S17: 6334.7453 | T17: 320.56774 | U17: 422.94455 | V17: 549.08064 | W17: 4232.623 | X17: 5740.9977 | Y17: 7353.2431 | Z17: 9011.3788 | AB17: =+J17/G17-1 -> 1.4913678 | AC17: =+#REF!/J17-1 -> #REF! | AD17: =+K17/#REF!-1 -> #REF! | AF17: =J17-S17 -> -5521.7296 | AG17: =#REF!-#REF! -> #REF! | AH17: =K17-T17 -> 1337.0514 | AJ17: =IF(ISNUMBER(J17/S17-1),J17/S17-1,"n.a.") -> -0.87165772 | AK17: =IF(ISNUMBER(K17/T17-1),K17/T17-1,"n.a.") -> 4.1708856 | AL17: =IF(ISNUMBER(L17/U17-1),L17/U17-1,"n.a.") -> 3.7171772 | AM17: =IF(ISNUMBER(M17/V17-1),M17/V17-1,"n.a.") -> 3.7956383 | AN17: =IF(ISNUMBER(N17/W17-1),N17/W17-1,"n.a.") -> -0.021142322 | AO17: =IF(ISNUMBER(O17/X17-1),O17/X17-1,"n.a.") -> 0.019309919 | AP17: =IF(ISNUMBER(P17/Y17-1),P17/Y17-1,"n.a.") -> -0.01091361 | AQ17: =IF(ISNUMBER(Q17/Z17-1),Q17/Z17-1,"n.a.") -> -0.015318013
B19: Depreciation | C19: 折旧 | D19: =-Model!#REF! -> #REF! | E19: =-Model!#REF! -> #REF! | F19: =-Model!C33 -> 0 | G19: =-Model!D33 -> 77.859575 | H19: =-Model!E33 -> 102.17591 | J19: =-Model!E33 -> 102.17591 | K19: =-Model!G33 -> 173.1049 | L19: =-Model!H33 -> 211.99102 | M19: =-Model!I33 -> 241.69914 | N19: =-Model!J33 -> 325.93172 | O19: =-Model!K33 -> 392.57668 | P19: =-Model!L33 -> 473.34602 | Q19: =-Model!M33 -> 691.37348 | S19: 451.48698 | T19: 59.13137 | U19: 76.445661 | V19: 95.812121 | W19: 337.90731 | X19: 392.84852 | Y19: 475.36584 | Z19: 697.79391 | AB19: =+J19/G19-1 -> 0.31231019 | AC19: =+#REF!/J19-1 -> #REF! | AD19: =+K19/#REF!-1 -> #REF! | AF19: =J19-S19 -> -349.31106 | AG19: =#REF!-#REF! -> #REF! | AH19: =K19-T19 -> 113.97353 | AJ19: =IF(ISNUMBER(J19/S19-1),J19/S19-1,"n.a.") -> -0.77369023 | AK19: =IF(ISNUMBER(K19/T19-1),K19/T19-1,"n.a.") -> 1.927463 | AL19: =IF(ISNUMBER(L19/U19-1),L19/U19-1,"n.a.") -> 1.7730942 | AM19: =IF(ISNUMBER(M19/V19-1),M19/V19-1,"n.a.") -> 1.5226363 | AN19: =IF(ISNUMBER(N19/W19-1),N19/W19-1,"n.a.") -> -0.035440471 | AO19: =IF(ISNUMBER(O19/X19-1),O19/X19-1,"n.a.") -> -0.00069197872 | AP19: =IF(ISNUMBER(P19/Y19-1),P19/Y19-1,"n.a.") -> -0.0042489683 | AQ19: =IF(ISNUMBER(Q19/Z19-1),Q19/Z19-1,"n.a.") -> -0.0092010332
B20: Amortization | C20: 摊销 | D20: =-Model!#REF! -> #REF! | E20: =-Model!#REF! -> #REF! | F20: =-Model!C34 -> 0 | G20: =-Model!D34 -> 7.1119131 | H20: =-Model!E34 -> 7.5485512 | J20: =-Model!E34 -> 7.5485512 | K20: =-Model!G34 -> 12.007907 | L20: =-Model!H34 -> 11.95035 | M20: =-Model!I34 -> 12.33999 | N20: =-Model!J34 -> 17.11997 | O20: =-Model!K34 -> 23.639184 | P20: =-Model!L34 -> 32.629976 | Q20: =-Model!M34 -> 42.739316 | S20: 6.0011608 | T20: 19.77375 | U20: 15.393992 | V20: 11.596321 | W20: 18.608242 | X20: 23.651014 | Y20: 32.743301 | Z20: 43.137101 | AB20: =+J20/G20-1 -> 0.061395307 | AC20: =+#REF!/J20-1 -> #REF! | AD20: =+K20/#REF!-1 -> #REF! | AF20: =J20-S20 -> 1.5473904 | AG20: =#REF!-#REF! -> #REF! | AH20: =K20-T20 -> -7.7658432 | AJ20: =IF(ISNUMBER(J20/S20-1),J20/S20-1,"n.a.") -> 0.25784852 | AK20: =IF(ISNUMBER(K20/T20-1),K20/T20-1,"n.a.") -> -0.39273497 | AL20: =IF(ISNUMBER(L20/U20-1),L20/U20-1,"n.a.") -> -0.22370039 | AM20: =IF(ISNUMBER(M20/V20-1),M20/V20-1,"n.a.") -> 0.064129807 | AN20: =IF(ISNUMBER(N20/W20-1),N20/W20-1,"n.a.") -> -0.079979169 | AO20: =IF(ISNUMBER(O20/X20-1),O20/X20-1,"n.a.") -> -0.00050021337 | AP20: =IF(ISNUMBER(P20/Y20-1),P20/Y20-1,"n.a.") -> -0.0034610067 | AQ20: =IF(ISNUMBER(Q20/Z20-1),Q20/Z20-1,"n.a.") -> -0.0092214151
B21: EBIT (Operating profit) | C21: EBIT | D21: =Model!#REF! -> #REF! | E21: =Model!#REF! -> #REF! | F21: =Model!C35 -> 380.2942 | G21: =Model!D35 -> 241.36158 | H21: =Model!E35 -> 703.29121 | J21: =Model!E35 -> 703.29121 | K21: =Model!G35 -> 1472.5063 | L21: =Model!H35 -> 1771.163 | M21: =Model!I35 -> 2379.153 | N21: =Model!J35 -> 3800.0839 | O21: =Model!K35 -> 5435.64 | P21: =Model!L35 -> 6767.0167 | Q21: =Model!M35 -> 8139.2296 | S21: 5877.2572 | T21: 241.66262 | U21: 331.1049 | V21: 441.6722 | W21: 3876.1075 | X21: 5324.4981 | Y21: 6845.134 | Z21: 8270.4478 | AB21: =+J21/G21-1 -> 1.9138491 | AC21: =+#REF!/J21-1 -> #REF! | AD21: =+K21/#REF!-1 -> #REF! | AF21: =J21-S21 -> -5173.966 | AG21: =#REF!-#REF! -> #REF! | AH21: =K21-T21 -> 1230.8437 | AJ21: =IF(ISNUMBER(J21/S21-1),J21/S21-1,"n.a.") -> -0.88033683 | AK21: =IF(ISNUMBER(K21/T21-1),K21/T21-1,"n.a.") -> 5.0932315 | AL21: =IF(ISNUMBER(L21/U21-1),L21/U21-1,"n.a.") -> 4.3492504 | AM21: =IF(ISNUMBER(M21/V21-1),M21/V21-1,"n.a.") -> 4.3866941 | AN21: =IF(ISNUMBER(N21/W21-1),N21/W21-1,"n.a.") -> -0.019613391 | AO21: =IF(ISNUMBER(O21/X21-1),O21/X21-1,"n.a.") -> 0.02087368 | AP21: =IF(ISNUMBER(P21/Y21-1),P21/Y21-1,"n.a.") -> -0.011412091 | AQ21: =IF(ISNUMBER(Q21/Z21-1),Q21/Z21-1,"n.a.") -> -0.015865914
B23: Interest income | C23: 利息收入 | D23: =Model!#REF! -> #REF! | E23: =Model!#REF! -> #REF! | F23: =Model!C39 -> 0 | G23: =Model!D39 -> 2.7387298 | H23: =Model!E39 -> 20.080901 | J23: =Model!E39 -> 20.080901 | K23: =Model!G39 -> 29.262542 | L23: =Model!H39 -> 19.820948 | M23: =Model!I39 -> 122.48631 | N23: =Model!J39 -> 260.35607 | O23: =Model!K39 -> 270.40038 | P23: =Model!L39 -> 322.80575 | Q23: =Model!M39 -> 339.57589 | S23: 321.3525 | T23: 3.7305807 | U23: 4.6632259 | V23: 5.5958711 | W23: 181.94424 | X23: 292.448 | Y23: 346.33455 | Z23: 368.93115 | AB23: =+J23/G23-1 -> 6.332195 | AC23: =+#REF!/J23-1 -> #REF! | AD23: =+K23/#REF!-1 -> #REF! | AF23: =J23-S23 -> -301.2716 | AG23: =#REF!-#REF! -> #REF! | AH23: =K23-T23 -> 25.531962 | AJ23: =IF(ISNUMBER(J23/S23-1),J23/S23-1,"n.a.") -> -0.9375113 | AK23: =IF(ISNUMBER(K23/T23-1),K23/T23-1,"n.a.") -> 6.8439644 | AL23: =IF(ISNUMBER(L23/U23-1),L23/U23-1,"n.a.") -> 3.2504799 | AM23: =IF(ISNUMBER(M23/V23-1),M23/V23-1,"n.a.") -> 20.888693 | AN23: =IF(ISNUMBER(N23/W23-1),N23/W23-1,"n.a.") -> 0.43096622 | AO23: =IF(ISNUMBER(O23/X23-1),O23/X23-1,"n.a.") -> -0.075389896 | AP23: =IF(ISNUMBER(P23/Y23-1),P23/Y23-1,"n.a.") -> -0.067936624 | AQ23: =IF(ISNUMBER(Q23/Z23-1),Q23/Z23-1,"n.a.") -> -0.079568403
B24: Interest expense | C24: 利息支出 | D24: =D23+D25 -> #REF! | E24: =E23+E25 -> #REF! | F24: =F23+F25 -> 10.454 | G24: =G23+G25 -> 7.820805 | H24: =H23+H25 -> 6.1152435 | J24: =J23+J25 -> 6.1152435 | K24: =K23+K25 -> 17.868585 | L24: =L23+L25 -> 60.860431 | M24: =M23+M25 -> 124.77192 | N24: =N23+N25 -> 69.820337 | O24: =O23+O25 -> 131.35327 | P24: =P23+P25 -> 131.35327 | Q24: =Q23+Q25 -> 131.35327 | S24: 0.98 | T24: 13.102404 | U24: 13.102404 | V24: 13.102404 | W24: 90.278082 | X24: 131.35327 | Y24: 131.35327 | Z24: 131.35327 | AF24: =J24-S24 -> 5.1352435 | AG24: =#REF!-#REF! -> #REF! | AH24: =K24-T24 -> 4.7661812 | AJ24: =IF(ISNUMBER(J24/S24-1),J24/S24-1,"n.a.") -> 5.2400444 | AK24: =IF(ISNUMBER(K24/T24-1),K24/T24-1,"n.a.") -> 0.36376388 | AL24: =IF(ISNUMBER(L24/U24-1),L24/U24-1,"n.a.") -> 3.6449821 | AM24: =IF(ISNUMBER(M24/V24-1),M24/V24-1,"n.a.") -> 8.5228269 | AN24: =IF(ISNUMBER(N24/W24-1),N24/W24-1,"n.a.") -> -0.22660811 | AO24: =IF(ISNUMBER(O24/X24-1),O24/X24-1,"n.a.") -> 0 | AP24: =IF(ISNUMBER(P24/Y24-1),P24/Y24-1,"n.a.") -> 0 | AQ24: =IF(ISNUMBER(Q24/Z24-1),Q24/Z24-1,"n.a.") -> 0
B25: Net interest income/(expense) | C25: 财务费用 | D25: =-Model!#REF! -> #REF! | E25: =-Model!#REF! -> #REF! | F25: =-Model!C38 -> 10.454 | G25: =-Model!D38 -> 5.0820752 | H25: =-Model!E38 -> -13.965657 | J25: =-Model!E38 -> -13.965657 | K25: =-Model!G38 -> -11.393957 | L25: =-Model!H38 -> 41.039484 | M25: =-Model!I38 -> 2.2856168 | N25: =-Model!J38 -> -190.53573 | O25: =-Model!K38 -> -139.04711 | P25: =-Model!L38 -> -191.45248 | Q25: =-Model!M38 -> -208.22262 | S25: -320.3725 | T25: 9.3718231 | U25: 8.4391779 | V25: 7.5065327 | W25: -91.666162 | X25: -161.09473 | Y25: -214.98127 | Z25: -237.57788 | AB25: =+J25/G25-1 -> -3.7480225 | AC25: =+#REF!/J25-1 -> #REF! | AD25: =+K25/#REF!-1 -> #REF! | AF25: =J25-S25 -> 306.40684 | AG25: =#REF!-#REF! -> #REF! | AH25: =K25-T25 -> -20.76578 | AJ25: =IF(ISNUMBER(J25/S25-1),J25/S25-1,"n.a.") -> -0.95640807 | AK25: =IF(ISNUMBER(K25/T25-1),K25/T25-1,"n.a.") -> -2.2157674 | AL25: =IF(ISNUMBER(L25/U25-1),L25/U25-1,"n.a.") -> 3.8629717 | AM25: =IF(ISNUMBER(M25/V25-1),M25/V25-1,"n.a.") -> -0.6955163 | AN25: =IF(ISNUMBER(N25/W25-1),N25/W25-1,"n.a.") -> 1.0785831 | AO25: =IF(ISNUMBER(O25/X25-1),O25/X25-1,"n.a.") -> -0.13686124 | AP25: =IF(ISNUMBER(P25/Y25-1),P25/Y25-1,"n.a.") -> -0.10944581 | AQ25: =IF(ISNUMBER(Q25/Z25-1),Q25/Z25-1,"n.a.") -> -0.12356059
B27: Investment gains/losses | C27: 投资收益 | D27: =Model!#REF! -> #REF! | E27: =Model!#REF! -> #REF! | F27: =Model!C43 -> 19.021 | G27: =Model!D43 -> 13.060716 | H27: =Model!E43 -> 7.1893001 | J27: =Model!E43 -> 7.1893001 | K27: =Model!G43 -> 22.526716 | L27: =Model!H43 -> 70.018458 | M27: =Model!I43 -> 141.5636 | N27: =Model!J43 -> 95.315854 | O27: =Model!K43 -> 110 | P27: =Model!L43 -> 110 | Q27: =Model!M43 -> 110 | S27: 60 | T27: 8.9883266 | U27: -0.024134033 | V27: 0.96340535 | W27: 105.79103 | X27: 110 | Y27: 110 | Z27: 110 | AB27: =+J27/G27-1 -> -0.44954778 | AC27: =+#REF!/J27-1 -> #REF! | AD27: =+K27/#REF!-1 -> #REF! | AF27: =J27-S27 -> -52.8107 | AG27: =#REF!-#REF! -> #REF! | AH27: =K27-T27 -> 13.538389 | AJ27: =IF(ISNUMBER(J27/S27-1),J27/S27-1,"n.a.") -> -0.88017833 | AK27: =IF(ISNUMBER(K27/T27-1),K27/T27-1,"n.a.") -> 1.5062191 | AL27: =IF(ISNUMBER(L27/U27-1),L27/U27-1,"n.a.") -> -2902.2332 | AM27: =IF(ISNUMBER(M27/V27-1),M27/V27-1,"n.a.") -> 145.94085 | AN27: =IF(ISNUMBER(N27/W27-1),N27/W27-1,"n.a.") -> -0.099017609 | AO27: =IF(ISNUMBER(O27/X27-1),O27/X27-1,"n.a.") -> 0 | AP27: =IF(ISNUMBER(P27/Y27-1),P27/Y27-1,"n.a.") -> 0 | AQ27: =IF(ISNUMBER(Q27/Z27-1),Q27/Z27-1,"n.a.") -> 0
B28: Non-operating income/(loss) | C28: 营业外收支 | D28: =Model!#REF! -> #REF! | E28: =Model!#REF! -> #REF! | F28: =Model!C47 -> -9.3561 | G28: =Model!D47 -> -1.5794621 | H28: =Model!E47 -> -4.1295241 | J28: =Model!E47 -> -4.1295241 | K28: =Model!G47 -> -15.04049 | L28: =Model!H47 -> -18.256918 | M28: =Model!I47 -> -9.0968043 | N28: =Model!J47 -> -37.457737 | O28: =Model!K47 -> -30.607988 | P28: =Model!L47 -> -30.607988 | Q28: =Model!M47 -> -30.607988 | S28: -2 | T28: 0 | U28: 0 | V28: 0 | W28: -14.729772 | X28: -37.457737 | Y28: -37.457737 | Z28: -37.457737 | AF28: =J28-S28 -> -2.1295241 | AG28: =#REF!-#REF! -> #REF! | AH28: =K28-T28 -> -15.04049 | AJ28: =IF(ISNUMBER(J28/S28-1),J28/S28-1,"n.a.") -> 1.0647621 | AK28: =IF(ISNUMBER(K28/T28-1),K28/T28-1,"n.a.") -> n.a. | AL28: =IF(ISNUMBER(L28/U28-1),L28/U28-1,"n.a.") -> n.a. | AM28: =IF(ISNUMBER(M28/V28-1),M28/V28-1,"n.a.") -> n.a. | AN28: =IF(ISNUMBER(N28/W28-1),N28/W28-1,"n.a.") -> 1.542995 | AO28: =IF(ISNUMBER(O28/X28-1),O28/X28-1,"n.a.") -> -0.18286608 | AP28: =IF(ISNUMBER(P28/Y28-1),P28/Y28-1,"n.a.") -> -0.18286608 | AQ28: =IF(ISNUMBER(Q28/Z28-1),Q28/Z28-1,"n.a.") -> -0.18286608
B29: Pre-tax profit (Income before tax) | C29: 利润总额 | D29: =Model!#REF! -> #REF! | E29: =Model!#REF! -> #REF! | F29: =Model!C50 -> 389.8051 | G29: =Model!D50 -> 273.32785 | H29: =Model!E50 -> 736.50294 | J29: =Model!E50 -> 736.50294 | K29: =Model!G50 -> 1513.5168 | L29: =Model!H50 -> 1836.0097 | M29: =Model!I50 -> 2579.2709 | N29: =Model!J50 -> 4107.3123 | O29: =Model!K50 -> 5739.0791 | P29: =Model!L50 -> 7113.8612 | Q29: =Model!M50 -> 8495.2442 | S29: 6343.5997 | T29: 252.51783 | U29: 333.8803 | V29: 446.36778 | W29: 4128.7716 | X29: 5616.9697 | Y29: 7191.4921 | Z29: 8639.4025 | AB29: =+J29/G29-1 -> 1.694577 | AC29: =+#REF!/J29-1 -> #REF! | AD29: =+K29/#REF!-1 -> #REF! | AF29: =J29-S29 -> -5607.0967 | AG29: =#REF!-#REF! -> #REF! | AH29: =K29-T29 -> 1260.999 | AJ29: =IF(ISNUMBER(J29/S29-1),J29/S29-1,"n.a.") -> -0.88389826 | AK29: =IF(ISNUMBER(K29/T29-1),K29/T29-1,"n.a.") -> 4.9937027 | AL29: =IF(ISNUMBER(L29/U29-1),L29/U29-1,"n.a.") -> 4.4990059 | AM29: =IF(ISNUMBER(M29/V29-1),M29/V29-1,"n.a.") -> 4.7783538 | AN29: =IF(ISNUMBER(N29/W29-1),N29/W29-1,"n.a.") -> -0.0051975142 | AO29: =IF(ISNUMBER(O29/X29-1),O29/X29-1,"n.a.") -> 0.021739376 | AP29: =IF(ISNUMBER(P29/Y29-1),P29/Y29-1,"n.a.") -> -0.010794828 | AQ29: =IF(ISNUMBER(Q29/Z29-1),Q29/Z29-1,"n.a.") -> -0.016686143
B31: Provision for taxes | C31: 所得税 | D31: =-Model!#REF! -> #REF! | E31: =-Model!#REF! -> #REF! | F31: =-Model!C53 -> 93.6393 | G31: =-Model!D53 -> 57.496914 | H31: =-Model!E53 -> 165.92903 | J31: =-Model!E53 -> 165.92903 | K31: =-Model!G53 -> 320.55641 | L31: =-Model!H53 -> 395.48918 | M31: =-Model!I53 -> 539.49813 | N31: =-Model!J53 -> 780.88329 | O31: =-Model!K53 -> 1176.5112 | P31: =-Model!L53 -> 1458.3415 | Q31: =-Model!M53 -> 1741.5251 | S31: 1008.1373 | T31: 57.515113 | U31: 75.748781 | V31: 101.0434 | W31: 822.31469 | X31: 1123.3939 | Y31: 1438.2984 | Z31: 1727.8805 | AB31: =+J31/G31-1 -> 1.8858772 | AC31: =+#REF!/J31-1 -> #REF! | AD31: =+K31/#REF!-1 -> #REF! | AF31: =J31-S31 -> -842.20826 | AG31: =#REF!-#REF! -> #REF! | AH31: =K31-T31 -> 263.04129 | AJ31: =IF(ISNUMBER(J31/S31-1),J31/S31-1,"n.a.") -> -0.83541028 | AK31: =IF(ISNUMBER(K31/T31-1),K31/T31-1,"n.a.") -> 4.5734292 | AL31: =IF(ISNUMBER(L31/U31-1),L31/U31-1,"n.a.") -> 4.2210633 | AM31: =IF(ISNUMBER(M31/V31-1),M31/V31-1,"n.a.") -> 4.3392715 | AN31: =IF(ISNUMBER(N31/W31-1),N31/W31-1,"n.a.") -> -0.050383871 | AO31: =IF(ISNUMBER(O31/X31-1),O31/X31-1,"n.a.") -> 0.047282861 | AP31: =IF(ISNUMBER(P31/Y31-1),P31/Y31-1,"n.a.") -> 0.013935302 | AQ31: =IF(ISNUMBER(Q31/Z31-1),Q31/Z31-1,"n.a.") -> 0.0078967037
B32: Effective tax rate | C32: 有效税率 | D32: =IF(ISERROR(D31/D29)," ",(D31/D29)) | E32: =IF(ISERROR(E31/E29)," ",(E31/E29)) | F32: =IF(ISERROR(F31/F29)," ",(F31/F29)) -> 0.24022082 | G32: =IF(ISERROR(G31/G29)," ",(G31/G29)) -> 0.21035878 | H32: =IF(ISERROR(H31/H29)," ",(H31/H29)) -> 0.2252931 | J32: =IF(ISERROR(J31/J29)," ",(J31/J29)) -> 0.2252931 | K32: =IF(ISERROR(K31/K29)," ",(K31/K29)) -> 0.21179574 | L32: =IF(ISERROR(L31/L29)," ",(L31/L29)) -> 0.21540691 | M32: =IF(ISERROR(M31/M29)," ",(M31/M29)) -> 0.20916691 | N32: =IF(ISERROR(N31/N29)," ",(N31/N29)) -> 0.19012026 | O32: =IF(ISERROR(O31/O29)," ",(O31/O29)) -> 0.205 | P32: =IF(ISERROR(P31/P29)," ",(P31/P29)) -> 0.205 | Q32: =IF(ISERROR(Q31/Q29)," ",(Q31/Q29)) -> 0.205 | S32: 0.15892196 | T32: 0.22776654 | U32: 0.22687407 | V32: 0.22636804 | W32: 0.19916691 | X32: 0.2 | Y32: 0.2 | Z32: 0.2 | AF32: =J32-S32 -> 0.066371144 | AG32: =#REF!-#REF! -> #REF! | AH32: =K32-T32 -> -0.015970802 | AJ32: =IF(ISNUMBER(J32/S32-1),J32/S32-1,"n.a.") -> 0.41763356 | AK32: =IF(ISNUMBER(K32/T32-1),K32/T32-1,"n.a.") -> -0.070119176 | AL32: =IF(ISNUMBER(L32/U32-1),L32/U32-1,"n.a.") -> -0.050544165 | AM32: =IF(ISNUMBER(M32/V32-1),M32/V32-1,"n.a.") -> -0.075987431 | AN32: =IF(ISNUMBER(N32/W32-1),N32/W32-1,"n.a.") -> -0.04542244 | AO32: =IF(ISNUMBER(O32/X32-1),O32/X32-1,"n.a.") -> 0.025 | AP32: =IF(ISNUMBER(P32/Y32-1),P32/Y32-1,"n.a.") -> 0.025 | AQ32: =IF(ISNUMBER(Q32/Z32-1),Q32/Z32-1,"n.a.") -> 0.025
B34: Minority interest | C34: 少数股东损益 | D34: =-Model!#REF! -> #REF! | E34: =-Model!#REF! -> #REF! | F34: =-Model!C54 -> 0 | G34: =-Model!D54 -> 0 | H34: =-Model!E54 -> 0 | J34: =-Model!E54 -> 0 | K34: =-Model!G54 -> 0 | L34: =-Model!H54 -> 0 | M34: =-Model!I54 -> 0 | N34: =-Model!J54 -> -0.27984775 | O34: =-Model!K54 -> -0.27984775 | P34: =-Model!L54 -> -0.27984775 | Q34: =-Model!M54 -> -0.27984775 | S34: 2.8606495 | T34: 16.534368 | U34: 16.534368 | V34: 16.534368 | W34: 0 | X34: -0.27984775 | Y34: -0.27984775 | Z34: -0.27984775 | AF34: =J34-S34 -> -2.8606495 | AG34: =#REF!-#REF! -> #REF! | AH34: =K34-T34 -> -16.534368 | AJ34: =IF(ISNUMBER(J34/S34-1),J34/S34-1,"n.a.") -> -1 | AK34: =IF(ISNUMBER(K34/T34-1),K34/T34-1,"n.a.") -> -1 | AL34: =IF(ISNUMBER(L34/U34-1),L34/U34-1,"n.a.") -> -1 | AM34: =IF(ISNUMBER(M34/V34-1),M34/V34-1,"n.a.") -> -1 | AN34: =IF(ISNUMBER(N34/W34-1),N34/W34-1,"n.a.") -> n.a. | AO34: =IF(ISNUMBER(O34/X34-1),O34/X34-1,"n.a.") -> 0 | AP34: =IF(ISNUMBER(P34/Y34-1),P34/Y34-1,"n.a.") -> 0 | AQ34: =IF(ISNUMBER(Q34/Z34-1),Q34/Z34-1,"n.a.") -> 0
B35: Net income | C35: 净利润 | D35: =Model!#REF! -> #REF! | E35: =Model!#REF! -> #REF! | F35: =Model!C57 -> 296.1658 | G35: =Model!D57 -> 215.83094 | H35: =Model!E57 -> 570.57391 | J35: =Model!E57 -> 570.57391 | K35: =Model!G57 -> 1192.9604 | L35: =Model!H57 -> 1440.5206 | M35: =Model!I57 -> 2039.7728 | N35: =Model!J57 -> 3326.7089 | O35: =Model!K57 -> 4562.8478 | P35: =Model!L57 -> 5655.7995 | Q35: =Model!M57 -> 6753.999 | S35: 5332.6017 | T35: 178.46835 | U35: 241.59715 | V35: 328.79001 | W35: 3306.457 | X35: 4493.8556 | Y35: 5753.4735 | Z35: 6911.8019 | AB35: =+J35/G35-1 -> 1.643615 | AC35: =+#REF!/J35-1 -> #REF! | AD35: =+K35/#REF!-1 -> #REF! | AF35: =J35-S35 -> -4762.0278 | AG35: =#REF!-#REF! -> #REF! | AH35: =K35-T35 -> 1014.4921 | AJ35: =IF(ISNUMBER(J35/S35-1),J35/S35-1,"n.a.") -> -0.89300271 | AK35: =IF(ISNUMBER(K35/T35-1),K35/T35-1,"n.a.") -> 5.6844367 | AL35: =IF(ISNUMBER(L35/U35-1),L35/U35-1,"n.a.") -> 4.9624899 | AM35: =IF(ISNUMBER(M35/V35-1),M35/V35-1,"n.a.") -> 5.203877 | AN35: =IF(ISNUMBER(N35/W35-1),N35/W35-1,"n.a.") -> 0.0061249537 | AO35: =IF(ISNUMBER(O35/X35-1),O35/X35-1,"n.a.") -> 0.015352549 | AP35: =IF(ISNUMBER(P35/Y35-1),P35/Y35-1,"n.a.") -> -0.016976534 | AQ35: =IF(ISNUMBER(Q35/Z35-1),Q35/Z35-1,"n.a.") -> -0.02283093 | AS35: =(Q35/O35)^0.5-1 -> 0.21664117
B37: Basic EPS (Rmb) | C37: 基本每股收益（元） | D37: =Model!#REF! -> #REF! | E37: =Model!#REF! -> #REF! | F37: =Model!C60 -> 1.9637077 | G37: =Model!D60 -> 0.47435372 | H37: =Model!E60 -> 1.219175 | J37: =Model!E60 -> 1.219175 | K37: =Model!G60 -> 2.2940973 | L37: =Model!H60 -> 2.7701626 | M37: =Model!I60 -> 3.9225419 | N37: =Model!J60 -> 6.3973571 | O37: =Model!K60 -> 8.7744879 | P37: =Model!L60 -> 10.876266 | Q37: =Model!M60 -> 12.988135 | S37: 1.9747675 | T37: 0.60682262 | U37: 0.82147122 | V37: 1.1179417 | W37: 6.3584121 | X37: 8.641814 | Y37: 11.064096 | Z37: 13.291594 | AB37: =+J37/G37-1 -> 1.5701812 | AC37: =+#REF!/J37-1 -> #REF! | AD37: =+K37/#REF!-1 -> #REF! | AF37: =J37-S37 -> -0.75559252 | AG37: =#REF!-#REF! -> #REF! | AH37: =K37-T37 -> 1.6872747 | AJ37: =IF(ISNUMBER(J37/S37-1),J37/S37-1,"n.a.") -> -0.38262353 | AK37: =IF(ISNUMBER(K37/T37-1),K37/T37-1,"n.a.") -> 2.7805072 | AL37: =IF(ISNUMBER(L37/U37-1),L37/U37-1,"n.a.") -> 2.3721968 | AM37: =IF(ISNUMBER(M37/V37-1),M37/V37-1,"n.a.") -> 2.5087177 | AN37: =IF(ISNUMBER(N37/W37-1),N37/W37-1,"n.a.") -> 0.0061249537 | AO37: =IF(ISNUMBER(O37/X37-1),O37/X37-1,"n.a.") -> 0.015352549 | AP37: =IF(ISNUMBER(P37/Y37-1),P37/Y37-1,"n.a.") -> -0.016976534 | AQ37: =IF(ISNUMBER(Q37/Z37-1),Q37/Z37-1,"n.a.") -> -0.02283093
B38: YoY | L38: =L37/K37-1 -> 0.2075175 | M38: =M37/L37-1 -> 0.415997 | N38: =N37/M37-1 -> 0.63092127 | O38: =O37/N37-1 -> 0.37158013 | P38: =P37/O37-1 -> 0.2395328 | Q38: =Q37/P37-1 -> 0.19417229 | W38: 0.62099276 | X38: 0.35084127 | Y38: 0.28029781 | Z38: 0.20132679
B40: Growth analysis | C40: 利润率分析
B41: Total revenues | K41: =K4/J4-1 -> 0.65794076 | L41: =L4/K4-1 -> 0.21891747 | M41: =M4/L4-1 -> 0.32419494 | N41: =N4/M4-1 -> 0.40629862 | O41: =O4/N4-1 -> 0.32534294 | P41: =P4/O4-1 -> 0.21015705 | Q41: =Q4/P4-1 -> 0.17275087 | W41: 0.44984851 | X41: 0.33117838 | Y41: 0.23248764 | Z41: 0.17850025
B42: Energy drinks | L42: =L5/K5-1 -> 0.23975022 | M42: =M5/L5-1 -> 0.26476027 | N42: =N5/M5-1 -> 0.28711036 | O42: =O5/N5-1 -> 0.1979 | P42: =P5/O5-1 -> 0.17 | Q42: =Q5/P5-1 -> 0.14 | W42: 0.31005 | X42: 0.2177 | Y42: 0.2 | Z42: 0.15
B43: Other beverage | L43: =L6/K6-1 -> -0.14228767 | M43: =M6/L6-1 -> 1.8664623 | N43: =N6/M6-1 -> 1.7536885 | O43: =O6/N6-1 -> 0.9982 | P43: =P6/O6-1 -> 0.3365 | Q43: =Q6/P6-1 -> 0.2625 | W43: 2.036 | X43: 0.9303 | Y43: 0.34 | Z43: 0.2625
B44: GP | L44: =L11/K11-1 -> 0.1626708 | M44: =M11/L11-1 -> 0.34756578 | N44: =N11/M11-1 -> 0.46301495 | O44: =O11/N11-1 -> 0.32832537 | P44: =P11/O11-1 -> 0.23640366 | Q44: =Q11/P11-1 -> 0.18128073 | W44: 0.51705666 | X44: 0.34282453 | Y44: 0.25159475 | Z44: 0.18681682
B45: Energy drinks | L45: =L12/K12-1 -> 0.16375823 | M45: =M12/L12-1 -> 0.32501304 | N45: =N12/M12-1 -> 0.36896111 | O45: =O12/N12-1 -> 0.26394562 | P45: =P12/O12-1 -> 0.19825526 | Q45: =Q12/P12-1 -> 0.14 | W45: 0.39106977 | X45: 0.28747801 | Y45: 0.21154351 | Z45: 0.14891524
B46: Other beverage | L46: =L13/K13-1 -> 0.12606706 | M46: =M13/L13-1 -> 1.8972881 | N46: =N13/M13-1 -> 3.2601609 | O46: =O13/N13-1 -> 0.94161322 | P46: =P13/O13-1 -> 0.47145226 | Q46: =Q13/P13-1 -> 0.38762362 | W46: 4.2866497 | X46: 0.87016968 | Y46: 0.51290444 | Z46: 0.3837706
B47: OP | L47: =L21/K21-1 -> 0.20282204 | M47: =M21/L21-1 -> 0.34327161 | N47: =N21/M21-1 -> 0.59724232 | O47: =O21/N21-1 -> 0.43040001 | P47: =P21/O21-1 -> 0.24493467 | Q47: =Q21/P21-1 -> 0.2027796 | W47: 0.62919638 | X47: 0.4011528 | Y47: 0.28559233 | Z47: 0.20822293
B48: NP | L48: =L35/K35-1 -> 0.2075175 | M48: =M35/L35-1 -> 0.415997 | N48: =N35/M35-1 -> 0.63092127 | O48: =O35/N35-1 -> 0.37158013 | P48: =P35/O35-1 -> 0.2395328 | Q48: =Q35/P35-1 -> 0.19417229 | W48: 0.62099276 | X48: 0.35084127 | Y48: 0.28029781 | Z48: 0.20132679
B51: Margin analysis | C51: 利润率分析
B52: Gross margin | C52: 毛利率 | D52: =1-D10/D4 -> #REF! | E52: =1-E10/E4 -> #REF! | F52: =1-F10/F4 -> 0.47922117 | G52: =1-G10/G4 -> 0.4596798 | H52: =1-H10/H4 -> 0.46736425 | J52: =1-J10/J4 -> 0.46736425 | K52: =1-K10/K4 -> 0.44372835 | L52: =1-L10/L4 -> 0.42325261 | M52: =1-M10/M4 -> 0.43072263 | N52: =1-N10/N4 -> 0.44809377 | O52: =1-O10/O4 -> 0.44910212 | P52: =1-P10/P4 -> 0.45884251 | Q52: =1-Q10/Q4 -> 0.46217985 | S52: 0.44660892 | T52: 0.2230015 | U52: 0.23483893 | V52: 0.24820089 | W52: 0.45068891 | X52: 0.45201403 | Y52: 0.45902155 | Z52: 0.46226083 | AB52: =+J52-G52 -> 0.0076844473 | AC52: =+#REF!-J52 -> #REF! | AD52: =+K52-#REF! -> #REF! | AF52: =J52-S52 -> 0.020755324 | AG52: =#REF!-#REF! -> #REF! | AH52: =K52-T52 -> 0.22072685 | AJ52: =+J52-S52 -> 0.020755324 | AK52: =+K52-T52 -> 0.22072685 | AL52: =+L52-U52 -> 0.18841368 | AM52: =+M52-V52 -> 0.18252174 | AN52: =+N52-W52 -> -0.0025951371 | AO52: =+O52-X52 -> -0.0029119159 | AP52: =+P52-Y52 -> -0.00017903907 | AQ52: =+Q52-Z52 -> -8.0981711e-05
B53: Energy drinks | K53: =K12/K5 -> 0.46088723 | L53: =L12/L5 -> 0.43263659 | M53: =M12/M5 -> 0.45324726 | N53: =N12/N5 -> 0.48207045 | O53: =O12/O5 -> 0.50864916 | P53: =P12/P5 -> 0.52093293 | Q53: =Q12/Q5 -> 0.52093293 | W53: 0.48127824 | X53: 0.50969459 | Y53: 0.51459764 | Z53: 0.51411224 | AN53: =+N53-W53 -> 0.0007922084 | AO53: =+O53-X53 -> -0.0010454273 | AP53: =+P53-Y53 -> 0.0063352896 | AQ53: =+Q53-Z53 -> 0.0068206919
B54: Other beverage | K54: =K13/K6 -> 0.13000051 | L54: =L13/L6 -> 0.17067411 | M54: =M13/M6 -> 0.17250953 | N54: =N13/N6 -> 0.26688508 | O54: =O13/O6 -> 0.25932719 | P54: =P13/P6 -> 0.28551259 | Q54: =Q13/Q6 -> 0.31380912 | W54: 0.30039442 | X54: 0.2585714 | Y54: 0.29193569 | Z54: 0.31997784 | AN54: =+N54-W54 -> -0.033509346 | AO54: =+O54-X54 -> 0.00075578858 | AP54: =+P54-Y54 -> -0.006423096 | AQ54: =+Q54-Z54 -> -0.0061687159
B55: EBITDA margin | C55: EBITDA利润率 | D55: =D17/D4 -> #REF! | E55: =E17/E4 -> #REF! | F55: =F17/F4 -> 0.13372712 | G55: =G17/G4 -> 0.10743348 | H55: =H17/H4 -> 0.19317371 | J55: =J17/J4 -> 0.19317371 | K55: =K17/K4 -> 0.23755536 | L55: =L17/L4 -> 0.23456943 | M55: =M17/M4 -> 0.23379564 | N55: =N17/N4 -> 0.26158055 | O55: =O17/O4 -> 0.27876719 | P55: =P17/P4 -> 0.28629875 | Q55: =Q17/Q4 -> 0.29784326 | S55: 0.31905641 | T55: 0.11560749 | U55: 0.12153591 | V55: 0.12796022 | W55: 0.25920348 | X55: 0.27228732 | Y55: 0.2829674 | Z55: 0.29425174 | AB55: =+J55-G55 -> 0.085740226 | AC55: =+#REF!-J55 -> #REF! | AD55: =+K55-#REF! -> #REF! | AF55: =J55-S55 -> -0.1258827 | AG55: =#REF!-#REF! -> #REF! | AH55: =K55-T55 -> 0.12194787 | AJ55: =+J55-S55 -> -0.1258827 | AK55: =+K55-T55 -> 0.12194787 | AL55: =+L55-U55 -> 0.11303352 | AM55: =+M55-V55 -> 0.10583542 | AN55: =+N55-W55 -> 0.0023770731 | AO55: =+O55-X55 -> 0.0064798665 | AP55: =+P55-Y55 -> 0.0033313502 | AQ55: =+Q55-Z55 -> 0.0035915154
B56: SG&A | C56: SG&A率 | D56: =+D52-D57 -> #REF! | E56: =+E52-E57 -> #REF! | F56: =+F52-F57 -> 0.34549405 | G56: =+G52-G57 -> 0.38022014 | H56: =+H52-H57 -> 0.30026123 | J56: =+J52-J57 -> 0.30026123 | K56: =+K52-K57 -> 0.23270173 | L56: =+L52-L57 -> 0.21501253 | M56: =+M52-M57 -> 0.2194826 | N56: =+N52-N57 -> 0.20817209 | O56: =O15/O4 -> 0.19969185 | P56: =P15/P4 -> 0.19439185 | Q56: =Q15/Q4 -> 0.19079185 | S56: 0.15059441 | T56: 0.13584985 | U56: 0.13969375 | V56: 0.14527162 | W56: 0.21331824 | X56: =X15/X4 -> 0.20209185 | Y56: =Y15/Y4 -> 0.19709185 | Z56: =Z15/Z4 -> 0.19359185 | AB56: =+J56-G56 -> -0.079958907 | AC56: =+#REF!-J56 -> #REF! | AD56: =+K56-#REF! -> #REF! | AF56: =+AF52-AF57 -> 0.14966683 | AG56: =+AG52-AG57 -> #REF! | AH56: =+AH52-AH57 -> 0.096851886 | AJ56: =+J56-S56 -> 0.14966683 | AK56: =+K56-T56 -> 0.096851886 | AL56: =+L56-U56 -> 0.075318785 | AM56: =+M56-V56 -> 0.074210978 | AN56: =+N56-W56 -> -0.0051461506 | AO56: =+O56-X56 -> -0.0024 | AP56: =+P56-Y56 -> -0.0027 | AQ56: =+Q56-Z56 -> -0.0028
B57: Operating profit margin | C57: EBIT利润率 | D57: =D21/D4 -> #REF! | E57: =E21/E4 -> #REF! | F57: =F21/F4 -> 0.13372712 | G57: =G21/G4 -> 0.079459659 | H57: =H21/H4 -> 0.16710301 | J57: =J21/J4 -> 0.16710301 | K57: =K21/K4 -> 0.21102662 | L57: =L21/L4 -> 0.20824008 | M57: =M21/M4 -> 0.21124003 | N57: =N21/N4 -> 0.23992168 | O57: =O21/O4 -> 0.25893975 | P57: =P21/P4 -> 0.26638118 | Q57: =Q21/Q4 -> 0.27320198 | S57: 0.29601452 | T57: 0.087151656 | U57: 0.095145181 | V57: 0.10292927 | W57: 0.23737066 | X57: 0.25253334 | Y57: 0.26341435 | Z57: 0.27005786 | AB57: =+J57-G57 -> 0.087643354 | AC57: =+#REF!-J57 -> #REF! | AD57: =+K57-#REF! -> #REF! | AF57: =J57-S57 -> -0.1289115 | AG57: =#REF!-#REF! -> #REF! | AH57: =K57-T57 -> 0.12387497 | AJ57: =+J57-S57 -> -0.1289115 | AK57: =+K57-T57 -> 0.12387497 | AL57: =+L57-U57 -> 0.1130949 | AM57: =+M57-V57 -> 0.10831076 | AN57: =+N57-W57 -> 0.0025510135 | AO57: =+O57-X57 -> 0.006406404 | AP57: =+P57-Y57 -> 0.0029668352 | AQ57: =+Q57-Z57 -> 0.0031441141
B58: Pre-tax profit margin | C58: 税前利润率 | D58: =D29/D4 -> #REF! | E58: =E29/E4 -> #REF! | F58: =F29/F4 -> 0.13707154 | G58: =G29/G4 -> 0.089983412 | H58: =H29/H4 -> 0.17499417 | J58: =J29/J4 -> 0.17499417 | K58: =K29/K4 -> 0.21690389 | L58: =L29/L4 -> 0.21586427 | M58: =M29/M4 -> 0.22900809 | N58: =N29/N4 -> 0.25931882 | O58: =O29/O4 -> 0.2733948 | P58: =P29/P4 -> 0.28003459 | Q58: =Q29/Q4 -> 0.28515199 | S58: 0.31950237 | T58: 0.09106641 | U58: 0.09594271 | V58: 0.10402355 | W58: 0.25284367 | X58: 0.26640485 | Y58: 0.2767429 | Z58: 0.28210547 | AB58: =+J58-G58 -> 0.085010757 | AC58: =+#REF!-J58 -> #REF! | AD58: =+K58-#REF! -> #REF! | AF58: =J58-S58 -> -0.1445082 | AG58: =#REF!-#REF! -> #REF! | AH58: =K58-T58 -> 0.12583748 | AJ58: =+J58-S58 -> -0.1445082 | AK58: =+K58-T58 -> 0.12583748 | AL58: =+L58-U58 -> 0.11992156 | AM58: =+M58-V58 -> 0.12498453 | AN58: =+N58-W58 -> 0.0064751409 | AO58: =+O58-X58 -> 0.006989945 | AP58: =+P58-Y58 -> 0.0032916959 | AQ58: =+Q58-Z58 -> 0.003046518
B59: Net profit margin | C59: 净利润率 | D59: =D35/D4 -> #REF! | E59: =E35/E4 -> #REF! | F59: =F35/F4 -> 0.10414411 | G59: =G35/G4 -> 0.071054612 | H59: =H35/H4 -> 0.13556919 | J59: =J35/J4 -> 0.13556919 | K59: =K35/K4 -> 0.17096457 | L59: =L35/L4 -> 0.16936562 | M59: =M35/M4 -> 0.18110717 | N59: =N35/N4 -> 0.21003472 | O59: =O35/O4 -> 0.2173622 | P59: =P35/P4 -> 0.22263852 | Q59: =Q35/Q4 -> 0.22670522 | S59: 0.26858235 | T59: 0.064361681 | U59: 0.069424538 | V59: 0.076622703 | W59: 0.20248558 | X59: 0.21313716 | Y59: 0.22140509 | Z59: 0.22569351 | AB59: =+J59-G59 -> 0.064514578 | AC59: =+#REF!-J59 -> #REF! | AD59: =+K59-#REF! -> #REF! | AF59: =J59-S59 -> -0.13301316 | AG59: =#REF!-#REF! -> #REF! | AH59: =K59-T59 -> 0.10660289 | AJ59: =+J59-S59 -> -0.13301316 | AK59: =+K59-T59 -> 0.10660289 | AL59: =+L59-U59 -> 0.099941078 | AM59: =+M59-V59 -> 0.10448447 | AN59: =+N59-W59 -> 0.0075491413 | AO59: =+O59-X59 -> 0.0042250405 | AP59: =+P59-Y59 -> 0.0012334307 | AQ59: =+Q59-Z59 -> 0.0010117099
B61: Source: Company data, Goldman Sachs Research estimates.
B63: vs. consensus
B64: Consensus Sales | J64: 19774 | K64: 26478
B65: diff. | J65: =+J4/J64-1 -> -0.78715847 | K65: =+K4/K64-1 -> -0.73646716
B66: Consensus EBIT | J66: 5889 | K66: 8228
B67: diff. | J67: =+J21/J66-1 -> -0.88057544 | K67: =+K21/K66-1 -> -0.82103715
B68: Consensus NI | J68: 5248 | K68: 7406
B69: diff. | J69: =+J35/J68-1 -> -0.89127784 | K69: =+K35/K68-1 -> -0.83891974

Sheet Segment
B2: Annual | D2: 财务预测汇总 | U2: Halves | AZ2: Quarters
B4: Net Profit | D4: 净利润 | F4: =F65 -> 296.1658 | G4: =G65 -> 215.83094 | H4: =H65 -> 570.57391 | I4: =I65 -> 812.06352 | J4: =J65 -> 1192.9604 | K4: =K65 -> 1440.5206 | L4: =L65 -> 2039.7728 | M4: =M65 -> 3326.7089 | ... P4: =P65 -> 6753.999
B5: EPS | D5: EPS | F5: =F68 -> 1.9637077 | G5: =G68 -> 0.47435372 | H5: =H68 -> 1.219175 | I5: =I68 -> 1.7351785 | J5: =J68 -> 2.2940973 | K5: =K68 -> 2.7701626 | L5: =L68 -> 3.9225419 | M5: =M68 -> 6.3973571 | ... P5: =P68 -> 12.988135
B6: YoY | D6: YoY | G6: =G5/F5-1 -> -0.75843975 | H6: =H5/G5-1 -> 1.5701812 | I6: =I5/H5-1 -> 0.42323983 | J6: =J5/I5-1 -> 0.32211028 | K6: =K5/J5-1 -> 0.2075175 | L6: =L5/K5-1 -> 0.415997 | M6: =M5/L5-1 -> 0.63092127 | N6: =N5/M5-1 -> 0.37158013 | ... P6: =P5/O5-1 -> 0.19417229
B8: Financial summaries | F8: 2017 | G8: 2018 | H8: 2019 | I8: 2020 | J8: 2021 | K8: 2022 | L8: 2023 | M8: 2024 | N8: 2025E | O8: 2026E | P8: 2027E | V8: 1H20 | W8: 2H20 | X8: 1H21 | Y8: 2H21 | Z8: 1H22 | AA8: 2H22 | AB8: 1H23 | AC8: 2H23 | AD8: 1H24 | AE8: 2H24 | AF8: 1H25E | AG8: 2H25E | AH8: 1H26E | AI8: 2H26E | BB8: 1Q20 | BC8: 2Q20 | BD8: 3Q20 | BE8: 4Q20 | BF8: 1Q21 | BG8: 2Q21 | BH8: 3Q21 | BI8: 4Q21 | BJ8: 1Q22 | BK8: 2Q22 | BL8: 3Q22 | BM8: 4Q22 | BN8: 1Q23 | BO8: 2Q23 | BP8: 3Q23 | BQ8: 4Q23 | BR8: 1Q24 | BS8: 2Q24 | BT8: 3Q24 | BU8: 4Q24 | BV8: 1Q25 | BW8: 2Q25 | BX8: 3Q25 | BY8: 4Q25E | BZ8: 1Q26E | CA8: 2Q26E | CB8: 3Q26E | CC8: 4Q26E
B9: Total revenue | D9: 营业收入 | F9: =Model!C13 -> 2843.8076 | G9: =Model!D13 -> 3037.536 | H9: =Model!E13 -> 4208.7285 | I9: =Model!F13 -> 4958.5026 | J9: =Model!G13 -> 6977.8225 | K9: =Model!H13 -> 8505.3897 | L9: =Model!I13 -> 11262.794 | M9: =Model!J13 -> 15838.852 | N9: =SUM(N11,N13,N15,N16) -> 20991.911 | O9: =SUM(O11,O13,O15,O16) -> 25403.508 | P9: =SUM(P11,P13,P15,P16) -> 29791.987 | U9: =D9 -> 营业收入 | V9: =+SUM(BB9:BC9) -> 2469.4627 | W9: =+I9-V9 -> 2489.0399 | X9: =+SUM(BF9:BG9) -> 3682.2618 | Y9: =+J9-X9 -> 3295.5607 | Z9: =+SUM(BJ9:BK9) -> 4291.274 | AA9: =K9-Z9 -> 4214.1157 | AB9: ='Raw Data'!Y8 -> 5460.1849 | AC9: =L9-AB9 -> 5802.6092 | AD9: ='Raw Data'!AC8 -> 7873.2879 | AE9: =M9-AD9 -> 7965.564 | AF9: =BV9+BW9 -> 10736.628 | AG9: =BX9+BY9 -> 10255.283 | AH9: =BZ9+CA9 -> 13147.167 | AI9: =CB9+CC9 -> 12256.342 | AZ9: =U9 -> 营业收入 | BB9: =+Quarterly!D43 -> 933.21619 | BC9: =+Quarterly!E43 -> 1536.2465 | BD9: =+Quarterly!F43 -> 1574.1342 | BE9: =+I9-SUM(BB9:BD9) -> 914.90569 | BF9: =+Quarterly!H43 -> 1711.2617 | BG9: =+Quarterly!I43 -> 1971 | BH9: =+Quarterly!J43 -> 1877.9507 | BI9: =+J9-SUM(BF9:BH9) -> 1417.61 | BJ9: =+Quarterly!L43 -> 2006.5429 | BK9: =+Quarterly!M43 -> 2284.7311 | BL9: =+Quarterly!N43 -> 2353.0738 | BM9: =+Quarterly!O43 -> 1861.0419 | BN9: =+Quarterly!P43 -> 2490.866 | BO9: =+Quarterly!Q43 -> 2969.3189 | BP9: =+Quarterly!R43 -> 3180.7274 | BQ9: =+Quarterly!S43 -> 2621.8817 | ... CC9: =+Quarterly!AE43 -> 4744.3135
B10: Accretion | D10: 较上一期绝对增量 | G10: =G9-F9 -> 193.7284 | H10: =H9-G9 -> 1171.1925 | I10: =I9-H9 -> 749.77414 | J10: =J9-I9 -> 2019.3199 | K10: =K9-J9 -> 1527.5673 | L10: =L9-K9 -> 2757.4044 | M10: =M9-L9 -> 4576.0577 | N10: =N9-M9 -> 5153.0587 | ... P10: =P9-O9 -> 4388.4781 | U10: =D10 -> 较上一期绝对增量 | X10: =X9-V9 -> 1212.7991 | Y10: =Y9-W9 -> 806.5208 | Z10: =Z9-X9 -> 609.01224 | AA10: =AA9-Y9 -> 918.55501 | AB10: =AB9-Z9 -> 1168.9109 | AC10: =AC9-AA9 -> 1588.4934 | AD10: =AD9-AB9 -> 2413.1029 | AE10: =AE9-AD9 -> 92.276124 | AF10: =AF9-AE9 -> 2771.0639 | AG10: =AG9-AF9 -> -481.34521 | AH10: =AH9-AG9 -> 2891.8841 | AI10: =AI9-AH9 -> -890.82494 | AZ10: =D10 -> 较上一期绝对增量 | BF10: =BF9-BB9 -> 778.04554 | BG10: =BG9-BC9 -> 434.75352 | BH10: =BH9-BD9 -> 303.81648 | BI10: =BI9-BE9 -> 502.70433 | BJ10: =BJ9-BF9 -> 295.28114 | BK10: =BK9-BG9 -> 313.7311 | BL10: =BL9-BH9 -> 475.12312 | BM10: =BM9-BI9 -> 443.4319 | ... CC10: =CC9-BY9 -> 596.37091
B11: Energy drinks | D11: 东鹏特饮 | G11: =+G74 -> 2885.4971 | H11: =+H74 -> 4003.0305 | I11: =+I74 -> 4655.1538 | J11: =+J74 -> 6591.8979 | K11: =+K74 -> 8172.3068 | L11: =+L74 -> 10336.009 | M11: =+M74 -> 13303.584 | N11: =+N74 -> 15936.364 | ... P11: =+P74 -> 21255.922 | U11: =+D11 -> 东鹏特饮 | V11: =+V74 -> 2272.3273 | W11: =+W74 -> 2382.8265 | X11: =+X74 -> 3547.2256 | Y11: =+Y74 -> 3044.6723 | Z11: =+Z74 -> 4118.3335 | AA11: =+AA74 -> 4053.9733 | AB11: =+AB74 -> 5134.9885 | AC11: =+AC74 -> 5201.0205 | ... AE11: =+AE74 -> 6447.6431 | AF11: =BV11+BW11 -> 8360.511 | AG11: =BX11+BY11 -> 7575.8526 | AH11: =BZ11+CA11 -> 10071.618 | AI11: =CB11+CC11 -> 8573.9269 | AZ11: =+U11 -> 东鹏特饮 | BD11: =+BD74 -> 1493.9188 | BE11: =+BE74 -> 888.9077 | BF11: =+BF74 -> 1645.0964 | BG11: =+BG74 -> 1902.1292 | BH11: =+BH74 -> 1791.118 | BI11: =+BI74 -> 1253.5543 | BJ11: =+BJ74 -> 1906.5175 | BK11: =+BK74 -> 2211.816 | ... BR11: =+BR74 -> 3100.6926 | BS11: =Quarterly!U90 -> 3755.2486 | BT11: =Quarterly!V90 -> 3667.457 | BU11: =Quarterly!W90 -> 2778.0709 | BV11: =Quarterly!X90 -> 3900.5289 | BW11: =Quarterly!Y90 -> 4459.9821 | BX11: =Quarterly!Z90 -> 4202.6446 | BY11: =Quarterly!AA90 -> 3373.208 | BZ11: =Quarterly!AB90 -> 4719.64 | ... CC11: =Quarterly!AE90 -> 3572.7799
B12: Other beverage | D12: 其他饮料 | G12: =+G177 -> 135.6807 | H12: =+H177 -> 188.7768 | I12: =+I177 -> 280.5093 | J12: =+J177 -> 371.94956 | K12: =+K177 -> 319.02572 | L12: =+L177 -> 914.47521 | M12: =+M177 -> 2518.1799 | N12: =+N177 -> 5031.827 | ... P12: =+P177 -> 8490.3589 | U12: =+D12 -> 其他饮料 | V12: =+V177 -> 186.8873 | W12: =+W177 -> 134.2044 | X12: =+X177 -> 125.26 | Y12: =+Y177 -> 246.68956 | Z12: =+Z177 -> 165.92805 | AA12: =+AA177 -> 153.09767 | AB12: =+AB177 -> 319.9848 | AC12: =+AC177 -> 594.49041 | ... AE12: =+AE177 -> 1512.4799 | AF12: =BV12+BW12 -> 2370.0423 | AG12: =BX12+BY12 -> 2661.7847 | AH12: =BZ12+CA12 -> 3075.5482 | AI12: =CB12+CC12 -> 3649.4885 | AZ12: =+U12 -> 其他饮料 | BD12: =+BD177 -> 73.6436 | BE12: =+BE177 -> 60.5608 | BF12: =+BF177 -> 61.5905 | BG12: =+BG177 -> 63.6695 | BH12: =+BH177 -> 85.615 | BI12: =+BI177 -> 161.07456 | BJ12: =+BJ177 -> 92.7097 | BK12: =+BK177 -> 73.218354 | ... BR12: =+BR177 -> 376.8936 | BS12: =Quarterly!U92 -> 628.8064 | BT12: =Quarterly!V92 -> 1016.293 | BU12: =Quarterly!W92 -> 498.30205 | BV12: =Quarterly!X92 -> 944.6384 | BW12: =Quarterly!Y92 -> 1425.4039 | BX12: =Quarterly!Z92 -> 1901.0519 | BY12: =Quarterly!AA92 -> 760.73278 | BZ12: =Quarterly!AB92 -> 1243.4882 | ... CC12: =Quarterly!AE92 -> 1138.6074
B13: Electrolyte drinks | D13: 电解质饮料 | M13: =M188 -> 1495.0141 | N13: =N188 -> 3303.9811 | O13: =O188 -> 4493.4143 | P13: =P188 -> 5684.1691 | U13: =+D13 -> 电解质饮料 | AZ13: 电解质饮料 | BR13: =Quarterly!T177 -> 157.65 | BS13: =Quarterly!U177 -> 318.1878 | BT13: =Quarterly!V177 -> 736.6667 | BU13: =Quarterly!W177 -> 282.50957 | BV13: =Quarterly!X177 -> 569.8415 | BW13: =Quarterly!Y177 -> 922.89694 | BX13: =Quarterly!Z177 -> 1354.0319 | BY13: =Quarterly!AA177 -> 457.21079 | ... CC13: =Quarterly!AE177 -> 700.12431
B14: Water | D14: 包装饮用水 | G14: =+G243 -> 36.6265 | H14: =+H243 -> 40.8852 | I14: =+I243 -> 40.5824 | J14: =+J243 -> 0 | K14: =+K243 -> 0 | L14: =+L243 -> 0 | M14: =+M243 -> 0 | N14: =+N243 -> 0 | ... P14: =+P243 -> 0 | U14: =+D14 -> 包装饮用水 | V14: =+V243 -> 0 | W14: =+W243 -> 0 | X14: =+X243 -> 0 | Y14: =+Y243 -> 0 | Z14: =+Z243 -> 0 | AA14: =+AA243 -> 0 | AB14: =+AB243 -> 0 | AC14: =+AC243 -> 0 | ... AE14: =+AE243 -> 0 | AF14: =BV14+BW14 -> 0 | AG14: =BX14+BY14 -> 0 | AH14: =BZ14+CA14 -> 0 | AI14: =CB14+CC14 -> 0 | AZ14: 包装饮用水 | BE14: =+W14 -> 0
B15: Other drinks | D15: 其他 | M15: =M190 -> 1023.1658 | N15: =N190 -> 1727.8459 | O15: =O190 -> 2231.6225 | P15: =P190 -> 2806.1898 | U15: =+D15 -> 其他 | AZ15: 其他 | BR15: =Quarterly!T179 -> 217.1284 | BS15: =Quarterly!U179 -> 310.6186 | BT15: =Quarterly!V179 -> 279.6263 | BU15: =Quarterly!W179 -> 215.79248 | BV15: =Quarterly!X179 -> 374.7969 | BW15: =Quarterly!Y179 -> 502.50692 | BX15: =Quarterly!Z179 -> 547.02008 | BY15: =Quarterly!AA179 -> 303.52199 | ... CC15: =Quarterly!AE179 -> 438.48307
B16: Others | D16: 其他 | G16: =+G260 -> 16.3582 | H16: =+H260 -> 16.9211 | I16: =+I260 -> 22.8394 | J16: =+J260 -> 13.975034 | K16: =K9-K11-K12 -> 14.057179 | L16: =L9-L11-L12 -> 12.309875 | M16: =M9-M11-M12 -> 17.087687 | N16: =+N260 -> 23.719902 | O16: =+O260 -> 32.926267 | P16: =+P260 -> 45.705884 | U16: =+D16 -> 其他 | V16: =+V260 -> 10.248172 | W16: =+W260 -> 12.591228 | X16: =+X260 -> 9.7761564 | Y16: =+Y260 -> 4.1988779 | Z16: =+Z260 -> 7.0124213 | AA16: =+AA260 -> 7.0447582 | AB16: =+AB260 -> 5.2116289 | AC16: =+AC260 -> 7.0982465 | ... AE16: =+AE260 -> 5.4410345 | AF16: =BV16+BW16 -> 0 | AG16: =BX16+BY16 -> 0 | AH16: =BZ16+CA16 -> 0 | AI16: =CB16+CC16 -> 0 | AZ16: =+U16 -> 其他 | BD16: =+BD260 -> 6.5718274 | BE16: =+BE260 -> 6.0194004 | BF16: =+BF260 -> 4.5748272 | BG16: =+BG260 -> 5.2013272 | BH16: =+BH260 -> 1.2177031 | BI16: =+BI260 -> 2.9811769 | BJ16: =+BJ260 -> 7.3156683 | BK16: =+BK260 -> -0.303247 | ... CC16: =+CC260 -> 0
D17: check | G17: =+G9-SUM(G11:G12,G16) -> -3.8000007e-07 | H17: =+H9-SUM(H11:H12,H16) -> 7.927e-05 | I17: =+I9-SUM(I11:I12,I16) -> 0.00011873 | J17: =+J9-SUM(J11:J12,J16) -> 0 | K17: =+K9-SUM(K11:K12,K16) -> 0 | L17: =+L9-SUM(L11:L12,L16) -> 0 | M17: =+M9-SUM(M11:M12,M16) -> 0 | N17: =+N9-SUM(N11:N12,N16) -> 0 | ... P17: =+P9-SUM(P11:P12,P16) -> 0 | V17: =+V9-SUM(V11:V12,V16) -> -7.214e-05 | W17: =+W9-SUM(W11:W12,W16) -> -40.582209 | X17: =+X9-SUM(X11:X12,X16) -> -2.0399998e-06 | Y17: =+Y9-SUM(Y11:Y16) -> 2.0399993e-06 | Z17: =+Z9-SUM(Z11:Z16) -> 0 | AA17: =+AA9-SUM(AA11:AA16) -> 0 | AB17: =+AB9-SUM(AB11:AB16) -> 0 | AC17: =+AC9-SUM(AC11:AC16) -> 0 | AD17: =+AD9-SUM(AD11:AD16) -> 0 | AE17: =+AE9-SUM(AE11:AE16) -> 0 | AZ17: o | BD17: =+BD9-SUM(BD11:BD16) -> 0 | BE17: =+BE9-SUM(BE11:BE16) -> -40.582209 | BH17: =+BH9-SUM(BH11:BH16) -> 0
B18: YoY change - revenue | D18: 收入增速 | F18: =IF(ISNUMBER(F9/#REF!),F9/#REF!-1,"") | G18: =IF(ISNUMBER(G9/F9),G9/F9-1,"") -> 0.068122893 | H18: =IF(ISNUMBER(H9/G9),H9/G9-1,"") -> 0.3855732 | I18: =IF(ISNUMBER(I9/H9),I9/H9-1,"") -> 0.17814742 | J18: =IF(ISNUMBER(J9/I9),J9/I9-1,"") -> 0.40724388 | K18: =IF(ISNUMBER(K9/J9),K9/J9-1,"") -> 0.21891747 | L18: =IF(ISNUMBER(L9/K9),L9/K9-1,"") -> 0.32419494 | M18: =IF(ISNUMBER(M9/L9),M9/L9-1,"") -> 0.40629862 | N18: =IF(ISNUMBER(N9/M9),N9/M9-1,"") -> 0.32534294 | ... P18: =IF(ISNUMBER(P9/O9),P9/O9-1,"") -> 0.17275087 | U18: =D18 -> 收入增速 | V18: =IF(ISNUMBER(V9/#REF!),V9/#REF!-1,"") | W18: =IF(ISNUMBER(W9/#REF!),W9/#REF!-1,"") | X18: =IF(ISNUMBER(X9/V9),X9/V9-1,"") -> 0.4911186 | Y18: =IF(ISNUMBER(Y9/W9),Y9/W9-1,"") -> 0.32402887 | Z18: =IF(ISNUMBER(Z9/X9),Z9/X9-1,"") -> 0.16539081 | AA18: =IF(ISNUMBER(AA9/Y9),AA9/Y9-1,"") -> 0.27872495 | AB18: =IF(ISNUMBER(AB9/Z9),AB9/Z9-1,"") -> 0.27239252 | AC18: =IF(ISNUMBER(AC9/AA9),AC9/AA9-1,"") -> 0.37694585 | AD18: =IF(ISNUMBER(AD9/AB9),AD9/AB9-1,"") -> 0.44194527 | AE18: =IF(ISNUMBER(AE9/AC9),AE9/AC9-1,"") -> 0.37275556 | ... AI18: =IF(ISNUMBER(AI9/AG9),AI9/AG9-1,"") -> 0.19512472 | AZ18: =U18 -> 收入增速 | BF18: =BF9/BB9-1 -> 0.83372486 | BG18: =BG9/BC9-1 -> 0.28299724 | BH18: =BH9/BD9-1 -> 0.19300544 | BI18: =BI9/BE9-1 -> 0.54946027 | BJ18: =BJ9/BF9-1 -> 0.17255171 | BK18: =BK9/BG9-1 -> 0.15917357 | BL18: =BL9/BH9-1 -> 0.25300085 | BM18: =BM9/BI9-1 -> 0.31280246 | ... CC18: =CC9/BY9-1 -> 0.14377511
