Workbook
Name A_ALL_BOX: #REF!
Name A_ALL_DBX: #REF!
Name A_ALL_KEYWORDS_TYPE_ScalarContributed_EQTY_200019588: #REF!,#REF!,#REF!,#REF!
Name A_ALL_KEYWORDS_TYPE_ScalarContributed_ISSR_208018133: #REF!,#REF!,#REF!,#REF!,#REF!,#REF!,#REF!,#REF!,#REF!,#REF!,#REF!,#REF!
Name A_ALL_KEYWORDS_TYPE_Vector_EQTY_200019588: #REF!,#REF!,#REF!,#REF!,#REF!,#REF!,#REF!
Name A_ALL_KEYWORDS_TYPE_Vector_ISSR_208018133: #REF!,#REF!,#REF!,#REF!,#REF!,#REF!,#REF!,#REF!,#REF!,#REF!,#REF!,#REF!,#REF!,#REF!,#REF!,#REF!,#REF!,#REF!,#REF!,#REF!,#REF!,#REF!,#REF!
Name A_ALL_MDB: #REF!
Name A_ALL_NTNX: [1]NTNX_Annotation_Sheet!$A$1:$CB$331
Name A_ALL_PVTL: #REF!
Name A_ALL_SECTION_KEYWORDS_EQTY_200019588_13A: #REF!
Name A_ALL_SECTION_KEYWORDS_EQTY_200019588_13K: #REF!
Name A_ALL_SECTION_KEYWORDS_ISSR_208018133_1314: #REF!
Name A_ALL_SECTION_KEYWORDS_ISSR_208018133_1319: #REF!
Name A_ALL_SECTION_KEYWORDS_ISSR_208018133_131E: #REF!
Name A_ALL_SECTION_KEYWORDS_ISSR_208018133_13V: #REF!,#REF!
Name A_ALL_SECTION_KEYWORDS_ISSR_208020111_136J: #REF!,#REF!
Name A_ALL_SNOW: #REF!
Name A_ALL_TTAN: #REF!
Name AL_email: "alamba@isigrp.com"
Name AL_phone: "(XXX) XXX-XXXX"
Name AVELIFE: 3
Name BB_email: "bbaytosh@isigrp.com"
Name BB_phone: "(212) 446-9469"
Name CUR3MTH: 6
Name CURCYTD: 9
Name CURMTH: 1
Name CURMYTD: 12
Name CURRENT_MONTH_FIXING: 23
Name CURRENT_MONTH_SPOT: 6
Name CURWEEK: 1
Name CYTDVOL: 11
Name DB: "WIRENYPROD"
Name E_ALL_BOX: #REF!
Name E_ALL_DBX: #REF!
Name E_ALL_MDB: #REF!
Name E_ALL_MSFT: [2]MSFT_Exchange_Sheet!$A$1:$FE$331
Name E_ALL_NTNX: [1]NTNX_Exchange_Sheet!$A$1:$CB$331
Name E_ALL_PING: #REF!
Name E_ALL_PVTL: #REF!
Name E_ALL_SECTION_KEYWORDS_ISSR_208020111_136J: #REF!,#REF!
Name E_ALL_SNOW: #REF!
Name E_ALL_TTAN: #REF!
Name FINCriteriaType: 1
Name fx: 120
Name FYE: "FYE"
Name HB_email: "hbellini@isigrp.com"
Name HB_phone: "(XXX) XXX-XXXX"
Name L_ALL_BOX: #REF!
Name L_ALL_DBX: #REF!
Name L_ALL_DOCU: #REF!
Name L_ALL_KEYWORDS_TYPE_ScalarContributed_EQTY_200019588: #REF!,#REF!,#REF!,#REF!
Name L_ALL_KEYWORDS_TYPE_ScalarContributed_ISSR_208018133: #REF!,#REF!,#REF!,#REF!,#REF!,#REF!,#REF!,#REF!,#REF!,#REF!,#REF!,#REF!
Name L_ALL_KEYWORDS_TYPE_Vector_EQTY_200019588: #REF!,#REF!,#REF!,#REF!,#REF!,#REF!,#REF!
Name L_ALL_KEYWORDS_TYPE_Vector_ISSR_208018133: #REF!,#REF!,#REF!,#REF!,#REF!,#REF!,#REF!,#REF!,#REF!,#REF!,#REF!,#REF!,#REF!,#REF!,#REF!,#REF!,#REF!,#REF!,#REF!,#REF!,#REF!,#REF!,#REF!
Name L_ALL_MDB: #REF!
Name L_ALL_MSFT: [2]MSFT_Live_Sheet!$A$1:$FE$331
Name L_ALL_NTNX: [1]NTNX_Live_Sheet!$A$1:$CB$331
Name L_ALL_PING: #REF!
Name L_ALL_PVTL: #REF!
Name L_ALL_SECTION_KEYWORDS_EQTY_200019588_13A: #REF!

Sheet __FDSCACHE__
B1: This sheet contains FactSet XML data for use with this workbook's =FDS codes. Modifying the worksheet's contents may damage the workbook's =FDS functionality.

Sheet Cover
C2: Snowflake Analyst Model
C3: Ticker: | D3: SNOW
C4: Date: | D4: =TODAY() -> 45995
B6: Kash Rangan
B7: (415) 249-7318
B8: kash.rangan@gs.com
B10: Matthew Martino
B11: (212) 902-0695
B12: matt.martino@gs.com
B14: Selina Zhang
B15: (212) 357-9979
B16: selina.zhang@gs.com
B18: Nishad Patwardhan
B19: (332) 245-7726
B20: nishad.patwardhan@gs.com

Sheet Revenue Build
B2: Snowflake Inc.
B3: Income Statement (Non-GAAP)
B4: Fiscal Year Ends Jan 31
B5: ($ millions, except per share amounts)
C7: =Dates!M3 -> 2018 (A) | H7: =Dates!R3 -> 2019 (A) | M7: =Dates!W3 -> 2020 (A) | R7: =Dates!AB3 -> 2021 (A) | W7: =Dates!AG3 -> 2022 (A) | AB7: =Dates!AL3 -> 2023 (A) | AG7: =Dates!AQ3 -> 2024 (A) | AL7: =Dates!AV3 -> 2025 (A) | AQ7: =Dates!BA3 -> 2026 (E) | AV7: =Dates!BF3 -> 2027 (E) | BA7: =Dates!BK3 -> 2028 (E) | BF7: =Dates!BP3 -> 2029 (E) | BK7: =Dates!BU3 -> 2030 (E)
C8: =Dates!M4 -> 1Q18 (A) | D8: =Dates!N4 -> 2Q18 (A) | E8: =Dates!O4 -> 3Q18 (A) | F8: =Dates!P4 -> 4Q18 (A) | G8: =Dates!Q4 -> FY18 (A) | H8: =Dates!R4 -> 1Q19 (A) | I8: =Dates!S4 -> 2Q19 (A) | J8: =Dates!T4 -> 3Q19 (A) | ... BO8: =Dates!BY4 -> FY30 (E)
C9: =Dates!M5 -> 42855 | D9: =Dates!N5 -> 42947 | E9: =Dates!O5 -> 43039 | F9: =Dates!P5 -> 43131 | G9: =Dates!Q5 -> 43131 | H9: =Dates!R5 -> 43220 | I9: =Dates!S5 -> 43312 | J9: =Dates!T5 -> 43404 | ... BO9: =Dates!BY5 -> 47514
A11: TREV | B11: Total revenue | H11: =H15+H51 -> 13.403 | I11: =I15+I51 -> 17.905 | J11: =J15+J51 -> 28.68 | K11: =K15+K51 -> 36.678 | L11: =L15+L51 -> 96.666 | M11: =M15+M51 -> 43.705 | N11: =N15+N51 -> 60.339 | O11: =O15+O51 -> 73.012 | ... BO11: =BO15+BO51 -> 10933.987
A12: TREVYY | B12: % yoy | H12: =IFERROR(H11/C11-1,"--") -> -- | I12: =IFERROR(I11/D11-1,"--") -> -- | J12: =IFERROR(J11/E11-1,"--") -> -- | K12: =IFERROR(K11/F11-1,"--") -> -- | L12: =IFERROR(L11/G11-1,"--") -> -- | M12: =IFERROR(M11/H11-1,"--") -> 2.2608371 | N12: =IFERROR(N11/I11-1,"--") -> 2.3699525 | O12: =IFERROR(O11/J11-1,"--") -> 1.5457462 | ... BO12: =IFERROR(BO11/BJ11-1,"--") -> 0.23213886
A13: TREVQQ | B13: % qoq | H13: =IFERROR(H11/F11-1,"--") -> -- | I13: =IFERROR(I11/H11-1,"--") -> 0.33589495 | J13: =IFERROR(J11/I11-1,"--") -> 0.60178721 | K13: =IFERROR(K11/J11-1,"--") -> 0.27887029 | L13: -- | M13: =IFERROR(M11/K11-1,"--") -> 0.19158624 | N13: =IFERROR(N11/M11-1,"--") -> 0.38059719 | O13: =IFERROR(O11/N11-1,"--") -> 0.21003 | P13: =IFERROR(P11/O11-1,"--") -> 0.20106284 | Q13: -- | R13: =IFERROR(R11/P11-1,"--") -> 0.24087716 | S13: =IFERROR(S11/R11-1,"--") -> 0.2235905 | T13: =IFERROR(T11/S11-1,"--") -> 0.19887341 | U13: =IFERROR(U11/T11-1,"--") -> 0.19321029 | V13: -- | W13: =IFERROR(W11/U11-1,"--") -> 0.20186911 | X13: =IFERROR(X11/W11-1,"--") -> 0.18908411 | Y13: =IFERROR(Y11/X11-1,"--") -> 0.2286681 | Z13: =IFERROR(Z11/Y11-1,"--") -> 0.14750883 | AA13: -- | AB13: =IFERROR(AB11/Z11-1,"--") -> 0.10057221 | AC13: =IFERROR(AC11/AB11-1,"--") -> 0.1772778 | AD13: =IFERROR(AD11/AC11-1,"--") -> 0.1202217 | AE13: =IFERROR(AE11/AD11-1,"--") -> 0.057419017 | AF13: -- | AG13: =IFERROR(AG11/AE11-1,"--") -> 0.058720366 | AH13: =IFERROR(AH11/AG11-1,"--") -> 0.080851637 | AI13: =IFERROR(AI11/AH11-1,"--") -> 0.089248358 | AJ13: =IFERROR(AJ11/AI11-1,"--") -> 0.055199524 | AK13: -- | AL13: =IFERROR(AL11/AJ11-1,"--") -> 0.0697174 | AM13: =IFERROR(AM11/AL11-1,"--") -> 0.048405411 | AN13: =IFERROR(AN11/AM11-1,"--") -> 0.084333633 | AO13: =IFERROR(AO11/AN11-1,"--") -> 0.047422019 | AP13: -- | AQ13: =IFERROR(AQ11/AO11-1,"--") -> 0.056045482 | AR13: =IFERROR(AR11/AQ11-1,"--") -> 0.098740588 | AS13: =IFERROR(AS11/AR11-1,"--") -> 0.059337851 | AT13: =IFERROR(AT11/AS11-1,"--") -> 0.029593363 | AU13: -- | AV13: =IFERROR(AV11/AT11-1,"--") -> 0.051415566 | AW13: =IFERROR(AW11/AV11-1,"--") -> 0.077702662 | AX13: =IFERROR(AX11/AW11-1,"--") -> 0.061679661 | AY13: =IFERROR(AY11/AX11-1,"--") -> 0.031227037 | AZ13: -- | BA13: =IFERROR(BA11/AY11-1,"--") -> 0.051656838 | BB13: =IFERROR(BB11/BA11-1,"--") -> 0.080750139 | BC13: =IFERROR(BC11/BB11-1,"--") -> 0.06458557 | BD13: =IFERROR(BD11/BC11-1,"--") -> 0.020906453 | BE13: -- | BF13: =IFERROR(BF11/BD11-1,"--") -> 0.043255196 | BG13: =IFERROR(BG11/BF11-1,"--") -> 0.078245432 | BH13: =IFERROR(BH11/BG11-1,"--") -> 0.08362997 | BI13: =IFERROR(BI11/BH11-1,"--") -> 0.025390643 | BJ13: -- | BK13: =IFERROR(BK11/BI11-1,"--") -> 0.037762815 | BL13: =IFERROR(BL11/BK11-1,"--") -> 0.064624957 | BM13: =IFERROR(BM11/BL11-1,"--") -> 0.090957753 | BN13: =IFERROR(BN11/BM11-1,"--") -> 0.014809061 | BO13: --
A15: PRODREV | B15: Product revenue | H15: ='IS (Non-GAAP)'!H14 -> 13.186 | I15: ='IS (Non-GAAP)'!I14 -> 17.675 | J15: ='IS (Non-GAAP)'!J14 -> 28.457 | K15: ='IS (Non-GAAP)'!K14 -> 36.365 | L15: =SUM(H15:K15) -> 95.683 | M15: ='IS (Non-GAAP)'!M14 -> 42.766 | N15: ='IS (Non-GAAP)'!N14 -> 57.818 | O15: ='IS (Non-GAAP)'!O14 -> 69.213 | P15: ='IS (Non-GAAP)'!P14 -> 82.432 | Q15: =SUM(M15:P15) -> 252.229 | R15: ='IS (Non-GAAP)'!R14 -> 101.817 | S15: ='IS (Non-GAAP)'!S14 -> 125.216 | T15: ='IS (Non-GAAP)'!T14 -> 148.473 | U15: ='IS (Non-GAAP)'!U14 -> 178.288 | V15: =SUM(R15:U15) -> 553.794 | W15: ='IS (Non-GAAP)'!W14 -> 213.83 | X15: ='IS (Non-GAAP)'!X14 -> 254.623 | Y15: ='IS (Non-GAAP)'!Y14 -> 312.458 | Z15: ='IS (Non-GAAP)'!Z14 -> 359.558 | AA15: =SUM(W15:Z15) -> 1140.469 | AB15: ='IS (Non-GAAP)'!AB14 -> 394.434 | AC15: ='IS (Non-GAAP)'!AC14 -> 466.268 | AD15: ='IS (Non-GAAP)'!AD14 -> 522.752 | AE15: ='IS (Non-GAAP)'!AE14 -> 555.329 | AF15: =SUM(AB15:AE15) -> 1938.783 | AG15: ='IS (Non-GAAP)'!AG14 -> 590.072 | AH15: ='IS (Non-GAAP)'!AH14 -> 640.209 | AI15: ='IS (Non-GAAP)'!AI14 -> 698.478 | AJ15: ='IS (Non-GAAP)'!AJ14 -> 738.09 | AK15: =SUM(AG15:AJ15) -> 2666.849 | AL15: ='IS (Non-GAAP)'!AL14 -> 789.587 | AM15: ='IS (Non-GAAP)'!AM14 -> 829.25 | AN15: ='IS (Non-GAAP)'!AN14 -> 900.282 | AO15: ='IS (Non-GAAP)'!AO14 -> 943.303 | AP15: =SUM(AL15:AO15) -> 3462.422 | AQ15: ='IS (Non-GAAP)'!AQ14 -> 996.813 | AR15: ='IS (Non-GAAP)'!AR14 -> 1090.496 | AS15: ='IS (Non-GAAP)'!AS14 -> 1158.377 | AT15: =AT96 -> 1198.816 | AU15: =SUM(AQ15:AT15) -> 4444.502 | AV15: =AV96 -> 1261.6397 | AW15: =AW96 -> 1353.2086 | AX15: =AX96 -> 1440.4205 | AY15: =AY96 -> 1492.4918 | AZ15: =SUM(AV15:AY15) -> 5547.7607 | BA15: =BA96 -> 1571.2058 | BB15: =BB96 -> 1690.9536 | BC15: =BC96 -> 1804.6013 | BD15: =BD96 -> 1849.6205 | BE15: =SUM(BA15:BD15) -> 6916.3812 | BF15: =BF96 -> 1931.2045 | BG15: =BG96 -> 2074.1306 | BH15: =BH96 -> 2254.078 | BI15: =BI96 -> 2319.8661 | BJ15: =SUM(BF15:BI15) -> 8579.2792 | BK15: =BK96 -> 2408.8503 | BL15: =BL96 -> 2554.3169 | BM15: =BM96 -> 2794.5987 | BN15: =BN96 -> 2844.6724 | BO15: =SUM(BK15:BN15) -> 10602.438
A16: PRODREVCHG | B16: $ change yoy | H16: -- | I16: =I15-H15 -> 4.489 | J16: =J15-I15 -> 10.782 | K16: =K15-J15 -> 7.908 | L16: =L15-G15 -> 95.683 | M16: =M15-K15 -> 6.401 | N16: =N15-M15 -> 15.052 | O16: =O15-N15 -> 11.395 | P16: =P15-O15 -> 13.219 | Q16: =Q15-L15 -> 156.546 | R16: =R15-P15 -> 19.385 | S16: =S15-R15 -> 23.399 | T16: =T15-S15 -> 23.257 | U16: =U15-T15 -> 29.815 | V16: =V15-Q15 -> 301.565 | W16: =W15-U15 -> 35.542 | X16: =X15-W15 -> 40.793 | Y16: =Y15-X15 -> 57.835 | Z16: =Z15-Y15 -> 47.1 | AA16: =AA15-V15 -> 586.675 | AB16: =AB15-Z15 -> 34.876 | AC16: =AC15-AB15 -> 71.834 | AD16: =AD15-AC15 -> 56.484 | AE16: =AE15-AD15 -> 32.577 | AF16: =AF15-AA15 -> 798.314 | AG16: =AG15-AE15 -> 34.743 | AH16: =AH15-AG15 -> 50.137 | AI16: =AI15-AH15 -> 58.269 | AJ16: =AJ15-AI15 -> 39.612 | AK16: =AK15-AF15 -> 728.066 | AL16: =AL15-AJ15 -> 51.497 | AM16: =AM15-AL15 -> 39.663 | AN16: =AN15-AM15 -> 71.032 | AO16: =AO15-AN15 -> 43.021 | AP16: =AP15-AK15 -> 795.573 | AQ16: =AQ15-AO15 -> 53.51 | AR16: =AR15-AQ15 -> 93.683 | AS16: =AS15-AR15 -> 67.881 | AT16: =AT15-AS15 -> 40.439006 | AU16: =AU15-AP15 -> 982.08001 | AV16: =AV15-AT15 -> 62.823731 | AW16: =AW15-AV15 -> 91.568828 | AX16: =AX15-AW15 -> 87.21194 | AY16: =AY15-AX15 -> 52.071344 | AZ16: =AZ15-AU15 -> 1103.2586 | BA16: =BA15-AY15 -> 78.713983 | BB16: =BB15-BA15 -> 119.74774 | BC16: =BC15-BB15 -> 113.64776 | BD16: =BD15-BC15 -> 45.019135 | BE16: =BE15-AZ15 -> 1368.6206 | BF16: =BF15-BD15 -> 81.584033 | BG16: =BG15-BF15 -> 142.9261 | BH16: =BH15-BG15 -> 179.94745 | BI16: =BI15-BH15 -> 65.788056 | BJ16: =BJ15-BE15 -> 1662.898 | BK16: =BK15-BI15 -> 88.984167 | BL16: =BL15-BK15 -> 145.4666 | BM16: =BM15-BL15 -> 240.28182 | BN16: =BN15-BM15 -> 50.073735 | BO16: =BO15-BJ15 -> 2023.159
A17: PRODREVYY | B17: % yoy | H17: =IFERROR(H15/C15-1,"--") -> -- | I17: =IFERROR(I15/D15-1,"--") -> -- | J17: =IFERROR(J15/E15-1,"--") -> -- | K17: =IFERROR(K15/F15-1,"--") -> -- | L17: =IFERROR(L15/G15-1,"--") -> -- | M17: =IFERROR(M15/H15-1,"--") -> 2.2432883 | N17: =IFERROR(N15/I15-1,"--") -> 2.271174 | O17: =IFERROR(O15/J15-1,"--") -> 1.4321959 | ... BO17: =IFERROR(BO15/BJ15-1,"--") -> 0.23581923
A18: PRODREVQQ | B18: % qoq | H18: =IFERROR(H15/F15-1,"--") -> -- | I18: =IFERROR(I15/H15-1,"--") -> 0.34043683 | J18: =IFERROR(J15/I15-1,"--") -> 0.61001414 | K18: =IFERROR(K15/J15-1,"--") -> 0.27789296 | L18: -- | M18: =IFERROR(M15/K15-1,"--") -> 0.1760209 | N18: =IFERROR(N15/M15-1,"--") -> 0.35196184 | O18: =IFERROR(O15/N15-1,"--") -> 0.19708395 | P18: =IFERROR(P15/O15-1,"--") -> 0.19099013 | Q18: -- | R18: =IFERROR(R15/P15-1,"--") -> 0.23516353 | S18: =IFERROR(S15/R15-1,"--") -> 0.22981427 | T18: =IFERROR(T15/S15-1,"--") -> 0.18573505 | U18: =IFERROR(U15/T15-1,"--") -> 0.20081092 | V18: -- | W18: =IFERROR(W15/U15-1,"--") -> 0.19935161 | X18: =IFERROR(X15/W15-1,"--") -> 0.19077304 | Y18: =IFERROR(Y15/X15-1,"--") -> 0.22713973 | Z18: =IFERROR(Z15/Y15-1,"--") -> 0.15074026 | AA18: -- | AB18: =IFERROR(AB15/Z15-1,"--") -> 0.096996868 | AC18: =IFERROR(AC15/AB15-1,"--") -> 0.18211919 | AD18: =IFERROR(AD15/AC15-1,"--") -> 0.12114063 | AE18: =IFERROR(AE15/AD15-1,"--") -> 0.062318269 | AF18: -- | AG18: =IFERROR(AG15/AE15-1,"--") -> 0.062562913 | AH18: =IFERROR(AH15/AG15-1,"--") -> 0.084967597 | AI18: =IFERROR(AI15/AH15-1,"--") -> 0.09101559 | AJ18: =IFERROR(AJ15/AI15-1,"--") -> 0.056711879 | AK18: -- | AL18: =IFERROR(AL15/AJ15-1,"--") -> 0.069770624 | AM18: =IFERROR(AM15/AL15-1,"--") -> 0.05023259 | AN18: =IFERROR(AN15/AM15-1,"--") -> 0.085658125 | AO18: =IFERROR(AO15/AN15-1,"--") -> 0.047786138 | AP18: -- | AQ18: =IFERROR(AQ15/AO15-1,"--") -> 0.056726206 | AR18: =IFERROR(AR15/AQ15-1,"--") -> 0.093982522 | AS18: =IFERROR(AS15/AR15-1,"--") -> 0.062247821 | AT18: =IFERROR(AT15/AS15-1,"--") -> 0.034910056 | AU18: -- | AV18: =IFERROR(AV15/AT15-1,"--") -> 0.052404815 | AW18: =IFERROR(AW15/AV15-1,"--") -> 0.07257922 | AX18: =IFERROR(AX15/AW15-1,"--") -> 0.064448262 | AY18: =IFERROR(AY15/AX15-1,"--") -> 0.036150099 | AZ18: -- | BA18: =IFERROR(BA15/AY15-1,"--") -> 0.052739975 | BB18: =IFERROR(BB15/BA15-1,"--") -> 0.076213912 | BC18: =IFERROR(BC15/BB15-1,"--") -> 0.067209272 | BD18: =IFERROR(BD15/BC15-1,"--") -> 0.024946859 | BE18: -- | BF18: =IFERROR(BF15/BD15-1,"--") -> 0.044108526 | BG18: =IFERROR(BG15/BF15-1,"--") -> 0.074008783 | BH18: =IFERROR(BH15/BG15-1,"--") -> 0.086758012 | BI18: =IFERROR(BI15/BH15-1,"--") -> 0.029186237 | BJ18: -- | BK18: =IFERROR(BK15/BI15-1,"--") -> 0.038357458 | BL18: =IFERROR(BL15/BK15-1,"--") -> 0.060388394 | BM18: =IFERROR(BM15/BL15-1,"--") -> 0.094068918 | BN18: =IFERROR(BN15/BM15-1,"--") -> 0.017918041 | BO18: --
B19: % total revenue | H19: =H15/H$11 -> 0.98380959 | I19: =I15/I$11 -> 0.98715443 | J19: =J15/J$11 -> 0.99222455 | K19: =K15/K$11 -> 0.99146627 | L19: =L15/L$11 -> 0.98983096 | M19: =M15/M$11 -> 0.97851504 | N19: =N15/N$11 -> 0.95821939 | O19: =O15/O$11 -> 0.94796746 | ... BO19: =BO15/BO$11 -> 0.9696772
B21: Product Revenue (ex. Leap Year) | AL21: =AG15*(1+AL22) -> 778.89504
B22: % yoy | AL22: 0.32
B23: % qoq | AL23: =IFERROR(AL21/AJ15-1,"--") -> 0.05528464
B24: Net New Revenue (YoY) | AL24: =IFERROR(AL15-AG15,"--") -> 199.515
B25: Net New Revenue (QoQ) | AL25: =IFERROR(AL21-AJ15,"--") -> 40.80504
B27: Net New Product Revenue (Q/Q) | I27: =I15-H15 -> 4.489 | J27: =J15-I15 -> 10.782 | K27: =K15-J15 -> 7.908 | M27: =M15-K15 -> 6.401 | N27: =N15-M15 -> 15.052 | O27: =O15-N15 -> 11.395 | P27: =P15-O15 -> 13.219 | Q27: =SUM(M27:P27) -> 46.067 | R27: =R15-P15 -> 19.385 | S27: =S15-R15 -> 23.399 | T27: =T15-S15 -> 23.257 | U27: =U15-T15 -> 29.815 | V27: =SUM(R27:U27) -> 95.856 | W27: =W15-U15 -> 35.542 | X27: =X15-W15 -> 40.793 | Y27: =Y15-X15 -> 57.835 | Z27: =Z15-Y15 -> 47.1 | AA27: =SUM(W27:Z27) -> 181.27 | AB27: =AB15-Z15 -> 34.876 | AC27: =AC15-AB15 -> 71.834 | AD27: =AD15-AC15 -> 56.484 | AE27: =AE15-AD15 -> 32.577 | AF27: =SUM(AB27:AE27) -> 195.771 | AG27: =AG15-AE15 -> 34.743 | AH27: =AH15-AG15 -> 50.137 | AI27: =AI15-AH15 -> 58.269 | AJ27: =AJ15-AI15 -> 39.612 | AK27: =SUM(AG27:AJ27) -> 182.761 | AL27: =AL15-AJ15 -> 51.497 | AM27: =AM15-AL15 -> 39.663 | AN27: =AN15-AM15 -> 71.032 | AO27: =AO15-AN15 -> 43.021 | AP27: =SUM(AL27:AO27) -> 205.213 | AQ27: =AQ15-AO15 -> 53.51 | AR27: =AR15-AQ15 -> 93.683 | AS27: =AS15-AR15 -> 67.881 | AT27: =AT15-AS15 -> 40.439006 | AU27: =SUM(AQ27:AT27) -> 255.51301 | AV27: =AV15-AT15 -> 62.823731 | AW27: =AW15-AV15 -> 91.568828 | AX27: =AX15-AW15 -> 87.21194 | AY27: =AY15-AX15 -> 52.071344 | AZ27: =SUM(AV27:AY27) -> 293.67584 | BA27: =BA15-AY15 -> 78.713983 | BB27: =BB15-BA15 -> 119.74774 | BC27: =BC15-BB15 -> 113.64776 | BD27: =BD15-BC15 -> 45.019135 | BE27: =SUM(BA27:BD27) -> 357.12862 | BF27: =BF15-BD15 -> 81.584033 | BG27: =BG15-BF15 -> 142.9261 | BH27: =BH15-BG15 -> 179.94745 | BI27: =BI15-BH15 -> 65.788056 | BJ27: =SUM(BF27:BI27) -> 470.24563 | BK27: =BK15-BI15 -> 88.984167 | BL27: =BL15-BK15 -> 145.4666 | BM27: =BM15-BL15 -> 240.28182 | BN27: =BN15-BM15 -> 50.073735 | BO27: =SUM(BK27:BN27) -> 524.80633
B28: =B52 -> % yoy | N28: =N27/I27 -> 3.3530853 | O28: =O27/J27 -> 1.056854 | P28: =P27/K27 -> 1.6715984 | R28: =R27/M27-1 -> 2.0284331 | S28: =S27/N27-1 -> 0.55454425 | T28: =T27/O27-1 -> 1.0409829 | U28: =U27/P27-1 -> 1.2554656 | V28: =V27/Q27-1 -> 1.0807954 | W28: =W27/R27-1 -> 0.83347949 | X28: =X27/S27-1 -> 0.7433651 | Y28: =Y27/T27-1 -> 1.4867782 | ... BO28: =BO27/BJ27-1 -> 0.11602595
B30: Storage Revenue | AG30: =AG15*11% -> 64.90792 | AH30: =AH15*11% -> 70.42299 | AI30: =AI15*11% -> 76.83258 | AJ30: =AJ15*11% -> 81.1899 | AK30: =SUM(AG30:AJ30) -> 293.35339 | AL30: =AL15*11% -> 86.85457 | AM30: =AM15*11% -> 91.2175 | AN30: =AN15*11% -> 99.03102 | AO30: =AO15*11% -> 103.76333 | AP30: =SUM(AL30:AO30) -> 380.86642
B31: % Product Revenue | AG31: =AG30/AG15 -> 0.11 | AH31: =AH30/AH15 -> 0.11 | AI31: =AI30/AI15 -> 0.11 | AJ31: =AJ30/AJ15 -> 0.11 | AK31: =AK30/AK15 -> 0.11 | AL31: =AL30/AL15 -> 0.11 | AM31: =AM30/AM15 -> 0.11 | AN31: =AN30/AN15 -> 0.11 | ... AP31: =AP30/AP15 -> 0.11
B32: Implied Compute Revenue | AG32: =AG15-AG30 -> 525.16408 | AH32: =AH15-AH30 -> 569.78601 | AI32: =AI15-AI30 -> 621.64542 | AJ32: =AJ15-AJ30 -> 656.9001 | AK32: =SUM(AG32:AJ32) -> 2373.4956 | AL32: =AL15-AL30 -> 702.73243 | AM32: =AM15-AM30 -> 738.0325 | AN32: =AN15-AN30 -> 801.25098 | AO32: =AO15-AO30 -> 839.53967 | AP32: =SUM(AL32:AO32) -> 3081.5556
B33: =B22 -> % yoy | AL33: =AL32/AG32-1 -> 0.33811975 | AM33: =AM32/AH32-1 -> 0.29528014 | AN33: =AN32/AI32-1 -> 0.28891962 | AO33: =AO32/AJ32-1 -> 0.27803249 | AP33: =AP32/AK32-1 -> 0.29831948
B34: =B23 -> % qoq | AH34: =AH32/AG32-1 -> 0.084967597 | AI34: =AI32/AH32-1 -> 0.09101559 | AJ34: =AJ32/AI32-1 -> 0.056711879 | AL34: =AL32/AJ32-1 -> 0.069770624 | AM34: =AM32/AL32-1 -> 0.05023259 | AN34: =AN32/AM32-1 -> 0.085658125 | AO34: =AO32/AN32-1 -> 0.047786138
B35: Compute Revenue vs. Product Revenue Growth | AP35: =AP33-AP17 -> 0
B37: Snowpark Revenue | AG37: 3.5 | AH37: 6.5 | AI37: 11 | AJ37: 14 | AK37: 35 | AL37: 18 | AM37: 23 | AN37: 27 | AO37: 31 | AP37: 100
B38: % yoy | AL38: =AL37/AG37-1 -> 4.1428571 | AM38: =AM37/AH37-1 -> 2.5384615 | AN38: =AN37/AI37-1 -> 1.4545455 | AO38: =AO37/AJ37-1 -> 1.2142857 | AP38: =AP37/AK37-1 -> 1.8571429
B39: % qoq | AH39: =AH37/AG37-1 -> 0.85714286 | AI39: =AI37/AH37-1 -> 0.69230769 | AJ39: =AJ37/AI37-1 -> 0.27272727 | AL39: =AL37/AJ37-1 -> 0.28571429 | AM39: =AM37/AL37-1 -> 0.27777778 | AN39: =AN37/AM37-1 -> 0.17391304 | AO39: =AO37/AN37-1 -> 0.14814815
B40: % Revenue | AG40: =AG37/AG15 -> 0.0059314795 | AH40: =AH37/AH15 -> 0.010152934 | AI40: =AI37/AI15 -> 0.015748528 | AJ40: =AJ37/AJ15 -> 0.018967877 | AK40: =AK37/AK15 -> 0.013124103 | AL40: =AL37/AL15 -> 0.022796728 | AM40: =AM37/AM15 -> 0.027735906 | AN40: =AN37/AN15 -> 0.029990603 | ... AP40: =AP37/AP15 -> 0.028881517
B41: Growth ex. Snowpark | AL41: =(AL15-AL37)/(AG15-AG37)-1 -> 0.31541737 | AM41: =(AM15-AM37)/(AH15-AH37)-1 -> 0.27227166 | AN41: =(AN15-AN37)/(AI15-AI37)-1 -> 0.27026901 | AO41: =(AO15-AO37)/(AJ15-AJ37)-1 -> 0.2599304 | AP41: =(AP15-AP37)/(AK15-AK37)-1 -> 0.27758925
B43: Data Engineering | AN43: 200
B45: AI Revenue (Run-rate) | AS45: 100
B47: AI/ML Weekly Users | AM47: 2500 | AN47: 3200 | AO47: 4000 | AQ47: 5200 | AR47: 6100 | AS47: 7300
B48: % qoq | AN48: =AN47/AM47-1 -> 0.28 | AO48: =AO47/AN47-1 -> 0.25 | AQ48: =AQ47/AO47-1 -> 0.3 | AR48: =AR47/AQ47-1 -> 0.17307692 | AS48: =AS47/AR47-1 -> 0.19672131
B49: Net Adds | AN49: =AN47-AM47 -> 700 | AO49: =AO47-AN47 -> 800 | AQ49: =AQ47-AO47 -> 1200 | AR49: =AR47-AQ47 -> 900 | AS49: =AS47-AR47 -> 1200
A51: SERVREV | B51: Professional services revenue | H51: ='IS (Non-GAAP)'!H19 -> 0.217 | I51: ='IS (Non-GAAP)'!I19 -> 0.23 | J51: ='IS (Non-GAAP)'!J19 -> 0.223 | K51: ='IS (Non-GAAP)'!K19 -> 0.313 | L51: =SUM(H51:K51) -> 0.983 | M51: ='IS (Non-GAAP)'!M19 -> 0.939 | N51: ='IS (Non-GAAP)'!N19 -> 2.521 | O51: ='IS (Non-GAAP)'!O19 -> 3.799 | P51: ='IS (Non-GAAP)'!P19 -> 5.26 | Q51: =SUM(M51:P51) -> 12.519 | R51: ='IS (Non-GAAP)'!R19 -> 6.998 | S51: ='IS (Non-GAAP)'!S19 -> 7.929 | T51: ='IS (Non-GAAP)'!T19 -> 11.151 | U51: ='IS (Non-GAAP)'!U19 -> 12.177 | V51: =SUM(R51:U51) -> 38.255 | W51: ='IS (Non-GAAP)'!W19 -> 15.084 | X51: ='IS (Non-GAAP)'!X19 -> 17.575 | Y51: ='IS (Non-GAAP)'!Y19 -> 21.983 | Z51: ='IS (Non-GAAP)'!Z19 -> 24.216 | AA51: =SUM(W51:Z51) -> 78.858 | AB51: ='IS (Non-GAAP)'!AB19 -> 27.937 | AC51: ='IS (Non-GAAP)'!AC19 -> 30.98 | AD51: ='IS (Non-GAAP)'!AD19 -> 34.276 | AE51: ='IS (Non-GAAP)'!AE19 -> 33.683 | AF51: =SUM(AB51:AE51) -> 126.876 | AG51: ='IS (Non-GAAP)'!AG19 -> 33.527 | AH51: ='IS (Non-GAAP)'!AH19 -> 33.809 | AI51: ='IS (Non-GAAP)'!AI19 -> 35.695 | AJ51: ='IS (Non-GAAP)'!AJ19 -> 36.609 | AK51: =SUM(AG51:AJ51) -> 139.64 | AL51: ='IS (Non-GAAP)'!AL19 -> 39.122 | AM51: ='IS (Non-GAAP)'!AM19 -> 39.573 | AN51: ='IS (Non-GAAP)'!AN19 -> 41.812 | AO51: ='IS (Non-GAAP)'!AO19 -> 43.467 | AP51: =SUM(AL51:AO51) -> 163.974 | AQ51: ='IS (Non-GAAP)'!AQ19 -> 45.261 | AR51: ='IS (Non-GAAP)'!AR19 -> 54.473 | AS51: ='IS (Non-GAAP)'!AS19 -> 54.532 | AT51: =AO51*(1+AT52) -> 49.98705 | AU51: =SUM(AQ51:AT51) -> 204.25305 | AV51: =AQ51*(1+AV52) -> 51.371235 | AW51: =AR51*(1+AW52) -> 61.826855 | AX51: =AS51*(1+AX52) -> 61.89382 | AY51: =AT51*(1+AY52) -> 56.735302 | AZ51: =SUM(AV51:AY51) -> 231.82721 | BA51: =AV51*(1+BA52) -> 58.049496 | BB51: =AW51*(1+BB52) -> 69.864346 | BC51: =AX51*(1+BC52) -> 69.940017 | BD51: =AY51*(1+BD52) -> 64.110891 | BE51: =SUM(BA51:BD51) -> 261.96475 | BF51: =BA51*(1+BF52) -> 65.305682 | BG51: =BB51*(1+BG52) -> 78.597389 | BH51: =BC51*(1+BH52) -> 78.682519 | BI51: =BD51*(1+BI52) -> 72.124752 | BJ51: =SUM(BF51:BI51) -> 294.71034 | BK51: =BF51*(1+BK52) -> 73.468893 | BL51: =BG51*(1+BL52) -> 88.422063 | BM51: =BH51*(1+BM52) -> 88.517834 | BN51: =BI51*(1+BN52) -> 81.140346 | BO51: =SUM(BK51:BN51) -> 331.54914
A52: SERVREVYY | B52: % yoy | H52: =IFERROR(H51/C51-1,"--") -> -- | I52: =IFERROR(I51/D51-1,"--") -> -- | J52: =IFERROR(J51/E51-1,"--") -> -- | K52: =IFERROR(K51/F51-1,"--") -> -- | L52: =IFERROR(L51/G51-1,"--") -> -- | M52: =IFERROR(M51/H51-1,"--") -> 3.3271889 | N52: =IFERROR(N51/I51-1,"--") -> 9.9608696 | O52: =IFERROR(O51/J51-1,"--") -> 16.035874 | ... AS52: =IFERROR(AS51/AN51-1,"--") -> 0.30421888 | AT52: 0.15 | AU52: =IFERROR(AU51/AP51-1,"--") -> 0.24564291 | AV52: 0.135 | AW52: =AV52 -> 0.135 | AX52: =AW52 -> 0.135 | AY52: =AX52 -> 0.135 | AZ52: =IFERROR(AZ51/AU51-1,"--") -> 0.135 | BA52: 0.13 | BB52: =BA52 -> 0.13 | BC52: =BB52 -> 0.13 | BD52: =BC52 -> 0.13 | BE52: =IFERROR(BE51/AZ51-1,"--") -> 0.13 | BF52: 0.125 | BG52: =BF52 -> 0.125 | BH52: =BG52 -> 0.125 | BI52: =BH52 -> 0.125 | BJ52: =IFERROR(BJ51/BE51-1,"--") -> 0.125 | BK52: 0.125 | BL52: =BK52 -> 0.125 | BM52: =BL52 -> 0.125 | BN52: =BM52 -> 0.125 | BO52: =IFERROR(BO51/BJ51-1,"--") -> 0.125
A53: SERVREVQQ | B53: % qoq | H53: =IFERROR(H51/F51-1,"--") -> -- | I53: =IFERROR(I51/H51-1,"--") -> 0.059907834 | J53: =IFERROR(J51/I51-1,"--") -> -0.030434783 | K53: =IFERROR(K51/J51-1,"--") -> 0.40358744 | L53: -- | M53: =IFERROR(M51/K51-1,"--") -> 2 | N53: =IFERROR(N51/M51-1,"--") -> 1.684771 | O53: =IFERROR(O51/N51-1,"--") -> 0.50694169 | P53: =IFERROR(P51/O51-1,"--") -> 0.38457489 | Q53: -- | R53: =IFERROR(R51/P51-1,"--") -> 0.33041825 | S53: =IFERROR(S51/R51-1,"--") -> 0.13303801 | T53: =IFERROR(T51/S51-1,"--") -> 0.40635641 | U53: =IFERROR(U51/T51-1,"--") -> 0.092009685 | V53: -- | W53: =IFERROR(W51/U51-1,"--") -> 0.23872875 | X53: =IFERROR(X51/W51-1,"--") -> 0.16514187 | Y53: =IFERROR(Y51/X51-1,"--") -> 0.25081081 | Z53: =IFERROR(Z51/Y51-1,"--") -> 0.10157849 | AA53: -- | AB53: =IFERROR(AB51/Z51-1,"--") -> 0.15365874 | AC53: =IFERROR(AC51/AB51-1,"--") -> 0.10892365 | AD53: =IFERROR(AD51/AC51-1,"--") -> 0.10639122 | AE53: =IFERROR(AE51/AD51-1,"--") -> -0.017300735 | AF53: -- | AG53: =IFERROR(AG51/AE51-1,"--") -> -0.0046314164 | AH53: =IFERROR(AH51/AG51-1,"--") -> 0.0084111313 | AI53: =IFERROR(AI51/AH51-1,"--") -> 0.055783963 | AJ53: =IFERROR(AJ51/AI51-1,"--") -> 0.025605827 | AK53: -- | AL53: =IFERROR(AL51/AJ51-1,"--") -> 0.068644322 | AM53: =IFERROR(AM51/AL51-1,"--") -> 0.01152804 | AN53: =IFERROR(AN51/AM51-1,"--") -> 0.056578981 | AO53: =IFERROR(AO51/AN51-1,"--") -> 0.039581938 | AP53: -- | AQ53: =IFERROR(AQ51/AO51-1,"--") -> 0.04127269 | AR53: =IFERROR(AR51/AQ51-1,"--") -> 0.20353063 | AS53: =IFERROR(AS51/AR51-1,"--") -> 0.0010831054 | AT53: =IFERROR(AT51/AS51-1,"--") -> -0.083344642 | AU53: -- | AV53: =IFERROR(AV51/AT51-1,"--") -> 0.027690872 | AW53: =IFERROR(AW51/AV51-1,"--") -> 0.20353063 | AX53: =IFERROR(AX51/AW51-1,"--") -> 0.0010831054 | AY53: =IFERROR(AY51/AX51-1,"--") -> -0.083344642 | AZ53: -- | BA53: =IFERROR(BA51/AY51-1,"--") -> 0.023163599 | BB53: =IFERROR(BB51/BA51-1,"--") -> 0.20353063 | BC53: =IFERROR(BC51/BB51-1,"--") -> 0.0010831054 | BD53: =IFERROR(BD51/BC51-1,"--") -> -0.083344642 | BE53: -- | BF53: =IFERROR(BF51/BD51-1,"--") -> 0.018636327 | BG53: =IFERROR(BG51/BF51-1,"--") -> 0.20353063 | BH53: =IFERROR(BH51/BG51-1,"--") -> 0.0010831054 | BI53: =IFERROR(BI51/BH51-1,"--") -> -0.083344642 | BJ53: -- | BK53: =IFERROR(BK51/BI51-1,"--") -> 0.018636327 | BL53: =IFERROR(BL51/BK51-1,"--") -> 0.20353063 | BM53: =IFERROR(BM51/BL51-1,"--") -> 0.0010831054 | BN53: =IFERROR(BN51/BM51-1,"--") -> -0.083344642 | BO53: --
B54: % total revenue | H54: =H51/H$11 -> 0.016190405 | I54: =I51/I$11 -> 0.012845574 | J54: =J51/J$11 -> 0.0077754533 | K54: =K51/K$11 -> 0.0085337259 | L54: =L51/L$11 -> 0.010169036 | M54: =M51/M$11 -> 0.021484956 | N54: =N51/N$11 -> 0.041780606 | O54: =O51/O$11 -> 0.052032543 | ... BO54: =BO51/BO$11 -> 0.030322802
A55: CUST | B55: Total Customers | J55: 702 | K55: 948 | L55: =K55 -> 948 | M55: 1194 | N55: 1547 | O55: 1934 | P55: 2392 | Q55: =P55 -> 2392 | R55: 2720 | S55: 3117 | T55: 3554 | U55: 4139 | V55: =U55 -> 4139 | W55: 4532 | X55: 4990 | Y55: 5416 | Z55: 5944 | AA55: =Z55 -> 5944 | AB55: 6322 | AC55: 6823 | AD55: 7212 | AE55: 7776 | AF55: =AE55 -> 7776 | AG55: 8087 | AH55: 8487 | AI55: 8885 | AJ55: 9384 | AK55: =AJ55 -> 9384 | AL55: 9741 | AM55: 10147 | AN55: 10490 | AO55: 11023 | AP55: =AO55 -> 11023 | AQ55: 11473 | AR55: 12006 | AS55: 12621 | AT55: =AT82+AT68 -> 13198.791 | AU55: =AT55 -> 13198.791 | AV55: =AV82+AV68 -> 13692.83 | AW55: =AW82+AW68 -> 14268.396 | AX55: =AX82+AX68 -> 14946.757 | AY55: =AY82+AY68 -> 15576.27 | AZ55: =AY55 -> 15576.27 | BA55: =BA82+BA68 -> 16104.903 | BB55: =BB82+BB68 -> 16725.288 | BC55: =BC82+BC68 -> 17460.813 | BD55: =BD82+BD68 -> 18134.174 | BE55: =BD55 -> 18134.174 | BF55: =BF82+BF68 -> 18680.69 | BG55: =BG82+BG68 -> 19328.731 | BH55: =BH82+BH68 -> 20103.895 | BI55: =BI82+BI68 -> 20801.466 | BJ55: =BI55 -> 20801.466 | BK55: =BK82+BK68 -> 21348.306 | BL55: =BL82+BL68 -> 22005.934 | BM55: =BM82+BM68 -> 22802.451 | BN55: =BN82+BN68 -> 23484.936 | BO55: =BN55 -> 23484.936
A56: CUSTADD | B56: Net customer adds | K56: =K55-J55 -> 246 | L56: -- | M56: =M55-K55 -> 246 | N56: =N55-M55 -> 353 | O56: =O55-N55 -> 387 | P56: =P55-O55 -> 458 | Q56: =SUM(M56:P56) -> 1444 | R56: =R55-P55 -> 328 | S56: =S55-R55 -> 397 | T56: =T55-S55 -> 437 | U56: =U55-T55 -> 585 | V56: =SUM(R56:U56) -> 1747 | W56: =W55-U55 -> 393 | X56: =X55-W55 -> 458 | Y56: =Y55-X55 -> 426 | Z56: =Z55-Y55 -> 528 | AA56: =SUM(W56:Z56) -> 1805 | AB56: =AB55-Z55 -> 378 | AC56: =AC55-AB55 -> 501 | AD56: =AD55-AC55 -> 389 | AE56: =AE55-AD55 -> 564 | AF56: =SUM(AB56:AE56) -> 1832 | AG56: =AG55-AE55 -> 311 | AH56: =AH55-AG55 -> 400 | AI56: =AI55-AH55 -> 398 | AJ56: =AJ55-AI55 -> 499 | AK56: =SUM(AG56:AJ56) -> 1608 | AL56: =AL55-AJ55 -> 357 | AM56: =AM55-AL55 -> 406 | AN56: =AN55-AM55 -> 343 | AO56: =AO55-AN55 -> 533 | AP56: =SUM(AL56:AO56) -> 1639 | AQ56: =AQ55-AO55 -> 450 | AR56: =AR55-AQ55 -> 533 | AS56: =AS55-AR55 -> 615 | AT56: =AT55-AS55 -> 577.7913 | AU56: =SUM(AQ56:AT56) -> 2175.7913 | AV56: =AV55-AT55 -> 494.03876 | AW56: =AW55-AV55 -> 575.56575 | AX56: =AX55-AW55 -> 678.36147 | AY56: =AY55-AX55 -> 629.5132 | AZ56: =SUM(AV56:AY56) -> 2377.4792 | BA56: =BA55-AY55 -> 528.63217 | BB56: =BB55-BA55 -> 620.38573 | BC56: =BC55-BB55 -> 735.52466 | BD56: =BD55-BC55 -> 673.36129 | BE56: =SUM(BA56:BD56) -> 2557.9038 | BF56: =BF55-BD55 -> 546.5157 | BG56: =BG55-BF55 -> 648.04093 | BH56: =BH55-BG55 -> 775.16358 | BI56: =BI55-BH55 -> 697.57154 | BJ56: =SUM(BF56:BI56) -> 2667.2918 | BK56: =BK55-BI55 -> 546.84034 | BL56: =BL55-BK55 -> 657.62787 | BM56: =BM55-BL55 -> 796.51631 | BN56: =BN55-BM55 -> 682.48493 | BO56: =SUM(BK56:BN56) -> 2683.4695
A57: CUSTYY | B57: % yoy | J57: =IFERROR(J55/E55-1,"--") -> -- | K57: =IFERROR(K55/F55-1,"--") -> -- | L57: =IFERROR(L55/G55-1,"--") -> -- | M57: =IFERROR(M55/H55-1,"--") -> -- | N57: =IFERROR(N55/I55-1,"--") -> -- | O57: =IFERROR(O55/J55-1,"--") -> 1.7549858 | P57: =IFERROR(P55/K55-1,"--") -> 1.5232068 | Q57: =IFERROR(Q55/L55-1,"--") -> 1.5232068 | ... AE57: =IFERROR(AE55/Z55-1,"--") -> 0.30820996 | AF57: =AF55/AA55-1 -> 0.30820996 | AG57: =IFERROR(AG55/AB55-1,"--") -> 0.2791838 | AH57: =IFERROR(AH55/AC55-1,"--") -> 0.24388099 | AI57: =IFERROR(AI55/AD55-1,"--") -> 0.23197449 | AJ57: =IFERROR(AJ55/AE55-1,"--") -> 0.20679012 | AK57: =AK55/AF55-1 -> 0.20679012 | AL57: =IFERROR(AL55/AG55-1,"--") -> 0.20452578 | AM57: =IFERROR(AM55/AH55-1,"--") -> 0.19559326 | AN57: =IFERROR(AN55/AI55-1,"--") -> 0.18064153 | AO57: =IFERROR(AO55/AJ55-1,"--") -> 0.17465899 | AP57: =AP55/AK55-1 -> 0.17465899 | AQ57: =IFERROR(AQ55/AL55-1,"--") -> 0.17780515 | AR57: =IFERROR(AR55/AM55-1,"--") -> 0.18320686 | AS57: =IFERROR(AS55/AN55-1,"--") -> 0.20314585 | AT57: =IFERROR(AT55/AO55-1,"--") -> 0.19738649 | AU57: =AU55/AP55-1 -> 0.19738649 | AV57: =IFERROR(AV55/AQ55-1,"--") -> 0.19348297 | AW57: =IFERROR(AW55/AR55-1,"--") -> 0.18843877 | AX57: =IFERROR(AX55/AS55-1,"--") -> 0.18427678 | AY57: =IFERROR(AY55/AT55-1,"--") -> 0.18012855 | AZ57: =AZ55/AU55-1 -> 0.18012855 | BA57: =IFERROR(BA55/AV55-1,"--") -> 0.17615588 | BB57: =IFERROR(BB55/AW55-1,"--") -> 0.17219123 | BC57: =IFERROR(BC55/AX55-1,"--") -> 0.16820075 | BD57: =IFERROR(BD55/AY55-1,"--") -> 0.16421799 | BE57: =BE55/AZ55-1 -> 0.16421799 | BF57: =IFERROR(BF55/BA55-1,"--") -> 0.15993809 | BG57: =IFERROR(BG55/BB55-1,"--") -> 0.15565905 | BH57: =IFERROR(BH55/BC55-1,"--") -> 0.15137219 | BI57: =IFERROR(BI55/BD55-1,"--") -> 0.14708647 | BJ57: =BJ55/BE55-1 -> 0.14708647 | BK57: =IFERROR(BK55/BF55-1,"--") -> 0.14280074 | BL57: =IFERROR(BL55/BG55-1,"--") -> 0.13850901 | BM57: =IFERROR(BM55/BH55-1,"--") -> 0.13423051 | BN57: =IFERROR(BN55/BI55-1,"--") -> 0.12900386 | BO57: =BO55/BJ55-1 -> 0.12900386
A58: CUSTQQ | B58: % qoq | J58: =IFERROR(J55/I55-1,"--") -> -- | K58: =IFERROR(K55/J55-1,"--") -> 0.35042735 | L58: -- | M58: =IFERROR(M55/K55-1,"--") -> 0.25949367 | N58: =IFERROR(N55/M55-1,"--") -> 0.29564489 | O58: =IFERROR(O55/N55-1,"--") -> 0.2501616 | P58: =IFERROR(P55/O55-1,"--") -> 0.23681489 | Q58: -- | R58: =IFERROR(R55/P55-1,"--") -> 0.13712375 | S58: =IFERROR(S55/R55-1,"--") -> 0.14595588 | T58: =IFERROR(T55/S55-1,"--") -> 0.14019891 | U58: =IFERROR(U55/T55-1,"--") -> 0.16460326 | V58: -- | W58: =IFERROR(W55/U55-1,"--") -> 0.094950471 | X58: =IFERROR(X55/W55-1,"--") -> 0.10105914 | Y58: =IFERROR(Y55/X55-1,"--") -> 0.085370741 | Z58: =IFERROR(Z55/Y55-1,"--") -> 0.097488922 | AB58: =IFERROR(AB55/Z55-1,"--") -> 0.06359354 | AC58: =IFERROR(AC55/AB55-1,"--") -> 0.079247074 | AD58: =IFERROR(AD55/AC55-1,"--") -> 0.057013044 | AE58: =IFERROR(AE55/AD55-1,"--") -> 0.078202995 | AG58: =IFERROR(AG55/AE55-1,"--") -> 0.039994856 | AH58: =IFERROR(AH55/AG55-1,"--") -> 0.0494621 | AI58: =IFERROR(AI55/AH55-1,"--") -> 0.046895252 | AJ58: =IFERROR(AJ55/AI55-1,"--") -> 0.056162071 | AL58: =IFERROR(AL55/AJ55-1,"--") -> 0.038043478 | AM58: =IFERROR(AM55/AL55-1,"--") -> 0.041679499 | AN58: =IFERROR(AN55/AM55-1,"--") -> 0.033803095 | AO58: =IFERROR(AO55/AN55-1,"--") -> 0.050810296 | AQ58: =IFERROR(AQ55/AO55-1,"--") -> 0.040823732 | AR58: =IFERROR(AR55/AQ55-1,"--") -> 0.046456899 | AS58: =IFERROR(AS55/AR55-1,"--") -> 0.051224388 | AT58: =IFERROR(AT55/AS55-1,"--") -> 0.045780152 | AV58: =IFERROR(AV55/AT55-1,"--") -> 0.037430606 | AW58: =IFERROR(AW55/AV55-1,"--") -> 0.042034097 | AX58: =IFERROR(AX55/AW55-1,"--") -> 0.047542939 | AY58: =IFERROR(AY55/AX55-1,"--") -> 0.042117042 | BA58: =IFERROR(BA55/AY55-1,"--") -> 0.033938302 | BB58: =IFERROR(BB55/BA55-1,"--") -> 0.038521545 | BC58: =IFERROR(BC55/BB55-1,"--") -> 0.0439768 | BD58: =IFERROR(BD55/BC55-1,"--") -> 0.038564143 | BF58: =IFERROR(BF55/BD55-1,"--") -> 0.030137336 | BG58: =IFERROR(BG55/BF55-1,"--") -> 0.034690417 | BH58: =IFERROR(BH55/BG55-1,"--") -> 0.040104215 | BI58: =IFERROR(BI55/BH55-1,"--") -> 0.034698329 | BK58: =IFERROR(BK55/BI55-1,"--") -> 0.026288548 | BL58: =IFERROR(BL55/BK55-1,"--") -> 0.030804686 | BM58: =IFERROR(BM55/BL55-1,"--") -> 0.036195524 | BN58: =IFERROR(BN55/BM55-1,"--") -> 0.029930332
A60: ARPC | B60: Average product revenue per customer | K60: =(K15*10^6)/AVERAGE(K55,J55) -> 44078.788 | M60: =(M15*10^6)/AVERAGE(M55,L55) -> 39930.906 | N60: =(N15*10^6)/AVERAGE(N55,M55) -> 42187.523 | O60: =(O15*10^6)/AVERAGE(O55,N55) -> 39766.159 | P60: =(P15*10^6)/AVERAGE(P55,O55) -> 38110.032 | Q60: =(Q15*10^6)/AVERAGE(Q55,L55) -> 151035.33 | R60: =(R15*10^6)/AVERAGE(R55,Q55) -> 39834.507 | S60: =(S15*10^6)/AVERAGE(S55,R55) -> 42904.232 | T60: =(T15*10^6)/AVERAGE(T55,S55) -> 44512.967 | U60: =(U15*10^6)/AVERAGE(U55,T55) -> 46350.708 | V60: =(V15*10^6)/AVERAGE(V55,Q55) -> 169589.34 | W60: =(W15*10^6)/AVERAGE(W55,V55) -> 49320.724 | X60: =(X15*10^6)/AVERAGE(X55,W55) -> 53480.991 | Y60: =(Y15*10^6)/AVERAGE(Y55,X55) -> 60053.431 | Z60: =(Z15*10^6)/AVERAGE(Z55,Y55) -> 63302.465 | AA60: =(AA15*10^6)/AVERAGE(AA55,V55) -> 226216.21 | AB60: =(AB15*10^6)/AVERAGE(AB55,AA55) -> 64313.387 | AC60: =(AC15*10^6)/AVERAGE(AC55,AB55) -> 70942.259 | AD60: =(AD15*10^6)/AVERAGE(AD55,AC55) -> 74492.626 | AE60: =(AE15*10^6)/AVERAGE(AE55,AD55) -> 74103.149 | AF60: =(AF15*10^6)/AVERAGE(AF55,AA55) -> 282621.43 | AG60: =(AG15*10^6)/AVERAGE(AG55,AF55) -> 74396.016 | AH60: =(AH15*10^6)/AVERAGE(AH55,AG55) -> 77254.616 | AI60: =(AI15*10^6)/AVERAGE(AI55,AH55) -> 80414.23 | AJ60: =(AJ15*10^6)/AVERAGE(AJ55,AI55) -> 80802.452 | AK60: =(AK15*10^6)/AVERAGE(AK55,AF55) -> 310821.56 | AL60: =(AL15*10^6)/AVERAGE(AL55,AK55) -> 82571.19 | AM60: =(AM15*10^6)/AVERAGE(AM55,AL55) -> 83391.995 | AN60: =(AN15*10^6)/AVERAGE(AN55,AM55) -> 87249.309 | AO60: =(AO15*10^6)/AVERAGE(AO55,AN55) -> 87696.091 | AP60: =(AP15*10^6)/AVERAGE(AP55,AK55) -> 339336.7 | AQ60: =(AQ15*10^6)/AVERAGE(AQ55,AP55) -> 88621.355 | AR60: =(AR15*10^6)/AVERAGE(AR55,AQ55) -> 92891.179 | AS60: =(AS15*10^6)/AVERAGE(AS55,AR55) -> 94073.74 | AT60: =(AT15*10^6)/AVERAGE(AT55,AS55) -> 92860.24 | AU60: =(AU15*10^6)/AVERAGE(AU55,AP55) -> 366983.76 | AV60: =(AV15*10^6)/AVERAGE(AV55,AU55) -> 93831.437 | AW60: =(AW15*10^6)/AVERAGE(AW55,AV55) -> 96791.791 | AX60: =(AX15*10^6)/AVERAGE(AX55,AW55) -> 98607.767 | AY60: =(AY15*10^6)/AVERAGE(AY55,AX55) -> 97794.482 | AZ60: =(AZ15*10^6)/AVERAGE(AZ55,AU55) -> 385595.05 | BA60: =(BA15*10^6)/AVERAGE(BA55,AZ55) -> 99188.614 | BB60: =(BB15*10^6)/AVERAGE(BB55,BA55) -> 103012.11 | BC60: =(BC15*10^6)/AVERAGE(BC55,BB55) -> 105575.15 | BD60: =(BD15*10^6)/AVERAGE(BD55,BC55) -> 103925.9 | BE60: =(BE15*10^6)/AVERAGE(BE55,AZ55) -> 410340.55 | BF60: =(BF15*10^6)/AVERAGE(BF55,BE55) -> 104914.39 | BG60: =(BG15*10^6)/AVERAGE(BG55,BF55) -> 109137.71 | BH60: =(BH15*10^6)/AVERAGE(BH55,BG55) -> 114325.54 | BI60: =(BI15*10^6)/AVERAGE(BI55,BH55) -> 113426.02 | BJ60: =(BJ15*10^6)/AVERAGE(BJ55,BE55) -> 440690.29 | BK60: =(BK15*10^6)/AVERAGE(BK55,BJ55) -> 114299.56 | BL60: =(BL15*10^6)/AVERAGE(BL55,BK55) -> 117834.7 | BM60: =(BM15*10^6)/AVERAGE(BM55,BL55) -> 124735.52 | BN60: =(BN15*10^6)/AVERAGE(BN55,BM55) -> 122913.5 | BO60: =(BO15*10^6)/AVERAGE(BO55,BJ55) -> 478812.36
A61: ARPCYY | B61: % yoy | K61: =IFERROR(K60/F60-1,"--") -> -- | M61: =IFERROR(M60/H60-1,"--") -> -- | N61: =IFERROR(N60/I60-1,"--") -> -- | O61: =IFERROR(O60/J60-1,"--") -> -- | P61: =IFERROR(P60/K60-1,"--") -> -0.13541106 | Q61: =IFERROR(Q60/L60-1,"--") -> -- | R61: =IFERROR(R60/M60-1,"--") -> -0.0024141364 | S61: =IFERROR(S60/N60-1,"--") -> 0.016988644 | T61: =IFERROR(T60/O60-1,"--") -> 0.11936801 | ... BO61: =IFERROR(BO60/BJ60-1,"--") -> 0.086505368
A62: APRCQQ | B62: % qoq | K62: =IFERROR(K60/J60-1,"--") -> -- | M62: =IFERROR(M60/K60-1,"--") -> -0.094101548 | N62: =IFERROR(N60/M60-1,"--") -> 0.056513046 | O62: =IFERROR(O60/N60-1,"--") -> -0.057395256 | P62: =IFERROR(P60/O60-1,"--") -> -0.041646637 | Q62: -- | R62: =IFERROR(R60/P60-1,"--") -> 0.045249888 | S62: =IFERROR(S60/R60-1,"--") -> 0.077061945 | T62: =IFERROR(T60/S60-1,"--") -> 0.037495951 | U62: =IFERROR(U60/T60-1,"--") -> 0.04128554 | V62: -- | W62: =IFERROR(W60/U60-1,"--") -> 0.064077032 | X62: =IFERROR(X60/W60-1,"--") -> 0.084351299 | Y62: =IFERROR(Y60/X60-1,"--") -> 0.122893 | Z62: =IFERROR(Z60/Y60-1,"--") -> 0.054102389 | AA62: -- | AB62: =IFERROR(AB60/Z60-1,"--") -> 0.015969707 | AC62: =IFERROR(AC60/AB60-1,"--") -> 0.10307143 | AD62: =IFERROR(AD60/AC60-1,"--") -> 0.050045857 | AE62: =IFERROR(AE60/AD60-1,"--") -> -0.0052283886 | AF62: -- | AG62: =IFERROR(AG60/AE60-1,"--") -> 0.0039521492 | AH62: =IFERROR(AH60/AG60-1,"--") -> 0.038424098 | AI62: =IFERROR(AI60/AH60-1,"--") -> 0.04089871 | AJ62: =IFERROR(AJ60/AI60-1,"--") -> 0.0048277829 | AK62: -- | AL62: =IFERROR(AL60/AJ60-1,"--") -> 0.021889649 | AM62: =IFERROR(AM60/AL60-1,"--") -> 0.0099405814 | AN62: =IFERROR(AN60/AM60-1,"--") -> 0.046255211 | AO62: =IFERROR(AO60/AN60-1,"--") -> 0.0051207425 | AP62: -- | AQ62: =IFERROR(AQ60/AO60-1,"--") -> 0.010550803 | AR62: =IFERROR(AR60/AQ60-1,"--") -> 0.048180537 | AS62: =IFERROR(AS60/AR60-1,"--") -> 0.012730604 | AT62: =IFERROR(AT60/AS60-1,"--") -> -0.012899459 | AU62: -- | AV62: =IFERROR(AV60/AT60-1,"--") -> 0.010458697 | AW62: =IFERROR(AW60/AV60-1,"--") -> 0.031549704 | AX62: =IFERROR(AX60/AW60-1,"--") -> 0.018761674 | AY62: =IFERROR(AY60/AX60-1,"--") -> -0.0082476748 | AZ62: -- | BA62: =IFERROR(BA60/AY60-1,"--") -> 0.014255733 | BB62: =IFERROR(BB60/BA60-1,"--") -> 0.038547697 | BC62: =IFERROR(BC60/BB60-1,"--") -> 0.024880955 | BD62: =IFERROR(BD60/BC60-1,"--") -> -0.015621584 | BE62: -- | BF62: =IFERROR(BF60/BD60-1,"--") -> 0.0095115233 | BG62: =IFERROR(BG60/BF60-1,"--") -> 0.040254933 | BH62: =IFERROR(BH60/BG60-1,"--") -> 0.047534681 | BI62: =IFERROR(BI60/BH60-1,"--") -> -0.0078680436 | BJ62: -- | BK62: =IFERROR(BK60/BI60-1,"--") -> 0.0077014361 | BL62: =IFERROR(BL60/BK60-1,"--") -> 0.030928667 | BM62: =IFERROR(BM60/BL60-1,"--") -> 0.058563645 | BN62: =IFERROR(BN60/BM60-1,"--") -> -0.014607062 | BO62: --
A64: APREVPC | B64: Average product revenue per customer (annualized) | M64: =(M15*10^6*4)/AVERAGE(M55,L55) -> 159723.62 | N64: =(N15*10^6*4)/AVERAGE(N55,M55) -> 168750.09 | O64: =(O15*10^6*4)/AVERAGE(O55,N55) -> 159064.64 | P64: =(P15*10^6*4)/AVERAGE(P55,O55) -> 152440.13 | Q64: =(Q15*10^6)/AVERAGE(Q55,L55) -> 151035.33 | R64: =(R15*10^6*4)/AVERAGE(R55,Q55) -> 159338.03 | S64: =(S15*10^6*4)/AVERAGE(S55,R55) -> 171616.93 | T64: =(T15*10^6*4)/AVERAGE(T55,S55) -> 178051.87 | U64: =(U15*10^6*4)/AVERAGE(U55,T55) -> 185402.83 | V64: =(V15*10^6)/AVERAGE(V55,Q55) -> 169589.34 | W64: =(W15*10^6*4)/AVERAGE(W55,V55) -> 197282.9 | X64: =(X15*10^6*4)/AVERAGE(X55,W55) -> 213923.97 | Y64: =(Y15*10^6*4)/AVERAGE(Y55,X55) -> 240213.72 | Z64: =(Z15*10^6*4)/AVERAGE(Z55,Y55) -> 253209.86 | AA64: =(AA15*10^6)/AVERAGE(AA55,V55) -> 226216.21 | AB64: =(AB15*10^6*4)/AVERAGE(AB55,AA55) -> 257253.55 | AC64: =(AC15*10^6*4)/AVERAGE(AC55,AB55) -> 283769.04 | AD64: =(AD15*10^6*4)/AVERAGE(AD55,AC55) -> 297970.5 | AE64: =(AE15*10^6*4)/AVERAGE(AE55,AD55) -> 296412.6 | AF64: =(AF15*10^6)/AVERAGE(AF55,AA55) -> 282621.43 | AG64: =(AG15*10^6*4)/AVERAGE(AG55,AF55) -> 297584.06 | AH64: =(AH15*10^6*4)/AVERAGE(AH55,AG55) -> 309018.46 | AI64: =(AI15*10^6*4)/AVERAGE(AI55,AH55) -> 321656.92 | AJ64: =(AJ15*10^6*4)/AVERAGE(AJ55,AI55) -> 323209.81 | AK64: =(AK15*10^6)/AVERAGE(AK55,AF55) -> 310821.56 | AL64: =(AL15*10^6*4)/AVERAGE(AL55,AK55) -> 330284.76 | AM64: =(AM15*10^6*4)/AVERAGE(AM55,AL55) -> 333567.98 | AN64: =(AN15*10^6*4)/AVERAGE(AN55,AM55) -> 348997.24 | AO64: =(AO15*10^6*4)/AVERAGE(AO55,AN55) -> 350784.36 | AP64: =(AP15*10^6)/AVERAGE(AP55,AK55) -> 339336.7 | AQ64: =(AQ15*10^6*4)/AVERAGE(AQ55,AP55) -> 354485.42 | AR64: =(AR15*10^6*4)/AVERAGE(AR55,AQ55) -> 371564.72 | AS64: =(AS15*10^6*4)/AVERAGE(AS55,AR55) -> 376294.96 | AT64: =(AT15*10^6*4)/AVERAGE(AT55,AS55) -> 371440.96 | AU64: =(AU15*10^6)/AVERAGE(AU55,AP55) -> 366983.76 | AV64: =(AV15*10^6*4)/AVERAGE(AV55,AU55) -> 375325.75 | AW64: =(AW15*10^6*4)/AVERAGE(AW55,AV55) -> 387167.16 | AX64: =(AX15*10^6*4)/AVERAGE(AX55,AW55) -> 394431.07 | AY64: =(AY15*10^6*4)/AVERAGE(AY55,AX55) -> 391177.93 | AZ64: =(AZ15*10^6)/AVERAGE(AZ55,AU55) -> 385595.05 | BA64: =(BA15*10^6*4)/AVERAGE(BA55,AZ55) -> 396754.46 | BB64: =(BB15*10^6*4)/AVERAGE(BB55,BA55) -> 412048.43 | BC64: =(BC15*10^6*4)/AVERAGE(BC55,BB55) -> 422300.59 | BD64: =(BD15*10^6*4)/AVERAGE(BD55,BC55) -> 415703.58 | BE64: =(BE15*10^6)/AVERAGE(BE55,AZ55) -> 410340.55 | BF64: =(BF15*10^6*4)/AVERAGE(BF55,BE55) -> 419657.56 | BG64: =(BG15*10^6*4)/AVERAGE(BG55,BF55) -> 436550.84 | BH64: =(BH15*10^6*4)/AVERAGE(BH55,BG55) -> 457302.15 | BI64: =(BI15*10^6*4)/AVERAGE(BI55,BH55) -> 453704.07 | BJ64: =(BJ15*10^6)/AVERAGE(BJ55,BE55) -> 440690.29 | BK64: =(BK15*10^6*4)/AVERAGE(BK55,BJ55) -> 457198.25 | BL64: =(BL15*10^6*4)/AVERAGE(BL55,BK55) -> 471338.78 | BM64: =(BM15*10^6*4)/AVERAGE(BM55,BL55) -> 498942.1 | BN64: =(BN15*10^6*4)/AVERAGE(BN55,BM55) -> 491654.02 | BO64: =(BO15*10^6)/AVERAGE(BO55,BJ55) -> 478812.36
A65: APREVPCYY | B65: % yoy | M65: =IFERROR(M64/H64-1,"--") -> -- | N65: =IFERROR(N64/I64-1,"--") -> -- | O65: =IFERROR(O64/J64-1,"--") -> -- | P65: =IFERROR(P64/K64-1,"--") -> -- | Q65: =IFERROR(Q64/L64-1,"--") -> -- | R65: =IFERROR(R64/M64-1,"--") -> -0.0024141364 | S65: =IFERROR(S64/N64-1,"--") -> 0.016988644 | T65: =IFERROR(T64/O64-1,"--") -> 0.11936801 | ... BO65: =IFERROR(BO64/BJ64-1,"--") -> 0.086505368
A66: APREVPCQQ | B66: % qoq | M66: =IFERROR(M64/K64-1,"--") -> -- | N66: =IFERROR(N64/M64-1,"--") -> 0.056513046 | O66: =IFERROR(O64/N64-1,"--") -> -0.057395256 | P66: =IFERROR(P64/O64-1,"--") -> -0.041646637 | Q66: -- | R66: =IFERROR(R64/P64-1,"--") -> 0.045249888 | S66: =IFERROR(S64/R64-1,"--") -> 0.077061945 | T66: =IFERROR(T64/S64-1,"--") -> 0.037495951 | U66: =IFERROR(U64/T64-1,"--") -> 0.04128554 | V66: -- | W66: =IFERROR(W64/U64-1,"--") -> 0.064077032 | X66: =IFERROR(X64/W64-1,"--") -> 0.084351299 | Y66: =IFERROR(Y64/X64-1,"--") -> 0.122893 | Z66: =IFERROR(Z64/Y64-1,"--") -> 0.054102389 | AA66: -- | AB66: =IFERROR(AB64/Z64-1,"--") -> 0.015969707 | AC66: =IFERROR(AC64/AB64-1,"--") -> 0.10307143 | AD66: =IFERROR(AD64/AC64-1,"--") -> 0.050045857 | AE66: =IFERROR(AE64/AD64-1,"--") -> -0.0052283886 | AF66: -- | AG66: =IFERROR(AG64/AE64-1,"--") -> 0.0039521492 | AH66: =IFERROR(AH64/AG64-1,"--") -> 0.038424098 | AI66: =IFERROR(AI64/AH64-1,"--") -> 0.04089871 | AJ66: =IFERROR(AJ64/AI64-1,"--") -> 0.0048277829 | AK66: -- | AL66: =IFERROR(AL64/AJ64-1,"--") -> 0.021889649 | AM66: =IFERROR(AM64/AL64-1,"--") -> 0.0099405814 | AN66: =IFERROR(AN64/AM64-1,"--") -> 0.046255211 | AO66: =IFERROR(AO64/AN64-1,"--") -> 0.0051207425 | AP66: -- | AQ66: =IFERROR(AQ64/AO64-1,"--") -> 0.010550803 | AR66: =IFERROR(AR64/AQ64-1,"--") -> 0.048180537 | AS66: =IFERROR(AS64/AR64-1,"--") -> 0.012730604 | AT66: =IFERROR(AT64/AS64-1,"--") -> -0.012899459 | AU66: -- | AV66: =IFERROR(AV64/AT64-1,"--") -> 0.010458697 | AW66: =IFERROR(AW64/AV64-1,"--") -> 0.031549704 | AX66: =IFERROR(AX64/AW64-1,"--") -> 0.018761674 | AY66: =IFERROR(AY64/AX64-1,"--") -> -0.0082476748 | AZ66: -- | BA66: =IFERROR(BA64/AY64-1,"--") -> 0.014255733 | BB66: =IFERROR(BB64/BA64-1,"--") -> 0.038547697 | BC66: =IFERROR(BC64/BB64-1,"--") -> 0.024880955 | BD66: =IFERROR(BD64/BC64-1,"--") -> -0.015621584 | BE66: -- | BF66: =IFERROR(BF64/BD64-1,"--") -> 0.0095115233 | BG66: =IFERROR(BG64/BF64-1,"--") -> 0.040254933 | BH66: =IFERROR(BH64/BG64-1,"--") -> 0.047534681 | BI66: =IFERROR(BI64/BH64-1,"--") -> -0.0078680436 | BJ66: -- | BK66: =IFERROR(BK64/BI64-1,"--") -> 0.0077014361 | BL66: =IFERROR(BL64/BK64-1,"--") -> 0.030928667 | BM66: =IFERROR(BM64/BL64-1,"--") -> 0.058563645 | BN66: =IFERROR(BN64/BM64-1,"--") -> -0.014607062 | BO66: --
A68: MNCUST | B68: Customers >$1mn in Revenue | J68: 14 | K68: 14 | L68: =K68 -> 14 | M68: 16 | N68: 22 | O68: 31 | P68: 41 | Q68: =P68 -> 41 | R68: 48 | S68: 56 | T68: 65 | U68: 77 | V68: =U68 -> 77 | W68: 104 | X68: 116 | Y68: 148 | Z68: 184 | AA68: =Z68 -> 184 | AB68: 206 | AC68: 248 | AD68: 287 | AE68: 330 | AF68: =AE68 -> 330 | AG68: 373 | AH68: 401 | AI68: 436 | AJ68: 455 | AK68: =AJ68 -> 455 | AL68: 479 | AM68: 507 | AN68: 540 | AO68: 579 | AP68: =AO68 -> 579 | AQ68: 606 | AR68: 654 | AS68: 688 | AT68: =AO68*(1+AT70) -> 725.55884 | AU68: =AT68 -> 725.55884 | AV68: =AQ68*(1+AV70) -> 757.87819 | AW68: =AR68*(1+AW70) -> 801.55814 | AX68: =AS68*(1+AX70) -> 838.41336 | AY68: =AT68*(1+AY70) -> 879.10456 | AZ68: =AY68 -> 879.10456 | BA68: =AV68*(1+BA70) -> 912.20043 | BB68: =AW68*(1+BB70) -> 958.36221 | BC68: =AX68*(1+BC70) -> 995.71989 | BD68: =AY68*(1+BD70) -> 1037.0129 | BE68: =BD68 -> 1037.0129 | BF68: =BA68*(1+BF70) -> 1067.8438 | BG68: =BB68*(1+BG70) -> 1113.2566 | BH68: =BC68*(1+BH70) -> 1147.6907 | BI68: =BD68*(1+BI70) -> 1185.9529 | BJ68: =BI68 -> 1185.9529 | BK68: =BF68*(1+BK70) -> 1211.6013 | BL68: =BG68*(1+BL70) -> 1253.1085 | BM68: =BH68*(1+BM70) -> 1281.5391 | BN68: =BI68*(1+BN70) -> 1313.59 | BO68: =BN68 -> 1313.59
A69: MNCUSTADD | B69: Net customer adds | K69: =K68-J68 -> 0 | M69: =M68-K68 -> 2 | N69: =N68-M68 -> 6 | O69: =O68-N68 -> 9 | P69: =P68-O68 -> 10 | Q69: =SUM(M69:P69) -> 27 | R69: =R68-P68 -> 7 | S69: =S68-R68 -> 8 | T69: =T68-S68 -> 9 | U69: =U68-T68 -> 12 | V69: =V68-Q68 -> 36 | W69: =W68-U68 -> 27 | X69: =X68-W68 -> 12 | Y69: =Y68-X68 -> 32 | Z69: =Z68-Y68 -> 36 | AA69: =AA68-V68 -> 107 | AB69: =AB68-Z68 -> 22 | AC69: =AC68-AB68 -> 42 | AD69: =AD68-AC68 -> 39 | AE69: =AE68-AD68 -> 43 | AF69: =AF68-AA68 -> 146 | AG69: =AG68-AE68 -> 43 | AH69: =AH68-AG68 -> 28 | AI69: =AI68-AH68 -> 35 | AJ69: =AJ68-AI68 -> 19 | AK69: =AK68-AF68 -> 125 | AL69: =AL68-AJ68 -> 24 | AM69: =AM68-AL68 -> 28 | AN69: =AN68-AM68 -> 33 | AO69: =AO68-AN68 -> 39 | AP69: =AP68-AK68 -> 124 | AQ69: =AQ68-AO68 -> 27 | AR69: =AR68-AQ68 -> 48 | AS69: =AS68-AR68 -> 34 | AT69: =AT68-AS68 -> 37.558839 | AU69: =AU68-AP68 -> 146.55884 | AV69: =AV68-AU68 -> 32.31935 | AW69: =AW68-AV68 -> 43.679956 | AX69: =AX68-AW68 -> 36.855219 | AY69: =AY68-AX68 -> 40.691193 | AZ69: =AZ68-AU68 -> 153.54572 | BA69: =BA68-AZ68 -> 33.095877 | BB69: =BB68-BA68 -> 46.161781 | BC69: =BC68-BB68 -> 37.35768 | BD69: =BD68-BC68 -> 41.293004 | BE69: =BE68-AZ68 -> 157.90834 | BF69: =BF68-BE68 -> 30.830889 | BG69: =BG68-BF68 -> 45.412832 | BH69: =BH68-BG68 -> 34.434101 | BI69: =BI68-BH68 -> 38.262195 | BJ69: =BJ68-BE68 -> 148.94002 | BK69: =BK68-BJ68 -> 25.648353 | BL69: =BL68-BK68 -> 41.507183 | BM69: =BM68-BL68 -> 28.430637 | BN69: =BN68-BM68 -> 32.050912 | BO69: =BO68-BJ68 -> 127.63708
A70: MNCUSTYY | B70: % yoy | J70: =IFERROR(J68/E68-1,"--") -> -- | K70: =IFERROR(K68/F68-1,"--") -> -- | L70: =IFERROR(L68/G68-1,"--") -> -- | M70: =IFERROR(M68/H68-1,"--") -> -- | N70: =IFERROR(N68/I68-1,"--") -> -- | O70: =IFERROR(O68/J68-1,"--") -> 1.2142857 | P70: =IFERROR(P68/K68-1,"--") -> 1.9285714 | Q70: =IFERROR(Q68/L68-1,"--") -> 1.9285714 | ... AS70: =IFERROR(AS68/AN68-1,"--") -> 0.27407407 | AT70: =AS70+AT73 -> 0.25312407 | AU70: =IFERROR(AU68/AP68-1,"--") -> 0.25312407 | AV70: =AT70+AV73 -> 0.25062407 | AW70: =AV70+AW73 -> 0.22562407 | AX70: =AW70+AX73 -> 0.21862407 | AY70: =AX70+AY73 -> 0.21162407 | AZ70: =IFERROR(AZ68/AU68-1,"--") -> 0.21162407 | BA70: =AY70+BA73 -> 0.20362407 | BB70: =BA70+BB73 -> 0.19562407 | BC70: =BB70+BC73 -> 0.18762407 | BD70: =BC70+BD73 -> 0.17962407 | BE70: =IFERROR(BE68/AZ68-1,"--") -> 0.17962407 | BF70: =BD70+BF73 -> 0.17062407 | BG70: =BF70+BG73 -> 0.16162407 | BH70: =BG70+BH73 -> 0.15262407 | BI70: =BH70+BI73 -> 0.14362407 | BJ70: =IFERROR(BJ68/BE68-1,"--") -> 0.14362407 | BK70: =BI70+BK73 -> 0.13462407 | BL70: =BK70+BL73 -> 0.12562407 | BM70: =BL70+BM73 -> 0.11662407 | BN70: =BM70+BN73 -> 0.10762407 | BO70: =IFERROR(BO68/BJ68-1,"--") -> 0.10762407
A71: MNCUSTQQ | B71: % qoq | J71: =IFERROR(J68/I68-1,"--") -> -- | K71: =IFERROR(K68/J68-1,"--") -> 0 | L71: -- | M71: =IFERROR(M68/K68-1,"--") -> 0.14285714 | N71: =IFERROR(N68/M68-1,"--") -> 0.375 | O71: =IFERROR(O68/N68-1,"--") -> 0.40909091 | P71: =IFERROR(P68/O68-1,"--") -> 0.32258065 | Q71: -- | R71: =IFERROR(R68/P68-1,"--") -> 0.17073171 | S71: =IFERROR(S68/R68-1,"--") -> 0.16666667 | T71: =IFERROR(T68/S68-1,"--") -> 0.16071429 | U71: =IFERROR(U68/T68-1,"--") -> 0.18461538 | V71: -- | W71: =IFERROR(W68/U68-1,"--") -> 0.35064935 | X71: =IFERROR(X68/W68-1,"--") -> 0.11538462 | Y71: =IFERROR(Y68/X68-1,"--") -> 0.27586207 | Z71: =IFERROR(Z68/Y68-1,"--") -> 0.24324324 | AA71: -- | AB71: =IFERROR(AB68/Z68-1,"--") -> 0.11956522 | AC71: =IFERROR(AC68/AB68-1,"--") -> 0.2038835 | AD71: =IFERROR(AD68/AC68-1,"--") -> 0.15725806 | AE71: =IFERROR(AE68/AD68-1,"--") -> 0.14982578 | AF71: -- | AG71: =IFERROR(AG68/AE68-1,"--") -> 0.13030303 | AH71: =IFERROR(AH68/AG68-1,"--") -> 0.075067024 | AI71: =IFERROR(AI68/AH68-1,"--") -> 0.087281796 | AJ71: =IFERROR(AJ68/AI68-1,"--") -> 0.043577982 | AK71: -- | AL71: =IFERROR(AL68/AJ68-1,"--") -> 0.052747253 | AM71: =IFERROR(AM68/AL68-1,"--") -> 0.058455115 | AN71: =IFERROR(AN68/AM68-1,"--") -> 0.065088757 | AO71: =IFERROR(AO68/AN68-1,"--") -> 0.072222222 | AP71: -- | AQ71: =IFERROR(AQ68/AO68-1,"--") -> 0.046632124 | AR71: =IFERROR(AR68/AQ68-1,"--") -> 0.079207921 | AS71: =IFERROR(AS68/AR68-1,"--") -> 0.051987768 | AT71: =IFERROR(AT68/AS68-1,"--") -> 0.054591336 | AU71: -- | AV71: =IFERROR(AV68/AU68-1,"--") -> 0.044544079 | AW71: =IFERROR(AW68/AV68-1,"--") -> 0.057634533 | AX71: =IFERROR(AX68/AW68-1,"--") -> 0.04597947 | AY71: =IFERROR(AY68/AX68-1,"--") -> 0.04853357 | AZ71: -- | BA71: =IFERROR(BA68/AZ68-1,"--") -> 0.037647259 | BB71: =IFERROR(BB68/BA68-1,"--") -> 0.050604866 | BC71: =IFERROR(BC68/BB68-1,"--") -> 0.038980752 | BD71: =IFERROR(BD68/BC68-1,"--") -> 0.041470503 | BE71: -- | BF71: =IFERROR(BF68/BE68-1,"--") -> 0.029730478 | BG71: =IFERROR(BG68/BF68-1,"--") -> 0.042527599 | BH71: =IFERROR(BH68/BG68-1,"--") -> 0.030930964 | BI71: =IFERROR(BI68/BH68-1,"--") -> 0.03333842 | BJ71: -- | BK71: =IFERROR(BK68/BJ68-1,"--") -> 0.021626789 | BL71: =IFERROR(BL68/BK68-1,"--") -> 0.034258121 | BM71: =IFERROR(BM68/BL68-1,"--") -> 0.022688089 | BN71: =IFERROR(BN68/BM68-1,"--") -> 0.025009703 | BO71: --
B72: % total customers | K72: =K68/K$55 -> 0.014767932 | M72: =M68/M$55 -> 0.013400335 | N72: =N68/N$55 -> 0.014221073 | O72: =O68/O$55 -> 0.016028956 | P72: =P68/P$55 -> 0.017140468 | Q72: =Q68/Q$55 -> 0.017140468 | R72: =R68/R$55 -> 0.017647059 | S72: =S68/S$55 -> 0.017965993 | T72: =T68/T$55 -> 0.018289252 | ... BO72: =BO68/BO$55 -> 0.055933302
B73: Implied Q/Q Deceleration | R73: =R70-P70 -> 0.071428571 | S73: =S70-R70 -> -0.45454545 | T73: =T70-S70 -> -0.44868035 | U73: =U70-T70 -> -0.21872541 | V73: =AVERAGE(R73:U73) -> -0.26263066 | W73: =W70-U70 -> 0.28861789 | X73: =X70-W70 -> -0.095238095 | Y73: =Y70-X70 -> 0.20549451 | Z73: =Z70-Y70 -> 0.11268731 | AA73: =AVERAGE(W73:Z73) -> 0.1278904 | AB73: =AB70-Z70 -> -0.40884116 | AC73: =AC70-AB70 -> 0.1571618 | AD73: =AD70-AC70 -> -0.19874185 | AE73: =AE70-AD70 -> -0.14571093 | AF73: =AVERAGE(AB73:AE73) -> -0.14903303 | AG73: =AG70-AE70 -> 0.017201351 | AH73: =AH70-AG70 -> -0.19374413 | AI73: =AI70-AH70 -> -0.097771721 | AJ73: =AJ70-AI70 -> -0.14037588 | AK73: =AVERAGE(AG73:AJ73) -> -0.1036726 | AL73: =AL70-AJ70 -> -0.094605573 | AM73: =AM70-AL70 -> -0.019843154 | AN73: =AN70-AM70 -> -0.025807042 | AO73: =AO70-AN70 -> 0.033995362 | AP73: =AVERAGE(AL73:AO73) -> -0.026565102 | AQ73: =AQ70-AO70 -> -0.0073917732 | AR73: =AR70-AQ70 -> 0.024805129 | AS73: =AS70-AR70 -> -0.015866754 | AT73: -0.02095 | AU73: =AVERAGE(AQ73:AT73) -> -0.0048508496 | AV73: -0.0025 | AW73: -0.025 | AX73: -0.007 | AY73: -0.007 | AZ73: =AVERAGE(AV73:AY73) -> -0.010375 | BA73: -0.008 | BB73: =BA73 -> -0.008 | BC73: =BB73 -> -0.008 | BD73: =BC73 -> -0.008 | BE73: =AVERAGE(BA73:BD73) -> -0.008 | BF73: -0.009 | BG73: =BF73 -> -0.009 | BH73: =BG73 -> -0.009 | BI73: =BH73 -> -0.009 | BJ73: =AVERAGE(BF73:BI73) -> -0.009 | BK73: -0.009 | BL73: =BK73 -> -0.009 | BM73: =BL73 -> -0.009 | BN73: =BM73 -> -0.009 | BO73: =AVERAGE(BK73:BN73) -> -0.009
B74: % Seasonality | M74: =IFERROR(M69/Q69,"--") -> 0.074074074 | N74: =IFERROR(N69/Q69,"--") -> 0.22222222 | O74: =IFERROR(O69/Q69,"--") -> 0.33333333 | P74: =IFERROR(P69/Q69,"--") -> 0.37037037 | R74: =IFERROR(R69/V69,"--") -> 0.19444444 | S74: =IFERROR(S69/V69,"--") -> 0.22222222 | T74: =IFERROR(T69/V69,"--") -> 0.25 | U74: =IFERROR(U69/V69,"--") -> 0.33333333 | W74: =IFERROR(W69/AA69,"--") -> 0.25233645 | X74: =IFERROR(X69/AA69,"--") -> 0.11214953 | Y74: =IFERROR(Y69/AA69,"--") -> 0.29906542 | Z74: =IFERROR(Z69/AA69,"--") -> 0.3364486 | AB74: =IFERROR(AB69/AF69,"--") -> 0.15068493 | AC74: =IFERROR(AC69/AF69,"--") -> 0.28767123 | AD74: =IFERROR(AD69/AF69,"--") -> 0.26712329 | AE74: =IFERROR(AE69/AF69,"--") -> 0.29452055 | AG74: =IFERROR(AG69/AK69,"--") -> 0.344 | AH74: =IFERROR(AH69/AK69,"--") -> 0.224 | AI74: =IFERROR(AI69/AK69,"--") -> 0.28 | AJ74: =IFERROR(AJ69/AK69,"--") -> 0.152 | AL74: =IFERROR(AL69/AP69,"--") -> 0.19354839 | AM74: =IFERROR(AM69/AP69,"--") -> 0.22580645 | AN74: =IFERROR(AN69/AP69,"--") -> 0.26612903 | AO74: =IFERROR(AO69/AP69,"--") -> 0.31451613 | AQ74: =IFERROR(AQ69/AU69,"--") -> 0.18422635 | AR74: =IFERROR(AR69/AU69,"--") -> 0.32751351 | AS74: =IFERROR(AS69/AU69,"--") -> 0.23198874 | AT74: =IFERROR(AT69/AU69,"--") -> 0.2562714 | AV74: =IFERROR(AV69/AZ69,"--") -> 0.21048682 | AW74: =IFERROR(AW69/AZ69,"--") -> 0.28447524 | AX74: =IFERROR(AX69/AZ69,"--") -> 0.24002766 | AY74: =IFERROR(AY69/AZ69,"--") -> 0.26501028 | BA74: =IFERROR(BA69/BE69,"--") -> 0.20958916 | BB74: =IFERROR(BB69/BE69,"--") -> 0.29233276 | BC74: =IFERROR(BC69/BE69,"--") -> 0.23657825 | BD74: =IFERROR(BD69/BE69,"--") -> 0.26149983 | BF74: =IFERROR(BF69/BJ69,"--") -> 0.20700205 | BG74: =IFERROR(BG69/BJ69,"--") -> 0.30490685 | BH74: =IFERROR(BH69/BJ69,"--") -> 0.23119442 | BI74: =IFERROR(BI69/BJ69,"--") -> 0.25689667 | BK74: =IFERROR(BK69/BO69,"--") -> 0.2009475 | BL74: =IFERROR(BL69/BO69,"--") -> 0.32519689 | BM74: =IFERROR(BM69/BO69,"--") -> 0.22274589 | BN74: =IFERROR(BN69/BO69,"--") -> 0.25110971
B76: Avg. TTM Product Revenue Customer >$1mn | R76: 3194 | S76: 3230 | T76: 3243 | U76: 3395 | V76: =U76 -> 3395 | W76: 3250 | X76: 3475 | Y76: 3467 | Z76: 3478 | AA76: =Z76 -> 3478 | AB76: 3660 | AC76: =(SUM(AB15:AC15,Y15:Z15)*AC80)/AC68*1000 -> 3708.1887 | AD76: =(SUM(AB15:AD15,Z15)*AD80)/AD68*1000 -> 3704.6597 | AE76: =(SUM(AB15:AE15)*AE80)/AE68*1000 -> 3642.562 | AF76: =AE76 -> 3642.562 | AG76: =(SUM(AG15,AC15:AE15)*AG80)/AG68*1000 -> 3662.2773 | AH76: =(SUM(AG15:AH15,AD15:AE15)*AH80)/AH68*1000 -> 3684.1688 | AI76: =(SUM(AG15:AI15,AE15)*AI80)/AI68*1000 -> 3703.3422 | AJ76: =(SUM(AG15:AJ15)*AJ80)/AJ68*1000 -> 3692.5602 | AK76: =AJ76 -> 3692.5602 | AL76: =(SUM(AL15,AH15:AJ15)*AL80)/AL68*1000 -> 3889.638 | AM76: =(SUM(AL15:AM15,AI15:AJ15)*AM80)/AM68*1000 -> 3676.1283 | AN76: =(SUM(AL15:AN15,AJ15)*AN80)/AN68*1000 -> 3981.0332 | AO76: =(SUM(AL15:AO15)*AO80)/AO68*1000 -> 3887.0022 | AP76: =AO76 -> 3887.0022 | AQ76: =(SUM(AQ15,AM15:AO15)*AQ80)/AQ68*1000 -> 3996.6463 | AR76: =(SUM(AQ15:AR15,AN15:AO15)*AR80)/AR68*1000 -> 4027.0627 | AS76: =(SUM(AQ15:AS15,AO15)*AS80)/AS68*1000 -> 4079.3934 | AT76: =AS76*(1+AT78) -> 4120.1873 | AU76: =AT76 -> 4120.1873 | AV76: =AU76*(1+AV78) -> 4212.8915 | AW76: =AV76*(1+AW78) -> 4223.4237 | AX76: =AW76*(1+AX78) -> 4274.1048 | AY76: =AX76*(1+AY78) -> 4321.12 | AZ76: =AY76 -> 4321.12 | BA76: =AZ76*(1+BA78) -> 4429.148 | BB76: =BA76*(1+BB78) -> 4486.7269 | BC76: =BB76*(1+BC78) -> 4589.9216 | BD76: =BC76*(1+BD78) -> 4667.9503 | BE76: =BD76 -> 4667.9503 | BF76: =BE76*(1+BF78) -> 4791.651 | BG76: =BF76*(1+BG78) -> 4853.9424 | BH76: =BG76*(1+BH78) -> 4999.5607 | BI76: =BH76*(1+BI78) -> 5144.548 | BJ76: =BI76 -> 5144.548 | BK76: =BJ76*(1+BK78) -> 5350.3299 | BL76: =BK76*(1+BL78) -> 5468.0371 | BM76: =BL76*(1+BM78) -> 5664.8865 | BN76: =BM76*(1+BN78) -> 5834.8331 | BO76: =BN76 -> 5834.8331
B77: % yoy | J77: =IFERROR(J76/E76-1,"--") -> -- | K77: =IFERROR(K76/F76-1,"--") -> -- | L77: =IFERROR(L76/G76-1,"--") -> -- | M77: =IFERROR(M76/H76-1,"--") -> -- | N77: =IFERROR(N76/I76-1,"--") -> -- | O77: =IFERROR(O76/J76-1,"--") -> -- | P77: =IFERROR(P76/K76-1,"--") -> -- | Q77: =IFERROR(Q76/L76-1,"--") -> -- | ... BO77: =IFERROR(BO76/BJ76-1,"--") -> 0.13417799
B78: % qoq | J78: =IFERROR(J76/I76-1,"--") -> -- | K78: =IFERROR(K76/J76-1,"--") -> -- | L78: -- | M78: =IFERROR(M76/K76-1,"--") -> -- | N78: =IFERROR(N76/M76-1,"--") -> -- | O78: =IFERROR(O76/N76-1,"--") -> -- | P78: =IFERROR(P76/O76-1,"--") -> -- | Q78: -- | R78: =IFERROR(R76/P76-1,"--") -> -- | S78: =IFERROR(S76/R76-1,"--") -> 0.011271133 | T78: =IFERROR(T76/S76-1,"--") -> 0.0040247678 | U78: =IFERROR(U76/T76-1,"--") -> 0.046870182 | V78: -- | W78: =IFERROR(W76/U76-1,"--") -> -0.042709867 | X78: =IFERROR(X76/W76-1,"--") -> 0.069230769 | Y78: =IFERROR(Y76/X76-1,"--") -> -0.0023021583 | Z78: =IFERROR(Z76/Y76-1,"--") -> 0.0031727718 | AA78: -- | AB78: =IFERROR(AB76/Z76-1,"--") -> 0.052328925 | AC78: =IFERROR(AC76/AB76-1,"--") -> 0.013166314 | AD78: =IFERROR(AD76/AC76-1,"--") -> -0.00095169324 | AE78: =IFERROR(AE76/AD76-1,"--") -> -0.01676204 | AF78: -- | AG78: =IFERROR(AG76/AE76-1,"--") -> 0.0054124869 | AH78: =IFERROR(AH76/AG76-1,"--") -> 0.0059775536 | AI78: =IFERROR(AI76/AH76-1,"--") -> 0.005204274 | AJ78: =IFERROR(AJ76/AI76-1,"--") -> -0.0029114371 | AK78: -- | AL78: =IFERROR(AL76/AJ76-1,"--") -> 0.0533716 | AM78: =IFERROR(AM76/AL76-1,"--") -> -0.054891919 | AN78: =IFERROR(AN76/AM76-1,"--") -> 0.08294186 | AO78: =IFERROR(AO76/AN76-1,"--") -> -0.023619742 | AP78: -- | AQ78: =IFERROR(AQ76/AO76-1,"--") -> 0.02820788 | AR78: =IFERROR(AR76/AQ76-1,"--") -> 0.0076104617 | AS78: =IFERROR(AS76/AR76-1,"--") -> 0.012994756 | AT78: 0.01 | AU78: -- | AV78: 0.0225 | AW78: 0.0025 | AX78: 0.012 | AY78: 0.011 | BA78: 0.025 | BB78: 0.013 | BC78: 0.023 | BD78: 0.017 | BF78: 0.0265 | BG78: 0.013 | BH78: 0.03 | BI78: 0.029 | BK78: 0.04 | BL78: 0.022 | BM78: 0.036 | BN78: 0.03 | BO78: --
B79: TTM Revenue | R79: =R76*R68/1000 -> 153.312 | S79: =S76*S68/1000 -> 180.88 | T79: =T76*T68/1000 -> 210.795 | U79: =U76*U68/1000 -> 261.415 | W79: =W76*W68/1000 -> 338 | X79: =X76*X68/1000 -> 403.1 | Y79: =Y76*Y68/1000 -> 513.116 | Z79: =Z76*Z68/1000 -> 639.952 | AB79: =AB76*AB68/1000 -> 753.96 | AC79: =AC76*AC68/1000 -> 919.6308 | AD79: =AD76*AD68/1000 -> 1063.2373 | AE79: =AE76*AE68/1000 -> 1202.0455 | AG79: =AG76*AG68/1000 -> 1366.0294 | AH79: =AH76*AH68/1000 -> 1477.3517 | AI79: =AI76*AI68/1000 -> 1614.6572 | AJ79: =AJ76*AJ68/1000 -> 1680.1149 | AL79: =AL76*AL68/1000 -> 1863.1366 | AM79: =AM76*AM68/1000 -> 1863.7971 | AN79: =AN76*AN68/1000 -> 2149.7579 | AO79: =AO76*AO68/1000 -> 2250.5743 | AQ79: =AQ76*AQ68/1000 -> 2421.9677 | AR79: =AR76*AR68/1000 -> 2633.699 | AS79: =AS76*AS68/1000 -> 2806.6226 | AT79: =AT76*AT68/1000 -> 2989.4383 | AV79: =AV76*AV68/1000 -> 3192.8586 | AW79: =AW76*AW68/1000 -> 3385.3197 | AX79: =AX76*AX68/1000 -> 3583.4666 | AY79: =AY76*AY68/1000 -> 3798.7163 | BA79: =BA76*BA68/1000 -> 4040.2707 | BB79: =BB76*BB68/1000 -> 4299.9095 | BC79: =BC76*BC68/1000 -> 4570.2763 | BD79: =BD76*BD68/1000 -> 4840.7246 | BF79: =BF76*BF68/1000 -> 5116.7347 | BG79: =BG76*BG68/1000 -> 5403.6835 | BH79: =BH76*BH68/1000 -> 5737.9494 | BI79: =BI76*BI68/1000 -> 6101.1917 | BK79: =BK76*BK68/1000 -> 6482.4665 | BL79: =BL76*BL68/1000 -> 6852.0435 | BM79: =BM76*BM68/1000 -> 7259.7734 | BN79: =BN76*BN68/1000 -> 7664.5784
B80: % TTM Revenue | R80: =R79/SUM(R15,N15:P15) -> 0.4925212 | S80: =S79/SUM(R15:S15,O15:P15) -> 0.47766176 | T80: =T79/SUM(R15:T15,P15) -> 0.4603134 | U80: =U79/SUM(R15:U15) -> 0.47204376 | V80: =U80 -> 0.47204376 | W80: =W79/SUM(W15,S15:U15) -> 0.50765462 | X80: =X79/SUM(W15:X15,T15:U15) -> 0.50690757 | Y80: =Y79/SUM(W15:Y15,U15) -> 0.53494218 | Z80: =Z79/SUM(W15:Z15) -> 0.56113055 | AA80: =Z80 -> 0.56113055 | AB80: =AB79/SUM(AB15,X15:Z15) -> 0.57071789 | AC80: 0.6 | AD80: 0.61 | AE80: 0.62 | AF80: =AE80 -> 0.62 | AG80: 0.64 | AH80: 0.64 | AI80: 0.65 | AJ80: 0.63 | AK80: =AJ80 -> 0.63 | AL80: 0.65 | AM80: 0.61 | AN80: 0.66 | AO80: 0.65 | AP80: =AO80 -> 0.65 | AQ80: 0.66 | AR80: 0.67 | AS80: =+AR80 -> 0.67 | AT80: =AT79/SUM(AQ15:AT15) -> 0.67261491 | AU80: =AT80 -> 0.67261491 | AV80: =AV79/SUM(AV15,AR15:AT15) -> 0.67798592 | AW80: =AW79/SUM(AV15:AW15,AS15:AT15) -> 0.68087119 | AX80: =AX79/SUM(AV15:AX15,AT15) -> 0.6820344 | AY80: =AY79/SUM(AV15:AY15) -> 0.68472966 | AZ80: =AY80 -> 0.68472966 | BA80: =BA79/SUM(BA15,AW15:AY15) -> 0.68978066 | BB80: =BB79/SUM(BA15:BB15,AX15:AY15) -> 0.69408551 | BC80: =BC79/SUM(BA15:BC15,AY15) -> 0.69676784 | BD80: =BD79/SUM(BA15:BD15) -> 0.69989269 | BE80: =BD80 -> 0.69989269 | BF80: =BF79/SUM(BF15,BB15:BD15) -> 0.70319785 | BG80: =BG79/SUM(BF15:BG15,BC15:BD15) -> 0.70548252 | BH80: =BH79/SUM(BF15:BH15,BD15) -> 0.70759966 | BI80: =BI79/SUM(BF15:BI15) -> 0.71115434 | BJ80: =BI80 -> 0.71115434 | BK80: =BK79/SUM(BK15,BG15:BI15) -> 0.71574695 | BL80: =BL79/SUM(BK15:BL15,BH15:BI15) -> 0.71846111 | BM80: =BM79/SUM(BK15:BM15,BI15) -> 0.72038486 | BN80: =BN79/SUM(BK15:BN15) -> 0.72290714 | BO80: =BN80 -> 0.72290714
A82: MNCUST | B82: Customers <$1mn in Revenue | J82: =J55-J68 -> 688 | K82: =K55-K68 -> 934 | L82: =L55-L68 -> 934 | M82: =M55-M68 -> 1178 | N82: =N55-N68 -> 1525 | O82: =O55-O68 -> 1903 | P82: =P55-P68 -> 2351 | Q82: =Q55-Q68 -> 2351 | ... AE82: =AE55-AE68 -> 7446 | AF82: =AE82 -> 7446 | AG82: =AG55-AG68 -> 7714 | AH82: =AH55-AH68 -> 8086 | AI82: =AI55-AI68 -> 8449 | AJ82: =AJ55-AJ68 -> 8929 | AK82: =AJ82 -> 8929 | AL82: =AL55-AL68 -> 9262 | AM82: =AM55-AM68 -> 9640 | AN82: =AN55-AN68 -> 9950 | AO82: =AO55-AO68 -> 10444 | AP82: =AO82 -> 10444 | AQ82: =AQ55-AQ68 -> 10867 | AR82: =AR55-AR68 -> 11352 | AS82: =AS55-AS68 -> 11933 | AT82: =AO82*(1+AT84) -> 12473.232 | AU82: =AT82 -> 12473.232 | AV82: =AQ82*(1+AV84) -> 12934.952 | AW82: =AR82*(1+AW84) -> 13466.838 | AX82: =AS82*(1+AX84) -> 14108.344 | AY82: =AT82*(1+AY84) -> 14697.166 | AZ82: =AY82 -> 14697.166 | BA82: =AV82*(1+BA84) -> 15192.702 | BB82: =AW82*(1+BB84) -> 15766.926 | BC82: =AX82*(1+BC84) -> 16465.093 | BD82: =AY82*(1+BD84) -> 17097.161 | BE82: =BD82 -> 17097.161 | BF82: =BA82*(1+BF84) -> 17612.846 | BG82: =BB82*(1+BG84) -> 18215.474 | BH82: =BC82*(1+BH84) -> 18956.204 | BI82: =BD82*(1+BI84) -> 19615.513 | BJ82: =BI82 -> 19615.513 | BK82: =BF82*(1+BK84) -> 20136.705 | BL82: =BG82*(1+BL84) -> 20752.826 | BM82: =BH82*(1+BM84) -> 21520.912 | BN82: =BI82*(1+BN84) -> 22171.346 | BO82: =BN82 -> 22171.346
A83: MNCUSTADD | B83: Net customer adds | K83: =K82-J82 -> 246 | M83: =M82-K82 -> 244 | N83: =N82-M82 -> 347 | O83: =O82-N82 -> 378 | P83: =P82-O82 -> 448 | Q83: =Q82-L82 -> 1417 | R83: =R82-P82 -> 321 | S83: =S82-R82 -> 389 | T83: =T82-S82 -> 428 | U83: =U82-T82 -> 573 | V83: =V82-Q82 -> 1711 | W83: =W82-U82 -> 366 | X83: =X82-W82 -> 446 | Y83: =Y82-X82 -> 394 | Z83: =Z82-Y82 -> 492 | AA83: =AA82-V82 -> 1698 | AB83: =AB82-Z82 -> 356 | AC83: =AC82-AB82 -> 459 | AD83: =AD82-AC82 -> 350 | AE83: =AE82-AD82 -> 521 | AF83: =AF82-AA82 -> 1686 | AG83: =AG82-AE82 -> 268 | AH83: =AH82-AG82 -> 372 | AI83: =AI82-AH82 -> 363 | AJ83: =AJ82-AI82 -> 480 | AK83: =AK82-AF82 -> 1483 | AL83: =AL82-AJ82 -> 333 | AM83: =AM82-AL82 -> 378 | AN83: =AN82-AM82 -> 310 | AO83: =AO82-AN82 -> 494 | AP83: =AP82-AK82 -> 1515 | AQ83: =AQ82-AO82 -> 423 | AR83: =AR82-AQ82 -> 485 | AS83: =AS82-AR82 -> 581 | AT83: =AT82-AS82 -> 540.23246 | AU83: =AU82-AP82 -> 2029.2325 | AV83: =AV82-AU82 -> 461.71941 | AW83: =AW82-AV82 -> 531.88579 | AX83: =AX82-AW82 -> 641.50626 | AY83: =AY82-AX82 -> 588.82201 | AZ83: =AZ82-AU82 -> 2223.9335 | BA83: =BA82-AZ82 -> 495.53629 | BB83: =BB82-BA82 -> 574.22395 | BC83: =BC82-BB82 -> 698.16698 | BD83: =BD82-BC82 -> 632.06828 | BE83: =BE82-AZ82 -> 2399.9955 | BF83: =BF82-BE82 -> 515.68481 | BG83: =BG82-BF82 -> 602.6281 | BH83: =BH82-BG82 -> 740.72948 | BI83: =BI82-BH82 -> 659.30935 | BJ83: =BJ82-BE82 -> 2518.3517 | BK83: =BK82-BJ82 -> 521.19199 | BL83: =BL82-BK82 -> 616.12069 | BM83: =BM82-BL82 -> 768.08568 | BN83: =BN82-BM82 -> 650.43401 | BO83: =BO82-BJ82 -> 2555.8324
A84: MNCUSTYY | B84: % yoy | J84: =IFERROR(J82/E82-1,"--") -> -- | K84: =IFERROR(K82/F82-1,"--") -> -- | L84: =IFERROR(L82/G82-1,"--") -> -- | M84: =IFERROR(M82/H82-1,"--") -> -- | N84: =IFERROR(N82/I82-1,"--") -> -- | O84: =IFERROR(O82/J82-1,"--") -> 1.7659884 | P84: =IFERROR(P82/K82-1,"--") -> 1.5171306 | Q84: =IFERROR(Q82/L82-1,"--") -> 1.5171306 | ... AS84: =IFERROR(AS82/AN82-1,"--") -> 0.19929648 | AT84: =AS84+AT87 -> 0.19429648 | AU84: =IFERROR(AU82/AP82-1,"--") -> 0.19429648 | AV84: =AT84+AV87 -> 0.19029648 | AW84: =AV84+AW87 -> 0.18629648 | AX84: =AW84+AX87 -> 0.18229648 | AY84: =AX84+AY87 -> 0.17829648 | AZ84: =IFERROR(AZ82/AU82-1,"--") -> 0.17829648 | BA84: =AY84+BA87 -> 0.17454648 | BB84: =BA84+BB87 -> 0.17079648 | BC84: =BB84+BC87 -> 0.16704648 | BD84: =BC84+BD87 -> 0.16329648 | BE84: =IFERROR(BE82/AZ82-1,"--") -> 0.16329648 | BF84: =BD84+BF87 -> 0.15929648 | BG84: =BF84+BG87 -> 0.15529648 | BH84: =BG84+BH87 -> 0.15129648 | BI84: =BH84+BI87 -> 0.14729648 | BJ84: =IFERROR(BJ82/BE82-1,"--") -> 0.14729648 | BK84: =BI84+BK87 -> 0.14329648 | BL84: =BK84+BL87 -> 0.13929648 | BM84: =BL84+BM87 -> 0.13529648 | BN84: =BM84+BN87 -> 0.13029648 | BO84: =IFERROR(BO82/BJ82-1,"--") -> 0.13029648
A85: MNCUSTQQ | B85: % qoq | J85: =IFERROR(J82/I82-1,"--") -> -- | K85: =IFERROR(K82/J82-1,"--") -> 0.35755814 | L85: -- | M85: =IFERROR(M82/K82-1,"--") -> 0.26124197 | N85: =IFERROR(N82/M82-1,"--") -> 0.29456706 | O85: =IFERROR(O82/N82-1,"--") -> 0.24786885 | P85: =IFERROR(P82/O82-1,"--") -> 0.23541776 | Q85: -- | R85: =IFERROR(R82/P82-1,"--") -> 0.13653764 | S85: =IFERROR(S82/R82-1,"--") -> 0.14558383 | T85: =IFERROR(T82/S82-1,"--") -> 0.13982359 | U85: =IFERROR(U82/T82-1,"--") -> 0.16423044 | V85: -- | W85: =IFERROR(W82/U82-1,"--") -> 0.090103397 | X85: =IFERROR(X82/W82-1,"--") -> 0.10072267 | Y85: =IFERROR(Y82/X82-1,"--") -> 0.080837095 | Z85: =IFERROR(Z82/Y82-1,"--") -> 0.093394077 | AA85: -- | AB85: =IFERROR(AB82/Z82-1,"--") -> 0.061805556 | AC85: =IFERROR(AC82/AB82-1,"--") -> 0.075049052 | AD85: =IFERROR(AD82/AC82-1,"--") -> 0.053231939 | AE85: =IFERROR(AE82/AD82-1,"--") -> 0.075234657 | AF85: -- | AG85: =IFERROR(AG82/AE82-1,"--") -> 0.035992479 | AH85: =IFERROR(AH82/AG82-1,"--") -> 0.048224008 | AI85: =IFERROR(AI82/AH82-1,"--") -> 0.044892407 | AJ85: =IFERROR(AJ82/AI82-1,"--") -> 0.056811457 | AK85: -- | AL85: =IFERROR(AL82/AJ82-1,"--") -> 0.03729421 | AM85: =IFERROR(AM82/AL82-1,"--") -> 0.04081192 | AN85: =IFERROR(AN82/AM82-1,"--") -> 0.032157676 | AO85: =IFERROR(AO82/AN82-1,"--") -> 0.049648241 | AP85: -- | AQ85: =IFERROR(AQ82/AO82-1,"--") -> 0.040501723 | AR85: =IFERROR(AR82/AQ82-1,"--") -> 0.044630533 | AS85: =IFERROR(AS82/AR82-1,"--") -> 0.051180409 | AT85: =IFERROR(AT82/AS82-1,"--") -> 0.045272141 | AU85: -- | AV85: =IFERROR(AV82/AU82-1,"--") -> 0.037016821 | AW85: =IFERROR(AW82/AV82-1,"--") -> 0.041120044 | AX85: =IFERROR(AX82/AW82-1,"--") -> 0.047635998 | AY85: =IFERROR(AY82/AX82-1,"--") -> 0.041735728 | AZ85: -- | BA85: =IFERROR(BA82/AZ82-1,"--") -> 0.033716452 | BB85: =IFERROR(BB82/BA82-1,"--") -> 0.037796038 | BC85: =IFERROR(BC82/BB82-1,"--") -> 0.044280475 | BD85: =IFERROR(BD82/BC82-1,"--") -> 0.038388382 | BE85: -- | BF85: =IFERROR(BF82/BE82-1,"--") -> 0.030162013 | BG85: =IFERROR(BG82/BF82-1,"--") -> 0.034215259 | BH85: =IFERROR(BH82/BG82-1,"--") -> 0.040664847 | BI85: =IFERROR(BI82/BH82-1,"--") -> 0.034780663 | BJ85: -- | BK85: =IFERROR(BK82/BJ82-1,"--") -> 0.026570398 | BL85: =IFERROR(BL82/BK82-1,"--") -> 0.030596897 | BM85: =IFERROR(BM82/BL82-1,"--") -> 0.037011137 | BN85: =IFERROR(BN82/BM82-1,"--") -> 0.030223349 | BO85: --
B86: % total customers | K86: =K82/K$55 -> 0.98523207 | M86: =M82/M$55 -> 0.98659966 | N86: =N82/N$55 -> 0.98577893 | O86: =O82/O$55 -> 0.98397104 | P86: =P82/P$55 -> 0.98285953 | Q86: =Q82/Q$55 -> 0.98285953 | R86: =R82/R$55 -> 0.98235294 | S86: =S82/S$55 -> 0.98203401 | T86: =T82/T$55 -> 0.98171075 | ... BO86: =BO82/BO$55 -> 0.9440667
B87: Implied Q/Q Deceleration | R87: =R84-P84 -> -0.24887935 | S87: =S84-R84 -> -0.26103816 | T87: =T84-S84 -> -0.1737922 | U87: =U84-T84 -> -0.1056455 | V87: =AVERAGE(R87:U87) -> -0.1973388 | W87: =W84-U84 -> -0.070589786 | X87: =X84-W84 -> -0.064895527 | Y87: =Y84-X84 -> -0.082401881 | Z87: =Z84-Y84 -> -0.091867541 | AA87: =AVERAGE(W87:Z87) -> -0.077438684 | AB87: =AB84-Z84 -> -0.036810201 | AC87: =AC84-AB84 -> -0.032215813 | AD87: =AD84-AC84 -> -0.034454043 | AE87: =AE84-AD84 -> -0.021832289 | AF87: =AVERAGE(AB87:AE87) -> -0.031328087 | AG87: =AG84-AE84 -> -0.03142645 | AH87: =AH84-AG84 -> -0.031471998 | AI87: =AI84-AH84 -> -0.0097376838 | AJ87: =AJ84-AI84 -> -0.020904864 | AK87: =AVERAGE(AG87:AJ87) -> -0.023385249 | AL87: =AL84-AJ84 -> 0.0015067609 | AM87: =AM84-AL84 -> -0.0084900773 | AN87: =AN84-AM84 -> -0.014529862 | AO87: =AO84-AN84 -> -0.0079823045 | AP87: =AVERAGE(AL87:AO87) -> -0.0073738706 | AQ87: =AQ84-AO84 -> 0.0036168508 | AR87: =AR84-AQ84 -> 0.0043046545 | AS87: =AS84-AR84 -> 0.021703121 | AT87: -0.005 | AU87: =AVERAGE(AQ87:AT87) -> 0.0061561567 | AV87: -0.004 | AW87: =AV87 -> -0.004 | AX87: =AW87 -> -0.004 | AY87: =AX87 -> -0.004 | AZ87: =AVERAGE(AV87:AY87) -> -0.004 | BA87: -0.00375 | BB87: =BA87 -> -0.00375 | BC87: =BB87 -> -0.00375 | BD87: =BC87 -> -0.00375 | BE87: =AVERAGE(BA87:BD87) -> -0.00375 | BF87: -0.004 | BG87: =BF87 -> -0.004 | BH87: =BG87 -> -0.004 | BI87: -0.004 | BJ87: =AVERAGE(BF87:BI87) -> -0.004 | BK87: -0.004 | BL87: =BK87 -> -0.004 | BM87: =BL87 -> -0.004 | BN87: -0.005 | BO87: =AVERAGE(BK87:BN87) -> -0.00425
B88: % Seasonality | M88: =IFERROR(M83/Q83,"--") -> 0.17219478 | N88: =IFERROR(N83/Q83,"--") -> 0.24488356 | O88: =IFERROR(O83/Q83,"--") -> 0.26676076 | P88: =IFERROR(P83/Q83,"--") -> 0.3161609 | R88: =IFERROR(R83/V83,"--") -> 0.18760959 | S88: =IFERROR(S83/V83,"--") -> 0.22735243 | T88: =IFERROR(T83/V83,"--") -> 0.25014611 | U88: =IFERROR(U83/V83,"--") -> 0.33489188 | W88: =IFERROR(W83/AA83,"--") -> 0.2155477 | X88: =IFERROR(X83/AA83,"--") -> 0.26266196 | Y88: =IFERROR(Y83/AA83,"--") -> 0.23203769 | Z88: =IFERROR(Z83/AA83,"--") -> 0.28975265 | AB88: =IFERROR(AB83/AF83,"--") -> 0.21115065 | AC88: =IFERROR(AC83/AF83,"--") -> 0.27224199 | AD88: =IFERROR(AD83/AF83,"--") -> 0.20759193 | AE88: =IFERROR(AE83/AF83,"--") -> 0.30901542 | AG88: =IFERROR(AG83/AK83,"--") -> 0.18071477 | AH88: =IFERROR(AH83/AK83,"--") -> 0.25084289 | AI88: =IFERROR(AI83/AK83,"--") -> 0.24477411 | AJ88: =IFERROR(AJ83/AK83,"--") -> 0.32366824 | AL88: =IFERROR(AL83/AP83,"--") -> 0.21980198 | AM88: =IFERROR(AM83/AP83,"--") -> 0.24950495 | AN88: =IFERROR(AN83/AP83,"--") -> 0.20462046 | AO88: =IFERROR(AO83/AP83,"--") -> 0.32607261 | AQ88: =IFERROR(AQ83/AU83,"--") -> 0.2084532 | AR88: =IFERROR(AR83/AU83,"--") -> 0.23900662 | AS88: =IFERROR(AS83/AU83,"--") -> 0.28631515 | AT88: =IFERROR(AT83/AU83,"--") -> 0.26622502 | AV88: =IFERROR(AV83/AZ83,"--") -> 0.20761386 | AW88: =IFERROR(AW83/AZ83,"--") -> 0.23916444 | AX88: =IFERROR(AX83/AZ83,"--") -> 0.28845569 | AY88: =IFERROR(AY83/AZ83,"--") -> 0.26476602 | BA88: =IFERROR(BA83/BE83,"--") -> 0.20647384 | BB88: =IFERROR(BB83/BE83,"--") -> 0.23926043 | BC88: =IFERROR(BC83/BE83,"--") -> 0.29090345 | BD88: =IFERROR(BD83/BE83,"--") -> 0.26336228 | BF88: =IFERROR(BF83/BJ83,"--") -> 0.20477077 | BG88: =IFERROR(BG83/BJ83,"--") -> 0.23929465 | BH88: =IFERROR(BH83/BJ83,"--") -> 0.29413265 | BI88: =IFERROR(BI83/BJ83,"--") -> 0.26180193 | BK88: =IFERROR(BK83/BO83,"--") -> 0.2039226 | BL88: =IFERROR(BL83/BO83,"--") -> 0.24106459 | BM88: =IFERROR(BM83/BO83,"--") -> 0.30052271 | BN88: =IFERROR(BN83/BO83,"--") -> 0.25449009
B90: Avg. TTM Product Revenue Customer <$1mn | R90: =(R93*1000)/R82 -> 59.11976 | S90: =(S93*1000)/S82 -> 64.618752 | T90: =(T93*1000)/T82 -> 70.83491 | U90: =(U93*1000)/U82 -> 71.979074 | V90: =U90 -> 71.979074 | W90: =(W93*1000)/W82 -> 74.030488 | X90: =(X93*1000)/X82 -> 80.450144 | Y90: =(Y93*1000)/Y82 -> 84.677866 | Z90: =(Z93*1000)/Z82 -> 86.895313 | AA90: =Z90 -> 86.895313 | AB90: =(AB93*1000)/AB82 -> 92.726128 | AC90: =(AC93*1000)/AC82 -> 93.245202 | AD90: =(AD93*1000)/AD82 -> 98.162409 | AE90: =(AE93*1000)/AE82 -> 98.944069 | AF90: =AE90 -> 98.944069 | AG90: =(AG93*1000)/AG82 -> 99.610003 | AH90: =(AH93*1000)/AH82 -> 102.7715 | AI90: =(AI93*1000)/AI82 -> 102.9034 | AJ90: =(AJ93*1000)/AJ82 -> 110.50892 | AK90: =AJ90 -> 110.50892 | AL90: =(AL93*1000)/AL82 -> 108.3165 | AM90: =(AM93*1000)/AM82 -> 123.61078 | AN90: =(AN93*1000)/AN82 -> 111.30161 | AO90: =(AO93*1000)/AO82 -> 116.03291 | AP90: =AO90 -> 116.03291 | AQ90: =(AQ93*1000)/AQ82 -> 114.81369 | AR90: =(AR93*1000)/AR82 -> 114.27017 | AS90: =(AS93*1000)/AS82 -> 115.84399 | AT90: =AS90*(1+AT92) -> 116.6549 | AU90: =AT90 -> 116.6549 | AV90: =AU90*(1+AV92) -> 117.23818 | AW90: =AV90*(1+AW92) -> 117.82437 | AX90: =AW90*(1+AX92) -> 118.41349 | AY90: =AX90*(1+AY92) -> 119.00556 | AZ90: =AY90 -> 119.00556 | BA90: =AZ90*(1+BA92) -> 119.60058 | BB90: =BA90*(1+BB92) -> 120.19859 | BC90: =BB90*(1+BC92) -> 120.79958 | BD90: =BC90*(1+BD92) -> 121.40358 | BE90: =BD90 -> 121.40358 | BF90: =BE90*(1+BF92) -> 122.61761 | BG90: =BF90*(1+BG92) -> 123.84379 | BH90: =BG90*(1+BH92) -> 125.08223 | BI90: =BH90*(1+BI92) -> 126.33305 | BJ90: =BI90 -> 126.33305 | BK90: =BJ90*(1+BK92) -> 127.84905 | BL90: =BK90*(1+BL92) -> 129.38323 | BM90: =BL90*(1+BM92) -> 130.93583 | BN90: =BM90*(1+BN92) -> 132.50706 | BO90: =BN90 -> 132.50706
B91: % yoy | R91: =IFERROR(R90/M90-1,"--") -> -- | S91: =IFERROR(S90/N90-1,"--") -> -- | T91: =IFERROR(T90/O90-1,"--") -> -- | U91: =IFERROR(U90/P90-1,"--") -> -- | V91: =IFERROR(V90/Q90-1,"--") -> -- | W91: =IFERROR(W90/R90-1,"--") -> 0.25221224 | X91: =IFERROR(X90/S90-1,"--") -> 0.24499686 | Y91: =IFERROR(Y90/T90-1,"--") -> 0.19542563 | ... BO91: =IFERROR(BO90/BJ90-1,"--") -> 0.048870933
B92: % qoq | R92: =IFERROR(R90/P90-1,"--") -> -- | S92: =IFERROR(S90/R90-1,"--") -> 0.093014443 | T92: =IFERROR(T90/S90-1,"--") -> 0.096197427 | U92: =IFERROR(U90/T90-1,"--") -> 0.016152553 | V92: -- | W92: =IFERROR(W90/U90-1,"--") -> 0.028500137 | X92: =IFERROR(X90/W90-1,"--") -> 0.086716379 | Y92: =IFERROR(Y90/X90-1,"--") -> 0.052550841 | Z92: =IFERROR(Z90/Y90-1,"--") -> 0.026186845 | AA92: -- | AB92: =IFERROR(AB90/Z90-1,"--") -> 0.067101614 | AC92: =IFERROR(AC90/AB90-1,"--") -> 0.0055979188 | AD92: =IFERROR(AD90/AB90-1,"--") -> 0.058627278 | AE92: =IFERROR(AE90/AD90-1,"--") -> 0.0079629325 | AF92: -- | AG92: =IFERROR(AG90/AE90-1,"--") -> 0.0067304013 | AH92: =IFERROR(AH90/AG90-1,"--") -> 0.031738718 | AI92: =IFERROR(AI90/AG90-1,"--") -> 0.033062887 | AJ92: =IFERROR(AJ90/AI90-1,"--") -> 0.073909332 | AK92: -- | AL92: =IFERROR(AL90/AJ90-1,"--") -> -0.019839309 | AM92: =IFERROR(AM90/AL90-1,"--") -> 0.14119997 | AN92: =IFERROR(AN90/AL90-1,"--") -> 0.027559205 | AO92: =IFERROR(AO90/AN90-1,"--") -> 0.042508771 | AP92: -- | AQ92: =IFERROR(AQ90/AO90-1,"--") -> -0.010507565 | AR92: =IFERROR(AR90/AQ90-1,"--") -> -0.0047338525 | AS92: =IFERROR(AS90/AQ90-1,"--") -> 0.0089737356 | AT92: 0.007 | AU92: -- | AV92: 0.005 | AW92: 0.005 | AX92: 0.005 | AY92: 0.005 | AZ92: -- | BA92: 0.005 | BB92: 0.005 | BC92: 0.005 | BD92: 0.005 | BE92: -- | BF92: 0.01 | BG92: 0.01 | BH92: 0.01 | BI92: 0.01 | BJ92: -- | BK92: 0.012 | BL92: =BK92 -> 0.012 | BM92: =BL92 -> 0.012 | BN92: =BM92 -> 0.012 | BO92: --
B93: TTM Revenue | R93: =R79/R80*R94 -> 157.968 | S93: =S79/S80*S94 -> 197.798 | T93: =T79/T80*T94 -> 247.143 | U93: =U79/U80*U94 -> 292.379 | W93: =W79/W80*W94 -> 327.807 | X93: =X79/X80*X94 -> 392.114 | Y93: =Y79/Y80*Y94 -> 446.083 | Z93: =Z79/Z80*Z94 -> 500.517 | AB93: =AB79/AB80*AB94 -> 567.113 | AC93: =AC79/AC80*AC94 -> 613.0872 | AD93: =AD79/AD80*AD94 -> 679.77468 | AE93: =AE79/AE80*AE94 -> 736.73754 | AG93: =AG79/AG80*AG94 -> 768.39156 | AH93: =AH79/AH80*AH94 -> 831.01032 | AI93: =AI79/AI80*AI94 -> 869.4308 | AJ93: =AJ79/AJ80*AJ94 -> 986.73413 | AL93: =AL79/AL80*AL94 -> 1003.2274 | AM93: =AM79/AM80*AM94 -> 1191.608 | AN93: =AN79/AN80*AN94 -> 1107.4511 | AO93: =AO79/AO80*AO94 -> 1211.8477 | AQ93: =AQ79/AQ80*AQ94 -> 1247.6803 | AR93: =AR79/AR80*AR94 -> 1297.195 | AS93: =AS79/AS80*AS94 -> 1382.3664 | AT93: =AT79/AT80*AT94 -> 1455.0637 | AV93: =AV79/AV80*AV94 -> 1516.4702 | AW93: =AW79/AW80*AW94 -> 1586.7216 | AX93: =AX79/AX80*AX94 -> 1670.6182 | AY93: =AY79/AY80*AY94 -> 1749.0444 | BA93: =BA79/BA80*BA94 -> 1817.0561 | BB93: =BB79/BB80*BB94 -> 1895.1622 | BC93: =BC79/BC80*BC94 -> 1988.9763 | BD93: =BD79/BD80*BD94 -> 2075.6566 | BF93: =BF79/BF80*BF94 -> 2159.6452 | BG93: =BG79/BG80*BG94 -> 2255.8734 | BH93: =BH79/BH80*BH94 -> 2371.0842 | BI93: =BI79/BI80*BI94 -> 2478.0876 | BK93: =BK79/BK80*BK94 -> 2574.4585 | BL93: =BL79/BL80*BL94 -> 2685.0677 | BM93: =BM79/BM80*BM94 -> 2817.8585 | BN93: =BN79/BN80*BN94 -> 2937.8599
B94: % TTM Revenue | R94: =1-R80 -> 0.5074788 | S94: =1-S80 -> 0.52233824 | T94: =1-T80 -> 0.5396866 | U94: =1-U80 -> 0.52795624 | V94: =U94 -> 0.52795624 | W94: =1-W80 -> 0.49234538 | X94: =1-X80 -> 0.49309243 | Y94: =1-Y80 -> 0.46505782 | Z94: =1-Z80 -> 0.43886945 | AA94: =Z94 -> 0.43886945 | AB94: =1-AB80 -> 0.42928211 | AC94: =1-AC80 -> 0.4 | AD94: =1-AD80 -> 0.39 | AE94: =1-AE80 -> 0.38 | AF94: =AE94 -> 0.38 | AG94: =1-AG80 -> 0.36 | AH94: =1-AH80 -> 0.36 | AI94: =1-AI80 -> 0.35 | AJ94: =1-AJ80 -> 0.37 | AK94: =AJ94 -> 0.37 | AL94: =1-AL80 -> 0.35 | AM94: =1-AM80 -> 0.39 | AN94: =1-AN80 -> 0.34 | AO94: =1-AO80 -> 0.35 | AP94: =AO94 -> 0.35 | AQ94: =1-AQ80 -> 0.34 | AR94: =1-AR80 -> 0.33 | AS94: =1-AS80 -> 0.33 | AT94: =1-AT80 -> 0.32738509 | AU94: =AT94 -> 0.32738509 | AV94: =1-AV80 -> 0.32201408 | AW94: =1-AW80 -> 0.31912881 | AX94: =1-AX80 -> 0.3179656 | AY94: =1-AY80 -> 0.31527034 | AZ94: =AY94 -> 0.31527034 | BA94: =1-BA80 -> 0.31021934 | BB94: =1-BB80 -> 0.30591449 | BC94: =1-BC80 -> 0.30323216 | BD94: =1-BD80 -> 0.30010731 | BE94: =BD94 -> 0.30010731 | BF94: =1-BF80 -> 0.29680215 | BG94: =1-BG80 -> 0.29451748 | BH94: =1-BH80 -> 0.29240034 | BI94: =1-BI80 -> 0.28884566 | BJ94: =BI94 -> 0.28884566 | BK94: =1-BK80 -> 0.28425305 | BL94: =1-BL80 -> 0.28153889 | BM94: =1-BM80 -> 0.27961514 | BN94: =1-BN80 -> 0.27709286 | BO94: =BN94 -> 0.27709286
B96: Product revenue | H96: =H15 -> 13.186 | I96: =I15 -> 17.675 | J96: =J15 -> 28.457 | K96: =K15 -> 36.365 | L96: =L15 -> 95.683 | M96: =M15 -> 42.766 | N96: =N15 -> 57.818 | O96: =O15 -> 69.213 | ... AE96: =AE15 -> 555.329 | AF96: =SUM(AB96:AE96) -> 1938.783 | AG96: =(((AG68*AG76)+(AG82*AG90))/1000)-SUM(AC15:AE15) -> 590.072 | AH96: =AH15 -> 640.209 | AI96: =AI15 -> 698.478 | AJ96: =AJ15 -> 738.09 | AK96: =SUM(AG96:AJ96) -> 2666.849 | AL96: =(((AL68*AL76)+(AL82*AL90))/1000)-SUM(AH15:AJ15) -> 789.587 | AM96: =AM15 -> 829.25 | AN96: =AN15 -> 900.282 | AO96: =AO15 -> 943.303 | AP96: =SUM(AL96:AO96) -> 3462.422 | AQ96: =(((AQ68*AQ76)+(AQ82*AQ90))/1000)-SUM(AM15:AO15) -> 996.813 | AR96: =AR15 -> 1090.496 | AS96: =AS15 -> 1158.377 | AT96: =(((AT68*AT76)+(AT82*AT90))/1000)-SUM(AQ15:AS15) -> 1198.816 | AU96: =SUM(AQ96:AT96) -> 4444.502 | AV96: =(((AV68*AV76)+(AV82*AV90))/1000)-SUM(AR15:AT15) -> 1261.6397 | AW96: =(((AW68*AW76)+(AW82*AW90))/1000)-SUM(AV15,AS15:AT15) -> 1353.2086 | AX96: =(((AX68*AX76)+(AX82*AX90))/1000)-SUM(AV15:AW15,AT15) -> 1440.4205 | AY96: =(((AY68*AY76)+(AY82*AY90))/1000)-SUM(AV15:AX15) -> 1492.4918 | AZ96: =SUM(AV96:AY96) -> 5547.7607 | BA96: =(((BA68*BA76)+(BA82*BA90))/1000)-SUM(AW15:AY15) -> 1571.2058 | BB96: =(((BB68*BB76)+(BB82*BB90))/1000)-SUM(BA15,AX15:AY15) -> 1690.9536 | BC96: =(((BC68*BC76)+(BC82*BC90))/1000)-SUM(BA15:BB15,AY15) -> 1804.6013 | BD96: =(((BD68*BD76)+(BD82*BD90))/1000)-SUM(BA15:BC15) -> 1849.6205 | BE96: =SUM(BA96:BD96) -> 6916.3812 | BF96: =(((BF68*BF76)+(BF82*BF90))/1000)-SUM(BB15:BD15) -> 1931.2045 | BG96: =(((BG68*BG76)+(BG82*BG90))/1000)-SUM(BF15,BC15:BD15) -> 2074.1306 | BH96: =(((BH68*BH76)+(BH82*BH90))/1000)-SUM(BF15:BG15,BD15) -> 2254.078 | BI96: =(((BI68*BI76)+(BI82*BI90))/1000)-SUM(BF15:BH15) -> 2319.8661 | BJ96: =SUM(BF96:BI96) -> 8579.2792 | BK96: =(((BK68*BK76)+(BK82*BK90))/1000)-SUM(BG15:BI15) -> 2408.8503 | BL96: =(((BL68*BL76)+(BL82*BL90))/1000)-SUM(BK15,BH15:BI15) -> 2554.3169 | BM96: =(((BM68*BM76)+(BM82*BM90))/1000)-SUM(BK15:BL15,BI15) -> 2794.5987 | BN96: =(((BN68*BN76)+(BN82*BN90))/1000)-SUM(BK15:BM15) -> 2844.6724 | BO96: =SUM(BK96:BN96) -> 10602.438
B97: $ change qoq | I97: =I96-H96 -> 4.489 | J97: =J96-I96 -> 10.782 | K97: =K96-J96 -> 7.908 | L97: =SUM(H97:K97) -> 23.179 | M97: -- | N97: =N96-M96 -> 15.052 | O97: =O96-N96 -> 11.395 | P97: =P96-O96 -> 13.219 | Q97: =SUM(M97:P97) -> 39.666 | R97: =R96-P96 -> 19.385 | S97: =S96-R96 -> 23.399 | T97: =T96-S96 -> 23.257 | U97: =U96-T96 -> 29.815 | V97: =SUM(R97:U97) -> 95.856 | W97: =W96-U96 -> 35.542 | X97: =X96-W96 -> 40.793 | Y97: =Y96-X96 -> 57.835 | Z97: =Z96-Y96 -> 47.1 | AA97: =SUM(W97:Z97) -> 181.27 | AB97: =AB96-Z96 -> 34.876 | AC97: =AC96-AB96 -> 71.834 | AD97: =AD96-AC96 -> 56.484 | AE97: =AE96-AD96 -> 32.577 | AF97: =SUM(AB97:AE97) -> 195.771 | AG97: =AG96-AE96 -> 34.743 | AH97: =AH96-AG96 -> 50.137 | AI97: =AI96-AH96 -> 58.269 | AJ97: =AJ96-AI96 -> 39.612 | AK97: =SUM(AG97:AJ97) -> 182.761 | AL97: =AL96-AJ96 -> 51.497 | AM97: =AM96-AL96 -> 39.663 | AN97: =AN96-AM96 -> 71.032 | AO97: =AO96-AN96 -> 43.021 | AP97: =SUM(AL97:AO97) -> 205.213 | AQ97: =AQ96-AO96 -> 53.51 | AR97: =AR96-AQ96 -> 93.683 | AS97: =AS96-AR96 -> 67.881 | AT97: =AT96-AS96 -> 40.439006 | AU97: =SUM(AQ97:AT97) -> 255.51301 | AV97: =AV96-AT96 -> 62.823731 | AW97: =AW96-AV96 -> 91.568828 | AX97: =AX96-AW96 -> 87.21194 | AY97: =AY96-AX96 -> 52.071344 | AZ97: =SUM(AV97:AY97) -> 293.67584 | BA97: =BA96-AY96 -> 78.713983 | BB97: =BB96-BA96 -> 119.74774 | BC97: =BC96-BB96 -> 113.64776 | BD97: =BD96-BC96 -> 45.019135 | BE97: =SUM(BA97:BD97) -> 357.12862 | BF97: =BF96-BD96 -> 81.584033 | BG97: =BG96-BF96 -> 142.9261 | BH97: =BH96-BG96 -> 179.94745 | BI97: =BI96-BH96 -> 65.788056 | BJ97: =SUM(BF97:BI97) -> 470.24563 | BK97: =BK96-BI96 -> 88.984167 | BL97: =BL96-BK96 -> 145.4666 | BM97: =BM96-BL96 -> 240.28182 | BN97: =BN96-BM96 -> 50.073735 | BO97: =SUM(BK97:BN97) -> 524.80633
B98: % yoy | H98: =IFERROR(H96/C96-1,"--") -> -- | I98: =IFERROR(I96/D96-1,"--") -> -- | J98: =IFERROR(J96/E96-1,"--") -> -- | K98: =IFERROR(K96/F96-1,"--") -> -- | L98: =IFERROR(L96/G96-1,"--") -> -- | M98: =IFERROR(M96/H96-1,"--") -> 2.2432883 | N98: =IFERROR(N96/I96-1,"--") -> 2.271174 | O98: =IFERROR(O96/J96-1,"--") -> 1.4321959 | ... BO98: =IFERROR(BO96/BJ96-1,"--") -> 0.23581923
B99: % qoq | H99: =IFERROR(H96/G96-1,"--") -> -- | I99: =IFERROR(I96/H96-1,"--") -> 0.34043683 | J99: =IFERROR(J96/I96-1,"--") -> 0.61001414 | K99: =IFERROR(K96/J96-1,"--") -> 0.27789296 | L99: -- | M99: =IFERROR(M96/K96-1,"--") -> 0.1760209 | N99: =IFERROR(N96/M96-1,"--") -> 0.35196184 | O99: =IFERROR(O96/N96-1,"--") -> 0.19708395 | P99: =IFERROR(P96/O96-1,"--") -> 0.19099013 | Q99: -- | R99: =IFERROR(R96/P96-1,"--") -> 0.23516353 | S99: =IFERROR(S96/R96-1,"--") -> 0.22981427 | T99: =IFERROR(T96/S96-1,"--") -> 0.18573505 | U99: =IFERROR(U96/T96-1,"--") -> 0.20081092 | V99: -- | W99: =IFERROR(W96/U96-1,"--") -> 0.19935161 | X99: =IFERROR(X96/W96-1,"--") -> 0.19077304 | Y99: =IFERROR(Y96/X96-1,"--") -> 0.22713973 | Z99: =IFERROR(Z96/Y96-1,"--") -> 0.15074026 | AA99: -- | AB99: =IFERROR(AB96/Z96-1,"--") -> 0.096996868 | AC99: =IFERROR(AC96/AB96-1,"--") -> 0.18211919 | AD99: =IFERROR(AD96/AC96-1,"--") -> 0.12114063 | AE99: =IFERROR(AE96/AD96-1,"--") -> 0.062318269 | AF99: -- | AG99: =IFERROR(AG96/AE96-1,"--") -> 0.062562913 | AH99: =IFERROR(AH96/AG96-1,"--") -> 0.084967597 | AI99: =IFERROR(AI96/AH96-1,"--") -> 0.09101559 | AJ99: =IFERROR(AJ96/AI96-1,"--") -> 0.056711879 | AK99: -- | AL99: =IFERROR(AL96/AJ96-1,"--") -> 0.069770624 | AM99: =IFERROR(AM96/AL96-1,"--") -> 0.05023259 | AN99: =IFERROR(AN96/AM96-1,"--") -> 0.085658125 | AO99: =IFERROR(AO96/AN96-1,"--") -> 0.047786138 | AP99: -- | AQ99: =IFERROR(AQ96/AO96-1,"--") -> 0.056726206 | AR99: =IFERROR(AR96/AQ96-1,"--") -> 0.093982522 | AS99: =IFERROR(AS96/AR96-1,"--") -> 0.062247821 | AT99: =IFERROR(AT96/AS96-1,"--") -> 0.034910056 | AU99: -- | AV99: =IFERROR(AV96/AT96-1,"--") -> 0.052404815 | AW99: =IFERROR(AW96/AV96-1,"--") -> 0.07257922 | AX99: =IFERROR(AX96/AW96-1,"--") -> 0.064448262 | AY99: =IFERROR(AY96/AX96-1,"--") -> 0.036150099 | AZ99: -- | BA99: =IFERROR(BA96/AY96-1,"--") -> 0.052739975 | BB99: =IFERROR(BB96/BA96-1,"--") -> 0.076213912 | BC99: =IFERROR(BC96/BB96-1,"--") -> 0.067209272 | BD99: =IFERROR(BD96/BC96-1,"--") -> 0.024946859 | BE99: -- | BF99: =IFERROR(BF96/BD96-1,"--") -> 0.044108526 | BG99: =IFERROR(BG96/BF96-1,"--") -> 0.074008783 | BH99: =IFERROR(BH96/BG96-1,"--") -> 0.086758012 | BI99: =IFERROR(BI96/BH96-1,"--") -> 0.029186237 | BJ99: -- | BK99: =IFERROR(BK96/BI96-1,"--") -> 0.038357458 | BL99: =IFERROR(BL96/BK96-1,"--") -> 0.060388394 | BM99: =IFERROR(BM96/BL96-1,"--") -> 0.094068918 | BN99: =IFERROR(BN96/BM96-1,"--") -> 0.017918041 | BO99: --
B100: % total revenue | H100: =H96/H$11 -> 0.98380959 | I100: =I96/I$11 -> 0.98715443 | J100: =J96/J$11 -> 0.99222455 | K100: =K96/K$11 -> 0.99146627 | L100: =L96/L$11 -> 0.98983096 | M100: =M96/M$11 -> 0.97851504 | N100: =N96/N$11 -> 0.95821939 | O100: =O96/O$11 -> 0.94796746 | ... BO100: =BO96/BO$11 -> 0.9696772
B101: % seasonality | H101: =H96/L96 -> 0.13780922 | I101: =I96/L96 -> 0.18472456 | J101: =J96/L96 -> 0.29740915 | K101: =K96/L96 -> 0.38005706 | M101: =M96/Q96 -> 0.16955227 | N101: =N96/Q96 -> 0.2292282 | O101: =O96/Q96 -> 0.2744054 | P101: =P96/Q96 -> 0.32681413 | R101: =R96/V96 -> 0.18385356 | S101: =S96/V96 -> 0.22610574 | T101: =T96/V96 -> 0.2681015 | U101: =U96/V96 -> 0.3219392 | W101: =W96/AA96 -> 0.18749304 | X101: =X96/AA96 -> 0.22326166 | Y101: =Y96/AA96 -> 0.27397325 | Z101: =Z96/AA96 -> 0.31527205 | AB101: =AB96/AF96 -> 0.20344412 | AC101: =AC96/AF96 -> 0.2404952 | AD101: =AD96/AF96 -> 0.26962894 | AE101: =AE96/AF96 -> 0.28643175 | AG101: =AG96/AK96 -> 0.22126187 | AH101: =AH96/AK96 -> 0.24006196 | AI101: =AI96/AK96 -> 0.26191134 | AJ101: =AJ96/AK96 -> 0.27676483 | AL101: =AL96/AP96 -> 0.2280447 | AM101: =AM96/AP96 -> 0.23949998 | AN101: =AN96/AP96 -> 0.2600151 | AO101: =AO96/AP96 -> 0.27244022 | AQ101: =AQ96/AU96 -> 0.22428002 | AR101: =AR96/AU96 -> 0.24535842 | AS101: =AS96/AU96 -> 0.26063145 | AT101: =AT96/AU96 -> 0.26973011 | AV101: =AV96/AZ96 -> 0.22741423 | AW101: =AW96/AZ96 -> 0.24391978 | AX101: =AX96/AZ96 -> 0.25963999 | AY101: =AY96/AZ96 -> 0.269026 | BA101: =BA96/BE96 -> 0.22717166 | BB101: =BB96/BE96 -> 0.24448531 | BC101: =BC96/BE96 -> 0.26091699 | BD101: =BD96/BE96 -> 0.26742604 | BF101: =BF96/BJ96 -> 0.22510102 | BG101: =BG96/BJ96 -> 0.24176047 | BH101: =BH96/BJ96 -> 0.26273513 | BI101: =BI96/BJ96 -> 0.27040338 | BK101: =BK96/BO96 -> 0.22719776 | BL101: =BL96/BO96 -> 0.24091787 | BM101: =BM96/BO96 -> 0.26358076 | BN101: =BN96/BO96 -> 0.26830361
A103: RPO | B103: Remaining performance obligations | J103: 82.8 | K103: 128 | L103: =K103 -> 128 | M103: 137.9 | N103: 221.1 | O103: 273 | P103: 426.3 | Q103: =P103 -> 426.3 | R103: 467.8 | S103: 688.2 | T103: 927.9 | U103: 1333 | V103: =U103 -> 1333 | W103: 1432 | X103: 1529 | Y103: 1804 | Z103: 2646 | AA103: =Z103 -> 2646 | AB103: 2610 | AC103: 2716 | AD103: 3003 | AE103: 3661 | AF103: =AE103 -> 3661 | AG103: 3409 | AH103: 3540 | AI103: 3699 | AJ103: 5175 | AK103: =AJ103 -> 5175 | AL103: 4988 | AM103: 5231 | AN103: 5732 | AO103: 6867 | AP103: =AO103 -> 6867 | AQ103: 6687 | AR103: 6932 | AS103: 7881
A104: RPOCHG | B104: $ change qoq | K104: =K103-J103 -> 45.2 | M104: =M103-K103 -> 9.9 | N104: =N103-M103 -> 83.2 | O104: =O103-N103 -> 51.9 | P104: =P103-O103 -> 153.3 | Q104: =Q103-L103 -> 298.3 | R104: =R103-P103 -> 41.5 | S104: =S103-R103 -> 220.4 | T104: =T103-S103 -> 239.7 | U104: =U103-T103 -> 405.1 | V104: =V103-Q103 -> 906.7 | W104: =W103-U103 -> 99 | X104: =X103-W103 -> 97 | Y104: =Y103-X103 -> 275 | Z104: =Z103-Y103 -> 842 | AA104: =AA103-V103 -> 1313 | AB104: =AB103-Z103 -> -36 | AC104: =AC103-AB103 -> 106 | AD104: =AD103-AC103 -> 287 | AE104: =AE103-AD103 -> 658 | AF104: =AF103-AA103 -> 1015 | AG104: =AG103-AE103 -> -252 | AH104: =AH103-AG103 -> 131 | AI104: =AI103-AH103 -> 159 | AJ104: =AJ103-AI103 -> 1476 | AK104: =AK103-AF103 -> 1514 | AL104: =AL103-AJ103 -> -187 | AM104: =AM103-AL103 -> 243 | AN104: =AN103-AM103 -> 501 | AO104: =AO103-AN103 -> 1135 | AP104: =AP103-AK103 -> 1692 | AQ104: =AQ103-AO103 -> -180 | AR104: =AR103-AQ103 -> 245 | AS104: =AS103-AR103 -> 949
A105: RPOYY | B105: % yoy | J105: =IFERROR(J103/E103-1,"--") -> -- | K105: =IFERROR(K103/F103-1,"--") -> -- | L105: =IFERROR(L103/G103-1,"--") -> -- | M105: =IFERROR(M103/H103-1,"--") -> -- | N105: =IFERROR(N103/I103-1,"--") -> -- | O105: =IFERROR(O103/J103-1,"--") -> 2.2971014 | P105: =IFERROR(P103/K103-1,"--") -> 2.3304688 | Q105: =IFERROR(Q103/L103-1,"--") -> 2.3304688 | ... AS105: =IFERROR(AS103/AN103-1,"--") -> 0.37491277
A106: RPOQQ | B106: % qoq | J106: =IFERROR(J103/I103-1,"--") -> -- | K106: =IFERROR(K103/J103-1,"--") -> 0.54589372 | L106: -- | M106: =IFERROR(M103/K103-1,"--") -> 0.07734375 | N106: =IFERROR(N103/M103-1,"--") -> 0.60333575 | O106: =IFERROR(O103/N103-1,"--") -> 0.23473541 | P106: =IFERROR(P103/O103-1,"--") -> 0.56153846 | Q106: -- | R106: =IFERROR(R103/P103-1,"--") -> 0.097349285 | S106: =IFERROR(S103/R103-1,"--") -> 0.47114151 | T106: =IFERROR(T103/S103-1,"--") -> 0.34829991 | U106: =IFERROR(U103/T103-1,"--") -> 0.43657722 | V106: -- | W106: =IFERROR(W103/U103-1,"--") -> 0.074268567 | X106: =IFERROR(X103/W103-1,"--") -> 0.06773743 | Y106: =IFERROR(Y103/X103-1,"--") -> 0.17985612 | Z106: =IFERROR(Z103/Y103-1,"--") -> 0.46674058 | AA106: -- | AB106: =IFERROR(AB103/Z103-1,"--") -> -0.013605442 | AC106: =IFERROR(AC103/AB103-1,"--") -> 0.040613027 | AD106: =IFERROR(AD103/AC103-1,"--") -> 0.1056701 | AE106: =IFERROR(AE103/AD103-1,"--") -> 0.21911422 | AF106: -- | AG106: =IFERROR(AG103/AE103-1,"--") -> -0.068833652 | AH106: =IFERROR(AH103/AG103-1,"--") -> 0.038427691 | AI106: =IFERROR(AI103/AH103-1,"--") -> 0.044915254 | AJ106: =IFERROR(AJ103/AI103-1,"--") -> 0.39902676 | AK106: -- | AL106: =IFERROR(AL103/AJ103-1,"--") -> -0.036135266 | AM106: =IFERROR(AM103/AL103-1,"--") -> 0.048716921 | AN106: =IFERROR(AN103/AM103-1,"--") -> 0.095775186 | AO106: =IFERROR(AO103/AN103-1,"--") -> 0.19801117 | AP106: -- | AQ106: =IFERROR(AQ103/AO103-1,"--") -> -0.02621232 | AR106: =IFERROR(AR103/AQ103-1,"--") -> 0.036638253 | AS106: =IFERROR(AS103/AR103-1,"--") -> 0.13690133
A108: cRPO | B108: Current RPO | U108: =U103*U112 -> 733.15 | V108: =U108 -> 733.15 | W108: =W103*W112 -> 787.6 | X108: =X103*X112 -> 856.24 | Y108: =Y103*Y112 -> 992.2 | Z108: =Z103*Z112 -> 1375.92 | AA108: =Z108 -> 1375.92 | AB108: =AB103*AB112 -> 1383.3 | AC108: =AC103*AC112 -> 1548.12 | AD108: =AD103*AD112 -> 1651.65 | AE108: =AE103*AE112 -> 2013.55 | AF108: =AE108 -> 2013.55 | AG108: =AG103*AG112 -> 1943.13 | AH108: =AH103*AH112 -> 2017.8 | AI108: =AI103*AI112 -> 2108.43 | AJ108: =AJ103*AJ112 -> 2587.5 | AK108: =AJ108 -> 2587.5 | AL108: =AL103*AL112 -> 2543.88 | AM108: =AM103*AM112 -> 2615.5 | AN108: =AN103*AN112 -> 2866 | AO108: =AO103*AO112 -> 3296.16 | AP108: =AO108 -> 3296.16 | AQ108: =AQ103*AQ112 -> 3343.5 | AR108: =AR103*AR112 -> 3466 | AS108: =AS103*AS112 -> 3782.88
B109: $ change qoq | W109: =W108-U108 -> 54.45 | X109: =X108-W108 -> 68.64 | Y109: =Y108-X108 -> 135.96 | Z109: =Z108-Y108 -> 383.72 | AB109: =AB108-Z108 -> 7.38 | AC109: =AC108-AB108 -> 164.82 | AD109: =AD108-AC108 -> 103.53 | AE109: =AE108-AD108 -> 361.9 | AG109: =AG108-AE108 -> -70.42 | AH109: =AH108-AG108 -> 74.67 | AI109: =AI108-AH108 -> 90.63 | AJ109: =AJ108-AI108 -> 479.07 | AL109: =AL108-AJ108 -> -43.62 | AM109: =AM108-AL108 -> 71.62 | AN109: =AN108-AM108 -> 250.5 | AO109: =AO108-AN108 -> 430.16 | AQ109: =AQ108-AO108 -> 47.34 | AR109: =AR108-AQ108 -> 122.5 | AS109: =AS108-AR108 -> 316.88
A110: cRPOYY | B110: % yoy | U110: =IFERROR(U108/P108-1,"--") -> -- | V110: =IFERROR(V108/Q108-1,"--") -> -- | W110: =IFERROR(W108/R108-1,"--") -> -- | X110: =IFERROR(X108/S108-1,"--") -> -- | Y110: =IFERROR(Y108/T108-1,"--") -> -- | Z110: =IFERROR(Z108/U108-1,"--") -> 0.87672373 | AA110: =IFERROR(AA108/V108-1,"--") -> 0.87672373 | AB110: =IFERROR(AB108/W108-1,"--") -> 0.7563484 | ... AS110: =IFERROR(AS108/AN108-1,"--") -> 0.31991626
A111: cRPOQQ | B111: % qoq | U111: =IFERROR(U108/T108-1,"--") -> -- | V111: -- | W111: =IFERROR(W108/U108-1,"--") -> 0.074268567 | X111: =IFERROR(X108/W108-1,"--") -> 0.087150838 | Y111: =IFERROR(Y108/X108-1,"--") -> 0.15878726 | Z111: =IFERROR(Z108/Y108-1,"--") -> 0.38673655 | AA111: -- | AB111: =IFERROR(AB108/Z108-1,"--") -> 0.0053636839 | AC111: =IFERROR(AC108/AB108-1,"--") -> 0.11914986 | AD111: =IFERROR(AD108/AC108-1,"--") -> 0.066874661 | AE111: =IFERROR(AE108/AD108-1,"--") -> 0.21911422 | AF111: -- | AG111: =IFERROR(AG108/AE108-1,"--") -> -0.034973058 | AH111: =IFERROR(AH108/AG108-1,"--") -> 0.038427691 | AI111: =IFERROR(AI108/AH108-1,"--") -> 0.044915254 | AJ111: =IFERROR(AJ108/AI108-1,"--") -> 0.22721646 | AK111: -- | AL111: =IFERROR(AL108/AJ108-1,"--") -> -0.016857971 | AM111: =IFERROR(AM108/AL108-1,"--") -> 0.028153844 | AN111: =IFERROR(AN108/AM108-1,"--") -> 0.095775186 | AO111: =IFERROR(AO108/AN108-1,"--") -> 0.15009072 | AP111: -- | AQ111: =IFERROR(AQ108/AO108-1,"--") -> 0.014362167 | AR111: =IFERROR(AR108/AQ108-1,"--") -> 0.036638253 | AS111: =IFERROR(AS108/AR108-1,"--") -> 0.091425274
B112: % of total RPO | U112: 0.55 | W112: 0.55 | X112: 0.56 | Y112: 0.55 | Z112: 0.52 | AB112: 0.53 | AC112: 0.57 | AD112: 0.55 | AE112: 0.55 | AG112: 0.57 | AH112: 0.57 | AI112: 0.57 | AJ112: 0.5 | AL112: 0.51 | AM112: 0.5 | AN112: 0.5 | AO112: 0.48 | AQ112: 0.5 | AR112: 0.5 | AS112: 0.48
A114: NER | B114: Dollar-based net expansion rate | J114: 1.65 | K114: 1.8 | L114: =K114 -> 1.8 | M114: 1.87 | N114: 2.23 | O114: 1.89 | P114: 1.69 | Q114: =P114 -> 1.69 | R114: 1.71 | S114: 1.61 | T114: 1.64 | U114: 1.65 | V114: =U114 -> 1.65 | W114: 1.66 | X114: 1.69 | Y114: 1.72 | Z114: 1.78 | AA114: =Z114 -> 1.78 | AB114: 1.75 | AC114: 1.72 | AD114: 1.65 | AE114: 1.58 | AF114: =AE114 -> 1.58 | AG114: 1.51 | AH114: 1.42 | AI114: 1.35 | AJ114: 1.31 | AK114: =AJ114 -> 1.31 | AL114: 1.28 | AM114: 1.27 | AN114: 1.27 | AO114: 1.26 | AP114: =AO114 -> 1.26 | AQ114: 1.24 | AR114: 1.25 | AS114: 1.25
AC115: =AC114-AB114 -> -0.03 | AD115: =AD114-AC114 -> -0.07 | AE115: =AE114-AD114 -> -0.07 | AG115: =AG114-AE114 -> -0.07 | AH115: =AH114-AG114 -> -0.09 | AI115: =AI114-AH114 -> -0.07 | AJ115: =AJ114-AI114 -> -0.04 | AL115: =AL114-AJ114 -> -0.03 | AM115: =AM114-AL114 -> -0.01 | AN115: =AN114-AM114 -> 0 | AO115: =AO114-AN114 -> -0.01 | AQ115: =AQ114-AO114 -> -0.02 | AR115: =AR114-AQ114 -> 0.01 | AS115: =AS114-AR114 -> 0
B116: Employee Headcount
B117: Cost of Revenue | AD117: 801 | AE117: 861 | AF117: =AE117 -> 861 | AG117: 907 | AH117: 925 | AI117: 925 | AJ117: 939 | AK117: =AJ117 -> 939 | AL117: 963 | AM117: 1002 | AN117: 1080 | AO117: 1084 | AP117: =AO117 -> 1084 | AQ117: 1123 | AR117: 1189 | AS117: 1258
B118: % yoy | AB118: =IFERROR(AB117/W117-1,"--") -> -- | AC118: =IFERROR(AC117/X117-1,"--") -> -- | AD118: =IFERROR(AD117/Y117-1,"--") -> -- | AE118: =IFERROR(AE117/Z117-1,"--") -> -- | AF118: =IFERROR(AF117/AA117-1,"--") -> -- | AG118: =IFERROR(AG117/AB117-1,"--") -> -- | AH118: =IFERROR(AH117/AC117-1,"--") -> -- | AI118: =IFERROR(AI117/AD117-1,"--") -> 0.15480649 | ... AS118: =IFERROR(AS117/AN117-1,"--") -> 0.16481481
B119: % qoq | AB119: =IFERROR(AB117/Z117-1,"--") -> -- | AC119: =IFERROR(AC117/AB117-1,"--") -> -- | AD119: =IFERROR(AD117/AC117-1,"--") -> -- | AE119: =IFERROR(AE117/AD117-1,"--") -> 0.074906367 | AG119: =IFERROR(AG117/AE117-1,"--") -> 0.053426249 | AH119: =IFERROR(AH117/AG117-1,"--") -> 0.019845645 | AI119: =IFERROR(AI117/AH117-1,"--") -> 0 | AJ119: =IFERROR(AJ117/AI117-1,"--") -> 0.015135135 | AL119: =IFERROR(AL117/AJ117-1,"--") -> 0.025559105 | AM119: =IFERROR(AM117/AL117-1,"--") -> 0.040498442 | AN119: =IFERROR(AN117/AM117-1,"--") -> 0.077844311 | AO119: =IFERROR(AO117/AN117-1,"--") -> 0.0037037037 | AQ119: =IFERROR(AQ117/AO117-1,"--") -> 0.03597786 | AR119: =IFERROR(AR117/AQ117-1,"--") -> 0.058771149 | AS119: =IFERROR(AS117/AR117-1,"--") -> 0.05803196
B120: Net New Adds (YoY) | AB120: =IFERROR(AB117-W117,"--") -> 0 | AC120: =IFERROR(AC117-X117,"--") -> 0 | AD120: =IFERROR(AD117-Y117,"--") -> 801 | AE120: =IFERROR(AE117-Z117,"--") -> 861 | AF120: =IFERROR(AF117-AA117,"--") -> 861 | AG120: =IFERROR(AG117-AB117,"--") -> 907 | AH120: =IFERROR(AH117-AC117,"--") -> 925 | AI120: =IFERROR(AI117-AD117,"--") -> 124 | ... AS120: =IFERROR(AS117-AN117,"--") -> 178
B121: Net New Adds (QoQ) | AB121: =IFERROR(AB117-Z117,"--") -> 0 | AC121: =IFERROR(AC117-AB117,"--") -> 0 | AD121: =IFERROR(AD117-AC117,"--") -> 801 | AE121: =IFERROR(AE117-AD117,"--") -> 60 | AG121: =IFERROR(AG117-AE117,"--") -> 46 | AH121: =IFERROR(AH117-AG117,"--") -> 18 | AI121: =IFERROR(AI117-AH117,"--") -> 0 | AJ121: =IFERROR(AJ117-AI117,"--") -> 14 | AL121: =IFERROR(AL117-AJ117,"--") -> 24 | AM121: =IFERROR(AM117-AL117,"--") -> 39 | AN121: =IFERROR(AN117-AM117,"--") -> 78 | AO121: =IFERROR(AO117-AN117,"--") -> 4 | AQ121: =IFERROR(AQ117-AO117,"--") -> 39 | AR121: =IFERROR(AR117-AQ117,"--") -> 66 | AS121: =IFERROR(AS117-AR117,"--") -> 69
B122: % total | AB122: =IFERROR(AB117/AB$145,"--") -> -- | AC122: =IFERROR(AC117/AC$145,"--") -> -- | AD122: =IFERROR(AD117/AD$145,"--") -> 0.14440238 | AE122: =IFERROR(AE117/AE$145,"--") -> 0.14632903 | AF122: =IFERROR(AF117/AF$145,"--") -> 0.14632903 | AG122: =IFERROR(AG117/AG$145,"--") -> 0.1437401 | AH122: =IFERROR(AH117/AH$145,"--") -> 0.13890975 | AI122: =IFERROR(AI117/AI$145,"--") -> 0.13637034 | ... AS122: =IFERROR(AS117/AS$145,"--") -> 0.13942148
...

Sheet IS (GAAP)
B2: Snowflake Inc.
B3: Fiscal Year Ends Jan. 31
B4: ($ millions, except per share amounts)
C6: =Dates!M3 -> 2018 (A) | H6: =Dates!R3 -> 2019 (A) | M6: =Dates!W3 -> 2020 (A) | R6: =Dates!AB3 -> 2021 (A) | W6: =Dates!AG3 -> 2022 (A) | AB6: =Dates!AL3 -> 2023 (A) | AG6: =Dates!AQ3 -> 2024 (A) | AL6: =Dates!AV3 -> 2025 (A) | AQ6: =Dates!BA3 -> 2026 (E) | AV6: =Dates!BF3 -> 2027 (E) | BA6: =Dates!BK3 -> 2028 (E) | BF6: =Dates!BP3 -> 2029 (E) | BK6: =Dates!BU3 -> 2030 (E)
C7: =Dates!M4 -> 1Q18 (A) | D7: =Dates!N4 -> 2Q18 (A) | E7: =Dates!O4 -> 3Q18 (A) | F7: =Dates!P4 -> 4Q18 (A) | G7: =Dates!Q4 -> FY18 (A) | H7: =Dates!R4 -> 1Q19 (A) | I7: =Dates!S4 -> 2Q19 (A) | J7: =Dates!T4 -> 3Q19 (A) | ... BO7: =Dates!BY4 -> FY30 (E)
C8: =Dates!M5 -> 42855 | D8: =Dates!N5 -> 42947 | E8: =Dates!O5 -> 43039 | F8: =Dates!P5 -> 43131 | G8: =Dates!Q5 -> 43131 | H8: =Dates!R5 -> 43220 | I8: =Dates!S5 -> 43312 | J8: =Dates!T5 -> 43404 | ... BO8: =Dates!BY5 -> 47514
B10: Total Revenue | C10: =SUM(C14,C19) -> 0 | D10: =SUM(D14,D19) -> 0 | E10: =SUM(E14,E19) -> 0 | F10: =SUM(F14,F19) -> 0 | G10: =SUM(C10:F10) -> 0 | H10: =SUM(H14,H19) -> 13.403 | I10: =SUM(I14,I19) -> 17.905 | J10: =SUM(J14,J19) -> 28.68 | K10: =SUM(K14,K19) -> 36.678 | L10: =SUM(H10:K10) -> 96.666 | M10: =SUM(M14,M19) -> 43.705 | N10: =SUM(N14,N19) -> 60.339 | O10: =SUM(O14,O19) -> 73.012 | P10: =SUM(P14,P19) -> 87.692 | Q10: =SUM(M10:P10) -> 264.748 | R10: =SUM(R14,R19) -> 108.815 | S10: =SUM(S14,S19) -> 133.145 | T10: =SUM(T14,T19) -> 159.624 | U10: =SUM(U14,U19) -> 190.465 | V10: =SUM(R10:U10) -> 592.049 | W10: =SUM(W14,W19) -> 228.914 | X10: =SUM(X14,X19) -> 272.198 | Y10: =SUM(Y14,Y19) -> 334.441 | Z10: =SUM(Z14,Z19) -> 383.774 | AA10: =SUM(W10:Z10) -> 1219.327 | AB10: =SUM(AB14,AB19) -> 422.371 | AC10: =SUM(AC14,AC19) -> 497.248 | AD10: =SUM(AD14,AD19) -> 557.028 | AE10: =SUM(AE14,AE19) -> 589.012 | AF10: =SUM(AB10:AE10) -> 2065.659 | AG10: =SUM(AG14,AG19) -> 623.599 | AH10: =SUM(AH14,AH19) -> 674.018 | AI10: =SUM(AI14,AI19) -> 734.173 | AJ10: =SUM(AJ14,AJ19) -> 774.699 | AK10: =SUM(AG10:AJ10) -> 2806.489 | AL10: =SUM(AL14,AL19) -> 828.709 | AM10: =SUM(AM14,AM19) -> 868.823 | AN10: =SUM(AN14,AN19) -> 942.094 | AO10: =SUM(AO14,AO19) -> 986.77 | AP10: =SUM(AL10:AO10) -> 3626.396 | AQ10: =SUM(AQ14,AQ19) -> 1042.074 | AR10: =SUM(AR14,AR19) -> 1144.969 | AS10: =SUM(AS14,AS19) -> 1212.909 | AT10: =SUM(AT14,AT19) -> 1248.8031 | AU10: =SUM(AQ10:AT10) -> 4648.7551 | AV10: =SUM(AV14,AV19) -> 1313.011 | AW10: =SUM(AW14,AW19) -> 1415.0354 | AX10: =SUM(AX14,AX19) -> 1502.3143 | AY10: =SUM(AY14,AY19) -> 1549.2272 | AZ10: =SUM(AV10:AY10) -> 5779.5879 | BA10: =SUM(BA14,BA19) -> 1629.2553 | BB10: =SUM(BB14,BB19) -> 1760.8179 | BC10: =SUM(BC14,BC19) -> 1874.5414 | BD10: =SUM(BD14,BD19) -> 1913.7314 | BE10: =SUM(BA10:BD10) -> 7178.346 | BF10: =SUM(BF14,BF19) -> 1996.5102 | BG10: =SUM(BG14,BG19) -> 2152.728 | BH10: =SUM(BH14,BH19) -> 2332.7606 | BI10: =SUM(BI14,BI19) -> 2391.9909 | BJ10: =SUM(BF10:BI10) -> 8873.9896 | BK10: =SUM(BK14,BK19) -> 2482.3192 | BL10: =SUM(BL14,BL19) -> 2642.7389 | BM10: =SUM(BM14,BM19) -> 2883.1165 | BN10: =SUM(BN14,BN19) -> 2925.8128 | BO10: =SUM(BK10:BN10) -> 10933.987
B11: % yoy | C11: -- | D11: -- | E11: -- | F11: -- | G11: -- | H11: =IFERROR(H10/C10-1,"--") -> -- | I11: =IFERROR(I10/D10-1,"--") -> -- | J11: =IFERROR(J10/E10-1,"--") -> -- | K11: =IFERROR(K10/F10-1,"--") -> -- | L11: =IFERROR(L10/G10-1,"--") -> -- | M11: =IFERROR(M10/H10-1,"--") -> 2.2608371 | N11: =IFERROR(N10/I10-1,"--") -> 2.3699525 | O11: =IFERROR(O10/J10-1,"--") -> 1.5457462 | ... BO11: =IFERROR(BO10/BJ10-1,"--") -> 0.23213886
B12: % qoq | C12: -- | D12: =IFERROR(D10/C10-1,"--") -> -- | E12: =IFERROR(E10/D10-1,"--") -> -- | F12: =IFERROR(F10/E10-1,"--") -> -- | H12: =IFERROR(H10/F10-1,"--") -> -- | I12: =IFERROR(I10/H10-1,"--") -> 0.33589495 | J12: =IFERROR(J10/I10-1,"--") -> 0.60178721 | K12: =IFERROR(K10/J10-1,"--") -> 0.27887029 | M12: =IFERROR(M10/K10-1,"--") -> 0.19158624 | N12: =IFERROR(N10/M10-1,"--") -> 0.38059719 | O12: =IFERROR(O10/N10-1,"--") -> 0.21003 | P12: =IFERROR(P10/O10-1,"--") -> 0.20106284 | R12: =IFERROR(R10/P10-1,"--") -> 0.24087716 | S12: =IFERROR(S10/R10-1,"--") -> 0.2235905 | T12: =IFERROR(T10/S10-1,"--") -> 0.19887341 | U12: =IFERROR(U10/T10-1,"--") -> 0.19321029 | W12: =IFERROR(W10/U10-1,"--") -> 0.20186911 | X12: =IFERROR(X10/W10-1,"--") -> 0.18908411 | Y12: =IFERROR(Y10/X10-1,"--") -> 0.2286681 | Z12: =IFERROR(Z10/Y10-1,"--") -> 0.14750883 | AB12: =IFERROR(AB10/Z10-1,"--") -> 0.10057221 | AC12: =IFERROR(AC10/AB10-1,"--") -> 0.1772778 | AD12: =IFERROR(AD10/AC10-1,"--") -> 0.1202217 | AE12: =IFERROR(AE10/AD10-1,"--") -> 0.057419017 | AG12: =IFERROR(AG10/AE10-1,"--") -> 0.058720366 | AH12: =IFERROR(AH10/AG10-1,"--") -> 0.080851637 | AI12: =IFERROR(AI10/AH10-1,"--") -> 0.089248358 | AJ12: =IFERROR(AJ10/AI10-1,"--") -> 0.055199524 | AL12: =IFERROR(AL10/AJ10-1,"--") -> 0.0697174 | AM12: =IFERROR(AM10/AL10-1,"--") -> 0.048405411 | AN12: =IFERROR(AN10/AM10-1,"--") -> 0.084333633 | AO12: =IFERROR(AO10/AN10-1,"--") -> 0.047422019 | AQ12: =IFERROR(AQ10/AO10-1,"--") -> 0.056045482 | AR12: =IFERROR(AR10/AQ10-1,"--") -> 0.098740588 | AS12: =IFERROR(AS10/AR10-1,"--") -> 0.059337851 | AT12: =IFERROR(AT10/AS10-1,"--") -> 0.029593363 | AV12: =IFERROR(AV10/AT10-1,"--") -> 0.051415566 | AW12: =IFERROR(AW10/AV10-1,"--") -> 0.077702662 | AX12: =IFERROR(AX10/AW10-1,"--") -> 0.061679661 | AY12: =IFERROR(AY10/AX10-1,"--") -> 0.031227037 | BA12: =IFERROR(BA10/AY10-1,"--") -> 0.051656838 | BB12: =IFERROR(BB10/BA10-1,"--") -> 0.080750139 | BC12: =IFERROR(BC10/BB10-1,"--") -> 0.06458557 | BD12: =IFERROR(BD10/BC10-1,"--") -> 0.020906453 | BF12: =IFERROR(BF10/BD10-1,"--") -> 0.043255196 | BG12: =IFERROR(BG10/BF10-1,"--") -> 0.078245432 | BH12: =IFERROR(BH10/BG10-1,"--") -> 0.08362997 | BI12: =IFERROR(BI10/BH10-1,"--") -> 0.025390643 | BK12: =IFERROR(BK10/BI10-1,"--") -> 0.037762815 | BL12: =IFERROR(BL10/BK10-1,"--") -> 0.064624957 | BM12: =IFERROR(BM10/BL10-1,"--") -> 0.090957753 | BN12: =IFERROR(BN10/BM10-1,"--") -> 0.014809061
A14: TREV | B14: Product Revenue | G14: =SUM(C14:F14) -> 0 | H14: 13.186 | I14: 17.675 | J14: 28.457 | K14: 36.365 | L14: =SUM(H14:K14) -> 95.683 | M14: 42.766 | N14: 57.818 | O14: 69.213 | P14: 82.432 | Q14: =SUM(M14:P14) -> 252.229 | R14: 101.817 | S14: 125.216 | T14: 148.473 | U14: 178.288 | V14: =SUM(R14:U14) -> 553.794 | W14: 213.83 | X14: 254.623 | Y14: 312.458 | Z14: 359.558 | AA14: =SUM(W14:Z14) -> 1140.469 | AB14: 394.434 | AC14: 466.268 | AD14: 522.752 | AE14: 555.329 | AF14: =SUM(AB14:AE14) -> 1938.783 | AG14: 590.072 | AH14: 640.209 | AI14: 698.478 | AJ14: 738.09 | AK14: =SUM(AG14:AJ14) -> 2666.849 | AL14: 789.587 | AM14: 829.25 | AN14: 900.282 | AO14: 943.303 | AP14: =SUM(AL14:AO14) -> 3462.422 | AQ14: 996.813 | AR14: 1090.496 | AS14: 1158.377 | AT14: ='Revenue Build'!AT15 -> 1198.816 | AU14: =SUM(AQ14:AT14) -> 4444.502 | AV14: ='Revenue Build'!AV15 -> 1261.6397 | AW14: ='Revenue Build'!AW15 -> 1353.2086 | AX14: ='Revenue Build'!AX15 -> 1440.4205 | AY14: ='Revenue Build'!AY15 -> 1492.4918 | AZ14: =SUM(AV14:AY14) -> 5547.7607 | BA14: ='Revenue Build'!BA15 -> 1571.2058 | BB14: ='Revenue Build'!BB15 -> 1690.9536 | BC14: ='Revenue Build'!BC15 -> 1804.6013 | BD14: ='Revenue Build'!BD15 -> 1849.6205 | BE14: =SUM(BA14:BD14) -> 6916.3812 | BF14: ='Revenue Build'!BF15 -> 1931.2045 | BG14: ='Revenue Build'!BG15 -> 2074.1306 | BH14: ='Revenue Build'!BH15 -> 2254.078 | BI14: ='Revenue Build'!BI15 -> 2319.8661 | BJ14: =SUM(BF14:BI14) -> 8579.2792 | BK14: ='Revenue Build'!BK15 -> 2408.8503 | BL14: ='Revenue Build'!BL15 -> 2554.3169 | BM14: ='Revenue Build'!BM15 -> 2794.5987 | BN14: ='Revenue Build'!BN15 -> 2844.6724 | BO14: =SUM(BK14:BN14) -> 10602.438
A15: TREVYY | B15: % yoy | C15: -- | D15: -- | E15: -- | F15: -- | G15: -- | H15: =IFERROR(H14/C14-1,"--") -> -- | I15: =IFERROR(I14/D14-1,"--") -> -- | J15: =IFERROR(J14/E14-1,"--") -> -- | K15: =IFERROR(K14/F14-1,"--") -> -- | L15: =IFERROR(L14/G14-1,"--") -> -- | M15: =IFERROR(M14/H14-1,"--") -> 2.2432883 | N15: =IFERROR(N14/I14-1,"--") -> 2.271174 | O15: =IFERROR(O14/J14-1,"--") -> 1.4321959 | ... BO15: =IFERROR(BO14/BJ14-1,"--") -> 0.23581923
A16: TREVQQ | B16: % qoq | C16: -- | D16: =IFERROR(D14/C14-1,"--") -> -- | E16: =IFERROR(E14/D14-1,"--") -> -- | F16: =IFERROR(F14/E14-1,"--") -> -- | H16: =IFERROR(H14/F14-1,"--") -> -- | I16: =IFERROR(I14/H14-1,"--") -> 0.34043683 | J16: =IFERROR(J14/I14-1,"--") -> 0.61001414 | K16: =IFERROR(K14/J14-1,"--") -> 0.27789296 | M16: =IFERROR(M14/K14-1,"--") -> 0.1760209 | N16: =IFERROR(N14/M14-1,"--") -> 0.35196184 | O16: =IFERROR(O14/N14-1,"--") -> 0.19708395 | P16: =IFERROR(P14/O14-1,"--") -> 0.19099013 | R16: =IFERROR(R14/P14-1,"--") -> 0.23516353 | S16: =IFERROR(S14/R14-1,"--") -> 0.22981427 | T16: =IFERROR(T14/S14-1,"--") -> 0.18573505 | U16: =IFERROR(U14/T14-1,"--") -> 0.20081092 | W16: =IFERROR(W14/U14-1,"--") -> 0.19935161 | X16: =IFERROR(X14/W14-1,"--") -> 0.19077304 | Y16: =IFERROR(Y14/X14-1,"--") -> 0.22713973 | Z16: =IFERROR(Z14/Y14-1,"--") -> 0.15074026 | AB16: =IFERROR(AB14/Z14-1,"--") -> 0.096996868 | AC16: =IFERROR(AC14/AB14-1,"--") -> 0.18211919 | AD16: =IFERROR(AD14/AC14-1,"--") -> 0.12114063 | AE16: =IFERROR(AE14/AD14-1,"--") -> 0.062318269 | AG16: =IFERROR(AG14/AE14-1,"--") -> 0.062562913 | AH16: =IFERROR(AH14/AG14-1,"--") -> 0.084967597 | AI16: =IFERROR(AI14/AH14-1,"--") -> 0.09101559 | AJ16: =IFERROR(AJ14/AI14-1,"--") -> 0.056711879 | AL16: =IFERROR(AL14/AJ14-1,"--") -> 0.069770624 | AM16: =IFERROR(AM14/AL14-1,"--") -> 0.05023259 | AN16: =IFERROR(AN14/AM14-1,"--") -> 0.085658125 | AO16: =IFERROR(AO14/AN14-1,"--") -> 0.047786138 | AQ16: =IFERROR(AQ14/AO14-1,"--") -> 0.056726206 | AR16: =IFERROR(AR14/AQ14-1,"--") -> 0.093982522 | AS16: =IFERROR(AS14/AR14-1,"--") -> 0.062247821 | AT16: =IFERROR(AT14/AS14-1,"--") -> 0.034910056 | AV16: =IFERROR(AV14/AT14-1,"--") -> 0.052404815 | AW16: =IFERROR(AW14/AV14-1,"--") -> 0.07257922 | AX16: =IFERROR(AX14/AW14-1,"--") -> 0.064448262 | AY16: =IFERROR(AY14/AX14-1,"--") -> 0.036150099 | BA16: =IFERROR(BA14/AY14-1,"--") -> 0.052739975 | BB16: =IFERROR(BB14/BA14-1,"--") -> 0.076213912 | BC16: =IFERROR(BC14/BB14-1,"--") -> 0.067209272 | BD16: =IFERROR(BD14/BC14-1,"--") -> 0.024946859 | BF16: =IFERROR(BF14/BD14-1,"--") -> 0.044108526 | BG16: =IFERROR(BG14/BF14-1,"--") -> 0.074008783 | BH16: =IFERROR(BH14/BG14-1,"--") -> 0.086758012 | BI16: =IFERROR(BI14/BH14-1,"--") -> 0.029186237 | BK16: =IFERROR(BK14/BI14-1,"--") -> 0.038357458 | BL16: =IFERROR(BL14/BK14-1,"--") -> 0.060388394 | BM16: =IFERROR(BM14/BL14-1,"--") -> 0.094068918 | BN16: =IFERROR(BN14/BM14-1,"--") -> 0.017918041
B17: % total revenue | C17: =IFERROR(C14/C$10,"--") -> -- | D17: =IFERROR(D14/D$10,"--") -> -- | E17: =IFERROR(E14/E$10,"--") -> -- | F17: =IFERROR(F14/F$10,"--") -> -- | G17: =IFERROR(G14/G$10,"--") -> -- | H17: =IFERROR(H14/H$10,"--") -> 0.98380959 | I17: =IFERROR(I14/I$10,"--") -> 0.98715443 | J17: =IFERROR(J14/J$10,"--") -> 0.99222455 | ... BO17: =IFERROR(BO14/BO$10,"--") -> 0.9696772
A19: TREV | B19: Professional Services & Other Revenue | G19: =SUM(C19:F19) -> 0 | H19: 0.217 | I19: 0.23 | J19: 0.223 | K19: 0.313 | L19: =SUM(H19:K19) -> 0.983 | M19: 0.939 | N19: 2.521 | O19: 3.799 | P19: 5.26 | Q19: =SUM(M19:P19) -> 12.519 | R19: 6.998 | S19: 7.929 | T19: 11.151 | U19: 12.177 | V19: =SUM(R19:U19) -> 38.255 | W19: 15.084 | X19: 17.575 | Y19: 21.983 | Z19: 24.216 | AA19: =SUM(W19:Z19) -> 78.858 | AB19: 27.937 | AC19: 30.98 | AD19: 34.276 | AE19: 33.683 | AF19: =SUM(AB19:AE19) -> 126.876 | AG19: 33.527 | AH19: 33.809 | AI19: 35.695 | AJ19: 36.609 | AK19: =SUM(AG19:AJ19) -> 139.64 | AL19: 39.122 | AM19: 39.573 | AN19: 41.812 | AO19: 43.467 | AP19: =SUM(AL19:AO19) -> 163.974 | AQ19: 45.261 | AR19: 54.473 | AS19: 54.532 | AT19: ='Revenue Build'!AT51 -> 49.98705 | AU19: =SUM(AQ19:AT19) -> 204.25305 | AV19: ='Revenue Build'!AV51 -> 51.371235 | AW19: ='Revenue Build'!AW51 -> 61.826855 | AX19: ='Revenue Build'!AX51 -> 61.89382 | AY19: ='Revenue Build'!AY51 -> 56.735302 | AZ19: =SUM(AV19:AY19) -> 231.82721 | BA19: ='Revenue Build'!BA51 -> 58.049496 | BB19: ='Revenue Build'!BB51 -> 69.864346 | BC19: ='Revenue Build'!BC51 -> 69.940017 | BD19: ='Revenue Build'!BD51 -> 64.110891 | BE19: =SUM(BA19:BD19) -> 261.96475 | BF19: ='Revenue Build'!BF51 -> 65.305682 | BG19: ='Revenue Build'!BG51 -> 78.597389 | BH19: ='Revenue Build'!BH51 -> 78.682519 | BI19: ='Revenue Build'!BI51 -> 72.124752 | BJ19: =SUM(BF19:BI19) -> 294.71034 | BK19: ='Revenue Build'!BK51 -> 73.468893 | BL19: ='Revenue Build'!BL51 -> 88.422063 | BM19: ='Revenue Build'!BM51 -> 88.517834 | BN19: ='Revenue Build'!BN51 -> 81.140346 | BO19: =SUM(BK19:BN19) -> 331.54914
A20: TREVYY | B20: % yoy | C20: -- | D20: -- | E20: -- | F20: -- | G20: -- | H20: =IFERROR(H19/C19-1,"--") -> -- | I20: =IFERROR(I19/D19-1,"--") -> -- | J20: =IFERROR(J19/E19-1,"--") -> -- | K20: =IFERROR(K19/F19-1,"--") -> -- | L20: =IFERROR(L19/G19-1,"--") -> -- | M20: =IFERROR(M19/H19-1,"--") -> 3.3271889 | N20: =IFERROR(N19/I19-1,"--") -> 9.9608696 | O20: =IFERROR(O19/J19-1,"--") -> 16.035874 | ... BO20: =IFERROR(BO19/BJ19-1,"--") -> 0.125
A21: TREVQQ | B21: % qoq | C21: -- | D21: =IFERROR(D19/C19-1,"--") -> -- | E21: =IFERROR(E19/D19-1,"--") -> -- | F21: =IFERROR(F19/E19-1,"--") -> -- | H21: =IFERROR(H19/F19-1,"--") -> -- | I21: =IFERROR(I19/H19-1,"--") -> 0.059907834 | J21: =IFERROR(J19/I19-1,"--") -> -0.030434783 | K21: =IFERROR(K19/J19-1,"--") -> 0.40358744 | M21: =IFERROR(M19/K19-1,"--") -> 2 | N21: =IFERROR(N19/M19-1,"--") -> 1.684771 | O21: =IFERROR(O19/N19-1,"--") -> 0.50694169 | P21: =IFERROR(P19/O19-1,"--") -> 0.38457489 | R21: =IFERROR(R19/P19-1,"--") -> 0.33041825 | S21: =IFERROR(S19/R19-1,"--") -> 0.13303801 | T21: =IFERROR(T19/S19-1,"--") -> 0.40635641 | U21: =IFERROR(U19/T19-1,"--") -> 0.092009685 | W21: =IFERROR(W19/U19-1,"--") -> 0.23872875 | X21: =IFERROR(X19/W19-1,"--") -> 0.16514187 | Y21: =IFERROR(Y19/X19-1,"--") -> 0.25081081 | Z21: =IFERROR(Z19/Y19-1,"--") -> 0.10157849 | AB21: =IFERROR(AB19/Z19-1,"--") -> 0.15365874 | AC21: =IFERROR(AC19/AB19-1,"--") -> 0.10892365 | AD21: =IFERROR(AD19/AC19-1,"--") -> 0.10639122 | AE21: =IFERROR(AE19/AD19-1,"--") -> -0.017300735 | AG21: =IFERROR(AG19/AE19-1,"--") -> -0.0046314164 | AH21: =IFERROR(AH19/AG19-1,"--") -> 0.0084111313 | AI21: =IFERROR(AI19/AH19-1,"--") -> 0.055783963 | AJ21: =IFERROR(AJ19/AI19-1,"--") -> 0.025605827 | AL21: =IFERROR(AL19/AJ19-1,"--") -> 0.068644322 | AM21: =IFERROR(AM19/AL19-1,"--") -> 0.01152804 | AN21: =IFERROR(AN19/AM19-1,"--") -> 0.056578981 | AO21: =IFERROR(AO19/AN19-1,"--") -> 0.039581938 | AQ21: =IFERROR(AQ19/AO19-1,"--") -> 0.04127269 | AR21: =IFERROR(AR19/AQ19-1,"--") -> 0.20353063 | AS21: =IFERROR(AS19/AR19-1,"--") -> 0.0010831054 | AT21: =IFERROR(AT19/AS19-1,"--") -> -0.083344642 | AV21: =IFERROR(AV19/AT19-1,"--") -> 0.027690872 | AW21: =IFERROR(AW19/AV19-1,"--") -> 0.20353063 | AX21: =IFERROR(AX19/AW19-1,"--") -> 0.0010831054 | AY21: =IFERROR(AY19/AX19-1,"--") -> -0.083344642 | BA21: =IFERROR(BA19/AY19-1,"--") -> 0.023163599 | BB21: =IFERROR(BB19/BA19-1,"--") -> 0.20353063 | BC21: =IFERROR(BC19/BB19-1,"--") -> 0.0010831054 | BD21: =IFERROR(BD19/BC19-1,"--") -> -0.083344642 | BF21: =IFERROR(BF19/BD19-1,"--") -> 0.018636327 | BG21: =IFERROR(BG19/BF19-1,"--") -> 0.20353063 | BH21: =IFERROR(BH19/BG19-1,"--") -> 0.0010831054 | BI21: =IFERROR(BI19/BH19-1,"--") -> -0.083344642 | BK21: =IFERROR(BK19/BI19-1,"--") -> 0.018636327 | BL21: =IFERROR(BL19/BK19-1,"--") -> 0.20353063 | BM21: =IFERROR(BM19/BL19-1,"--") -> 0.0010831054 | BN21: =IFERROR(BN19/BM19-1,"--") -> -0.083344642
B22: % total revenue | C22: =IFERROR(C19/C$10,"--") -> -- | D22: =IFERROR(D19/D$10,"--") -> -- | E22: =IFERROR(E19/E$10,"--") -> -- | F22: =IFERROR(F19/F$10,"--") -> -- | G22: =IFERROR(G19/G$10,"--") -> -- | H22: =IFERROR(H19/H$10,"--") -> 0.016190405 | I22: =IFERROR(I19/I$10,"--") -> 0.012845574 | J22: =IFERROR(J19/J$10,"--") -> 0.0077754533 | ... BO22: =IFERROR(BO19/BO$10,"--") -> 0.030322802
B24: Total Cost of Revenue | C24: =SUM(C28,C33) -> 0 | D24: =SUM(D28,D33) -> 0 | E24: =SUM(E28,E33) -> 0 | F24: =SUM(F28,F33) -> 0 | G24: =SUM(C24:F24) -> 0 | H24: =SUM(H28,H33) -> 7.439 | I24: =SUM(I28,I33) -> 9.735 | J24: =SUM(J28,J33) -> 13.824 | K24: =SUM(K28,K33) -> 20.389 | L24: =SUM(H24:K24) -> 51.387 | M24: =SUM(M28,M33) -> 24.038 | N24: =SUM(N28,N33) -> 28.508 | O24: =SUM(O28,O33) -> 29.489 | P24: =SUM(P28,P33) -> 34.522 | Q24: =SUM(M24:P24) -> 116.557 | R24: =SUM(R28,R33) -> 42.557 | S24: =SUM(S28,S33) -> 50.446 | T24: =SUM(T28,T33) -> 66.681 | U24: =SUM(U28,U33) -> 82.904 | V24: =SUM(R24:U24) -> 242.588 | W24: =SUM(W28,W33) -> 97.346 | X24: =SUM(X28,X33) -> 106.121 | Y24: =SUM(Y28,Y33) -> 120.786 | Z24: =SUM(Z28,Z33) -> 134.18 | AA24: =SUM(W24:Z24) -> 458.433 | AB24: =SUM(AB28,AB33) -> 147.93 | AC24: =SUM(AC28,AC33) -> 173.232 | AD24: =SUM(AD28,AD33) -> 190.721 | AE24: =SUM(AE28,AE33) -> 205.657 | AF24: =SUM(AB24:AE24) -> 717.54 | AG24: =SUM(AG28,AG33) -> 209.414 | AH24: =SUM(AH28,AH33) -> 218.392 | AI24: =SUM(AI28,AI33) -> 228.948 | AJ24: =SUM(AJ28,AJ33) -> 241.804 | AK24: =SUM(AG24:AJ24) -> 898.558 | AL24: =SUM(AL28,AL33) -> 272.517 | AM24: =SUM(AM28,AM33) -> 288.078 | AN24: =SUM(AN28,AN33) -> 320.894 | AO24: =SUM(AO28,AO33) -> 333.184 | AP24: =SUM(AL24:AO24) -> 1214.673 | AQ24: =SUM(AQ28,AQ33) -> 348.786 | AR24: =SUM(AR28,AR33) -> 371.815 | AS24: =SUM(AS28,AS33) -> 390.873 | AT24: =SUM(AT28,AT33) -> 419.05282 | AU24: =SUM(AQ24:AT24) -> 1530.5268 | AV24: =SUM(AV28,AV33) -> 411.60689 | AW24: =SUM(AW28,AW33) -> 433.85455 | AX24: =SUM(AX28,AX33) -> 462.03589 | AY24: =SUM(AY28,AY33) -> 496.11632 | AZ24: =SUM(AV24:AY24) -> 1803.6137 | BA24: =SUM(BA28,BA33) -> 482.35201 | BB24: =SUM(BB28,BB33) -> 509.02856 | BC24: =SUM(BC28,BC33) -> 544.31546 | BD24: =SUM(BD28,BD33) -> 581.43991 | BE24: =SUM(BA24:BD24) -> 2117.1359 | BF24: =SUM(BF28,BF33) -> 558.81374 | BG24: =SUM(BG28,BG33) -> 587.69456 | BH24: =SUM(BH28,BH33) -> 639.60199 | BI24: =SUM(BI28,BI33) -> 688.70756 | BJ24: =SUM(BF24:BI24) -> 2474.8179 | BK24: =SUM(BK28,BK33) -> 662.84769 | BL24: =SUM(BL28,BL33) -> 687.59166 | BM24: =SUM(BM28,BM33) -> 753.64391 | BN24: =SUM(BN28,BN33) -> 806.45184 | BO24: =SUM(BK24:BN24) -> 2910.5351
B25: % yoy | C25: -- | D25: -- | E25: -- | F25: -- | G25: =IFERROR(G24/B24-1,"--") -> -- | H25: =IFERROR(H24/C24-1,"--") -> -- | I25: =IFERROR(I24/D24-1,"--") -> -- | J25: =IFERROR(J24/E24-1,"--") -> -- | K25: =IFERROR(K24/F24-1,"--") -> -- | L25: =IFERROR(L24/G24-1,"--") -> -- | M25: =IFERROR(M24/H24-1,"--") -> 2.2313483 | N25: =IFERROR(N24/I24-1,"--") -> 1.9284027 | ... BO25: =IFERROR(BO24/BJ24-1,"--") -> 0.17606033
B26: % qoq | C26: -- | D26: =IFERROR(D24/C24-1,"--") -> -- | E26: =IFERROR(E24/D24-1,"--") -> -- | F26: =IFERROR(F24/E24-1,"--") -> -- | H26: =IFERROR(H24/F24-1,"--") -> -- | I26: =IFERROR(I24/H24-1,"--") -> 0.30864363 | J26: =IFERROR(J24/I24-1,"--") -> 0.42003082 | K26: =IFERROR(K24/J24-1,"--") -> 0.47489873 | M26: =IFERROR(M24/K24-1,"--") -> 0.17896905 | N26: =IFERROR(N24/M24-1,"--") -> 0.18595557 | O26: =IFERROR(O24/N24-1,"--") -> 0.034411393 | P26: =IFERROR(P24/O24-1,"--") -> 0.17067381 | R26: =IFERROR(R24/P24-1,"--") -> 0.23275013 | S26: =IFERROR(S24/R24-1,"--") -> 0.18537491 | T26: =IFERROR(T24/S24-1,"--") -> 0.32182928 | U26: =IFERROR(U24/T24-1,"--") -> 0.24329269 | W26: =IFERROR(W24/U24-1,"--") -> 0.17420149 | X26: =IFERROR(X24/W24-1,"--") -> 0.090142379 | Y26: =IFERROR(Y24/X24-1,"--") -> 0.13819131 | Z26: =IFERROR(Z24/Y24-1,"--") -> 0.11089033 | AB26: =IFERROR(AB24/Z24-1,"--") -> 0.10247429 | AC26: =IFERROR(AC24/AB24-1,"--") -> 0.17104036 | AD26: =IFERROR(AD24/AC24-1,"--") -> 0.1009571 | AE26: =IFERROR(AE24/AD24-1,"--") -> 0.078313348 | AG26: =IFERROR(AG24/AE24-1,"--") -> 0.018268282 | AH26: =IFERROR(AH24/AG24-1,"--") -> 0.042872014 | AI26: =IFERROR(AI24/AH24-1,"--") -> 0.048335104 | AJ26: =IFERROR(AJ24/AI24-1,"--") -> 0.056152489 | AL26: =IFERROR(AL24/AJ24-1,"--") -> 0.1270161 | AM26: =IFERROR(AM24/AL24-1,"--") -> 0.057101025 | AN26: =IFERROR(AN24/AM24-1,"--") -> 0.11391359 | AO26: =IFERROR(AO24/AN24-1,"--") -> 0.038299251 | AQ26: =IFERROR(AQ24/AO24-1,"--") -> 0.046826978 | AR26: =IFERROR(AR24/AQ24-1,"--") -> 0.066026159 | AS26: =IFERROR(AS24/AR24-1,"--") -> 0.051256673 | AT26: =IFERROR(AT24/AS24-1,"--") -> 0.072094569 | AV26: =IFERROR(AV24/AT24-1,"--") -> -0.017768473 | AW26: =IFERROR(AW24/AV24-1,"--") -> 0.054050746 | AX26: =IFERROR(AX24/AW24-1,"--") -> 0.064955733 | AY26: =IFERROR(AY24/AX24-1,"--") -> 0.073761419 | BA26: =IFERROR(BA24/AY24-1,"--") -> -0.027744105 | BB26: =IFERROR(BB24/BA24-1,"--") -> 0.055305149 | BC26: =IFERROR(BC24/BB24-1,"--") -> 0.069322036 | BD26: =IFERROR(BD24/BC24-1,"--") -> 0.068203928 | BF26: =IFERROR(BF24/BD24-1,"--") -> -0.038914021 | BG26: =IFERROR(BG24/BF24-1,"--") -> 0.051682356 | BH26: =IFERROR(BH24/BG24-1,"--") -> 0.088323839 | BI26: =IFERROR(BI24/BH24-1,"--") -> 0.076775186 | BK26: =IFERROR(BK24/BI24-1,"--") -> -0.037548395 | BL26: =IFERROR(BL24/BK24-1,"--") -> 0.037329799 | BM26: =IFERROR(BM24/BL24-1,"--") -> 0.096063179 | BN26: =IFERROR(BN24/BM24-1,"--") -> 0.070070142
A28: TREV | B28: Cost of Product Revenue | G28: =SUM(C28:F28) -> 0 | H28: 6.945 | I28: 8.211 | J28: 11.141 | K28: 15.101 | L28: =SUM(H28:K28) -> 41.398 | M28: 19.637 | N28: 23.562 | O28: 24.646 | P28: 28.777 | Q28: =SUM(M28:P28) -> 96.622 | R28: 35.533 | S28: 42.716 | T28: 51.816 | U28: 63.77 | V28: =SUM(R28:U28) -> 193.835 | W28: 72.08 | X28: 81.048 | Y28: 92.292 | Z28: 102.397 | AA28: =SUM(W28:Z28) -> 347.817 | AB28: 111.411 | AC28: 131.606 | AD28: 145.929 | AE28: 158.601 | AF28: =SUM(AB28:AE28) -> 547.547 | AG28: 159.378 | AH28: 169.046 | AI28: 180 | AJ28: 192.776 | AK28: =SUM(AG28:AJ28) -> 701.2 | AL28: 219.657 | AM28: 235.582 | AN28: 263.622 | AO28: 273.208 | AP28: =SUM(AL28:AO28) -> 992.069 | AQ28: 285.276 | AR28: 302.316 | AS28: 320.81 | AT28: ='IS (Non-GAAP)'!AT28+'IS (Non-GAAP)'!AT95+'IS (Non-GAAP)'!AT113 -> 354.63743 | AU28: =SUM(AQ28:AT28) -> 1263.0394 | AV28: ='IS (Non-GAAP)'!AV28+'IS (Non-GAAP)'!AV95+'IS (Non-GAAP)'!AV113 -> 346.90912 | AW28: ='IS (Non-GAAP)'!AW28+'IS (Non-GAAP)'!AW95+'IS (Non-GAAP)'!AW113 -> 359.36958 | AX28: ='IS (Non-GAAP)'!AX28+'IS (Non-GAAP)'!AX95+'IS (Non-GAAP)'!AX113 -> 388.16851 | AY28: ='IS (Non-GAAP)'!AY28+'IS (Non-GAAP)'!AY95+'IS (Non-GAAP)'!AY113 -> 428.4082 | AZ28: =SUM(AV28:AY28) -> 1522.8554 | BA28: ='IS (Non-GAAP)'!BA28+'IS (Non-GAAP)'!BA95+'IS (Non-GAAP)'!BA113 -> 414.87579 | BB28: ='IS (Non-GAAP)'!BB28+'IS (Non-GAAP)'!BB95+'IS (Non-GAAP)'!BB113 -> 431.01173 | BC28: ='IS (Non-GAAP)'!BC28+'IS (Non-GAAP)'!BC95+'IS (Non-GAAP)'!BC113 -> 467.48651 | BD28: ='IS (Non-GAAP)'!BD28+'IS (Non-GAAP)'!BD95+'IS (Non-GAAP)'!BD113 -> 512.00681 | BE28: =SUM(BA28:BD28) -> 1825.3808 | BF28: ='IS (Non-GAAP)'!BF28+'IS (Non-GAAP)'!BF95+'IS (Non-GAAP)'!BF113 -> 490.523 | BG28: ='IS (Non-GAAP)'!BG28+'IS (Non-GAAP)'!BG95+'IS (Non-GAAP)'!BG113 -> 508.28983 | BH28: ='IS (Non-GAAP)'!BH28+'IS (Non-GAAP)'!BH95+'IS (Non-GAAP)'!BH113 -> 562.19675 | BI28: ='IS (Non-GAAP)'!BI28+'IS (Non-GAAP)'!BI95+'IS (Non-GAAP)'!BI113 -> 620.03209 | BJ28: =SUM(BF28:BI28) -> 2181.0417 | BK28: ='IS (Non-GAAP)'!BK28+'IS (Non-GAAP)'!BK95+'IS (Non-GAAP)'!BK113 -> 595.4056 | BL28: ='IS (Non-GAAP)'!BL28+'IS (Non-GAAP)'!BL95+'IS (Non-GAAP)'!BL113 -> 608.54561 | BM28: ='IS (Non-GAAP)'!BM28+'IS (Non-GAAP)'!BM95+'IS (Non-GAAP)'!BM113 -> 678.01485 | BN28: ='IS (Non-GAAP)'!BN28+'IS (Non-GAAP)'!BN95+'IS (Non-GAAP)'!BN113 -> 741.05878 | BO28: =SUM(BK28:BN28) -> 2623.0248
A29: TREVYY | B29: % yoy | C29: -- | D29: -- | E29: -- | F29: -- | G29: -- | H29: =IFERROR(H28/C28-1,"--") -> -- | I29: =IFERROR(I28/D28-1,"--") -> -- | J29: =IFERROR(J28/E28-1,"--") -> -- | K29: =IFERROR(K28/F28-1,"--") -> -- | L29: =IFERROR(L28/G28-1,"--") -> -- | M29: =IFERROR(M28/H28-1,"--") -> 1.8275018 | N29: =IFERROR(N28/I28-1,"--") -> 1.8695652 | O29: =IFERROR(O28/J28-1,"--") -> 1.2121892 | ... BO29: =IFERROR(BO28/BJ28-1,"--") -> 0.20264774
A30: TREVQQ | B30: % qoq | C30: -- | D30: =IFERROR(D28/C28-1,"--") -> -- | E30: =IFERROR(E28/D28-1,"--") -> -- | F30: =IFERROR(F28/E28-1,"--") -> -- | H30: =IFERROR(H28/F28-1,"--") -> -- | I30: =IFERROR(I28/H28-1,"--") -> 0.18228942 | J30: =IFERROR(J28/I28-1,"--") -> 0.35683839 | K30: =IFERROR(K28/J28-1,"--") -> 0.35544386 | M30: =IFERROR(M28/K28-1,"--") -> 0.30037746 | N30: =IFERROR(N28/M28-1,"--") -> 0.19987778 | O30: =IFERROR(O28/N28-1,"--") -> 0.046006281 | P30: =IFERROR(P28/O28-1,"--") -> 0.16761341 | R30: =IFERROR(R28/P28-1,"--") -> 0.23477082 | S30: =IFERROR(S28/R28-1,"--") -> 0.20215011 | T30: =IFERROR(T28/S28-1,"--") -> 0.21303493 | U30: =IFERROR(U28/T28-1,"--") -> 0.23070094 | W30: =IFERROR(W28/U28-1,"--") -> 0.13031206 | X30: =IFERROR(X28/W28-1,"--") -> 0.12441731 | Y30: =IFERROR(Y28/X28-1,"--") -> 0.1387326 | Z30: =IFERROR(Z28/Y28-1,"--") -> 0.10948945 | AB30: =IFERROR(AB28/Z28-1,"--") -> 0.088029923 | AC30: =IFERROR(AC28/AB28-1,"--") -> 0.18126576 | AD30: =IFERROR(AD28/AC28-1,"--") -> 0.10883242 | AE30: =IFERROR(AE28/AD28-1,"--") -> 0.086836749 | AG30: =IFERROR(AG28/AE28-1,"--") -> 0.0048990864 | AH30: =IFERROR(AH28/AG28-1,"--") -> 0.060660819 | AI30: =IFERROR(AI28/AH28-1,"--") -> 0.06479893 | AJ30: =IFERROR(AJ28/AI28-1,"--") -> 0.070977778 | AL30: =IFERROR(AL28/AJ28-1,"--") -> 0.13944163 | AM30: =IFERROR(AM28/AL28-1,"--") -> 0.072499397 | AN30: =IFERROR(AN28/AM28-1,"--") -> 0.11902437 | AO30: =IFERROR(AO28/AN28-1,"--") -> 0.036362671 | AQ30: =IFERROR(AQ28/AO28-1,"--") -> 0.044171474 | AR30: =IFERROR(AR28/AQ28-1,"--") -> 0.059731628 | AS30: =IFERROR(AS28/AR28-1,"--") -> 0.0611744 | AT30: =IFERROR(AT28/AS28-1,"--") -> 0.10544381 | AV30: =IFERROR(AV28/AT28-1,"--") -> -0.021792124 | AW30: =IFERROR(AW28/AV28-1,"--") -> 0.035918492 | AX30: =IFERROR(AX28/AW28-1,"--") -> 0.080137362 | AY30: =IFERROR(AY28/AX28-1,"--") -> 0.10366554 | BA30: =IFERROR(BA28/AY28-1,"--") -> -0.031587669 | BB30: =IFERROR(BB28/BA28-1,"--") -> 0.038893439 | BC30: =IFERROR(BC28/BB28-1,"--") -> 0.084625959 | BD30: =IFERROR(BD28/BC28-1,"--") -> 0.095233319 | BF30: =IFERROR(BF28/BD28-1,"--") -> -0.041960003 | BG30: =IFERROR(BG28/BF28-1,"--") -> 0.036220175 | BH30: =IFERROR(BH28/BG28-1,"--") -> 0.10605549 | BI30: =IFERROR(BI28/BH28-1,"--") -> 0.10287384 | BK30: =IFERROR(BK28/BI28-1,"--") -> -0.039718086 | BL30: =IFERROR(BL28/BK28-1,"--") -> 0.022069 | BM30: =IFERROR(BM28/BL28-1,"--") -> 0.11415618 | BN30: =IFERROR(BN28/BM28-1,"--") -> 0.09298312
B31: % gross margins | C31: =IFERROR((C14-C28)/C14,"--") -> -- | D31: =IFERROR((D14-D28)/D14,"--") -> -- | E31: =IFERROR((E14-E28)/E14,"--") -> -- | F31: =IFERROR((F14-F28)/F14,"--") -> -- | G31: =IFERROR((G14-G28)/G14,"--") -> -- | H31: =IFERROR((H14-H28)/H14,"--") -> 0.47330502 | I31: =IFERROR((I14-I28)/I14,"--") -> 0.53544554 | J31: =IFERROR((J14-J28)/J14,"--") -> 0.60849703 | ... BO31: =IFERROR((BO14-BO28)/BO14,"--") -> 0.75260173
A33: TREV | B33: Cost of Professional Services & Other Revenue | G33: =SUM(C33:F33) -> 0 | H33: 0.494 | I33: 1.524 | J33: =13.824-J28 -> 2.683 | K33: =20.389-K28 -> 5.288 | L33: =SUM(H33:K33) -> 9.989 | M33: =24.038-M28 -> 4.401 | N33: =28.508-N28 -> 4.946 | O33: =29.489-O28 -> 4.843 | P33: =34.522-P28 -> 5.745 | Q33: =SUM(M33:P33) -> 19.935 | R33: =42.557-R28 -> 7.024 | S33: =50.446-S28 -> 7.73 | T33: 14.865 | U33: 19.134 | V33: =SUM(R33:U33) -> 48.753 | W33: 25.266 | X33: 25.073 | Y33: 28.494 | Z33: 31.783 | AA33: =SUM(W33:Z33) -> 110.616 | AB33: 36.519 | AC33: 41.626 | AD33: 44.792 | AE33: 47.056 | AF33: =SUM(AB33:AE33) -> 169.993 | AG33: 50.036 | AH33: 49.346 | AI33: 48.948 | AJ33: 49.028 | AK33: =SUM(AG33:AJ33) -> 197.358 | AL33: 52.86 | AM33: 52.496 | AN33: 57.272 | AO33: 59.976 | AP33: =SUM(AL33:AO33) -> 222.604 | AQ33: 63.51 | AR33: 69.499 | AS33: 70.063 | AT33: ='IS (Non-GAAP)'!AT33+'IS (Non-GAAP)'!AT96+'IS (Non-GAAP)'!AT117 -> 64.415393 | AU33: =SUM(AQ33:AT33) -> 267.48739 | AV33: ='IS (Non-GAAP)'!AV33+'IS (Non-GAAP)'!AV96+'IS (Non-GAAP)'!AV117 -> 64.697767 | AW33: ='IS (Non-GAAP)'!AW33+'IS (Non-GAAP)'!AW96+'IS (Non-GAAP)'!AW117 -> 74.484975 | AX33: ='IS (Non-GAAP)'!AX33+'IS (Non-GAAP)'!AX96+'IS (Non-GAAP)'!AX117 -> 73.867385 | AY33: ='IS (Non-GAAP)'!AY33+'IS (Non-GAAP)'!AY96+'IS (Non-GAAP)'!AY117 -> 67.708112 | AZ33: =SUM(AV33:AY33) -> 280.75824 | BA33: ='IS (Non-GAAP)'!BA33+'IS (Non-GAAP)'!BA96+'IS (Non-GAAP)'!BA117 -> 67.476225 | BB33: ='IS (Non-GAAP)'!BB33+'IS (Non-GAAP)'!BB96+'IS (Non-GAAP)'!BB117 -> 78.016829 | BC33: ='IS (Non-GAAP)'!BC33+'IS (Non-GAAP)'!BC96+'IS (Non-GAAP)'!BC117 -> 76.828944 | BD33: ='IS (Non-GAAP)'!BD33+'IS (Non-GAAP)'!BD96+'IS (Non-GAAP)'!BD117 -> 69.433104 | BE33: =SUM(BA33:BD33) -> 291.7551 | BF33: ='IS (Non-GAAP)'!BF33+'IS (Non-GAAP)'!BF96+'IS (Non-GAAP)'!BF117 -> 68.290746 | BG33: ='IS (Non-GAAP)'!BG33+'IS (Non-GAAP)'!BG96+'IS (Non-GAAP)'!BG117 -> 79.404728 | BH33: ='IS (Non-GAAP)'!BH33+'IS (Non-GAAP)'!BH96+'IS (Non-GAAP)'!BH117 -> 77.405242 | BI33: ='IS (Non-GAAP)'!BI33+'IS (Non-GAAP)'!BI96+'IS (Non-GAAP)'!BI117 -> 68.675467 | BJ33: =SUM(BF33:BI33) -> 293.77618 | BK33: ='IS (Non-GAAP)'!BK33+'IS (Non-GAAP)'!BK96+'IS (Non-GAAP)'!BK117 -> 67.442091 | BL33: ='IS (Non-GAAP)'!BL33+'IS (Non-GAAP)'!BL96+'IS (Non-GAAP)'!BL117 -> 79.046056 | BM33: ='IS (Non-GAAP)'!BM33+'IS (Non-GAAP)'!BM96+'IS (Non-GAAP)'!BM117 -> 75.629057 | BN33: ='IS (Non-GAAP)'!BN33+'IS (Non-GAAP)'!BN96+'IS (Non-GAAP)'!BN117 -> 65.393056 | BO33: =SUM(BK33:BN33) -> 287.51026
A34: TREVYY | B34: % yoy | C34: -- | D34: -- | E34: -- | F34: -- | G34: -- | H34: =IFERROR(H33/C33-1,"--") -> -- | I34: =IFERROR(I33/D33-1,"--") -> -- | J34: =IFERROR(J33/E33-1,"--") -> -- | K34: =IFERROR(K33/F33-1,"--") -> -- | L34: =IFERROR(L33/G33-1,"--") -> -- | M34: =IFERROR(M33/H33-1,"--") -> 7.9089069 | N34: =IFERROR(N33/I33-1,"--") -> 2.2454068 | O34: =IFERROR(O33/J33-1,"--") -> 0.80506895 | ... BO34: =IFERROR(BO33/BJ33-1,"--") -> -0.021328896
A35: TREVQQ | B35: % qoq | C35: -- | D35: =IFERROR(D33/C33-1,"--") -> -- | E35: =IFERROR(E33/D33-1,"--") -> -- | F35: =IFERROR(F33/E33-1,"--") -> -- | H35: =IFERROR(H33/F33-1,"--") -> -- | I35: =IFERROR(I33/H33-1,"--") -> 2.0850202 | J35: =IFERROR(J33/I33-1,"--") -> 0.76049869 | K35: =IFERROR(K33/J33-1,"--") -> 0.97092807 | M35: =IFERROR(M33/K33-1,"--") -> -0.16773828 | N35: =IFERROR(N33/M33-1,"--") -> 0.12383549 | O35: =IFERROR(O33/N33-1,"--") -> -0.020824909 | P35: =IFERROR(P33/O33-1,"--") -> 0.18624819 | R35: =IFERROR(R33/P33-1,"--") -> 0.22262837 | S35: =IFERROR(S33/R33-1,"--") -> 0.10051253 | T35: =IFERROR(T33/S33-1,"--") -> 0.92302717 | U35: =IFERROR(U33/T33-1,"--") -> 0.28718466 | W35: =IFERROR(W33/U33-1,"--") -> 0.32047664 | X35: =IFERROR(X33/W33-1,"--") -> -0.007638724 | Y35: =IFERROR(Y33/X33-1,"--") -> 0.13644159 | Z35: =IFERROR(Z33/Y33-1,"--") -> 0.11542781 | AB35: =IFERROR(AB33/Z33-1,"--") -> 0.14901048 | AC35: =IFERROR(AC33/AB33-1,"--") -> 0.13984501 | AD35: =IFERROR(AD33/AC33-1,"--") -> 0.076058233 | AE35: =IFERROR(AE33/AD33-1,"--") -> 0.05054474 | AG35: =IFERROR(AG33/AE33-1,"--") -> 0.0633288 | AH35: =IFERROR(AH33/AG33-1,"--") -> -0.013790071 | AI35: =IFERROR(AI33/AH33-1,"--") -> -0.0080654967 | AJ35: =IFERROR(AJ33/AI33-1,"--") -> 0.0016343875 | AL35: =IFERROR(AL33/AJ33-1,"--") -> 0.078159419 | AM35: =IFERROR(AM33/AL33-1,"--") -> -0.0068861143 | AN35: =IFERROR(AN33/AM33-1,"--") -> 0.09097836 | AO35: =IFERROR(AO33/AN33-1,"--") -> 0.047213298 | AQ35: =IFERROR(AQ33/AO33-1,"--") -> 0.058923569 | AR35: =IFERROR(AR33/AQ33-1,"--") -> 0.09430011 | AS35: =IFERROR(AS33/AR33-1,"--") -> 0.0081152247 | AT35: =IFERROR(AT33/AS33-1,"--") -> -0.080607548 | AV35: =IFERROR(AV33/AT33-1,"--") -> 0.004383643 | AW35: =IFERROR(AW33/AV33-1,"--") -> 0.15127581 | AX35: =IFERROR(AX33/AW33-1,"--") -> -0.0082914621 | AY35: =IFERROR(AY33/AX33-1,"--") -> -0.083382848 | BA35: =IFERROR(BA33/AY33-1,"--") -> -0.0034248028 | BB35: =IFERROR(BB33/BA33-1,"--") -> 0.15621211 | BC35: =IFERROR(BC33/BB33-1,"--") -> -0.01522601 | BD35: =IFERROR(BD33/BC33-1,"--") -> -0.096263724 | BF35: =IFERROR(BF33/BD33-1,"--") -> -0.016452644 | BG35: =IFERROR(BG33/BF33-1,"--") -> 0.16274507 | BH35: =IFERROR(BH33/BG33-1,"--") -> -0.025180945 | BI35: =IFERROR(BI33/BH33-1,"--") -> -0.11278015 | BK35: =IFERROR(BK33/BI33-1,"--") -> -0.017959477 | BL35: =IFERROR(BL33/BK33-1,"--") -> 0.1720582 | BM35: =IFERROR(BM33/BL33-1,"--") -> -0.043227948 | BN35: =IFERROR(BN33/BM33-1,"--") -> -0.13534482
B36: % gross margins | C36: =IFERROR((C19-C33)/C19,"--") -> -- | D36: =IFERROR((D19-D33)/D19,"--") -> -- | E36: =IFERROR((E19-E33)/E19,"--") -> -- | F36: =IFERROR((F19-F33)/F19,"--") -> -- | G36: =IFERROR((G19-G33)/G19,"--") -> -- | H36: =IFERROR((H19-H33)/H19,"--") -> -1.2764977 | I36: =IFERROR((I19-I33)/I19,"--") -> -5.626087 | J36: =IFERROR((J19-J33)/J19,"--") -> -11.03139 | ... BO36: =IFERROR((BO19-BO33)/BO19,"--") -> 0.1328276
B38: Gross Profit | C38: =C10-C24 -> 0 | D38: =D10-D24 -> 0 | E38: =E10-E24 -> 0 | F38: =F10-F24 -> 0 | G38: =SUM(C38:F38) -> 0 | H38: =H10-H24 -> 5.964 | I38: =I10-I24 -> 8.17 | J38: =J10-J24 -> 14.856 | K38: =K10-K24 -> 16.289 | L38: =SUM(H38:K38) -> 45.279 | M38: =M10-M24 -> 19.667 | N38: =N10-N24 -> 31.831 | O38: =O10-O24 -> 43.523 | P38: =P10-P24 -> 53.17 | Q38: =SUM(M38:P38) -> 148.191 | R38: =R10-R24 -> 66.258 | S38: =S10-S24 -> 82.699 | T38: =T10-T24 -> 92.943 | U38: =U10-U24 -> 107.561 | V38: =SUM(R38:U38) -> 349.461 | W38: =W10-W24 -> 131.568 | X38: =X10-X24 -> 166.077 | Y38: =Y10-Y24 -> 213.655 | Z38: =Z10-Z24 -> 249.594 | AA38: =SUM(W38:Z38) -> 760.894 | AB38: =AB10-AB24 -> 274.441 | AC38: =AC10-AC24 -> 324.016 | AD38: =AD10-AD24 -> 366.307 | AE38: =AE10-AE24 -> 383.355 | AF38: =SUM(AB38:AE38) -> 1348.119 | AG38: =AG10-AG24 -> 414.185 | AH38: =AH10-AH24 -> 455.626 | AI38: =AI10-AI24 -> 505.225 | AJ38: =AJ10-AJ24 -> 532.895 | AK38: =SUM(AG38:AJ38) -> 1907.931 | AL38: =AL10-AL24 -> 556.192 | AM38: =AM10-AM24 -> 580.745 | AN38: =AN10-AN24 -> 621.2 | AO38: =AO10-AO24 -> 653.586 | AP38: =SUM(AL38:AO38) -> 2411.723 | AQ38: =AQ10-AQ24 -> 693.288 | AR38: =AR10-AR24 -> 773.154 | AS38: =AS10-AS24 -> 822.036 | AT38: =AT10-AT24 -> 829.75024 | AU38: =SUM(AQ38:AT38) -> 3118.2282 | AV38: =AV10-AV24 -> 901.40408 | AW38: =AW10-AW24 -> 981.18087 | AX38: =AX10-AX24 -> 1040.2784 | AY38: =AY10-AY24 -> 1053.1108 | AZ38: =SUM(AV38:AY38) -> 3975.9742 | BA38: =BA10-BA24 -> 1146.9033 | BB38: =BB10-BB24 -> 1251.7894 | BC38: =BC10-BC24 -> 1330.2259 | BD38: =BD10-BD24 -> 1332.2915 | BE38: =SUM(BA38:BD38) -> 5061.21 | BF38: =BF10-BF24 -> 1437.6964 | BG38: =BG10-BG24 -> 1565.0334 | BH38: =BH10-BH24 -> 1693.1586 | BI38: =BI10-BI24 -> 1703.2833 | BJ38: =SUM(BF38:BI38) -> 6399.1717 | BK38: =BK10-BK24 -> 1819.4715 | BL38: =BL10-BL24 -> 1955.1473 | BM38: =BM10-BM24 -> 2129.4726 | BN38: =BN10-BN24 -> 2119.3609 | BO38: =SUM(BK38:BN38) -> 8023.4523
B39: % yoy | C39: -- | D39: -- | E39: -- | F39: -- | G39: -- | H39: =IFERROR(H38/C38-1,"--") -> -- | I39: =IFERROR(I38/D38-1,"--") -> -- | J39: =IFERROR(J38/E38-1,"--") -> -- | K39: =IFERROR(K38/F38-1,"--") -> -- | L39: =IFERROR(L38/G38-1,"--") -> -- | M39: =IFERROR(M38/H38-1,"--") -> 2.297619 | N39: =IFERROR(N38/I38-1,"--") -> 2.8960832 | O39: =IFERROR(O38/J38-1,"--") -> 1.9296581 | ... BO39: =IFERROR(BO38/BJ38-1,"--") -> 0.25382669
B40: % qoq | C40: -- | D40: =IFERROR(D38/C38-1,"--") -> -- | E40: =IFERROR(E38/D38-1,"--") -> -- | F40: =IFERROR(F38/E38-1,"--") -> -- | H40: =IFERROR(H38/F38-1,"--") -> -- | I40: =IFERROR(I38/H38-1,"--") -> 0.36988598 | J40: =IFERROR(J38/I38-1,"--") -> 0.81835985 | K40: =IFERROR(K38/J38-1,"--") -> 0.096459343 | M40: =IFERROR(M38/K38-1,"--") -> 0.20737921 | N40: =IFERROR(N38/M38-1,"--") -> 0.61849799 | O40: =IFERROR(O38/N38-1,"--") -> 0.36731488 | P40: =IFERROR(P38/O38-1,"--") -> 0.22165292 | R40: =IFERROR(R38/P38-1,"--") -> 0.24615385 | S40: =IFERROR(S38/R38-1,"--") -> 0.24813607 | T40: =IFERROR(T38/S38-1,"--") -> 0.12387091 | U40: =IFERROR(U38/T38-1,"--") -> 0.15727919 | W40: =IFERROR(W38/U38-1,"--") -> 0.22319428 | X40: =IFERROR(X38/W38-1,"--") -> 0.26229022 | Y40: =IFERROR(Y38/X38-1,"--") -> 0.28648157 | Z40: =IFERROR(Z38/Y38-1,"--") -> 0.16821043 | AB40: =IFERROR(AB38/Z38-1,"--") -> 0.099549669 | AC40: =IFERROR(AC38/AB38-1,"--") -> 0.18063992 | AD40: =IFERROR(AD38/AC38-1,"--") -> 0.13052133 | AE40: =IFERROR(AE38/AD38-1,"--") -> 0.046540197 | AG40: =IFERROR(AG38/AE38-1,"--") -> 0.080421541 | AH40: =IFERROR(AH38/AG38-1,"--") -> 0.10005432 | AI40: =IFERROR(AI38/AH38-1,"--") -> 0.10885902 | AJ40: =IFERROR(AJ38/AI38-1,"--") -> 0.054767678 | AL40: =IFERROR(AL38/AJ38-1,"--") -> 0.043717806 | AM40: =IFERROR(AM38/AL38-1,"--") -> 0.044144828 | AN40: =IFERROR(AN38/AM38-1,"--") -> 0.069660522 | AO40: =IFERROR(AO38/AN38-1,"--") -> 0.052134578 | AQ40: =IFERROR(AQ38/AO38-1,"--") -> 0.060744875 | AR40: =IFERROR(AR38/AQ38-1,"--") -> 0.11519888 | AS40: =IFERROR(AS38/AR38-1,"--") -> 0.063224144 | AT40: =IFERROR(AT38/AS38-1,"--") -> 0.0093843036 | AV40: =IFERROR(AV38/AT38-1,"--") -> 0.08635592 | AW40: =IFERROR(AW38/AV38-1,"--") -> 0.088502804 | AX40: =IFERROR(AX38/AW38-1,"--") -> 0.060231061 | AY40: =IFERROR(AY38/AX38-1,"--") -> 0.012335546 | BA40: =IFERROR(BA38/AY38-1,"--") -> 0.089062306 | BB40: =IFERROR(BB38/BA38-1,"--") -> 0.091451514 | BC40: =IFERROR(BC38/BB38-1,"--") -> 0.06265953 | BD40: =IFERROR(BD38/BC38-1,"--") -> 0.0015527871 | BF40: =IFERROR(BF38/BD38-1,"--") -> 0.079115564 | BG40: =IFERROR(BG38/BF38-1,"--") -> 0.088570152 | BH40: =IFERROR(BH38/BG38-1,"--") -> 0.081867348 | BI40: =IFERROR(BI38/BH38-1,"--") -> 0.0059797871 | BK40: =IFERROR(BK38/BI38-1,"--") -> 0.068214237 | BL40: =IFERROR(BL38/BK38-1,"--") -> 0.074568797 | BM40: =IFERROR(BM38/BL38-1,"--") -> 0.089162262 | BN40: =IFERROR(BN38/BM38-1,"--") -> -0.0047484466
B41: % gross margin | C41: =IFERROR(C38/C$10,"--") -> -- | D41: =IFERROR(D38/D$10,"--") -> -- | E41: =IFERROR(E38/E$10,"--") -> -- | F41: =IFERROR(F38/F$10,"--") -> -- | G41: =IFERROR(G38/G$10,"--") -> -- | H41: =IFERROR(H38/H$10,"--") -> 0.44497501 | I41: =IFERROR(I38/I$10,"--") -> 0.45629712 | J41: =IFERROR(J38/J$10,"--") -> 0.51799163 | ... BO41: =IFERROR(BO38/BO$10,"--") -> 0.73380845
B43: Sales & Marketing | G43: =SUM(C43:F43) -> 0 | H43: 23.148 | I43: 24.056 | J43: 32.257 | K43: 46.181 | L43: =SUM(H43:K43) -> 125.642 | M43: 64.052 | N43: 73.413 | O43: 75.668 | P43: 80.444 | Q43: =SUM(M43:P43) -> 293.577 | R43: 97.877 | S43: 92.663 | T43: 134.727 | U43: 154.05 | V43: =SUM(R43:U43) -> 479.317 | W43: 166.804 | X43: 182.903 | Y43: 190.971 | Z43: 203.287 | AA43: =SUM(W43:Z43) -> 743.965 | AB43: 243.912 | AC43: 274.645 | AD43: 284.477 | AE43: 303.473 | AF43: =SUM(AB43:AE43) -> 1106.507 | AG43: 331.558 | AH43: 343.288 | AI43: 355.079 | AJ43: 361.822 | AK43: =SUM(AG43:AJ43) -> 1391.747 | AL43: 400.822 | AM43: 400.625 | AN43: 437.962 | AO43: 432.683 | AP43: =SUM(AL43:AO43) -> 1672.092 | AQ43: 458.554 | AR43: 501.957 | AS43: 550.364 | AT43: ='IS (Non-GAAP)'!AT43+'IS (Non-GAAP)'!AT97+'IS (Non-GAAP)'!AT120 -> 691.49717 | AU43: =SUM(AQ43:AT43) -> 2202.3722 | AV43: ='IS (Non-GAAP)'!AV43+'IS (Non-GAAP)'!AV97+'IS (Non-GAAP)'!AV120 -> 715.3195 | AW43: ='IS (Non-GAAP)'!AW43+'IS (Non-GAAP)'!AW97+'IS (Non-GAAP)'!AW120 -> 767.52509 | AX43: ='IS (Non-GAAP)'!AX43+'IS (Non-GAAP)'!AX97+'IS (Non-GAAP)'!AX120 -> 830.49271 | AY43: ='IS (Non-GAAP)'!AY43+'IS (Non-GAAP)'!AY97+'IS (Non-GAAP)'!AY120 -> 845.64053 | AZ43: =SUM(AV43:AY43) -> 3158.9778 | BA43: ='IS (Non-GAAP)'!BA43+'IS (Non-GAAP)'!BA97+'IS (Non-GAAP)'!BA120 -> 864.20521 | BB43: ='IS (Non-GAAP)'!BB43+'IS (Non-GAAP)'!BB97+'IS (Non-GAAP)'!BB120 -> 930.13868 | BC43: ='IS (Non-GAAP)'!BC43+'IS (Non-GAAP)'!BC97+'IS (Non-GAAP)'!BC120 -> 1009.9886 | BD43: ='IS (Non-GAAP)'!BD43+'IS (Non-GAAP)'!BD97+'IS (Non-GAAP)'!BD120 -> 1017.972 | BE43: =SUM(BA43:BD43) -> 3822.3045 | BF43: ='IS (Non-GAAP)'!BF43+'IS (Non-GAAP)'!BF97+'IS (Non-GAAP)'!BF120 -> 1021.4488 | BG43: ='IS (Non-GAAP)'!BG43+'IS (Non-GAAP)'!BG97+'IS (Non-GAAP)'!BG120 -> 1097.0384 | BH43: ='IS (Non-GAAP)'!BH43+'IS (Non-GAAP)'!BH97+'IS (Non-GAAP)'!BH120 -> 1213.6786 | BI43: ='IS (Non-GAAP)'!BI43+'IS (Non-GAAP)'!BI97+'IS (Non-GAAP)'!BI120 -> 1228.1753 | BJ43: =SUM(BF43:BI43) -> 4560.3411 | BK43: ='IS (Non-GAAP)'!BK43+'IS (Non-GAAP)'!BK97+'IS (Non-GAAP)'!BK120 -> 1231.2718 | BL43: ='IS (Non-GAAP)'!BL43+'IS (Non-GAAP)'!BL97+'IS (Non-GAAP)'!BL120 -> 1305.5543 | BM43: ='IS (Non-GAAP)'!BM43+'IS (Non-GAAP)'!BM97+'IS (Non-GAAP)'!BM120 -> 1455.0855 | BN43: ='IS (Non-GAAP)'!BN43+'IS (Non-GAAP)'!BN97+'IS (Non-GAAP)'!BN120 -> 1456.6893 | BO43: =SUM(BK43:BN43) -> 5448.6009
B44: % yoy | C44: -- | D44: -- | E44: -- | F44: -- | G44: -- | H44: =IFERROR(H43/C43-1,"--") -> -- | I44: =IFERROR(I43/D43-1,"--") -> -- | J44: =IFERROR(J43/E43-1,"--") -> -- | K44: =IFERROR(K43/F43-1,"--") -> -- | L44: =IFERROR(L43/G43-1,"--") -> -- | M44: =IFERROR(M43/H43-1,"--") -> 1.7670641 | N44: =IFERROR(N43/I43-1,"--") -> 2.0517542 | O44: =IFERROR(O43/J43-1,"--") -> 1.3457854 | ... BO44: =IFERROR(BO43/BJ43-1,"--") -> 0.19477926
B45: % qoq | C45: -- | D45: =IFERROR(D43/C43-1,"--") -> -- | E45: =IFERROR(E43/D43-1,"--") -> -- | F45: =IFERROR(F43/E43-1,"--") -> -- | H45: =IFERROR(H43/F43-1,"--") -> -- | I45: =IFERROR(I43/H43-1,"--") -> 0.039225851 | J45: =IFERROR(J43/I43-1,"--") -> 0.34091287 | K45: =IFERROR(K43/J43-1,"--") -> 0.43165824 | M45: =IFERROR(M43/K43-1,"--") -> 0.38697733 | N45: =IFERROR(N43/M43-1,"--") -> 0.14614688 | O45: =IFERROR(O43/N43-1,"--") -> 0.030716631 | P45: =IFERROR(P43/O43-1,"--") -> 0.063117831 | R45: =IFERROR(R43/P43-1,"--") -> 0.21670976 | S45: =IFERROR(S43/R43-1,"--") -> -0.053270942 | T45: =IFERROR(T43/S43-1,"--") -> 0.45394602 | U45: =IFERROR(U43/T43-1,"--") -> 0.14342337 | W45: =IFERROR(W43/U43-1,"--") -> 0.082791302 | X45: =IFERROR(X43/W43-1,"--") -> 0.096514472 | Y45: =IFERROR(Y43/X43-1,"--") -> 0.044110813 | Z45: =IFERROR(Z43/Y43-1,"--") -> 0.064491467 | AB45: =IFERROR(AB43/Z43-1,"--") -> 0.19984062 | AC45: =IFERROR(AC43/AB43-1,"--") -> 0.12600036 | AD45: =IFERROR(AD43/AC43-1,"--") -> 0.03579894 | AE45: =IFERROR(AE43/AD43-1,"--") -> 0.06677517 | AG45: =IFERROR(AG43/AE43-1,"--") -> 0.092545301 | AH45: =IFERROR(AH43/AG43-1,"--") -> 0.035378425 | AI45: =IFERROR(AI43/AH43-1,"--") -> 0.034347254 | AJ45: =IFERROR(AJ43/AI43-1,"--") -> 0.01899014 | AL45: =IFERROR(AL43/AJ43-1,"--") -> 0.10778781 | AM45: =IFERROR(AM43/AL43-1,"--") -> -0.00049148999 | AN45: =IFERROR(AN43/AM43-1,"--") -> 0.09319688 | AO45: =IFERROR(AO43/AN43-1,"--") -> -0.012053557 | AQ45: =IFERROR(AQ43/AO43-1,"--") -> 0.059792042 | AR45: =IFERROR(AR43/AQ43-1,"--") -> 0.094651884 | AS45: =IFERROR(AS43/AR43-1,"--") -> 0.096436547 | AT45: =IFERROR(AT43/AS43-1,"--") -> 0.25643605 | AV45: =IFERROR(AV43/AT43-1,"--") -> 0.034450357 | AW45: =IFERROR(AW43/AV43-1,"--") -> 0.0729822 | AX45: =IFERROR(AX43/AW43-1,"--") -> 0.082039819 | AY45: =IFERROR(AY43/AX43-1,"--") -> 0.018239567 | BA45: =IFERROR(BA43/AY43-1,"--") -> 0.02195339 | BB45: =IFERROR(BB43/BA43-1,"--") -> 0.076293763 | BC45: =IFERROR(BC43/BB43-1,"--") -> 0.085847331 | BD45: =IFERROR(BD43/BC43-1,"--") -> 0.0079044823 | BF45: =IFERROR(BF43/BD43-1,"--") -> 0.0034153365 | BG45: =IFERROR(BG43/BF43-1,"--") -> 0.074002362 | BH45: =IFERROR(BH43/BG43-1,"--") -> 0.10632283 | BI45: =IFERROR(BI43/BH43-1,"--") -> 0.011944476 | BK45: =IFERROR(BK43/BI43-1,"--") -> 0.0025211973 | BL45: =IFERROR(BL43/BK43-1,"--") -> 0.060329861 | BM45: =IFERROR(BM43/BL43-1,"--") -> 0.11453468 | BN45: =IFERROR(BN43/BM43-1,"--") -> 0.0011021833
B46: % revenue | C46: =IFERROR(C43/C$10,"--") -> -- | D46: =IFERROR(D43/D$10,"--") -> -- | E46: =IFERROR(E43/E$10,"--") -> -- | F46: =IFERROR(F43/F$10,"--") -> -- | G46: =IFERROR(G43/G$10,"--") -> -- | H46: =IFERROR(H43/H$10,"--") -> 1.727076 | I46: =IFERROR(I43/I$10,"--") -> 1.3435353 | J46: =IFERROR(J43/J$10,"--") -> 1.1247211 | ... BO46: =IFERROR(BO43/BO$10,"--") -> 0.49831784
B48: Research & Development | G48: =SUM(C48:F48) -> 0 | H48: 18.682 | I48: 9.605 | J48: 12.82 | K48: 27.574 | L48: =SUM(H48:K48) -> 68.681 | M48: 21.618 | N48: 26.164 | O48: 27.669 | P48: 29.709 | Q48: =SUM(M48:P48) -> 105.16 | R48: 33.278 | S48: 36.533 | T48: 74.138 | U48: 93.997 | V48: =SUM(R48:U48) -> 237.946 | W48: 109.796 | X48: 118.087 | Y48: 115.9 | Z48: 123.149 | AA48: =SUM(W48:Z48) -> 466.932 | AB48: 150.798 | AC48: 183.748 | AD48: 211.387 | AE48: 242.125 | AF48: =SUM(AB48:AE48) -> 788.058 | AG48: 277.412 | AH48: 313.996 | AI48: 332.065 | AJ48: 364.476 | AK48: =SUM(AG48:AJ48) -> 1287.949 | AL48: 410.794 | AM48: 437.66 | AN48: 442.435 | AO48: 492.49 | AP48: =SUM(AL48:AO48) -> 1783.379 | AQ48: 472.404 | AR48: 492.003 | AS48: 494.027 | AT48: ='IS (Non-GAAP)'!AT48+'IS (Non-GAAP)'!AT98+'IS (Non-GAAP)'!AT123 -> 406.83005 | AU48: =SUM(AQ48:AT48) -> 1865.264 | AV48: ='IS (Non-GAAP)'!AV48+'IS (Non-GAAP)'!AV98+'IS (Non-GAAP)'!AV123 -> 412.17157 | AW48: ='IS (Non-GAAP)'!AW48+'IS (Non-GAAP)'!AW98+'IS (Non-GAAP)'!AW123 -> 423.74445 | AX48: ='IS (Non-GAAP)'!AX48+'IS (Non-GAAP)'!AX98+'IS (Non-GAAP)'!AX123 -> 439.27919 | AY48: ='IS (Non-GAAP)'!AY48+'IS (Non-GAAP)'!AY98+'IS (Non-GAAP)'!AY123 -> 488.63544 | AZ48: =SUM(AV48:AY48) -> 1763.8307 | BA48: ='IS (Non-GAAP)'!BA48+'IS (Non-GAAP)'!BA98+'IS (Non-GAAP)'!BA123 -> 491.29556 | BB48: ='IS (Non-GAAP)'!BB48+'IS (Non-GAAP)'!BB98+'IS (Non-GAAP)'!BB123 -> 505.60951 | BC48: ='IS (Non-GAAP)'!BC48+'IS (Non-GAAP)'!BC98+'IS (Non-GAAP)'!BC123 -> 525.11051 | BD48: ='IS (Non-GAAP)'!BD48+'IS (Non-GAAP)'!BD98+'IS (Non-GAAP)'!BD123 -> 580.16415 | BE48: =SUM(BA48:BD48) -> 2102.1797 | BF48: ='IS (Non-GAAP)'!BF48+'IS (Non-GAAP)'!BF98+'IS (Non-GAAP)'!BF123 -> 576.84481 | BG48: ='IS (Non-GAAP)'!BG48+'IS (Non-GAAP)'!BG98+'IS (Non-GAAP)'!BG123 -> 591.07828 | BH48: ='IS (Non-GAAP)'!BH48+'IS (Non-GAAP)'!BH98+'IS (Non-GAAP)'!BH123 -> 624.21681 | BI48: ='IS (Non-GAAP)'!BI48+'IS (Non-GAAP)'!BI98+'IS (Non-GAAP)'!BI123 -> 695.18165 | BJ48: =SUM(BF48:BI48) -> 2487.3215 | BK48: ='IS (Non-GAAP)'!BK48+'IS (Non-GAAP)'!BK98+'IS (Non-GAAP)'!BK123 -> 684.87102 | BL48: ='IS (Non-GAAP)'!BL48+'IS (Non-GAAP)'!BL98+'IS (Non-GAAP)'!BL123 -> 691.20339 | BM48: ='IS (Non-GAAP)'!BM48+'IS (Non-GAAP)'!BM98+'IS (Non-GAAP)'!BM123 -> 733.93978 | BN48: ='IS (Non-GAAP)'!BN48+'IS (Non-GAAP)'!BN98+'IS (Non-GAAP)'!BN123 -> 812.22893 | BO48: =SUM(BK48:BN48) -> 2922.2431
B49: % yoy | C49: -- | D49: -- | E49: -- | F49: -- | G49: -- | H49: =IFERROR(H48/C48-1,"--") -> -- | I49: =IFERROR(I48/D48-1,"--") -> -- | J49: =IFERROR(J48/E48-1,"--") -> -- | K49: =IFERROR(K48/F48-1,"--") -> -- | L49: =IFERROR(L48/G48-1,"--") -> -- | M49: =IFERROR(M48/H48-1,"--") -> 0.15715662 | N49: =IFERROR(N48/I48-1,"--") -> 1.7239979 | O49: =IFERROR(O48/J48-1,"--") -> 1.1582683 | ... BO49: =IFERROR(BO48/BJ48-1,"--") -> 0.17485538
B50: % qoq | C50: -- | D50: =IFERROR(D48/C48-1,"--") -> -- | E50: =IFERROR(E48/D48-1,"--") -> -- | F50: =IFERROR(F48/E48-1,"--") -> -- | H50: =IFERROR(H48/F48-1,"--") -> -- | I50: =IFERROR(I48/H48-1,"--") -> -0.48586875 | J50: =IFERROR(J48/I48-1,"--") -> 0.3347215 | K50: =IFERROR(K48/J48-1,"--") -> 1.150858 | M50: =IFERROR(M48/K48-1,"--") -> -0.21600058 | N50: =IFERROR(N48/M48-1,"--") -> 0.21028772 | O50: =IFERROR(O48/N48-1,"--") -> 0.057521786 | P50: =IFERROR(P48/O48-1,"--") -> 0.073728722 | R50: =IFERROR(R48/P48-1,"--") -> 0.12013195 | S50: =IFERROR(S48/R48-1,"--") -> 0.097812369 | T50: =IFERROR(T48/S48-1,"--") -> 1.0293433 | U50: =IFERROR(U48/T48-1,"--") -> 0.26786533 | W50: =IFERROR(W48/U48-1,"--") -> 0.16807983 | X50: =IFERROR(X48/W48-1,"--") -> 0.075512769 | Y50: =IFERROR(Y48/X48-1,"--") -> -0.018520244 | Z50: =IFERROR(Z48/Y48-1,"--") -> 0.062545298 | AB50: =IFERROR(AB48/Z48-1,"--") -> 0.22451664 | AC50: =IFERROR(AC48/AB48-1,"--") -> 0.21850422 | AD50: =IFERROR(AD48/AC48-1,"--") -> 0.15041796 | AE50: =IFERROR(AE48/AD48-1,"--") -> 0.14541102 | AG50: =IFERROR(AG48/AE48-1,"--") -> 0.14573877 | AH50: =IFERROR(AH48/AG48-1,"--") -> 0.13187605 | AI50: =IFERROR(AI48/AH48-1,"--") -> 0.057545319 | AJ50: =IFERROR(AJ48/AI48-1,"--") -> 0.097604385 | AL50: =IFERROR(AL48/AJ48-1,"--") -> 0.12708107 | AM50: =IFERROR(AM48/AL48-1,"--") -> 0.065400176 | AN50: =IFERROR(AN48/AM48-1,"--") -> 0.010910296 | AO50: =IFERROR(AO48/AN48-1,"--") -> 0.11313526 | AQ50: =IFERROR(AQ48/AO48-1,"--") -> -0.040784584 | AR50: =IFERROR(AR48/AQ48-1,"--") -> 0.041487794 | AS50: =IFERROR(AS48/AR48-1,"--") -> 0.0041137961 | AT50: =IFERROR(AT48/AS48-1,"--") -> -0.1765024 | AV50: =IFERROR(AV48/AT48-1,"--") -> 0.013129616 | AW50: =IFERROR(AW48/AV48-1,"--") -> 0.028077816 | AX50: =IFERROR(AX48/AW48-1,"--") -> 0.036660634 | AY50: =IFERROR(AY48/AX48-1,"--") -> 0.11235737 | BA50: =IFERROR(BA48/AY48-1,"--") -> 0.0054439597 | BB50: =IFERROR(BB48/BA48-1,"--") -> 0.029135118 | BC50: =IFERROR(BC48/BB48-1,"--") -> 0.038569299 | BD50: =IFERROR(BD48/BC48-1,"--") -> 0.104842 | BF50: =IFERROR(BF48/BD48-1,"--") -> -0.0057213918 | BG50: =IFERROR(BG48/BF48-1,"--") -> 0.024674702 | BH50: =IFERROR(BH48/BG48-1,"--") -> 0.056064545 | BI50: =IFERROR(BI48/BH48-1,"--") -> 0.11368619 | BK50: =IFERROR(BK48/BI48-1,"--") -> -0.014831565 | BL50: =IFERROR(BL48/BK48-1,"--") -> 0.0092460797 | BM50: =IFERROR(BM48/BL48-1,"--") -> 0.061828961 | BN50: =IFERROR(BN48/BM48-1,"--") -> 0.10666973
B51: % revenue | C51: =IFERROR(C48/C$10,"--") -> -- | D51: =IFERROR(D48/D$10,"--") -> -- | E51: =IFERROR(E48/E$10,"--") -> -- | F51: =IFERROR(F48/F$10,"--") -> -- | G51: =IFERROR(G48/G$10,"--") -> -- | H51: =IFERROR(H48/H$10,"--") -> 1.393867 | I51: =IFERROR(I48/I$10,"--") -> 0.53644233 | J51: =IFERROR(J48/J$10,"--") -> 0.44700139 | ... BO51: =IFERROR(BO48/BO$10,"--") -> 0.26726235
B53: General & Administrative | G53: =SUM(C53:F53) -> 0 | H53: 6.051 | I53: 6.927 | J53: 8.773 | K53: 14.304 | L53: =SUM(H53:K53) -> 36.055 | M53: 21.272 | N53: 27.823 | O53: 30.318 | P53: 28.129 | Q53: =SUM(M53:P53) -> 107.542 | R53: 31.506 | S53: 31.186 | T53: 53.532 | U53: 59.911 | V53: =SUM(R53:U53) -> 176.135 | W53: 60.563 | X53: 65.228 | Y53: 64.055 | Z53: 75.187 | AA53: =SUM(W53:Z53) -> 265.033 | AB53: 68.497 | AC53: 73.355 | AD53: 76.462 | AE53: 77.507 | AF53: =SUM(AB53:AE53) -> 295.821 | AG53: 78.453 | AH53: 83.749 | AI53: 78.704 | AJ53: 82.102 | AK53: =SUM(AG53:AJ53) -> 323.008 | AL53: 93.148 | AM53: 97.763 | AN53: 106.26 | AO53: 115.091 | AP53: =SUM(AL53:AO53) -> 412.262 | AQ53: 209.587 | AR53: 119.47 | AS53: 107.118 | AT53: ='IS (Non-GAAP)'!AT53+'IS (Non-GAAP)'!AT99+SUM('IS (Non-GAAP)'!AT127:AT130) -> 115.86074 | AU53: =SUM(AQ53:AT53) -> 552.03574 | AV53: ='IS (Non-GAAP)'!AV53+'IS (Non-GAAP)'!AV99+SUM('IS (Non-GAAP)'!AV127:AV130) -> 113.56483 | AW53: ='IS (Non-GAAP)'!AW53+'IS (Non-GAAP)'!AW99+SUM('IS (Non-GAAP)'!AW127:AW130) -> 119.02817 | AX53: ='IS (Non-GAAP)'!AX53+'IS (Non-GAAP)'!AX99+SUM('IS (Non-GAAP)'!AX127:AX130) -> 115.38785 | AY53: ='IS (Non-GAAP)'!AY53+'IS (Non-GAAP)'!AY99+SUM('IS (Non-GAAP)'!AY127:AY130) -> 126.66571 | AZ53: =SUM(AV53:AY53) -> 474.64657 | BA53: ='IS (Non-GAAP)'!BA53+'IS (Non-GAAP)'!BA99+SUM('IS (Non-GAAP)'!BA127:BA130) -> 126.19719 | BB53: ='IS (Non-GAAP)'!BB53+'IS (Non-GAAP)'!BB99+SUM('IS (Non-GAAP)'!BB127:BB130) -> 132.20967 | BC53: ='IS (Non-GAAP)'!BC53+'IS (Non-GAAP)'!BC99+SUM('IS (Non-GAAP)'!BC127:BC130) -> 127.04897 | BD53: ='IS (Non-GAAP)'!BD53+'IS (Non-GAAP)'!BD99+SUM('IS (Non-GAAP)'!BD127:BD130) -> 139.18779 | BE53: =SUM(BA53:BD53) -> 524.64362 | BF53: ='IS (Non-GAAP)'!BF53+'IS (Non-GAAP)'!BF99+SUM('IS (Non-GAAP)'!BF127:BF130) -> 146.60128 | BG53: ='IS (Non-GAAP)'!BG53+'IS (Non-GAAP)'!BG99+SUM('IS (Non-GAAP)'!BG127:BG130) -> 152.96886 | BH53: ='IS (Non-GAAP)'!BH53+'IS (Non-GAAP)'!BH99+SUM('IS (Non-GAAP)'!BH127:BH130) -> 148.71681 | BI53: ='IS (Non-GAAP)'!BI53+'IS (Non-GAAP)'!BI99+SUM('IS (Non-GAAP)'!BI127:BI130) -> 164.34647 | BJ53: =SUM(BF53:BI53) -> 612.63342 | BK53: ='IS (Non-GAAP)'!BK53+'IS (Non-GAAP)'!BK99+SUM('IS (Non-GAAP)'!BK127:BK130) -> 172.34131 | BL53: ='IS (Non-GAAP)'!BL53+'IS (Non-GAAP)'!BL99+SUM('IS (Non-GAAP)'!BL127:BL130) -> 177.21432 | BM53: ='IS (Non-GAAP)'!BM53+'IS (Non-GAAP)'!BM99+SUM('IS (Non-GAAP)'!BM127:BM130) -> 172.26738 | BN53: ='IS (Non-GAAP)'!BN53+'IS (Non-GAAP)'!BN99+SUM('IS (Non-GAAP)'!BN127:BN130) -> 189.31772 | BO53: =SUM(BK53:BN53) -> 711.14074
B54: % yoy | C54: -- | D54: -- | E54: -- | F54: -- | G54: -- | H54: =IFERROR(H53/C53-1,"--") -> -- | I54: =IFERROR(I53/D53-1,"--") -> -- | J54: =IFERROR(J53/E53-1,"--") -> -- | K54: =IFERROR(K53/F53-1,"--") -> -- | L54: =IFERROR(L53/G53-1,"--") -> -- | M54: =IFERROR(M53/H53-1,"--") -> 2.515452 | N54: =IFERROR(N53/I53-1,"--") -> 3.0166017 | O54: =IFERROR(O53/J53-1,"--") -> 2.4558304 | ... BO54: =IFERROR(BO53/BJ53-1,"--") -> 0.16079326
B55: % qoq | C55: -- | D55: =IFERROR(D53/C53-1,"--") -> -- | E55: =IFERROR(E53/D53-1,"--") -> -- | F55: =IFERROR(F53/E53-1,"--") -> -- | H55: =IFERROR(H53/F53-1,"--") -> -- | I55: =IFERROR(I53/H53-1,"--") -> 0.14476946 | J55: =IFERROR(J53/I53-1,"--") -> 0.26649343 | K55: =IFERROR(K53/J53-1,"--") -> 0.63045708 | M55: =IFERROR(M53/K53-1,"--") -> 0.48713647 | N55: =IFERROR(N53/M53-1,"--") -> 0.30796352 | O55: =IFERROR(O53/N53-1,"--") -> 0.089674011 | P55: =IFERROR(P53/O53-1,"--") -> -0.072201333 | R55: =IFERROR(R53/P53-1,"--") -> 0.12005404 | S55: =IFERROR(S53/R53-1,"--") -> -0.010156796 | T55: =IFERROR(T53/S53-1,"--") -> 0.71653947 | U55: =IFERROR(U53/T53-1,"--") -> 0.11916237 | W55: =IFERROR(W53/U53-1,"--") -> 0.01088281 | X55: =IFERROR(X53/W53-1,"--") -> 0.077027228 | Y55: =IFERROR(Y53/X53-1,"--") -> -0.017983075 | Z55: =IFERROR(Z53/Y53-1,"--") -> 0.17378815 | AB55: =IFERROR(AB53/Z53-1,"--") -> -0.088978148 | AC55: =IFERROR(AC53/AB53-1,"--") -> 0.070922814 | AD55: =IFERROR(AD53/AC53-1,"--") -> 0.042355668 | AE55: =IFERROR(AE53/AD53-1,"--") -> 0.01366692 | AG55: =IFERROR(AG53/AE53-1,"--") -> 0.012205349 | AH55: =IFERROR(AH53/AG53-1,"--") -> 0.067505385 | AI55: =IFERROR(AI53/AH53-1,"--") -> -0.060239525 | AJ55: =IFERROR(AJ53/AI53-1,"--") -> 0.043174426 | AL55: =IFERROR(AL53/AJ53-1,"--") -> 0.13453996 | AM55: =IFERROR(AM53/AL53-1,"--") -> 0.04954481 | AN55: =IFERROR(AN53/AM53-1,"--") -> 0.086914272 | AO55: =IFERROR(AO53/AN53-1,"--") -> 0.083107472 | AQ55: =IFERROR(AQ53/AO53-1,"--") -> 0.82105464 | AR55: =IFERROR(AR53/AQ53-1,"--") -> -0.42997419 | AS55: =IFERROR(AS53/AR53-1,"--") -> -0.10338997 | AT55: =IFERROR(AT53/AS53-1,"--") -> 0.081617851 | AV55: =IFERROR(AV53/AT53-1,"--") -> -0.019816113 | AW55: =IFERROR(AW53/AV53-1,"--") -> 0.048107662 | AX55: =IFERROR(AX53/AW53-1,"--") -> -0.030583657 | AY55: =IFERROR(AY53/AX53-1,"--") -> 0.0977387 | BA55: =IFERROR(BA53/AY53-1,"--") -> -0.0036988661 | BB55: =IFERROR(BB53/BA53-1,"--") -> 0.047643481 | BC55: =IFERROR(BC53/BB53-1,"--") -> -0.039034168 | BD55: =IFERROR(BD53/BC53-1,"--") -> 0.095544429 | BF55: =IFERROR(BF53/BD53-1,"--") -> 0.053262459 | BG55: =IFERROR(BG53/BF53-1,"--") -> 0.04343467 | BH55: =IFERROR(BH53/BG53-1,"--") -> -0.027796775 | BI55: =IFERROR(BI53/BH53-1,"--") -> 0.10509675 | BK55: =IFERROR(BK53/BI53-1,"--") -> 0.048646283 | BL55: =IFERROR(BL53/BK53-1,"--") -> 0.028275346 | BM55: =IFERROR(BM53/BL53-1,"--") -> -0.027915042 | BN55: =IFERROR(BN53/BM53-1,"--") -> 0.098976041
B56: % revenue | C56: =IFERROR(C53/C$10,"--") -> -- | D56: =IFERROR(D53/D$10,"--") -> -- | E56: =IFERROR(E53/E$10,"--") -> -- | F56: =IFERROR(F53/F$10,"--") -> -- | G56: =IFERROR(G53/G$10,"--") -> -- | H56: =IFERROR(H53/H$10,"--") -> 0.45146609 | I56: =IFERROR(I53/I$10,"--") -> 0.38687517 | J56: =IFERROR(J53/J$10,"--") -> 0.30589261 | ... BO56: =IFERROR(BO53/BO$10,"--") -> 0.06503947
B58: Other | G58: =SUM(C58:F58) -> 0 | H58: 0 | I58: 0 | J58: 0 | K58: 0 | L58: =SUM(H58:K58) -> 0 | M58: 0 | N58: 0 | O58: 0 | P58: 0 | Q58: =SUM(M58:P58) -> 0 | R58: 0 | S58: 0 | T58: 0 | U58: 0 | V58: =SUM(R58:U58) -> 0 | W58: 0 | X58: 0 | Y58: 0 | Z58: 0 | AA58: =SUM(W58:Z58) -> 0 | AB58: 0 | AC58: 0 | AD58: 0 | AE58: 0 | AF58: =SUM(AB58:AE58) -> 0 | AG58: 0 | AH58: 0 | AI58: 0 | AJ58: 0 | AK58: =SUM(AG58:AJ58) -> 0 | AL58: 0 | AM58: 0 | AN58: 0 | AO58: 0 | AP58: =SUM(AL58:AO58) -> 0 | AQ58: 0 | AR58: 0 | AS58: 0 | AT58: ='IS (Non-GAAP)'!AT58 -> 0 | AU58: =SUM(AQ58:AT58) -> 0 | AV58: ='IS (Non-GAAP)'!AV58 -> 0 | AW58: ='IS (Non-GAAP)'!AW58 -> 0 | AX58: ='IS (Non-GAAP)'!AX58 -> 0 | AY58: ='IS (Non-GAAP)'!AY58 -> 0 | AZ58: =SUM(AV58:AY58) -> 0 | BA58: ='IS (Non-GAAP)'!BA58 -> 0 | BB58: ='IS (Non-GAAP)'!BB58 -> 0 | BC58: ='IS (Non-GAAP)'!BC58 -> 0 | BD58: ='IS (Non-GAAP)'!BD58 -> 0 | BE58: =SUM(BA58:BD58) -> 0 | BF58: ='IS (Non-GAAP)'!BF58 -> 0 | BG58: ='IS (Non-GAAP)'!BG58 -> 0 | BH58: ='IS (Non-GAAP)'!BH58 -> 0 | BI58: ='IS (Non-GAAP)'!BI58 -> 0 | BJ58: =SUM(BF58:BI58) -> 0 | BK58: ='IS (Non-GAAP)'!BK58 -> 0 | BL58: ='IS (Non-GAAP)'!BL58 -> 0 | BM58: ='IS (Non-GAAP)'!BM58 -> 0 | BN58: ='IS (Non-GAAP)'!BN58 -> 0 | BO58: =SUM(BK58:BN58) -> 0
B59: % yoy | C59: -- | D59: -- | E59: -- | F59: -- | G59: -- | H59: =IFERROR(H58/C58-1,"--") -> -- | I59: =IFERROR(I58/D58-1,"--") -> -- | J59: =IFERROR(J58/E58-1,"--") -> -- | K59: =IFERROR(K58/F58-1,"--") -> -- | L59: =IFERROR(L58/G58-1,"--") -> -- | M59: =IFERROR(M58/H58-1,"--") -> -- | N59: =IFERROR(N58/I58-1,"--") -> -- | O59: =IFERROR(O58/J58-1,"--") -> -- | ... BO59: =IFERROR(BO58/BJ58-1,"--") -> --
B60: % qoq | C60: -- | D60: =IFERROR(D58/C58-1,"--") -> -- | E60: =IFERROR(E58/D58-1,"--") -> -- | F60: =IFERROR(F58/E58-1,"--") -> -- | H60: =IFERROR(H58/F58-1,"--") -> -- | I60: =IFERROR(I58/H58-1,"--") -> -- | J60: =IFERROR(J58/I58-1,"--") -> -- | K60: =IFERROR(K58/J58-1,"--") -> -- | M60: =IFERROR(M58/K58-1,"--") -> -- | N60: =IFERROR(N58/M58-1,"--") -> -- | O60: =IFERROR(O58/N58-1,"--") -> -- | P60: =IFERROR(P58/O58-1,"--") -> -- | R60: =IFERROR(R58/P58-1,"--") -> -- | S60: =IFERROR(S58/R58-1,"--") -> -- | T60: =IFERROR(T58/S58-1,"--") -> -- | U60: =IFERROR(U58/T58-1,"--") -> -- | W60: =IFERROR(W58/U58-1,"--") -> -- | X60: =IFERROR(X58/W58-1,"--") -> -- | Y60: =IFERROR(Y58/X58-1,"--") -> -- | Z60: =IFERROR(Z58/Y58-1,"--") -> -- | AB60: =IFERROR(AB58/Z58-1,"--") -> -- | AC60: =IFERROR(AC58/AB58-1,"--") -> -- | AD60: =IFERROR(AD58/AC58-1,"--") -> -- | AE60: =IFERROR(AE58/AD58-1,"--") -> -- | AG60: =IFERROR(AG58/AE58-1,"--") -> -- | AH60: =IFERROR(AH58/AG58-1,"--") -> -- | AI60: =IFERROR(AI58/AH58-1,"--") -> -- | AJ60: =IFERROR(AJ58/AI58-1,"--") -> -- | AL60: =IFERROR(AL58/AJ58-1,"--") -> -- | AM60: =IFERROR(AM58/AL58-1,"--") -> -- | AN60: =IFERROR(AN58/AM58-1,"--") -> -- | AO60: =IFERROR(AO58/AN58-1,"--") -> -- | AQ60: =IFERROR(AQ58/AO58-1,"--") -> -- | AR60: =IFERROR(AR58/AQ58-1,"--") -> -- | AS60: =IFERROR(AS58/AR58-1,"--") -> -- | AT60: =IFERROR(AT58/AS58-1,"--") -> -- | AV60: =IFERROR(AV58/AT58-1,"--") -> -- | AW60: =IFERROR(AW58/AV58-1,"--") -> -- | AX60: =IFERROR(AX58/AW58-1,"--") -> -- | AY60: =IFERROR(AY58/AX58-1,"--") -> -- | BA60: =IFERROR(BA58/AY58-1,"--") -> -- | BB60: =IFERROR(BB58/BA58-1,"--") -> -- | BC60: =IFERROR(BC58/BB58-1,"--") -> -- | BD60: =IFERROR(BD58/BC58-1,"--") -> -- | BF60: =IFERROR(BF58/BD58-1,"--") -> -- | BG60: =IFERROR(BG58/BF58-1,"--") -> -- | BH60: =IFERROR(BH58/BG58-1,"--") -> -- | BI60: =IFERROR(BI58/BH58-1,"--") -> -- | BK60: =IFERROR(BK58/BI58-1,"--") -> -- | BL60: =IFERROR(BL58/BK58-1,"--") -> -- | BM60: =IFERROR(BM58/BL58-1,"--") -> -- | BN60: =IFERROR(BN58/BM58-1,"--") -> --
B61: % revenue | C61: =IFERROR(C58/C$10,"--") -> -- | D61: =IFERROR(D58/D$10,"--") -> -- | E61: =IFERROR(E58/E$10,"--") -> -- | F61: =IFERROR(F58/F$10,"--") -> -- | G61: =IFERROR(G58/G$10,"--") -> -- | H61: =IFERROR(H58/H$10,"--") -> 0 | I61: =IFERROR(I58/I$10,"--") -> 0 | J61: =IFERROR(J58/J$10,"--") -> 0 | ... BO61: =IFERROR(BO58/BO$10,"--") -> 0
B63: Total Operating Expenses | C63: =SUM(C43,C48,C53,C58) -> 0 | D63: =SUM(D43,D48,D53,D58) -> 0 | E63: =SUM(E43,E48,E53,E58) -> 0 | F63: =SUM(F43,F48,F53,F58) -> 0 | G63: =SUM(C63:F63) -> 0 | H63: =SUM(H43,H48,H53,H58) -> 47.881 | I63: =SUM(I43,I48,I53,I58) -> 40.588 | J63: =SUM(J43,J48,J53,J58) -> 53.85 | K63: =SUM(K43,K48,K53,K58) -> 88.059 | L63: =SUM(H63:K63) -> 230.378 | M63: =SUM(M43,M48,M53,M58) -> 106.942 | N63: =SUM(N43,N48,N53,N58) -> 127.4 | O63: =SUM(O43,O48,O53,O58) -> 133.655 | P63: =SUM(P43,P48,P53,P58) -> 138.282 | Q63: =SUM(M63:P63) -> 506.279 | R63: =SUM(R43,R48,R53,R58) -> 162.661 | S63: =SUM(S43,S48,S53,S58) -> 160.382 | T63: =SUM(T43,T48,T53,T58) -> 262.397 | U63: =SUM(U43,U48,U53,U58) -> 307.958 | V63: =SUM(R63:U63) -> 893.398 | W63: =SUM(W43,W48,W53,W58) -> 337.163 | X63: =SUM(X43,X48,X53,X58) -> 366.218 | Y63: =SUM(Y43,Y48,Y53,Y58) -> 370.926 | Z63: =SUM(Z43,Z48,Z53,Z58) -> 401.623 | AA63: =SUM(W63:Z63) -> 1475.93 | AB63: =SUM(AB43,AB48,AB53,AB58) -> 463.207 | AC63: =SUM(AC43,AC48,AC53,AC58) -> 531.748 | AD63: =SUM(AD43,AD48,AD53,AD58) -> 572.326 | AE63: =SUM(AE43,AE48,AE53,AE58) -> 623.105 | AF63: =SUM(AB63:AE63) -> 2190.386 | AG63: =SUM(AG43,AG48,AG53,AG58) -> 687.423 | AH63: =SUM(AH43,AH48,AH53,AH58) -> 741.033 | AI63: =SUM(AI43,AI48,AI53,AI58) -> 765.848 | AJ63: =SUM(AJ43,AJ48,AJ53,AJ58) -> 808.4 | AK63: =SUM(AG63:AJ63) -> 3002.704 | AL63: =SUM(AL43,AL48,AL53,AL58) -> 904.764 | AM63: =SUM(AM43,AM48,AM53,AM58) -> 936.048 | AN63: =SUM(AN43,AN48,AN53,AN58) -> 986.657 | AO63: =SUM(AO43,AO48,AO53,AO58) -> 1040.264 | AP63: =SUM(AL63:AO63) -> 3867.733 | AQ63: =SUM(AQ43,AQ48,AQ53,AQ58) -> 1140.545 | AR63: =SUM(AR43,AR48,AR53,AR58) -> 1113.43 | AS63: =SUM(AS43,AS48,AS53,AS58) -> 1151.509 | AT63: =SUM(AT43,AT48,AT53,AT58) -> 1214.188 | AU63: =SUM(AQ63:AT63) -> 4619.672 | AV63: =SUM(AV43,AV48,AV53,AV58) -> 1241.0559 | AW63: =SUM(AW43,AW48,AW53,AW58) -> 1310.2977 | AX63: =SUM(AX43,AX48,AX53,AX58) -> 1385.1597 | AY63: =SUM(AY43,AY48,AY53,AY58) -> 1460.9417 | AZ63: =SUM(AV63:AY63) -> 5397.455 | BA63: =SUM(BA43,BA48,BA53,BA58) -> 1481.698 | BB63: =SUM(BB43,BB48,BB53,BB58) -> 1567.9579 | BC63: =SUM(BC43,BC48,BC53,BC58) -> 1662.1481 | BD63: =SUM(BD43,BD48,BD53,BD58) -> 1737.324 | BE63: =SUM(BA63:BD63) -> 6449.1279 | BF63: =SUM(BF43,BF48,BF53,BF58) -> 1744.8948 | BG63: =SUM(BG43,BG48,BG53,BG58) -> 1841.0855 | BH63: =SUM(BH43,BH48,BH53,BH58) -> 1986.6122 | BI63: =SUM(BI43,BI48,BI53,BI58) -> 2087.7035 | BJ63: =SUM(BF63:BI63) -> 7660.296 | BK63: =SUM(BK43,BK48,BK53,BK58) -> 2088.4842 | BL63: =SUM(BL43,BL48,BL53,BL58) -> 2173.972 | BM63: =SUM(BM43,BM48,BM53,BM58) -> 2361.2927 | BN63: =SUM(BN43,BN48,BN53,BN58) -> 2458.236 | BO63: =SUM(BK63:BN63) -> 9081.9848
B64: % yoy | C64: -- | D64: -- | E64: -- | F64: -- | G64: -- | H64: =IFERROR(H63/C63-1,"--") -> -- | I64: =IFERROR(I63/D63-1,"--") -> -- | J64: =IFERROR(J63/E63-1,"--") -> -- | K64: =IFERROR(K63/F63-1,"--") -> -- | L64: =IFERROR(L63/G63-1,"--") -> -- | M64: =IFERROR(M63/H63-1,"--") -> 1.2334955 | N64: =IFERROR(N63/I63-1,"--") -> 2.1388588 | O64: =IFERROR(O63/J63-1,"--") -> 1.481987 | ... BO64: =IFERROR(BO63/BJ63-1,"--") -> 0.18559188
B65: % qoq | C65: -- | D65: =IFERROR(D63/C63-1,"--") -> -- | E65: =IFERROR(E63/D63-1,"--") -> -- | F65: =IFERROR(F63/E63-1,"--") -> -- | H65: =IFERROR(H63/F63-1,"--") -> -- | I65: =IFERROR(I63/H63-1,"--") -> -0.15231511 | J65: =IFERROR(J63/I63-1,"--") -> 0.32674682 | K65: =IFERROR(K63/J63-1,"--") -> 0.63526462 | M65: =IFERROR(M63/K63-1,"--") -> 0.21443578 | N65: =IFERROR(N63/M63-1,"--") -> 0.19129996 | O65: =IFERROR(O63/N63-1,"--") -> 0.049097331 | P65: =IFERROR(P63/O63-1,"--") -> 0.034618982 | R65: =IFERROR(R63/P63-1,"--") -> 0.17629916 | S65: =IFERROR(S63/R63-1,"--") -> -0.014010734 | T65: =IFERROR(T63/S63-1,"--") -> 0.63607512 | U65: =IFERROR(U63/T63-1,"--") -> 0.17363384 | W65: =IFERROR(W63/U63-1,"--") -> 0.094834361 | X65: =IFERROR(X63/W63-1,"--") -> 0.086174936 | Y65: =IFERROR(Y63/X63-1,"--") -> 0.012855731 | Z65: =IFERROR(Z63/Y63-1,"--") -> 0.082757747 | AB65: =IFERROR(AB63/Z63-1,"--") -> 0.15333783 | AC65: =IFERROR(AC63/AB63-1,"--") -> 0.14797056 | AD65: =IFERROR(AD63/AC63-1,"--") -> 0.076310583 | AE65: =IFERROR(AE63/AD63-1,"--") -> 0.088723909 | AG65: =IFERROR(AG63/AE63-1,"--") -> 0.10322177 | AH65: =IFERROR(AH63/AG63-1,"--") -> 0.077986916 | AI65: =IFERROR(AI63/AH63-1,"--") -> 0.033487038 | AJ65: =IFERROR(AJ63/AI63-1,"--") -> 0.055561939 | AL65: =IFERROR(AL63/AJ63-1,"--") -> 0.11920336 | AM65: =IFERROR(AM63/AL63-1,"--") -> 0.034576973 | AN65: =IFERROR(AN63/AM63-1,"--") -> 0.054066672 | AO65: =IFERROR(AO63/AN63-1,"--") -> 0.054331951 | AQ65: =IFERROR(AQ63/AO63-1,"--") -> 0.096399568 | AR65: =IFERROR(AR63/AQ63-1,"--") -> -0.023773722 | AS65: =IFERROR(AS63/AR63-1,"--") -> 0.034199725 | AT65: =IFERROR(AT63/AS63-1,"--") -> 0.05443202 | AV65: =IFERROR(AV63/AT63-1,"--") -> 0.022128318 | AW65: =IFERROR(AW63/AV63-1,"--") -> 0.055792658 | AX65: =IFERROR(AX63/AW63-1,"--") -> 0.057133614 | AY65: =IFERROR(AY63/AX63-1,"--") -> 0.054709893 | BA65: =IFERROR(BA63/AY63-1,"--") -> 0.014207459 | BB65: =IFERROR(BB63/BA63-1,"--") -> 0.058216922 | BC65: =IFERROR(BC63/BB63-1,"--") -> 0.060071917 | BD65: =IFERROR(BD63/BC63-1,"--") -> 0.045228158 | BF65: =IFERROR(BF63/BD63-1,"--") -> 0.0043577679 | BG65: =IFERROR(BG63/BF63-1,"--") -> 0.055126917 | BH65: =IFERROR(BH63/BG63-1,"--") -> 0.079043973 | BI65: =IFERROR(BI63/BH63-1,"--") -> 0.050886249 | BK65: =IFERROR(BK63/BI63-1,"--") -> 0.0003739447 | BL65: =IFERROR(BL63/BK63-1,"--") -> 0.040932961 | BM65: =IFERROR(BM63/BL63-1,"--") -> 0.086165181 | BN65: =IFERROR(BN63/BM63-1,"--") -> 0.041055169
B67: GAAP Operating Income | C67: =C38-C63 -> 0 | D67: =D38-D63 -> 0 | E67: =E38-E63 -> 0 | F67: =F38-F63 -> 0 | G67: =SUM(C67:F67) -> 0 | H67: =H38-H63 -> -41.917 | I67: =I38-I63 -> -32.418 | J67: =J38-J63 -> -38.994 | K67: =K38-K63 -> -71.77 | L67: =SUM(H67:K67) -> -185.099 | M67: =M38-M63 -> -87.275 | N67: =N38-N63 -> -95.569 | O67: =O38-O63 -> -90.132 | P67: =P38-P63 -> -85.112 | Q67: =SUM(M67:P67) -> -358.088 | R67: =R38-R63 -> -96.403 | S67: =S38-S63 -> -77.683 | T67: =T38-T63 -> -169.454 | U67: =U38-U63 -> -200.397 | V67: =SUM(R67:U67) -> -543.937 | W67: =W38-W63 -> -205.595 | X67: =X38-X63 -> -200.141 | Y67: =Y38-Y63 -> -157.271 | Z67: =Z38-Z63 -> -152.029 | AA67: =SUM(W67:Z67) -> -715.036 | AB67: =AB38-AB63 -> -188.766 | AC67: =AC38-AC63 -> -207.732 | AD67: =AD38-AD63 -> -206.019 | AE67: =AE38-AE63 -> -239.75 | AF67: =SUM(AB67:AE67) -> -842.267 | AG67: =AG38-AG63 -> -273.238 | AH67: =AH38-AH63 -> -285.407 | AI67: =AI38-AI63 -> -260.623 | AJ67: =AJ38-AJ63 -> -275.505 | AK67: =SUM(AG67:AJ67) -> -1094.773 | AL67: =AL38-AL63 -> -348.572 | AM67: =AM38-AM63 -> -355.303 | AN67: =AN38-AN63 -> -365.457 | AO67: =AO38-AO63 -> -386.678 | AP67: =SUM(AL67:AO67) -> -1456.01 | AQ67: =AQ38-AQ63 -> -447.257 | AR67: =AR38-AR63 -> -340.276 | AS67: =AS38-AS63 -> -329.473 | AT67: =AT38-AT63 -> -384.43773 | AU67: =SUM(AQ67:AT67) -> -1501.4437 | AV67: =AV38-AV63 -> -339.65182 | AW67: =AW38-AW63 -> -329.11684 | AX67: =AX38-AX63 -> -344.88131 | AY67: =AY38-AY63 -> -407.83085 | AZ67: =SUM(AV67:AY67) -> -1421.4808 | BA67: =BA38-BA63 -> -334.79464 | BB67: =BB38-BB63 -> -316.16849 | BC67: =BC38-BC63 -> -331.92219 | BD67: =BD38-BD63 -> -405.03253 | BE67: =SUM(BA67:BD67) -> -1387.9179 | BF67: =BF38-BF63 -> -307.1984 | BG67: =BG38-BG63 -> -276.05208 | BH67: =BH38-BH63 -> -293.45365 | BI67: =BI38-BI63 -> -384.42017 | BJ67: =SUM(BF67:BI67) -> -1261.1243 | BK67: =BK38-BK63 -> -269.01269 | BL67: =BL38-BL63 -> -218.82473 | BM67: =BM38-BM63 -> -231.82006 | BN67: =BN38-BN63 -> -338.87502 | BO67: =SUM(BK67:BN67) -> -1058.5325
B68: % yoy | C68: -- | D68: -- | E68: -- | F68: -- | G68: -- | H68: =IFERROR(H67/C67-1,"--") -> -- | I68: =IFERROR(I67/D67-1,"--") -> -- | J68: =IFERROR(J67/E67-1,"--") -> -- | K68: =IFERROR(K67/F67-1,"--") -> -- | L68: =IFERROR(L67/G67-1,"--") -> -- | M68: =IFERROR(M67/H67-1,"--") -> 1.0820908 | N68: =IFERROR(N67/I67-1,"--") -> 1.9480227 | O68: =IFERROR(O67/J67-1,"--") -> 1.3114325 | ... BO68: =IFERROR(BO67/BJ67-1,"--") -> -0.1606438
B69: % qoq | C69: -- | D69: =IFERROR(D67/C67-1,"--") -> -- | E69: =IFERROR(E67/D67-1,"--") -> -- | F69: =IFERROR(F67/E67-1,"--") -> -- | H69: =IFERROR(H67/F67-1,"--") -> -- | I69: =IFERROR(I67/H67-1,"--") -> -0.2266145 | J69: =IFERROR(J67/I67-1,"--") -> 0.20285027 | K69: =IFERROR(K67/J67-1,"--") -> 0.84053957 | M69: =IFERROR(M67/K67-1,"--") -> 0.21603734 | N69: =IFERROR(N67/M67-1,"--") -> 0.095032942 | O69: =IFERROR(O67/N67-1,"--") -> -0.056890833 | P69: =IFERROR(P67/O67-1,"--") -> -0.05569609 | R69: =IFERROR(R67/P67-1,"--") -> 0.13266049 | S69: =IFERROR(S67/R67-1,"--") -> -0.19418483 | T69: =IFERROR(T67/S67-1,"--") -> 1.1813524 | U69: =IFERROR(U67/T67-1,"--") -> 0.18260413 | W69: =IFERROR(W67/U67-1,"--") -> 0.025938512 | X69: =IFERROR(X67/W67-1,"--") -> -0.026527882 | Y69: =IFERROR(Y67/X67-1,"--") -> -0.21419899 | Z69: =IFERROR(Z67/Y67-1,"--") -> -0.033331002 | AB69: =IFERROR(AB67/Z67-1,"--") -> 0.24164469 | AC69: =IFERROR(AC67/AB67-1,"--") -> 0.1004736 | AD69: =IFERROR(AD67/AC67-1,"--") -> -0.0082462018 | AE69: =IFERROR(AE67/AD67-1,"--") -> 0.16372762 | AG69: =IFERROR(AG67/AE67-1,"--") -> 0.13967883 | AH69: =IFERROR(AH67/AG67-1,"--") -> 0.044536265 | AI69: =IFERROR(AI67/AH67-1,"--") -> -0.086837394 | AJ69: =IFERROR(AJ67/AI67-1,"--") -> 0.057101637 | AL69: =IFERROR(AL67/AJ67-1,"--") -> 0.26521116 | AM69: =IFERROR(AM67/AL67-1,"--") -> 0.019310214 | AN69: =IFERROR(AN67/AM67-1,"--") -> 0.028578425 | AO69: =IFERROR(AO67/AN67-1,"--") -> 0.058067023 | AQ69: =IFERROR(AQ67/AO67-1,"--") -> 0.15666524 | AR69: =IFERROR(AR67/AQ67-1,"--") -> -0.23919357 | AS69: =IFERROR(AS67/AR67-1,"--") -> -0.031747758 | AT69: =IFERROR(AT67/AS67-1,"--") -> 0.16682619 | AV69: =IFERROR(AV67/AT67-1,"--") -> -0.11649717 | AW69: =IFERROR(AW67/AV67-1,"--") -> -0.031017003 | AX69: =IFERROR(AX67/AW67-1,"--") -> 0.047899337 | AY69: =IFERROR(AY67/AX67-1,"--") -> 0.18252522 | BA69: =IFERROR(BA67/AY67-1,"--") -> -0.17908456 | BB69: =IFERROR(BB67/BA67-1,"--") -> -0.055634551 | BC69: =IFERROR(BC67/BB67-1,"--") -> 0.049826914 | BD69: =IFERROR(BD67/BC67-1,"--") -> 0.22026348 | BF69: =IFERROR(BF67/BD67-1,"--") -> -0.24154636 | BG69: =IFERROR(BG67/BF67-1,"--") -> -0.10138829 | BH69: =IFERROR(BH67/BG67-1,"--") -> 0.063037295 | BI69: =IFERROR(BI67/BH67-1,"--") -> 0.30998597 | BK69: =IFERROR(BK67/BI67-1,"--") -> -0.30021184 | BL69: =IFERROR(BL67/BK67-1,"--") -> -0.18656354 | BM69: =IFERROR(BM67/BL67-1,"--") -> 0.059386966 | BN69: =IFERROR(BN67/BM67-1,"--") -> 0.46180195
B70: % operating margin | C70: =IFERROR(C67/C$10,"--") -> -- | D70: =IFERROR(D67/D$10,"--") -> -- | E70: =IFERROR(E67/E$10,"--") -> -- | F70: =IFERROR(F67/F$10,"--") -> -- | G70: =IFERROR(G67/G$10,"--") -> -- | H70: =IFERROR(H67/H$10,"--") -> -3.1274342 | I70: =IFERROR(I67/I$10,"--") -> -1.8105557 | J70: =IFERROR(J67/J$10,"--") -> -1.3596234 | ... BO70: =IFERROR(BO67/BO$10,"--") -> -0.096811205
B72: Interest Income | J72: 2.025 | K72: 4.196 | L72: =SUM(H72:K72) -> 6.221 | M72: 3.594 | N72: 3.167 | O72: 2.491 | P72: 2.299 | Q72: =SUM(M72:P72) -> 11.551 | R72: 2.448 | S72: 1.689 | T72: 1.517 | U72: 1.853 | W72: 2.612 | X72: 2.19 | Y72: 1.985 | Z72: 2.342 | AB72: 4.759 | AC72: 11.692 | AD72: 21.857 | AE72: 35.531 | AG72: 43.131 | AH72: 50.28 | AI72: 53.491 | AJ72: 53.761 | AK72: =SUM(AG72:AJ72) -> 200.663 | AL72: 54.779 | AM72: 49.265 | AN72: 48.655 | AO72: 56.31 | AP72: =SUM(AL72:AO72) -> 209.009 | AQ72: 53.163 | AR72: 49.467 | AS72: 45.481 | AT72: ='IS (Non-GAAP)'!AT73 -> 45.481 | AU72: =SUM(AQ72:AT72) -> 193.592 | AV72: ='IS (Non-GAAP)'!AV73 -> 52.542541 | AW72: ='IS (Non-GAAP)'!AW73 -> 55.844677 | AX72: ='IS (Non-GAAP)'!AX73 -> 53.30925 | AY72: ='IS (Non-GAAP)'!AY73 -> 51.684826 | AZ72: =SUM(AV72:AY72) -> 213.38129 | BA72: ='IS (Non-GAAP)'!BA73 -> 59.057247 | BB72: ='IS (Non-GAAP)'!BB73 -> 66.004471 | BC72: ='IS (Non-GAAP)'!BC73 -> 67.82414 | BD72: ='IS (Non-GAAP)'!BD73 -> 70.684397 | BE72: =SUM(BA72:BD72) -> 263.57025 | BF72: ='IS (Non-GAAP)'!BF73 -> 84.006502 | BG72: ='IS (Non-GAAP)'!BG73 -> 93.330041 | BH72: ='IS (Non-GAAP)'!BH73 -> 95.979835 | BI72: ='IS (Non-GAAP)'!BI73 -> 100.59121 | BJ72: =SUM(BF72:BI72) -> 373.90759 | BK72: ='IS (Non-GAAP)'!BK73 -> 117.15836 | BL72: ='IS (Non-GAAP)'!BL73 -> 128.13914 | BM72: ='IS (Non-GAAP)'!BM73 -> 132.32357 | BN72: ='IS (Non-GAAP)'!BN73 -> 139.18875 | BO72: =SUM(BK72:BN72) -> 516.80981
B73: Interest Expense | AN73: -0.689 | AO73: -2.07 | AQ73: -2.071 | AR73: -2.074 | AS73: -2.075
B74: Other Income / (Expense), Net | G74: =SUM(C74:F74) -> 0 | H74: 1.076 | I74: 1.161 | J74: -0.18 | K74: -0.021 | L74: =SUM(H74:K74) -> 2.036 | M74: -0.287 | N74: -0.492 | O74: -0.04 | P74: -0.186 | Q74: =SUM(M74:P74) -> -1.005 | R74: 0.067 | S74: -1.109 | T74: -0.519 | U74: 0.951 | V74: =SUM(R74:U74) -> -0.61 | W74: -0.488 | X74: 8.746 | Y74: 1.609 | Z74: 19.08 | AA74: =SUM(W74:Z74) -> 28.947 | AB74: -8.481 | AC74: -22.92 | AD74: -13.271 | AE74: -2.893 | AF74: =SUM(AB74:AE74) -> -47.565 | AG74: -2.562 | AH74: 4.086 | AI74: -4.17 | AJ74: 47.533 | AK74: =SUM(AG74:AJ74) -> 44.887 | AL74: -21.302 | AM74: -7.946 | AN74: -8.474 | AO74: 2.383 | AP74: =SUM(AL74:AO74) -> -35.339 | AQ74: -28.058 | AR74: -4.985 | AS74: -1.854
B75: GAAP Income Before Taxes | C75: =C67+C74 -> 0 | D75: =D67+D74 -> 0 | E75: =E67+E74 -> 0 | F75: =F67+F74 -> 0 | G75: =SUM(C75:F75) -> 0 | H75: =SUM(H67,H72:H74) -> -40.841 | I75: =SUM(I67,I72:I74) -> -31.257 | J75: =SUM(J67,J72:J74) -> -37.149 | K75: =SUM(K67,K72:K74) -> -67.595 | L75: =SUM(H75:K75) -> -176.842 | M75: =SUM(M67,M72:M74) -> -83.968 | N75: =SUM(N67,N72:N74) -> -92.894 | O75: =SUM(O67,O72:O74) -> -87.681 | P75: =SUM(P67,P72:P74) -> -82.999 | Q75: =SUM(M75:P75) -> -347.542 | R75: =SUM(R67,R72:R74) -> -93.888 | S75: =SUM(S67,S72:S74) -> -77.103 | T75: =SUM(T67,T72:T74) -> -168.456 | U75: =SUM(U67,U72:U74) -> -197.593 | V75: =SUM(R75:U75) -> -537.04 | W75: =SUM(W67,W72:W74) -> -203.471 | X75: =SUM(X67,X72:X74) -> -189.205 | Y75: =SUM(Y67,Y72:Y74) -> -153.677 | Z75: =SUM(Z67,Z72:Z74) -> -130.607 | AA75: =SUM(W75:Z75) -> -676.96 | AB75: =SUM(AB67,AB72:AB74) -> -192.488 | AC75: =SUM(AC67,AC72:AC74) -> -218.96 | AD75: =SUM(AD67,AD72:AD74) -> -197.433 | AE75: =SUM(AE67,AE72:AE74) -> -207.112 | AF75: =SUM(AB75:AE75) -> -815.993 | AG75: =SUM(AG67,AG72:AG74) -> -232.669 | AH75: =SUM(AH67,AH72:AH74) -> -231.041 | AI75: =SUM(AI67,AI72:AI74) -> -211.302 | AJ75: =SUM(AJ67,AJ72:AJ74) -> -174.211 | AK75: =SUM(AG75:AJ75) -> -849.223 | AL75: =SUM(AL67,AL72:AL74) -> -315.095 | AM75: =SUM(AM67,AM72:AM74) -> -313.984 | AN75: =SUM(AN67,AN72:AN74) -> -325.965 | AO75: =SUM(AO67,AO72:AO74) -> -330.055 | AP75: =SUM(AL75:AO75) -> -1285.099 | AQ75: =SUM(AQ67,AQ72:AQ74) -> -424.223 | AR75: =SUM(AR67,AR72:AR74) -> -297.868 | AS75: =SUM(AS67,AS72:AS74) -> -287.921 | AT75: =SUM(AT67,AT72:AT74) -> -338.95673 | AU75: =SUM(AQ75:AT75) -> -1348.9687 | AV75: =SUM(AV67,AV72:AV74) -> -287.10928 | AW75: =SUM(AW67,AW72:AW74) -> -273.27216 | AX75: =SUM(AX67,AX72:AX74) -> -291.57207 | AY75: =SUM(AY67,AY72:AY74) -> -356.14603 | AZ75: =SUM(AV75:AY75) -> -1208.0995 | BA75: =SUM(BA67,BA72:BA74) -> -275.7374 | BB75: =SUM(BB67,BB72:BB74) -> -250.16402 | BC75: =SUM(BC67,BC72:BC74) -> -264.09805 | BD75: =SUM(BD67,BD72:BD74) -> -334.34814 | BE75: =SUM(BA75:BD75) -> -1124.3476 | BF75: =SUM(BF67,BF72:BF74) -> -223.1919 | BG75: =SUM(BG67,BG72:BG74) -> -182.72204 | BH75: =SUM(BH67,BH72:BH74) -> -197.47382 | BI75: =SUM(BI67,BI72:BI74) -> -283.82896 | BJ75: =SUM(BF75:BI75) -> -887.21671 | BK75: =SUM(BK67,BK72:BK74) -> -151.85433 | BL75: =SUM(BL67,BL72:BL74) -> -90.685591 | BM75: =SUM(BM67,BM72:BM74) -> -99.496497 | BN75: =SUM(BN67,BN72:BN74) -> -199.68627 | BO75: =SUM(BK75:BN75) -> -541.72268
B77: (Provision for) Benefit from Income Taxes | G77: =SUM(C77:F77) -> 0 | H77: -0.171 | I77: -0.155 | J77: -0.199 | K77: -0.308 | L77: =SUM(H77:K77) -> -0.833 | M77: 0.159 | N77: -0.521 | O77: -0.376 | P77: -0.255 | Q77: =SUM(M77:P77) -> -0.993 | R77: 0.244 | S77: -0.531 | T77: -0.433 | U77: -1.342 | V77: =SUM(R77:U77) -> -2.062 | W77: 0.251 | X77: -0.514 | Y77: -1.179 | Z77: -1.546 | AA77: =SUM(W77:Z77) -> -2.988 | AB77: 26.694 | AC77: -3.846 | AD77: -4.009 | AE77: -0.372 | AF77: =SUM(AB77:AE77) -> 18.467 | AG77: 6.605 | AH77: 3.721 | AI77: -3.392 | AJ77: 4.299 | AK77: =SUM(AG77:AJ77) -> 11.233 | AL77: -2.721 | AM77: -3.786 | AN77: -1.937 | AO77: 4.331 | AP77: =SUM(AL77:AO77) -> -4.113 | AQ77: -5.729 | AR77: -0.062 | AS77: -3.682 | AT77: ='IS (Non-GAAP)'!AT78 -> -33.029949 | AU77: =SUM(AQ77:AT77) -> -42.502949 | AV77: ='IS (Non-GAAP)'!AV78 -> -49.907912 | AW77: ='IS (Non-GAAP)'!AW78 -> -60.633084 | AX77: ='IS (Non-GAAP)'!AX78 -> -61.809911 | AY77: ='IS (Non-GAAP)'!AY78 -> -47.790357 | AZ77: =SUM(AV77:AY77) -> -220.14126 | BA77: ='IS (Non-GAAP)'!BA78 -> -70.589568 | BB77: ='IS (Non-GAAP)'!BB78 -> -85.772815 | BC77: ='IS (Non-GAAP)'!BC78 -> -89.316436 | BD77: ='IS (Non-GAAP)'!BD78 -> -72.564067 | BE77: =SUM(BA77:BD77) -> -318.24289 | BF77: ='IS (Non-GAAP)'!BF78 -> -101.8967 | BG77: ='IS (Non-GAAP)'!BG78 -> -121.59076 | BH77: ='IS (Non-GAAP)'!BH78 -> -128.91847 | BI77: ='IS (Non-GAAP)'!BI78 -> -108.87688 | BJ77: =SUM(BF77:BI77) -> -461.28281 | BK77: ='IS (Non-GAAP)'!BK78 -> -145.49104 | BL77: ='IS (Non-GAAP)'!BL78 -> -169.27079 | BM77: ='IS (Non-GAAP)'!BM78 -> -180.86137 | BN77: ='IS (Non-GAAP)'!BN78 -> -155.22764 | BO77: =SUM(BK77:BN77) -> -650.85084
B78: Effective Tax Rate | C78: =IFERROR(IF(AND(C75>=0,C77>=0),-1*(C77/C75),IF(AND(C75>=0,C77<0),-1*(C77/C75),IF(AND(C75<0,C77>=0),(C77/C75),C77/C75))),"--") -> -- | D78: =IFERROR(IF(AND(D75>=0,D77>=0),-1*(D77/D75),IF(AND(D75>=0,D77<0),-1*(D77/D75),IF(AND(D75<0,D77>=0),(D77/D75),D77/D75))),"--") -> -- | E78: =IFERROR(IF(AND(E75>=0,E77>=0),-1*(E77/E75),IF(AND(E75>=0,E77<0),-1*(E77/E75),IF(AND(E75<0,E77>=0),(E77/E75),E77/E75))),"--") -> -- | F78: =IFERROR(IF(AND(F75>=0,F77>=0),-1*(F77/F75),IF(AND(F75>=0,F77<0),-1*(F77/F75),IF(AND(F75<0,F77>=0),(F77/F75),F77/F75))),"--") -> -- | G78: =IFERROR(IF(AND(G75>=0,G77>=0),-1*(G77/G75),IF(AND(G75>=0,G77<0),-1*(G77/G75),IF(AND(G75<0,G77>=0),(G77/G75),G77/G75))),"--") -> -- | H78: =IFERROR(IF(AND(H75>=0,H77>=0),-1*(H77/H75),IF(AND(H75>=0,H77<0),-1*(H77/H75),IF(AND(H75<0,H77>=0),(H77/H75),H77/H75))),"--") -> 0.004186969 | I78: =IFERROR(IF(AND(I75>=0,I77>=0),-1*(I77/I75),IF(AND(I75>=0,I77<0),-1*(I77/I75),IF(AND(I75<0,I77>=0),(I77/I75),I77/I75))),"--") -> 0.0049588892 | J78: =IFERROR(IF(AND(J75>=0,J77>=0),-1*(J77/J75),IF(AND(J75>=0,J77<0),-1*(J77/J75),IF(AND(J75<0,J77>=0),(J77/J75),J77/J75))),"--") -> 0.0053568064 | ... BO78: =IFERROR(IF(AND(BO75>=0,BO77>=0),-1*(BO77/BO75),IF(AND(BO75>=0,BO77<0),-1*(BO77/BO75),IF(AND(BO75<0,BO77>=0),(BO77/BO75),BO77/BO75))),"--") -> 1.2014465
B80: GAAP Net Income | C80: =C75+C77 -> 0 | D80: =D75+D77 -> 0 | E80: =E75+E77 -> 0 | F80: =F75+F77 -> 0 | G80: =SUM(C80:F80) -> 0 | H80: =H75+H77 -> -41.012 | I80: =I75+I77 -> -31.412 | J80: =J75+J77 -> -37.348 | K80: =K75+K77 -> -67.903 | L80: =SUM(H80:K80) -> -177.675 | M80: =M75+M77 -> -83.809 | N80: =N75+N77 -> -93.415 | O80: =O75+O77 -> -88.057 | P80: =P75+P77 -> -83.254 | Q80: =SUM(M80:P80) -> -348.535 | R80: =R75+R77 -> -93.644 | S80: =S75+S77 -> -77.634 | T80: =T75+T77 -> -168.889 | U80: =U75+U77 -> -198.935 | V80: =SUM(R80:U80) -> -539.102 | W80: =W75+W77 -> -203.22 | X80: =X75+X77 -> -189.719 | Y80: =Y75+Y77 -> -154.856 | Z80: =Z75+Z77 -> -132.153 | AA80: =SUM(W80:Z80) -> -679.948 | AB80: =AB75+AB77 -> -165.794 | AC80: =AC75+AC77 -> -222.806 | AD80: =AD75+AD77 -> -201.442 | AE80: =AE75+AE77 -> -207.484 | AF80: =SUM(AB80:AE80) -> -797.526 | AG80: =AG75+AG77 -> -226.064 | AH80: =AH75+AH77 -> -227.32 | AI80: =AI75+AI77 -> -214.694 | AJ80: =AJ75+AJ77 -> -169.912 | AK80: =SUM(AG80:AJ80) -> -837.99 | AL80: =AL75+AL77 -> -317.816 | AM80: =AM75+AM77 -> -317.77 | AN80: =AN75+AN77 -> -327.902 | AO80: =AO75+AO77 -> -325.724 | AP80: =SUM(AL80:AO80) -> -1289.212 | AQ80: =AQ75+AQ77 -> -429.952 | AR80: =AR75+AR77 -> -297.93 | AS80: =AS75+AS77 -> -291.603 | AT80: =AT75+AT77 -> -371.98667 | AU80: =SUM(AQ80:AT80) -> -1391.4717 | AV80: =AV75+AV77 -> -337.01719 | AW80: =AW75+AW77 -> -333.90524 | AX80: =AX75+AX77 -> -353.38198 | AY80: =AY75+AY77 -> -403.93639 | AZ80: =SUM(AV80:AY80) -> -1428.2408 | BA80: =BA75+BA77 -> -346.32696 | BB80: =BB75+BB77 -> -335.93684 | BC80: =BC75+BC77 -> -353.41449 | BD80: =BD75+BD77 -> -406.9122 | BE80: =SUM(BA80:BD80) -> -1442.5905 | BF80: =BF75+BF77 -> -325.0886 | BG80: =BG75+BG77 -> -304.3128 | BH80: =BH75+BH77 -> -326.39229 | BI80: =BI75+BI77 -> -392.70584 | BJ80: =SUM(BF80:BI80) -> -1348.4995 | BK80: =BK75+BK77 -> -297.34537 | BL80: =BL75+BL77 -> -259.95638 | BM80: =BM75+BM77 -> -280.35787 | BN80: =BN75+BN77 -> -354.91391 | BO80: =SUM(BK80:BN80) -> -1192.5735
B81: % GAAP net margin | C81: =IFERROR(C80/C10,"--") -> -- | D81: =IFERROR(D80/D10,"--") -> -- | E81: =IFERROR(E80/E10,"--") -> -- | F81: =IFERROR(F80/F10,"--") -> -- | G81: =IFERROR(G80/G10,"--") -> -- | H81: =IFERROR(H80/H10,"--") -> -3.059912 | I81: =IFERROR(I80/I10,"--") -> -1.7543703 | J81: =IFERROR(J80/J10,"--") -> -1.3022315 | ... BO81: =IFERROR(BO80/BO10,"--") -> -0.10907032
B83: Other Comprehensive Income (Loss), Net of Taxes
B84: Net Loss Attributable to Noncontrolling Interest | AD84: -0.506 | AE84: -0.315 | AF84: =SUM(AB84:AE84) -> -0.821 | AG84: -0.437 | AH84: -0.453 | AI84: -0.443 | AJ84: -0.56 | AK84: =SUM(AG84:AJ84) -> -1.893 | AL84: -0.828 | AM84: -0.871 | AN84: -3.623 | AO84: 1.75 | AP84: =SUM(AL84:AO84) -> -3.572 | AQ84: 0.14 | AR84: 0.087 | AS84: 2.354
B85: Comprehensive Loss | R85: =R80-R84 -> -93.644 | S85: =S80-S84 -> -77.634 | T85: =T80-T84 -> -168.889 | U85: =U80-U84 -> -198.935 | V85: =SUM(R85:U85) -> -539.102 | W85: =W80-W84 -> -203.22 | X85: =X80-X84 -> -189.719 | Y85: =Y80-Y84 -> -154.856 | Z85: =Z80-Z84 -> -132.153 | AA85: =SUM(W85:Z85) -> -679.948 | AB85: =AB80-AB84 -> -165.794 | AC85: =AC80-AC84 -> -222.806 | AD85: =AD80-AD84 -> -200.936 | AE85: =AE80-AE84 -> -207.169 | AF85: =SUM(AB85:AE85) -> -796.705 | AG85: =AG80-AG84 -> -225.627 | AH85: =AH80-AH84 -> -226.867 | AI85: =AI80-AI84 -> -214.251 | AJ85: =AJ80-AJ84 -> -169.352 | AK85: =SUM(AG85:AJ85) -> -836.097 | AL85: =AL80-AL84 -> -316.988 | AM85: =AM80-AM84 -> -316.899 | AN85: =AN80-AN84 -> -324.279 | AO85: =AO80-AO84 -> -327.474 | AP85: =SUM(AL85:AO85) -> -1285.64 | AQ85: =AQ80-AQ84 -> -430.092 | AR85: =AR80-AR84 -> -298.017 | AS85: =AS80-AS84 -> -293.957 | AT85: =AT80-AT84 -> -371.98667 | AU85: =SUM(AQ85:AT85) -> -1394.0527 | AV85: =AV80-AV84 -> -337.01719 | AW85: =AW80-AW84 -> -333.90524 | AX85: =AX80-AX84 -> -353.38198 | AY85: =AY80-AY84 -> -403.93639 | AZ85: =SUM(AV85:AY85) -> -1428.2408 | BA85: =BA80-BA84 -> -346.32696 | BB85: =BB80-BB84 -> -335.93684 | BC85: =BC80-BC84 -> -353.41449 | BD85: =BD80-BD84 -> -406.9122 | BE85: =SUM(BA85:BD85) -> -1442.5905 | BF85: =BF80-BF84 -> -325.0886 | BG85: =BG80-BG84 -> -304.3128 | BH85: =BH80-BH84 -> -326.39229 | BI85: =BI80-BI84 -> -392.70584 | BJ85: =SUM(BF85:BI85) -> -1348.4995 | BK85: =BK80-BK84 -> -297.34537 | BL85: =BL80-BL84 -> -259.95638 | BM85: =BM80-BM84 -> -280.35787 | BN85: =BN80-BN84 -> -354.91391 | BO85: =SUM(BK85:BN85) -> -1192.5735
B87: GAAP EPS (Basic) | C87: =IFERROR(C80/C90,"--") -> -- | D87: =IFERROR(D80/D90,"--") -> -- | E87: =IFERROR(E80/E90,"--") -> -- | F87: =IFERROR(F80/F90,"--") -> -- | G87: =IFERROR(G80/G90,"--") -> -- | H87: =IFERROR(H80/H90,"--") -> -- | I87: =IFERROR(I80/I90,"--") -> -- | J87: =IFERROR(J80/J90,"--") -> -- | ... BO87: =IFERROR(BO80/BO90,"--") -> -3.2657104
B88: GAAP EPS (Diluted) | C88: =IFERROR(C$80/C91,"--") -> -- | D88: =IFERROR(D$80/D91,"--") -> -- | E88: =IFERROR(E$80/E91,"--") -> -- | F88: =IFERROR(F$80/F91,"--") -> -- | G88: =IFERROR(G80/G91,"--") -> -- | H88: =IFERROR(H$80/H91,"--") -> -- | I88: =IFERROR(I$80/I91,"--") -> -- | J88: =IFERROR(J$80/J91,"--") -> -- | K88: =IFERROR(K$80/K91,"--") -> -- | L88: =IFERROR(L80/L91,"--") -> -- | M88: =IFERROR(M$80/M91,"--") -> -- | N88: =IFERROR(N$80/N91,"--") -> -- | O88: =IFERROR(O$80/O91,"--") -> -- | P88: =IFERROR(P$80/P91,"--") -> -- | Q88: =IFERROR(Q80/Q91,"--") -> -- | R88: =IFERROR(R$80/R91,"--") -> -- | S88: =IFERROR(S$80/S91,"--") -> -- | T88: =IFERROR(T$80/T91,"--") -> -1.0121102 | U88: =IFERROR(U$80/U91,"--") -> -0.70017512 | V88: =IFERROR(V80/V91,"--") -> -2.3907494 | W88: =IFERROR(W$80/W91,"--") -> -0.69742577 | X88: =IFERROR(X$80/X91,"--") -> -0.6372459 | Y88: =IFERROR(Y$80/Y91,"--") -> -0.51106463 | Z88: =IFERROR(Z$80/Z91,"--") -> -0.4281043 | AA88: =IFERROR(AA80/AA91,"--") -> -2.2649775 | AB88: =IFERROR(AB$80/AB91,"--") -> -0.52740003 | AC88: =IFERROR(AC$80/AC91,"--") -> -0.6998643 | AD88: =IFERROR(AD$80/AD91,"--") -> -0.62924079 | AE88: =IFERROR(AE$80/AE91,"--") -> -0.64451237 | AF88: =IFERROR(AF80/AF91,"--") -> -2.502482 | AG88: =IFERROR(AG$80/AG91,"--") -> -0.69739046 | AH88: =IFERROR(AH$80/AH91,"--") -> -0.69445675 | AI88: =IFERROR(AI$80/AI91,"--") -> -0.65195105 | AJ88: =IFERROR(AJ$80/AJ91,"--") -> -0.51320682 | AK88: =IFERROR(AK80/AK91,"--") -> -2.5550793 | AL88: =IFERROR(AL$80/AL91,"--") -> -0.95273155 | AM88: =IFERROR(AM$80/AM91,"--") -> -0.94941455 | AN88: =IFERROR(AN$80/AN91,"--") -> -0.98836813 | AO88: =IFERROR(AO$80/AO91,"--") -> -0.98277776 | AP88: =IFERROR(AP80/AP91,"--") -> -3.8730253 | AQ88: =IFERROR(AQ$80/AQ91,"--") -> -1.2924784 | AR88: =IFERROR(AR$80/AR91,"--") -> -0.88877288 | AS88: =IFERROR(AS$80/AS91,"--") -> -0.78103832 | AT88: =IFERROR(AT$80/AT91,"--") -> -0.99031208 | AU88: =IFERROR(AU80/AU91,"--") -> -3.9283509 | AV88: =IFERROR(AV$80/AV91,"--") -> -0.8879392 | AW88: =IFERROR(AW$80/AW91,"--") -> -0.87755467 | AX88: =IFERROR(AX$80/AX91,"--") -> -0.92639081 | AY88: =IFERROR(AY$80/AY91,"--") -> -1.0561886 | AZ88: =IFERROR(AZ80/AZ91,"--") -> -3.7487787 | BA88: =IFERROR(BA$80/BA91,"--") -> -0.90146957 | BB88: =IFERROR(BB$80/BB91,"--") -> -0.86989608 | BC88: =IFERROR(BC$80/BC91,"--") -> -0.91043872 | BD88: =IFERROR(BD$80/BD91,"--") -> -1.0428822 | BE88: =IFERROR(BE80/BE91,"--") -> -3.7258869 | BF88: =IFERROR(BF$80/BF91,"--") -> -0.82892612 | BG88: =IFERROR(BG$80/BG91,"--") -> -0.77201399 | BH88: =IFERROR(BH$80/BH91,"--") -> -0.82384759 | BI88: =IFERROR(BI$80/BI91,"--") -> -0.98625099 | BJ88: =IFERROR(BJ80/BJ91,"--") -> -3.4123642 | BK88: =IFERROR(BK$80/BK91,"--") -> -0.74302827 | BL88: =IFERROR(BL$80/BL91,"--") -> -0.64636756 | BM88: =IFERROR(BM$80/BM91,"--") -> -0.69364533 | BN88: =IFERROR(BN$80/BN91,"--") -> -0.87378388 | BO88: =IFERROR(BO80/BO91,"--") -> -2.9579152
B90: Weighted Average Basic Shares Outstanding | R90: 235.137 | S90: 241.1 | T90: 166.8682 | U90: 284.12178 | V90: =IFERROR(AVERAGE(R90:U90),"--") -> 231.80674 | W90: 291.38585 | X90: 297.7171 | Y90: 303.00669 | Z90: 308.69347 | AA90: =IFERROR(AVERAGE(W90:Z90),"--") -> 300.20078 | AB90: 314.361 | AC90: 318.356 | AD90: 320.135 | AE90: 321.924 | AF90: =IFERROR(AVERAGE(AB90:AE90),"--") -> 318.694 | AG90: 324.157 | AH90: 327.335 | AI90: 329.31 | AJ90: 331.079 | AK90: =IFERROR(AVERAGE(AG90:AJ90),"--") -> 327.97025 | AL90: 333.584 | AM90: 334.701 | AN90: 331.761 | AO90: 331.432 | AP90: =IFERROR(AVERAGE(AL90:AO90),"--") -> 332.8695 | AQ90: 332.657 | AR90: 335.215 | AS90: 339.648 | AT90: ='IS (Non-GAAP)'!AT91 -> 340.62571 | AU90: =IFERROR(AVERAGE(AQ90:AT90),"--") -> 337.03643 | AV90: ='IS (Non-GAAP)'!AV91 -> 341.54985 | AW90: ='IS (Non-GAAP)'!AW91 -> 342.49509 | AX90: ='IS (Non-GAAP)'!AX91 -> 343.46101 | AY90: ='IS (Non-GAAP)'!AY91 -> 344.44721 | AZ90: =IFERROR(AVERAGE(AV90:AY90),"--") -> 342.98829 | BA90: ='IS (Non-GAAP)'!BA91 -> 346.18043 | BB90: ='IS (Non-GAAP)'!BB91 -> 348.18043 | BC90: ='IS (Non-GAAP)'!BC91 -> 350.18043 | BD90: ='IS (Non-GAAP)'!BD91 -> 352.18043 | BE90: =IFERROR(AVERAGE(BA90:BD90),"--") -> 349.18043 | BF90: ='IS (Non-GAAP)'!BF91 -> 354.18043 | BG90: ='IS (Non-GAAP)'!BG91 -> 356.18043 | BH90: ='IS (Non-GAAP)'!BH91 -> 358.18043 | BI90: ='IS (Non-GAAP)'!BI91 -> 360.18043 | BJ90: =IFERROR(AVERAGE(BF90:BI90),"--") -> 357.18043 | BK90: ='IS (Non-GAAP)'!BK91 -> 362.18043 | BL90: ='IS (Non-GAAP)'!BL91 -> 364.18043 | BM90: ='IS (Non-GAAP)'!BM91 -> 366.18043 | BN90: ='IS (Non-GAAP)'!BN91 -> 368.18043 | BO90: =IFERROR(AVERAGE(BK90:BN90),"--") -> 365.18043
A91: WADSO | B91: Weighted Average Diluted Shares Outstanding | T91: 166.8682 | U91: 284.12178 | V91: =IFERROR(AVERAGE(R91:U91),"--") -> 225.49499 | W91: 291.38585 | X91: 297.7171 | Y91: 303.00669 | Z91: 308.69347 | AA91: =IFERROR(AVERAGE(W91:Z91),"--") -> 300.20078 | AB91: 314.361 | AC91: 318.356 | AD91: 320.135 | AE91: 321.924 | AF91: =IFERROR(AVERAGE(AB91:AE91),"--") -> 318.694 | AG91: 324.157 | AH91: 327.335 | AI91: 329.31 | AJ91: 331.079 | AK91: =IFERROR(AVERAGE(AG91:AJ91),"--") -> 327.97025 | AL91: 333.584 | AM91: 334.701 | AN91: 331.761 | AO91: 331.432 | AP91: =IFERROR(AVERAGE(AL91:AO91),"--") -> 332.8695 | AQ91: 332.657 | AR91: 335.215 | AS91: 373.353 | AT91: ='IS (Non-GAAP)'!AT92 -> 375.62571 | AU91: =IFERROR(AVERAGE(AQ91:AT91),"--") -> 354.21268 | AV91: ='IS (Non-GAAP)'!AV92 -> 379.54985 | AW91: ='IS (Non-GAAP)'!AW92 -> 380.49509 | AX91: ='IS (Non-GAAP)'!AX92 -> 381.46101 | AY91: ='IS (Non-GAAP)'!AY92 -> 382.44721 | AZ91: =IFERROR(AVERAGE(AV91:AY91),"--") -> 380.98829 | BA91: ='IS (Non-GAAP)'!BA92 -> 384.18043 | BB91: ='IS (Non-GAAP)'!BB92 -> 386.18043 | BC91: ='IS (Non-GAAP)'!BC92 -> 388.18043 | BD91: ='IS (Non-GAAP)'!BD92 -> 390.18043 | BE91: =IFERROR(AVERAGE(BA91:BD91),"--") -> 387.18043 | BF91: ='IS (Non-GAAP)'!BF92 -> 392.18043 | BG91: ='IS (Non-GAAP)'!BG92 -> 394.18043 | BH91: ='IS (Non-GAAP)'!BH92 -> 396.18043 | BI91: ='IS (Non-GAAP)'!BI92 -> 398.18043 | BJ91: =IFERROR(AVERAGE(BF91:BI91),"--") -> 395.18043 | BK91: ='IS (Non-GAAP)'!BK92 -> 400.18043 | BL91: ='IS (Non-GAAP)'!BL92 -> 402.18043 | BM91: ='IS (Non-GAAP)'!BM92 -> 404.18043 | BN91: ='IS (Non-GAAP)'!BN92 -> 406.18043 | BO91: =IFERROR(AVERAGE(BK91:BN91),"--") -> 403.18043

Sheet IS (Non-GAAP)
B2: Snowflake Inc.
B3: Fiscal Year Ends Jan. 31
B4: ($ millions, except per share amounts)
C6: =Dates!M3 -> 2018 (A) | H6: =Dates!R3 -> 2019 (A) | M6: =Dates!W3 -> 2020 (A) | R6: =Dates!AB3 -> 2021 (A) | W6: =Dates!AG3 -> 2022 (A) | AB6: =Dates!AL3 -> 2023 (A) | AG6: =Dates!AQ3 -> 2024 (A) | AL6: =Dates!AV3 -> 2025 (A) | AQ6: =Dates!BA3 -> 2026 (E) | AV6: =Dates!BF3 -> 2027 (E) | BA6: =Dates!BK3 -> 2028 (E) | BF6: =Dates!BP3 -> 2029 (E) | BK6: =Dates!BU3 -> 2030 (E)
C7: =Dates!M4 -> 1Q18 (A) | D7: =Dates!N4 -> 2Q18 (A) | E7: =Dates!O4 -> 3Q18 (A) | F7: =Dates!P4 -> 4Q18 (A) | G7: =Dates!Q4 -> FY18 (A) | H7: =Dates!R4 -> 1Q19 (A) | I7: =Dates!S4 -> 2Q19 (A) | J7: =Dates!T4 -> 3Q19 (A) | ... BO7: =Dates!BY4 -> FY30 (E)
C8: =Dates!M5 -> 42855 | D8: =Dates!N5 -> 42947 | E8: =Dates!O5 -> 43039 | F8: =Dates!P5 -> 43131 | G8: =Dates!Q5 -> 43131 | H8: =Dates!R5 -> 43220 | I8: =Dates!S5 -> 43312 | J8: =Dates!T5 -> 43404 | ... BO8: =Dates!BY5 -> 47514
A10: TREV | B10: Total Revenue | C10: =SUM(C14,C19) -> 0 | D10: =SUM(D14,D19) -> 0 | E10: =SUM(E14,E19) -> 0 | F10: =SUM(F14,F19) -> 0 | G10: =SUM(C10:F10) -> 0 | H10: =SUM(H14,H19) -> 13.403 | I10: =SUM(I14,I19) -> 17.905 | J10: =SUM(J14,J19) -> 28.68 | K10: =SUM(K14,K19) -> 36.678 | L10: =SUM(H10:K10) -> 96.666 | M10: =SUM(M14,M19) -> 43.705 | N10: =SUM(N14,N19) -> 60.339 | O10: =SUM(O14,O19) -> 73.012 | P10: =SUM(P14,P19) -> 87.692 | Q10: =SUM(M10:P10) -> 264.748 | R10: =SUM(R14,R19) -> 108.815 | S10: =SUM(S14,S19) -> 133.145 | T10: =SUM(T14,T19) -> 159.624 | U10: =SUM(U14,U19) -> 190.465 | V10: =SUM(R10:U10) -> 592.049 | W10: =SUM(W14,W19) -> 228.914 | X10: =SUM(X14,X19) -> 272.198 | Y10: =SUM(Y14,Y19) -> 334.441 | Z10: =SUM(Z14,Z19) -> 383.774 | AA10: =SUM(W10:Z10) -> 1219.327 | AB10: =SUM(AB14,AB19) -> 422.371 | AC10: =SUM(AC14,AC19) -> 497.248 | AD10: =SUM(AD14,AD19) -> 557.028 | AE10: =SUM(AE14,AE19) -> 589.012 | AF10: =SUM(AB10:AE10) -> 2065.659 | AG10: =SUM(AG14,AG19) -> 623.599 | AH10: =SUM(AH14,AH19) -> 674.018 | AI10: =SUM(AI14,AI19) -> 734.173 | AJ10: =SUM(AJ14,AJ19) -> 774.699 | AK10: =SUM(AG10:AJ10) -> 2806.489 | AL10: =SUM(AL14,AL19) -> 828.709 | AM10: =SUM(AM14,AM19) -> 868.823 | AN10: =SUM(AN14,AN19) -> 942.094 | AO10: =SUM(AO14,AO19) -> 986.77 | AP10: =SUM(AL10:AO10) -> 3626.396 | AQ10: =SUM(AQ14,AQ19) -> 1042.074 | AR10: =SUM(AR14,AR19) -> 1144.969 | AS10: =SUM(AS14,AS19) -> 1212.909 | AT10: =SUM(AT14,AT19) -> 1248.8031 | AU10: =SUM(AQ10:AT10) -> 4648.7551 | AV10: =SUM(AV14,AV19) -> 1313.011 | AW10: =SUM(AW14,AW19) -> 1415.0354 | AX10: =SUM(AX14,AX19) -> 1502.3143 | AY10: =SUM(AY14,AY19) -> 1549.2272 | AZ10: =SUM(AV10:AY10) -> 5779.5879 | BA10: =SUM(BA14,BA19) -> 1629.2553 | BB10: =SUM(BB14,BB19) -> 1760.8179 | BC10: =SUM(BC14,BC19) -> 1874.5414 | BD10: =SUM(BD14,BD19) -> 1913.7314 | BE10: =SUM(BA10:BD10) -> 7178.346 | BF10: =SUM(BF14,BF19) -> 1996.5102 | BG10: =SUM(BG14,BG19) -> 2152.728 | BH10: =SUM(BH14,BH19) -> 2332.7606 | BI10: =SUM(BI14,BI19) -> 2391.9909 | BJ10: =SUM(BF10:BI10) -> 8873.9896 | BK10: =SUM(BK14,BK19) -> 2482.3192 | BL10: =SUM(BL14,BL19) -> 2642.7389 | BM10: =SUM(BM14,BM19) -> 2883.1165 | BN10: =SUM(BN14,BN19) -> 2925.8128 | BO10: =SUM(BK10:BN10) -> 10933.987
A11: TREVYY | B11: % yoy | C11: -- | D11: -- | E11: -- | F11: -- | G11: -- | H11: =IFERROR(H10/C10-1,"--") -> -- | I11: =IFERROR(I10/D10-1,"--") -> -- | J11: =IFERROR(J10/E10-1,"--") -> -- | K11: =IFERROR(K10/F10-1,"--") -> -- | L11: =IFERROR(L10/G10-1,"--") -> -- | M11: =IFERROR(M10/H10-1,"--") -> 2.2608371 | N11: =IFERROR(N10/I10-1,"--") -> 2.3699525 | O11: =IFERROR(O10/J10-1,"--") -> 1.5457462 | ... BO11: =IFERROR(BO10/BJ10-1,"--") -> 0.23213886
A12: TREVQQ | B12: % qoq | C12: -- | D12: =IFERROR(D10/C10-1,"--") -> -- | E12: =IFERROR(E10/D10-1,"--") -> -- | F12: =IFERROR(F10/E10-1,"--") -> -- | H12: =IFERROR(H10/F10-1,"--") -> -- | I12: =IFERROR(I10/H10-1,"--") -> 0.33589495 | J12: =IFERROR(J10/I10-1,"--") -> 0.60178721 | K12: =IFERROR(K10/J10-1,"--") -> 0.27887029 | M12: =IFERROR(M10/K10-1,"--") -> 0.19158624 | N12: =IFERROR(N10/M10-1,"--") -> 0.38059719 | O12: =IFERROR(O10/N10-1,"--") -> 0.21003 | P12: =IFERROR(P10/O10-1,"--") -> 0.20106284 | R12: =IFERROR(R10/P10-1,"--") -> 0.24087716 | S12: =IFERROR(S10/R10-1,"--") -> 0.2235905 | T12: =IFERROR(T10/S10-1,"--") -> 0.19887341 | U12: =IFERROR(U10/T10-1,"--") -> 0.19321029 | W12: =IFERROR(W10/U10-1,"--") -> 0.20186911 | X12: =IFERROR(X10/W10-1,"--") -> 0.18908411 | Y12: =IFERROR(Y10/X10-1,"--") -> 0.2286681 | Z12: =IFERROR(Z10/Y10-1,"--") -> 0.14750883 | AB12: =IFERROR(AB10/Z10-1,"--") -> 0.10057221 | AC12: =IFERROR(AC10/AB10-1,"--") -> 0.1772778 | AD12: =IFERROR(AD10/AC10-1,"--") -> 0.1202217 | AE12: =IFERROR(AE10/AD10-1,"--") -> 0.057419017 | AG12: =IFERROR(AG10/AE10-1,"--") -> 0.058720366 | AH12: =IFERROR(AH10/AG10-1,"--") -> 0.080851637 | AI12: =IFERROR(AI10/AH10-1,"--") -> 0.089248358 | AJ12: =IFERROR(AJ10/AI10-1,"--") -> 0.055199524 | AL12: =IFERROR(AL10/AJ10-1,"--") -> 0.0697174 | AM12: =IFERROR(AM10/AL10-1,"--") -> 0.048405411 | AN12: =IFERROR(AN10/AM10-1,"--") -> 0.084333633 | AO12: =IFERROR(AO10/AN10-1,"--") -> 0.047422019 | AQ12: =IFERROR(AQ10/AO10-1,"--") -> 0.056045482 | AR12: =IFERROR(AR10/AQ10-1,"--") -> 0.098740588 | AS12: =IFERROR(AS10/AR10-1,"--") -> 0.059337851 | AT12: =IFERROR(AT10/AS10-1,"--") -> 0.029593363 | AV12: =IFERROR(AV10/AT10-1,"--") -> 0.051415566 | AW12: =IFERROR(AW10/AV10-1,"--") -> 0.077702662 | AX12: =IFERROR(AX10/AW10-1,"--") -> 0.061679661 | AY12: =IFERROR(AY10/AX10-1,"--") -> 0.031227037 | BA12: =IFERROR(BA10/AY10-1,"--") -> 0.051656838 | BB12: =IFERROR(BB10/BA10-1,"--") -> 0.080750139 | BC12: =IFERROR(BC10/BB10-1,"--") -> 0.06458557 | BD12: =IFERROR(BD10/BC10-1,"--") -> 0.020906453 | BF12: =IFERROR(BF10/BD10-1,"--") -> 0.043255196 | BG12: =IFERROR(BG10/BF10-1,"--") -> 0.078245432 | BH12: =IFERROR(BH10/BG10-1,"--") -> 0.08362997 | BI12: =IFERROR(BI10/BH10-1,"--") -> 0.025390643 | BK12: =IFERROR(BK10/BI10-1,"--") -> 0.037762815 | BL12: =IFERROR(BL10/BK10-1,"--") -> 0.064624957 | BM12: =IFERROR(BM10/BL10-1,"--") -> 0.090957753 | BN12: =IFERROR(BN10/BM10-1,"--") -> 0.014809061
B14: Product Revenue | G14: =SUM(C14:F14) -> 0 | H14: ='IS (GAAP)'!H14 -> 13.186 | I14: ='IS (GAAP)'!I14 -> 17.675 | J14: ='IS (GAAP)'!J14 -> 28.457 | K14: ='IS (GAAP)'!K14 -> 36.365 | L14: =SUM(H14:K14) -> 95.683 | M14: ='IS (GAAP)'!M14 -> 42.766 | N14: ='IS (GAAP)'!N14 -> 57.818 | O14: ='IS (GAAP)'!O14 -> 69.213 | P14: ='IS (GAAP)'!P14 -> 82.432 | Q14: =SUM(M14:P14) -> 252.229 | R14: ='IS (GAAP)'!R14 -> 101.817 | S14: ='IS (GAAP)'!S14 -> 125.216 | T14: ='IS (GAAP)'!T14 -> 148.473 | U14: ='IS (GAAP)'!U14 -> 178.288 | V14: =SUM(R14:U14) -> 553.794 | W14: ='IS (GAAP)'!W14 -> 213.83 | X14: ='IS (GAAP)'!X14 -> 254.623 | Y14: ='IS (GAAP)'!Y14 -> 312.458 | Z14: ='IS (GAAP)'!Z14 -> 359.558 | AA14: =SUM(W14:Z14) -> 1140.469 | AB14: ='IS (GAAP)'!AB14 -> 394.434 | AC14: ='IS (GAAP)'!AC14 -> 466.268 | AD14: ='IS (GAAP)'!AD14 -> 522.752 | AE14: ='IS (GAAP)'!AE14 -> 555.329 | AF14: =SUM(AB14:AE14) -> 1938.783 | AG14: ='IS (GAAP)'!AG14 -> 590.072 | AH14: ='IS (GAAP)'!AH14 -> 640.209 | AI14: ='IS (GAAP)'!AI14 -> 698.478 | AJ14: ='IS (GAAP)'!AJ14 -> 738.09 | AK14: =SUM(AG14:AJ14) -> 2666.849 | AL14: ='IS (GAAP)'!AL14 -> 789.587 | AM14: ='IS (GAAP)'!AM14 -> 829.25 | AN14: ='IS (GAAP)'!AN14 -> 900.282 | AO14: ='IS (GAAP)'!AO14 -> 943.303 | AP14: =SUM(AL14:AO14) -> 3462.422 | AQ14: ='IS (GAAP)'!AQ14 -> 996.813 | AR14: ='IS (GAAP)'!AR14 -> 1090.496 | AS14: ='IS (GAAP)'!AS14 -> 1158.377 | AT14: ='IS (GAAP)'!AT14 -> 1198.816 | AU14: =SUM(AQ14:AT14) -> 4444.502 | AV14: ='IS (GAAP)'!AV14 -> 1261.6397 | AW14: ='IS (GAAP)'!AW14 -> 1353.2086 | AX14: ='IS (GAAP)'!AX14 -> 1440.4205 | AY14: ='IS (GAAP)'!AY14 -> 1492.4918 | AZ14: =SUM(AV14:AY14) -> 5547.7607 | BA14: ='IS (GAAP)'!BA14 -> 1571.2058 | BB14: ='IS (GAAP)'!BB14 -> 1690.9536 | BC14: ='IS (GAAP)'!BC14 -> 1804.6013 | BD14: ='IS (GAAP)'!BD14 -> 1849.6205 | BE14: =SUM(BA14:BD14) -> 6916.3812 | BF14: ='IS (GAAP)'!BF14 -> 1931.2045 | BG14: ='IS (GAAP)'!BG14 -> 2074.1306 | BH14: ='IS (GAAP)'!BH14 -> 2254.078 | BI14: ='IS (GAAP)'!BI14 -> 2319.8661 | BJ14: =SUM(BF14:BI14) -> 8579.2792 | BK14: ='IS (GAAP)'!BK14 -> 2408.8503 | BL14: ='IS (GAAP)'!BL14 -> 2554.3169 | BM14: ='IS (GAAP)'!BM14 -> 2794.5987 | BN14: ='IS (GAAP)'!BN14 -> 2844.6724 | BO14: =SUM(BK14:BN14) -> 10602.438
B15: % yoy | C15: -- | D15: -- | E15: -- | F15: -- | G15: -- | H15: =IFERROR(H14/C14-1,"--") -> -- | I15: =IFERROR(I14/D14-1,"--") -> -- | J15: =IFERROR(J14/E14-1,"--") -> -- | K15: =IFERROR(K14/F14-1,"--") -> -- | L15: =IFERROR(L14/G14-1,"--") -> -- | M15: =IFERROR(M14/H14-1,"--") -> 2.2432883 | N15: =IFERROR(N14/I14-1,"--") -> 2.271174 | O15: =IFERROR(O14/J14-1,"--") -> 1.4321959 | ... BO15: =IFERROR(BO14/BJ14-1,"--") -> 0.23581923
B16: % qoq | C16: -- | D16: =IFERROR(D14/C14-1,"--") -> -- | E16: =IFERROR(E14/D14-1,"--") -> -- | F16: =IFERROR(F14/E14-1,"--") -> -- | H16: =IFERROR(H14/F14-1,"--") -> -- | I16: =IFERROR(I14/H14-1,"--") -> 0.34043683 | J16: =IFERROR(J14/I14-1,"--") -> 0.61001414 | K16: =IFERROR(K14/J14-1,"--") -> 0.27789296 | M16: =IFERROR(M14/K14-1,"--") -> 0.1760209 | N16: =IFERROR(N14/M14-1,"--") -> 0.35196184 | O16: =IFERROR(O14/N14-1,"--") -> 0.19708395 | P16: =IFERROR(P14/O14-1,"--") -> 0.19099013 | R16: =IFERROR(R14/P14-1,"--") -> 0.23516353 | S16: =IFERROR(S14/R14-1,"--") -> 0.22981427 | T16: =IFERROR(T14/S14-1,"--") -> 0.18573505 | U16: =IFERROR(U14/T14-1,"--") -> 0.20081092 | W16: =IFERROR(W14/U14-1,"--") -> 0.19935161 | X16: =IFERROR(X14/W14-1,"--") -> 0.19077304 | Y16: =IFERROR(Y14/X14-1,"--") -> 0.22713973 | Z16: =IFERROR(Z14/Y14-1,"--") -> 0.15074026 | AB16: =IFERROR(AB14/Z14-1,"--") -> 0.096996868 | AC16: =IFERROR(AC14/AB14-1,"--") -> 0.18211919 | AD16: =IFERROR(AD14/AC14-1,"--") -> 0.12114063 | AE16: =IFERROR(AE14/AD14-1,"--") -> 0.062318269 | AG16: =IFERROR(AG14/AE14-1,"--") -> 0.062562913 | AH16: =IFERROR(AH14/AG14-1,"--") -> 0.084967597 | AI16: =IFERROR(AI14/AH14-1,"--") -> 0.09101559 | AJ16: =IFERROR(AJ14/AI14-1,"--") -> 0.056711879 | AL16: =IFERROR(AL14/AJ14-1,"--") -> 0.069770624 | AM16: =IFERROR(AM14/AL14-1,"--") -> 0.05023259 | AN16: =IFERROR(AN14/AM14-1,"--") -> 0.085658125 | AO16: =IFERROR(AO14/AN14-1,"--") -> 0.047786138 | AQ16: =IFERROR(AQ14/AO14-1,"--") -> 0.056726206 | AR16: =IFERROR(AR14/AQ14-1,"--") -> 0.093982522 | AS16: =IFERROR(AS14/AR14-1,"--") -> 0.062247821 | AT16: =IFERROR(AT14/AS14-1,"--") -> 0.034910056 | AV16: =IFERROR(AV14/AT14-1,"--") -> 0.052404815 | AW16: =IFERROR(AW14/AV14-1,"--") -> 0.07257922 | AX16: =IFERROR(AX14/AW14-1,"--") -> 0.064448262 | AY16: =IFERROR(AY14/AX14-1,"--") -> 0.036150099 | BA16: =IFERROR(BA14/AY14-1,"--") -> 0.052739975 | BB16: =IFERROR(BB14/BA14-1,"--") -> 0.076213912 | BC16: =IFERROR(BC14/BB14-1,"--") -> 0.067209272 | BD16: =IFERROR(BD14/BC14-1,"--") -> 0.024946859 | BF16: =IFERROR(BF14/BD14-1,"--") -> 0.044108526 | BG16: =IFERROR(BG14/BF14-1,"--") -> 0.074008783 | BH16: =IFERROR(BH14/BG14-1,"--") -> 0.086758012 | BI16: =IFERROR(BI14/BH14-1,"--") -> 0.029186237 | BK16: =IFERROR(BK14/BI14-1,"--") -> 0.038357458 | BL16: =IFERROR(BL14/BK14-1,"--") -> 0.060388394 | BM16: =IFERROR(BM14/BL14-1,"--") -> 0.094068918 | BN16: =IFERROR(BN14/BM14-1,"--") -> 0.017918041
B17: % total revenue | H17: =IFERROR(H14/H$10,"--") -> 0.98380959 | I17: =IFERROR(I14/I$10,"--") -> 0.98715443 | J17: =IFERROR(J14/J$10,"--") -> 0.99222455 | K17: =IFERROR(K14/K$10,"--") -> 0.99146627 | L17: =IFERROR(L14/L$10,"--") -> 0.98983096 | M17: =IFERROR(M14/M$10,"--") -> 0.97851504 | N17: =IFERROR(N14/N$10,"--") -> 0.95821939 | O17: =IFERROR(O14/O$10,"--") -> 0.94796746 | ... BO17: =IFERROR(BO14/BO$10,"--") -> 0.9696772
