Workbook
Name __FDS_UNIQUE_RANGE_ID_GENERATOR_COUNTER: 50
Name __FDS_USED_FOR_REUSING_RANGE_IDS_RECYCLE: {22,8,23,4,14,18,17,43,48,47,45,46,1,51,50,49}
Name A_ALL_CRWV: #REF!
Name A_ALL_MNDY: #REF!
Name A_ALL_MSFT: #REF!
Name A_ALL_NTNX: [1]NTNX_Annotation_Sheet!$A$1:$CB$331
Name A_ALL_TTAN: #REF!
Name AL_email: "alamba@isigrp.com"
Name AL_phone: "(XXX) XXX-XXXX"
Name AVELIFE: 3
Name BB_email: "bbaytosh@isigrp.com"
Name BB_phone: "(212) 446-9469"
Name CUR3MTH: 6
Name CURCYTD: 9
Name CURMTH: 1
Name CURMYTD: 12
Name CURRENT_MONTH_FIXING: 23
Name CURRENT_MONTH_SPOT: 6
Name CURWEEK: 1
Name CYTDVOL: 11
Name DB: "WIRENYPROD"
Name E_ALL_CRWV: #REF!
Name E_ALL_MNDY: #REF!
Name E_ALL_MSFT: #REF!
Name E_ALL_NTNX: [1]NTNX_Exchange_Sheet!$A$1:$CB$331
Name E_ALL_TTAN: #REF!
Name FINCriteriaType: 1
Name fx: 120
Name FYE: "FYE"
Name HB_email: "hbellini@isigrp.com"
Name HB_phone: "(XXX) XXX-XXXX"
Name L_ALL_CRWV: #REF!
Name L_ALL_MNDY: #REF!
Name L_ALL_MSFT: #REF!
Name L_ALL_NTNX: [1]NTNX_Live_Sheet!$A$1:$CB$331
Name L_ALL_TTAN: #REF!
Name LastListUpdate: 0
Name Low: 1
Name M1_Seasonality: 0.3
Name M2_Seasonality: 0.3
Name M3_Seasonality: 0.4
Name MyBegOfYEar: IF(BegOfYear5253week<>"",BegOfYear5253week,IF(TaxYearEnd="","",TaxYearEnd-364))
Name MyBookIncome: IF(BookIncome = "","",BookIncome)
Name MyFEIN: IF(FEIN="","",FEIN)
Name MyLastYear: IF(TaxYearEnd="","",TaxYearEnd-366)
Name MyName: IF(TheName = "","",TheName)
Name MyNextYear: IF(TaxYearEnd="","",TaxYearEnd+365)
Name MyTaxYear: IF(TaxYearEnd="","",TaxYearEnd)
Name MYTDVOL: 14
Name NextButton: "Button 18"
Name NvsASD: "V1999-12-31"
Name NvsAutoDrillOk: "VN"
Name NvsElapsedTime: 0.00102581018290948
Name NvsEndTime: 36558.0571400463
Name NvsInstSpec1: ","
Name NvsInstSpec2: ","
Name NvsInstSpec3: ","
Name NvsInstSpec4: ","
Name NvsInstSpec5: ","
Name NvsInstSpec6: ","

Sheet __FDSCACHE__
B1: This sheet contains FactSet XML data for use with this workbook's =FDS codes. Modifying the worksheet's contents may damage the workbook's =FDS functionality.

Sheet Cover
C2: CoreWeave Analyst Model
C3: Ticker: | D3: CRWV
C4: Date: | D4: =TODAY() -> 45975
B6: Kash Rangan
B7: (415) 249-7318
B8: kash.rangan@gs.com
B10: Matthew Martino
B11: (212) 902-0695
B12: matt.martino@gs.com
B14: Nishad Patwardhan
B15: (332) 245-7726
B16: nishad.patwardhan@gs.com
B18: Selina Zhang
B19: (212) 357-9979
B20: selina.zhang@gs.com

Sheet Revenue and CapEx Build
B2: CoreWeave, Inc.
B3: Fiscal Year Ends Dec. 31
B4: ($ millions, except per share amounts)
C6: =Dates!C3 -> 2022 (A) | H6: =Dates!H3 -> 2023 (A) | M6: =Dates!M3 -> 2024 (A) | R6: =Dates!R3 -> 2025 (E) | W6: =Dates!W3 -> 2026 (E) | AB6: =Dates!AB3 -> 2027 (E) | AG6: =Dates!AG3 -> 2028 (E)
C7: =Dates!C4 -> 1Q22 (A) | D7: =Dates!D4 -> 2Q22 (A) | E7: =Dates!E4 -> 3Q22 (A) | F7: =Dates!F4 -> 4Q22 (A) | G7: =Dates!G4 -> FY22 (A) | H7: =Dates!H4 -> 1Q23 (A) | I7: =Dates!I4 -> 2Q23 (A) | J7: =Dates!J4 -> 3Q23 (A) | ... AK7: =Dates!AK4 -> FY28 (E)
C8: =Dates!C5 -> 44651 | D8: =Dates!D5 -> 44742 | E8: =Dates!E5 -> 44834 | F8: =Dates!F5 -> 44926 | G8: =Dates!G5 -> 44926 | H8: =Dates!H5 -> 45016 | I8: =Dates!I5 -> 45107 | J8: =Dates!J5 -> 45199 | ... AK8: =Dates!AK5 -> 47118
A10: TREV | B10: Total Revenue | G10: 15.83 | H10: =M10/(1+M11) -> 7.9236843 | I10: =N10/(1+N11) -> 29.8436 | J10: =O10/(1+O11) -> 75.178825 | K10: =L10-J10-I10-H10 -> 115.99689 | L10: 228.943 | M10: 188.684 | N10: 395.371 | O10: 583.941 | P10: 747.43 | Q10: =SUM(M10:P10) -> 1915.426 | R10: 981.632 | S10: 1212.788 | T10: 1364.676 | U10: =U16*U23 -> 1542.8798 | V10: =SUM(R10:U10) -> 5101.9758 | W10: =W16*W23 -> 2227.1272 | X10: =X16*X23 -> 2964.1923 | Y10: =Y16*Y23 -> 3289.6841 | Z10: =Z16*Z23 -> 3520.6358 | AA10: =SUM(W10:Z10) -> 12001.639 | AB10: =AB16*AB23 -> 3811.6134 | AC10: =AC16*AC23 -> 4153.968 | AD10: =AD16*AD23 -> 4473.8327 | AE10: =AE16*AE23 -> 4771.4757 | AF10: =SUM(AB10:AE10) -> 17210.89 | AG10: =AG16*AG23 -> 5118.4482 | AH10: =AH16*AH23 -> 5329.7807 | AI10: =AI16*AI23 -> 5519.2672 | AJ10: =AJ16*AJ23 -> 5687.5931 | AK10: =SUM(AG10:AJ10) -> 21655.089
A11: TREVYY | B11: % yoy | H11: =IFERROR(H10/C10-1,"") | I11: =IFERROR(I10/D10-1,"") | J11: =IFERROR(J10/E10-1,"") | K11: =IFERROR(K10/F10-1,"") | L11: =IFERROR(L10/G10-1,"") -> 13.462603 | M11: 22.81266 | N11: 12.2481 | O11: 6.76736 | P11: =IFERROR(P10/K10-1,"") -> 5.4435348 | Q11: =IFERROR(Q10/L10-1,"") -> 7.3663881 | R11: =IFERROR(R10/M10-1,"") -> 4.2025185 | S11: =IFERROR(S10/N10-1,"") -> 2.0674683 | T11: =IFERROR(T10/O10-1,"") -> 1.3370101 | U11: =IFERROR(U10/P10-1,"") -> 1.0642466 | V11: =IFERROR(V10/Q10-1,"") -> 1.6636246 | W11: =IFERROR(W10/R10-1,"") -> 1.2688005 | ... AK11: =IFERROR(AK10/AF10-1,"") -> 0.25822019
A12: TREVQQ | B12: % qoq | H12: =IFERROR(H10/F10-1,"") | I12: =IFERROR(I10/H10-1,"") -> 2.7663793 | J12: =IFERROR(J10/I10-1,"") -> 1.5190937 | K12: =IFERROR(K10/J10-1,"") -> 0.5429463 | M12: =IFERROR(M10/K10-1,"") -> 0.62662981 | N12: =IFERROR(N10/M10-1,"") -> 1.0954135 | O12: =IFERROR(O10/N10-1,"") -> 0.47694444 | P12: =IFERROR(P10/O10-1,"") -> 0.2799752 | R12: =IFERROR(R10/P10-1,"") -> 0.31334306 | S12: =IFERROR(S10/R10-1,"") -> 0.23548132 | T12: =IFERROR(T10/S10-1,"") -> 0.12523871 | U12: =IFERROR(U10/T10-1,"") -> 0.13058326 | W12: =IFERROR(W10/U10-1,"") -> 0.44348713 | X12: =IFERROR(X10/W10-1,"") -> 0.33094883 | Y12: =IFERROR(Y10/X10-1,"") -> 0.10980793 | Z12: =IFERROR(Z10/Y10-1,"") -> 0.070204816 | AB12: =IFERROR(AB10/Z10-1,"") -> 0.082649169 | AC12: =IFERROR(AC10/AB10-1,"") -> 0.089818799 | AD12: =IFERROR(AD10/AC10-1,"") -> 0.077002222 | AE12: =IFERROR(AE10/AD10-1,"") -> 0.066529754 | AG12: =IFERROR(AG10/AE10-1,"") -> 0.072718069 | AH12: =IFERROR(AH10/AG10-1,"") -> 0.041288386 | AI12: =IFERROR(AI10/AH10-1,"") -> 0.035552396 | AJ12: =IFERROR(AJ10/AI10-1,"") -> 0.030497879
B13: Net New Revenue (yoy) | H13: =H10-C10 -> 7.9236843 | I13: =I10-D10 -> 29.8436 | J13: =J10-E10 -> 75.178825 | K13: =K10-F10 -> 115.99689 | L13: =L10-G10 -> 213.113 | M13: =M10-H10 -> 180.76032 | N13: =N10-I10 -> 365.5274 | O13: =O10-J10 -> 508.76217 | ... AK13: =AK10-AF10 -> 4444.1993
B14: Net New Revenue (qoq) | H14: =H10-F10 -> 7.9236843 | I14: =I10-H10 -> 21.919916 | J14: =J10-I10 -> 45.335225 | K14: =K10-J10 -> 40.818065 | M14: =M10-K10 -> 72.68711 | N14: =N10-M10 -> 206.687 | O14: =O10-N10 -> 188.57 | P14: =P10-O10 -> 163.489 | R14: =R10-P10 -> 234.202 | S14: =S10-R10 -> 231.156 | T14: =T10-S10 -> 151.888 | U14: =U10-T10 -> 178.20384 | W14: =W10-U10 -> 684.24736 | X14: =X10-W10 -> 737.06513 | Y14: =Y10-X10 -> 325.49181 | Z14: =Z10-Y10 -> 230.95167 | AB14: =AB10-Z10 -> 290.97762 | AC14: =AC10-AB10 -> 342.35454 | AD14: =AD10-AC10 -> 319.86477 | AE14: =AE10-AD10 -> 297.64299 | AG14: =AG10-AE10 -> 346.9725 | AH14: =AH10-AG10 -> 211.33246 | AI14: =AI10-AH10 -> 189.48647 | AJ14: =AJ10-AI10 -> 168.32594
B16: Revenue / Average Net Assets | O16: =O$10/O$23 -> 0.086095277 | P16: =P$10/P$23 -> 0.097257296 | R16: =R$10/R$23 -> 0.10414591 | S16: =S$10/S$23 -> 0.1070543 | T16: =T$10/T$23 -> 0.10389865 | U16: 0.0976 | V16: =AVERAGE(R16:U16) -> 0.10317472 | W16: 0.098 | X16: 0.101 | Y16: 0.103 | Z16: 0.105 | AA16: =AVERAGE(W16:Z16) -> 0.10175 | AB16: 0.106 | AC16: =AB16 -> 0.106 | AD16: =AC16 -> 0.106 | AE16: =AD16 -> 0.106 | AF16: =AVERAGE(AB16:AE16) -> 0.106 | AG16: 0.108 | AH16: =AG16 -> 0.108 | AI16: =AH16 -> 0.108 | AJ16: =AI16 -> 0.108 | AK16: =AVERAGE(AG16:AJ16) -> 0.108
B17: Revenue / Average Net Assets, Annualized | O17: =O16*4 -> 0.34438111 | P17: =P16*4 -> 0.38902918 | R17: =R16*4 -> 0.41658366 | S17: =S16*4 -> 0.42821721 | T17: =T16*4 -> 0.4155946 | U17: =U16*4 -> 0.3904 | W17: =W16*4 -> 0.392 | X17: =X16*4 -> 0.404 | Y17: =Y16*4 -> 0.412 | Z17: =Z16*4 -> 0.42 | AB17: =AB16*4 -> 0.424 | AC17: =AC16*4 -> 0.424 | AD17: =AD16*4 -> 0.424 | AE17: =AE16*4 -> 0.424 | AG17: =AG16*4 -> 0.432 | AH17: =AH16*4 -> 0.432 | AI17: =AI16*4 -> 0.432 | AJ17: =AJ16*4 -> 0.432
B18: Revenue / Average Gross Assets | O18: =O$10/O$28 -> 0.080338949 | P18: =P$10/P$28 -> 0.088204788 | R18: =R$10/R$28 -> 0.092537485 | S18: =S$10/S$28 -> 0.093253366 | T18: =T$10/T$28 -> 0.088622363 | U18: =U$10/U$28 -> 0.082175834 | W18: =W$10/W$28 -> 0.083496471 | X18: =X$10/X$28 -> 0.08573449 | Y18: =Y$10/Y$28 -> 0.085200041 | Z18: =Z$10/Z$28 -> 0.084261617 | AB18: =AB$10/AB$28 -> 0.082922964 | AC18: =AC$10/AC$28 -> 0.081183094 | AD18: =AD$10/AD$28 -> 0.079357218 | AE18: =AE$10/AE$28 -> 0.077468268 | AG18: =AG$10/AG$28 -> 0.076872621 | AH18: =AH$10/AH$28 -> 0.074703951 | AI18: =AI$10/AI$28 -> 0.072522393 | AJ18: =AJ$10/AJ$28 -> 0.070332762
A20: NAEXCIP | B20: Net Assets (ex. CIP) | O20: =O25+O115 -> 6656.25 | P20: =P25+P115 -> 8713.908 | Q20: =Q25+Q115 -> 8713.908 | R20: =R25+R115 -> 10137.182 | S20: =S25+S115 -> 12520.254 | T20: =T25+T115 -> 13749.115 | U20: =U25+U115 -> 17867.275 | V20: =V25+V115 -> 17867.275 | ... AK20: =AK25+AK115 -> 53401.082
B21: % yoy | M21: =IFERROR(M20/H20-1,"") | N21: =IFERROR(N20/I20-1,"") | O21: =IFERROR(O20/J20-1,"") | P21: =IFERROR(P20/K20-1,"") | Q21: =IFERROR(Q20/L20-1,"") | R21: =IFERROR(R20/M20-1,"") | S21: =IFERROR(S20/N20-1,"") | T21: =IFERROR(T20/O20-1,"") -> 1.0655947 | ... AK21: =IFERROR(AK20/AF20-1,"") -> 0.15162077
B22: % qoq | M22: =IFERROR(M20/K20-1,"") | N22: =IFERROR(N20/M20-1,"") | O22: =IFERROR(O20/N20-1,"") | P22: =IFERROR(P20/O20-1,"") -> 0.30913172 | R22: =IFERROR(R20/P20-1,"") -> 0.1633336 | S22: =IFERROR(S20/R20-1,"") -> 0.23508229 | T22: =IFERROR(T20/S20-1,"") -> 0.098149846 | U22: =IFERROR(U20/T20-1,"") -> 0.29952183 | W22: =IFERROR(W20/U20-1,"") -> 0.54384483 | X22: =IFERROR(X20/W20-1,"") -> 0.12790889 | Y22: =IFERROR(Y20/X20-1,"") -> 0.053104148 | Z22: =IFERROR(Z20/Y20-1,"") -> 0.046701387 | AB22: =IFERROR(AB20/Z20-1,"") -> 0.097021411 | AC22: =IFERROR(AC20/AB20-1,"") -> 0.083253192 | AD22: =IFERROR(AD20/AC20-1,"") -> 0.071231669 | AE22: =IFERROR(AE20/AD20-1,"") -> 0.062140492 | AG22: =IFERROR(AG20/AE20-1,"") -> 0.044108716 | AH22: =IFERROR(AH20/AG20-1,"") -> 0.038587201 | AI22: =IFERROR(AI20/AH20-1,"") -> 0.032630345 | AJ22: =IFERROR(AJ20/AI20-1,"") -> 0.028432797
B23: Average Net Assets (ex. CIP) | O23: =O28+AVERAGE(N115:O115) -> 6782.4975 | P23: =AVERAGE(O20:P20) -> 7685.079 | Q23: =P23 -> 7685.079 | R23: =AVERAGE(Q20:R20) -> 9425.545 | S23: =AVERAGE(R20:S20) -> 11328.718 | T23: =AVERAGE(S20:T20) -> 13134.684 | U23: =AVERAGE(T20:U20) -> 15808.195 | V23: =U23 -> 15808.195 | W23: =AVERAGE(V20:W20) -> 22725.788 | X23: =AVERAGE(W20:X20) -> 29348.439 | Y23: =AVERAGE(X20:Y20) -> 31938.681 | Z23: =AVERAGE(Y20:Z20) -> 33529.865 | AA23: =Z23 -> 33529.865 | AB23: =AVERAGE(AA20:AB20) -> 35958.617 | AC23: =AVERAGE(AB20:AC20) -> 39188.377 | AD23: =AVERAGE(AC20:AD20) -> 42205.969 | AE23: =AVERAGE(AD20:AE20) -> 45013.922 | AF23: =AE23 -> 45013.922 | AG23: =AVERAGE(AF20:AG20) -> 47393.039 | AH23: =AVERAGE(AG20:AH20) -> 49349.821 | AI23: =AVERAGE(AH20:AI20) -> 51104.326 | AJ23: =AVERAGE(AI20:AJ20) -> 52662.899 | AK23: =AJ23 -> 52662.899
B25: Gross Assets (ex. CIP) | O25: =O31-O59 -> 7268.467 | P25: =P31-P59 -> 9679.139 | Q25: =P25 -> 9679.139 | R25: =R31-R59 -> 11536.739 | S25: =S31-S59 -> 14473.861 | T25: =T31-T59 -> 16323.693 | U25: =U31-U59 -> 21227.002 | V25: =U25 -> 21227.002 | W25: =W31-W59 -> 32119.617 | X25: =X31-X59 -> 37028.572 | Y25: =Y31-Y59 -> 40194.024 | Z25: =Z31-Z59 -> 43370.378 | AA25: =Z25 -> 43370.378 | AB25: =AB31-AB59 -> 48561.054 | AC25: =AC31-AC59 -> 53774.734 | AD25: =AD31-AD59 -> 58977.02 | AE25: =AE31-AE59 -> 64208.276 | AF25: =AE25 -> 64208.276 | AG25: =AG31-AG59 -> 68958.727 | AH25: =AH31-AH59 -> 73732.005 | AI25: =AI31-AI59 -> 78476.628 | AJ25: =AJ31-AJ59 -> 83257.191 | AK25: =AJ25 -> 83257.191
B26: % yoy | M26: =IFERROR(M25/H25-1,"") | N26: =IFERROR(N25/I25-1,"") | O26: =IFERROR(O25/J25-1,"") | Q26: =IFERROR(Q25/L25-1,"") | S26: =IFERROR(S25/N25-1,"") | T26: =IFERROR(T25/O25-1,"") -> 1.2458234 | U26: =IFERROR(U25/P25-1,"") -> 1.1930672 | V26: =IFERROR(V25/Q25-1,"") -> 1.1930672 | W26: =IFERROR(W25/R25-1,"") -> 1.7841157 | X26: =IFERROR(X25/S25-1,"") -> 1.5583064 | Y26: =IFERROR(Y25/T25-1,"") -> 1.4623119 | Z26: =IFERROR(Z25/U25-1,"") -> 1.0431702 | ... AK26: =IFERROR(AK25/AF25-1,"") -> 0.29667383
B27: % qoq | M27: =IFERROR(M25/K25-1,"") | N27: =IFERROR(N25/M25-1,"") | O27: =IFERROR(O25/N25-1,"") | P27: =IFERROR(P25/O25-1,"") -> 0.33166168 | R27: =IFERROR(R25/P25-1,"") -> 0.1919179 | S27: =IFERROR(S25/R25-1,"") -> 0.25458858 | T27: =IFERROR(T25/S25-1,"") -> 0.12780501 | U27: =IFERROR(U25/T25-1,"") -> 0.30037988 | W27: =IFERROR(W25/U25-1,"") -> 0.51314899 | X27: =IFERROR(X25/W25-1,"") -> 0.15283356 | Y27: =IFERROR(Y25/X25-1,"") -> 0.085486734 | Z27: =IFERROR(Z25/Y25-1,"") -> 0.079025536 | AB27: =IFERROR(AB25/Z25-1,"") -> 0.11968253 | AC27: =IFERROR(AC25/AB25-1,"") -> 0.1073634 | AD27: =IFERROR(AD25/AC25-1,"") -> 0.0967422 | AE27: =IFERROR(AE25/AD25-1,"") -> 0.088699898 | AG27: =IFERROR(AG25/AE25-1,"") -> 0.073985024 | AH27: =IFERROR(AH25/AG25-1,"") -> 0.069219356 | AI27: =IFERROR(AI25/AH25-1,"") -> 0.064349565 | AJ27: =IFERROR(AJ25/AI25-1,"") -> 0.060917032
B28: Average Gross Assets (ex. CIP) | O28: =AVERAGE(O25,N25) -> 7268.467 | P28: =AVERAGE(P25,O25) -> 8473.803 | Q28: =AVERAGE(Q25,L25) -> 9679.139 | R28: =AVERAGE(R25,Q25) -> 10607.939 | S28: =AVERAGE(S25,R25) -> 13005.3 | T28: =AVERAGE(T25,S25) -> 15398.777 | U28: =AVERAGE(U25,T25) -> 18775.348 | V28: =AVERAGE(V25,Q25) -> 15453.071 | W28: =AVERAGE(W25,V25) -> 26673.309 | X28: =AVERAGE(X25,W25) -> 34574.094 | Y28: =AVERAGE(Y25,X25) -> 38611.298 | Z28: =AVERAGE(Z25,Y25) -> 41782.201 | AA28: =AVERAGE(AA25,V25) -> 32298.69 | AB28: =AVERAGE(AB25,AA25) -> 45965.716 | AC28: =AVERAGE(AC25,AB25) -> 51167.894 | AD28: =AVERAGE(AD25,AC25) -> 56375.877 | AE28: =AVERAGE(AE25,AD25) -> 61592.648 | AF28: =AVERAGE(AF25,AA25) -> 53789.327 | AG28: =AVERAGE(AG25,AF25) -> 66583.501 | AH28: =AVERAGE(AH25,AG25) -> 71345.366 | AI28: =AVERAGE(AI25,AH25) -> 76104.316 | AJ28: =AVERAGE(AJ25,AI25) -> 80866.909 | AK28: =AVERAGE(AK25,AF25) -> 73732.733
B30: Balance Sheet Pulls
B31: =BS!B20 -> Property, Plant, and Equipment, Gross | M31: =BS!M20 -> 5268.215 | N31: =BS!N20 -> 7385.5522 | O31: =BS!O20 -> 9728.807 | P31: =BS!P20 -> 12880.005 | Q31: =BS!Q20 -> 12880.005 | R31: =BS!R20 -> 15610.549 | S31: =BS!S20 -> 18585.117 | T31: =BS!T20 -> 23233.759 | ... AK31: =BS!AK20 -> 100089.77
B32: =BS!B22 -> Property and Equipment, Net | M32: =BS!M22 -> 5072.433 | N32: =BS!N22 -> 7025.8302 | O32: =BS!O22 -> 9116.59 | P32: =BS!P22 -> 11914.774 | Q32: =BS!Q22 -> 11914.774 | R32: =BS!R22 -> 14210.992 | S32: =BS!S22 -> 16631.51 | T32: =BS!T22 -> 20659.181 | ... AK32: =BS!AK22 -> 70233.659
A34: CAPEXFL | B34: CapEx (including Finance Leases) | M34: 1100 | N34: 2600 | O34: 2200 | P34: 2400 | Q34: =SUM(M34:P34) -> 8300 | R34: 1900 | S34: 2900 | T34: 1900 | U34: =U46-U66+U73 -> 6323.333 | V34: =SUM(R34:U34) -> 13023.333 | W34: =W46-W66+W73 -> 12383.64 | X34: =X46-X66+X73 -> 6399.9805 | Y34: =Y46-Y66+Y73 -> 4656.4769 | Z34: =Z46-Z66+Z73 -> 4667.3795 | AA34: =SUM(W34:Z34) -> 28107.477 | AB34: =AB46-AB66+AB73 -> 6681.7016 | AC34: =AC46-AC66+AC73 -> 6704.705 | AD34: =AD46-AD66+AD73 -> 6693.3113 | AE34: =AE46-AE66+AE73 -> 6722.2808 | AF34: =SUM(AB34:AE34) -> 26801.999 | AG34: =AG46-AG66+AG73 -> 6241.476 | AH34: =AH46-AH66+AH73 -> 6264.3038 | AI34: =AI46-AI66+AI73 -> 6235.6476 | AJ34: =AJ46-AJ66+AJ73 -> 6271.5884 | AK34: =SUM(AG34:AJ34) -> 25013.016
A35: CAPEXFLYY | B35: % yoy | M35: =IFERROR(M34/H34-1,"") | N35: =IFERROR(N34/I34-1,"") | O35: =IFERROR(O34/J34-1,"") | P35: =IFERROR(P34/K34-1,"") | Q35: =IFERROR(Q34/L34-1,"") | R35: =IFERROR(R34/M34-1,"") -> 0.72727273 | S35: =IFERROR(S34/N34-1,"") -> 0.11538462 | T35: =IFERROR(T34/O34-1,"") -> -0.13636364 | ... AK35: =IFERROR(AK34/AF34-1,"") -> -0.06674811
A36: CAPEXFYQQ | B36: % qoq | M36: =IFERROR(M34/K34-1,"") | N36: =IFERROR(N34/M34-1,"") -> 1.3636364 | O36: =IFERROR(O34/N34-1,"") -> -0.15384615 | P36: =IFERROR(P34/O34-1,"") -> 0.090909091 | R36: =IFERROR(R34/P34-1,"") -> -0.20833333 | S36: =IFERROR(S34/R34-1,"") -> 0.52631579 | T36: =IFERROR(T34/S34-1,"") -> -0.34482759 | U36: =IFERROR(U34/T34-1,"") -> 2.32807 | W36: =IFERROR(W34/U34-1,"") -> 0.95840386 | X36: =IFERROR(X34/W34-1,"") -> -0.48319068 | Y36: =IFERROR(Y34/X34-1,"") -> -0.27242327 | Z36: =IFERROR(Z34/Y34-1,"") -> 0.0023413777 | AB36: =IFERROR(AB34/Z34-1,"") -> 0.43157453 | AC36: =IFERROR(AC34/AB34-1,"") -> 0.0034427537 | AD36: =IFERROR(AD34/AC34-1,"") -> -0.001699363 | AE36: =IFERROR(AE34/AD34-1,"") -> 0.0043281354 | AG36: =IFERROR(AG34/AE34-1,"") -> -0.071524057 | AH36: =IFERROR(AH34/AG34-1,"") -> 0.0036574329 | AI36: =IFERROR(AI34/AH34-1,"") -> -0.0045745223 | AJ36: =IFERROR(AJ34/AI34-1,"") -> 0.0057637635
B37: Net New CapEx (yoy) | M37: =M34-H34 -> 1100 | N37: =N34-I34 -> 2600 | O37: =O34-J34 -> 2200 | P37: =P34-K34 -> 2400 | Q37: =Q34-L34 -> 8300 | R37: =R34-M34 -> 800 | S37: =S34-N34 -> 300 | T37: =T34-O34 -> -300 | ... AK37: =AK34-AF34 -> -1788.9828
B38: Net New CapEx (qoq) | M38: =M34-K34 -> 1100 | N38: =N34-M34 -> 1500 | O38: =O34-N34 -> -400 | P38: =P34-O34 -> 200 | R38: =R34-P34 -> -500 | S38: =S34-R34 -> 1000 | T38: =T34-S34 -> -1000 | U38: =U34-T34 -> 4423.333 | W38: =W34-U34 -> 6060.3068 | X38: =X34-W34 -> -5983.6593 | Y38: =Y34-X34 -> -1743.5036 | Z38: =Z34-Y34 -> 10.902571 | AB38: =AB34-Z34 -> 2014.3221 | AC38: =AC34-AB34 -> 23.003453 | AD38: =AD34-AC34 -> -11.393728 | AE38: =AE34-AD34 -> 28.969558 | AG38: =AG34-AE34 -> -480.8048 | AH38: =AH34-AG34 -> 22.82778 | AI38: =AI34-AH34 -> -28.656198 | AJ38: =AJ34-AI34 -> 35.940798
B40: CapEx Efficiency
B41: CapEx / Revenue | P41: =P46/P10 -> 4.2160443 | Q41: =Q46/Q10 -> 4.5431554 | R41: =R46/R10 -> 1.4336931 | S41: =S46/S10 -> 2.0226058 | T41: =T46/T10 -> 2.4026113 | U41: =U46/U10 -> 5.4173642 | V41: =V46/V10 -> 3.0375446 | W41: =W46/W10 -> 3.9600768 | ... AK41: =AK46/AK10 -> 1.1444152
B42: CapEx / NTM Revenue | P42: =P46/(T10+R10+S10+U10) -> 0.61764267 | Q42: =Q46/V10 -> 1.705629 | R42: =R46/(S10+T10+U10+W10) -> 0.22171964 | S42: =S46/(T10+U10+W10+X10) -> 0.30288057 | T42: =T46/(U10+V10+X10+Y10) -> 0.25419444 | U42: =U46/(Y10+W10+X10+Z10) -> 0.69643335 | V42: =V46/AA10 -> 1.2912802 | W42: =W46/(X10+Y10+Z10+AB10) -> 0.64916187 | X42: =X46/(Y10+Z10+AB10+AC10) -> 0.34345092 | Y42: =Y46/(Z10+AC10+AB10+AD10) -> 0.22483311 | Z42: =Z46/(AD10+AB10+AC10+AE10) -> 0.20003491 | AA42: =AA46/AF10 -> 1.2158301 | AB42: =AB46/(AC10+AD10+AE10+AG10) -> 0.23091132 | AC42: =AC46/(AD10+AE10+AG10+AH10) -> 0.34834693 | AD42: =AD46/(AE10+AH10+AG10+AI10) -> 0.27466343 | AE42: =AE46/(AI10+AG10+AH10+AJ10) -> 0.27510225 | AF42: =AF46/AK10 -> 1.0523963
B43: CapEx / Net New Revenue (yoy) | P43: =P46/P13 -> 4.9905492 | Q43: =Q46/Q13 -> 5.1598967 | R43: =R46/R13 -> 1.774844 | S43: =S46/S13 -> 3.0009065 | T43: =T46/T13 -> 4.1996145 | U43: =U46/U13 -> 10.507692 | V43: =V46/V13 -> 4.8634039 | W43: =W46/W13 -> 7.0811954 | ... AK43: =AK46/AK13 -> 5.5763504
B45: CapEx Breakdown
B46: Total Purchase of P&E (incl. CIP) | G46: =-CF!G40 -> 72.404 | L46: =-CF!L40 -> 2943.13 | M46: =-CF!M40 -> 1741.935 | P46: =-CF!P40 -> 3151.198 | Q46: =-CF!Q40 -> 8702.078 | R46: =-CF!R40 -> 1407.359 | S46: =-CF!S40 -> 2452.992 | T46: =-CF!T40 -> 3278.786 | U46: =+U52+U66+U80+U87+U93 -> 8358.342 | V46: =SUM(R46:U46) -> 15497.479 | W46: =+W52+W66+W80+W87+W93 -> 8819.5948 | X46: =+X52+X66+X80+X87+X93 -> 5074.7969 | Y46: =+Y52+Y66+Y80+Y87+Y93 -> 3588.3477 | Z46: =+Z52+Z66+Z80+Z87+Z93 -> 3442.7788 | AA46: =SUM(W46:Z46) -> 20925.518 | AB46: =+AB52+AB66+AB80+AB87+AB93 -> 4275.9522 | AC46: =+AC52+AC66+AC80+AC87+AC93 -> 6860.1832 | AD46: =+AD52+AD66+AD80+AD87+AD93 -> 5696.2371 | AE46: =+AE52+AE66+AE80+AE87+AE93 -> 5957.3637 | AF46: =SUM(AB46:AE46) -> 22789.736 | AG46: =+AG52+AG66+AG80+AG87+AG93 -> 5527.3864 | AH46: =+AH52+AH66+AH80+AH87+AH93 -> 6317.1606 | AI46: =+AI52+AI66+AI80+AI87+AI93 -> 6489.2091 | AJ46: =+AJ52+AJ66+AJ80+AJ87+AJ93 -> 6448.6564 | AK46: =SUM(AG46:AJ46) -> 24782.413
B47: % yoy | L47: =IFERROR(L46/G46-1,"") -> 39.648721 | M47: =IFERROR(M46/H46-1,"") | N47: =IFERROR(N46/I46-1,"") | O47: =IFERROR(O46/J46-1,"") | P47: =IFERROR(P46/K46-1,"") | Q47: =IFERROR(Q46/L46-1,"") -> 1.9567427 | R47: =IFERROR(R46/M46-1,"") -> -0.19207146 | S47: =IFERROR(S46/N46-1,"") | ... AK47: =IFERROR(AK46/AF46-1,"") -> 0.087437445
B48: % qoq | M48: =IFERROR(M46/K46-1,"") | N48: =IFERROR(N46/M46-1,"") -> -1 | O48: =IFERROR(O46/N46-1,"") | P48: =IFERROR(P46/O46-1,"") | R48: =IFERROR(R46/P46-1,"") -> -0.55338922 | S48: =IFERROR(S46/R46-1,"") -> 0.74297532 | T48: =IFERROR(T46/S46-1,"") -> 0.33664765 | U48: =IFERROR(U46/T46-1,"") -> 1.5492185 | W48: =IFERROR(W46/U46-1,"") -> 0.055184723 | X48: =IFERROR(X46/W46-1,"") -> -0.42459977 | Y48: =IFERROR(Y46/X46-1,"") -> -0.29290811 | Z48: =IFERROR(Z46/Y46-1,"") -> -0.040567129 | AB48: =IFERROR(AB46/Z46-1,"") -> 0.2420061 | AC48: =IFERROR(AC46/AB46-1,"") -> 0.60436387 | AD48: =IFERROR(AD46/AC46-1,"") -> -0.16966692 | AE48: =IFERROR(AE46/AD46-1,"") -> 0.045841937 | AG48: =IFERROR(AG46/AE46-1,"") -> -0.072175757 | AH48: =IFERROR(AH46/AG46-1,"") -> 0.14288384 | AI48: =IFERROR(AI46/AH46-1,"") -> 0.027235094 | AJ48: =IFERROR(AJ46/AI46-1,"") -> -0.0062492386
B49: Net New CapEx (yoy) | P49: =P46-K46 -> 3151.198 | Q49: =Q46-L46 -> 5758.948 | R49: =R46-M46 -> -334.576 | S49: =S46-N46 -> 2452.992 | T49: =T46-O46 -> 3278.786 | U49: =U46-P46 -> 5207.144 | V49: =V46-Q46 -> 6795.401 | W49: =W46-R46 -> 7412.2358 | ... AK49: =AK46-AF46 -> 1992.6763
B50: Net New CapEx (qoq) | P50: =P46-O46 -> 3151.198 | R50: =R46-P46 -> -1743.839 | S50: =S46-R46 -> 1045.633 | T50: =T46-S46 -> 825.794 | U50: =U46-T46 -> 5079.556 | W50: =W46-U46 -> 461.25279 | X50: =X46-W46 -> -3744.7979 | Y50: =Y46-X46 -> -1486.4491 | Z50: =Z46-Y46 -> -145.56896 | AB50: =AB46-Z46 -> 833.17346 | AC50: =AC46-AB46 -> 2584.231 | AD50: =AD46-AC46 -> -1163.9461 | AE50: =AE46-AD46 -> 261.12654 | AG50: =AG46-AE46 -> -429.97723 | AH50: =AH46-AG46 -> 789.77419 | AI50: =AI46-AH46 -> 172.04846 | AJ50: =AJ46-AI46 -> -40.552616
B52: CapEx (Fixed Assets) | P52: 2340.018 | Q52: 8119.4499 | R52: =R46-R66-R80-R87-R93 -> 483.104 | S52: =S46-S66-S80-S87-S93 -> 2359.475 | T52: =T46-T66-T80-T87-T93 -> 382.361 | U52: =T52+U56 -> 4758.361 | V52: =SUM(R52:U52) -> 7983.301 | W52: =U52+W56 -> 10758.361 | X52: =W52+X56 -> 4758.361 | Y52: =X52+Y56 -> 3008.361 | Z52: =Y52+Z56 -> 3008.361 | AA52: =SUM(W52:Z52) -> 21533.444 | AB52: =Z52+AB56 -> 5008.361 | AC52: =AB52+AC56 -> 5008.361 | AD52: =AC52+AD56 -> 5008.361 | AE52: =AD52+AE56 -> 5008.361 | AF52: =SUM(AB52:AE52) -> 20033.444 | AG52: =AE52+AG56 -> 4508.361 | AH52: =AG52+AH56 -> 4508.361 | AI52: =AH52+AI56 -> 4508.361 | AJ52: =AI52+AJ56 -> 4508.361 | AK52: =SUM(AG52:AJ52) -> 18033.444
B53: % yoy | M53: =IFERROR(M52/H52-1,"") | N53: =IFERROR(N52/I52-1,"") | O53: =IFERROR(O52/J52-1,"") | P53: =IFERROR(P52/K52-1,"") | Q53: =IFERROR(Q52/L52-1,"") | R53: =IFERROR(R52/M52-1,"") | S53: =IFERROR(S52/N52-1,"") | T53: =IFERROR(T52/O52-1,"") | ... AK53: =IFERROR(AK52/AF52-1,"") -> -0.099833059
B54: % qoq | R54: =IFERROR(R52/P52-1,"") -> -0.79354689 | S54: =IFERROR(S52/R52-1,"") -> 3.8839898 | T54: =IFERROR(T52/S52-1,"") -> -0.83794658 | U54: =IFERROR(U52/T52-1,"") -> 11.444682 | W54: =IFERROR(W52/U52-1,"") -> 1.2609384 | X54: =IFERROR(X52/W52-1,"") -> -0.55770577 | Y54: =IFERROR(Y52/X52-1,"") -> -0.36777369 | Z54: =IFERROR(Z52/Y52-1,"") -> 0 | AB54: =IFERROR(AB52/Z52-1,"") -> 0.66481383 | AC54: =IFERROR(AC52/AB52-1,"") -> 0 | AD54: =IFERROR(AD52/AC52-1,"") -> 0 | AE54: =IFERROR(AE52/AD52-1,"") -> 0 | AG54: =IFERROR(AG52/AE52-1,"") -> -0.099833059 | AH54: =IFERROR(AH52/AG52-1,"") -> 0 | AI54: =IFERROR(AI52/AH52-1,"") -> 0 | AJ54: =IFERROR(AJ52/AI52-1,"") -> 0
B55: Net New CapEx (yoy) | Q55: =Q52-L52 -> 8119.4499 | R55: =R52-M52 -> 483.104 | S55: =S52-N52 -> 2359.475 | T55: =T52-O52 -> 382.361 | U55: =U52-P52 -> 2418.343 | V55: =V52-Q52 -> -136.14892 | W55: =W52-R52 -> 10275.257 | X55: =X52-S52 -> 2398.886 | ... AK55: =AK52-AF52 -> -2000
B56: Net New CapEx (qoq) | R56: =R52-P52 -> -1856.914 | S56: =S52-Q52 -> -5759.9749 | T56: =T52-R52 -> -100.743 | U56: 4376 | W56: 6000 | X56: -6000 | Y56: -1750 | AB56: 2000 | AG56: -500 | AH56: 0 | AI56: =AH56 -> 0 | AJ56: =AI56 -> 0
B57: % of Total Purchase of P&E | R57: =R52/R$46 -> 0.34326991 | S57: =S52/S$46 -> 0.96187635 | T57: =T52/T$46 -> 0.11661664 | U57: =U52/U$46 -> 0.56929484 | V57: =V52/V$46 -> 0.51513546 | W57: =W52/W$46 -> 1.2198249 | X57: =X52/X$46 -> 0.93764561 | Y57: =Y52/Y$46 -> 0.83836942 | ... AK57: =AK52/AK$46 -> 0.72767104
B59: Total CIP | K59: =K124 -> 2256.673 | L59: =K59 -> 2256.673 | O59: =O124 -> 2460.34 | P59: =P124 -> 3200.866 | Q59: =P59 -> 3200.866 | R59: =R124 -> 4073.81 | S59: =S124 -> 4111.256 | T59: =T124 -> 6910.066 | U59: =T59*(1+U61) -> 10365.099 | V59: =U59 -> 10365.099 | W59: =U59*(1+W61) -> 8292.0792 | X59: =W59*(1+X61) -> 8457.9208 | Y59: =X59*(1+Y61) -> 8880.8168 | Z59: =Y59*(1+Z61) -> 9147.2413 | AA59: =Z59 -> 9147.2413 | AB59: =Z59*(1+AB61) -> 8232.5172 | AC59: =AB59*(1+AC61) -> 9879.0206 | AD59: =AC59*(1+AD61) -> 10372.972 | AE59: =AD59*(1+AE61) -> 11099.08 | AF59: =AE59 -> 11099.08 | AG59: =AE59*(1+AG61) -> 11876.015 | AH59: =AG59*(1+AH61) -> 13419.897 | AI59: =AH59*(1+AI61) -> 15164.484 | AJ59: =AI59*(1+AJ61) -> 16832.577 | AK59: =AJ59 -> 16832.577
B60: % yoy | M60: =IFERROR(M59/H59-1,"") | N60: =IFERROR(N59/I59-1,"") | O60: =IFERROR(O59/J59-1,"") | P60: =IFERROR(P59/K59-1,"") -> 0.41840045 | Q60: =IFERROR(Q59/L59-1,"") -> 0.41840045 | R60: =IFERROR(R59/M59-1,"") | S60: =IFERROR(S59/N59-1,"") | T60: =IFERROR(T59/O59-1,"") -> 1.8085817 | ... AK60: =IFERROR(AK59/AF59-1,"") -> 0.51657413
B61: % qoq | P61: =IFERROR(P59/O59-1,"") -> 0.30098523 | R61: =R59/P59-1 -> 0.27272119 | S61: =IFERROR(S59/R59-1,"") -> 0.0091918867 | T61: =IFERROR(T59/S59-1,"") -> 0.68076763 | U61: 0.5 | W61: -0.2 | X61: 0.02 | Y61: 0.05 | Z61: 0.03 | AB61: -0.1 | AC61: 0.2 | AD61: 0.05 | AE61: 0.07 | AG61: 0.07 | AH61: 0.13 | AI61: 0.13 | AJ61: 0.11
B62: Net New CapEx (yoy) | P62: =P59-K59 -> 944.193 | Q62: =Q59-L59 -> 944.193 | R62: =R59-M59 -> 4073.81 | S62: =S59-N59 -> 4111.256 | T62: =T59-O59 -> 4449.726 | U62: =U59-P59 -> 7164.233 | V62: =V59-Q59 -> 7164.233 | W62: =W59-R59 -> 4218.2692 | ... AK62: =AK59-AF59 -> 5733.4974
B63: Net New CapEx (qoq) | P63: =P59-O59 -> 740.526 | R63: =R59-P59 -> 872.944 | S63: =S59-R59 -> 37.446 | T63: =T59-S59 -> 2798.81 | U63: =U59-T59 -> 3455.033 | W63: =W59-U59 -> -2073.0198 | X63: =X59-W59 -> 165.84158 | Y63: =Y59-X59 -> 422.89604 | Z63: =Z59-Y59 -> 266.4245 | AB63: =AB59-Z59 -> -914.72413 | AC63: =AC59-AB59 -> 1646.5034 | AD63: =AD59-AC59 -> 493.95103 | AE63: =AE59-AD59 -> 726.10802 | AG63: =AG59-AE59 -> 776.93558 | AH63: =AH59-AG59 -> 1543.882 | AI63: =AI59-AH59 -> 1744.5866 | AJ63: =AJ59-AI59 -> 1668.0932
B64: % of PPE, Gross | O64: =O59/O31 -> 0.25289226 | P64: =P59/P31 -> 0.24851434 | Q64: =Q59/Q31 -> 0.24851434 | R64: =R59/R31 -> 0.2609652 | S64: =S59/S31 -> 0.22121227 | T64: =T59/T31 -> 0.2974149 | U64: =U59/U31 -> 0.32809147 | V64: =V59/V31 -> 0.32809147 | ... AK64: =AK59/AK31 -> 0.1681748
B66: Change in CIP | P66: =P59-O59 -> 740.526 | Q66: =Q59-L59 -> 944.193 | R66: =R59-Q59 -> 872.944 | S66: =S59-R59 -> 37.446 | T66: =T59-S59 -> 2798.81 | U66: =U59-T59 -> 3455.033 | V66: =SUM(R66:U66) -> 7164.233 | W66: =W59-U59 -> -2073.0198 | X66: =X59-W59 -> 165.84158 | Y66: =Y59-X59 -> 422.89604 | Z66: =Z59-Y59 -> 266.4245 | AA66: =SUM(W66:Z66) -> -1217.8577 | AB66: =AB59-Z59 -> -914.72413 | AC66: =AC59-AB59 -> 1646.5034 | AD66: =AD59-AC59 -> 493.95103 | AE66: =AE59-AD59 -> 726.10802 | AF66: =SUM(AB66:AE66) -> 1951.8384 | AG66: =AG59-AE59 -> 776.93558 | AH66: =AH59-AG59 -> 1543.882 | AI66: =AI59-AH59 -> 1744.5866 | AJ66: =AJ59-AI59 -> 1668.0932 | AK66: =SUM(AG66:AJ66) -> 5733.4974
B67: % yoy | M67: =IFERROR(M66/H66-1,"") | N67: =IFERROR(N66/I66-1,"") | O67: =IFERROR(O66/J66-1,"") | P67: =IFERROR(P66/K66-1,"") | Q67: =IFERROR(Q66/L66-1,"") | R67: =IFERROR(R66/M66-1,"") | S67: =IFERROR(S66/N66-1,"") | T67: =IFERROR(T66/O66-1,"") | ... AK67: =IFERROR(AK66/AF66-1,"") -> 1.9374858
B68: % qoq | M68: =IFERROR(M66/K66-1,"") | N68: =IFERROR(N66/M66-1,"") | O68: =IFERROR(O66/N66-1,"") | P68: =IFERROR(P66/O66-1,"") | R68: =IFERROR(R66/P66-1,"") -> 0.17881614 | S68: =IFERROR(S66/R66-1,"") -> -0.95710378 | T68: =IFERROR(T66/S66-1,"") -> 73.742563 | U68: =IFERROR(U66/T66-1,"") -> 0.234465 | W68: =IFERROR(W66/U66-1,"") -> -1.6 | X68: =IFERROR(X66/W66-1,"") -> -1.08 | Y68: =IFERROR(Y66/X66-1,"") -> 1.55 | Z68: =IFERROR(Z66/Y66-1,"") -> -0.37 | AB68: =IFERROR(AB66/Z66-1,"") -> -4.4333333 | AC68: =IFERROR(AC66/AB66-1,"") -> -2.8 | AD68: =IFERROR(AD66/AC66-1,"") -> -0.7 | AE68: =IFERROR(AE66/AD66-1,"") -> 0.47 | AG68: =IFERROR(AG66/AE66-1,"") -> 0.07 | AH68: =IFERROR(AH66/AG66-1,"") -> 0.98714286 | AI68: =IFERROR(AI66/AH66-1,"") -> 0.13 | AJ68: =IFERROR(AJ66/AI66-1,"") -> -0.043846154
B69: Net New CapEx (yoy) | R69: =R66-M66 -> 872.944 | S69: =S66-N66 -> 37.446 | T69: =T66-O66 -> 2798.81 | U69: =U66-P66 -> 2714.507 | V69: =V66-Q66 -> 6220.04 | W69: =W66-R66 -> -2945.9638 | X69: =X66-S66 -> 128.39558 | Y69: =Y66-T66 -> -2375.914 | ... AK69: =AK66-AF66 -> 3781.6591
B70: Net New CapEx (qoq) | R70: =R66-P66 -> 132.418 | S70: =S66-R66 -> -835.498 | T70: =T66-S66 -> 2761.364 | U70: =U66-T66 -> 656.223 | W70: =W66-U66 -> -5528.0528 | X70: =X66-W66 -> 2238.8614 | Y70: =Y66-X66 -> 257.05446 | Z70: =Z66-Y66 -> -156.47153 | AB70: =AB66-Z66 -> -1181.1486 | AC70: =AC66-AB66 -> 2561.2276 | AD70: =AD66-AC66 -> -1152.5524 | AE70: =AE66-AD66 -> 232.15698 | AG70: =AG66-AE66 -> 50.827561 | AH70: =AH66-AG66 -> 766.94641 | AI70: =AI66-AH66 -> 200.70466 | AJ70: =AJ66-AI66 -> -76.493414
B71: % of Total Purchase of P&E | R71: =R66/R$46 -> 0.62027102 | S71: =S66/S$46 -> 0.015265439 | T71: =T66/T$46 -> 0.85361167 | U71: =U66/U$46 -> 0.41336344 | V71: =V66/V$46 -> 0.46228377 | W71: =W66/W$46 -> -0.23504706 | X71: =X66/X$46 -> 0.032679453 | Y71: =Y66/Y$46 -> 0.11785258 | ... AK71: =AK66/AK$46 -> 0.23135348
B73: Total Finance Leases (GSe) | P73: =P34-P46+P66 -> -10.672 | Q73: =Q34-Q46+Q66 -> 542.115 | R73: =R34-R46+R66 -> 1365.585 | S73: =S34-S46+S66 -> 484.454 | T73: =T34-T46+T66 -> 1420.024 | U73: =T73*(1+U75) -> 1420.024 | V73: =SUM(R73:U73) -> 4690.087 | W73: =U73*(1+W75) -> 1491.0252 | X73: =W73*(1+X75) -> 1491.0252 | Y73: =X73*(1+Y75) -> 1491.0252 | Z73: =Y73*(1+Z75) -> 1491.0252 | AA73: =SUM(W73:Z73) -> 5964.1008 | AB73: =Z73*(1+AB75) -> 1491.0252 | AC73: =AB73*(1+AC75) -> 1491.0252 | AD73: =AC73*(1+AD75) -> 1491.0252 | AE73: =AD73*(1+AE75) -> 1491.0252 | AF73: =SUM(AB73:AE73) -> 5964.1008 | AG73: =AE73*(1+AG75) -> 1491.0252 | AH73: =AG73*(1+AH75) -> 1491.0252 | AI73: =AH73*(1+AI75) -> 1491.0252 | AJ73: =AI73*(1+AJ75) -> 1491.0252 | AK73: =SUM(AG73:AJ73) -> 5964.1008
B74: % yoy | M74: =IFERROR(M73/H73-1,"") | N74: =IFERROR(N73/I73-1,"") | O74: =IFERROR(O73/J73-1,"") | P74: =IFERROR(P73/K73-1,"") | Q74: =IFERROR(Q73/L73-1,"") | R74: =IFERROR(R73/M73-1,"") | S74: =IFERROR(S73/N73-1,"") | T74: =IFERROR(T73/O73-1,"") | ... AK74: =IFERROR(AK73/AF73-1,"") -> 0
B75: % qoq | P75: =IFERROR(#REF!/O73-1,"") | R75: =R73/P73-1 -> -128.95961 | S75: =IFERROR(S73/R73-1,"") -> -0.64524068 | T75: =IFERROR(T73/S73-1,"") -> 1.9311844 | U75: 0 | W75: 0.05 | X75: 0 | Y75: 0 | Z75: 0 | AB75: 0 | AC75: 0 | AD75: 0 | AE75: 0 | AG75: 0 | AH75: 0 | AI75: 0 | AJ75: 0
B76: Net New Finance Leases (yoy) | R76: =R73-M73 -> 1365.585 | S76: =S73-N73 -> 484.454 | T76: =T73-O73 -> 1420.024 | U76: =U73-P73 -> 1430.696 | V76: =V73-Q73 -> 4147.972 | W76: =W73-R73 -> 125.4402 | X76: =X73-S73 -> 1006.5712 | Y76: =Y73-T73 -> 71.0012 | ... AK76: =AK73-AF73 -> 0
B77: Net New Finance Leases (qoq) | R77: =R73-P73 -> 1376.257 | S77: =S73-R73 -> -881.131 | T77: =T73-S73 -> 935.57 | U77: =U73-T73 -> 0 | W77: =W73-U73 -> 71.0012 | X77: =X73-W73 -> 0 | Y77: =Y73-X73 -> 0 | Z77: =Z73-Y73 -> 0 | AB77: =AB73-Z73 -> 0 | AC77: =AC73-AB73 -> 0 | AD77: =AD73-AC73 -> 0 | AE77: =AE73-AD73 -> 0 | AG77: =AG73-AE73 -> 0 | AH77: =AH73-AG73 -> 0 | AI77: =AI73-AH73 -> 0 | AJ77: =AJ73-AI73 -> 0
B78: % of Total CapEx | R78: =R73/R$34 -> 0.71872895 | S78: =S73/S$46 -> 0.19749514 | T78: =T73/T$46 -> 0.43309444 | U78: =U73/U$46 -> 0.16989302 | V78: =V73/V$46 -> 0.30263548 | W78: =W73/W$46 -> 0.16905824 | X78: =X73/X$46 -> 0.29380983 | Y78: =Y73/Y$46 -> 0.41551859 | Z78: =Z73/Z$46 -> 0.43308772 | ... AK78: =AK73/AK$46 -> 0.2406586
B80: Capitalized Internally Developed Software | M80: 6.142 | N80: 6 | O80: 10 | P80: 9.002 | Q80: =SUM(M80:P80) -> 31.144 | R80: 26 | S80: 17 | T80: 19 | U80: =U83*U84 -> 20.589005 | V80: =SUM(R80:U80) -> 82.589005 | W80: =W83*W84 -> 27.625832 | X80: =X83*X84 -> 39.511605 | Y80: =Y83*Y84 -> 48.45 | Z80: =Z83*Z84 -> 43.236911 | AA80: =SUM(W80:Z80) -> 158.82435 | AB80: =AB83*AB84 -> 61.977952 | AC80: =AC83*AC84 -> 67.327775 | AD80: =AD83*AD84 -> 72.824383 | AE80: =AE83*AE84 -> 80.082278 | AF80: =SUM(AB80:AE80) -> 282.21239 | AG80: =AG83*AG84 -> 71.274645 | AH80: =AH83*AH84 -> 75.743747 | AI80: =AI83*AI84 -> 78.893082 | AJ80: =AJ83*AJ84 -> 84.086392 | AK80: =SUM(AG80:AJ80) -> 309.99787
B81: % yoy | M81: =IFERROR(M80/H80-1,"") | N81: =IFERROR(N80/I80-1,"") | O81: =IFERROR(O80/J80-1,"") | P81: =IFERROR(P80/K80-1,"") | Q81: =IFERROR(Q80/L80-1,"") | R81: =IFERROR(R80/M80-1,"") -> 3.2331488 | S81: =IFERROR(S80/N80-1,"") -> 1.8333333 | T81: =IFERROR(T80/O80-1,"") -> 0.9 | ... AK81: =IFERROR(AK80/AF80-1,"") -> 0.098455909
B82: % qoq | M82: =IFERROR(M80/K80-1,"") | N82: =IFERROR(N80/M80-1,"") -> -0.023119505 | O82: =IFERROR(O80/N80-1,"") -> 0.66666667 | P82: =IFERROR(P80/O80-1,"") -> -0.0998 | R82: =IFERROR(R80/P80-1,"") -> 1.8882471 | S82: =IFERROR(S80/R80-1,"") -> -0.34615385 | T82: =IFERROR(T80/S80-1,"") -> 0.11764706 | U82: =IFERROR(U80/T80-1,"") -> 0.083631848 | W82: =IFERROR(W80/U80-1,"") -> 0.34177593 | X82: =IFERROR(X80/W80-1,"") -> 0.43024129 | Y82: =IFERROR(Y80/X80-1,"") -> 0.22622202 | Z82: =IFERROR(Z80/Y80-1,"") -> -0.1075973 | AB82: =IFERROR(AB80/Z80-1,"") -> 0.43345006 | AC82: =IFERROR(AC80/AB80-1,"") -> 0.086318154 | AD82: =IFERROR(AD80/AC80-1,"") -> 0.081639534 | AE82: =IFERROR(AE80/AD80-1,"") -> 0.09966298 | AG82: =IFERROR(AG80/AE80-1,"") -> -0.1099823 | AH82: =IFERROR(AH80/AG80-1,"") -> 0.062702542 | AI82: =IFERROR(AI80/AH80-1,"") -> 0.04157881 | AJ82: =IFERROR(AJ80/AI80-1,"") -> 0.065827196
B83: % of Non-GAAP T&I | M83: =M80/M84 -> 0.06784941 | N83: =N80/N84 -> 0.033184739 | O83: =O80/O84 -> 0.035292291 | P83: =P80/P84 -> 0.022726885 | Q83: =Q80/Q84 -> 0.032756513 | R83: =R80/R84 -> 0.051301985 | S83: =S80/S84 -> 0.027321087 | T83: =T80/T84 -> 0.027343795 | U83: 0.023 | V83: =V80/'IS (Non-GAAP)'!V$23 -> 0.030374067 | W83: 0.023 | X83: 0.025 | Y83: =T83 -> 0.027343795 | Z83: =U83 -> 0.023 | AA83: =AA80/'IS (Non-GAAP)'!AA$23 -> 0.024687713 | AB83: 0.03 | AC83: =AB83 -> 0.03 | AD83: =AC83 -> 0.03 | AE83: =AD83 -> 0.03 | AF83: =AF80/'IS (Non-GAAP)'!AF$23 -> 0.03 | AG83: 0.025 | AH83: =AG83 -> 0.025 | AI83: =AH83 -> 0.025 | AJ83: =AI83 -> 0.025 | AK83: =AK80/'IS (Non-GAAP)'!AK$23 -> 0.025
B84: Non-GAAP T&I | M84: ='IS (Non-GAAP)'!M23 -> 90.524 | N84: ='IS (Non-GAAP)'!N23 -> 180.806 | O84: ='IS (Non-GAAP)'!O23 -> 283.348 | P84: ='IS (Non-GAAP)'!P23 -> 396.09475 | Q84: ='IS (Non-GAAP)'!Q23 -> 950.77275 | R84: ='IS (Non-GAAP)'!R23 -> 506.803 | S84: ='IS (Non-GAAP)'!S23 -> 622.23 | T84: ='IS (Non-GAAP)'!T23 -> 694.856 | ... AK84: ='IS (Non-GAAP)'!AK23 -> 12399.915
B85: Useful Life | M85: 4.5 | N85: =M85 -> 4.5 | O85: =N85 -> 4.5 | P85: =O85 -> 4.5 | Q85: =P85 -> 4.5 | R85: 4.5 | S85: 4.5 | T85: =S85 -> 4.5 | U85: =T85 -> 4.5 | V85: =U85 -> 4.5 | W85: 4.5 | X85: =W85 -> 4.5 | Y85: =X85 -> 4.5 | Z85: =Y85 -> 4.5 | AA85: =Z85 -> 4.5 | AB85: 4.5 | AC85: =AB85 -> 4.5 | AD85: =AC85 -> 4.5 | AE85: =AD85 -> 4.5 | AF85: =AE85 -> 4.5 | AG85: 4.5 | AH85: =AG85 -> 4.5 | AI85: =AH85 -> 4.5 | AJ85: =AI85 -> 4.5 | AK85: =AJ85 -> 4.5
B87: Capitalized Labor | M87: 4.073 | N87: 5.295 | O87: 5.617 | P87: 10.571 | Q87: =SUM(M87:P87) -> 25.556 | R87: =M87*(1+R88) -> 12.219 | S87: =N87*(1+S88) -> 15.885 | T87: =O87*(1+T88) -> 16.851 | U87: =P87*(1+U88) -> 31.713 | V87: =SUM(R87:U87) -> 76.668 | W87: =R87*(1+W88) -> 36.657 | X87: =S87*(1+X88) -> 39.7125 | Y87: =T87*(1+Y88) -> 33.702 | Z87: =U87*(1+Z88) -> 47.5695 | AA87: =SUM(W87:Z87) -> 157.641 | AB87: =W87*(1+AB88) -> 54.9855 | AC87: =X87*(1+AC88) -> 59.56875 | AD87: =Y87*(1+AD88) -> 38.7573 | AE87: =Z87*(1+AE88) -> 54.704925 | AF87: =SUM(AB87:AE87) -> 208.01647 | AG87: =AB87*(1+AG88) -> 82.47825 | AH87: =AC87*(1+AH88) -> 89.353125 | AI87: =AD87*(1+AI88) -> 44.570895 | AJ87: =AE87*(1+AJ88) -> 62.910664 | AK87: =SUM(AG87:AJ87) -> 279.31293
B88: % yoy | M88: =IFERROR(M87/H87-1,"") | N88: =IFERROR(N87/I87-1,"") | O88: =IFERROR(O87/J87-1,"") | P88: =IFERROR(P87/K87-1,"") | Q88: =IFERROR(Q87/L87-1,"") | R88: 2 | S88: 2 | T88: 2 | U88: 2 | V88: =IFERROR(V87/Q87-1,"") -> 2 | W88: 2 | X88: 1.5 | Y88: 1 | Z88: 0.5 | AA88: =IFERROR(AA87/V87-1,"") -> 1.0561512 | AB88: 0.5 | AC88: =AB88 -> 0.5 | AD88: 0.15 | AE88: =AD88 -> 0.15 | AF88: =IFERROR(AF87/AA87-1,"") -> 0.31955821 | AG88: 0.5 | AH88: =AG88 -> 0.5 | AI88: 0.15 | AJ88: =AI88 -> 0.15 | AK88: =IFERROR(AK87/AF87-1,"") -> 0.34274429
B89: % qoq | M89: =IFERROR(M87/K87-1,"") | N89: =IFERROR(N87/M87-1,"") -> 0.30002455 | O89: =IFERROR(O87/N87-1,"") -> 0.060812087 | P89: =IFERROR(P87/O87-1,"") -> 0.88196546 | R89: =IFERROR(R87/P87-1,"") -> 0.15589821 | S89: =IFERROR(S87/R87-1,"") -> 0.30002455 | T89: =IFERROR(T87/S87-1,"") -> 0.060812087 | U89: =IFERROR(U87/T87-1,"") -> 0.88196546 | W89: =IFERROR(W87/U87-1,"") -> 0.15589821 | X89: =IFERROR(X87/W87-1,"") -> 0.083353793 | Y89: =IFERROR(Y87/X87-1,"") -> -0.15135033 | Z89: =IFERROR(Z87/Y87-1,"") -> 0.4114741 | AB89: =IFERROR(AB87/Z87-1,"") -> 0.15589821 | AC89: =IFERROR(AC87/AB87-1,"") -> 0.083353793 | AD89: =IFERROR(AD87/AC87-1,"") -> -0.34936859 | AE89: =IFERROR(AE87/AD87-1,"") -> 0.4114741 | AG89: =IFERROR(AG87/AE87-1,"") -> 0.50769332 | AH89: =IFERROR(AH87/AG87-1,"") -> 0.083353793 | AI89: =IFERROR(AI87/AH87-1,"") -> -0.50118258 | AJ89: =IFERROR(AJ87/AI87-1,"") -> 0.4114741
B90: % of Non-GAAP Cost of Revenue | M90: =M87/'IS (Non-GAAP)'!M$14 -> 0.069231031 | N90: =N87/'IS (Non-GAAP)'!N$14 -> 0.048807241 | O90: =O87/'IS (Non-GAAP)'!O$14 -> 0.039317388 | P90: =P87/'IS (Non-GAAP)'!P$14 -> 0.058127211 | Q90: =Q87/'IS (Non-GAAP)'!Q$14 -> 0.051938576 | R90: =R87/'IS (Non-GAAP)'!R$14 -> 0.047050262 | S90: =S87/'IS (Non-GAAP)'!S$14 -> 0.051247556 | T90: =T87/'IS (Non-GAAP)'!T$14 -> 0.046130345 | ... AK90: =AK87/'IS (Non-GAAP)'!AK$14 -> 0.061420278
B91: Useful Life | M91: 6 | N91: =M91 -> 6 | O91: =N91 -> 6 | P91: =O91 -> 6 | Q91: =P91 -> 6 | R91: 6 | S91: =R91 -> 6 | T91: =S91 -> 6 | U91: =T91 -> 6 | V91: =U91 -> 6 | W91: 6 | X91: =W91 -> 6 | Y91: =X91 -> 6 | Z91: =Y91 -> 6 | AA91: =Z91 -> 6 | AB91: 6 | AC91: =AB91 -> 6 | AD91: =AC91 -> 6 | AE91: =AD91 -> 6 | AF91: =AE91 -> 6 | AG91: 6 | AH91: =AG91 -> 6 | AI91: =AH91 -> 6 | AJ91: =AI91 -> 6 | AK91: =AJ91 -> 6
B93: Capitalized Interest | M93: =-'IS (GAAP)'!M56 -> 32.177 | N93: =-'IS (GAAP)'!N56 -> 40.687 | O93: =-'IS (GAAP)'!O56 -> 35.072 | P93: =-'IS (GAAP)'!P56 -> 51.081 | Q93: =-'IS (GAAP)'!Q56 -> 159.017 | R93: =-'IS (GAAP)'!R56 -> 13.092 | S93: =-'IS (GAAP)'!S56 -> 23.186 | T93: =-'IS (GAAP)'!T56 -> 61.764 | U93: =U59*(U98) -> 92.646 | V93: =SUM(R93:U93) -> 190.688 | W93: =W59*(W98) -> 69.97076 | X93: =X59*(X98) -> 71.370176 | Y93: =Y59*(Y98) -> 74.938684 | Z93: =Z59*(Z98) -> 77.186845 | AA93: =SUM(W93:Z93) -> 293.46647 | AB93: =AB59*(AB98) -> 65.351902 | AC93: =AC59*(AC98) -> 78.422282 | AD93: =AD59*(AD98) -> 82.343396 | AE93: =AE59*(AE98) -> 88.107434 | AF93: =SUM(AB93:AE93) -> 314.22501 | AG93: =AG59*(AG98) -> 88.336947 | AH93: =AH59*(AH98) -> 99.82075 | AI93: =AI59*(AI98) -> 112.79745 | AJ93: =AJ59*(AJ98) -> 125.20517 | AK93: =SUM(AG93:AJ93) -> 426.16031
B94: % yoy | M94: =IFERROR(M93/H93-1,"") | N94: =IFERROR(N93/I93-1,"") | O94: =IFERROR(O93/J93-1,"") | P94: =IFERROR(P93/K93-1,"") | Q94: =IFERROR(Q93/L93-1,"") | R94: =IFERROR(R93/M93-1,"") -> -0.59312552 | S94: =IFERROR(S93/N93-1,"") -> -0.43013739 | T94: =IFERROR(T93/O93-1,"") -> 0.76106296 | ... AK94: =IFERROR(AK93/AF93-1,"") -> 0.35622656
B95: % qoq | M95: =IFERROR(M93/K93-1,"") | N95: =IFERROR(N93/M93-1,"") -> 0.26447462 | O95: =IFERROR(O93/N93-1,"") -> -0.13800477 | P95: =IFERROR(P93/O93-1,"") -> 0.45646099 | R95: =IFERROR(R93/P93-1,"") -> -0.74370118 | S95: =IFERROR(S93/R93-1,"") -> 0.77100519 | T95: =IFERROR(T93/S93-1,"") -> 1.6638489 | U95: =IFERROR(U93/T93-1,"") -> 0.5 | W95: =IFERROR(W93/U93-1,"") -> -0.24475142 | X95: =IFERROR(X93/W93-1,"") -> 0.02 | Y95: =IFERROR(Y93/X93-1,"") -> 0.05 | Z95: =IFERROR(Z93/Y93-1,"") -> 0.03 | AB95: =IFERROR(AB93/Z93-1,"") -> -0.1533285 | AC95: =IFERROR(AC93/AB93-1,"") -> 0.2 | AD95: =IFERROR(AD93/AC93-1,"") -> 0.05 | AE95: =IFERROR(AE93/AD93-1,"") -> 0.07 | AG95: =IFERROR(AG93/AE93-1,"") -> 0.0026049193 | AH95: =IFERROR(AH93/AG93-1,"") -> 0.13 | AI95: =IFERROR(AI93/AH93-1,"") -> 0.13 | AJ95: =IFERROR(AJ93/AI93-1,"") -> 0.11
B96: Useful Life | M96: 6 | N96: =M96 -> 6 | O96: =N96 -> 6 | P96: =O96 -> 6 | Q96: =P96 -> 6 | R96: 6 | S96: =R96 -> 6 | T96: =S96 -> 6 | U96: =T96 -> 6 | V96: =U96 -> 6 | W96: 6 | X96: =W96 -> 6 | Y96: =X96 -> 6 | Z96: =Y96 -> 6 | AA96: =Z96 -> 6 | AB96: 6 | AC96: =AB96 -> 6 | AD96: =AC96 -> 6 | AE96: =AD96 -> 6 | AF96: =AE96 -> 6 | AG96: 6 | AH96: =AG96 -> 6 | AI96: =AH96 -> 6 | AJ96: =AI96 -> 6 | AK96: =AJ96 -> 6
B97: % PPE | M97: =M93/M31 -> 0.0061077614 | N97: =N93/N31 -> 0.005508999 | O97: =O93/O31 -> 0.0036049641 | P97: =P93/P31 -> 0.0039659146 | Q97: =Q93/Q31 -> 0.012346036 | R97: 0.0039306045 | S97: 0.0054576479 | T97: 0.0054576479 | U97: 0.0019734831 | V97: =V93/V31 -> 0.0060359392 | W97: 0.0013990112 | X97: 0.0013941514 | Y97: 0.0012836676 | Z97: 0.001254325 | AA97: =AA93/AA31 -> 0.0055879621 | AB97: 0.0011013438 | AC97: 0.0011396384 | AD97: 0.0010816383 | AE97: 0.0010743136 | AF97: =AF93/AF31 -> 0.0041725674 | AG97: 0.0011013438 | AH97: 0.0011396384 | AI97: 0.0010816383 | AJ97: 0.0010743136 | AK97: =AK93/AK31 -> 0.004257781
B98: % of Capex CIP | P98: =P93/P59 -> 0.015958494 | R98: =R93/R59 -> 0.0032136992 | S98: =S93/S59 -> 0.0056396391 | T98: =T93/T59 -> 0.0089382648 | U98: =T98 -> 0.0089382648 | W98: =U98-0.05% -> 0.0084382648 | X98: =W98 -> 0.0084382648 | Y98: =X98 -> 0.0084382648 | Z98: =Y98 -> 0.0084382648 | AB98: =Z98-0.05% -> 0.0079382648 | AC98: =AB98 -> 0.0079382648 | AD98: =AC98 -> 0.0079382648 | AE98: =AD98 -> 0.0079382648 | AG98: =AE98-0.05% -> 0.0074382648 | AH98: =AG98 -> 0.0074382648 | AI98: =AH98 -> 0.0074382648 | AJ98: =AI98 -> 0.0074382648
B100: Depreciation and Amortization | AA100: =AA101-V101 -> 3591.8513
B101: Total Depreciation and Amortization | L101: =CF!L14 -> 103.21 | M101: =M110+M106 -> 80.82 | N101: =N110+N106 -> 167.839 | O101: =O110+O106 -> 259.672 | P101: =P110+P106 -> 365.939 | Q101: =Q110+Q106 -> 874.27 | R101: =R110+R106 -> 457.98878 | S101: =S110+S106 -> 567.49224 | T101: =T110+T106 -> 630.40265 | ... AK101: =AK110+AK106 -> 12018.204
B102: % yoy | M102: =IFERROR(M101/H101-1,"") | N102: =IFERROR(N101/I101-1,"") | O102: =IFERROR(O101/J101-1,"") | P102: =IFERROR(P101/K101-1,"") | Q102: =IFERROR(Q101/L101-1,"") -> 7.4707877 | R102: =IFERROR(R101/M101-1,"") -> 4.6667753 | S102: =IFERROR(S101/N101-1,"") -> 2.3811703 | T102: =IFERROR(T101/O101-1,"") -> 1.4276882 | ... AK102: =IFERROR(AK101/AF101-1,"") -> 0.37155393
B103: % qoq | M103: =IFERROR(M101/K101-1,"") | N103: =IFERROR(N101/M101-1,"") -> 1.0767013 | O103: =IFERROR(O101/N101-1,"") -> 0.54714935 | P103: =IFERROR(P101/O101-1,"") -> 0.4092355 | R103: =IFERROR(R101/P101-1,"") -> 0.25154405 | S103: =IFERROR(S101/R101-1,"") -> 0.23909638 | T103: =IFERROR(T101/S101-1,"") -> 0.11085688 | U103: =IFERROR(U101/T101-1,"") -> 0.24547204 | W103: =IFERROR(W101/U101-1,"") -> 0.49728224 | X103: =IFERROR(X101/W101-1,"") -> 0.17445595 | Y103: =IFERROR(Y101/X101-1,"") -> 0.096015677 | Z103: =IFERROR(Z101/Y101-1,"") -> 0.087856643 | AB103: =IFERROR(AB101/Z101-1,"") -> 0.13190369 | AC103: =IFERROR(AC101/AB101-1,"") -> 0.11708688 | AD103: =IFERROR(AD101/AC101-1,"") -> 0.10462308 | AE103: =IFERROR(AE101/AD101-1,"") -> 0.095282643 | AG103: =IFERROR(AG101/AE101-1,"") -> 0.074157272 | AH103: =IFERROR(AH101/AG101-1,"") -> 0.073911359 | AI103: =IFERROR(AI101/AH101-1,"") -> 0.068428497 | AJ103: =IFERROR(AJ101/AI101-1,"") -> 0.064551646
B104: % of Revenue | M104: =M101/'KPI Summary'!M10 -> 0.42833521 | N104: =N101/'KPI Summary'!N10 -> 0.42451014 | O104: =O101/'KPI Summary'!O10 -> 0.44468876 | P104: =P101/'KPI Summary'!P10 -> 0.48959635 | Q104: =Q101/'KPI Summary'!Q10 -> 0.45643632 | R104: =R101/'KPI Summary'!R10 -> 0.46655852 | S104: =S101/'KPI Summary'!S10 -> 0.46792369 | T104: =T101/'KPI Summary'!T10 -> 0.46194309 | ... AK104: =AK101/'KPI Summary'!AK10 -> 0.55498289
B106: Fixed Asset Depreciation | M106: 79 | N106: 164 | O106: 253 | P106: 357.527 | Q106: =SUM(M106:P106) -> 853.527 | R106: 443 | S106: 553 | T106: 621 | U106: ='Depreciation Build'!U28 -> 760 | V106: ='Depreciation Build'!V28 -> 2059.8218 | W106: ='Depreciation Build'!W28 -> 1144.463 | X106: ='Depreciation Build'!X28 -> 1342.728 | Y106: ='Depreciation Build'!Y28 -> 1468.0764 | Z106: ='Depreciation Build'!Z28 -> 1593.4248 | AA106: ='Depreciation Build'!AA28 -> 5548.6922 | AB106: ='Depreciation Build'!AB28 -> 1802.1065 | ... AK106: ='Depreciation Build'!AK28 -> 11580.09
B107: % yoy | M107: =IFERROR(M106/H106-1,"") | N107: =IFERROR(N106/I106-1,"") | O107: =IFERROR(O106/J106-1,"") | P107: =IFERROR(P106/K106-1,"") | Q107: =IFERROR(Q106/L106-1,"") | R107: =IFERROR(R106/M106-1,"") -> 4.6075949 | S107: =IFERROR(S106/N106-1,"") -> 2.3719512 | T107: =IFERROR(T106/O106-1,"") -> 1.4545455 | ... AK107: =IFERROR(AK106/AF106-1,"") -> 0.36872147
B108: % qoq | M108: =IFERROR(M106/K106-1,"") | N108: =IFERROR(N106/M106-1,"") -> 1.0759494 | O108: =IFERROR(O106/N106-1,"") -> 0.54268293 | P108: =IFERROR(P106/O106-1,"") -> 0.4131502 | R108: =IFERROR(R106/P106-1,"") -> 0.23906726 | S108: =IFERROR(S106/R106-1,"") -> 0.248307 | T108: =IFERROR(T106/S106-1,"") -> 0.12296564 | U108: =IFERROR(U106/T106-1,"") -> 0.22383253 | W108: =IFERROR(W106/U106-1,"") -> 0.50587236 | X108: =IFERROR(X106/W106-1,"") -> 0.17323849 | Y108: =IFERROR(Y106/X106-1,"") -> 0.09335351 | Z108: =IFERROR(Z106/Y106-1,"") -> 0.085382732 | AB108: =IFERROR(AB106/Z106-1,"") -> 0.13096427 | AC108: =IFERROR(AC106/AB106-1,"") -> 0.11579877 | AD108: =IFERROR(AD106/AC106-1,"") -> 0.10378105 | AE108: =IFERROR(AE106/AD106-1,"") -> 0.09402322 | AG108: =IFERROR(AG106/AE106-1,"") -> 0.076230155 | AH108: =IFERROR(AH106/AG106-1,"") -> 0.071883048 | AI108: =IFERROR(AI106/AH106-1,"") -> 0.067062398 | AJ108: =IFERROR(AJ106/AI106-1,"") -> 0.062847682
B110: Total Amortization | G110: =SUM(G111:G113) -> 0 | H110: =SUM(H111:H113) -> 0 | I110: =SUM(I111:I113) -> 0 | J110: =SUM(J111:J113) -> 0 | K110: =SUM(K111:K113) -> 0 | L110: =SUM(L111:L113) -> 0 | M110: =SUM(M111:M113) -> 1.82 | N110: =SUM(N111:N113) -> 3.839 | ... AK110: =SUM(AK111:AK113) -> 438.11369
B111: Amortization - Capitalized Internally Developed Software | M111: 0.954 | N111: 1.364 | O111: 1.839 | P111: 2.415 | Q111: =SUM(M111:P111) -> 6.572 | R111: =SUM(P80,Q80:R80)/(R85*4) -> 3.6747778 | S111: =SUM(Q80,R80:S80)/(S85*4) -> 4.1191111 | T111: =SUM(R80,S80:T80)/(T85*4) -> 3.4444444 | U111: =SUM(Q80,R80:U80)/(U85*4) -> 6.3185003 | V111: =SUM(R111:U111) -> 17.556834 | W111: =SUM(Q80,V80,W80)/(W85*4) -> 7.8532687 | X111: =SUM(Q80,V80,W80:X80)/(X85*4) -> 10.048358 | Y111: =SUM(Q80,V80,W80:Y80)/(Y85*4) -> 12.740025 | Z111: =SUM(Q80,V80,W80:Z80)/(Z85*4) -> 15.142075 | AA111: =SUM(W111:Z111) -> 45.783726 | AB111: =SUM(Q80,V80,AA80,AB80)/(AB85*4) -> 18.585295 | AC111: =SUM(Q80,V80,AA80,AB80:AC80)/(AC85*4) -> 22.325727 | AD111: =SUM(Q80,V80,AA80,AB80:AD80)/(AD85*4) -> 26.371526 | AE111: =SUM(Q80,V80,AA80,AB80:AE80)/(AE85*4) -> 30.820541 | AF111: =SUM(AB111:AE111) -> 98.103088 | AG111: =SUM(V80,AA80,AF80,AG80)/(AG85*4) -> 33.050021 | AH111: =SUM(V80,AA80,AF80,AG80:AH80)/(AH85*4) -> 37.258007 | AI111: =SUM(V80,AA80,AF80,AG80:AI80)/(AI85*4) -> 41.640956 | AJ111: =SUM(V80,AA80,AF80,AG80:AJ80)/(AJ85*4) -> 46.312423 | AK111: =SUM(AG111:AJ111) -> 158.26141
B112: Amortization - Capitalized Labor | M112: 0.036 | N112: 0.075 | O112: 0.441 | P112: 0.662 | Q112: =SUM(M112:P112) -> 1.214 | R112: =SUM(P87,Q87:R87)/(R91*4) -> 2.0144167 | S112: =SUM(Q87,R87:S87)/(S91*4) -> 2.2358333 | T112: =SUM(R87,S87:T87)/(T91*4) -> 1.873125 | U112: =SUM(Q87,R87:U87)/(U91*4) -> 4.2593333 | V112: =SUM(R112:U112) -> 10.382708 | W112: =SUM(Q87,V87,W87)/(W91*4) -> 5.7867083 | X112: =SUM(Q87,V87,W87:X87)/(X91*4) -> 7.4413958 | Y112: =SUM(Q87,V87,W87:Y87)/(Y91*4) -> 8.8456458 | Z112: =SUM(Q87,V87,W87:Z87)/(Z91*4) -> 10.827708 | AA112: =SUM(W112:Z112) -> 32.901458 | AB112: =SUM(Q87,V87,AA87,AB87)/(AB91*4) -> 13.118771 | AC112: =SUM(Q87,V87,AA87,AB87:AC87)/(AC91*4) -> 15.600802 | AD112: =SUM(Q87,V87,AA87,AB87:AD87)/(AD91*4) -> 17.21569 | AE112: =SUM(Q87,V87,AA87,AB87:AE87)/(AE91*4) -> 19.495061 | AF112: =SUM(AB112:AE112) -> 65.430324 | AG112: =SUM(V87,AA87,AF87,AG87)/(AG91*4) -> 21.866822 | AH112: =SUM(V87,AA87,AF87,AG87:AH87)/(AH91*4) -> 25.589869 | AI112: =SUM(V87,AA87,AF87,AG87:AI87)/(AI91*4) -> 27.446989 | AJ112: =SUM(V87,AA87,AF87,AG87:AJ87)/(AJ91*4) -> 30.068267 | AK112: =SUM(AG112:AJ112) -> 104.97195
B113: Amortization - Capitalized Interest | M113: 0.83 | N113: 2.4 | O113: 4.392 | P113: 5.335 | Q113: =SUM(M113:P113) -> 12.957 | R113: =SUM(P93,Q93:R93)/(R96*4) -> 9.2995833 | S113: =SUM(Q93,R93:S93)/(S96*4) -> 8.1372917 | T113: =SUM(R93,S93:T93)/(T96*4) -> 4.0850833 | U113: =SUM(Q93,R93:U93)/(U96*4) -> 14.571042 | V113: =SUM(R113:U113) -> 36.093 | W113: =SUM(Q93,V93,W93)/(W96*4) -> 17.48649 | X113: =SUM(Q93,V93,W93:X93)/(X96*4) -> 20.460247 | Y113: =SUM(Q93,V93,W93:Y93)/(Y96*4) -> 23.582693 | Z113: =SUM(Q93,V93,W93:Z93)/(Z96*4) -> 26.798811 | AA113: =SUM(W113:Z113) -> 88.328241 | AB113: =SUM(Q93,V93,AA93,AB93)/(AB96*4) -> 29.521807 | AC113: =SUM(Q93,V93,AA93,AB93:AC93)/(AC96*4) -> 32.789402 | AD113: =SUM(Q93,V93,AA93,AB93:AD93)/(AD96*4) -> 36.220377 | AE113: =SUM(Q93,V93,AA93,AB93:AE93)/(AE96*4) -> 39.89152 | AF113: =SUM(AB113:AE113) -> 138.42311 | AG113: =SUM(V93,AA93,AF93,AG93)/(AG96*4) -> 36.946518 | AH113: =SUM(V93,AA93,AF93,AG93:AH93)/(AH96*4) -> 41.105716 | AI113: =SUM(V93,AA93,AF93,AG93:AI93)/(AI96*4) -> 45.805609 | AJ113: =SUM(V93,AA93,AF93,AG93:AJ93)/(AJ96*4) -> 51.022491 | AK113: =SUM(AG113:AJ113) -> 174.88033
B115: Accumulated Depreciation and Amortization | K115: =BS!K21 -> -116.796 | L115: =K115 -> -116.796 | M115: =BS!M21 -> -195.782 | N115: =BS!N21 -> -359.722 | O115: =BS!O21 -> -612.217 | P115: =BS!P21 -> -965.231 | Q115: =P115 -> -965.231 | R115: =BS!R21 -> -1399.557 | S115: =BS!S21 -> -1953.607 | T115: =BS!T21 -> -2574.578 | U115: =T115-U101 -> -3359.7269 | V115: =U115 -> -3359.7269 | W115: =V115-W101 -> -4535.3163 | X115: =W115-X101 -> -5915.9944 | Y115: =X115-Y101 -> -7429.2392 | Z115: =Y115-Z101 -> -9075.4325 | AA115: =Z115 -> -9075.4325 | AB115: =AA115-AB101 -> -10938.765 | AC115: =AB115-AC101 -> -13020.269 | AD115: =AC115-AD101 -> -15319.547 | AE115: =AD115-AE101 -> -17837.905 | AF115: =AE115 -> -17837.905 | AG115: =AF115-AG101 -> -20543.019 | AH115: =AG115-AH101 -> -23448.071 | AI115: =AH115-AI101 -> -26551.911 | AJ115: =AI115-AJ101 -> -29856.109 | AK115: =AJ115 -> -29856.109
B116: Accumulated Amortization | K116: -2.347 | L116: =K116 -> -2.347 | O116: -3.92 | P116: -4.441 | Q116: =P116 -> -4.441 | R116: -4.955 | S116: -11.055 | T116: -20.564
B117: Accumulated Depreciation (Implied) | K117: =K115-K116 -> -114.449 | L117: =K117 -> -114.449 | O117: =O115-O116 -> -608.297 | P117: =P115-P116 -> -960.79 | Q117: =P117 -> -960.79 | R117: =R115-R116 -> -1394.602 | S117: =S115-S116 -> -1942.552 | T117: =T115-T116 -> -2554.014
B119: Property and Equipment, Net, Breakdown
B120: Technology Equipment | K120: 1298.127 | L120: =K120 -> 1298.127 | O120: 6886.183 | P120: 9146.575 | Q120: =P120 -> 9146.575 | R120: 10746.445 | S120: 13170.295 | T120: 14628.79
B121: Software | K121: 14.937 | L121: =K121 -> 14.937 | O121: 69.209 | P121: 245.458 | Q121: =P121 -> 245.458 | R121: 245.458 | S121: 459.742 | T121: 541.567
B122: Data Center Equipment and Leasehold Improvements | K122: 39.332 | L122: =K122 -> 39.332 | O122: 308.264 | P122: 139.508 | Q122: =P122 -> 139.508 | R122: 534.12 | S122: 830.875 | T122: 1139.095
...

Sheet KPI Summary
B2: CoreWeave, Inc.
B3: Fiscal Year Ends Dec. 31
B4: ($ millions, except per share amounts)
C6: =Dates!C3 -> 2022 (A) | H6: =Dates!H3 -> 2023 (A) | M6: =Dates!M3 -> 2024 (A) | R6: =Dates!R3 -> 2025 (E) | W6: =Dates!W3 -> 2026 (E) | AB6: =Dates!AB3 -> 2027 (E) | AG6: =Dates!AG3 -> 2028 (E)
C7: =Dates!C4 -> 1Q22 (A) | D7: =Dates!D4 -> 2Q22 (A) | E7: =Dates!E4 -> 3Q22 (A) | F7: =Dates!F4 -> 4Q22 (A) | G7: =Dates!G4 -> FY22 (A) | H7: =Dates!H4 -> 1Q23 (A) | I7: =Dates!I4 -> 2Q23 (A) | J7: =Dates!J4 -> 3Q23 (A) | ... AK7: =Dates!AK4 -> FY28 (E)
C8: =Dates!C5 -> 44651 | D8: =Dates!D5 -> 44742 | E8: =Dates!E5 -> 44834 | F8: =Dates!F5 -> 44926 | G8: =Dates!G5 -> 44926 | H8: =Dates!H5 -> 45016 | I8: =Dates!I5 -> 45107 | J8: =Dates!J5 -> 45199 | ... AK8: =Dates!AK5 -> 47118
A10: TREV | B10: Total Revenue | G10: ='Revenue and CapEx Build'!G10 -> 15.83 | H10: ='Revenue and CapEx Build'!H10 -> 7.9236843 | I10: ='Revenue and CapEx Build'!I10 -> 29.8436 | J10: ='Revenue and CapEx Build'!J10 -> 75.178825 | K10: ='Revenue and CapEx Build'!K10 -> 115.99689 | L10: ='Revenue and CapEx Build'!L10 -> 228.943 | M10: ='Revenue and CapEx Build'!M10 -> 188.684 | N10: ='Revenue and CapEx Build'!N10 -> 395.371 | ... AK10: ='Revenue and CapEx Build'!AK10 -> 21655.089
A11: TREVYY | B11: % yoy | H11: =IFERROR(H10/C10-1,"") | I11: =IFERROR(I10/D10-1,"") | J11: =IFERROR(J10/E10-1,"") | K11: =IFERROR(K10/F10-1,"") | L11: =IFERROR(L10/G10-1,"") -> 13.462603 | M11: =IFERROR(M10/H10-1,"") -> 22.81266 | N11: =IFERROR(N10/I10-1,"") -> 12.2481 | O11: =IFERROR(O10/J10-1,"") -> 6.76736 | ... AK11: =IFERROR(AK10/AF10-1,"") -> 0.25822019
A12: TREVQQ | B12: % qoq | H12: =IFERROR(H10/F10-1,"") | I12: =IFERROR(I10/H10-1,"") -> 2.7663793 | J12: =IFERROR(J10/I10-1,"") -> 1.5190937 | K12: =IFERROR(K10/J10-1,"") -> 0.5429463 | M12: =IFERROR(M10/K10-1,"") -> 0.62662981 | N12: =IFERROR(N10/M10-1,"") -> 1.0954135 | O12: =IFERROR(O10/N10-1,"") -> 0.47694444 | P12: =IFERROR(P10/O10-1,"") -> 0.2799752 | R12: =IFERROR(R10/P10-1,"") -> 0.31334306 | S12: =IFERROR(S10/R10-1,"") -> 0.23548132 | T12: =IFERROR(T10/S10-1,"") -> 0.12523871 | U12: =IFERROR(U10/T10-1,"") -> 0.13058326 | W12: =IFERROR(W10/U10-1,"") -> 0.44348713 | X12: =IFERROR(X10/W10-1,"") -> 0.33094883 | Y12: =IFERROR(Y10/X10-1,"") -> 0.10980793 | Z12: =IFERROR(Z10/Y10-1,"") -> 0.070204816 | AB12: =IFERROR(AB10/Z10-1,"") -> 0.082649169 | AC12: =IFERROR(AC10/AB10-1,"") -> 0.089818799 | AD12: =IFERROR(AD10/AC10-1,"") -> 0.077002222 | AE12: =IFERROR(AE10/AD10-1,"") -> 0.066529754 | AG12: =IFERROR(AG10/AE10-1,"") -> 0.072718069 | AH12: =IFERROR(AH10/AG10-1,"") -> 0.041288386 | AI12: =IFERROR(AI10/AH10-1,"") -> 0.035552396 | AJ12: =IFERROR(AJ10/AI10-1,"") -> 0.030497879
B13: Net New Revenue (yoy) | H13: ='Revenue and CapEx Build'!H13 -> 7.9236843 | I13: ='Revenue and CapEx Build'!I13 -> 29.8436 | J13: ='Revenue and CapEx Build'!J13 -> 75.178825 | K13: ='Revenue and CapEx Build'!K13 -> 115.99689 | L13: ='Revenue and CapEx Build'!L13 -> 213.113 | M13: ='Revenue and CapEx Build'!M13 -> 180.76032 | N13: ='Revenue and CapEx Build'!N13 -> 365.5274 | O13: ='Revenue and CapEx Build'!O13 -> 508.76217 | ... AK13: ='Revenue and CapEx Build'!AK13 -> 4444.1993
B14: Net New Revenue (qoq) | H14: ='Revenue and CapEx Build'!H14 -> 7.9236843 | I14: ='Revenue and CapEx Build'!I14 -> 21.919916 | J14: ='Revenue and CapEx Build'!J14 -> 45.335225 | K14: ='Revenue and CapEx Build'!K14 -> 40.818065 | L14: ='Revenue and CapEx Build'!L14 -> 0 | M14: ='Revenue and CapEx Build'!M14 -> 72.68711 | N14: ='Revenue and CapEx Build'!N14 -> 206.687 | O14: ='Revenue and CapEx Build'!O14 -> 188.57 | ... AK14: ='Revenue and CapEx Build'!AK14 -> 0
B16: Revenue / Average Net Assets | O16: ='Revenue and CapEx Build'!O16 -> 0.086095277 | P16: ='Revenue and CapEx Build'!P16 -> 0.097257296 | Q16: ='Revenue and CapEx Build'!Q16 -> 0 | R16: ='Revenue and CapEx Build'!R16 -> 0.10414591 | S16: ='Revenue and CapEx Build'!S16 -> 0.1070543 | T16: ='Revenue and CapEx Build'!T16 -> 0.10389865 | U16: ='Revenue and CapEx Build'!U16 -> 0.0976 | V16: ='Revenue and CapEx Build'!V16 -> 0.10317472 | ... AK16: ='Revenue and CapEx Build'!AK16 -> 0.108
B17: Revenue / Average Net Assets, Annualized | O17: ='Revenue and CapEx Build'!O17 -> 0.34438111 | P17: ='Revenue and CapEx Build'!P17 -> 0.38902918 | Q17: ='Revenue and CapEx Build'!Q17 -> 0 | R17: ='Revenue and CapEx Build'!R17 -> 0.41658366 | S17: ='Revenue and CapEx Build'!S17 -> 0.42821721 | T17: ='Revenue and CapEx Build'!T17 -> 0.4155946 | U17: ='Revenue and CapEx Build'!U17 -> 0.3904 | V17: ='Revenue and CapEx Build'!V17 -> 0 | ... AK17: ='Revenue and CapEx Build'!AK17 -> 0
B18: Revenue / Average Gross Assets | O18: ='Revenue and CapEx Build'!O18 -> 0.080338949 | P18: ='Revenue and CapEx Build'!P18 -> 0.088204788 | Q18: ='Revenue and CapEx Build'!Q18 -> 0 | R18: ='Revenue and CapEx Build'!R18 -> 0.092537485 | S18: ='Revenue and CapEx Build'!S18 -> 0.093253366 | T18: ='Revenue and CapEx Build'!T18 -> 0.088622363 | U18: ='Revenue and CapEx Build'!U18 -> 0.082175834 | V18: ='Revenue and CapEx Build'!V18 -> 0 | ... AK18: ='Revenue and CapEx Build'!AK18 -> 0
B20: Revenue from Customer Commitments
B21: Committed Contracts Revenue | G21: =G$10*G24 -> 3.166 | J21: =J$10*J24 -> 63.150213 | L21: =L$10*L24 -> 201.46984 | M21: =M$10*M24 -> 177.36296 | O21: =O$10*O24 -> 554.74395 | Q21: =Q$10*Q24 -> 1838.809 | R21: =R$10*R24 -> 961.99936
B22: % yoy | H22: =IFERROR(H21/C21-1,"") | I22: =IFERROR(I21/D21-1,"") | J22: =IFERROR(J21/E21-1,"") | L22: =IFERROR(L21/G21-1,"") -> 62.635452 | M22: =IFERROR(M21/H21-1,"") | N22: =IFERROR(N21/I21-1,"") | O22: =IFERROR(O21/J21-1,"") -> 7.7845143 | Q22: =IFERROR(Q21/L21-1,"") -> 8.1269689 | R22: =IFERROR(R21/M21-1,"") -> 4.4239023
B23: % qoq | H23: =IFERROR(H21/F21-1,"") | I23: =IFERROR(I21/H21-1,"") | J23: =IFERROR(J21/I21-1,"") | M23: =IFERROR(M21/K21-1,"") | O23: =IFERROR(O21/N21-1,"")
B24: % of Total Revenue | G24: 0.2 | J24: 0.84 | L24: 0.88 | M24: 0.94 | O24: 0.95 | Q24: 0.96 | R24: 0.98
B26: On-Demand Services Revenue | G26: =G$10*G29 -> 12.664 | J26: =J$10*J29 -> 12.028612 | L26: =L$10*L29 -> 27.47316 | M26: =M$10*M29 -> 11.32104 | O26: =O$10*O29 -> 29.19705 | Q26: =Q$10*Q29 -> 76.61704 | R26: =R$10*R29 -> 19.63264 | S26: =S$10*S29 -> 1212.788 | T26: =T$10*T29 -> 1364.676
B27: % yoy | H27: =IFERROR(H26/C26-1,"") | I27: =IFERROR(I26/D26-1,"") | J27: =IFERROR(J26/E26-1,"") | L27: =IFERROR(L26/G26-1,"") -> 1.1693904 | M27: =IFERROR(M26/H26-1,"") | N27: =IFERROR(N26/I26-1,"") | O27: =IFERROR(O26/J26-1,"") -> 1.4273 | Q27: =IFERROR(Q26/L26-1,"") -> 1.788796 | R27: =IFERROR(R26/M26-1,"") -> 0.73417283 | S27: =IFERROR(S26/N26-1,"") | T27: =IFERROR(T26/O26-1,"") -> 45.740201
B28: % qoq | H28: =IFERROR(H26/F26-1,"") | I28: =IFERROR(I26/H26-1,"") | J28: =IFERROR(J26/I26-1,"") | O28: =IFERROR(O26/N26-1,"") | R28: =IFERROR(R26/Q26-1,"") -> -0.74375622 | S28: =IFERROR(S26/R26-1,"") -> 60.774066 | T28: =IFERROR(T26/S26-1,"") -> 0.12523871
B29: % of Total Revenue | G29: =1-G24 -> 0.8 | J29: =1-J24 -> 0.16 | L29: =1-L24 -> 0.12 | M29: =1-M24 -> 0.06 | O29: =1-O24 -> 0.05 | Q29: =1-Q24 -> 0.04 | R29: =1-R24 -> 0.02 | S29: =1-S24 -> 1 | T29: =1-T24 -> 1
B31: Remaining Performance Obligations
A32: RPO | B32: RPO | K32: 9900 | L32: =K32 -> 9900 | M32: 15911.178 | N32: 16200 | O32: 15000 | P32: 15100 | Q32: =P32 -> 15100 | R32: 14665.098 | S32: 30100 | T32: 50000
A33: RPOYY | B33: % yoy | H33: =IFERROR(H32/C32-1,"") | I33: =IFERROR(I32/D32-1,"") | J33: =IFERROR(J32/E32-1,"") | M33: =IFERROR(M32/H32-1,"") | N33: =IFERROR(N32/I32-1,"") | O33: =IFERROR(O32/J32-1,"") | P33: =IFERROR(P32/K32-1,"") -> 0.52525253 | Q33: =Q32/L32-1 -> 0.52525253 | R33: =IFERROR(R32/M32-1,"") -> -0.078314755 | S33: =IFERROR(S32/N32-1,"") -> 0.85802469 | T33: =IFERROR(T32/O32-1,"") -> 2.3333333
A34: RPOQQ | B34: % qoq | H34: =IFERROR(H32/F32-1,"") | I34: =IFERROR(I32/H32-1,"") | J34: =IFERROR(J32/I32-1,"") | K34: =IFERROR(K32/J32-1,"") | M34: =IFERROR(M32/K32-1,"") -> 0.6071897 | O34: =IFERROR(O32/N32-1,"") -> -0.074074074 | P34: =P32/O32-1 -> 0.0066666667 | R34: =R32/Q32-1 -> -0.028801457 | S34: =S32/R32-1 -> 1.0524923 | T34: =T32/S32-1 -> 0.66112957
A36: 24MCRPO | B36: 24-Month cRPO | K36: =K32*K39 -> 4059 | L36: =K36 -> 4059 | N36: =N32*N39 -> 7290 | O36: =O32*O39 -> 7500 | P36: =P32*P39 -> 8154 | Q36: =P36 -> 8154 | R36: =R32*R39 -> 8505.7568 | S36: =S32*S39 -> 15050 | T36: =T32*T39 -> 20000
A37: 24MCRPOYY | B37: % yoy | H37: =IFERROR(H36/C36-1,"") | I37: =IFERROR(I36/D36-1,"") | J37: =IFERROR(J36/E36-1,"") | M37: =IFERROR(M36/H36-1,"") | N37: =IFERROR(N36/I36-1,"") | O37: =IFERROR(O36/J36-1,"") | Q37: =Q36/L36-1 -> 1.0088692
A38: 24MCRPOQQ | B38: % qoq | H38: =IFERROR(H36/F36-1,"") | I38: =IFERROR(I36/H36-1,"") | J38: =IFERROR(J36/I36-1,"") | N38: =IFERROR(N36/M36-1,"") | O38: =IFERROR(O36/N36-1,"") -> 0.028806584 | P38: =P36/O36-1 -> 0.0872 | R38: =R36/Q36-1 -> 0.043139176 | S38: =S36/R36-1 -> 0.76938987 | T38: =T36/S36-1 -> 0.32890365
B39: % of Total RPO | K39: 0.41 | L39: =K39 -> 0.41 | N39: 0.45 | O39: 0.5 | P39: 0.54 | Q39: =P39 -> 0.54 | R39: 0.58 | S39: 0.5 | T39: 0.4
B41: Next 24-Month Revenue (GSe) | K41: =SUM(M10:P10,R10:U10) -> 7017.4018 | L41: =Q10+V10 -> 7017.4018 | M41: =SUM(N10:P10,R10:U10,W10) -> 9055.845 | N41: =SUM(O10:P10,R10:U10,W10:X10) -> 11624.666 | O41: =SUM(P10,R10:U10,W10:Y10) -> 14330.409 | P41: =SUM(R10:U10,W10:Z10) -> 17103.615 | Q41: =V10+AA10 -> 17103.615 | R41: =SUM(S10:U10,W10:Z10,AB10) -> 19933.597 | S41: =SUM(T10:U10,W10:Z10,AB10:AC10) -> 22874.777 | T41: =SUM(U10:V10,X10:AA10,AC10:AD10) -> 37048.808
B42: Assumed non-Contracted Revenue to be Added | K42: =K41-K36 -> 2958.4018 | L42: =K42 -> 2958.4018 | N42: =N41-N36 -> 4334.6664 | O42: =O41-O36 -> 6830.4095 | P42: =P41-P36 -> 8949.6153 | Q42: =P42 -> 8949.6153 | R42: =R41-R36 -> 11427.84 | S42: =S41-S36 -> 7824.7767 | T42: =T41-T36 -> 17048.808
B43: % N24M Covered by cRPO | K43: =(K41-K42)/K41 -> 0.57841921 | L43: =K43 -> 0.57841921 | N43: =(N41-N42)/N41 -> 0.62711477 | O43: =(O41-O42)/O41 -> 0.52336257 | P43: =(P41-P42)/P41 -> 0.47674131 | Q43: =P43 -> 0.47674131 | R43: =(R41-R42)/R41 -> 0.42670457 | S43: =(S41-S42)/S41 -> 0.65792992 | T43: =(T41-T42)/T41 -> 0.53982843
A45: 24MCRPO | B45: 25 to 48-Month cRPO | K45: =K$32*K48 -> 3960 | L45: =K45 -> 3960 | N45: =N$32*N48 -> 6480 | P45: =P$32*P48 -> 6342 | Q45: =P45 -> 6342 | R45: =R$32*R48 -> 5866.0392 | S45: =S$32*S48 -> 12040 | T45: =T$32*T48 -> 19500
A46: 24MCRPOYY | B46: % yoy | H46: =IFERROR(H45/C45-1,"") | I46: =IFERROR(I45/D45-1,"") | J46: =IFERROR(J45/E45-1,"") | P46: =P45/K45-1 -> 0.60151515 | Q46: =Q45/L45-1 -> 0.60151515
A47: 24MCRPOQQ | B47: % qoq | H47: =IFERROR(H45/F45-1,"") | I47: =IFERROR(I45/H45-1,"") | J47: =IFERROR(J45/I45-1,"") | R47: =R45/Q45-1 -> -0.075049007 | S47: =S45/R45-1 -> 1.0524923 | T47: =T45/S45-1 -> 0.61960133
B48: % of Total RPO | K48: 0.4 | L48: =K48 -> 0.4 | N48: 0.4 | P48: 0.42 | Q48: =P48 -> 0.42 | R48: 0.4 | S48: 0.4 | T48: 0.39
A50: RPO | B50: Backlog (non-GAAP metric) | M50: 15911.178 | N50: 16200 | R50: 25856.694 | S50: 30100 | T50: 55600
A51: RPOYY | B51: % yoy | H51: =IFERROR(H50/C50-1,"") | I51: =IFERROR(I50/D50-1,"") | J51: =IFERROR(J50/E50-1,"") | K51: =IFERROR(K50/F50-1,"") | R51: =R50/M50-1 -> 0.62506472 | S51: =S50/N50-1 -> 0.85802469
A52: RPOQQ | B52: % qoq | H52: =IFERROR(H50/F50-1,"") | I52: =IFERROR(I50/H50-1,"") | J52: =IFERROR(J50/I50-1,"") | K52: =IFERROR(K50/J50-1,"") | S52: =IFERROR(S50/R50-1,"") -> 0.16410861 | T52: =IFERROR(T50/S50-1,"") -> 0.84717608
B53: Backlog not Included in RPO | M53: =M50-M32 -> 0 | R53: =R50-R32 -> 11191.596 | S53: =S50-S32 -> 0 | T53: =T50-T32 -> 5600
B55: Capacity (GPUs / Power / Data Centers)
A56: NOGPU | B56: Number of GPUs (thousands) | F56: 17 | G56: =F56 -> 17 | K56: 53 | L56: =K56 -> 53 | P56: 250 | Q56: =P56 -> 250
A57: RPOYY | B57: % yoy | K57: =IFERROR(K56/F56-1,"") -> 2.1176471 | L57: =IFERROR(L56/G56-1,"") -> 2.1176471 | M57: =IFERROR(M56/H56-1,"") | N57: =IFERROR(N56/I56-1,"") | O57: =IFERROR(O56/J56-1,"") | P57: =IFERROR(P56/K56-1,"") -> 3.7169811 | Q57: =IFERROR(Q56/L56-1,"") -> 3.7169811
A58: RPOQQ | B58: % qoq | K58: =IFERROR(K56/J56-1,"") | N58: =IFERROR(N56/M56-1,"") | O58: =IFERROR(O56/N56-1,"")
B59: Net New GPUs (yoy) | K59: =K56-F56 -> 36 | L59: =L56-G56 -> 36 | P59: =P56-K56 -> 197 | Q59: =Q56-L56 -> 197
B60: Net New GPUs (qoq)
B61: Revenue per GPU | G61: =IFERROR(G$10/G56,"") -> 0.93117647 | K61: =IFERROR(K$10/K56,"") -> 2.1886206 | L61: =IFERROR(L$10/L56,"") -> 4.3196792 | P61: =IFERROR(P$10/P56,"") -> 2.98972 | Q61: =IFERROR(Q$10/Q56,"") -> 7.661704
A63: RPO | B63: Active Power (MW) | F63: 10 | G63: =F63 -> 10 | K63: 70 | L63: =K63 -> 70 | P63: 360 | Q63: =P63 -> 360 | R63: 420 | S63: 470 | T63: 590
A64: RPOYY | B64: % yoy | K64: =IFERROR(K63/F63-1,"") -> 6 | L64: =IFERROR(L63/G63-1,"") -> 6 | P64: =IFERROR(P63/K63-1,"") -> 4.1428571 | Q64: =IFERROR(Q63/L63-1,"") -> 4.1428571
A65: RPOQQ | B65: % qoq | K65: =IFERROR(K63/J63-1,"") | R65: =R63/P63-1 -> 0.16666667 | S65: =S63/Q63-1 -> 0.30555556 | T65: =T63/R63-1 -> 0.4047619
B66: Net New MW (yoy) | K66: =K63-F63 -> 60 | L66: =L63-G63 -> 60 | P66: =P63-K63 -> 290 | Q66: =Q63-L63 -> 290
B67: Net New MW (qoq) | R67: =R63-Q63 -> 60 | S67: =S63-R63 -> 50 | T67: =T63-S63 -> 120
B68: Revenue per MW | G68: =IFERROR(G$10/G63,"") -> 1.583 | K68: =IFERROR(K$10/K63,"") -> 1.6570984 | L68: =IFERROR(L$10/L63,"") -> 3.2706143 | P68: =IFERROR(P$10/P63,"") -> 2.0761944 | Q68: =IFERROR(Q$10/Q63,"") -> 5.3206278 | R68: =IFERROR(R$10/R63,"") -> 2.337219 | S68: =IFERROR(S$10/S63,"") -> 2.5804 | T68: =IFERROR(T$10/T63,"") -> 2.3130102
A70: RPO | B70: Contracted Power | P70: 1300 | Q70: =P70 -> 1300 | R70: 1600 | S70: 2200 | T70: 2900
A71: RPOYY | B71: % yoy | K71: =IFERROR(K70/F70-1,"") | L71: =IFERROR(L70/G70-1,"") | M71: =IFERROR(M70/H70-1,"") | N71: =IFERROR(N70/I70-1,"") | O71: =IFERROR(O70/J70-1,"") | P71: =IFERROR(P70/K70-1,"") | Q71: =IFERROR(Q70/L70-1,"")
A72: RPOQQ | B72: % qoq | R72: =R70/P70-1 -> 0.23076923 | S72: =S70/Q70-1 -> 0.69230769 | T72: =T70/R70-1 -> 0.8125
B73: Net New MW (yoy)
B74: Net New MW (qoq) | R74: =R70-Q70 -> 300 | S74: =S70-R70 -> 600 | T74: =T70-S70 -> 700
A76: RPO | B76: Number of Data Centers | F76: 3 | G76: =F76 -> 3 | K76: 10 | L76: =K76 -> 10 | P76: 32 | Q76: =P76 -> 32 | R76: 33 | S76: 33 | T76: 41
A77: RPOYY | B77: % yoy | K77: =IFERROR(K76/F76-1,"") -> 2.3333333 | L77: =IFERROR(L76/G76-1,"") -> 2.3333333 | M77: =IFERROR(M76/H76-1,"") | N77: =IFERROR(N76/I76-1,"") | O77: =IFERROR(O76/J76-1,"") | P77: =IFERROR(P76/K76-1,"") -> 2.2 | Q77: =IFERROR(Q76/L76-1,"") -> 2.2
A78: RPOQQ | B78: % qoq | K78: =IFERROR(K76/J76-1,"") | N78: =IFERROR(N76/M76-1,"") | O78: =IFERROR(O76/N76-1,"") | R78: =R76/P76-1 -> 0.03125 | S78: =S76/R76-1 -> 0 | T78: =T76/S76-1 -> 0.24242424
B79: Net New Data Centers (yoy) | K79: =K76-F76 -> 7 | L79: =L76-G76 -> 7 | P79: =P76-K76 -> 22 | Q79: =Q76-L76 -> 22 | R79: =R76-Q76 -> 1 | S79: =S76-R76 -> 0 | T79: =T76-S76 -> 8
B80: Net New Data Centers (qoq)
B81: Revenue per Data Center | G81: =IFERROR(G$10/G76,"") -> 5.2766667 | K81: =IFERROR(K$10/K76,"") -> 11.599689 | L81: =IFERROR(L$10/L76,"") -> 22.8943 | M81: =IFERROR(M$10/M76,"") | N81: =IFERROR(N$10/N76,"") | O81: =IFERROR(O$10/O76,"") | P81: =IFERROR(P$10/P76,"") -> 23.357187 | Q81: =IFERROR(Q$10/Q76,"") -> 59.857062 | R81: =IFERROR(R$10/R76,"") -> 29.746424 | ... T81: =IFERROR(T$10/T76,"") -> 33.28478
A83: NOGPU | B83: Number of GPUs (thousands) | F83: 17 | G83: =F83 -> 17 | K83: 53 | L83: =K83 -> 53 | P83: 250 | Q83: =P83 -> 250
A84: RPOYY | B84: % yoy | K84: =IFERROR(K83/F83-1,"") -> 2.1176471 | L84: =IFERROR(L83/G83-1,"") -> 2.1176471 | M84: =IFERROR(M83/H83-1,"") | N84: =IFERROR(N83/I83-1,"") | O84: =IFERROR(O83/J83-1,"") | P84: =IFERROR(P83/K83-1,"") -> 3.7169811 | Q84: =IFERROR(Q83/L83-1,"") -> 3.7169811
A85: RPOQQ | B85: % qoq | K85: =IFERROR(K83/J83-1,"") | N85: =IFERROR(N83/M83-1,"") | O85: =IFERROR(O83/N83-1,"")
B86: Net New GPUs (yoy) | K86: =K83-F83 -> 36 | L86: =L83-G83 -> 36 | P86: =P83-K83 -> 197 | Q86: =Q83-L83 -> 197
B87: Net New GPUs (qoq)
B88: Revenue per GPU | G88: =IFERROR(G$10/G83,"") -> 0.93117647 | K88: =IFERROR(K$10/K83,"") -> 2.1886206 | L88: =IFERROR(L$10/L83,"") -> 4.3196792 | P88: =IFERROR(P$10/P83,"") -> 2.98972 | Q88: =IFERROR(Q$10/Q83,"") -> 7.661704
B90: Employees
B91: Total | Q91: =Q95+Q100 -> 881
B92: % yoy
B93: % qoq
B95: United States | Q95: 791
B96: % yoy
B97: % qoq
B98: % of Total Employees
B100: International | Q100: 90
B101: % yoy
B102: % qoq
B103: % of Total Employees
B105: Revenue by Geography
B106: United States | G106: 10.376 | L106: 200.469 | M106: 176.694 | N106: 370.107 | O106: 547.15 | Q106: 1797.268 | R106: 929.424 | S106: 1147.655 | T106: 1281.336
B107: % yoy | L107: =IFERROR(L106/G106-1,"") -> 18.320451 | Q107: =IFERROR(Q106/L106-1,"") -> 7.9653163 | R107: =R106/M106-1 -> 4.2600767 | S107: =S106/N106-1 -> 2.1008735 | T107: =T106/O106-1 -> 1.3418368
B108: % qoq | N108: =N106/M106-1 -> 1.0946212 | O108: =O106/N106-1 -> 0.47835626 | S108: =S106/R106-1 -> 0.23480242 | T108: =T106/S106-1 -> 0.11648187
B109: % of Total Revenue | G109: =IFERROR(G106/G$10,"") -> 0.65546431 | L109: =IFERROR(L106/L$10,"") -> 0.87562843 | M109: =IFERROR(M106/M$10,"") -> 0.9364546 | N109: =IFERROR(N106/N$10,"") -> 0.93610052 | O109: =IFERROR(O106/O$10,"") -> 0.93699535 | Q109: =IFERROR(Q106/Q$10,"") -> 0.93831242 | R109: =IFERROR(R106/R$10,"") -> 0.9468151 | S109: =IFERROR(S106/S$10,"") -> 0.94629482 | T109: =IFERROR(T106/T$10,"") -> 0.93893056
B111: International | G111: 5.463 | L111: 28.474 | M111: 11.72 | N111: 25.264 | O111: 36.791 | Q111: 118.158 | R111: 52.208 | S111: 65.133 | T111: 83.34
B112: % yoy | L112: =IFERROR(L111/G111-1,"") -> 4.2121545 | Q112: =IFERROR(Q111/L111-1,"") -> 3.1496804 | R112: =R111/M111-1 -> 3.4546075 | S112: =S111/N111-1 -> 1.5780953 | T112: =T111/O111-1 -> 1.2652279
B113: % qoq | N113: =N111/M111-1 -> 1.1556314 | O113: =O111/N111-1 -> 0.45626187 | S113: =S111/R111-1 -> 0.24756742 | T113: =T111/S111-1 -> 0.27953572
B114: % of Total Revenue | G114: =IFERROR(G111/G$10,"") -> 0.34510423 | L114: =IFERROR(L111/L$10,"") -> 0.12437157 | M114: =IFERROR(M111/M$10,"") -> 0.062114435 | N114: =IFERROR(N111/N$10,"") -> 0.063899477 | O114: =IFERROR(O111/O$10,"") -> 0.063004653 | Q114: =IFERROR(Q111/Q$10,"") -> 0.061687583 | R114: =IFERROR(R111/R$10,"") -> 0.0531849 | S114: =IFERROR(S111/S$10,"") -> 0.053705182 | T114: =IFERROR(T111/T$10,"") -> 0.061069441
B116: Customer Concentration
B117: Customer A (GSe Microsoft) | G117: =IFERROR(G$10*G120,"") | L117: =IFERROR(L$10*L120,"") -> 80.13005 | M117: =IFERROR(M$10*M120,"") -> 62.26572 | N117: =IFERROR(N$10*N120,"") -> 233.26889 | O117: =IFERROR(O$10*O120,"") -> 379.56165 | Q117: =IFERROR(Q$10*Q120,"") -> 1187.5641 | R117: =IFERROR(R$10*R120,"") -> 706.77504 | S117: =IFERROR(S$10*S120,"") -> 861.07948 | T117: =IFERROR(T$10*T120,"") -> 914.33292
B118: % yoy | G118: =IFERROR(G117/B117-1,"") | L118: =IFERROR(L117/G117-1,"") | M118: =IFERROR(M117/H117-1,"") | Q118: =IFERROR(Q117/L117-1,"") -> 13.820459 | R118: =IFERROR(R117/M117-1,"") -> 10.350949 | S118: =IFERROR(S117/N117-1,"") -> 2.6913601 | T118: =IFERROR(T117/O117-1,"") -> 1.4089181
B119: % qoq
B120: % of Total Revenue | G120: <10% | L120: 0.35 | M120: 0.33 | N120: 0.59 | O120: 0.65 | Q120: 0.62 | R120: 0.72 | S120: 0.71 | T120: 0.67
B122: Efficiency Analysis
B123: GAAP CAC | M123: =M125/M127 -> 0.02077947 | N123: =N125/N127 -> 0.011479906 | O123: =O125/O127 -> 0.0085216318 | P123: =P125/P127 -> 0.0072806603 | Q123: =Q125/Q127 -> 0.0072806603 | R123: =R125/R127 -> 0.0078466684 | S123: =S125/S127 -> 0.017590471 | T123: =T125/T127 -> 0.031254523 | ... AK123: =AK125/AK127 -> 0.10635404
...

Sheet Depreciation Build
B2: CoreWeave, Inc.
B3: Fiscal Year Ends Dec. 31
B4: ($ millions, except per share amounts)
C6: =Dates!C3 -> 2022 (A) | H6: =Dates!H3 -> 2023 (A) | M6: =Dates!M3 -> 2024 (A) | R6: =Dates!R3 -> 2025 (E) | W6: =Dates!W3 -> 2026 (E) | AB6: =Dates!AB3 -> 2027 (E) | AG6: =Dates!AG3 -> 2028 (E)
C7: =Dates!C4 -> 1Q22 (A) | D7: =Dates!D4 -> 2Q22 (A) | E7: =Dates!E4 -> 3Q22 (A) | F7: =Dates!F4 -> 4Q22 (A) | G7: =Dates!G4 -> FY22 (A) | H7: =Dates!H4 -> 1Q23 (A) | I7: =Dates!I4 -> 2Q23 (A) | J7: =Dates!J4 -> 3Q23 (A) | ... AK7: =Dates!AK4 -> FY28 (E)
C8: =Dates!C5 -> 44651 | D8: =Dates!D5 -> 44742 | E8: =Dates!E5 -> 44834 | F8: =Dates!F5 -> 44926 | G8: =Dates!G5 -> 44926 | H8: =Dates!H5 -> 45016 | I8: =Dates!I5 -> 45107 | J8: =Dates!J5 -> 45199 | ... AK8: =Dates!AK5 -> 47118
B9: Metrics
A10: TREV | B10: Total Revenue | G10: ='Revenue and CapEx Build'!G10 -> 15.83 | H10: ='Revenue and CapEx Build'!H10 -> 7.9236843 | I10: ='Revenue and CapEx Build'!I10 -> 29.8436 | J10: ='Revenue and CapEx Build'!J10 -> 75.178825 | K10: ='Revenue and CapEx Build'!K10 -> 115.99689 | L10: ='Revenue and CapEx Build'!L10 -> 228.943 | M10: ='Revenue and CapEx Build'!M10 -> 188.684 | N10: ='Revenue and CapEx Build'!N10 -> 395.371 | ... AK10: ='Revenue and CapEx Build'!AK10 -> 21655.089
A11: TREVYY | B11: % yoy | H11: =IFERROR(H10/C10-1,"") | I11: =IFERROR(I10/D10-1,"") | J11: =IFERROR(J10/E10-1,"") | K11: =IFERROR(K10/F10-1,"") | L11: =IFERROR(L10/G10-1,"") -> 13.462603 | M11: =IFERROR(M10/H10-1,"") -> 22.81266 | N11: =IFERROR(N10/I10-1,"") -> 12.2481 | O11: =IFERROR(O10/J10-1,"") -> 6.76736 | ... AK11: =IFERROR(AK10/AF10-1,"") -> 0.25822019
A12: TREVQQ | B12: % qoq | H12: =IFERROR(H10/F10-1,"") | I12: =IFERROR(I10/H10-1,"") -> 2.7663793 | J12: =IFERROR(J10/I10-1,"") -> 1.5190937 | K12: =IFERROR(K10/J10-1,"") -> 0.5429463 | M12: =IFERROR(M10/K10-1,"") -> 0.62662981 | N12: =IFERROR(N10/M10-1,"") -> 1.0954135 | O12: =IFERROR(O10/N10-1,"") -> 0.47694444 | P12: =IFERROR(P10/O10-1,"") -> 0.2799752 | R12: =IFERROR(R10/P10-1,"") -> 0.31334306 | S12: =IFERROR(S10/R10-1,"") -> 0.23548132 | T12: =IFERROR(T10/S10-1,"") -> 0.12523871 | U12: =IFERROR(U10/T10-1,"") -> 0.13058326 | W12: =IFERROR(W10/U10-1,"") -> 0.44348713 | X12: =IFERROR(X10/W10-1,"") -> 0.33094883 | Y12: =IFERROR(Y10/X10-1,"") -> 0.10980793 | Z12: =IFERROR(Z10/Y10-1,"") -> 0.070204816 | AB12: =IFERROR(AB10/Z10-1,"") -> 0.082649169 | AC12: =IFERROR(AC10/AB10-1,"") -> 0.089818799 | AD12: =IFERROR(AD10/AC10-1,"") -> 0.077002222 | AE12: =IFERROR(AE10/AD10-1,"") -> 0.066529754 | AG12: =IFERROR(AG10/AE10-1,"") -> 0.072718069 | AH12: =IFERROR(AH10/AG10-1,"") -> 0.041288386 | AI12: =IFERROR(AI10/AH10-1,"") -> 0.035552396 | AJ12: =IFERROR(AJ10/AI10-1,"") -> 0.030497879
B14: Total CapEx (Including CIP) | F14: ='Revenue and CapEx Build'!F46 -> 0 | G14: ='Revenue and CapEx Build'!G46 -> 72.404 | H14: ='Revenue and CapEx Build'!H46 -> 0 | I14: ='Revenue and CapEx Build'!I46 -> 0 | J14: ='Revenue and CapEx Build'!J46 -> 0 | K14: ='Revenue and CapEx Build'!K46 -> 0 | L14: ='Revenue and CapEx Build'!L46 -> 2943.13 | M14: ='Revenue and CapEx Build'!M46 -> 1741.935 | ... AK14: ='Revenue and CapEx Build'!AK46 -> 24782.413
B15: % yoy | M15: =IFERROR(M14/H14-1,"") | N15: =IFERROR(N14/I14-1,"") | O15: =IFERROR(O14/J14-1,"") | P15: =IFERROR(P14/K14-1,"") | Q15: =IFERROR(Q14/L14-1,"") -> 1.9567427 | R15: =IFERROR(R14/M14-1,"") -> -0.19207146 | S15: =IFERROR(S14/N14-1,"") | T15: =IFERROR(T14/O14-1,"") | ... AK15: =IFERROR(AK14/AF14-1,"") -> 0.087437445
B16: % qoq | R16: =IFERROR(R14/P14-1,"") -> -0.55338922 | S16: =IFERROR(S14/R14-1,"") -> 0.74297532 | T16: =IFERROR(T14/S14-1,"") -> 0.33664765 | U16: =IFERROR(U14/T14-1,"") -> 1.5492185 | W16: =IFERROR(W14/U14-1,"") -> 0.055184723 | X16: =IFERROR(X14/W14-1,"") -> -0.42459977 | Y16: =IFERROR(Y14/X14-1,"") -> -0.29290811 | Z16: =IFERROR(Z14/Y14-1,"") -> -0.040567129 | AB16: =IFERROR(AB14/Z14-1,"") -> 0.2420061 | AC16: =IFERROR(AC14/AB14-1,"") -> 0.60436387 | AD16: =IFERROR(AD14/AC14-1,"") -> -0.16966692 | AE16: =IFERROR(AE14/AD14-1,"") -> 0.045841937 | AG16: =IFERROR(AG14/AE14-1,"") -> -0.072175757 | AH16: =IFERROR(AH14/AG14-1,"") -> 0.14288384 | AI16: =IFERROR(AI14/AH14-1,"") -> 0.027235094 | AJ16: =IFERROR(AJ14/AI14-1,"") -> -0.0062492386
B18: CapEx (Fixed Assets) | M18: 1200 | N18: 1900 | O18: =Q18-P18-N18-M18 -> 2679.4319 | P18: ='Revenue and CapEx Build'!P52 -> 2340.018 | Q18: ='Revenue and CapEx Build'!Q52 -> 8119.4499 | R18: ='Revenue and CapEx Build'!R52 -> 483.104 | S18: ='Revenue and CapEx Build'!S52 -> 2359.475 | T18: ='Revenue and CapEx Build'!T52 -> 382.361 | U18: ='Revenue and CapEx Build'!U52 -> 4758.361 | V18: ='Revenue and CapEx Build'!V52 -> 7983.301 | W18: ='Revenue and CapEx Build'!W52 -> 10758.361 | ... AK18: ='Revenue and CapEx Build'!AK52 -> 18033.444
B19: % yoy | M19: =IFERROR(M18/H18-1,"") | N19: =IFERROR(N18/I18-1,"") | O19: =IFERROR(O18/J18-1,"") | P19: =IFERROR(P18/K18-1,"") | Q19: =IFERROR(Q18/L18-1,"") | R19: =IFERROR(R18/M18-1,"") -> -0.59741333 | S19: =IFERROR(S18/N18-1,"") -> 0.24182895 | T19: =IFERROR(T18/O18-1,"") -> -0.85729774 | ... AK19: =IFERROR(AK18/AF18-1,"") -> -0.099833059
B20: % qoq | R20: =IFERROR(R18/P18-1,"") -> -0.79354689 | S20: =IFERROR(S18/R18-1,"") -> 3.8839898 | T20: =IFERROR(T18/S18-1,"") -> -0.83794658 | U20: =IFERROR(U18/T18-1,"") -> 11.444682 | W20: =IFERROR(W18/U18-1,"") -> 1.2609384 | X20: =IFERROR(X18/W18-1,"") -> -0.55770577 | Y20: =IFERROR(Y18/X18-1,"") -> -0.36777369 | Z20: =IFERROR(Z18/Y18-1,"") -> 0 | AB20: =IFERROR(AB18/Z18-1,"") -> 0.66481383 | AC20: =IFERROR(AC18/AB18-1,"") -> 0 | AD20: =IFERROR(AD18/AC18-1,"") -> 0 | AE20: =IFERROR(AE18/AD18-1,"") -> 0 | AG20: =IFERROR(AG18/AE18-1,"") -> -0.099833059 | AH20: =IFERROR(AH18/AG18-1,"") -> 0 | AI20: =IFERROR(AI18/AH18-1,"") -> 0 | AJ20: =IFERROR(AJ18/AI18-1,"") -> 0
B22: Depreciation and Amortization
B23: Total Depreciation and Amortization (from C/F) | G23: =CF!G14 -> 11.695 | H23: =CF!H14 -> 0 | I23: =CF!I14 -> 0 | J23: =CF!J14 -> 0 | K23: =CF!K14 -> 0 | L23: =CF!L14 -> 103.21 | M23: =CF!M14 -> 79.51 | N23: =CF!N14 -> 164.46 | ... T23: =CF!T14 -> 630.479 | U23: =U28+U39 -> 785.14888 | V23: =V28+V39 -> 2123.8544 | W23: =W28+W39 -> 1175.5895 | X23: =X28+X39 -> 1380.678 | Y23: =Y28+Y39 -> 1513.2448 | Z23: =Z28+Z39 -> 1646.1934 | AA23: =AA28+AA39 -> 5715.7057 | AB23: =AB28+AB39 -> 1863.3324 | ... AK23: =AK28+AK39 -> 12018.204
B24: % yoy | M24: =IFERROR(M23/H23-1,"") | N24: =IFERROR(N23/I23-1,"") | O24: =IFERROR(O23/J23-1,"") | P24: =IFERROR(P23/K23-1,"") | Q24: =IFERROR(Q23/L23-1,"") -> 7.3655944 | R24: =IFERROR(R23/M23-1,"") -> 4.577877 | S24: =IFERROR(S23/N23-1,"") -> 2.4019275 | T24: =IFERROR(T23/O23-1,"") -> 1.4819663 | ... AK24: =IFERROR(AK23/AF23-1,"") -> 0.37155393
B25: % qoq | M25: =IFERROR(M23/K23-1,"") | N25: =IFERROR(N23/M23-1,"") -> 1.0684191 | O25: =IFERROR(O23/N23-1,"") -> 0.54459443 | P25: =IFERROR(P23/O23-1,"") -> 0.43852156 | R25: =IFERROR(R23/P23-1,"") -> 0.21366705 | S25: =IFERROR(S23/R23-1,"") -> 0.2615215 | T25: =IFERROR(T23/S23-1,"") -> 0.12689975 | U25: =IFERROR(U23/T23-1,"") -> 0.24532122 | W25: =IFERROR(W23/U23-1,"") -> 0.49728224 | X25: =IFERROR(X23/W23-1,"") -> 0.17445595 | Y25: =IFERROR(Y23/X23-1,"") -> 0.096015677 | Z25: =IFERROR(Z23/Y23-1,"") -> 0.087856643 | AB25: =IFERROR(AB23/Z23-1,"") -> 0.13190369 | AC25: =IFERROR(AC23/AB23-1,"") -> 0.11708688 | AD25: =IFERROR(AD23/AC23-1,"") -> 0.10462308 | AE25: =IFERROR(AE23/AD23-1,"") -> 0.095282643 | AG25: =IFERROR(AG23/AE23-1,"") -> 0.074157272 | AH25: =IFERROR(AH23/AG23-1,"") -> 0.073911359 | AI25: =IFERROR(AI23/AH23-1,"") -> 0.068428497 | AJ25: =IFERROR(AJ23/AI23-1,"") -> 0.064551646
B26: % of Revenue | G26: =IFERROR(G23/G$10,"") -> 0.73878711 | H26: =IFERROR(H23/H$10,"") -> 0 | I26: =IFERROR(I23/I$10,"") -> 0 | J26: =IFERROR(J23/J$10,"") -> 0 | K26: =IFERROR(K23/K$10,"") -> 0 | L26: =IFERROR(L23/L$10,"") -> 0.4508109 | M26: =IFERROR(M23/M$10,"") -> 0.42139238 | N26: =IFERROR(N23/N$10,"") -> 0.41596374 | ... AK26: =IFERROR(AK23/AK$10,"") -> 0.55498289
B28: Fixed Asset Depreciation | M28: ='Revenue and CapEx Build'!M106 -> 79 | N28: ='Revenue and CapEx Build'!N106 -> 164 | O28: ='Revenue and CapEx Build'!O106 -> 253 | P28: ='Revenue and CapEx Build'!P106 -> 357.527 | Q28: ='Revenue and CapEx Build'!Q106 -> 853.527 | R28: ='Revenue and CapEx Build'!R106 -> 443 | S28: ='Revenue and CapEx Build'!S106 -> 553 | T28: ='Revenue and CapEx Build'!T106 -> 621 | U28: 760 | V28: =V58 -> 2059.8218 | W28: =W58 -> 1144.463 | X28: =X58 -> 1342.728 | Y28: =Y58 -> 1468.0764 | Z28: =Z58 -> 1593.4248 | AA28: =AA58 -> 5548.6922 | AB28: =AB58 -> 1802.1065 | AC28: =AC58 -> 2010.7882 | ... AK28: =AK58 -> 11580.09
B29: % yoy | M29: =IFERROR(M28/H28-1,"") | N29: =IFERROR(N28/I28-1,"") | O29: =IFERROR(O28/J28-1,"") | P29: =IFERROR(P28/K28-1,"") | Q29: =IFERROR(Q28/L28-1,"") | R29: =IFERROR(R28/M28-1,"") -> 4.6075949 | S29: =IFERROR(S28/N28-1,"") -> 2.3719512 | T29: =IFERROR(T28/O28-1,"") -> 1.4545455 | ... AK29: =IFERROR(AK28/AF28-1,"") -> 0.36872147
B30: % qoq | M30: =IFERROR(M28/K28-1,"") | N30: =IFERROR(N28/M28-1,"") -> 1.0759494 | O30: =IFERROR(O28/N28-1,"") -> 0.54268293 | P30: =IFERROR(P28/O28-1,"") -> 0.4131502 | R30: =IFERROR(R28/P28-1,"") -> 0.23906726 | S30: =IFERROR(S28/R28-1,"") -> 0.248307 | T30: =IFERROR(T28/S28-1,"") -> 0.12296564 | U30: =IFERROR(U28/T28-1,"") -> 0.22383253 | W30: =IFERROR(W28/U28-1,"") -> 0.50587236 | X30: =IFERROR(X28/W28-1,"") -> 0.17323849 | Y30: =IFERROR(Y28/X28-1,"") -> 0.09335351 | Z30: =IFERROR(Z28/Y28-1,"") -> 0.085382732 | AB30: =IFERROR(AB28/Z28-1,"") -> 0.13096427 | AC30: =IFERROR(AC28/AB28-1,"") -> 0.11579877 | AD30: =IFERROR(AD28/AC28-1,"") -> 0.10378105 | AE30: =IFERROR(AE28/AD28-1,"") -> 0.09402322 | AG30: =IFERROR(AG28/AE28-1,"") -> 0.076230155 | AH30: =IFERROR(AH28/AG28-1,"") -> 0.071883048 | AI30: =IFERROR(AI28/AH28-1,"") -> 0.067062398 | AJ30: =IFERROR(AJ28/AI28-1,"") -> 0.062847682
B31: % of Revenue | G31: =IFERROR(G28/G$10,"") -> 0 | H31: =IFERROR(H28/H$10,"") -> 0 | I31: =IFERROR(I28/I$10,"") -> 0 | J31: =IFERROR(J28/J$10,"") -> 0 | K31: =IFERROR(K28/K$10,"") -> 0 | L31: =IFERROR(L28/L$10,"") -> 0 | M31: =IFERROR(M28/M$10,"") -> 0.41868945 | N31: =IFERROR(N28/N$10,"") -> 0.41480028 | ... AK31: =IFERROR(AK28/AK$10,"") -> 0.53475144
B33: T&I Depreciation | G33: 11 | L33: 101 | M33: 77 | N33: 158 | O33: 256 | P33: =Q33-O33-N33-M33 -> 352 | Q33: 843 | R33: 429 | S33: 537 | T33: 349 | U33: =U28*U37 -> 427.11755 | V33: =SUM(R33:U33) -> 1742.1176 | W33: =W28*W37 -> 643.18452 | X33: =X28*X37 -> 754.60883 | Y33: =Y28*Y37 -> 825.05422 | Z33: =Z28*Z37 -> 895.4996 | AA33: =SUM(W33:Z33) -> 3118.3472 | AB33: =AB28*AB37 -> 1012.778 | AC33: =AC28*AC37 -> 1130.0565 | AD33: =AD28*AD37 -> 1247.3349 | AE33: =AE28*AE37 -> 1364.6134 | AF33: =SUM(AB33:AE33) -> 4754.7829 | AG33: =AG28*AG37 -> 1468.6381 | AH33: =AH28*AH37 -> 1574.2083 | AI33: =AI28*AI37 -> 1679.7784 | AJ33: =AJ28*AJ37 -> 1785.3486 | AK33: =SUM(AG33:AJ33) -> 6507.9734
B34: % yoy | M34: =IFERROR(M33/H33-1,"") | N34: =IFERROR(N33/I33-1,"") | O34: =IFERROR(O33/J33-1,"") | P34: =IFERROR(P33/K33-1,"") | Q34: =IFERROR(Q33/L33-1,"") -> 7.3465347 | R34: =IFERROR(R33/M33-1,"") -> 4.5714286 | S34: =IFERROR(S33/N33-1,"") -> 2.3987342 | T34: =IFERROR(T33/O33-1,"") -> 0.36328125 | ... AK34: =IFERROR(AK33/AF33-1,"") -> 0.36872147
B35: % qoq | M35: =IFERROR(M33/K33-1,"") | N35: =IFERROR(N33/M33-1,"") -> 1.0519481 | O35: =IFERROR(O33/N33-1,"") -> 0.62025316 | P35: =IFERROR(P33/O33-1,"") -> 0.375 | R35: =IFERROR(R33/P33-1,"") -> 0.21875 | S35: =IFERROR(S33/R33-1,"") -> 0.25174825 | T35: =IFERROR(T33/S33-1,"") -> -0.35009311 | U35: =IFERROR(U33/T33-1,"") -> 0.22383253 | W35: =IFERROR(W33/U33-1,"") -> 0.50587236 | X35: =IFERROR(X33/W33-1,"") -> 0.17323849 | Y35: =IFERROR(Y33/X33-1,"") -> 0.09335351 | Z35: =IFERROR(Z33/Y33-1,"") -> 0.085382732 | AB35: =IFERROR(AB33/Z33-1,"") -> 0.13096427 | AC35: =IFERROR(AC33/AB33-1,"") -> 0.11579877 | AD35: =IFERROR(AD33/AC33-1,"") -> 0.10378105 | AE35: =IFERROR(AE33/AD33-1,"") -> 0.09402322 | AG35: =IFERROR(AG33/AE33-1,"") -> 0.076230155 | AH35: =IFERROR(AH33/AG33-1,"") -> 0.071883048 | AI35: =IFERROR(AI33/AH33-1,"") -> 0.067062398 | AJ35: =IFERROR(AJ33/AI33-1,"") -> 0.062847682
B36: Implied Other Depreciation | G36: =G23-G33 -> 0.695 | L36: =L23-L33 -> 2.21 | M36: =M23-M33 -> 2.51 | Q36: =Q23-Q33 -> 20.413 | R36: =R23-R33 -> 14.497 | S36: =S23-S33 -> 22.481 | T36: =T23-T33 -> 281.479 | U36: =U23-U33 -> 358.03132 | V36: =V23-V33 -> 381.73681 | W36: =W23-W33 -> 532.40495 | X36: =X23-X33 -> 626.06921 | ... AK36: =AK23-AK33 -> 5510.2305
B37: % of Fixed Asset Depreciation | M37: =M33/M28 -> 0.97468354 | N37: =N33/N28 -> 0.96341463 | O37: =O33/O28 -> 1.0118577 | P37: =P33/P28 -> 0.98454103 | Q37: =Q33/Q28 -> 0.98766647 | R37: =R33/R28 -> 0.96839729 | S37: =S33/S28 -> 0.97106691 | T37: =T33/T28 -> 0.56199678 | U37: =T37 -> 0.56199678 | V37: =V33/V23 -> 0.82026225 | W37: =U37 -> 0.56199678 | X37: =W37 -> 0.56199678 | Y37: =X37 -> 0.56199678 | Z37: =Y37 -> 0.56199678 | AA37: =AA33/AA23 -> 0.54557518 | AB37: =Z37 -> 0.56199678 | AC37: =AB37 -> 0.56199678 | AD37: =AC37 -> 0.56199678 | AE37: =AD37 -> 0.56199678 | AF37: =AF33/AF23 -> 0.54263026 | AG37: =AE37 -> 0.56199678 | AH37: =AG37 -> 0.56199678 | AI37: =AH37 -> 0.56199678 | AJ37: =AI37 -> 0.56199678 | AK37: =AK33/AK23 -> 0.54150965
B39: Total Amortization | M39: =SUM(M40:M42) -> 1.82 | N39: =SUM(N40:N42) -> 3.839 | O39: =SUM(O40:O42) -> 6.672 | P39: =SUM(P40:P42) -> 8.412 | Q39: =SUM(Q40:Q42) -> 20.743 | R39: =SUM(R40:R42) -> 14.988778 | S39: =SUM(S40:S42) -> 14.492236 | T39: =SUM(T40:T42) -> 9.4026528 | ... AK39: =SUM(AK40:AK42) -> 438.11369
B40: Amortization - Capitalized Internally Developed Software | M40: ='Revenue and CapEx Build'!M111 -> 0.954 | N40: ='Revenue and CapEx Build'!N111 -> 1.364 | O40: ='Revenue and CapEx Build'!O111 -> 1.839 | P40: ='Revenue and CapEx Build'!P111 -> 2.415 | Q40: ='Revenue and CapEx Build'!Q111 -> 6.572 | R40: ='Revenue and CapEx Build'!R111 -> 3.6747778 | S40: ='Revenue and CapEx Build'!S111 -> 4.1191111 | T40: ='Revenue and CapEx Build'!T111 -> 3.4444444 | ... AK40: ='Revenue and CapEx Build'!AK111 -> 158.26141
B41: Amortization - Capitalized Labor | M41: ='Revenue and CapEx Build'!M112 -> 0.036 | N41: ='Revenue and CapEx Build'!N112 -> 0.075 | O41: ='Revenue and CapEx Build'!O112 -> 0.441 | P41: ='Revenue and CapEx Build'!P112 -> 0.662 | Q41: ='Revenue and CapEx Build'!Q112 -> 1.214 | R41: ='Revenue and CapEx Build'!R112 -> 2.0144167 | S41: ='Revenue and CapEx Build'!S112 -> 2.2358333 | T41: ='Revenue and CapEx Build'!T112 -> 1.873125 | ... AK41: ='Revenue and CapEx Build'!AK112 -> 104.97195
B42: Amortization - Capitalized Interest | M42: ='Revenue and CapEx Build'!M113 -> 0.83 | N42: ='Revenue and CapEx Build'!N113 -> 2.4 | O42: ='Revenue and CapEx Build'!O113 -> 4.392 | P42: ='Revenue and CapEx Build'!P113 -> 5.335 | Q42: ='Revenue and CapEx Build'!Q113 -> 12.957 | R42: ='Revenue and CapEx Build'!R113 -> 9.2995833 | S42: ='Revenue and CapEx Build'!S113 -> 8.1372917 | T42: ='Revenue and CapEx Build'!T113 -> 4.0850833 | ... AK42: ='Revenue and CapEx Build'!AK113 -> 174.88033
B44: Accumulated P&E Depreciation and Amortization | K44: =BS!K21 -> -116.796 | L44: =BS!L21 -> -116.796 | M44: =BS!M21 -> -195.782 | N44: =BS!N21 -> -359.722 | O44: =BS!O21 -> -612.217 | P44: =BS!P21 -> -965.231 | Q44: =BS!Q21 -> -965.231 | R44: =BS!R21 -> -1399.557 | ... AK44: =BS!AK21 -> -29856.109
B45: Accumulated Amortization | K45: ='Revenue and CapEx Build'!K116 -> -2.347 | L45: ='Revenue and CapEx Build'!L116 -> -2.347 | O45: ='Revenue and CapEx Build'!O116 -> -3.92 | P45: ='Revenue and CapEx Build'!P116 -> -4.441 | Q45: ='Revenue and CapEx Build'!Q116 -> -4.441 | R45: ='Revenue and CapEx Build'!R116 -> -4.955 | S45: ='Revenue and CapEx Build'!S116 -> -11.055 | T45: ='Revenue and CapEx Build'!T116 -> -20.564
B46: Accumulated Depreciation (Implied) | K46: =K44-K45 -> -114.449 | L46: =K46 -> -114.449 | O46: =O44-O45 -> -608.297 | P46: =P44-P45 -> -960.79 | Q46: =P46 -> -960.79 | R46: =R44-R45 -> -1394.602 | S46: =S44-S45 -> -1942.552 | T46: =T44-T45 -> -2554.014
B48: Property and Equipment, Net, Breakdown
B49: Technology Equipment | K49: ='Revenue and CapEx Build'!K120 -> 1298.127 | L49: ='Revenue and CapEx Build'!L120 -> 1298.127 | M49: 2500 | N49: 4000 | O49: ='Revenue and CapEx Build'!O120 -> 6886.183 | P49: ='Revenue and CapEx Build'!P120 -> 9146.575 | Q49: ='Revenue and CapEx Build'!Q120 -> 9146.575 | R49: ='Revenue and CapEx Build'!R120 -> 10746.445 | S49: ='Revenue and CapEx Build'!S120 -> 13170.295 | T49: ='Revenue and CapEx Build'!T120 -> 14628.79
B50: Software | K50: ='Revenue and CapEx Build'!K121 -> 14.937 | L50: ='Revenue and CapEx Build'!L121 -> 14.937 | O50: ='Revenue and CapEx Build'!O121 -> 69.209 | P50: ='Revenue and CapEx Build'!P121 -> 245.458 | Q50: ='Revenue and CapEx Build'!Q121 -> 245.458 | R50: ='Revenue and CapEx Build'!R121 -> 245.458 | S50: ='Revenue and CapEx Build'!S121 -> 459.742 | T50: ='Revenue and CapEx Build'!T121 -> 541.567
B51: Data Center Equipment and Leasehold Improvements | K51: ='Revenue and CapEx Build'!K122 -> 39.332 | L51: ='Revenue and CapEx Build'!L122 -> 39.332 | O51: ='Revenue and CapEx Build'!O122 -> 308.264 | P51: ='Revenue and CapEx Build'!P122 -> 139.508 | Q51: ='Revenue and CapEx Build'!Q122 -> 139.508 | R51: ='Revenue and CapEx Build'!R122 -> 534.12 | S51: ='Revenue and CapEx Build'!S122 -> 830.875 | T51: ='Revenue and CapEx Build'!T122 -> 1139.095
B52: Furniture, Fixtures, and Other Assets | K52: ='Revenue and CapEx Build'!K123 -> 1.717 | L52: ='Revenue and CapEx Build'!L123 -> 1.717 | O52: ='Revenue and CapEx Build'!O123 -> 4.811 | P52: ='Revenue and CapEx Build'!P123 -> 8.684 | Q52: ='Revenue and CapEx Build'!Q123 -> 8.684 | R52: ='Revenue and CapEx Build'!R123 -> 10.7146 | S52: ='Revenue and CapEx Build'!S123 -> 12.949 | T52: ='Revenue and CapEx Build'!T123 -> 14.241
B53: Construction in Progress | K53: ='Revenue and CapEx Build'!K124 -> 2256.673 | L53: ='Revenue and CapEx Build'!L124 -> 2256.673 | O53: ='Revenue and CapEx Build'!O124 -> 2460.34 | P53: ='Revenue and CapEx Build'!P124 -> 3200.866 | Q53: ='Revenue and CapEx Build'!Q124 -> 3200.866 | R53: ='Revenue and CapEx Build'!R124 -> 4073.81 | S53: ='Revenue and CapEx Build'!S124 -> 4111.256 | T53: ='Revenue and CapEx Build'!T124 -> 6910.066
B54: Total Property and Equipment (ex. D&A) | K54: =SUM(K49:K53) -> 3610.786 | L54: =K54 -> 3610.786 | O54: =SUM(O49:O53) -> 9728.807 | P54: =SUM(P49:P53) -> 12741.091 | Q54: =P54 -> 12741.091 | R54: =SUM(R49:R53) -> 15610.548 | S54: =SUM(S49:S53) -> 18585.117 | T54: =SUM(T49:T53) -> 23233.759
B56: Total Property and Equipment, Net | K56: =K54+K44 -> 3493.99 | L56: =K56 -> 3493.99 | O56: =O54+O44 -> 9116.59 | P56: =P54+P44 -> 11775.86 | Q56: =P56 -> 11775.86 | R56: =R54+R44 -> 14210.991 | S56: =S54+S44 -> 16631.51 | T56: =T54+T44 -> 20659.181
B58: Total Depreciation Waterfall (Fixed Assets) | G58: =SUM(G62:G82) -> 0 | H58: =SUM(H61:H82) -> 25.25 | I58: =SUM(I61:I82) -> 25.25 | J58: =SUM(J61:J82) -> 25.25 | K58: =SUM(K61:K82) -> 25.25 | L58: =SUM(L61:L82) -> 101 | M58: =SUM(M61:M82) -> 75.25 | N58: =SUM(N61:N82) -> 154.41667 | O58: =SUM(O61:O82) -> 266.05966 | ... AK58: =SUM(AK61:AK82) -> 11580.09
B59: % yoy | M59: =M58/H58-1 -> 1.980198 | N59: =N58/I58-1 -> 5.1155116 | O59: =O58/J58-1 -> 9.5370164 | P59: =P58/K58-1 -> 13.398432 | Q59: =Q58/L58-1 -> 7.5077895 | R59: =R58/M58-1 -> 4.0988671 | S59: =S58/N58-1 -> 2.1214325 | T59: =T58/O58-1 -> 0.87150847 | ... AK59: =AK58/AF58-1 -> 0.36872147
B61: FY22 Depreciation | G61: 11 | H61: 2.75 | I61: =H61 -> 2.75 | J61: =I61 -> 2.75 | K61: =J61 -> 2.75 | L61: =SUM(H61:K61) -> 11 | M61: =K61 -> 2.75 | N61: =M61 -> 2.75 | O61: =N61 -> 2.75 | P61: =O61 -> 2.75 | Q61: =SUM(M61:P61) -> 11 | R61: =P61 -> 2.75 | S61: =R61 -> 2.75 | T61: =S61 -> 2.75 | U61: =T61 -> 2.75 | V61: =SUM(R61:U61) -> 11 | W61: =U61 -> 2.75 | X61: =W61 -> 2.75 | Y61: =X61 -> 2.75 | Z61: =Y61 -> 2.75 | AA61: =SUM(W61:Z61) -> 11 | AB61: =Z61 -> 2.75 | AC61: =AB61 -> 2.75 | AD61: =AC61 -> 2.75 | AE61: =AD61 -> 2.75 | AF61: =SUM(AB61:AE61) -> 11
B62: FY23 Depreciation | H62: =+(101-11)/4 -> 22.5 | I62: =H62 -> 22.5 | J62: =I62 -> 22.5 | K62: =J62 -> 22.5 | L62: =SUM(H62:K62) -> 90 | M62: =K62 -> 22.5 | N62: =M62 -> 22.5 | O62: =N62 -> 22.5 | P62: =O62 -> 22.5 | Q62: =SUM(M62:P62) -> 90 | R62: =P62 -> 22.5 | S62: =R62 -> 22.5 | T62: =S62 -> 22.5 | U62: =T62 -> 22.5 | V62: =SUM(R62:U62) -> 90 | W62: =U62 -> 22.5 | X62: =W62 -> 22.5 | Y62: =X62 -> 22.5 | Z62: =Y62 -> 22.5 | AA62: =SUM(W62:Z62) -> 90 | AB62: =Z62 -> 22.5 | AC62: =AB62 -> 22.5 | AD62: =AC62 -> 22.5 | AE62: =AD62 -> 22.5 | AF62: =SUM(AB62:AE62) -> 90 | AG62: =AE62 -> 22.5 | AH62: =AG62 -> 22.5 | AI62: =AH62 -> 22.5 | AJ62: =AI62 -> 22.5 | AK62: =SUM(AG62:AJ62) -> 90
B63: 1Q24 Depreciation | M63: =M$18/(4*6) -> 50 | N63: =M63 -> 50 | O63: =N63 -> 50 | P63: =O63 -> 50 | Q63: =SUM(M63:P63) -> 200 | R63: =P63 -> 50 | S63: =R63 -> 50 | T63: =S63 -> 50 | U63: =T63 -> 50 | V63: =SUM(R63:U63) -> 200 | W63: =U63 -> 50 | X63: =W63 -> 50 | Y63: =X63 -> 50 | Z63: =Y63 -> 50 | AA63: =SUM(W63:Z63) -> 200 | AB63: =Z63 -> 50 | AC63: =AB63 -> 50 | AD63: =AC63 -> 50 | AE63: =AD63 -> 50 | AF63: =SUM(AB63:AE63) -> 200 | AG63: =AE63 -> 50 | AH63: =AG63 -> 50 | AI63: =AH63 -> 50 | AJ63: =AI63 -> 50 | AK63: =SUM(AG63:AJ63) -> 200
B64: 2Q24 Depreciation | N64: =N$18/(4*6) -> 79.166667 | O64: =N64 -> 79.166667 | P64: =O64 -> 79.166667 | Q64: =SUM(M64:P64) -> 237.5 | R64: =P64 -> 79.166667 | S64: =R64 -> 79.166667 | T64: =S64 -> 79.166667 | U64: =T64 -> 79.166667 | V64: =SUM(R64:U64) -> 316.66667 | W64: =U64 -> 79.166667 | X64: =W64 -> 79.166667 | Y64: =X64 -> 79.166667 | Z64: =Y64 -> 79.166667 | AA64: =SUM(W64:Z64) -> 316.66667 | AB64: =Z64 -> 79.166667 | AC64: =AB64 -> 79.166667 | AD64: =AC64 -> 79.166667 | AE64: =AD64 -> 79.166667 | AF64: =SUM(AB64:AE64) -> 316.66667 | AG64: =AE64 -> 79.166667 | AH64: =AG64 -> 79.166667 | AI64: =AH64 -> 79.166667 | AJ64: =AI64 -> 79.166667 | AK64: =SUM(AG64:AJ64) -> 316.66667
B65: 3Q24 Depreciation | O65: =O$18/(4*6) -> 111.643 | P65: =O65 -> 111.643 | Q65: =SUM(M65:P65) -> 223.28599 | R65: =P65 -> 111.643 | S65: =R65 -> 111.643 | T65: =S65 -> 111.643 | U65: =T65 -> 111.643 | V65: =SUM(R65:U65) -> 446.57199 | W65: =U65 -> 111.643 | X65: =W65 -> 111.643 | Y65: =X65 -> 111.643 | Z65: =Y65 -> 111.643 | AA65: =SUM(W65:Z65) -> 446.57199 | AB65: =Z65 -> 111.643 | AC65: =AB65 -> 111.643 | AD65: =AC65 -> 111.643 | AE65: =AD65 -> 111.643 | AF65: =SUM(AB65:AE65) -> 446.57199 | AG65: =AE65 -> 111.643 | AH65: =AG65 -> 111.643 | AI65: =AH65 -> 111.643 | AJ65: =AI65 -> 111.643 | AK65: =SUM(AG65:AJ65) -> 446.57199
B66: 4Q24 Depreciation | P66: =P$18/(4*6) -> 97.50075 | Q66: =SUM(M66:P66) -> 97.50075 | R66: =Q66 -> 97.50075 | S66: =R66 -> 97.50075 | T66: =S66 -> 97.50075 | U66: =T66 -> 97.50075 | V66: =SUM(R66:U66) -> 390.003 | W66: =U66 -> 97.50075 | X66: =W66 -> 97.50075 | Y66: =X66 -> 97.50075 | Z66: =Y66 -> 97.50075 | AA66: =SUM(W66:Z66) -> 390.003 | AB66: =Z66 -> 97.50075 | AC66: =AB66 -> 97.50075 | AD66: =AC66 -> 97.50075 | AE66: =AD66 -> 97.50075 | AF66: =SUM(AB66:AE66) -> 390.003 | AG66: =AE66 -> 97.50075 | AH66: =AG66 -> 97.50075 | AI66: =AH66 -> 97.50075 | AJ66: =AI66 -> 97.50075 | AK66: =SUM(AG66:AJ66) -> 390.003
B67: 1Q25 Depreciation | R67: =R$18/(4*6) -> 20.129333 | S67: =R67 -> 20.129333 | T67: =S67 -> 20.129333 | U67: =T67 -> 20.129333 | V67: =SUM(R67:U67) -> 80.517333 | W67: =U67 -> 20.129333 | X67: =W67 -> 20.129333 | Y67: =X67 -> 20.129333 | Z67: =Y67 -> 20.129333 | AA67: =SUM(W67:Z67) -> 80.517333 | AB67: =Z67 -> 20.129333 | AC67: =AB67 -> 20.129333 | AD67: =AC67 -> 20.129333 | AE67: =AD67 -> 20.129333 | AF67: =SUM(AB67:AE67) -> 80.517333 | AG67: =AE67 -> 20.129333 | AH67: =AG67 -> 20.129333 | AI67: =AH67 -> 20.129333 | AJ67: =AI67 -> 20.129333 | AK67: =SUM(AG67:AJ67) -> 80.517333
B68: 2Q25 Depreciation | S68: =S$18/(4*6) -> 98.311458 | T68: =S68 -> 98.311458 | U68: =T68 -> 98.311458 | V68: =SUM(R68:U68) -> 294.93437 | W68: =U68 -> 98.311458 | X68: =W68 -> 98.311458 | Y68: =X68 -> 98.311458 | Z68: =Y68 -> 98.311458 | AA68: =SUM(W68:Z68) -> 393.24583 | AB68: =Z68 -> 98.311458 | AC68: =AB68 -> 98.311458 | AD68: =AC68 -> 98.311458 | AE68: =AD68 -> 98.311458 | AF68: =SUM(AB68:AE68) -> 393.24583 | AG68: =AE68 -> 98.311458 | AH68: =AG68 -> 98.311458 | AI68: =AH68 -> 98.311458 | AJ68: =AI68 -> 98.311458 | AK68: =SUM(AG68:AJ68) -> 393.24583
B69: 3Q25 Depreciation | T69: =T$18/(4*6) -> 15.931708 | U69: =T69 -> 15.931708 | V69: =SUM(R69:U69) -> 31.863417 | W69: =U69 -> 15.931708 | X69: =W69 -> 15.931708 | Y69: =X69 -> 15.931708 | Z69: =Y69 -> 15.931708 | AA69: =SUM(W69:Z69) -> 63.726833 | AB69: =Z69 -> 15.931708 | AC69: =AB69 -> 15.931708 | AD69: =AC69 -> 15.931708 | AE69: =AD69 -> 15.931708 | AF69: =SUM(AB69:AE69) -> 63.726833 | AG69: =AE69 -> 15.931708 | AH69: =AG69 -> 15.931708 | AI69: =AH69 -> 15.931708 | AJ69: =AI69 -> 15.931708 | AK69: =SUM(AG69:AJ69) -> 63.726833
B70: 4Q25 Depreciation | U70: =U$18/(4*6) -> 198.26504 | V70: =SUM(R70:U70) -> 198.26504 | W70: =V70 -> 198.26504 | X70: =W70 -> 198.26504 | Y70: =X70 -> 198.26504 | Z70: =Y70 -> 198.26504 | AA70: =SUM(W70:Z70) -> 793.06017 | AB70: =Z70 -> 198.26504 | AC70: =AB70 -> 198.26504 | AD70: =AC70 -> 198.26504 | AE70: =AD70 -> 198.26504 | AF70: =SUM(AB70:AE70) -> 793.06017 | AG70: =AE70 -> 198.26504 | AH70: =AG70 -> 198.26504 | AI70: =AH70 -> 198.26504 | AJ70: =AI70 -> 198.26504 | AK70: =SUM(AG70:AJ70) -> 793.06017
B71: 1Q26 Depreciation | W71: =W$18/(4*6) -> 448.26504 | X71: =W71 -> 448.26504 | Y71: =X71 -> 448.26504 | Z71: =Y71 -> 448.26504 | AA71: =SUM(W71:Z71) -> 1793.0602 | AB71: =Z71 -> 448.26504 | AC71: =AB71 -> 448.26504 | AD71: =AC71 -> 448.26504 | AE71: =AD71 -> 448.26504 | AF71: =SUM(AB71:AE71) -> 1793.0602 | AG71: =AE71 -> 448.26504 | AH71: =AG71 -> 448.26504 | AI71: =AH71 -> 448.26504 | AJ71: =AI71 -> 448.26504 | AK71: =SUM(AG71:AJ71) -> 1793.0602
B72: 2Q26 Depreciation | X72: =X$18/(4*6) -> 198.26504 | Y72: =X72 -> 198.26504 | Z72: =Y72 -> 198.26504 | AA72: =SUM(W72:Z72) -> 594.79513 | AB72: =Z72 -> 198.26504 | AC72: =AB72 -> 198.26504 | AD72: =AC72 -> 198.26504 | AE72: =AD72 -> 198.26504 | AF72: =SUM(AB72:AE72) -> 793.06017 | AG72: =AE72 -> 198.26504 | AH72: =AG72 -> 198.26504 | AI72: =AH72 -> 198.26504 | AJ72: =AI72 -> 198.26504 | AK72: =SUM(AG72:AJ72) -> 793.06017
B73: 3Q26 Depreciation | Y73: =Y$18/(4*6) -> 125.34838 | Z73: =Y73 -> 125.34838 | AA73: =SUM(W73:Z73) -> 250.69675 | AB73: =Z73 -> 125.34838 | AC73: =AB73 -> 125.34838 | AD73: =AC73 -> 125.34838 | AE73: =AD73 -> 125.34838 | AF73: =SUM(AB73:AE73) -> 501.3935 | AG73: =AE73 -> 125.34838 | AH73: =AG73 -> 125.34838 | AI73: =AH73 -> 125.34838 | AJ73: =AI73 -> 125.34838 | AK73: =SUM(AG73:AJ73) -> 501.3935
B74: 4Q26 Depreciation | Z74: =Z$18/(4*6) -> 125.34838 | AA74: =SUM(W74:Z74) -> 125.34838 | AB74: =AA74 -> 125.34838 | AC74: =AB74 -> 125.34838 | AD74: =AC74 -> 125.34838 | AE74: =AD74 -> 125.34838 | AF74: =SUM(AB74:AE74) -> 501.3935 | AG74: =AE74 -> 125.34838 | AH74: =AG74 -> 125.34838 | AI74: =AH74 -> 125.34838 | AJ74: =AI74 -> 125.34838 | AK74: =SUM(AG74:AJ74) -> 501.3935
B75: 1Q27 Depreciation | AB75: =AB$18/(4*6) -> 208.68171 | AC75: =AB75 -> 208.68171 | AD75: =AC75 -> 208.68171 | AE75: =AD75 -> 208.68171 | AF75: =SUM(AB75:AE75) -> 834.72683 | AG75: =AE75 -> 208.68171 | AH75: =AG75 -> 208.68171 | AI75: =AH75 -> 208.68171 | AJ75: =AI75 -> 208.68171 | AK75: =SUM(AG75:AJ75) -> 834.72683
B76: 2Q27 Depreciation | AC76: =AC$18/(4*6) -> 208.68171 | AD76: =AC76 -> 208.68171 | AE76: =AD76 -> 208.68171 | AF76: =SUM(AB76:AE76) -> 626.04513 | AG76: =AE76 -> 208.68171 | AH76: =AG76 -> 208.68171 | AI76: =AH76 -> 208.68171 | AJ76: =AI76 -> 208.68171 | AK76: =SUM(AG76:AJ76) -> 834.72683
B77: 3Q27 Depreciation | AD77: =AD$18/(4*6) -> 208.68171 | AE77: =AD77 -> 208.68171 | AF77: =SUM(AB77:AE77) -> 417.36342 | AG77: =AE77 -> 208.68171 | AH77: =AG77 -> 208.68171 | AI77: =AH77 -> 208.68171 | AJ77: =AI77 -> 208.68171 | AK77: =SUM(AG77:AJ77) -> 834.72683
B78: 4Q27 Depreciation | AE78: =AE$18/(4*6) -> 208.68171 | AF78: =SUM(AB78:AE78) -> 208.68171 | AG78: =AE78 -> 208.68171 | AH78: =AG78 -> 208.68171 | AI78: =AH78 -> 208.68171 | AJ78: =AI78 -> 208.68171 | AK78: =SUM(AG78:AJ78) -> 834.72683
B79: 1Q28 Depreciation | AG79: =AG$18/(4*6) -> 187.84838 | AH79: =AG79 -> 187.84838 | AI79: =AH79 -> 187.84838 | AJ79: =AI79 -> 187.84838 | AK79: =SUM(AG79:AJ79) -> 751.3935
B80: 2Q28 Depreciation | AH80: =AH$18/(4*6) -> 187.84838 | AI80: =AH80 -> 187.84838 | AJ80: =AI80 -> 187.84838 | AK80: =SUM(AG80:AJ80) -> 563.54513
B81: 3Q28 Depreciation | AI81: =AI$18/(4*6) -> 187.84838 | AJ81: =AI81 -> 187.84838 | AK81: =SUM(AG81:AJ81) -> 375.69675
B82: 4Q28 Depreciation | AJ82: =AJ$18/(4*6) -> 187.84838 | AK82: =SUM(AG82:AJ82) -> 187.84838

Sheet IS (GAAP)
B2: CoreWeave, Inc.
B3: Fiscal Year Ends Dec. 31
B4: ($ millions, except per share amounts)
C6: =Dates!C3 -> 2022 (A) | H6: =Dates!H3 -> 2023 (A) | M6: =Dates!M3 -> 2024 (A) | R6: =Dates!R3 -> 2025 (E) | W6: =Dates!W3 -> 2026 (E) | AB6: =Dates!AB3 -> 2027 (E) | AG6: =Dates!AG3 -> 2028 (E)
C7: =Dates!C4 -> 1Q22 (A) | D7: =Dates!D4 -> 2Q22 (A) | E7: =Dates!E4 -> 3Q22 (A) | F7: =Dates!F4 -> 4Q22 (A) | G7: =Dates!G4 -> FY22 (A) | H7: =Dates!H4 -> 1Q23 (A) | I7: =Dates!I4 -> 2Q23 (A) | J7: =Dates!J4 -> 3Q23 (A) | ... AK7: =Dates!AK4 -> FY28 (E)
C8: =Dates!C5 -> 44651 | D8: =Dates!D5 -> 44742 | E8: =Dates!E5 -> 44834 | F8: =Dates!F5 -> 44926 | G8: =Dates!G5 -> 44926 | H8: =Dates!H5 -> 45016 | I8: =Dates!I5 -> 45107 | J8: =Dates!J5 -> 45199 | ... AK8: =Dates!AK5 -> 47118
A10: TREV | B10: Total Revenue | G10: ='KPI Summary'!G10 -> 15.83 | H10: ='KPI Summary'!H10 -> 7.9236843 | I10: ='KPI Summary'!I10 -> 29.8436 | J10: ='KPI Summary'!J10 -> 75.178825 | K10: ='KPI Summary'!K10 -> 115.99689 | L10: ='KPI Summary'!L10 -> 228.943 | M10: ='KPI Summary'!M10 -> 188.684 | N10: ='KPI Summary'!N10 -> 395.371 | ... AK10: ='KPI Summary'!AK10 -> 21655.089
A11: TREVYY | B11: % yoy | H11: =IFERROR(H10/C10-1,"") | I11: =IFERROR(I10/D10-1,"") | J11: =IFERROR(J10/E10-1,"") | K11: =IFERROR(K10/F10-1,"") | L11: =IFERROR(L10/G10-1,"") -> 13.462603 | M11: =IFERROR(M10/H10-1,"") -> 22.81266 | N11: =IFERROR(N10/I10-1,"") -> 12.2481 | O11: =IFERROR(O10/J10-1,"") -> 6.76736 | ... AK11: =IFERROR(AK10/AF10-1,"") -> 0.25822019
A12: TREVQQ | B12: % qoq | H12: =IFERROR(H10/F10-1,"") | I12: =IFERROR(I10/H10-1,"") -> 2.7663793 | J12: =IFERROR(J10/I10-1,"") -> 1.5190937 | K12: =IFERROR(K10/J10-1,"") -> 0.5429463 | M12: =IFERROR(M10/K10-1,"") -> 0.62662981 | N12: =IFERROR(N10/M10-1,"") -> 1.0954135 | O12: =IFERROR(O10/N10-1,"") -> 0.47694444 | P12: =IFERROR(P10/O10-1,"") -> 0.2799752 | R12: =IFERROR(R10/P10-1,"") -> 0.31334306 | S12: =IFERROR(S10/R10-1,"") -> 0.23548132 | T12: =IFERROR(T10/S10-1,"") -> 0.12523871 | U12: =IFERROR(U10/T10-1,"") -> 0.13058326 | W12: =IFERROR(W10/U10-1,"") -> 0.44348713 | X12: =IFERROR(X10/W10-1,"") -> 0.33094883 | Y12: =IFERROR(Y10/X10-1,"") -> 0.10980793 | Z12: =IFERROR(Z10/Y10-1,"") -> 0.070204816 | AB12: =IFERROR(AB10/Z10-1,"") -> 0.082649169 | AC12: =IFERROR(AC10/AB10-1,"") -> 0.089818799 | AD12: =IFERROR(AD10/AC10-1,"") -> 0.077002222 | AE12: =IFERROR(AE10/AD10-1,"") -> 0.066529754 | AG12: =IFERROR(AG10/AE10-1,"") -> 0.072718069 | AH12: =IFERROR(AH10/AG10-1,"") -> 0.041288386 | AI12: =IFERROR(AI10/AH10-1,"") -> 0.035552396 | AJ12: =IFERROR(AJ10/AI10-1,"") -> 0.030497879
A14: GAAPCOGS | B14: Cost of Revenue | G14: 12.122 | H14: =M14/(1+M15) -> 4.7868239 | I14: =N14/(1+N15) -> 9.7875371 | J14: =O14/(1+O15) -> 19.315417 | K14: =L14-J14-I14-H14 -> 34.890222 | L14: 68.78 | M14: 59.22 | N14: 108.838 | O14: 143.134 | P14: 182.158 | Q14: =SUM(M14:P14) -> 493.35 | R14: 262.394 | S14: 312.667 | T14: 368.824 | U14: ='IS (Non-GAAP)'!U14+'IS (Non-GAAP)'!U102 -> 426.87781 | V14: =SUM(R14:U14) -> 1370.7628 | W14: ='IS (Non-GAAP)'!W14+'IS (Non-GAAP)'!W102 -> 553.04022 | X14: ='IS (Non-GAAP)'!X14+'IS (Non-GAAP)'!X102 -> 736.30537 | Y14: ='IS (Non-GAAP)'!Y14+'IS (Non-GAAP)'!Y102 -> 815.57849 | Z14: ='IS (Non-GAAP)'!Z14+'IS (Non-GAAP)'!Z102 -> 871.14612 | AA14: =SUM(W14:Z14) -> 2976.0702 | AB14: ='IS (Non-GAAP)'!AB14+'IS (Non-GAAP)'!AB102 -> 880.9401 | AC14: ='IS (Non-GAAP)'!AC14+'IS (Non-GAAP)'!AC102 -> 967.70163 | AD14: ='IS (Non-GAAP)'!AD14+'IS (Non-GAAP)'!AD102 -> 1028.0868 | AE14: ='IS (Non-GAAP)'!AE14+'IS (Non-GAAP)'!AE102 -> 1105.2569 | AF14: =SUM(AB14:AE14) -> 3981.9854 | AG14: ='IS (Non-GAAP)'!AG14+'IS (Non-GAAP)'!AG102 -> 1102.096 | AH14: ='IS (Non-GAAP)'!AH14+'IS (Non-GAAP)'!AH102 -> 1146.1389 | AI14: ='IS (Non-GAAP)'!AI14+'IS (Non-GAAP)'!AI102 -> 1181.1142 | AJ14: ='IS (Non-GAAP)'!AJ14+'IS (Non-GAAP)'!AJ102 -> 1215.5768 | AK14: =SUM(AG14:AJ14) -> 4644.9259
A15: GAAPCOGSYY | B15: % yoy | H15: =IFERROR(H14/C14-1,"") | I15: =IFERROR(I14/D14-1,"") | J15: =IFERROR(J14/E14-1,"") | K15: =IFERROR(K14/F14-1,"") | L15: =IFERROR(L14/G14-1,"") -> 4.6739812 | M15: 11.37146 | N15: 10.12006 | O15: 6.41035 | P15: =IFERROR(P14/K14-1,"") -> 4.2208897 | Q15: =IFERROR(Q14/L14-1,"") -> 6.17287 | R15: =IFERROR(R14/M14-1,"") -> 3.4308342 | S15: =IFERROR(S14/N14-1,"") -> 1.8727742 | T15: =IFERROR(T14/O14-1,"") -> 1.5767742 | U15: =IFERROR(U14/P14-1,"") -> 1.343448 | V15: =IFERROR(V14/Q14-1,"") -> 1.7784794 | W15: =IFERROR(W14/R14-1,"") -> 1.107671 | ... AK15: =IFERROR(AK14/AF14-1,"") -> 0.16648492
A16: GAAPCOGSQQ | B16: % qoq | H16: =IFERROR(H14/F14-1,"") | I16: =IFERROR(I14/H14-1,"") -> 1.0446829 | J16: =IFERROR(J14/I14-1,"") -> 0.97347062 | K16: =IFERROR(K14/J14-1,"") -> 0.80634061 | M16: =IFERROR(M14/K14-1,"") -> 0.69732368 | N16: =IFERROR(N14/M14-1,"") -> 0.83785883 | O16: =IFERROR(O14/N14-1,"") -> 0.31511053 | P16: =IFERROR(P14/O14-1,"") -> 0.27263962 | R16: =IFERROR(R14/P14-1,"") -> 0.44047475 | S16: =IFERROR(S14/R14-1,"") -> 0.19159356 | T16: =IFERROR(T14/S14-1,"") -> 0.17960642 | U16: =IFERROR(U14/T14-1,"") -> 0.15740247 | W16: =IFERROR(W14/U14-1,"") -> 0.29554691 | X16: =IFERROR(X14/W14-1,"") -> 0.33137761 | Y16: =IFERROR(Y14/X14-1,"") -> 0.10766337 | Z16: =IFERROR(Z14/Y14-1,"") -> 0.068132784 | AB16: =IFERROR(AB14/Z14-1,"") -> 0.011242628 | AC16: =IFERROR(AC14/AB14-1,"") -> 0.09848744 | AD16: =IFERROR(AD14/AC14-1,"") -> 0.062400569 | AE16: =IFERROR(AE14/AD14-1,"") -> 0.075061878 | AG16: =IFERROR(AG14/AE14-1,"") -> -0.0028599041 | AH16: =IFERROR(AH14/AG14-1,"") -> 0.039962914 | AI16: =IFERROR(AI14/AH14-1,"") -> 0.030515746 | AJ16: =IFERROR(AJ14/AI14-1,"") -> 0.029178052
A18: GAAPGP | B18: Gross Profit | G18: =G10-G14 -> 3.708 | H18: =H10-H14 -> 3.1368604 | I18: =I10-I14 -> 20.056063 | J18: =J10-J14 -> 55.863408 | K18: =K10-K14 -> 81.106668 | L18: =L10-L14 -> 160.163 | M18: =M10-M14 -> 129.464 | N18: =N10-N14 -> 286.533 | ... AK18: =AK10-AK14 -> 17010.163
A19: GAAPGPYY | B19: % yoy | H19: =IFERROR(H18/C18-1,"") | I19: =IFERROR(I18/D18-1,"") | J19: =IFERROR(J18/E18-1,"") | K19: =IFERROR(K18/F18-1,"") | L19: =IFERROR(L18/G18-1,"") -> 42.193905 | M19: =IFERROR(M18/H18-1,"") -> 40.27184 | N19: =IFERROR(N18/I18-1,"") -> 13.286602 | O19: =IFERROR(O18/J18-1,"") -> 6.8908003 | ... AK19: =IFERROR(AK18/AF18-1,"") -> 0.2858331
A20: GAAPGPQQ | B20: % qoq | H20: =IFERROR(H18/F18-1,"") | I20: =IFERROR(I18/H18-1,"") -> 5.393674 | J20: =IFERROR(J18/I18-1,"") -> 1.7853626 | K20: =IFERROR(K18/J18-1,"") -> 0.45187468 | M20: =IFERROR(M18/K18-1,"") -> 0.59621894 | N20: =IFERROR(N18/M18-1,"") -> 1.2132253 | O20: =IFERROR(O18/N18-1,"") -> 0.53841617 | P20: =IFERROR(P18/O18-1,"") -> 0.28235713 | R20: =IFERROR(R18/P18-1,"") -> 0.27237507 | S20: =IFERROR(S18/R18-1,"") -> 0.25149255 | T20: =IFERROR(T18/S18-1,"") -> 0.10635348 | U20: =IFERROR(U18/T18-1,"") -> 0.12065049 | W20: =IFERROR(W18/U18-1,"") -> 0.5000752 | X20: =IFERROR(X18/W18-1,"") -> 0.33080718 | Y20: =IFERROR(Y18/X18-1,"") -> 0.11051669 | Z20: =IFERROR(Z18/Y18-1,"") -> 0.070887853 | AB20: =IFERROR(AB18/Z18-1,"") -> 0.10612748 | AC20: =IFERROR(AC18/AB18-1,"") -> 0.087213066 | AD20: =IFERROR(AD18/AC18-1,"") -> 0.081436894 | AE20: =IFERROR(AE18/AD18-1,"") -> 0.063984074 | AG20: =IFERROR(AG18/AE18-1,"") -> 0.095502599 | AH20: =IFERROR(AH18/AG18-1,"") -> 0.041652098 | AI20: =IFERROR(AI18/AH18-1,"") -> 0.036932223 | AJ20: =IFERROR(AJ18/AI18-1,"") -> 0.030857217
A21: GAAPGPM | B21: Gross Margin | C21: =IFERROR(C18/C$10,"") | D21: =IFERROR(D18/D$10,"") | E21: =IFERROR(E18/E$10,"") | F21: =IFERROR(F18/F$10,"") | G21: =IFERROR(G18/G$10,"") -> 0.23423879 | H21: =IFERROR(H18/H$10,"") -> 0.39588407 | I21: =IFERROR(I18/I$10,"") -> 0.672039 | J21: =IFERROR(J18/J$10,"") -> 0.74307371 | ... AK21: =IFERROR(AK18/AK$10,"") -> 0.78550419
B23: Technology and Infrastructure | G23: 18.106 | H23: =M23/(1+M24) -> 8.8592249 | I23: =N23/(1+N24) -> 17.162371 | J23: =O23/(1+O24) -> 39.900803 | K23: =L23-J23-I23-H23 -> 65.932601 | L23: 131.855 | M23: 92.881 | N23: 182.886 | O23: 285.509 | P23: 399.409 | Q23: =SUM(M23:P23) -> 960.685 | R23: 561.402 | S23: 669.913 | T23: 747.479 | U23: ='IS (Non-GAAP)'!U23+'IS (Non-GAAP)'!U103 -> 918.00515 | V23: =SUM(R23:U23) -> 2896.7991 | W23: ='IS (Non-GAAP)'!W23+'IS (Non-GAAP)'!W103 -> 1249.5854 | X23: ='IS (Non-GAAP)'!X23+'IS (Non-GAAP)'!X103 -> 1614.4329 | Y23: ='IS (Non-GAAP)'!Y23+'IS (Non-GAAP)'!Y103 -> 1807.4273 | Z23: ='IS (Non-GAAP)'!Z23+'IS (Non-GAAP)'!Z103 -> 1915.6002 | AA23: =SUM(W23:Z23) -> 6587.0458 | AB23: ='IS (Non-GAAP)'!AB23+'IS (Non-GAAP)'!AB103 -> 2097.7557 | AC23: ='IS (Non-GAAP)'!AC23+'IS (Non-GAAP)'!AC103 -> 2289.3596 | AD23: ='IS (Non-GAAP)'!AD23+'IS (Non-GAAP)'!AD103 -> 2456.7758 | AE23: ='IS (Non-GAAP)'!AE23+'IS (Non-GAAP)'!AE103 -> 2712.6216 | AF23: =SUM(AB23:AE23) -> 9556.5128 | AG23: ='IS (Non-GAAP)'!AG23+'IS (Non-GAAP)'!AG103 -> 2888.1232 | AH23: ='IS (Non-GAAP)'!AH23+'IS (Non-GAAP)'!AH103 -> 3066.4277 | AI23: ='IS (Non-GAAP)'!AI23+'IS (Non-GAAP)'!AI103 -> 3185.8296 | AJ23: ='IS (Non-GAAP)'!AJ23+'IS (Non-GAAP)'!AJ103 -> 3392.3536 | AK23: =SUM(AG23:AJ23) -> 12532.734
B24: % yoy | H24: =IFERROR(H23/C23-1,"") | I24: =IFERROR(I23/D23-1,"") | J24: =IFERROR(J23/E23-1,"") | K24: =IFERROR(K23/F23-1,"") | L24: =IFERROR(L23/G23-1,"") -> 6.2823926 | M24: 9.4841 | N24: 9.65622 | O24: 6.15547 | P24: =IFERROR(P23/K23-1,"") -> 5.0578378 | Q24: =IFERROR(Q23/L23-1,"") -> 6.2859201 | R24: =IFERROR(R23/M23-1,"") -> 5.0443148 | S24: =IFERROR(S23/N23-1,"") -> 2.6630087 | T24: =IFERROR(T23/O23-1,"") -> 1.6180576 | U24: =IFERROR(U23/P23-1,"") -> 1.2984088 | V24: =IFERROR(V23/Q23-1,"") -> 2.0153475 | W24: =IFERROR(W23/R23-1,"") -> 1.22583 | ... AK24: =IFERROR(AK23/AF23-1,"") -> 0.31143381
B25: % qoq | H25: =IFERROR(H23/F23-1,"") | I25: =IFERROR(I23/H23-1,"") -> 0.93723165 | J25: =IFERROR(J23/I23-1,"") -> 1.3249004 | K25: =IFERROR(K23/J23-1,"") -> 0.65241288 | M25: =IFERROR(M23/K23-1,"") -> 0.40872647 | N25: =IFERROR(N23/M23-1,"") -> 0.96903565 | O25: =IFERROR(O23/N23-1,"") -> 0.56113098 | P25: =IFERROR(P23/O23-1,"") -> 0.39893664 | R25: =IFERROR(R23/P23-1,"") -> 0.40558175 | S25: =IFERROR(S23/R23-1,"") -> 0.19328574 | T25: =IFERROR(T23/S23-1,"") -> 0.11578518 | U25: =IFERROR(U23/T23-1,"") -> 0.22813504 | W25: =IFERROR(W23/U23-1,"") -> 0.3611965 | X25: =IFERROR(X23/W23-1,"") -> 0.29197486 | Y25: =IFERROR(Y23/X23-1,"") -> 0.11954316 | Z25: =IFERROR(Z23/Y23-1,"") -> 0.059849062 | AB25: =IFERROR(AB23/Z23-1,"") -> 0.095090568 | AC25: =IFERROR(AC23/AB23-1,"") -> 0.091337595 | AD25: =IFERROR(AD23/AC23-1,"") -> 0.073127968 | AE25: =IFERROR(AE23/AD23-1,"") -> 0.10413884 | AG25: =IFERROR(AG23/AE23-1,"") -> 0.06469812 | AH25: =IFERROR(AH23/AG23-1,"") -> 0.061737156 | AI25: =IFERROR(AI23/AH23-1,"") -> 0.038938463 | AJ25: =IFERROR(AJ23/AI23-1,"") -> 0.064825787
B26: % of Total Revenue | C26: =IFERROR(C23/C$10,"") | D26: =IFERROR(D23/D$10,"") | E26: =IFERROR(E23/E$10,"") | F26: =IFERROR(F23/F$10,"") | G26: =IFERROR(G23/G$10,"") -> 1.1437776 | H26: =IFERROR(H23/H$10,"") -> 1.1180689 | I26: =IFERROR(I23/I$10,"") -> 0.57507709 | J26: =IFERROR(J23/J$10,"") -> 0.53074523 | ... AK26: =IFERROR(AK23/AK$10,"") -> 0.57874313
B27: Gross Margin (Including T&I) | C27: =IFERROR(C24/C$10,"") | D27: =IFERROR(D24/D$10,"") | E27: =IFERROR(E24/E$10,"") | F27: =IFERROR(F24/F$10,"") | G27: =(G18-G23)/G10 -> -0.90953885 | H27: =(H18-H23)/H10 -> -0.72218482 | I27: =(I18-I23)/I10 -> 0.096961901 | J27: =(J18-J23)/J10 -> 0.21232847 | K27: =(K18-K23)/K10 -> 0.13081443 | L27: =(L18-L23)/L10 -> 0.1236465 | M27: =(M18-M23)/M10 -> 0.19388501 | N27: =(N18-N23)/N10 -> 0.26215125 | ... AK27: =(AK18-AK23)/AK10 -> 0.20676106
B29: Depreciation Included in T&I | G29: ='Depreciation Build'!G33 -> 11 | L29: ='Depreciation Build'!L33 -> 101 | M29: ='Depreciation Build'!M33 -> 77 | N29: ='Depreciation Build'!N33 -> 158 | O29: ='Depreciation Build'!O33 -> 256 | P29: ='Depreciation Build'!P33 -> 352 | Q29: ='Depreciation Build'!Q33 -> 843 | R29: ='Depreciation Build'!R33 -> 429 | S29: ='Depreciation Build'!S33 -> 537 | ... AK29: ='Depreciation Build'!AK33 -> 6507.9734
B31: Implied Non-Depreciation T&I | G31: =G23-G29 -> 7.106 | L31: =L23-L29 -> 30.855 | M31: =M23-M29 -> 15.881 | N31: =N23-N29 -> 24.886 | O31: =O23-O29 -> 29.509 | P31: =P23-P29 -> 47.409 | Q31: =Q23-Q29 -> 117.685 | R31: =R23-R29 -> 132.402 | S31: =S23-S29 -> 132.913 | ... AK31: =AK23-AK29 -> 6024.7606
B32: % of Revenue | G32: =G31/G10 -> 0.4488945 | L32: =L31/L10 -> 0.13477154 | M32: =M31/M10 -> 0.084167179 | N32: =N31/N10 -> 0.062943413 | O32: =O31/O10 -> 0.050534215 | P32: =P31/P10 -> 0.063429351 | Q32: =Q31/Q10 -> 0.06144064 | R32: =R31/R10 -> 0.13487947 | S32: =S31/S10 -> 0.10959294 | ... AK32: =AK31/AK10 -> 0.27821454
B34: Sales & Marketing | G34: 2.481 | H34: =M34/(1+M35) -> 1.9425858 | I34: =N34/(1+N35) -> 2.4115328 | J34: =O34/(1+O35) -> 3.9969457 | K34: =L34-J34-I34-H34 -> 4.5659357 | L34: 12.917 | M34: 4.05 | N34: 4.172 | O34: 4.554 | P34: 5.613 | Q34: =SUM(M34:P34) -> 18.389 | R34: 10.549 | S34: 36.799 | T34: 44.645 | U34: ='IS (Non-GAAP)'!U32+'IS (Non-GAAP)'!U104 -> 47.715419 | V34: =SUM(R34:U34) -> 139.70842 | W34: ='IS (Non-GAAP)'!W32+'IS (Non-GAAP)'!W104 -> 76.969516 | X34: ='IS (Non-GAAP)'!X32+'IS (Non-GAAP)'!X104 -> 64.026554 | Y34: ='IS (Non-GAAP)'!Y32+'IS (Non-GAAP)'!Y104 -> 70.004478 | Z34: ='IS (Non-GAAP)'!Z32+'IS (Non-GAAP)'!Z104 -> 70.271891 | AA34: =SUM(W34:Z34) -> 281.27244 | AB34: ='IS (Non-GAAP)'!AB32+'IS (Non-GAAP)'!AB104 -> 72.725584 | AC34: ='IS (Non-GAAP)'!AC32+'IS (Non-GAAP)'!AC104 -> 84.348744 | AD34: ='IS (Non-GAAP)'!AD32+'IS (Non-GAAP)'!AD104 -> 81.423756 | AE34: ='IS (Non-GAAP)'!AE32+'IS (Non-GAAP)'!AE104 -> 92.688701 | AF34: =SUM(AB34:AE34) -> 331.18679 | AG34: ='IS (Non-GAAP)'!AG32+'IS (Non-GAAP)'!AG104 -> 94.92461 | AH34: ='IS (Non-GAAP)'!AH32+'IS (Non-GAAP)'!AH104 -> 97.870029 | AI34: ='IS (Non-GAAP)'!AI32+'IS (Non-GAAP)'!AI104 -> 97.501076 | AJ34: ='IS (Non-GAAP)'!AJ32+'IS (Non-GAAP)'!AJ104 -> 99.435408 | AK34: =SUM(AG34:AJ34) -> 389.73112
B35: % yoy | H35: =IFERROR(H34/C34-1,"") | I35: =IFERROR(I34/D34-1,"") | J35: =IFERROR(J34/E34-1,"") | K35: =IFERROR(K34/F34-1,"") | L35: =IFERROR(L34/G34-1,"") -> 4.2063684 | M35: 1.08485 | N35: 0.73002 | O35: 0.13937 | P35: =IFERROR(P34/K34-1,"") -> 0.22932086 | Q35: =IFERROR(Q34/L34-1,"") -> 0.42362778 | R35: =IFERROR(R34/M34-1,"") -> 1.6046914 | S35: =IFERROR(S34/N34-1,"") -> 7.8204698 | T35: =IFERROR(T34/O34-1,"") -> 8.8034695 | U35: =IFERROR(U34/P34-1,"") -> 7.5008763 | V35: =IFERROR(V34/Q34-1,"") -> 6.5973908 | W35: =IFERROR(W34/R34-1,"") -> 6.2963803 | ... AK35: =IFERROR(AK34/AF34-1,"") -> 0.17677136
B36: % qoq | H36: =IFERROR(H34/F34-1,"") | I36: =IFERROR(I34/H34-1,"") -> 0.2414035 | J36: =IFERROR(J34/I34-1,"") -> 0.65742952 | K36: =IFERROR(K34/J34-1,"") -> 0.14235621 | M36: =IFERROR(M34/K34-1,"") -> -0.11299671 | N36: =IFERROR(N34/M34-1,"") -> 0.030123457 | O36: =IFERROR(O34/N34-1,"") -> 0.0915628 | P36: =IFERROR(P34/O34-1,"") -> 0.23254282 | R36: =IFERROR(R34/P34-1,"") -> 0.87938714 | S36: =IFERROR(S34/R34-1,"") -> 2.4883875 | T36: =IFERROR(T34/S34-1,"") -> 0.21321232 | U36: =IFERROR(U34/T34-1,"") -> 0.068774083 | W36: =IFERROR(W34/U34-1,"") -> 0.61309525 | X36: =IFERROR(X34/W34-1,"") -> -0.16815698 | Y36: =IFERROR(Y34/X34-1,"") -> 0.093366327 | Z36: =IFERROR(Z34/Y34-1,"") -> 0.003819931 | AB36: =IFERROR(AB34/Z34-1,"") -> 0.034917141 | AC36: =IFERROR(AC34/AB34-1,"") -> 0.15982216 | AD36: =IFERROR(AD34/AC34-1,"") -> -0.034677321 | AE36: =IFERROR(AE34/AD34-1,"") -> 0.13834961 | AG36: =IFERROR(AG34/AE34-1,"") -> 0.024122777 | AH36: =IFERROR(AH34/AG34-1,"") -> 0.031029039 | AI36: =IFERROR(AI34/AH34-1,"") -> -0.0037698305 | AJ36: =IFERROR(AJ34/AI34-1,"") -> 0.01983908
B37: % of Total Revenue | C37: =IFERROR(C34/C$10,"") | D37: =IFERROR(D34/D$10,"") | E37: =IFERROR(E34/E$10,"") | F37: =IFERROR(F34/F$10,"") | G37: =IFERROR(G34/G$10,"") -> 0.15672773 | H37: =IFERROR(H34/H$10,"") -> 0.24516194 | I37: =IFERROR(I34/I$10,"") -> 0.080805694 | J37: =IFERROR(J34/J$10,"") -> 0.053165844 | ... AK37: =IFERROR(AK34/AK$10,"") -> 0.017997207
B38: Sales and Marketing Efficiency | M38: =M34/(M10-H10) -> 0.02240536 | N38: =N34/(N10-I10) -> 0.011413645 | O38: =O34/(O10-J10) -> 0.0089511371 | P38: =P34/(P10-K10) -> 0.0088893026 | Q38: =Q34/(Q10-L10) -> 0.010903757 | R38: =R34/(R10-M10) -> 0.013303521 | S38: =S34/(S10-N10) -> 0.045018638 | T38: =T34/(T10-O10) -> 0.057183295 | ... AK38: =AK34/(AK10-AF10) -> 0.087694339
B40: General & Administrative | G40: 6.001 | H40: =M40/(1+M41) -> 4.1810156 | I40: =N40/(1+N41) -> 5.118516 | J40: =O40/(1+O41) -> 8.1593435 | K40: =L40-J40-I40-H40 -> 12.383125 | L40: 29.842 | M40: 15.686 | N40: 21.754 | O40: 33.628 | P40: 47.576 | Q40: =SUM(M40:P40) -> 118.644 | R40: 174.757 | S40: 174.2 | T40: 151.878 | U40: ='IS (Non-GAAP)'!U38+'IS (Non-GAAP)'!U105 -> 83.010542 | V40: =SUM(R40:U40) -> 583.84554 | W40: ='IS (Non-GAAP)'!W38+'IS (Non-GAAP)'!W105 -> 112.15813 | X40: ='IS (Non-GAAP)'!X38+'IS (Non-GAAP)'!X105 -> 120.16928 | Y40: ='IS (Non-GAAP)'!Y38+'IS (Non-GAAP)'!Y105 -> 128.28173 | Z40: ='IS (Non-GAAP)'!Z38+'IS (Non-GAAP)'!Z105 -> 128.32714 | AA40: =SUM(W40:Z40) -> 488.93629 | AB40: ='IS (Non-GAAP)'!AB38+'IS (Non-GAAP)'!AB105 -> 125.59571 | AC40: ='IS (Non-GAAP)'!AC38+'IS (Non-GAAP)'!AC105 -> 145.54979 | AD40: ='IS (Non-GAAP)'!AD38+'IS (Non-GAAP)'!AD105 -> 140.70923 | AE40: ='IS (Non-GAAP)'!AE38+'IS (Non-GAAP)'!AE105 -> 160.03313 | AF40: =SUM(AB40:AE40) -> 571.88786 | AG40: ='IS (Non-GAAP)'!AG38+'IS (Non-GAAP)'!AG105 -> 153.75999 | AH40: ='IS (Non-GAAP)'!AH38+'IS (Non-GAAP)'!AH105 -> 158.44939 | AI40: ='IS (Non-GAAP)'!AI38+'IS (Non-GAAP)'!AI105 -> 157.52629 | AJ40: ='IS (Non-GAAP)'!AJ38+'IS (Non-GAAP)'!AJ105 -> 160.56003 | AK40: =SUM(AG40:AJ40) -> 630.2957
B41: % yoy | H41: =IFERROR(H40/C40-1,"") | I41: =IFERROR(I40/D40-1,"") | J41: =IFERROR(J40/E40-1,"") | K41: =IFERROR(K40/F40-1,"") | L41: =IFERROR(L40/G40-1,"") -> 3.9728379 | M41: 2.75172 | N41: 3.25006 | O41: 3.12141 | P41: =IFERROR(P40/K40-1,"") -> 2.8420028 | Q41: =IFERROR(Q40/L40-1,"") -> 2.9757389 | R41: =IFERROR(R40/M40-1,"") -> 10.140954 | S41: =IFERROR(S40/N40-1,"") -> 7.0077227 | T41: =IFERROR(T40/O40-1,"") -> 3.5164149 | U41: =IFERROR(U40/P40-1,"") -> 0.74479869 | V41: =IFERROR(V40/Q40-1,"") -> 3.9209867 | W41: =IFERROR(W40/R40-1,"") -> -0.35820525 | ... AK41: =IFERROR(AK40/AF40-1,"") -> 0.10213164
B42: % qoq | H42: =IFERROR(H40/F40-1,"") | I42: =IFERROR(I40/H40-1,"") -> 0.22422789 | J42: =IFERROR(J40/I40-1,"") -> 0.59408383 | K42: =IFERROR(K40/J40-1,"") -> 0.51766191 | M42: =IFERROR(M40/K40-1,"") -> 0.26672388 | N42: =IFERROR(N40/M40-1,"") -> 0.38684177 | O42: =IFERROR(O40/N40-1,"") -> 0.54583065 | P42: =IFERROR(P40/O40-1,"") -> 0.4147734 | R42: =IFERROR(R40/P40-1,"") -> 2.6732176 | S42: =IFERROR(S40/R40-1,"") -> -0.0031872829 | T42: =IFERROR(T40/S40-1,"") -> -0.12814007 | U42: =IFERROR(U40/T40-1,"") -> -0.45343932 | W42: =IFERROR(W40/U40-1,"") -> 0.3511311 | X42: =IFERROR(X40/W40-1,"") -> 0.071427357 | Y42: =IFERROR(Y40/X40-1,"") -> 0.067508508 | Z42: =IFERROR(Z40/Y40-1,"") -> 0.00035399816 | AB42: =IFERROR(AB40/Z40-1,"") -> -0.021284939 | AC42: =IFERROR(AC40/AB40-1,"") -> 0.15887551 | AD42: =IFERROR(AD40/AC40-1,"") -> -0.033257082 | AE42: =IFERROR(AE40/AD40-1,"") -> 0.13733211 | AG42: =IFERROR(AG40/AE40-1,"") -> -0.039198968 | AH42: =IFERROR(AH40/AG40-1,"") -> 0.030498179 | AI42: =IFERROR(AI40/AH40-1,"") -> -0.0058258261 | AJ42: =IFERROR(AJ40/AI40-1,"") -> 0.01925858
B43: % of Total Revenue | C43: =IFERROR(C40/C$10,"") | D43: =IFERROR(D40/D$10,"") | E43: =IFERROR(E40/E$10,"") | F43: =IFERROR(F40/F$10,"") | G43: =IFERROR(G40/G$10,"") -> 0.37909033 | H43: =IFERROR(H40/H$10,"") -> 0.52766055 | I43: =IFERROR(I40/I$10,"") -> 0.17151134 | J43: =IFERROR(J40/J$10,"") -> 0.10853247 | ... AK43: =IFERROR(AK40/AK$10,"") -> 0.029106124
A45: GAAPOPEX | B45: Total Operating Expenses | G45: =G40+G34+G23 -> 26.588 | H45: =H40+H34+H23 -> 14.982826 | I45: =I40+I34+I23 -> 24.69242 | J45: =J40+J34+J23 -> 52.057092 | K45: =K40+K34+K23 -> 82.881662 | L45: =L40+L34+L23 -> 174.614 | M45: =M40+M34+M23 -> 112.617 | N45: =N40+N34+N23 -> 208.812 | ... AK45: =AK40+AK34+AK23 -> 13552.761
A46: GAAPOPEXYY | B46: % yoy | H46: =IFERROR(H45/C45-1,"") | I46: =IFERROR(I45/D45-1,"") | J46: =IFERROR(J45/E45-1,"") | K46: =IFERROR(K45/F45-1,"") | L46: =IFERROR(L45/G45-1,"") -> 5.5673988 | M46: =IFERROR(M45/H45-1,"") -> 6.5164056 | N46: =IFERROR(N45/I45-1,"") -> 7.4565224 | O46: =IFERROR(O45/J45-1,"") -> 5.218 | ... AK46: =IFERROR(AK45/AF45-1,"") -> 0.29572614
A47: GAAPOPEXQQ | B47: % qoq | H47: =IFERROR(H45/F45-1,"") | I47: =IFERROR(I45/H45-1,"") -> 0.64804818 | J47: =IFERROR(J45/I45-1,"") -> 1.1082216 | K47: =IFERROR(K45/J45-1,"") -> 0.59213006 | M47: =IFERROR(M45/K45-1,"") -> 0.35876861 | N47: =IFERROR(N45/M45-1,"") -> 0.85417832 | O47: =IFERROR(O45/N45-1,"") -> 0.55015516 | P47: =IFERROR(P45/O45-1,"") -> 0.39824091 | R47: =IFERROR(R45/P45-1,"") -> 0.64982612 | S47: =IFERROR(S45/R45-1,"") -> 0.17972755 | T47: =IFERROR(T45/S45-1,"") -> 0.071618959 | U47: =IFERROR(U45/T45-1,"") -> 0.11094162 | W47: =IFERROR(W45/U45-1,"") -> 0.37186074 | X47: =IFERROR(X45/W45-1,"") -> 0.25016505 | Y47: =IFERROR(Y45/X45-1,"") -> 0.11513482 | Z47: =IFERROR(Z45/Y45-1,"") -> 0.054088309 | AB47: =IFERROR(AB45/Z45-1,"") -> 0.086026787 | AC47: =IFERROR(AC45/AB45-1,"") -> 0.097201097 | AD47: =IFERROR(AD45/AC45-1,"") -> 0.063372095 | AE47: =IFERROR(AE45/AD45-1,"") -> 0.10692212 | AG47: =IFERROR(AG45/AE45-1,"") -> 0.057822744 | AH47: =IFERROR(AH45/AG45-1,"") -> 0.059276609 | AI47: =IFERROR(AI45/AH45-1,"") -> 0.035545868 | AJ47: =IFERROR(AJ45/AI45-1,"") -> 0.061464913
A49: GAAPOI | B49: GAAP Operating Income | G49: =G18-G45 -> -22.88 | H49: =H18-H45 -> -11.845966 | I49: =I18-I45 -> -4.6363566 | J49: =J18-J45 -> 3.8063159 | K49: =K18-K45 -> -1.7749934 | L49: =L18-L45 -> -14.451 | M49: =M18-M45 -> 16.847 | N49: =N18-N45 -> 77.721 | ... AK49: =AK18-AK45 -> 3457.4024
A50: GAAPOIYY | B50: % yoy | H50: =IFERROR(H49/C49-1,"") | I50: =IFERROR(I49/D49-1,"") | J50: =IFERROR(J49/E49-1,"") | K50: =IFERROR(K49/F49-1,"") | L50: =IFERROR(L49/G49-1,"") -> -0.36840035 | M50: =IFERROR(M49/H49-1,"") -> -2.4221719 | N50: =IFERROR(N49/I49-1,"") -> -17.763378 | O50: =IFERROR(O49/J49-1,"") -> 29.76886 | ... AK50: =IFERROR(AK49/AF49-1,"") -> 0.24846753
A51: GAAPOIQQ | B51: % qoq | H51: =IFERROR(H49/F49-1,"") | I51: =IFERROR(I49/H49-1,"") -> -0.60861304 | J51: =IFERROR(J49/I49-1,"") -> -1.8209713 | K51: =IFERROR(K49/J49-1,"") -> -1.4663284 | M51: =IFERROR(M49/K49-1,"") -> -10.491303 | N51: =IFERROR(N49/M49-1,"") -> 3.6133436 | O51: =IFERROR(O49/N49-1,"") -> 0.50687716 | P51: =IFERROR(P49/O49-1,"") -> -0.037928208 | R51: =IFERROR(R49/P49-1,"") -> -1.2438007 | S51: =IFERROR(S49/R49-1,"") -> -1.6992719 | T51: =IFERROR(T49/S49-1,"") -> 1.6992556 | U51: =IFERROR(U49/T49-1,"") -> 0.29741408 | W51: =IFERROR(W49/U49-1,"") -> 2.4988957 | X51: =IFERROR(X49/W49-1,"") -> 0.82372873 | Y51: =IFERROR(Y49/X49-1,"") -> 0.091166344 | Z51: =IFERROR(Z49/Y49-1,"") -> 0.1428256 | AB51: =IFERROR(AB49/Z49-1,"") -> 0.18551775 | AC51: =IFERROR(AC49/AB49-1,"") -> 0.051074681 | AD51: =IFERROR(AD49/AC49-1,"") -> 0.14966678 | AE51: =IFERROR(AE49/AD49-1,"") -> -0.086017949 | AG51: =IFERROR(AG49/AE49-1,"") -> 0.25492283 | AH51: =IFERROR(AH49/AG49-1,"") -> -0.021203964 | AI51: =IFERROR(AI49/AH49-1,"") -> 0.042283061 | AJ51: =IFERROR(AJ49/AI49-1,"") -> -0.086513986
A52: GAAPOPM | B52: Operating Margin | C52: =IFERROR(C49/C$10,"") | D52: =IFERROR(D49/D$10,"") | E52: =IFERROR(E49/E$10,"") | F52: =IFERROR(F49/F$10,"") | G52: =IFERROR(G49/G$10,"") -> -1.4453569 | H52: =IFERROR(H49/H$10,"") -> -1.4950073 | I52: =IFERROR(I49/I$10,"") -> -0.15535514 | J52: =IFERROR(J49/J$10,"") -> 0.05063016 | ... AK52: =IFERROR(AK49/AK$10,"") -> 0.15965773
B53: Improvement (bps) | Q53: =(Q52-L52)*10000 -> 2324.6039 | V53: =(V52-Q52)*10000 -> -1476.1105 | AA53: =(AA52-V52)*10000 -> 1172.7841 | AF53: =(AF52-AA52)*10000 -> 218.97698 | AK53: =(AK52-AF52)*10000 -> -12.471991
B55: Interest Expense + OID Amortization | M55: 72.833 | N55: 107.453 | O55: 139.447 | P55: 200.108 | Q55: =SUM(M55:P55) -> 519.841 | R55: =R57+R56 -> 250.743 | S55: =S57+S56 -> 243.78 | T55: =T57+T56 -> 248.791 | U55: ='Debt Model'!U66+'Debt Model'!U67 -> 418.25762 | V55: ='Debt Model'!V66+'Debt Model'!V67 -> 1313.2486 | W55: ='Debt Model'!W66+'Debt Model'!W67 -> 532.78381 | X55: ='Debt Model'!X66+'Debt Model'!X67 -> 635.75706 | Y55: ='Debt Model'!Y66+'Debt Model'!Y67 -> 700.48071 | Z55: ='Debt Model'!Z66+'Debt Model'!Z67 -> 722.41582 | AA55: ='Debt Model'!AA66+'Debt Model'!AA67 -> 2591.4374 | AB55: ='Debt Model'!AB66+'Debt Model'!AB67 -> 629.64265 | ... AK55: ='Debt Model'!AK66+'Debt Model'!AK67 -> 3963.3661
B56: Capitalized Interest | M56: -32.177 | N56: -40.687 | O56: -35.072 | P56: -51.081 | Q56: =SUM(M56:P56) -> -159.017 | R56: =-36.278-S56 -> -13.092 | S56: -23.186 | T56: -61.764 | U56: =-'Revenue and CapEx Build'!U93 -> -92.646 | V56: =-'Revenue and CapEx Build'!V93 -> -190.688 | W56: =-'Revenue and CapEx Build'!W93 -> -69.97076 | X56: =-'Revenue and CapEx Build'!X93 -> -71.370176 | Y56: =-'Revenue and CapEx Build'!Y93 -> -74.938684 | Z56: =-'Revenue and CapEx Build'!Z93 -> -77.186845 | AA56: =-'Revenue and CapEx Build'!AA93 -> -293.46647 | AB56: =-'Revenue and CapEx Build'!AB93 -> -65.351902 | ... AK56: =-'Revenue and CapEx Build'!AK93 -> -426.16031
B57: Interest Expense, Net | G57: 9.444 | H57: =M57/(1+M58) -> 4.2742474 | I57: =N57/(1+N58) -> 8.4537894 | J57: =O57/(1+O58) -> -0.41398799 | K57: =L57-J57-I57-H57 -> 16.089951 | L57: 28.404 | M57: =SUM(M55:M56) -> 40.656 | N57: =SUM(N55:N56) -> 66.766 | O57: =SUM(O55:O56) -> 104.375 | P57: =SUM(P55:P56) -> 149.027 | Q57: =SUM(M57:P57) -> 360.824 | R57: 263.835 | S57: 266.966 | T57: 310.555 | U57: =U55+U56 -> 325.61162 | V57: =V55+V56 -> 1122.5606 | W57: =W55+W56 -> 462.81305 | X57: =X55+X56 -> 564.38688 | Y57: =Y55+Y56 -> 625.54203 | Z57: =Z55+Z56 -> 645.22897 | AA57: =AA55+AA56 -> 2297.9709 | AB57: =AB55+AB56 -> 564.29075 | ... AK57: =AK55+AK56 -> 3537.2058
B58: % yoy | H58: =IFERROR(H57/C57-1,"") | I58: =IFERROR(I57/D57-1,"") | J58: =IFERROR(J57/E57-1,"") | K58: =IFERROR(K57/F57-1,"") | L58: =IFERROR(L57/G57-1,"") -> 2.0076239 | M58: 8.51185 | N58: 6.89776 | O58: -253.12084 | P58: =IFERROR(P57/K57-1,"") -> 8.2621164 | Q58: =IFERROR(Q57/L57-1,"") -> 11.703281 | R58: =IFERROR(R57/M57-1,"") -> 5.4894481 | S58: =IFERROR(S57/N57-1,"") -> 2.9985322 | T58: =IFERROR(T57/O57-1,"") -> 1.9753772 | U58: =IFERROR(U57/P57-1,"") -> 1.184917 | V58: =IFERROR(V57/Q57-1,"") -> 2.111103 | W58: =IFERROR(W57/R57-1,"") -> 0.75417609 | ... AK58: =IFERROR(AK57/AF57-1,"") -> 0.21726298
B60: Loss on Fair Value Adjustments | G60: -2.884 | L60: -533.952 | M60: -97.5 | N60: -310.231 | O60: =-748.864-N60-M60 -> -341.133 | P60: -7.065 | Q60: =SUM(M60:P60) -> -755.929 | R60: 26.837 | S60: 0 | T60: 0 | U60: ='IS (Non-GAAP)'!U57-'IS (Non-GAAP)'!U123 -> 0 | V60: =SUM(R60:U60) -> 26.837 | W60: ='IS (Non-GAAP)'!W57-'IS (Non-GAAP)'!W123 -> 0 | X60: ='IS (Non-GAAP)'!X57-'IS (Non-GAAP)'!X123 -> 0 | Y60: ='IS (Non-GAAP)'!Y57-'IS (Non-GAAP)'!Y123 -> 0 | Z60: ='IS (Non-GAAP)'!Z57-'IS (Non-GAAP)'!Z123 -> 0 | AA60: =SUM(W60:Z60) -> 0 | AB60: ='IS (Non-GAAP)'!AB57-'IS (Non-GAAP)'!AB123 -> 0 | AC60: ='IS (Non-GAAP)'!AC57-'IS (Non-GAAP)'!AC123 -> 0 | AD60: ='IS (Non-GAAP)'!AD57-'IS (Non-GAAP)'!AD123 -> 0 | AE60: ='IS (Non-GAAP)'!AE57-'IS (Non-GAAP)'!AE123 -> 0 | AF60: =SUM(AB60:AE60) -> 0 | AG60: ='IS (Non-GAAP)'!AG57-'IS (Non-GAAP)'!AG123 -> 0 | AH60: ='IS (Non-GAAP)'!AH57-'IS (Non-GAAP)'!AH123 -> 0 | AI60: ='IS (Non-GAAP)'!AI57-'IS (Non-GAAP)'!AI123 -> 0 | AJ60: ='IS (Non-GAAP)'!AJ57-'IS (Non-GAAP)'!AJ123 -> 0 | AK60: =SUM(AG60:AJ60) -> 0
A61: GAAPOTHI | B61: Other Income, Net | G61: 0.192 | L61: 18.76 | M61: 7.46 | N61: 16.406 | O61: 10.244 | P61: 14.084 | Q61: =SUM(M61:P61) -> 48.194 | R61: -4.137 | S61: 5.023 | T61: 21.901 | U61: ='IS (Non-GAAP)'!U58-'IS (Non-GAAP)'!U124 -> 37.327874 | V61: =SUM(R61:U61) -> 60.114874 | W61: ='IS (Non-GAAP)'!W58-'IS (Non-GAAP)'!W124 -> 31.666695 | X61: ='IS (Non-GAAP)'!X58-'IS (Non-GAAP)'!X124 -> 30.179712 | Y61: ='IS (Non-GAAP)'!Y58-'IS (Non-GAAP)'!Y124 -> 30.309892 | Z61: ='IS (Non-GAAP)'!Z58-'IS (Non-GAAP)'!Z124 -> 30.876922 | AA61: =SUM(W61:Z61) -> 123.03322 | AB61: ='IS (Non-GAAP)'!AB58-'IS (Non-GAAP)'!AB124 -> 35.947752 | AC61: ='IS (Non-GAAP)'!AC58-'IS (Non-GAAP)'!AC124 -> 32.729174 | AD61: ='IS (Non-GAAP)'!AD58-'IS (Non-GAAP)'!AD124 -> 34.903458 | AE61: ='IS (Non-GAAP)'!AE58-'IS (Non-GAAP)'!AE124 -> 37.491765 | AF61: =SUM(AB61:AE61) -> 141.07215 | AG61: ='IS (Non-GAAP)'!AG58-'IS (Non-GAAP)'!AG124 -> 39.612086 | AH61: ='IS (Non-GAAP)'!AH58-'IS (Non-GAAP)'!AH124 -> 37.242486 | AI61: ='IS (Non-GAAP)'!AI58-'IS (Non-GAAP)'!AI124 -> 38.125277 | AJ61: ='IS (Non-GAAP)'!AJ58-'IS (Non-GAAP)'!AJ124 -> 40.669664 | AK61: =SUM(AG61:AJ61) -> 155.64951
B62: GAAP Income Before Taxes | G62: =G49+SUM(G60:G61)-G57 -> -35.016 | L62: =L49+SUM(L60:L61)-L57 -> -558.047 | M62: =M49+SUM(M60:M61)-M57 -> -113.849 | N62: =N49+SUM(N60:N61)-N57 -> -282.87 | O62: =O49+SUM(O60:O61)-O57 -> -318.148 | P62: =P49+SUM(P60:P61)-P57 -> -29.334 | Q62: =Q49+SUM(Q60:Q61)-Q57 -> -744.201 | R62: =R49+SUM(R60:R61)-R57 -> -268.605 | S62: =S49+SUM(S60:S61)-S57 -> -242.734 | ... AK62: =AK49+SUM(AK60:AK61)-AK57 -> 75.846123
A64: GAAPTAXES | B64: Provision for (Benefit from) Income Taxes | G64: -4.15 | L64: 35.701 | M64: 15.399 | N64: 40.151 | O64: 41.659 | P64: 22.038 | Q64: =SUM(M64:P64) -> 119.247 | R64: 46.036 | S64: 47.775 | T64: -126.68 | U64: ='IS (Non-GAAP)'!U61 -> 65.470894 | V64: =SUM(R64:U64) -> 32.601894 | W64: ='IS (Non-GAAP)'!W61 -> 32.665141 | X64: ='IS (Non-GAAP)'!X61 -> 6.6481212 | Y64: ='IS (Non-GAAP)'!Y61 -> 15.187231 | Z64: ='IS (Non-GAAP)'!Z61 -> -8.9920716 | AA64: =SUM(W64:Z64) -> 45.508422 | AB64: ='IS (Non-GAAP)'!AB61 -> 153.08441 | AC64: ='IS (Non-GAAP)'!AC61 -> -30.179843 | AD64: ='IS (Non-GAAP)'!AD61 -> -25.764935 | AE64: ='IS (Non-GAAP)'!AE61 -> -10.411007 | AF64: =SUM(AB64:AE64) -> 86.728625 | AG64: ='IS (Non-GAAP)'!AG61 -> 246.37397 | AH64: ='IS (Non-GAAP)'!AH61 -> -27.870481 | AI64: ='IS (Non-GAAP)'!AI61 -> -19.167803 | AJ64: ='IS (Non-GAAP)'!AJ61 -> 9.4910138 | AK64: =SUM(AG64:AJ64) -> 208.8267
B65: Effective Tax Rate | G65: =G64/G62 -> 0.11851725 | L65: =L64/L62 -> -0.063974898 | M65: =M64/M62 -> -0.13525811 | N65: =N64/N62 -> -0.14194153 | O65: =O64/O62 -> -0.1309422 | P65: =P64/P62 -> -0.75127838 | Q65: =Q64/Q62 -> -0.16023494 | R65: =R64/R62 -> -0.17138921 | S65: =S64/S62 -> -0.19682039 | ... AK65: =AK64/AK62 -> 2.7532943
B67: GAAP Net Loss from Continuing Operations | G67: =G62-G64 -> -30.866 | L67: =L62-L64 -> -593.748 | M67: =M62-M64 -> -129.248 | N67: =N62-N64 -> -323.021 | O67: =O62-O64 -> -359.807 | P67: =P62-P64 -> -51.372 | Q67: =Q62-Q64 -> -863.448 | R67: =R62-R64 -> -314.641 | S67: =S62-S64 -> -290.509 | ... AK67: =AK62-AK64 -> -132.98058
A69: GAAPEPSB | B69: GAAP EPS from Continuing Operations (Basic) | G69: =G67/G88 -> -0.17087781 | L69: =IFERROR(L67/L88,"") -> -3.0897983 | M69: =IFERROR(M67/M88,"") -> -0.61773759 | N69: =IFERROR(N67/N88,"") -> -1.5409396 | O69: =IFERROR(O67/O88,"") | P69: =IFERROR(P67/P88,"") | Q69: =IFERROR(Q67/Q88,"") -> -3.963425 | R69: =IFERROR(R67/R88,"") -> -1.2810698 | S69: =IFERROR(S67/S88,"") -> -0.59702913 | ... AK69: =IFERROR(AK67/AK88,"") -> -0.25007418
A70: GAAPEPSBYY | B70: % yoy | L70: =IFERROR(L69/G69-1,"") -> 17.081917 | M70: =IFERROR(M69/H69-1,"") | N70: =IFERROR(N69/I69-1,"") | O70: =IFERROR(O69/J69-1,"") | P70: =IFERROR(P69/K69-1,"") | Q70: =IFERROR(Q69/L69-1,"") -> 0.28274556 | R70: =IFERROR(R69/M69-1,"") -> 1.0738091 | S70: =IFERROR(S69/N69-1,"") -> -0.61255513 | ... AK70: =IFERROR(AK69/AF69-1,"") -> 0.57937068
B71: % qoq | M71: =IFERROR(M69/K69-1,"") | N71: =IFERROR(N69/M69-1,"") -> 1.4944889 | O71: =IFERROR(O69/N69-1,"") | P71: =IFERROR(P69/O69-1,"") | R71: =IFERROR(R69/P69-1,"") | S71: =IFERROR(S69/R69-1,"") -> -0.53396051 | T71: =IFERROR(T69/S69-1,"") -> -0.62952702 | U71: =IFERROR(U69/T69-1,"") -> 1.5936838 | W71: =IFERROR(W69/U69-1,"") -> -0.20737167 | X71: =IFERROR(X69/W69-1,"") -> -0.51439026 | Y71: =IFERROR(Y69/X69-1,"") -> 0.26508839 | Z71: =IFERROR(Z69/Y69-1,"") -> -0.50959006 | AB71: =IFERROR(AB69/Z69-1,"") -> -0.33563486 | AC71: =IFERROR(AC69/AB69-1,"") -> -1.1088505 | AD71: =IFERROR(AD69/AC69-1,"") -> 5.641952 | AE71: =IFERROR(AE69/AD69-1,"") -> -3.1690753 | AG71: =IFERROR(AG69/AE69-1,"") -> -0.47171713 | AH71: =IFERROR(AH69/AG69-1,"") -> -1.5214565 | AI71: =IFERROR(AI69/AH69-1,"") -> -0.84721088 | AJ71: =IFERROR(AJ69/AI69-1,"") -> -37.38944
A73: EPSGAAP | B73: GAAP EPS from Continuing Operations (Diluted) | G73: =G67/G89 -> -0.17087781 | L73: =IFERROR(L67/L89,"") -> -3.0897983 | M73: =IFERROR(M67/M89,"") -> -0.61773759 | N73: =IFERROR(N67/N89,"") -> -1.5409396 | O73: =IFERROR(O67/O89,"") | P73: =IFERROR(P67/P89,"") | Q73: =IFERROR(Q67/Q89,"") -> -3.963425 | R73: =IFERROR(R67/R89,"") -> -1.2621333 | S73: =IFERROR(S67/S89,"") -> -0.59702913 | ... AK73: =IFERROR(AK67/AK89,"") -> -0.25007418
A74: EPSGAAPYY | B74: % yoy | L74: =IFERROR(L73/G73-1,"") -> 17.081917 | M74: =IFERROR(M73/H73-1,"") | N74: =IFERROR(N73/I73-1,"") | O74: =IFERROR(O73/J73-1,"") | P74: =IFERROR(P73/K73-1,"") | Q74: =IFERROR(Q73/L73-1,"") -> 0.28274556 | R74: =IFERROR(R73/M73-1,"") -> 1.0431545 | S74: =IFERROR(S73/N73-1,"") -> -0.61255513 | ... AK74: =IFERROR(AK73/AF73-1,"") -> 0.57937068
A75: EPSGAAPQQ | B75: % qoq | M75: =IFERROR(M73/K73-1,"") | N75: =IFERROR(N73/M73-1,"") -> 1.4944889 | O75: =IFERROR(O73/N73-1,"") | P75: =IFERROR(P73/O73-1,"") | R75: =IFERROR(R73/P73-1,"") | S75: =IFERROR(S73/R73-1,"") -> -0.52696825 | T75: =IFERROR(T73/S73-1,"") -> -0.62952702 | U75: =IFERROR(U73/T73-1,"") -> 1.5936838 | W75: =IFERROR(W73/U73-1,"") -> -0.20737167 | X75: =IFERROR(X73/W73-1,"") -> -0.51439026 | Y75: =IFERROR(Y73/X73-1,"") -> 0.26508839 | Z75: =IFERROR(Z73/Y73-1,"") -> -0.50959006 | AB75: =IFERROR(AB73/Z73-1,"") -> -0.33563486 | AC75: =IFERROR(AC73/AB73-1,"") -> -1.1088505 | AD75: =IFERROR(AD73/AC73-1,"") -> 5.641952 | AE75: =IFERROR(AE73/AD73-1,"") -> -3.1690753 | AG75: =IFERROR(AG73/AE73-1,"") -> -0.47171713 | AH75: =IFERROR(AH73/AG73-1,"") -> -1.5214565 | AI75: =IFERROR(AI73/AH73-1,"") -> -0.84721088 | AJ75: =IFERROR(AJ73/AI73-1,"") -> -37.38944
B77: Net Loss from Discontinued Operations, Net of Tax | G77: -0.189 | L77: 0 | M77: 0 | N77: 0 | O77: 0 | P77: 0
B78: Net Income / (Loss) | G78: =G67+G77 -> -31.055 | L78: =L67+L77 -> -593.748 | M78: =M67+M77 -> -129.248 | N78: =N67+N77 -> -323.021 | O78: =O67+O77 -> -359.807 | P78: =P67+P77 -> -51.372 | Q78: =Q67+Q77 -> -863.448 | R78: =R67+R77 -> -314.641 | S78: =S67+S77 -> -290.509 | ... AK78: =AK67+AK77 -> -132.98058
A80: GAAPEPSB | B80: GAAP EPS (Basic) | G80: =G78/G88 -> -0.17192413 | L80: =IFERROR(L78/L88,"") -> -3.0897983 | M80: =IFERROR(M78/M88,"") -> -0.61773759 | N80: =IFERROR(N78/N88,"") -> -1.5409396 | O80: =IFERROR(O78/O88,"") | P80: =IFERROR(P78/P88,"") | Q80: =IFERROR(Q78/Q88,"") -> -3.963425 | R80: =IFERROR(R78/R88,"") -> -1.2810698 | S80: =IFERROR(S78/S88,"") -> -0.59702913 | ... AK80: =IFERROR(AK78/AK88,"") -> -0.25007418
A81: GAAPEPSBYY | B81: % yoy | L81: =IFERROR(L80/G80-1,"") -> 16.971871 | M81: =IFERROR(M80/H80-1,"") | N81: =IFERROR(N80/I80-1,"") | O81: =IFERROR(O80/J80-1,"") | P81: =IFERROR(P80/K80-1,"") | Q81: =IFERROR(Q80/L80-1,"") -> 0.28274556 | R81: =IFERROR(R80/M80-1,"") -> 1.0738091 | S81: =IFERROR(S80/N80-1,"") -> -0.61255513 | ... AK81: =IFERROR(AK80/AF80-1,"") -> 0.57937068
B82: % qoq | M82: =IFERROR(M80/K80-1,"") | N82: =IFERROR(N80/M80-1,"") -> 1.4944889 | O82: =IFERROR(O80/N80-1,"") | P82: =IFERROR(P80/O80-1,"") | R82: =IFERROR(R80/P80-1,"") | S82: =IFERROR(S80/R80-1,"") -> -0.53396051 | T82: =IFERROR(T80/S80-1,"") -> -0.62952702 | U82: =IFERROR(U80/T80-1,"") -> 1.5936838 | W82: =IFERROR(W80/U80-1,"") -> -0.20737167 | X82: =IFERROR(X80/W80-1,"") -> -0.51439026 | Y82: =IFERROR(Y80/X80-1,"") -> 0.26508839 | Z82: =IFERROR(Z80/Y80-1,"") -> -0.50959006 | AB82: =IFERROR(AB80/Z80-1,"") -> -0.33563486 | AC82: =IFERROR(AC80/AB80-1,"") -> -1.1088505 | AD82: =IFERROR(AD80/AC80-1,"") -> 5.641952 | AE82: =IFERROR(AE80/AD80-1,"") -> -3.1690753 | AG82: =IFERROR(AG80/AE80-1,"") -> -0.47171713 | AH82: =IFERROR(AH80/AG80-1,"") -> -1.5214565 | AI82: =IFERROR(AI80/AH80-1,"") -> -0.84721088 | AJ82: =IFERROR(AJ80/AI80-1,"") -> -37.38944
A84: EPSGAAP | B84: GAAP EPS (Diluted) | G84: =G78/G89 -> -0.17192413 | L84: =IFERROR(L78/L89,"") -> -3.0897983 | M84: =IFERROR(M78/M89,"") -> -0.61773759 | N84: =IFERROR(N78/N89,"") -> -1.5409396 | O84: =IFERROR(O78/O89,"") | P84: =IFERROR(P78/P89,"") | Q84: =IFERROR(Q78/Q89,"") -> -3.963425 | R84: =IFERROR(R78/R89,"") -> -1.2621333 | S84: =IFERROR(S78/S89,"") -> -0.59702913 | ... AK84: =IFERROR(AK78/AK89,"") -> -0.25007418
A85: EPSGAAPYY | B85: % yoy | L85: =IFERROR(L84/G84-1,"") -> 16.971871 | M85: =IFERROR(M84/H84-1,"") | N85: =IFERROR(N84/I84-1,"") | O85: =IFERROR(O84/J84-1,"") | P85: =IFERROR(P84/K84-1,"") | Q85: =IFERROR(Q84/L84-1,"") -> 0.28274556 | R85: =IFERROR(R84/M84-1,"") -> 1.0431545 | S85: =IFERROR(S84/N84-1,"") -> -0.61255513 | ... AK85: =IFERROR(AK84/AF84-1,"") -> 0.57937068
A86: EPSGAAPQQ | B86: % qoq | M86: =IFERROR(M84/K84-1,"") | N86: =IFERROR(N84/M84-1,"") -> 1.4944889 | O86: =IFERROR(O84/N84-1,"") | P86: =IFERROR(P84/O84-1,"") | R86: =IFERROR(R84/P84-1,"") | S86: =IFERROR(S84/R84-1,"") -> -0.52696825 | T86: =IFERROR(T84/S84-1,"") -> -0.62952702 | U86: =IFERROR(U84/T84-1,"") -> 1.5936838 | W86: =IFERROR(W84/U84-1,"") -> -0.20737167 | X86: =IFERROR(X84/W84-1,"") -> -0.51439026 | Y86: =IFERROR(Y84/X84-1,"") -> 0.26508839 | Z86: =IFERROR(Z84/Y84-1,"") -> -0.50959006 | AB86: =IFERROR(AB84/Z84-1,"") -> -0.33563486 | AC86: =IFERROR(AC84/AB84-1,"") -> -1.1088505 | AD86: =IFERROR(AD84/AC84-1,"") -> 5.641952 | AE86: =IFERROR(AE84/AD84-1,"") -> -3.1690753 | AG86: =IFERROR(AG84/AE84-1,"") -> -0.47171713 | AH86: =IFERROR(AH84/AG84-1,"") -> -1.5214565 | AI86: =IFERROR(AI84/AH84-1,"") -> -0.84721088 | AJ86: =IFERROR(AJ84/AI84-1,"") -> -37.38944
A88: WADSOB | B88: Weighted Average Basic Shares Outstanding | G88: 180.632 | L88: 192.164 | M88: 209.228 | N88: 209.626 | Q88: 217.854 | R88: 245.608 | S88: 486.591 | T88: 497.886 | U88: ='IS (Non-GAAP)'!U86 -> 499.37966 | V88: ='IS (Non-GAAP)'!V86 -> 432.36616 | W88: ='IS (Non-GAAP)'!W86 -> 502.37594 | X88: ='IS (Non-GAAP)'!X86 -> 505.39019 | Y88: ='IS (Non-GAAP)'!Y86 -> 508.42253 | Z88: ='IS (Non-GAAP)'!Z86 -> 511.47307 | AA88: ='IS (Non-GAAP)'!AA86 -> 506.91543 | AB88: ='IS (Non-GAAP)'!AB86 -> 514.54191 | ... AK88: ='IS (Non-GAAP)'!AK86 -> 531.76452
A89: WADSO | B89: Weighted Average Diluted Shares Outstanding | G89: 180.632 | L89: 192.164 | M89: 209.228 | N89: 209.626 | Q89: 217.854 | R89: 249.293 | S89: 486.591 | T89: 497.886 | U89: ='IS (Non-GAAP)'!U87 -> 499.37966 | V89: ='IS (Non-GAAP)'!V87 -> 433.28741 | W89: ='IS (Non-GAAP)'!W87 -> 502.37594 | X89: ='IS (Non-GAAP)'!X87 -> 505.39019 | Y89: ='IS (Non-GAAP)'!Y87 -> 508.42253 | Z89: ='IS (Non-GAAP)'!Z87 -> 511.47307 | AA89: ='IS (Non-GAAP)'!AA87 -> 506.91543 | AB89: ='IS (Non-GAAP)'!AB87 -> 514.54191 | ... AK89: ='IS (Non-GAAP)'!AK87 -> 531.76452
B91: Other Comprehensive Income / (Loss)
B92: Unrealized (Loss) Gain on Available-for-Sale Marketable Securities | G92: -0.156 | L92: 0.008 | M92: 0.058 | N92: 0.027 | O92: 0.073 | R92: 0 | S92: 0 | T92: 0.031
B93: Change in Fair Value of Derivatives, Net | M93: 0 | N93: 0 | O93: 0 | R93: 0 | S93: -0.271 | T93: -1.044
B94: Total Comprehensive Loss | G94: =G78+G92 -> -31.211 | L94: =L78+L92+L93 -> -593.74 | M94: =M78+M92+M93 -> -129.19 | N94: =N78+N92+N93 -> -322.994 | O94: =O78+O92+O93 -> -359.734 | P94: =P78+P92+P93 -> -51.372 | Q94: =Q78+Q92+Q93 -> -863.448 | R94: =R78+R92+R93 -> -314.641 | S94: =S78+S92+S93 -> -290.78 | T94: =T78+T92+T93 -> -111.137
B96: EBITDA
B97: EBIT | G97: =G49 -> -22.88 | L97: =L49 -> -14.451 | M97: =M49 -> 16.847 | N97: =N49 -> 77.721 | O97: =O49 -> 117.116 | P97: =P49 -> 112.674 | Q97: =Q49 -> 324.358 | R97: =R49 -> -27.47 | S97: =S49 -> 19.209 | ... AK97: =AK49 -> 3457.4024
B98: Depreciation and Amortization | G98: =CF!G14 -> 11.695 | L98: =CF!L14 -> 103.21 | M98: =CF!M14 -> 79.51 | N98: =CF!N14 -> 164.46 | O98: =CF!O14 -> 254.024 | P98: =CF!P14 -> 365.419 | Q98: =CF!Q14 -> 863.413 | R98: =CF!R14 -> 443.497 | S98: =CF!S14 -> 559.481 | ... AK98: =CF!AK14 -> 12018.204
B99: EBITDA | G99: =G97+G98 -> -11.185 | L99: =L97+L98 -> 88.759 | M99: =M97+M98 -> 96.357 | N99: =N97+N98 -> 242.181 | O99: =O97+O98 -> 371.14 | P99: =P97+P98 -> 478.093 | Q99: =Q97+Q98 -> 1187.771 | R99: =R97+R98 -> 416.027 | S99: =S97+S98 -> 578.69 | ... AK99: =AK97+AK98 -> 15475.606
B100: % Margin | G100: =IFERROR(G99/G10,"") -> -0.7065698 | H100: =IFERROR(H99/C99-1,"") | I100: =IFERROR(I99/D99-1,"") | J100: =IFERROR(J99/E99-1,"") | K100: =IFERROR(K99/F99-1,"") | L100: =IFERROR(L99/L10,"") -> 0.38769039 | M100: =IFERROR(M99/M10,"") -> 0.51067923 | N100: =IFERROR(N99/N10,"") -> 0.61254113 | O100: =IFERROR(O99/O10,"") -> 0.63557791 | P100: =IFERROR(P99/P10,"") -> 0.6396492 | Q100: =IFERROR(Q99/Q10,"") -> 0.62010801 | R100: =IFERROR(R99/R10,"") -> 0.42381157 | S100: =IFERROR(S99/S10,"") -> 0.47715677 | ... AK100: =IFERROR(AK99/AK10,"") -> 0.71464062

Sheet IS (Non-GAAP)
B2: CoreWeave, Inc.
B3: Fiscal Year Ends Dec. 31
B4: ($ millions, except per share amounts)
C6: =Dates!C3 -> 2022 (A) | H6: =Dates!H3 -> 2023 (A) | M6: =Dates!M3 -> 2024 (A) | R6: =Dates!R3 -> 2025 (E) | W6: =Dates!W3 -> 2026 (E) | AB6: =Dates!AB3 -> 2027 (E) | AG6: =Dates!AG3 -> 2028 (E)
C7: =Dates!C4 -> 1Q22 (A) | D7: =Dates!D4 -> 2Q22 (A) | E7: =Dates!E4 -> 3Q22 (A) | F7: =Dates!F4 -> 4Q22 (A) | G7: =Dates!G4 -> FY22 (A) | H7: =Dates!H4 -> 1Q23 (A) | I7: =Dates!I4 -> 2Q23 (A) | J7: =Dates!J4 -> 3Q23 (A) | ... AK7: =Dates!AK4 -> FY28 (E)
C8: =Dates!C5 -> 44651 | D8: =Dates!D5 -> 44742 | E8: =Dates!E5 -> 44834 | F8: =Dates!F5 -> 44926 | G8: =Dates!G5 -> 44926 | H8: =Dates!H5 -> 45016 | I8: =Dates!I5 -> 45107 | J8: =Dates!J5 -> 45199 | ... AK8: =Dates!AK5 -> 47118
A10: TREV | B10: Total Revenue | G10: ='KPI Summary'!G10 -> 15.83 | H10: ='KPI Summary'!H10 -> 7.9236843 | I10: ='KPI Summary'!I10 -> 29.8436 | J10: ='KPI Summary'!J10 -> 75.178825 | K10: ='KPI Summary'!K10 -> 115.99689 | L10: ='KPI Summary'!L10 -> 228.943 | M10: ='KPI Summary'!M10 -> 188.684 | N10: ='KPI Summary'!N10 -> 395.371 | ... AK10: ='KPI Summary'!AK10 -> 21655.089
A11: TREVYY | B11: % yoy | H11: =IFERROR(H10/C10-1,"") | I11: =IFERROR(I10/D10-1,"") | J11: =IFERROR(J10/E10-1,"") | K11: =IFERROR(K10/F10-1,"") | L11: =IFERROR(L10/G10-1,"") -> 13.462603 | M11: =IFERROR(M10/H10-1,"") -> 22.81266 | N11: =IFERROR(N10/I10-1,"") -> 12.2481 | O11: =IFERROR(O10/J10-1,"") -> 6.76736 | ... AK11: =IFERROR(AK10/AF10-1,"") -> 0.25822019
A12: TREVQQ | B12: % qoq | H12: =IFERROR(H10/F10-1,"") | I12: =IFERROR(I10/H10-1,"") -> 2.7663793 | J12: =IFERROR(J10/I10-1,"") -> 1.5190937 | K12: =IFERROR(K10/J10-1,"") -> 0.5429463 | M12: =IFERROR(M10/K10-1,"") -> 0.62662981 | N12: =IFERROR(N10/M10-1,"") -> 1.0954135 | O12: =IFERROR(O10/N10-1,"") -> 0.47694444 | P12: =IFERROR(P10/O10-1,"") -> 0.2799752 | R12: =IFERROR(R10/P10-1,"") -> 0.31334306 | S12: =IFERROR(S10/R10-1,"") -> 0.23548132 | T12: =IFERROR(T10/S10-1,"") -> 0.12523871 | U12: =IFERROR(U10/T10-1,"") -> 0.13058326 | W12: =IFERROR(W10/U10-1,"") -> 0.44348713 | X12: =IFERROR(X10/W10-1,"") -> 0.33094883 | Y12: =IFERROR(Y10/X10-1,"") -> 0.10980793 | Z12: =IFERROR(Z10/Y10-1,"") -> 0.070204816 | AB12: =IFERROR(AB10/Z10-1,"") -> 0.082649169 | AC12: =IFERROR(AC10/AB10-1,"") -> 0.089818799 | AD12: =IFERROR(AD10/AC10-1,"") -> 0.077002222 | AE12: =IFERROR(AE10/AD10-1,"") -> 0.066529754 | AG12: =IFERROR(AG10/AE10-1,"") -> 0.072718069 | AH12: =IFERROR(AH10/AG10-1,"") -> 0.041288386 | AI12: =IFERROR(AI10/AH10-1,"") -> 0.035552396 | AJ12: =IFERROR(AJ10/AI10-1,"") -> 0.030497879
A14: COGS | B14: Cost of Revenue | G14: ='IS (GAAP)'!G14-'IS (Non-GAAP)'!G102 -> 11.989 | H14: ='IS (GAAP)'!H14-'IS (Non-GAAP)'!H102 -> 4.7868239 | I14: ='IS (GAAP)'!I14-'IS (Non-GAAP)'!I102 -> 9.7875371 | J14: ='IS (GAAP)'!J14-'IS (Non-GAAP)'!J102 -> 19.315417 | K14: ='IS (GAAP)'!K14-'IS (Non-GAAP)'!K102 -> 34.890222 | L14: ='IS (GAAP)'!L14-'IS (Non-GAAP)'!L102 -> 68.086 | M14: ='IS (GAAP)'!M14-'IS (Non-GAAP)'!M102 -> 58.832 | N14: ='IS (GAAP)'!N14-'IS (Non-GAAP)'!N102 -> 108.488 | ... T14: ='IS (GAAP)'!T14-'IS (Non-GAAP)'!T102 -> 365.291 | U14: =U10-U18 -> 412.99189 | V14: =SUM(R14:U14) -> 1347.9499 | W14: =W10-W18 -> 534.51053 | X14: =X10-X18 -> 711.40616 | Y14: =Y10-Y18 -> 789.52419 | Z14: =Z10-Z18 -> 844.95259 | AA14: =SUM(W14:Z14) -> 2880.3935 | AB14: =AB10-AB18 -> 857.61302 | AC14: =AC10-AC18 -> 934.64279 | AD14: =AD10-AD18 -> 1006.6124 | AE14: =AE10-AE18 -> 1073.582 | AF14: =SUM(AB14:AE14) -> 3872.4502 | AG14: =AG10-AG18 -> 1074.8741 | AH14: =AH10-AH18 -> 1119.2539 | AI14: =AI10-AI18 -> 1159.0461 | AJ14: =AJ10-AJ18 -> 1194.3946 | AK14: =SUM(AG14:AJ14) -> 4547.5687
A15: COGSYY | B15: % yoy | H15: =IFERROR(H14/C14-1,"") | I15: =IFERROR(I14/D14-1,"") | J15: =IFERROR(J14/E14-1,"") | K15: =IFERROR(K14/F14-1,"") | L15: =IFERROR(L14/G14-1,"") -> 4.6790391 | M15: =IFERROR(M14/H14-1,"") -> 11.290404 | N15: =IFERROR(N14/I14-1,"") -> 10.0843 | O15: =IFERROR(O14/J14-1,"") -> 6.3963198 | ... AK15: =IFERROR(AK14/AF14-1,"") -> 0.17433885
A16: COGSQQ | B16: % qoq | H16: =IFERROR(H14/F14-1,"") | I16: =IFERROR(I14/H14-1,"") -> 1.0446829 | J16: =IFERROR(J14/I14-1,"") -> 0.97347062 | K16: =IFERROR(K14/J14-1,"") -> 0.80634061 | M16: =IFERROR(M14/K14-1,"") -> 0.68620308 | N16: =IFERROR(N14/M14-1,"") -> 0.84403046 | O16: =IFERROR(O14/N14-1,"") -> 0.31685532 | P16: =IFERROR(P14/O14-1,"") -> 0.27296606 | R16: =IFERROR(R14/P14-1,"") -> 0.42802902 | S16: =IFERROR(S14/R14-1,"") -> 0.19354951 | T16: =IFERROR(T14/S14-1,"") -> 0.17848732 | U16: =IFERROR(U14/T14-1,"") -> 0.13058326 | W16: =IFERROR(W14/U14-1,"") -> 0.29423977 | X16: =IFERROR(X14/W14-1,"") -> 0.33094883 | Y16: =IFERROR(Y14/X14-1,"") -> 0.10980793 | Z16: =IFERROR(Z14/Y14-1,"") -> 0.070204816 | AB16: =IFERROR(AB14/Z14-1,"") -> 0.014983596 | AC16: =IFERROR(AC14/AB14-1,"") -> 0.089818799 | AD16: =IFERROR(AD14/AC14-1,"") -> 0.077002222 | AE16: =IFERROR(AE14/AD14-1,"") -> 0.066529754 | AG16: =IFERROR(AG14/AE14-1,"") -> 0.0012035309 | AH16: =IFERROR(AH14/AG14-1,"") -> 0.041288386 | AI16: =IFERROR(AI14/AH14-1,"") -> 0.035552396 | AJ16: =IFERROR(AJ14/AI14-1,"") -> 0.030497879
A18: GP | B18: Gross Profit | G18: =G10-G14 -> 3.841 | H18: =H10-H14 -> 3.1368604 | I18: =I10-I14 -> 20.056063 | J18: =J10-J14 -> 55.863408 | K18: =K10-K14 -> 81.106668 | L18: =L10-L14 -> 160.857 | M18: =M10-M14 -> 129.852 | N18: =N10-N14 -> 286.883 | ... T18: =T10-T14 -> 999.385 | U18: =U$10*U21 -> 1129.8879 | V18: =V10-V14 -> 3754.0259 | W18: =W$10*W21 -> 1692.6167 | X18: =X$10*X21 -> 2252.7862 | Y18: =Y$10*Y21 -> 2500.1599 | Z18: =Z$10*Z21 -> 2675.6832 | AA18: =AA10-AA14 -> 9121.246 | AB18: =AB$10*AB21 -> 2954.0004 | AC18: =AC$10*AC21 -> 3219.3252 | AD18: =AD$10*AD21 -> 3467.2204 | AE18: =AE$10*AE21 -> 3697.8937 | AF18: =AF10-AF14 -> 13338.44 | AG18: =AG$10*AG21 -> 4043.5741 | AH18: =AH$10*AH21 -> 4210.5267 | AI18: =AI$10*AI21 -> 4360.2211 | AJ18: =AJ$10*AJ21 -> 4493.1986 | AK18: =AK10-AK14 -> 17107.52
A19: GPYY | B19: % yoy | H19: =IFERROR(H18/C18-1,"") | I19: =IFERROR(I18/D18-1,"") | J19: =IFERROR(J18/E18-1,"") | K19: =IFERROR(K18/F18-1,"") | L19: =IFERROR(L18/G18-1,"") -> 40.878938 | M19: =IFERROR(M18/H18-1,"") -> 40.39553 | N19: =IFERROR(N18/I18-1,"") -> 13.304054 | O19: =IFERROR(O18/J18-1,"") -> 6.8956514 | ... AK19: =IFERROR(AK18/AF18-1,"") -> 0.28257284
A20: GPQQ | B20: % qoq | H20: =IFERROR(H18/F18-1,"") | I20: =IFERROR(I18/H18-1,"") -> 5.393674 | J20: =IFERROR(J18/I18-1,"") -> 1.7853626 | K20: =IFERROR(K18/J18-1,"") -> 0.45187468 | M20: =IFERROR(M18/K18-1,"") -> 0.60100276 | N20: =IFERROR(N18/M18-1,"") -> 1.2093075 | O20: =IFERROR(O18/N18-1,"") -> 0.53748392 | P20: =IFERROR(P18/O18-1,"") -> 0.28224543 | R20: =IFERROR(R18/P18-1,"") -> 0.27646566 | S20: =IFERROR(S18/R18-1,"") -> 0.2505655 | T20: =IFERROR(T18/S18-1,"") -> 0.10695685 | U20: =IFERROR(U18/T18-1,"") -> 0.13058326 | W20: =IFERROR(W18/U18-1,"") -> 0.4980394 | X20: =IFERROR(X18/W18-1,"") -> 0.33094883 | Y20: =IFERROR(Y18/X18-1,"") -> 0.10980793 | Z20: =IFERROR(Z18/Y18-1,"") -> 0.070204816 | AB20: =IFERROR(AB18/Z18-1,"") -> 0.10401724 | AC20: =IFERROR(AC18/AB18-1,"") -> 0.089818799 | AD20: =IFERROR(AD18/AC18-1,"") -> 0.077002222 | AE20: =IFERROR(AE18/AD18-1,"") -> 0.066529754 | AG20: =IFERROR(AG18/AE18-1,"") -> 0.093480354 | AH20: =IFERROR(AH18/AG18-1,"") -> 0.041288386 | AI20: =IFERROR(AI18/AH18-1,"") -> 0.035552396 | AJ20: =IFERROR(AJ18/AI18-1,"") -> 0.030497879
A21: GPM | B21: Gross Margin | C21: =IFERROR(C18/C$10,"") | D21: =IFERROR(D18/D$10,"") | E21: =IFERROR(E18/E$10,"") | F21: =IFERROR(F18/F$10,"") | G21: =IFERROR(G18/G$10,"") -> 0.24264056 | H21: =IFERROR(H18/H$10,"") -> 0.39588407 | I21: =IFERROR(I18/I$10,"") -> 0.672039 | J21: =IFERROR(J18/J$10,"") -> 0.74307371 | ... T21: =IFERROR(T18/T$10,"") -> 0.73232401 | U21: =T21 -> 0.73232401 | V21: 0.74655307 | W21: 0.76 | X21: =W21 -> 0.76 | Y21: =X21 -> 0.76 | Z21: =Y21 -> 0.76 | AA21: =IFERROR(AA18/AA$10,"") -> 0.76 | AB21: 0.775 | AC21: =AB21 -> 0.775 | AD21: =AC21 -> 0.775 | AE21: =AD21 -> 0.775 | AF21: =IFERROR(AF18/AF$10,"") -> 0.775 | AG21: 0.79 | AH21: =AG21 -> 0.79 | AI21: =AH21 -> 0.79 | AJ21: =AI21 -> 0.79 | AK21: =IFERROR(AK18/AK$10,"") -> 0.79
B23: Technology and Infrastructure | G23: ='IS (GAAP)'!G23-'IS (Non-GAAP)'!G103 -> 17.482 | H23: ='IS (GAAP)'!H23-'IS (Non-GAAP)'!H103 -> 8.8592249 | I23: ='IS (GAAP)'!I23-'IS (Non-GAAP)'!I103 -> 17.162371 | J23: ='IS (GAAP)'!J23-'IS (Non-GAAP)'!J103 -> 39.900803 | K23: ='IS (GAAP)'!K23-'IS (Non-GAAP)'!K103 -> 65.932601 | L23: ='IS (GAAP)'!L23-'IS (Non-GAAP)'!L103 -> 124.755 | M23: ='IS (GAAP)'!M23-'IS (Non-GAAP)'!M103 -> 90.524 | N23: ='IS (GAAP)'!N23-'IS (Non-GAAP)'!N103 -> 180.806 | ... T23: ='IS (GAAP)'!T23-'IS (Non-GAAP)'!T103 -> 694.856 | U23: =P23*(1+U24) -> 895.17413 | V23: =SUM(R23:U23) -> 2719.0631 | W23: =R23*(1+W24) -> 1201.1231 | X23: =S23*(1+X24) -> 1580.4642 | Y23: =T23*(1+Y24) -> 1771.8828 | Z23: =U23*(1+Z24) -> 1879.8657 | AA23: =SUM(W23:Z23) -> 6433.3358 | AB23: =W23*(1+AB24) -> 2065.9317 | AC23: =X23*(1+AC24) -> 2244.2592 | AD23: =Y23*(1+AD24) -> 2427.4794 | AE23: =Z23*(1+AE24) -> 2669.4093 | AF23: =SUM(AB23:AE23) -> 9407.0796 | AG23: =AB23*(1+AG24) -> 2850.9858 | AH23: =AC23*(1+AH24) -> 3029.7499 | AI23: =AD23*(1+AI24) -> 3155.7233 | AJ23: =AE23*(1+AJ24) -> 3363.4557 | AK23: =SUM(AG23:AJ23) -> 12399.915
B24: % yoy | H24: =IFERROR(H23/C23-1,"") | I24: =IFERROR(I23/D23-1,"") | J24: =IFERROR(J23/E23-1,"") | K24: =IFERROR(K23/F23-1,"") | L24: =IFERROR(L23/G23-1,"") -> 6.1361972 | M24: =IFERROR(M23/H23-1,"") -> 9.2180496 | N24: =IFERROR(N23/I23-1,"") -> 9.5350246 | O24: =IFERROR(O23/J23-1,"") -> 6.1013107 | ... T24: =IFERROR(T23/O23-1,"") -> 1.452306 | U24: 1.26 | V24: =IFERROR(V23/Q23-1,"") -> 1.8598455 | W24: 1.37 | X24: 1.54 | Y24: 1.55 | Z24: 1.1 | AA24: =IFERROR(AA23/V23-1,"") -> 1.3660119 | AB24: 0.72 | AC24: 0.42 | AD24: 0.37 | AE24: 0.42 | AF24: =IFERROR(AF23/AA23-1,"") -> 0.4622398 | AG24: 0.38 | AH24: 0.35 | AI24: 0.3 | AJ24: 0.26 | AK24: =IFERROR(AK23/AF23-1,"") -> 0.31814709
B25: % qoq | H25: =IFERROR(H23/F23-1,"") | I25: =IFERROR(I23/H23-1,"") -> 0.93723165 | J25: =IFERROR(J23/I23-1,"") -> 1.3249004 | K25: =IFERROR(K23/J23-1,"") -> 0.65241288 | M25: =IFERROR(M23/K23-1,"") -> 0.37297784 | N25: =IFERROR(N23/M23-1,"") -> 0.99732668 | O25: =IFERROR(O23/N23-1,"") -> 0.56713826 | P25: =IFERROR(P23/O23-1,"") -> 0.39790911 | R25: =IFERROR(R23/P23-1,"") -> 0.27949941 | S25: =IFERROR(S23/R23-1,"") -> 0.22775516 | T25: =IFERROR(T23/S23-1,"") -> 0.1167189 | U25: =IFERROR(U23/T23-1,"") -> 0.28828726 | W25: =IFERROR(W23/U23-1,"") -> 0.34177593 | X25: 1.5 | Y25: =IFERROR(Y23/X23-1,"") -> 0.12111543 | Z25: =IFERROR(Z23/Y23-1,"") -> 0.060942453 | AB25: =IFERROR(AB23/Z23-1,"") -> 0.098978383 | AC25: =IFERROR(AC23/AB23-1,"") -> 0.086318154 | AD25: =IFERROR(AD23/AC23-1,"") -> 0.081639534 | AE25: =IFERROR(AE23/AD23-1,"") -> 0.09966298 | AG25: =IFERROR(AG23/AE23-1,"") -> 0.068021245 | AH25: =IFERROR(AH23/AG23-1,"") -> 0.062702542 | AI25: =IFERROR(AI23/AH23-1,"") -> 0.04157881 | AJ25: =IFERROR(AJ23/AI23-1,"") -> 0.065827196
B26: % of Total Revenue | C26: =IFERROR(C23/C$10,"") | D26: =IFERROR(D23/D$10,"") | E26: =IFERROR(E23/E$10,"") | F26: =IFERROR(F23/F$10,"") | G26: =IFERROR(G23/G$10,"") -> 1.1043588 | H26: =IFERROR(H23/H$10,"") -> 1.1180689 | I26: =IFERROR(I23/I$10,"") -> 0.57507709 | J26: =IFERROR(J23/J$10,"") -> 0.53074523 | ... AK26: =IFERROR(AK23/AK$10,"") -> 0.57260972
B27: Gross Margin (Including T&I) | C27: =IFERROR(C25/C$10,"") | D27: =IFERROR(D25/D$10,"") | E27: =IFERROR(E25/E$10,"") | F27: =IFERROR(F25/F$10,"") | G27: =(G18-G23)/G10 -> -0.86171826 | H27: =(H18-H23)/H10 -> -0.72218482 | I27: =(I18-I23)/I10 -> 0.096961901 | J27: =(J18-J23)/J10 -> 0.21232847 | K27: =(K18-K23)/K10 -> 0.13081443 | L27: =(L18-L23)/L10 -> 0.15768991 | M27: =(M18-M23)/M10 -> 0.20843315 | N27: =(N18-N23)/N10 -> 0.26829737 | ... AK27: =(AK18-AK23)/AK10 -> 0.21739028
B29: GAAP Implied R&D | G29: ='IS (GAAP)'!G31 -> 7.106 | L29: ='IS (GAAP)'!L31 -> 30.855 | M29: ='IS (GAAP)'!M31 -> 15.881 | N29: ='IS (GAAP)'!N31 -> 24.886 | O29: ='IS (GAAP)'!O31 -> 29.509 | P29: ='IS (GAAP)'!P31 -> 47.409 | Q29: ='IS (GAAP)'!Q31 -> 117.685 | R29: ='IS (GAAP)'!R31 -> 132.402 | S29: ='IS (GAAP)'!S31 -> 132.913 | ... AK29: ='IS (GAAP)'!AK31 -> 6024.7606
B30: % of Revenue | G30: ='IS (GAAP)'!G32 -> 0.4488945 | L30: ='IS (GAAP)'!L32 -> 0.13477154 | M30: ='IS (GAAP)'!M32 -> 0.084167179 | N30: ='IS (GAAP)'!N32 -> 0.062943413 | O30: ='IS (GAAP)'!O32 -> 0.050534215 | P30: ='IS (GAAP)'!P32 -> 0.063429351 | Q30: ='IS (GAAP)'!Q32 -> 0.06144064 | R30: ='IS (GAAP)'!R32 -> 0.13487947 | S30: ='IS (GAAP)'!S32 -> 0.10959294 | ... AK30: ='IS (GAAP)'!AK32 -> 0.27821454
B32: Sales & Marketing | G32: ='IS (GAAP)'!G34-'IS (Non-GAAP)'!G104 -> 2.407 | H32: ='IS (GAAP)'!H34-'IS (Non-GAAP)'!H104 -> 1.9425858 | I32: ='IS (GAAP)'!I34-'IS (Non-GAAP)'!I104 -> 2.4115328 | J32: ='IS (GAAP)'!J34-'IS (Non-GAAP)'!J104 -> 3.9969457 | K32: ='IS (GAAP)'!K34-'IS (Non-GAAP)'!K104 -> 4.5659357 | L32: ='IS (GAAP)'!L34-'IS (Non-GAAP)'!L104 -> 11.177 | M32: ='IS (GAAP)'!M34-'IS (Non-GAAP)'!M104 -> 3.183 | N32: ='IS (GAAP)'!N34-'IS (Non-GAAP)'!N104 -> 3.324 | ... T32: ='IS (GAAP)'!T34-'IS (Non-GAAP)'!T104 -> 34.835 | U32: =U$10*U35 -> 39.383868 | V32: =SUM(R32:U32) -> 110.25287 | W32: =W$10*W35 -> 35.634035 | X32: =X$10*X35 -> 47.427077 | Y32: =Y$10*Y35 -> 52.634946 | Z32: =Z$10*Z35 -> 52.809537 | AA32: =SUM(W32:Z32) -> 188.5056 | AB32: =AB$10*AB35 -> 57.174201 | AC32: =AC$10*AC35 -> 62.30952 | AD32: =AD$10*AD35 -> 67.107491 | AE32: =AE$10*AE35 -> 71.572136 | AF32: =SUM(AB32:AE32) -> 258.16335 | AG32: =AG$10*AG35 -> 76.776723 | AH32: =AH$10*AH35 -> 79.94671 | AI32: =AI$10*AI35 -> 82.789007 | AJ32: =AJ$10*AJ35 -> 85.313897 | AK32: =SUM(AG32:AJ32) -> 324.82634
B33: % yoy | H33: =IFERROR(H32/C32-1,"") | I33: =IFERROR(I32/D32-1,"") | J33: =IFERROR(J32/E32-1,"") | K33: =IFERROR(K32/F32-1,"") | L33: =IFERROR(L32/G32-1,"") -> 3.6435397 | M33: =IFERROR(M32/H32-1,"") -> 0.63853767 | N33: =IFERROR(N32/I32-1,"") -> 0.37837643 | O33: =IFERROR(O32/J32-1,"") -> -0.072541812 | ... AK33: =IFERROR(AK32/AF32-1,"") -> 0.25822019
B34: % qoq | H34: =IFERROR(H32/F32-1,"") | I34: =IFERROR(I32/H32-1,"") -> 0.2414035 | J34: =IFERROR(J32/I32-1,"") -> 0.65742952 | K34: =IFERROR(K32/J32-1,"") -> 0.14235621 | M34: =IFERROR(M32/K32-1,"") -> -0.30288112 | N34: =IFERROR(N32/M32-1,"") -> 0.044297832 | O34: =IFERROR(O32/N32-1,"") -> 0.11522262 | P34: =IFERROR(P32/O32-1,"") -> 0.28587807 | R34: =IFERROR(R32/P32-1,"") -> 0.62144018 | S34: =IFERROR(S32/R32-1,"") -> 2.6621814 | T34: =IFERROR(T32/S32-1,"") -> 0.23070129 | U34: =IFERROR(U32/T32-1,"") -> 0.13058326 | W34: =IFERROR(W32/U32-1,"") -> -0.095212403 | X34: =IFERROR(X32/W32-1,"") -> 0.33094883 | Y34: =IFERROR(Y32/X32-1,"") -> 0.10980793 | Z34: =IFERROR(Z32/Y32-1,"") -> 0.0033170152 | AB34: =IFERROR(AB32/Z32-1,"") -> 0.082649169 | AC34: =IFERROR(AC32/AB32-1,"") -> 0.089818799 | AD34: =IFERROR(AD32/AC32-1,"") -> 0.077002222 | AE34: =IFERROR(AE32/AD32-1,"") -> 0.066529754 | AG34: =IFERROR(AG32/AE32-1,"") -> 0.072718069 | AH34: =IFERROR(AH32/AG32-1,"") -> 0.041288386 | AI34: =IFERROR(AI32/AH32-1,"") -> 0.035552396 | AJ34: =IFERROR(AJ32/AI32-1,"") -> 0.030497879
B35: % of Total Revenue | C35: =IFERROR(C32/C$10,"") | D35: =IFERROR(D32/D$10,"") | E35: =IFERROR(E32/E$10,"") | F35: =IFERROR(F32/F$10,"") | G35: =IFERROR(G32/G$10,"") -> 0.15205306 | H35: =IFERROR(H32/H$10,"") -> 0.24516194 | I35: =IFERROR(I32/I$10,"") -> 0.080805694 | J35: =IFERROR(J32/J$10,"") -> 0.053165844 | ... T35: =IFERROR(T32/T$10,"") -> 0.025526205 | U35: =T35 -> 0.025526205 | V35: =IFERROR(V32/V$10,"") -> 0.021609837 | W35: 0.016 | X35: =W35 -> 0.016 | Y35: =X35 -> 0.016 | Z35: 0.015 | AA35: =IFERROR(AA32/AA$10,"") -> 0.015706654 | AB35: 0.015 | AC35: =AB35 -> 0.015 | AD35: =AC35 -> 0.015 | AE35: =AD35 -> 0.015 | AF35: =IFERROR(AF32/AF$10,"") -> 0.015 | AG35: 0.015 | AH35: =AG35 -> 0.015 | AI35: =AH35 -> 0.015 | AJ35: =AI35 -> 0.015 | AK35: =IFERROR(AK32/AK$10,"") -> 0.015
B36: Sales and Marketing Efficiency | M36: =M32/(M10-H10) -> 0.017608954 | N36: =N32/(N10-I10) -> 0.0090937095 | O36: =O32/(O10-J10) -> 0.0072863121 | P36: =P32/(P10-K10) -> 0.0075490973 | Q36: =Q32/(Q10-L10) -> 0.0088828349 | R36: =R32/(R10-M10) -> 0.0097471713 | S36: =S32/(S10-N10) -> 0.034627369 | T36: =T32/(T10-O10) -> 0.044618212 | ... AK36: =AK32/(AK10-AF10) -> 0.073089957
G37: =G38*19 -> 101.498
B38: General & Administrative | G38: ='IS (GAAP)'!G40-'IS (Non-GAAP)'!G105 -> 5.342 | H38: ='IS (GAAP)'!H40-'IS (Non-GAAP)'!H105 -> 4.1810156 | I38: ='IS (GAAP)'!I40-'IS (Non-GAAP)'!I105 -> 5.118516 | J38: ='IS (GAAP)'!J40-'IS (Non-GAAP)'!J105 -> 8.1593435 | K38: ='IS (GAAP)'!K40-'IS (Non-GAAP)'!K105 -> 12.383125 | L38: ='IS (GAAP)'!L40-'IS (Non-GAAP)'!L105 -> 24.222 | M38: ='IS (GAAP)'!M40-'IS (Non-GAAP)'!M105-M120-M121 -> 11.109 | N38: ='IS (GAAP)'!N40-'IS (Non-GAAP)'!N105-N120-N121 -> 17.372 | O38: ='IS (GAAP)'!O40-'IS (Non-GAAP)'!O105-O120-O121 -> 29.29 | P38: ='IS (GAAP)'!P40-'IS (Non-GAAP)'!P105-P120-P121 -> 44.01275 | Q38: ='IS (GAAP)'!Q40-'IS (Non-GAAP)'!Q105 -> 101.78375 | R38: ='IS (GAAP)'!R40-'IS (Non-GAAP)'!R105-R120-R121 -> 44.766 | S38: ='IS (GAAP)'!S40-'IS (Non-GAAP)'!S105-S120-S121 -> 52.499 | T38: ='IS (GAAP)'!T40-'IS (Non-GAAP)'!T105-T120-T121 -> 52.54 | U38: =U$10*U41 -> 58.629434 | V38: =SUM(R38:U38) -> 208.43443 | W38: =W$10*W41 -> 77.949452 | X38: =X$10*X41 -> 91.889962 | Y38: =Y$10*Y41 -> 98.690524 | Z38: =Z$10*Z41 -> 98.577803 | AA38: =SUM(W38:Z38) -> 367.10774 | AB38: =AB$10*AB41 -> 99.101949 | AC38: =AC$10*AC41 -> 108.00317 | AD38: =AD$10*AD41 -> 116.31965 | AE38: =AE$10*AE41 -> 124.05837 | AF38: =SUM(AB38:AE38) -> 447.48314 | AG38: =AG$10*AG41 -> 122.84276 | AH38: =AH$10*AH41 -> 127.91474 | AI38: =AI$10*AI41 -> 132.46241 | AJ38: =AJ$10*AJ41 -> 136.50223 | AK38: =SUM(AG38:AJ38) -> 519.72214
B39: % yoy | H39: =IFERROR(H38/C38-1,"") | I39: =IFERROR(I38/D38-1,"") | J39: =IFERROR(J38/E38-1,"") | K39: =IFERROR(K38/F38-1,"") | L39: =IFERROR(L38/G38-1,"") -> 3.5342568 | M39: =IFERROR(M38/H38-1,"") -> 1.6570099 | N39: =IFERROR(N38/I38-1,"") -> 2.3939525 | O39: =IFERROR(O38/J38-1,"") -> 2.5897496 | ... AK39: =IFERROR(AK38/AF38-1,"") -> 0.16143403
B40: % qoq | H40: =IFERROR(H38/F38-1,"") | I40: =IFERROR(I38/H38-1,"") -> 0.22422789 | J40: =IFERROR(J38/I38-1,"") -> 0.59408383 | K40: =IFERROR(K38/J38-1,"") -> 0.51766191 | M40: =IFERROR(M38/K38-1,"") -> -0.10289203 | N40: =IFERROR(N38/M38-1,"") -> 0.56377712 | O40: =IFERROR(O38/N38-1,"") -> 0.68604651 | P40: =IFERROR(P38/O38-1,"") -> 0.50265449 | R40: =IFERROR(R38/P38-1,"") -> 0.017114359 | S40: =IFERROR(S38/R38-1,"") -> 0.17274271 | T40: =IFERROR(T38/S38-1,"") -> 0.00078096726 | U40: =IFERROR(U38/T38-1,"") -> 0.11590091 | W40: =IFERROR(W38/U38-1,"") -> 0.32952762 | X40: =IFERROR(X38/W38-1,"") -> 0.17884039 | Y40: =IFERROR(Y38/X38-1,"") -> 0.07400767 | Z40: =IFERROR(Z38/Y38-1,"") -> -0.0011421715 | AB40: =IFERROR(AB38/Z38-1,"") -> 0.0053170851 | AC40: =IFERROR(AC38/AB38-1,"") -> 0.089818799 | AD40: =IFERROR(AD38/AC38-1,"") -> 0.077002222 | AE40: =IFERROR(AE38/AD38-1,"") -> 0.066529754 | AG40: =IFERROR(AG38/AE38-1,"") -> -0.0097987057 | AH40: =IFERROR(AH38/AG38-1,"") -> 0.041288386 | AI40: =IFERROR(AI38/AH38-1,"") -> 0.035552396 | AJ40: =IFERROR(AJ38/AI38-1,"") -> 0.030497879
B41: % of Total Revenue | C41: =IFERROR(C38/C$10,"") | D41: =IFERROR(D38/D$10,"") | E41: =IFERROR(E38/E$10,"") | F41: =IFERROR(F38/F$10,"") | G41: =IFERROR(G38/G$10,"") -> 0.33746052 | H41: =IFERROR(H38/H$10,"") -> 0.52766055 | I41: =IFERROR(I38/I$10,"") -> 0.17151134 | J41: =IFERROR(J38/J$10,"") -> 0.10853247 | ... T41: =IFERROR(T38/T$10,"") -> 0.038499981 | U41: 0.038 | V41: =IFERROR(V38/V$10,"") -> 0.040853669 | W41: =U41-0.3% -> 0.035 | X41: =W41-0.4% -> 0.031 | Y41: =X41-0.1% -> 0.03 | Z41: =Y41-0.2% -> 0.028 | AA41: =IFERROR(AA38/AA$10,"") -> 0.030588133 | AB41: =Z41-0.2% -> 0.026 | AC41: =AB41 -> 0.026 | AD41: =AC41 -> 0.026 | AE41: =AD41 -> 0.026 | AF41: =IFERROR(AF38/AF$10,"") -> 0.026 | AG41: =AE41-0.2% -> 0.024 | AH41: =AG41 -> 0.024 | AI41: =AH41 -> 0.024 | AJ41: =AI41 -> 0.024 | AK41: =IFERROR(AK38/AK$10,"") -> 0.024
A43: OPEX | B43: Total Operating Expenses | G43: =G38+G32+G23 -> 25.231 | H43: =H38+H32+H23 -> 14.982826 | I43: =I38+I32+I23 -> 24.69242 | J43: =J38+J32+J23 -> 52.057092 | K43: =K38+K32+K23 -> 82.881662 | L43: =L38+L32+L23 -> 160.154 | M43: =M38+M32+M23 -> 104.816 | N43: =N38+N32+N23 -> 201.502 | ... AK43: =AK38+AK32+AK23 -> 13244.463
A44: OPEXYY | B44: % yoy | H44: =IFERROR(H43/C43-1,"") | I44: =IFERROR(I43/D43-1,"") | J44: =IFERROR(J43/E43-1,"") | K44: =IFERROR(K43/F43-1,"") | L44: =IFERROR(L43/G43-1,"") -> 5.347509 | M44: =IFERROR(M43/H43-1,"") -> 5.9957428 | N44: =IFERROR(N43/I43-1,"") -> 7.1604801 | O44: =IFERROR(O43/J43-1,"") -> 5.0768857 | ... AK44: =IFERROR(AK43/AF43-1,"") -> 0.30968277
A45: OPEXQQ | B45: % qoq | H45: =IFERROR(H43/F43-1,"") | I45: =IFERROR(I43/H43-1,"") -> 0.64804818 | J45: =IFERROR(J43/I43-1,"") -> 1.1082216 | K45: =IFERROR(K43/J43-1,"") -> 0.59213006 | M45: =IFERROR(M43/K43-1,"") -> 0.26464646 | N45: =IFERROR(N43/M43-1,"") -> 0.92243551 | O45: =IFERROR(O43/N43-1,"") -> 0.56993479 | P45: =IFERROR(P43/O43-1,"") -> 0.40629455 | R45: =IFERROR(R43/P43-1,"") -> 0.2572047 | S45: =IFERROR(S43/R43-1,"") -> 0.25699359 | T45: =IFERROR(T43/S43-1,"") -> 0.11265031 | U45: =IFERROR(U43/T43-1,"") -> 0.2696856 | W45: =IFERROR(W43/U43-1,"") -> 0.32372455 | X45: =IFERROR(X43/W43-1,"") -> 0.3081103 | Y45: =IFERROR(Y43/X43-1,"") -> 0.11828657 | Z45: =IFERROR(Z43/Y43-1,"") -> 0.056179434 | AB45: =IFERROR(AB43/Z43-1,"") -> 0.094008415 | AC45: =IFERROR(AC43/AB43-1,"") -> 0.086564336 | AD45: =IFERROR(AD43/AC43-1,"") -> 0.081312439 | AE45: =IFERROR(AE43/AD43-1,"") -> 0.097335232 | AG45: =IFERROR(AG43/AE43-1,"") -> 0.064768916 | AH45: =IFERROR(AH43/AG43-1,"") -> 0.061301285 | AI45: =IFERROR(AI43/AH43-1,"") -> 0.041191902 | AJ45: =IFERROR(AJ43/AI43-1,"") -> 0.063571265
A47: OI | B47: Non-GAAP Operating Income | G47: =G18-G43 -> -21.39 | H47: =H18-H43 -> -11.845966 | I47: =I18-I43 -> -4.6363566 | J47: =J18-J43 -> 3.8063159 | K47: =K18-K43 -> -1.7749934 | L47: =L18-L43 -> 0.703 | M47: =M18-M43 -> 25.036 | N47: =N18-N43 -> 85.381 | ... AK47: =AK18-AK43 -> 3863.0573
A48: OIYY | B48: % yoy | H48: =IFERROR(H47/C47-1,"") | I48: =IFERROR(I47/D47-1,"") | J48: =IFERROR(J47/E47-1,"") | K48: =IFERROR(K47/F47-1,"") | L48: =IFERROR(L47/G47-1,"") -> -1.0328658 | M48: =IFERROR(M47/H47-1,"") -> -3.1134621 | N48: =IFERROR(N47/I47-1,"") -> -19.415538 | O48: =IFERROR(O47/J47-1,"") -> 31.770007 | ... AK48: =IFERROR(AK47/AF47-1,"") -> 0.19758227
A49: OIQQ | B49: % qoq | H49: =IFERROR(H47/F47-1,"") | I49: =IFERROR(I47/H47-1,"") -> -0.60861304 | J49: =IFERROR(J47/I47-1,"") -> -1.8209713 | K49: =IFERROR(K47/J47-1,"") -> -1.4663284 | M49: =IFERROR(M47/K47-1,"") -> -15.104841 | N49: =IFERROR(N47/M47-1,"") -> 2.4103291 | O49: =IFERROR(O47/N47-1,"") -> 0.46089879 | P49: =IFERROR(P47/O47-1,"") -> -0.032365132 | R49: =IFERROR(R47/P47-1,"") -> 0.34745973 | S49: =IFERROR(S47/R47-1,"") -> 0.22845917 | T49: =IFERROR(T47/S47-1,"") -> 0.086922137 | U49: =IFERROR(U47/T47-1,"") -> -0.37049047 | W49: =IFERROR(W47/U47-1,"") -> 1.764511 | X49: =IFERROR(X47/W47-1,"") -> 0.4104015 | Y49: =IFERROR(Y47/X47-1,"") -> 0.082450918 | Z49: =IFERROR(Z47/Y47-1,"") -> 0.11695696 | AB49: =IFERROR(AB47/Z47-1,"") -> 0.13556522 | AC49: =IFERROR(AC47/AB47-1,"") -> 0.099701511 | AD49: =IFERROR(AD47/AC47-1,"") -> 0.0640699 | AE49: =IFERROR(AE47/AD47-1,"") -> -0.027396359 | AG49: =IFERROR(AG47/AE47-1,"") -> 0.19224847 | AH49: =IFERROR(AH47/AG47-1,"") -> -0.020195375 | AI49: =IFERROR(AI47/AH47-1,"") -> 0.016785577 | AJ49: =IFERROR(AJ47/AI47-1,"") -> -0.08220362
A50: OPM | B50: Operating Margin | C50: =IFERROR(C47/C$10,"") | D50: =IFERROR(D47/D$10,"") | E50: =IFERROR(E47/E$10,"") | F50: =IFERROR(F47/F$10,"") | G50: =IFERROR(G47/G$10,"") -> -1.3512318 | H50: =IFERROR(H47/H$10,"") -> -1.4950073 | I50: =IFERROR(I47/I$10,"") -> -0.15535514 | J50: =IFERROR(J47/J$10,"") -> 0.05063016 | ... AK50: =IFERROR(AK47/AK$10,"") -> 0.17839028
B52: Interest Expense + OID Amortization | G52: ='IS (GAAP)'!G55 -> 0 | H52: ='IS (GAAP)'!H55 -> 0 | I52: ='IS (GAAP)'!I55 -> 0 | J52: ='IS (GAAP)'!J55 -> 0 | K52: ='IS (GAAP)'!K55 -> 0 | L52: ='IS (GAAP)'!L55 -> 0 | M52: ='IS (GAAP)'!M55 -> 72.833 | N52: ='IS (GAAP)'!N55 -> 107.453 | ... T52: ='IS (GAAP)'!T55 -> 248.791 | U52: ='Debt Model'!U66+'Debt Model'!U67 -> 418.25762 | V52: ='Debt Model'!V66+'Debt Model'!V67 -> 1313.2486 | W52: ='Debt Model'!W66+'Debt Model'!W67 -> 532.78381 | X52: ='Debt Model'!X66+'Debt Model'!X67 -> 635.75706 | Y52: ='Debt Model'!Y66+'Debt Model'!Y67 -> 700.48071 | Z52: ='Debt Model'!Z66+'Debt Model'!Z67 -> 722.41582 | AA52: ='Debt Model'!AA66+'Debt Model'!AA67 -> 2591.4374 | AB52: ='Debt Model'!AB66+'Debt Model'!AB67 -> 629.64265 | ... AK52: ='Debt Model'!AK66+'Debt Model'!AK67 -> 3963.3661
B53: Capitalized Interest | G53: ='IS (GAAP)'!G56 -> 0 | H53: ='IS (GAAP)'!H56 -> 0 | I53: ='IS (GAAP)'!I56 -> 0 | J53: ='IS (GAAP)'!J56 -> 0 | K53: ='IS (GAAP)'!K56 -> 0 | L53: ='IS (GAAP)'!L56 -> 0 | M53: ='IS (GAAP)'!M56 -> -32.177 | N53: ='IS (GAAP)'!N56 -> -40.687 | ... T53: ='IS (GAAP)'!T56 -> -61.764 | U53: =-'Revenue and CapEx Build'!U93 -> -92.646 | V53: =-'Revenue and CapEx Build'!V93 -> -190.688 | W53: =-'Revenue and CapEx Build'!W93 -> -69.97076 | X53: =-'Revenue and CapEx Build'!X93 -> -71.370176 | Y53: =-'Revenue and CapEx Build'!Y93 -> -74.938684 | Z53: =-'Revenue and CapEx Build'!Z93 -> -77.186845 | AA53: =-'Revenue and CapEx Build'!AA93 -> -293.46647 | AB53: =-'Revenue and CapEx Build'!AB93 -> -65.351902 | ... AK53: =-'Revenue and CapEx Build'!AK93 -> -426.16031
B54: Interest Expense, Net | G54: ='IS (GAAP)'!G57 -> 9.444 | H54: ='IS (GAAP)'!H57 -> 4.2742474 | I54: ='IS (GAAP)'!I57 -> 8.4537894 | J54: ='IS (GAAP)'!J57 -> -0.41398799 | K54: ='IS (GAAP)'!K57 -> 16.089951 | L54: ='IS (GAAP)'!L57 -> 28.404 | M54: ='IS (GAAP)'!M57 -> 40.656 | N54: ='IS (GAAP)'!N57 -> 66.766 | ... T54: ='IS (GAAP)'!T57 -> 310.555 | U54: =SUM(U52:U53) -> 325.61162 | V54: =SUM(V52:V53) -> 1122.5606 | W54: =SUM(W52:W53) -> 462.81305 | X54: =SUM(X52:X53) -> 564.38688 | Y54: =SUM(Y52:Y53) -> 625.54203 | Z54: =SUM(Z52:Z53) -> 645.22897 | AA54: =SUM(AA52:AA53) -> 2297.9709 | AB54: =SUM(AB52:AB53) -> 564.29075 | ... AK54: =SUM(AK52:AK53) -> 3537.2058
B55: % yoy | H55: =IFERROR(H54/C54-1,"") | I55: =IFERROR(I54/D54-1,"") | J55: =IFERROR(J54/E54-1,"") | K55: =IFERROR(K54/F54-1,"") | L55: =IFERROR(L54/G54-1,"") -> 2.0076239 | M55: =IFERROR(M54/H54-1,"") -> 8.51185 | N55: =IFERROR(N54/I54-1,"") -> 6.89776 | O55: =IFERROR(O54/J54-1,"") -> -253.12084 | ... AK55: =IFERROR(AK54/AF54-1,"") -> 0.21726298
B57: Loss on Fair Value Adjustments | G57: ='IS (GAAP)'!G60+G123 -> 0 | H57: ='IS (GAAP)'!H60+H123 -> 0 | I57: ='IS (GAAP)'!I60+I123 -> 0 | J57: ='IS (GAAP)'!J60+J123 -> 390.485 | K57: ='IS (GAAP)'!K60+K123 -> 143.467 | L57: ='IS (GAAP)'!L60+L123 -> 0 | M57: ='IS (GAAP)'!M60+M123 -> 0 | N57: ='IS (GAAP)'!N60+N123 -> 0 | ... T57: ='IS (GAAP)'!T60+T123 -> 0 | U57: =T57 -> 0 | V57: =SUM(R57:U57) -> 0 | W57: =U57 -> 0 | X57: =W57 -> 0 | Y57: =X57 -> 0 | Z57: =Y57 -> 0 | AA57: =SUM(W57:Z57) -> 0 | AB57: =Z57 -> 0 | AC57: =AB57 -> 0 | AD57: =AC57 -> 0 | AE57: =AD57 -> 0 | AF57: =SUM(AB57:AE57) -> 0 | AG57: =AE57 -> 0 | AH57: =AG57 -> 0 | AI57: =AH57 -> 0 | AJ57: =AI57 -> 0 | AK57: =SUM(AG57:AJ57) -> 0
A58: OTHI | B58: Other Income, Net | G58: ='IS (GAAP)'!G61+G124 -> 0.192 | H58: ='IS (GAAP)'!H61+H124 -> 0 | I58: ='IS (GAAP)'!I61+I124 -> 0 | J58: ='IS (GAAP)'!J61+J124 -> 0 | K58: ='IS (GAAP)'!K61+K124 -> 0 | L58: ='IS (GAAP)'!L61+L124 -> 18.76 | M58: ='IS (GAAP)'!M61+M122+M124 -> 7.46 | N58: ='IS (GAAP)'!N61+N122+N124 -> 16.406 | O58: ='IS (GAAP)'!O61+O122+O124 -> 21.368 | P58: ='IS (GAAP)'!P61+P122+P124 -> 14.084 | Q58: ='IS (GAAP)'!Q61+Q124 -> 59.318 | R58: ='IS (GAAP)'!R61+R122+R124 -> -2.318 | S58: ='IS (GAAP)'!S61+S122+S124 -> 2.82 | T58: ='IS (GAAP)'!T61+T122+T124 -> 24.293 | U58: =U128 -> 25.233874 | V58: =V128 -> 50.028874 | W58: =W128 -> 19.572695 | X58: =X128 -> 18.085712 | Y58: =Y128 -> 18.215892 | Z58: =Z128 -> 18.782922 | AA58: =AA128 -> 74.657221 | AB58: =AB128 -> 23.853752 | ... AK58: =AK128 -> 107.27351
B59: Non-GAAP Income Before Taxes | G59: =G47+SUM(G57:G58)-G54 -> -30.642 | H59: =H47+SUM(H57:H58)-H54 -> -16.120213 | I59: =I47+SUM(I57:I58)-I54 -> -13.090146 | J59: =J47+SUM(J57:J58)-J54 -> 394.7053 | K59: =K47+SUM(K57:K58)-K54 -> 125.60206 | L59: =L47+SUM(L57:L58)-L54 -> -8.941 | M59: =M47+SUM(M57:M58)-M54 -> -8.16 | N59: =N47+SUM(N57:N58)-N54 -> 35.021 | ... AK59: =AK47+SUM(AK57:AK58)-AK54 -> 433.12503
A61: TAXES | B61: Provision for (Benefit from) Income Taxes | G61: ='IS (GAAP)'!G64 -> -4.15 | H61: ='IS (GAAP)'!H64 -> 0 | I61: ='IS (GAAP)'!I64 -> 0 | J61: ='IS (GAAP)'!J64 -> 0 | K61: ='IS (GAAP)'!K64 -> 0 | L61: ='IS (GAAP)'!L64 -> 35.701 | M61: ='IS (GAAP)'!M64-M125 -> 15.399 | N61: ='IS (GAAP)'!N64-N125 -> 40.151 | O61: ='IS (GAAP)'!O64-O125 -> 41.659 | P61: ='IS (GAAP)'!P64-P125 -> 22.038 | Q61: ='IS (GAAP)'!Q64 -> 119.247 | R61: ='IS (GAAP)'!R64-R125 -> 46.036 | S61: ='IS (GAAP)'!S64-S125 -> 66.448 | T61: ='IS (GAAP)'!T64-T125 -> -28.138 | U61: =U59*U62 -> 65.470894 | V61: =SUM(R61:U61) -> 149.81689 | W61: =W59*W62 -> 32.665141 | X61: =X59*X62 -> 6.6481212 | Y61: =Y59*Y62 -> 15.187231 | Z61: =Z59*Z62 -> -8.9920716 | AA61: =SUM(W61:Z61) -> 45.508422 | AB61: =AB59*AB62 -> 153.08441 | AC61: =AC59*AC62 -> -30.179843 | AD61: =AD59*AD62 -> -25.764935 | AE61: =AE59*AE62 -> -10.411007 | AF61: =SUM(AB61:AE61) -> 86.728625 | AG61: =AG59*AG62 -> 246.37397 | AH61: =AH59*AH62 -> -27.870481 | AI61: =AI59*AI62 -> -19.167803 | AJ61: =AJ59*AJ62 -> 9.4910138 | AK61: =SUM(AG61:AJ61) -> 208.8267
B62: Effective Tax Rate | G62: =G61/G59 -> 0.13543502 | H62: =H61/H59 -> 0 | I62: =I61/I59 -> 0 | J62: =J61/J59 -> 0 | K62: =K61/K59 -> 0 | L62: =L61/L59 -> -3.9929538 | M62: =M61/M59 -> -1.8871324 | N62: =N61/N59 -> 1.1464835 | ... T62: =T61/T59 -> 0.40715981 | U62: -0.4 | V62: =V61/V59 -> -0.42053129 | W62: -0.5 | X62: -0.5 | Y62: -0.5 | Z62: -0.5 | AA62: =AA61/AA59 -> -0.5 | AB62: 0.8 | AC62: -0.3 | AD62: =AC62 -> -0.3 | AE62: =AD62 -> -0.3 | AF62: =AF61/AF59 -> 0.21023008 | AG62: 0.8 | AH62: -0.3 | AI62: =AH62 -> -0.3 | AJ62: =AI62 -> -0.3 | AK62: =AK61/AK59 -> 0.48213954
B64: Non-GAAP Net Income (Loss) from Continuing Operations | G64: =G59-G61 -> -26.492 | H64: =H59-H61 -> -16.120213 | I64: =I59-I61 -> -13.090146 | J64: =J59-J61 -> 394.7053 | K64: =K59-K61 -> 125.60206 | L64: =L59-L61 -> -44.642 | M64: =M59-M61 -> -23.559 | N64: =N59-N61 -> -5.13 | ... AK64: =AK59-AK61 -> 224.29833
A66: EPSB | B66: Non-GAAP EPS from Continuing Operations (Basic) | G66: =IFERROR(G64/G86,"") -> -0.14666283 | H66: =IFERROR(H64/H86,"") | I66: =IFERROR(I64/I86,"") | J66: =IFERROR(J64/J86,"") | K66: =IFERROR(K64/K86,"") | L66: =IFERROR(L64/L86,"") -> -0.23231198 | M66: =IFERROR(M64/M86,"") -> -0.11259965 | N66: =IFERROR(N64/N86,"") | ... AK66: =IFERROR(AK64/AK86,"") -> 0.4218001
A67: EPSBYY | B67: % yoy | H67: =IFERROR(H66/C66-1,"") | I67: =IFERROR(I66/D66-1,"") | J67: =IFERROR(J66/E66-1,"") | K67: =IFERROR(K66/F66-1,"") | L67: =IFERROR(L66/G66-1,"") -> 0.5839868 | M67: =IFERROR(M66/H66-1,"") | N67: =IFERROR(N66/I66-1,"") | O67: =IFERROR(O66/J66-1,"") | ... AK67: =IFERROR(AK66/AF66-1,"") -> -0.32785043
B68: % qoq | H68: =IFERROR(H66/F66-1,"") | I68: =IFERROR(I66/H66-1,"") | J68: =IFERROR(J66/I66-1,"") | K68: =IFERROR(K66/J66-1,"") | M68: =IFERROR(M66/K66-1,"") | N68: =IFERROR(N66/M66-1,"") | O68: =IFERROR(O66/N66-1,"") | P68: =IFERROR(P66/O66-1,"") | R68: =IFERROR(R66/P66-1,"") | S68: =IFERROR(S66/R66-1,"") -> -0.55852892 | T68: =IFERROR(T66/S66-1,"") -> -0.69389357 | U68: =IFERROR(U66/T66-1,"") -> 4.5763422 | W68: =IFERROR(W66/U66-1,"") -> -0.57489961 | X68: =IFERROR(X66/W66-1,"") -> -0.79769044 | Y68: =IFERROR(Y66/X66-1,"") -> 1.2708147 | Z68: =IFERROR(Z66/Y66-1,"") -> -1.5885497 | AB68: =IFERROR(AB66/Z66-1,"") -> 0.4102366 | AC68: =IFERROR(AC66/AB66-1,"") -> 2.3968011 | AD68: =IFERROR(AD66/AC66-1,"") -> -0.15137839 | AE68: =IFERROR(AE66/AD66-1,"") -> -0.59833341 | AG68: =IFERROR(AG66/AE66-1,"") -> 0.35713177 | AH68: =IFERROR(AH66/AG66-1,"") -> 0.94909832 | AI68: =IFERROR(AI66/AH66-1,"") -> -0.31635618 | AJ68: =IFERROR(AJ66/AI66-1,"") -> -1.4922008
A70: EPS | B70: Non-GAAP EPS from Continuing Operations (Diluted) | G70: =IFERROR(G64/G87,"") -> -0.14666283 | H70: =IFERROR(H64/H87,"") | I70: =IFERROR(I64/I87,"") | J70: =IFERROR(J64/J87,"") | K70: =IFERROR(K64/K87,"") | L70: =IFERROR(L64/L87,"") -> -0.23231198 | M70: =IFERROR(M64/M87,"") -> -0.11259965 | N70: =IFERROR(N64/N87,"") | ... AK70: =IFERROR(AK64/AK87,"") -> 0.4218001
A71: EPSYY | B71: % yoy | H71: =IFERROR(H70/C70-1,"") | I71: =IFERROR(I70/D70-1,"") | J71: =IFERROR(J70/E70-1,"") | K71: =IFERROR(K70/F70-1,"") | L71: =IFERROR(L70/G70-1,"") -> 0.5839868 | M71: =IFERROR(M70/H70-1,"") | N71: =IFERROR(N70/I70-1,"") | O71: =IFERROR(O70/J70-1,"") | ... AK71: =IFERROR(AK70/AF70-1,"") -> -0.32785043
A72: EPSQQ | B72: % qoq | H72: =IFERROR(H70/F70-1,"") | I72: =IFERROR(I70/H70-1,"") | J72: =IFERROR(J70/I70-1,"") | K72: =IFERROR(K70/J70-1,"") | M72: =IFERROR(M70/K70-1,"") | N72: =IFERROR(N70/M70-1,"") | O72: =IFERROR(O70/N70-1,"") | P72: =IFERROR(P70/O70-1,"") | R72: =IFERROR(R70/P70-1,"") | S72: =IFERROR(S70/R70-1,"") -> -0.55190527 | T72: =IFERROR(T70/S70-1,"") -> -0.69389357 | U72: =IFERROR(U70/T70-1,"") -> 4.5763422 | W72: =IFERROR(W70/U70-1,"") -> -0.57489961 | X72: =IFERROR(X70/W70-1,"") -> -0.79769044 | Y72: =IFERROR(Y70/X70-1,"") -> 1.2708147 | Z72: =IFERROR(Z70/Y70-1,"") -> -1.5885497 | AB72: =IFERROR(AB70/Z70-1,"") -> 0.4102366 | AC72: =IFERROR(AC70/AB70-1,"") -> 2.3968011 | AD72: =IFERROR(AD70/AC70-1,"") -> -0.15137839 | AE72: =IFERROR(AE70/AD70-1,"") -> -0.59833341 | AG72: =IFERROR(AG70/AE70-1,"") -> 0.35713177 | AH72: =IFERROR(AH70/AG70-1,"") -> 0.94909832 | AI72: =IFERROR(AI70/AH70-1,"") -> -0.31635618 | AJ72: =IFERROR(AJ70/AI70-1,"") -> -1.4922008
B74: Net Loss from Discontinued Operations, Net of Tax | G74: ='IS (GAAP)'!G77 -> -0.189 | H74: ='IS (GAAP)'!H77 -> 0 | I74: ='IS (GAAP)'!I77 -> 0 | J74: ='IS (GAAP)'!J77 -> 0 | K74: ='IS (GAAP)'!K77 -> 0 | L74: ='IS (GAAP)'!L77 -> 0 | M74: ='IS (GAAP)'!M77 -> 0 | N74: ='IS (GAAP)'!N77 -> 0 | ... T74: ='IS (GAAP)'!T77 -> 0
B75: Net Income (Loss) | G75: =G64+G74 -> -26.681 | H75: =H64+H74 -> -16.120213 | I75: =I64+I74 -> -13.090146 | J75: =J64+J74 -> 394.7053 | K75: =K64+K74 -> 125.60206 | L75: =L64+L74 -> -44.642 | M75: =M64+M74 -> -23.559 | N75: =N64+N74 -> -5.13 | ... AK75: =AK64+AK74 -> 224.29833
W76: =W75/W10 -> -0.044000821 | X76: =X75/X10 -> -0.006728431 | Y76: =Y75/Y10 -> -0.013849869 | Z76: =Z75/Z10 -> 0.0076623133 | AA76: =AA75/AA10 -> -0.011375551 | AB76: =AB75/AB10 -> 0.010040657 | AC76: =AC75/AC10 -> 0.031482987 | AD76: =AD75/AD10 -> 0.024955795 | ... AK76: =AK75/AK10 -> 0.010357765
A78: EPSB | B78: Non-GAAP EPS (Basic) | G78: =IFERROR(G75/G86,"") -> -0.14770915 | H78: =IFERROR(H75/H86,"") | I78: =IFERROR(I75/I86,"") | J78: =IFERROR(J75/J86,"") | K78: =IFERROR(K75/K86,"") | L78: =IFERROR(L75/L86,"") -> -0.23231198 | M78: =IFERROR(M75/M86,"") -> -0.11259965 | N78: =IFERROR(N75/N86,"") | ... AK78: =IFERROR(AK75/AK86,"") -> 0.4218001
A79: EPSBYY | B79: % yoy | H79: =IFERROR(H78/C78-1,"") | I79: =IFERROR(I78/D78-1,"") | J79: =IFERROR(J78/E78-1,"") | K79: =IFERROR(K78/F78-1,"") | L79: =IFERROR(L78/G78-1,"") -> 0.57276632 | M79: =IFERROR(M78/H78-1,"") | N79: =IFERROR(N78/I78-1,"") | O79: =IFERROR(O78/J78-1,"") | ... AK79: =IFERROR(AK78/AF78-1,"") -> -0.32785043
B80: % qoq | H80: =IFERROR(H78/F78-1,"") | I80: =IFERROR(I78/H78-1,"") | J80: =IFERROR(J78/I78-1,"") | K80: =IFERROR(K78/J78-1,"") | M80: =IFERROR(M78/K78-1,"") | N80: =IFERROR(N78/M78-1,"") | O80: =IFERROR(O78/N78-1,"") | P80: =IFERROR(P78/O78-1,"") | R80: =IFERROR(R78/P78-1,"") | S80: =IFERROR(S78/R78-1,"") -> -0.55852892 | T80: =IFERROR(T78/S78-1,"") -> -0.69389357 | U80: =IFERROR(U78/T78-1,"") -> 4.5763422 | W80: =IFERROR(W78/U78-1,"") -> -0.57489961 | X80: =IFERROR(X78/W78-1,"") -> -0.79769044 | Y80: =IFERROR(Y78/X78-1,"") -> 1.2708147 | Z80: =IFERROR(Z78/Y78-1,"") -> -1.5885497 | AB80: =IFERROR(AB78/Z78-1,"") -> 0.4102366 | AC80: =IFERROR(AC78/AB78-1,"") -> 2.3968011 | AD80: =IFERROR(AD78/AC78-1,"") -> -0.15137839 | AE80: =IFERROR(AE78/AD78-1,"") -> -0.59833341 | AG80: =IFERROR(AG78/AE78-1,"") -> 0.35713177 | AH80: =IFERROR(AH78/AG78-1,"") -> 0.94909832 | AI80: =IFERROR(AI78/AH78-1,"") -> -0.31635618 | AJ80: =IFERROR(AJ78/AI78-1,"") -> -1.4922008
A82: EPS | B82: Non-GAAP EPS (Diluted) | G82: =IFERROR(G75/G87,"") -> -0.14770915 | H82: =IFERROR(H75/H87,"") | I82: =IFERROR(I75/I87,"") | J82: =IFERROR(J75/J87,"") | K82: =IFERROR(K75/K87,"") | L82: =IFERROR(L75/L87,"") -> -0.23231198 | M82: =IFERROR(M75/M87,"") -> -0.11259965 | N82: =IFERROR(N75/N87,"") | ... AK82: =IFERROR(AK75/AK87,"") -> 0.4218001
A83: EPSYY | B83: % yoy | H83: =IFERROR(H82/C82-1,"") | I83: =IFERROR(I82/D82-1,"") | J83: =IFERROR(J82/E82-1,"") | K83: =IFERROR(K82/F82-1,"") | L83: =IFERROR(L82/G82-1,"") -> 0.57276632 | M83: =IFERROR(M82/H82-1,"") | N83: =IFERROR(N82/I82-1,"") | O83: =IFERROR(O82/J82-1,"") | ... AK83: =IFERROR(AK82/AF82-1,"") -> -0.32785043
A84: EPSQQ | B84: % qoq | H84: =IFERROR(H82/F82-1,"") | I84: =IFERROR(I82/H82-1,"") | J84: =IFERROR(J82/I82-1,"") | K84: =IFERROR(K82/J82-1,"") | M84: =IFERROR(M82/K82-1,"") | N84: =IFERROR(N82/M82-1,"") | O84: =IFERROR(O82/N82-1,"") | P84: =IFERROR(P82/O82-1,"") | R84: =IFERROR(R82/P82-1,"") | S84: =IFERROR(S82/R82-1,"") -> -0.55190527 | T84: =IFERROR(T82/S82-1,"") -> -0.69389357 | U84: =IFERROR(U82/T82-1,"") -> 4.5763422 | W84: =IFERROR(W82/U82-1,"") -> -0.57489961 | X84: =IFERROR(X82/W82-1,"") -> -0.79769044 | Y84: =IFERROR(Y82/X82-1,"") -> 1.2708147 | Z84: =IFERROR(Z82/Y82-1,"") -> -1.5885497 | AB84: =IFERROR(AB82/Z82-1,"") -> 0.4102366 | AC84: =IFERROR(AC82/AB82-1,"") -> 2.3968011 | AD84: =IFERROR(AD82/AC82-1,"") -> -0.15137839 | AE84: =IFERROR(AE82/AD82-1,"") -> -0.59833341 | AG84: =IFERROR(AG82/AE82-1,"") -> 0.35713177 | AH84: =IFERROR(AH82/AG82-1,"") -> 0.94909832 | AI84: =IFERROR(AI82/AH82-1,"") -> -0.31635618 | AJ84: =IFERROR(AJ82/AI82-1,"") -> -1.4922008
A86: WADSOB | B86: Weighted Average Basic Shares Outstanding | G86: ='IS (GAAP)'!G88 -> 180.632 | L86: ='IS (GAAP)'!L88 -> 192.164 | M86: ='IS (GAAP)'!M88 -> 209.228 | Q86: ='IS (GAAP)'!Q88 -> 217.854 | R86: ='IS (GAAP)'!R88 -> 245.608 | S86: ='IS (GAAP)'!S88 -> 486.591 | T86: ='IS (GAAP)'!T88 -> 497.886 | U86: =T86*(1+U88) -> 499.37966 | V86: =AVERAGE(R86:U86) -> 432.36616 | W86: =U86*(1+W88) -> 502.37594 | X86: =W86*(1+X88) -> 505.39019 | Y86: =X86*(1+Y88) -> 508.42253 | Z86: =Y86*(1+Z88) -> 511.47307 | AA86: =AVERAGE(W86:Z86) -> 506.91543 | AB86: =Z86*(1+AB88) -> 514.54191 | AC86: =AB86*(1+AC88) -> 517.62916 | AD86: =AC86*(1+AD88) -> 520.73493 | AE86: =AD86*(1+AE88) -> 523.85934 | AF86: =AVERAGE(AB86:AE86) -> 519.19133 | AG86: =AE86*(1+AG88) -> 527.0025 | AH86: =AG86*(1+AH88) -> 530.16451 | AI86: =AH86*(1+AI88) -> 533.3455 | AJ86: =AI86*(1+AJ88) -> 536.54557 | AK86: =AVERAGE(AG86:AJ86) -> 531.76452
A87: WADSO | B87: Weighted Average Diluted Shares Outstanding | G87: ='IS (GAAP)'!G89 -> 180.632 | L87: ='IS (GAAP)'!L89 -> 192.164 | M87: ='IS (GAAP)'!M89 -> 209.228 | Q87: ='IS (GAAP)'!Q89 -> 217.854 | R87: ='IS (GAAP)'!R89 -> 249.293 | S87: ='IS (GAAP)'!S89 -> 486.591 | T87: ='IS (GAAP)'!T89 -> 497.886 | U87: =T87*(1+U88) -> 499.37966 | V87: =AVERAGE(R87:U87) -> 433.28741 | W87: =U87*(1+W88) -> 502.37594 | X87: =W87*(1+X88) -> 505.39019 | Y87: =X87*(1+Y88) -> 508.42253 | Z87: =Y87*(1+Z88) -> 511.47307 | AA87: =AVERAGE(W87:Z87) -> 506.91543 | AB87: =Z87*(1+AB88) -> 514.54191 | AC87: =AB87*(1+AC88) -> 517.62916 | AD87: =AC87*(1+AD88) -> 520.73493 | AE87: =AD87*(1+AE88) -> 523.85934 | AF87: =AVERAGE(AB87:AE87) -> 519.19133 | AG87: =AE87*(1+AG88) -> 527.0025 | AH87: =AG87*(1+AH88) -> 530.16451 | AI87: =AH87*(1+AI88) -> 533.3455 | AJ87: =AI87*(1+AJ88) -> 536.54557 | AK87: =AVERAGE(AG87:AJ87) -> 531.76452
B88: % dilution (% qoq) | S88: =S87/R87-1 -> 0.95188393 | T88: =T87/S87-1 -> 0.023212513 | U88: 0.003 | W88: 0.006 | X88: =W88 -> 0.006 | Y88: =X88 -> 0.006 | Z88: =Y88 -> 0.006 | AB88: =Z88 -> 0.006 | AC88: =AB88 -> 0.006 | AD88: =AC88 -> 0.006 | AE88: =AD88 -> 0.006 | AG88: =AE88 -> 0.006 | AH88: =AG88 -> 0.006 | AI88: =AH88 -> 0.006 | AJ88: =AI88 -> 0.006
B90: Other Comprehensive Income / (Loss)
B91: Unrealized (Loss) Gain on Available-for-Sale Marketable Securities | G91: ='IS (GAAP)'!G92 -> -0.156 | H91: ='IS (GAAP)'!H92 -> 0 | I91: ='IS (GAAP)'!I92 -> 0 | J91: ='IS (GAAP)'!J92 -> 0 | K91: ='IS (GAAP)'!K92 -> 0 | L91: ='IS (GAAP)'!L92 -> 0.008 | M91: ='IS (GAAP)'!M92 -> 0.058 | N91: ='IS (GAAP)'!N92 -> 0.027 | ... AK91: ='IS (GAAP)'!AK92 -> 0
B92: Total Comprehensive Loss | G92: =G75+G91 -> -26.837 | H92: =H75+H91 -> -16.120213 | I92: =I75+I91 -> -13.090146 | J92: =J75+J91 -> 394.7053 | K92: =K75+K91 -> 125.60206 | L92: =L75+L91 -> -44.634 | M92: =M75+M91 -> -23.501 | N92: =N75+N91 -> -5.103 | ... AK92: =AK75+AK91 -> 224.29833
B94: Adjusted EBITDA
B95: EBITDA | G95: ='IS (GAAP)'!G99 -> -11.185 | L95: ='IS (GAAP)'!L99 -> 88.759 | M95: ='IS (GAAP)'!M99 -> 96.357 | N95: ='IS (GAAP)'!N99 -> 242.181 | O95: ='IS (GAAP)'!O99 -> 371.14 | P95: ='IS (GAAP)'!P99 -> 478.093 | Q95: ='IS (GAAP)'!Q99 -> 1187.771 | R95: ='IS (GAAP)'!R99 -> 416.027 | S95: ='IS (GAAP)'!S99 -> 578.69 | ... AK95: ='IS (GAAP)'!AK99 -> 15475.606
B96: Stock-Based Compensation | G96: =G106 -> 1.49 | L96: =L106 -> 15.154 | M96: =M106 -> 8.189 | N96: =N106 -> 7.66 | O96: =O106 -> 7.617 | P96: =P106 -> 8.022 | Q96: =Q106 -> 31.488 | R96: =R106 -> 183.973 | S96: =S106 -> 145.005 | ... AK96: =AK106 -> 405.65491
B97: Adjusted EBITDA | G97: =G95+G96 -> -9.695 | L97: =L95+L96 -> 103.913 | M97: =M95+M96 -> 104.546 | N97: =N95+N96 -> 249.841 | O97: =O95+O96 -> 378.757 | P97: =P95+P96 -> 486.115 | Q97: =Q95+Q96 -> 1219.259 | R97: =R95+R96 -> 600 | S97: =S95+S96 -> 723.695 | ... AK97: =AK95+AK96 -> 15881.261
B98: % yoy | L98: =IFERROR(L97/G97-1,"") -> -11.718205 | M98: =IFERROR(M97/H97-1,"") | N98: =IFERROR(N97/I97-1,"") | O98: =IFERROR(O97/J97-1,"") | P98: =IFERROR(P97/K97-1,"") | Q98: =IFERROR(Q97/L97-1,"") -> 10.73346 | R98: =IFERROR(R97/M97-1,"") -> 4.7391005 | S98: =IFERROR(S97/N97-1,"") -> 1.8966223 | ... AK98: =IFERROR(AK97/AF97-1,"") -> 0.32474262
B99: Adjusted EBITDA Margin | G99: =G97/G$10 -> -0.61244473 | L99: =L97/L$10 -> 0.45388153 | M99: =M97/M$10 -> 0.55407984 | N99: =N97/N$10 -> 0.63191534 | O99: =O97/O$10 -> 0.64862204 | P99: =P97/P$10 -> 0.65038198 | Q99: =Q97/Q$10 -> 0.63654717 | R99: =R97/R$10 -> 0.61122702 | S99: =S97/S$10 -> 0.59672012 | ... AK99: =AK97/AK$10 -> 0.73337316
B101: Stock-Based Compensation
B102: Cost of Revenue | G102: 0.133 | L102: 0.694 | M102: 0.388 | N102: 0.35 | O102: =0.271 -> 0.271 | P102: =0.298+0.00025 -> 0.29825 | Q102: =SUM(M102:P102) -> 1.30725 | R102: 2.693 | S102: 2.701 | T102: 3.533 | U102: =U$10*U$117*U108 -> 13.885919 | V102: =SUM(R102:U102) -> 22.812919 | W102: =W$10*W$117*W108 -> 18.529698 | X102: =X$10*X$117*X108 -> 24.899216 | Y102: =Y$10*Y$117*Y108 -> 26.054298 | Z102: =Z$10*Z$117*Z108 -> 26.19353 | AA102: =SUM(W102:Z102) -> 95.676743 | AB102: =AB$10*AB$117*AB108 -> 23.327074 | AC102: =AC$10*AC$117*AC108 -> 33.058837 | AD102: =AD$10*AD$117*AD108 -> 21.474397 | AE102: =AE$10*AE$117*AE108 -> 31.674848 | AF102: =SUM(AB102:AE102) -> 109.53516 | AG102: =AG$10*AG$117*AG108 -> 27.22183 | AH102: =AH$10*AH$117*AH108 -> 26.884979 | AI102: =AI$10*AI$117*AI108 -> 22.068103 | AJ102: =AJ$10*AJ$117*AJ108 -> 21.182267 | AK102: =SUM(AG102:AJ102) -> 97.357178
B103: Technology and Infrastructure | G103: 0.624 | L103: 7.1 | M103: 2.357 | N103: 2.08 | O103: =2.161 -> 2.161 | P103: =0.00025+3.314 -> 3.31425 | Q103: =SUM(M103:P103) -> 9.91225 | R103: 54.599 | S103: 47.683 | T103: 52.623 | U103: =U$10*U$117*U109 -> 22.831015 | V103: =SUM(R103:U103) -> 177.73601 | W103: =W$10*W$117*W109 -> 48.462288 | X103: =X$10*X$117*X109 -> 33.968717 | Y103: =Y$10*Y$117*Y109 -> 35.544537 | Z103: =Z$10*Z$117*Z109 -> 35.734484 | AA103: =SUM(W103:Z103) -> 153.71003 | AB103: =AB$10*AB$117*AB109 -> 31.823926 | AC103: =AC$10*AC$117*AC109 -> 45.100468 | AD103: =AD$10*AD$117*AD109 -> 29.296414 | AE103: =AE$10*AE$117*AE109 -> 43.212363 | AF103: =SUM(AB103:AE103) -> 149.43317 | AG103: =AG$10*AG$117*AG109 -> 37.13734 | AH103: =AH$10*AH$117*AH109 -> 36.677791 | AI103: =AI$10*AI$117*AI109 -> 30.106376 | AJ103: =AJ$10*AJ$117*AJ109 -> 28.897875 | AK103: =SUM(AG103:AJ103) -> 132.81938
B104: Sales and Marketing | G104: 0.074 | L104: 1.74 | M104: 0.867 | N104: 0.848 | O104: =0.847 -> 0.847 | P104: =0.846+0.00025 -> 0.84625 | Q104: =SUM(M104:P104) -> 3.40825 | R104: 2.82 | S104: 8.494 | T104: 9.81 | U104: =U$10*U$117*U110 -> 8.3315511 | V104: =SUM(R104:U104) -> 29.455551 | W104: =W$10*W$117*W110 -> 41.335481 | X104: =X$10*X$117*X110 -> 16.599477 | Y104: =Y$10*Y$117*Y110 -> 17.369532 | Z104: =Z$10*Z$117*Z110 -> 17.462354 | AA104: =SUM(W104:Z104) -> 92.766844 | AB104: =AB$10*AB$117*AB110 -> 15.551383 | AC104: =AC$10*AC$117*AC110 -> 22.039225 | AD104: =AD$10*AD$117*AD110 -> 14.316265 | AE104: =AE$10*AE$117*AE110 -> 21.116565 | AF104: =SUM(AB104:AE104) -> 73.023437 | AG104: =AG$10*AG$117*AG110 -> 18.147887 | AH104: =AH$10*AH$117*AH110 -> 17.923319 | AI104: =AI$10*AI$117*AI110 -> 14.712069 | AJ104: =AJ$10*AJ$117*AJ110 -> 14.121511 | AK104: =SUM(AG104:AJ104) -> 64.904785
B105: General and Administrative | G105: 0.659 | L105: 5.62 | M105: 4.577 | N105: 4.382 | O105: =4.338 -> 4.338 | P105: =3.563+0.00025 -> 3.56325 | Q105: =SUM(M105:P105) -> 16.86025 | R105: 123.861 | S105: 86.127 | T105: 78.465 | U105: =U$10*U$117*U111 -> 24.381108 | V105: =SUM(R105:U105) -> 312.83411 | W105: =W$10*W$117*W111 -> 34.208674 | X105: =X$10*X$117*X111 -> 28.279322 | Y105: =Y$10*Y$117*Y111 -> 29.591209 | Z105: =Z$10*Z$117*Z111 -> 29.749342 | AA105: =SUM(W105:Z105) -> 121.82855 | AB105: =AB$10*AB$117*AB111 -> 26.49376 | AC105: =AC$10*AC$117*AC111 -> 37.546624 | AD105: =AD$10*AD$117*AD111 -> 24.389579 | AE105: =AE$10*AE$117*AE111 -> 35.974756 | AF105: =SUM(AB105:AE105) -> 124.40472 | AG105: =AG$10*AG$117*AG111 -> 30.917234 | AH105: =AH$10*AH$117*AH111 -> 30.534655 | AI105: =AI$10*AI$117*AI111 -> 25.063881 | AJ105: =AJ$10*AJ$117*AJ111 -> 24.057791 | AK105: =SUM(AG105:AJ105) -> 110.57356
B106: Total Stock-Based Compensation | G106: =SUM(G102:G105) -> 1.49 | L106: =SUM(L102:L105) -> 15.154 | M106: =SUM(M102:M105) -> 8.189 | N106: =SUM(N102:N105) -> 7.66 | O106: =SUM(O102:O105) -> 7.617 | P106: =SUM(P102:P105) -> 8.022 | Q106: =SUM(Q102:Q105) -> 31.488 | R106: =SUM(R102:R105) -> 183.973 | S106: =SUM(S102:S105) -> 145.005 | ... AK106: =SUM(AK102:AK105) -> 405.65491
B108: Cost of Revenue as a % of Total SBC | G108: =G102/G$106 -> 0.089261745 | L108: =L102/L$106 -> 0.045796489 | M108: =M102/M$106 -> 0.047380633 | N108: =N102/N$106 -> 0.045691906 | O108: =O102/O$106 -> 0.035578312 | P108: =P102/P$106 -> 0.037179008 | Q108: =Q102/Q$106 -> 0.041515816 | R108: =R102/R$106 -> 0.014638018 | S108: =S102/S$106 -> 0.018626944 | T108: =T102/T$106 -> 0.024461508 | U108: 0.2 | V108: =V102/V$106 -> 0.042025233 | W108: 0.13 | X108: 0.24 | Y108: 0.24 | Z108: =X108 -> 0.24 | AA108: =AA102/AA$106 -> 0.20620781 | AB108: =Z108 -> 0.24 | AC108: =AB108 -> 0.24 | AD108: =AC108 -> 0.24 | AE108: =AD108 -> 0.24 | AF108: =AF102/AF$106 -> 0.24 | AG108: =AE108 -> 0.24 | AH108: =AG108 -> 0.24 | AI108: =AH108 -> 0.24 | AJ108: =AI108 -> 0.24 | AK108: =AK102/AK$106 -> 0.24
B109: Technology and Infrastructure as a % of Total SBC | G109: =G103/G$106 -> 0.41879195 | L109: =L103/L$106 -> 0.46852316 | M109: =M103/M$106 -> 0.28782513 | N109: =N103/N$106 -> 0.27154047 | O109: =O103/O$106 -> 0.2837075 | P109: =P103/P$106 -> 0.4131451 | Q109: =Q103/Q$106 -> 0.31479452 | R109: =R103/R$106 -> 0.29677724 | S109: =S103/S$106 -> 0.32883694 | T109: =T103/T$106 -> 0.36434699 | U109: =S109 -> 0.32883694 | V109: =V103/V$106 -> 0.32741964 | W109: 0.34 | X109: =V109 -> 0.32741964 | Y109: =X109 -> 0.32741964 | Z109: =Y109 -> 0.32741964 | AA109: =AA103/AA$106 -> 0.33128435 | AB109: =Z109 -> 0.32741964 | AC109: =AB109 -> 0.32741964 | AD109: =AC109 -> 0.32741964 | AE109: =AD109 -> 0.32741964 | AF109: =AF103/AF$106 -> 0.32741964 | AG109: =AE109 -> 0.32741964 | AH109: =AG109 -> 0.32741964 | AI109: =AH109 -> 0.32741964 | AJ109: =AI109 -> 0.32741964 | AK109: =AK103/AK$106 -> 0.32741964
B110: Sales and Marketing as a % of Total SBC | G110: =G104/G$106 -> 0.04966443 | L110: =L104/L$106 -> 0.11482117 | M110: =M104/M$106 -> 0.10587373 | N110: =N104/N$106 -> 0.11070496 | O110: =O104/O$106 -> 0.11119863 | P110: =P104/P$106 -> 0.10549115 | Q110: =Q104/Q$106 -> 0.10823965 | R110: =R104/R$106 -> 0.015328336 | S110: =S104/S$106 -> 0.05857729 | T110: =T104/T$106 -> 0.067921707 | U110: 0.12 | V110: =V104/V$106 -> 0.05426208 | W110: 0.29 | X110: 0.16 | Y110: =X110 -> 0.16 | Z110: =Y110 -> 0.16 | AA110: =AA104/AA$106 -> 0.19993623 | AB110: =Z110 -> 0.16 | AC110: =AB110 -> 0.16 | AD110: =AC110 -> 0.16 | AE110: =AD110 -> 0.16 | AF110: =AF104/AF$106 -> 0.16 | AG110: =AE110 -> 0.16 | AH110: =AG110 -> 0.16 | AI110: =AH110 -> 0.16 | AJ110: =AI110 -> 0.16 | AK110: =AK104/AK$106 -> 0.16
B111: General and Administrative as a % of Total SBC | G111: =G105/G$106 -> 0.44228188 | L111: =L105/L$106 -> 0.37085918 | M111: =M105/M$106 -> 0.5589205 | N111: =N105/N$106 -> 0.57206266 | O111: =O105/O$106 -> 0.56951556 | P111: =P105/P$106 -> 0.44418474 | Q111: =Q105/Q$106 -> 0.53545001 | R111: =R105/R$106 -> 0.6732564 | S111: =S105/S$106 -> 0.59395883 | T111: =T105/T$106 -> 0.5432698 | U111: =1-U108-U109-U110 -> 0.35116306 | V111: =V105/V$106 -> 0.57629305 | W111: =1-W108-W109-W110 -> 0.24 | X111: =1-X108-X109-X110 -> 0.27258036 | Y111: =1-Y108-Y109-Y110 -> 0.27258036 | Z111: =1-Z108-Z109-Z110 -> 0.27258036 | AA111: =AA105/AA$106 -> 0.26257162 | AB111: =1-AB108-AB109-AB110 -> 0.27258036 | AC111: =1-AC108-AC109-AC110 -> 0.27258036 | AD111: =1-AD108-AD109-AD110 -> 0.27258036 | AE111: =1-AE108-AE109-AE110 -> 0.27258036 | AF111: =AF105/AF$106 -> 0.27258036 | AG111: =1-AG108-AG109-AG110 -> 0.27258036 | AH111: =1-AH108-AH109-AH110 -> 0.27258036 | AI111: =1-AI108-AI109-AI110 -> 0.27258036 | AJ111: =1-AJ108-AJ109-AJ110 -> 0.27258036 | AK111: =AK105/AK$106 -> 0.27258036
B113: Cost of Revenue as a % of Revenue | G113: =G102/G$10 -> 0.0084017688 | L113: =L102/L$10 -> 0.0030313222 | M113: =M102/M$10 -> 0.0020563482 | N113: =N102/N$10 -> 0.00088524449 | O113: =O102/O$10 -> 0.00046408798 | P113: =P102/P$10 -> 0.00039903402 | Q113: =Q102/Q$10 -> 0.00068248525 | R113: =R102/R$10 -> 0.0027433906 | S113: =S102/S$10 -> 0.0022270999 | ... AK113: =AK102/AK$10 -> 0.0044958105
B114: Technology and Infrastructure as a % of Revenue | G114: =G103/G$10 -> 0.039418825 | L114: =L103/L$10 -> 0.031012086 | M114: =M103/M$10 -> 0.012491785 | N114: =N103/N$10 -> 0.0052608816 | O114: =O103/O$10 -> 0.0037007163 | P114: =P103/P$10 -> 0.0044341945 | Q114: =Q103/Q$10 -> 0.0051749585 | R114: =R103/R$10 -> 0.05562064 | S114: =S103/S$10 -> 0.039316847 | ... AK114: =AK103/AK$10 -> 0.0061334027
B115: Sales and Marketing as a % of Revenue | G115: =G104/G$10 -> 0.0046746684 | L115: =L104/L$10 -> 0.007600145 | M115: =M104/M$10 -> 0.0045949842 | N115: =N104/N$10 -> 0.0021448209 | O115: =O104/O$10 -> 0.001450489 | P115: =P104/P$10 -> 0.0011322131 | Q115: =Q104/Q$10 -> 0.0017793692 | R115: =R104/R$10 -> 0.002872767 | S115: =S104/S$10 -> 0.0070036973 | ... AK115: =AK104/AK$10 -> 0.002997207
B116: General and Administrative as a % of Revenue | G116: =G105/G$10 -> 0.041629817 | L116: =L105/L$10 -> 0.024547595 | M116: =M105/M$10 -> 0.024257489 | N116: =N105/N$10 -> 0.011083261 | O116: =O105/O$10 -> 0.0074288327 | P116: =P105/P$10 -> 0.0047673361 | Q116: =Q105/Q$10 -> 0.00880235 | R116: =R105/R$10 -> 0.12617865 | S116: =S105/S$10 -> 0.071015709 | ... AK116: =AK105/AK$10 -> 0.0051061236
B117: Total Stock-Based Compensation as a % of Revenue | G117: =G106/G$10 -> 0.094125079 | L117: =L106/L$10 -> 0.066191148 | M117: =M106/M$10 -> 0.043400606 | N117: =N106/N$10 -> 0.019374208 | O117: =O106/O$10 -> 0.013044126 | P117: =P106/P$10 -> 0.010732778 | Q117: =Q106/Q$10 -> 0.016439163 | R117: =R106/R$10 -> 0.18741545 | S117: =S106/S$10 -> 0.11956335 | T117: =T106/T$10 -> 0.10583538 | U117: 0.045 | V117: =V106/V$10 -> 0.10639772 | W117: 0.064 | X117: 0.035 | Y117: =X117-0.2% -> 0.033 | Z117: =Y117-0.2% -> 0.031 | AA117: =SUM(AA113:AA116) -> 0.038659898 | AB117: =Z117-0.55% -> 0.0255 | AC117: =AA117-0.55% -> 0.033159898 | AD117: =AB117-0.55% -> 0.02 | AE117: =AC117-0.55% -> 0.027659898 | AF117: =SUM(AF113:AF116) -> 0.02651789 | AG117: =AE117-0.55% -> 0.022159898 | AH117: =AF117-0.55% -> 0.02101789 | AI117: =AG117-0.55% -> 0.016659898 | AJ117: =AH117-0.55% -> 0.01551789 | AK117: =SUM(AK113:AK116) -> 0.018732544
B119: Non-GAAP Adjustments
B120: Acquisition-Related Costs | G120: 0 | H120: 0 | I120: 0 | J120: 0 | K120: 0 | L120: =SUM(H120:K120) -> 0 | M120: 0 | N120: 0 | O120: 0 | P120: 0 | Q120: =SUM(M120:P120) -> 0 | R120: 6.13 | S120: 29.474 | T120: 11.364
B121: Amortization of Acquired Intangibles | M121: 0 | N121: 0 | O121: 0 | P121: 0 | Q121: =SUM(M121:P121) -> 0 | R121: 0 | S121: 6.1 | T121: 9.509
B122: Loss on Extinguishment of Debt | M122: 0 | N122: 0 | O122: 0 | P122: 0 | Q122: =SUM(M122:P122) -> 0 | R122: 1.819 | S122: 8.487 | T122: 14.486
B123: Loss on Fair Value Adjustments | G123: 2.884 | H123: =-'IS (GAAP)'!H60 -> 0 | I123: =-'IS (GAAP)'!I60 -> 0 | J123: =390.485-I123-H123 -> 390.485 | K123: =L123-J123-I123-H123 -> 143.467 | L123: 533.952 | M123: =-'IS (GAAP)'!M60 -> 97.5 | N123: =-'IS (GAAP)'!N60 -> 310.231 | O123: =748.864-N123-M123 -> 341.133 | P123: 7.065 | Q123: =SUM(M123:P123) -> 755.929 | R123: -26.837 | S123: 0 | T123: 0 | U123: =T123 -> 0 | V123: =SUM(R123:U123) -> -26.837 | W123: =U123 -> 0 | X123: =W123 -> 0 | Y123: =X123 -> 0 | Z123: =Y123 -> 0 | AA123: =SUM(W123:Z123) -> 0 | AB123: =Z123 -> 0 | AC123: =AB123 -> 0 | AD123: =AC123 -> 0 | AE123: =AD123 -> 0 | AF123: =SUM(AB123:AE123) -> 0 | AG123: =AE123 -> 0 | AH123: =AG123 -> 0 | AI123: =AH123 -> 0 | AJ123: =AI123 -> 0 | AK123: =SUM(AG123:AJ123) -> 0
B124: Other Adjustments | G124: 0 | J124: 0 | K124: =L124-J124-I124-H124 -> 0 | L124: 0 | M124: 0 | N124: 0 | O124: 11.124 | P124: 0 | Q124: =SUM(M124:P124) -> 11.124 | R124: 0 | S124: -10.69 | T124: -12.094 | U124: =T124 -> -12.094 | V124: =SUM(R124:U124) -> -34.878 | W124: =U124 -> -12.094 | X124: =W124 -> -12.094 | Y124: =X124 -> -12.094 | Z124: =Y124 -> -12.094 | AA124: =SUM(W124:Z124) -> -48.376 | AB124: =Z124 -> -12.094 | AC124: =AB124 -> -12.094 | AD124: =AC124 -> -12.094 | AE124: =AD124 -> -12.094 | AF124: =SUM(AB124:AE124) -> -48.376 | AG124: =AE124 -> -12.094 | AH124: =AG124 -> -12.094 | AI124: =AH124 -> -12.094 | AJ124: =AI124 -> -12.094 | AK124: =SUM(AG124:AJ124) -> -48.376
B125: Income Tax Effect Related to Adjustments | M125: 0 | N125: 0 | O125: 0 | P125: 0 | Q125: =SUM(M125:P125) -> 0 | R125: 0 | S125: -18.673 | T125: -98.542
B127: Interest Income
...

Sheet BS
B2: CoreWeave, Inc.
B3: Fiscal Year Ends Dec. 31
B4: ($ millions, except per share amounts)
C6: =Dates!C3 -> 2022 (A) | H6: =Dates!H3 -> 2023 (A) | M6: =Dates!M3 -> 2024 (A) | R6: =Dates!R3 -> 2025 (E) | W6: =Dates!W3 -> 2026 (E) | AB6: =Dates!AB3 -> 2027 (E) | AG6: =Dates!AG3 -> 2028 (E)
C7: =Dates!C4 -> 1Q22 (A) | D7: =Dates!D4 -> 2Q22 (A) | E7: =Dates!E4 -> 3Q22 (A) | F7: =Dates!F4 -> 4Q22 (A) | G7: =Dates!G4 -> FY22 (A) | H7: =Dates!H4 -> 1Q23 (A) | I7: =Dates!I4 -> 2Q23 (A) | J7: =Dates!J4 -> 3Q23 (A) | ... AK7: =Dates!AK4 -> FY28 (E)
C8: =Dates!C5 -> 44651 | D8: =Dates!D5 -> 44742 | E8: =Dates!E5 -> 44834 | F8: =Dates!F5 -> 44926 | G8: =Dates!G5 -> 44926 | H8: =Dates!H5 -> 45016 | I8: =Dates!I5 -> 45107 | J8: =Dates!J5 -> 45199 | ... AK8: =Dates!AK5 -> 47118
B9: Current Assets
B10: Cash & Cash Equivalents | G10: =CF!G77-CF!G80-CF!G81 -> 7.384 | H10: =CF!H77-CF!H80-CF!H81 -> 0 | I10: =CF!I77-CF!I80-CF!I81 -> 0 | J10: 426.385 | K10: 217.147 | L10: =K10 -> 217.147 | M10: 1306.872 | N10: 1028.044 | O10: 1355.216 | P10: 1361.083 | Q10: =P10 -> 1361.083 | R10: 1276.456 | S10: 1152.883 | T10: 1894.399 | U10: =CF!U77-BS!U11-BS!U18 -> 1228.378 | V10: =U10 -> 1228.378 | W10: =CF!W77-BS!W11-BS!W18 -> 1053.4388 | X10: =CF!X77-BS!X11-BS!X18 -> 1068.7541 | Y10: =CF!Y77-BS!Y11-BS!Y18 -> 1135.4635 | Z10: =CF!Z77-BS!Z11-BS!Z18 -> 1576.1249 | AA10: =Z10 -> 1576.1249 | AB10: =CF!AB77-BS!AB11-BS!AB18 -> 1218.5051 | AC10: =CF!AC77-BS!AC11-BS!AC18 -> 1460.0922 | AD10: =CF!AD77-BS!AD11-BS!AD18 -> 1747.6819 | AE10: =CF!AE77-BS!AE11-BS!AE18 -> 1822.3486 | AF10: =AE10 -> 1822.3486 | AG10: =CF!AG77-BS!AG11-BS!AG18 -> 1572.9171 | AH10: =CF!AH77-BS!AH11-BS!AH18 -> 1665.8424 | AI10: =CF!AI77-BS!AI11-BS!AI18 -> 1933.6727 | AJ10: =CF!AJ77-BS!AJ11-BS!AJ18 -> 2439.1501 | AK10: =AJ10 -> 2439.1501
B11: Restricted Cash and Cash Equivalents, Current | K11: 42.94 | L11: =K11 -> 42.94 | M11: 35.493 | N11: 79.725 | O11: 69.576 | P11: 37.394 | Q11: =CF!Q80 -> 37.394 | R11: 624.25 | S11: 560.173 | T11: 596.777 | U11: =CF!U80 -> 596.777 | V11: =CF!V80 -> 596.777 | W11: =CF!W80 -> 596.777 | X11: =CF!X80 -> 596.777 | Y11: =CF!Y80 -> 596.777 | Z11: =CF!Z80 -> 596.777 | AA11: =CF!AA80 -> 596.777 | AB11: =CF!AB80 -> 596.777 | ... AK11: =CF!AK80 -> 596.777
